Workbook

Sheet 00_Паспорт
A1: SYMBIOSIS V7 — Character, Skills & Symbionts Registry v1.2
A2: Дополняющий нормативный реестр персонажей, навыков, симбионтов, обычного XP и неизменяемого мастерского GM_DIRECT. Frozen runtime pack v1.2 принимается по version+SHA через forward compatibility.
A5: Метрика | B5: Значение | C5: Проверка | D5: Примечание | F5: Source priority и scope
A6: Версия | B6: 1.2 | C6: PASS | D6: SYMBIOSIS_CHARACTER_SKILLS_SYMBIONTS_V1.2 | F6: Приоритет: решения 2026-08-01 > v1.2 extension > v1.1 builtAgainst. Current tuple: Rules v1.7 | Character-Skills-Symbionts v1.2 | Items v1.6_with_icons | Bestiary v1.4 | Sentient v1.2.
A7: Дата выпуска | B7: 2026-08-01 | C7: PASS | D7: Europe/Berlin
A8: Характеристики | B8: =COUNTA('01_Характеристики'!$A$6:$A$12) -> 7 | C8: =IF(B8=7,"PASS","FAIL") -> PASS | D8: Ожидается 7
A9: Расы | B9: =COUNTA('02_Расы'!$A$6:$A$8) -> 3 | C9: =IF(B9=3,"PASS","FAIL") -> PASS | D9: Ожидается 3
A10: Классы | B10: =COUNTA('03_Классы'!$A$6:$A$8) -> 3 | C10: =IF(B10=3,"PASS","FAIL") -> PASS | D10: Ожидается 3
A11: Навыки | B11: =COUNTA('04_Навыки'!$B$6:$B$50) -> 45 | C11: =IF(B11=45,"PASS","FAIL") -> PASS | D11: Ожидается 45
A12: Симбионты | B12: =COUNTA('07_Симбионты'!$A$6:$A$28) -> 23 | C12: =IF(B12=23,"PASS","FAIL") -> PASS | D12: Ожидается 23
A13: Узлы развития | B13: =COUNTA('09_Узлы_развития'!$A$6:$A$187) -> 182 | C13: =IF(B13=182,"PASS","FAIL") -> PASS | D13: Ожидается 182 | F13: Manifest integration
A14: Автоматизируемые способности | B14: =COUNTA('10_Способности'!$A$6:$A$172) -> 167 | C14: =IF(B14=167,"PASS","FAIL") -> PASS | D14: Ожидается 167 | F14: Реестр является пятым нормативным артефактом Development Baseline Manifest v1.1. Все payload обязаны содержать точный dependencyTuple v1.1.
A15: Контексты | B15: =COUNTA('11_Контексты_способностей'!$A$6:$A$339) -> 334 | C15: =IF(B15=334,"PASS","FAIL") -> PASS | D15: Ожидается 334
A16: Manual-only узлы | B16: =COUNTIF('09_Узлы_развития'!$K$6:$K$187,"NODE_ONLY_MANUAL") -> 15 | C16: =IF(B16=15,"PASS","FAIL") -> PASS | D16: Ожидается 15; без поведения
A17: GeneratedObjectType | B17: =COUNTA('13_Генерируемые_объекты'!$A$6) -> 1 | C17: =IF(B17=1,"PASS","FAIL") -> PASS | D17: Ожидается 1: WEB_ITEM
A18: QA сценарии | B18: =COUNTA('21_QA_совместимость'!$A$6:$A$56) -> 51 | C18: =IF(B18=51,"PASS","FAIL") -> PASS | D18: Ожидается 51: сохранены 42 + 8 GM_DIRECT + 1 group generator
A19: Программные проверки | B19: 60 | C19: =IF(B19=60,"PASS","FAIL") -> PASS | D19: Builder semantic and structural gate
A20: Payload | B20: 1144 | C20: =IF(B20=1144,"PASS","FAIL") -> PASS | D20: 1 142 builtAgainst payload + 2 forward-compatible operation payload
A21: Release gate | B21: =IF(COUNTIF('21_QA_совместимость'!$G$6:$G$56,"FAIL")+COUNTIF('22_Контроль'!$D$6:$D$53,"FAIL")=0,"PASS","FAIL") -> PASS | C21: =IF(B21="PASS","PASS","FAIL") -> PASS | D21: PASS только при нуле FAIL
A22: Связи SpeciesKey ↔ LinkedStatCode | B22: =COUNTA('07_Симбионты'!$A$35:$A$82) -> 48 | C22: =IF(B22=48,"PASS","FAIL") -> PASS | D22: 23 вида, 48 отношений, дословно извлечённых из профильных карточек Rules v1.6
A23: XP policy rows | B23: 36 | C23: =IF(B23=36,"PASS","FAIL") -> PASS | D23: 3 route + 7 points + 11 roll kinds + 8 never + 3 race + 3 suppression + 1 GM_DIRECT = 36
A24: SymbiontXpEvent fields | B24: 19 | C24: =IF(B24=19,"PASS","FAIL") -> PASS | D24: Все обязательные поля события
A25: GM direct award policy | B25: 1 | C25: =IF(B25=1,"PASS","FAIL") -> PASS | D25: GM_DIRECT_SYMBIONT_XP | F25: Q-GM-XP-001
A26: MasterSymbiontXpAward fields | B26: 11 | C26: =IF(B26=11,"PASS","FAIL") -> PASS | D26: Полный immutable receipt contract | F26: CORE-234

Sheet 01_Характеристики
A1: Канонические характеристики персонажа
A2: Семь кодов без aliases. Для Z/W используются специфичные исполняемые карточки Rules v1.5; M канонически означает «Метаболизм».
A5: StatCode | B5: Название | C5: Порядок | D5: Domain | E5: BaseMin | F5: BaseMax игрока | G5: EffectiveMin | H5: Cap35Scope | I5: Описание | J5: Rule IDs | K5: Источник | L5: ID unique
A6: S | B6: Сила | C6: 1 | D6: BASE_CHARACTERISTIC | E6: 1 | F6: 20 | G6: 1 | H6: SENTIENT_BASE_ONLY | I6: Игрок: базовое значение 1..20. Мыслящий противник: базовое значение 1..35. Постоянные и временные изменения применяются послойно; итог не ниже 1. | J6: CORE-073; CORE-078; CORE-079; CORE-160; CORE-197 | K6: Rules v1.5; при внутреннем конфликте — более специфичная карточка правила | L6: =COUNTIF($A$6:$A$12,A6) -> 1
A7: D | B7: Ловкость | C7: 2 | D7: BASE_CHARACTERISTIC | E7: 1 | F7: 20 | G7: 1 | H7: SENTIENT_BASE_ONLY | I7: Игрок: базовое значение 1..20. Мыслящий противник: базовое значение 1..35. Постоянные и временные изменения применяются послойно; итог не ниже 1. | J7: CORE-073; CORE-078; CORE-079; CORE-160; CORE-197 | K7: Rules v1.5; при внутреннем конфликте — более специфичная карточка правила | L7: =COUNTIF($A$6:$A$12,A7) -> 1
A8: M | B8: Метаболизм | C8: 3 | D8: BASE_CHARACTERISTIC | E8: 1 | F8: 20 | G8: 1 | H8: SENTIENT_BASE_ONLY | I8: Игрок: базовое значение 1..20. Мыслящий противник: базовое значение 1..35. Постоянные и временные изменения применяются послойно; итог не ниже 1. The higher-priority Rules!Справочники C140 explicitly says «Метаболизм». The lower-priority fallback PDF uses «Выносливость (M)», so the Rules value prevails under the user's stated source-priority rule. | J8: CORE-073; CORE-078; CORE-079; CORE-160; CORE-197 | K8: Rules v1.5; при внутреннем конфликте — более специфичная карточка правила | L8: =COUNTIF($A$6:$A$12,A8) -> 1
A9: Z | B9: Здоровье | C9: 4 | D9: BASE_CHARACTERISTIC | E9: 1 | F9: 20 | G9: 1 | H9: SENTIENT_BASE_ONLY | I9: Игрок: базовое значение 1..20. Мыслящий противник: базовое значение 1..35. Постоянные и временные изменения применяются послойно; итог не ниже 1. Rules!Справочники C141 says «Знания», but CORE-031, CORE-117, CORE-119 and Q-CORE-008 consistently use Z as «Здоровье»; the approved fallback PDF explicitly uses «Здоровье (Z)». | J9: CORE-031; CORE-073; CORE-078; CORE-079; CORE-160; CORE-197 | K9: Rules v1.5; при внутреннем конфликте — более специфичная карточка правила | L9: =COUNTIF($A$6:$A$12,A9) -> 1
A10: I | B10: Интеллект | C10: 5 | D10: BASE_CHARACTERISTIC | E10: 1 | F10: 20 | G10: 1 | H10: SENTIENT_BASE_ONLY | I10: Игрок: базовое значение 1..20. Мыслящий противник: базовое значение 1..35. Постоянные и временные изменения применяются послойно; итог не ниже 1. | J10: CORE-073; CORE-078; CORE-079; CORE-160; CORE-197 | K10: Rules v1.5; при внутреннем конфликте — более специфичная карточка правила | L10: =COUNTIF($A$6:$A$12,A10) -> 1
A11: W | B11: Мудрость | C11: 6 | D11: BASE_CHARACTERISTIC | E11: 1 | F11: 20 | G11: 1 | H11: SENTIENT_BASE_ONLY | I11: Игрок: базовое значение 1..20. Мыслящий противник: базовое значение 1..35. Постоянные и временные изменения применяются послойно; итог не ниже 1. Rules!Справочники C143 says «Воля», but the higher-priority CORE-081 card is titled «Слоты навыков от Мудрости» and the approved fallback PDF explicitly uses «Мудрость (W)» on physical page 105. | J11: CORE-073; CORE-078; CORE-079; CORE-081; CORE-160; CORE-197 | K11: Rules v1.5; при внутреннем конфликте — более специфичная карточка правила | L11: =COUNTIF($A$6:$A$12,A11) -> 1
A12: C | B12: Харизма | C12: 7 | D12: BASE_CHARACTERISTIC | E12: 1 | F12: 20 | G12: 1 | H12: SENTIENT_BASE_ONLY | I12: Игрок: базовое значение 1..20. Мыслящий противник: базовое значение 1..35. Постоянные и временные изменения применяются послойно; итог не ниже 1. | J12: CORE-073; CORE-078; CORE-079; CORE-160; CORE-197 | K12: Rules v1.5; при внутреннем конфликте — более специфичная карточка правила | L12: =COUNTIF($A$6:$A$12,A12) -> 1

Sheet 02_Расы
A1: Игровые расы
A2: Только PURE, FREE и UNITED. Множители XP заданы явно: баллы общего счётчика не удваиваются; у FREE прямое и распределённое начисление ×2.
A5: RaceCode | B5: Название | C5: ClassPolicy | D5: BaseSymbiontSlots | E5: SymbioticMonsterAllowed | F5: StatModifierProfileID | G5: GrantedSkillRefs | H5: SymbiontXPPolicy | I5: Creation Rule IDs | J5: Источник | K5: Status | L5: ID unique | M5: DirectXPMultiplier | N5: CounterPointMultiplier | O5: AllocationXPMultiplier
A6: PURE | B6: Чистый | C6: REQUIRED_PURE_CLASS | D6: 0 | E6: =FALSE() -> FALSE | F6: RACE-MOD-PURE | H6: STANDARD_XP_AWARD | I6: CORE-008; CORE-009; CORE-010; CORE-013 | J6: Rules Registry v1.5 | K6: ACTIVE | L6: =COUNTIF($A$6:$A$8,A6) -> 1 | M6: 1 | N6: 1 | O6: 1
A7: FREE | B7: Вольный | C7: NO_CLASS | D7: 1 | E7: =FALSE() -> FALSE | F7: RACE-MOD-FREE | H7: XP_AWARD_X2 | I7: CORE-006; CORE-007 | J7: Rules Registry v1.5 | K7: ACTIVE | L7: =COUNTIF($A$6:$A$8,A7) -> 1 | M7: 2 | N7: 1 | O7: 2
A8: UNITED | B8: Единый | C8: NO_CLASS | D8: 4 | E8: =TRUE() -> TRUE | F8: RACE-MOD-UNITED | G8: FOLLOWING_PAIN | H8: STANDARD_XP_AWARD | I8: CORE-001; CORE-004; CORE-005 | J8: Rules Registry v1.5 | K8: ACTIVE | L8: =COUNTIF($A$6:$A$8,A8) -> 1 | M8: 1 | N8: 1 | O8: 1

Sheet 03_Классы
A1: Классы Чистых
A2: Класс обязателен только для PURE; обязательный классовый навык резервирует один стартовый слот.
A5: ClassCode | B5: RaceCode | C5: Название | D5: MandatorySkillKey | E5: MandatorySkillSlotCost | F5: StatModifierProfileID | G5: ContextModifierRefs | H5: Rule IDs | I5: Источник | J5: Status | K5: ID unique
A6: SEEKER | B6: PURE | C6: Искатель | D6: PURE_SEEKER | E6: 1 | F6: CLASS-MOD-SEEKER | G6: CLASS-MOD-SEEKER-C-VS-PURE; CLASS-MOD-SEEKER-C-VS-UNITED | H6: CORE-009 | I6: Rules Registry v1.5 | J6: ACTIVE | K6: =COUNTIF($A$6:$A$8,A6) -> 1
A7: STALKER | B7: PURE | C7: Сталкер | D7: PURE_STALKER | E7: 1 | F7: CLASS-MOD-STALKER | G7: CLASS-MOD-STALKER-C-VS-PURE; CLASS-MOD-STALKER-C-VS-UNITED | H7: CORE-010 | I7: Rules Registry v1.5 | J7: ACTIVE | K7: =COUNTIF($A$6:$A$8,A7) -> 1
A8: SOLDIER | B8: PURE | C8: Солдат | D8: PURE_SOLDIER | E8: 1 | F8: CLASS-MOD-SOLDIER | G8: CLASS-MOD-SOLDIER-C-VS-PURE; CLASS-MOD-SOLDIER-C-VS-UNITED | H8: CORE-013 | I8: Rules Registry v1.5 | J8: ACTIVE | K8: =COUNTIF($A$6:$A$8,A8) -> 1

Sheet 04_Навыки
A1: Системный каталог навыков
A2: 41 выбираемый навык + 4 фиксированных. Существующие 15 runtime-ключей Sentient v1.1 сохранены; остальные 30 получают новые стабильные ключи этого реестра.
A5: SkillID | B5: SkillKey | C5: Название | D5: Категория | E5: OwnerScopeAllowed | F5: SlotCostMode | G5: BonusDomain / Scope | H5: MaxBonus | I5: CheckTags | J5: MandatoryRace | K5: MandatoryClass | L5: MissingSkillPenalty | M5: Rule IDs | N5: Source Question IDs | O5: Status | P5: ID unique
A6: SKL-001 | B6: UNARMED | C6: Рукопашный бой | D6: SELECTABLE_GENERAL | E6: PLAYER_HOST; SENTIENT_HOST; ADVISER_IF_GRANTED | F6: BONUS_LEVEL_FORMULA_CORE-165 | G6: Удары руками/ногами, блок без щита | H6: NO_RULED_UPPER_LIMIT | I6: UNARMED | L6: -5 | M6: CORE-165; CORE-167 | N6: Q-CORE-024; Q-CORE-051 | O6: ACTIVE | P6: =COUNTIF($B$6:$B$50,B6) -> 1
A7: SKL-002 | B7: GRAPPLING | C7: Борьба | D7: SELECTABLE_GENERAL | E7: PLAYER_HOST; SENTIENT_HOST; ADVISER_IF_GRANTED | F7: BONUS_LEVEL_FORMULA_CORE-165 | G7: Борцовские приёмы | H7: NO_RULED_UPPER_LIMIT | I7: GRAPPLING | L7: -5 | M7: CORE-165; CORE-167 | N7: Q-CORE-024; Q-CORE-051 | O7: ACTIVE | P7: =COUNTIF($B$6:$B$50,B7) -> 1
A8: SKL-003 | B8: WEAPON_THROWING | C8: Метание | D8: SELECTABLE_GENERAL | E8: PLAYER_HOST; SENTIENT_HOST; ADVISER_IF_GRANTED | F8: BONUS_LEVEL_FORMULA_CORE-165 | G8: Метание оружия | H8: NO_RULED_UPPER_LIMIT | I8: WEAPON_THROWING | L8: -3 | M8: CORE-165; CORE-167 | N8: Q-CORE-024; Q-CORE-051 | O8: ACTIVE | P8: =COUNTIF($B$6:$B$50,B8) -> 1
A9: SKL-004 | B9: OBJECT_THROWING | C9: Бросание | D9: SELECTABLE_GENERAL | E9: PLAYER_HOST; SENTIENT_HOST; ADVISER_IF_GRANTED | F9: BONUS_LEVEL_FORMULA_CORE-165 | G9: Бросание предметов | H9: NO_RULED_UPPER_LIMIT | I9: OBJECT_THROWING | L9: -2 | M9: CORE-165; CORE-167 | N9: Q-CORE-024; Q-CORE-051 | O9: ACTIVE | P9: =COUNTIF($B$6:$B$50,B9) -> 1
A10: SKL-005 | B10: SHOOTING | C10: Стрельба | D10: SELECTABLE_GENERAL | E10: PLAYER_HOST; SENTIENT_HOST; ADVISER_IF_GRANTED | F10: BONUS_LEVEL_FORMULA_CORE-165 | G10: Точность атак «Стрельба» | H10: NO_RULED_UPPER_LIMIT | I10: SHOOTING | M10: CORE-165; CORE-167 | N10: Q-CORE-024; Q-CORE-051 | O10: ACTIVE | P10: =COUNTIF($B$6:$B$50,B10) -> 1
A11: SKL-006 | B11: ARCHERY | C11: Стрельба из лука | D11: SELECTABLE_GENERAL | E11: PLAYER_HOST; SENTIENT_HOST; ADVISER_IF_GRANTED | F11: BONUS_LEVEL_FORMULA_CORE-165 | G11: Точность лука | H11: NO_RULED_UPPER_LIMIT | I11: ARCHERY | L11: -5 | M11: CORE-165; CORE-167 | N11: Q-CORE-024; Q-CORE-051 | O11: ACTIVE | P11: =COUNTIF($B$6:$B$50,B11) -> 1
A12: SKL-007 | B12: GROSS | C12: Владение грубым оружием | D12: SELECTABLE_GENERAL | E12: PLAYER_HOST; SENTIENT_HOST; ADVISER_IF_GRANTED | F12: BONUS_LEVEL_FORMULA_CORE-165 | G12: Урон/точность грубого оружия и тяжёлых подручных средств | H12: NO_RULED_UPPER_LIMIT | I12: GROSS | L12: -3 | M12: CORE-165; CORE-167 | N12: Q-CORE-024; Q-CORE-051 | O12: ACTIVE | P12: =COUNTIF($B$6:$B$50,B12) -> 1
A13: SKL-008 | B13: FENCING | C13: Фехтование | D13: SELECTABLE_GENERAL | E13: PLAYER_HOST; SENTIENT_HOST; ADVISER_IF_GRANTED | F13: BONUS_LEVEL_FORMULA_CORE-165 | G13: Урон/точность длинного клинкового, парирование | H13: NO_RULED_UPPER_LIMIT | I13: FENCING | L13: -5 | M13: CORE-165; CORE-167 | N13: Q-CORE-024; Q-CORE-051 | O13: ACTIVE | P13: =COUNTIF($B$6:$B$50,B13) -> 1
A14: SKL-009 | B14: SPEAR | C14: Владение копьём | D14: SELECTABLE_GENERAL | E14: PLAYER_HOST; SENTIENT_HOST; ADVISER_IF_GRANTED | F14: BONUS_LEVEL_FORMULA_CORE-165 | G14: Урон/точность копья | H14: NO_RULED_UPPER_LIMIT | I14: SPEAR | L14: -2 | M14: CORE-165; CORE-167 | N14: Q-CORE-024; Q-CORE-051 | O14: ACTIVE | P14: =COUNTIF($B$6:$B$50,B14) -> 1
A15: SKL-010 | B15: SHORT | C15: Владение коротким оружием | D15: SELECTABLE_GENERAL | E15: PLAYER_HOST; SENTIENT_HOST; ADVISER_IF_GRANTED | F15: BONUS_LEVEL_FORMULA_CORE-165 | G15: Урон/точность короткого клинкового, его метание, сходные предметы | H15: NO_RULED_UPPER_LIMIT | I15: SHORT | L15: -5 | M15: CORE-165; CORE-167 | N15: Q-CORE-024; Q-CORE-051 | O15: ACTIVE | P15: =COUNTIF($B$6:$B$50,B15) -> 1
A16: SKL-011 | B16: AXES | C16: Владение топорами | D16: SELECTABLE_GENERAL | E16: PLAYER_HOST; SENTIENT_HOST; ADVISER_IF_GRANTED | F16: BONUS_LEVEL_FORMULA_CORE-165 | G16: Урон/точность топоров | H16: NO_RULED_UPPER_LIMIT | I16: AXES | L16: -5 | M16: CORE-165; CORE-167 | N16: Q-CORE-024; Q-CORE-051 | O16: ACTIVE | P16: =COUNTIF($B$6:$B$50,B16) -> 1
A17: SKL-012 | B17: SHIELD | C17: Владение щитом | D17: SELECTABLE_GENERAL | E17: PLAYER_HOST; SENTIENT_HOST; ADVISER_IF_GRANTED | F17: BONUS_LEVEL_FORMULA_CORE-165 | G17: Урон/точность щитом и блок щитом | H17: NO_RULED_UPPER_LIMIT | I17: SHIELD | L17: -5 | M17: CORE-165; CORE-167 | N17: Q-CORE-024; Q-CORE-051 | O17: ACTIVE | P17: =COUNTIF($B$6:$B$50,B17) -> 1
A18: SKL-013 | B18: RIDING | C18: Наездник | D18: SELECTABLE_GENERAL | E18: PLAYER_HOST; SENTIENT_HOST; ADVISER_IF_GRANTED | F18: BONUS_LEVEL_FORMULA_CORE-165 | G18: Управление скакуном; небоевое разрешение исключено | H18: NO_RULED_UPPER_LIMIT | I18: RIDING | L18: -5 | M18: CORE-165; CORE-167 | N18: Q-CORE-024; Q-CORE-051 | O18: ACTIVE | P18: =COUNTIF($B$6:$B$50,B18) -> 1
A19: SKL-014 | B19: STEALTH | C19: Скрытность | D19: SELECTABLE_GENERAL | E19: PLAYER_HOST; SENTIENT_HOST; ADVISER_IF_GRANTED | F19: BONUS_LEVEL_FORMULA_CORE-165 | G19: Маскировка, сокрытие, схроны, скрытые перемещения; разрешение исключено | H19: NO_RULED_UPPER_LIMIT | I19: STEALTH | M19: CORE-165; CORE-167 | N19: Q-CORE-024; Q-CORE-051 | O19: ACTIVE | P19: =COUNTIF($B$6:$B$50,B19) -> 1
A20: SKL-015 | B20: THIEVERY | C20: Вор | D20: SELECTABLE_GENERAL | E20: PLAYER_HOST; SENTIENT_HOST; ADVISER_IF_GRANTED | F20: BONUS_LEVEL_FORMULA_CORE-165 | G20: Кражи, замки, обыск, городская маскировка; разрешение исключено | H20: NO_RULED_UPPER_LIMIT | I20: THIEVERY | M20: CORE-165; CORE-167 | N20: Q-CORE-024; Q-CORE-051 | O20: ACTIVE | P20: =COUNTIF($B$6:$B$50,B20) -> 1
A21: SKL-016 | B21: ACROBATICS | C21: Акробатика | D21: SELECTABLE_GENERAL | E21: PLAYER_HOST; SENTIENT_HOST; ADVISER_IF_GRANTED | F21: BONUS_LEVEL_FORMULA_CORE-165 | G21: Лазание, прыжки, кувырки, сложные маршруты, паркур | H21: NO_RULED_UPPER_LIMIT | I21: ACROBATICS | M21: CORE-165; CORE-167 | N21: Q-CORE-024; Q-CORE-051 | O21: ACTIVE | P21: =COUNTIF($B$6:$B$50,B21) -> 1
A22: SKL-017 | B22: ORIENTATION | C22: Ориентирование | D22: SELECTABLE_GENERAL | E22: PLAYER_HOST; SENTIENT_HOST; ADVISER_IF_GRANTED | F22: BONUS_LEVEL_FORMULA_CORE-165 | G22: Маршрут/путь/картина вслепую; разрешение исключено | H22: NO_RULED_UPPER_LIMIT | I22: ORIENTATION | M22: CORE-165; CORE-167 | N22: Q-CORE-024; Q-CORE-051 | O22: ACTIVE | P22: =COUNTIF($B$6:$B$50,B22) -> 1
A23: SKL-018 | B23: LEARNING | C23: Ученик | D23: SELECTABLE_GENERAL | E23: PLAYER_HOST; SENTIENT_HOST; ADVISER_IF_GRANTED | F23: BONUS_LEVEL_FORMULA_CORE-165 | G23: Обучение навыку; разрешение исключено | H23: NO_RULED_UPPER_LIMIT | I23: LEARNING | M23: CORE-165; CORE-167 | N23: Q-CORE-024; Q-CORE-051 | O23: ACTIVE | P23: =COUNTIF($B$6:$B$50,B23) -> 1
A24: SKL-019 | B24: TEACHING | C24: Учитель | D24: SELECTABLE_GENERAL | E24: PLAYER_HOST; SENTIENT_HOST; ADVISER_IF_GRANTED | F24: BONUS_LEVEL_FORMULA_CORE-165 | G24: Обучение/объяснение; разрешение исключено | H24: NO_RULED_UPPER_LIMIT | I24: TEACHING | M24: CORE-165; CORE-167 | N24: Q-CORE-024; Q-CORE-051 | O24: ACTIVE | P24: =COUNTIF($B$6:$B$50,B24) -> 1
A25: SKL-020 | B25: CRAFT | C25: Крафт | D25: SELECTABLE_GENERAL | E25: PLAYER_HOST; SENTIENT_HOST; ADVISER_IF_GRANTED | F25: BONUS_LEVEL_FORMULA_CORE-165 | G25: Можно выбрать и хранить; создание предметов приложением не исполняется | H25: NO_RULED_UPPER_LIMIT | I25: CRAFT | L25: -5 | M25: CORE-165; CORE-167 | N25: Q-CORE-024; Q-CORE-051 | O25: ACTIVE | P25: =COUNTIF($B$6:$B$50,B25) -> 1
A26: SKL-021 | B26: REPAIR | C26: Ремонт | D26: SELECTABLE_GENERAL | E26: PLAYER_HOST; SENTIENT_HOST; ADVISER_IF_GRANTED | F26: BONUS_LEVEL_FORMULA_CORE-165 | G26: Ремонт | H26: NO_RULED_UPPER_LIMIT | I26: REPAIR | L26: -5 | M26: CORE-165; CORE-167 | N26: Q-CORE-024; Q-CORE-051 | O26: ACTIVE | P26: =COUNTIF($B$6:$B$50,B26) -> 1
A27: SKL-022 | B27: TRACKING | C27: Выслеживание | D27: SELECTABLE_GENERAL | E27: PLAYER_HOST; SENTIENT_HOST; ADVISER_IF_GRANTED | F27: BONUS_LEVEL_FORMULA_CORE-165 | G27: Следы/направление/обнаружение; небоевое разрешение исключено | H27: NO_RULED_UPPER_LIMIT | I27: TRACKING | M27: CORE-165; CORE-167 | N27: Q-CORE-024; Q-CORE-051 | O27: ACTIVE | P27: =COUNTIF($B$6:$B$50,B27) -> 1
A28: SKL-023 | B28: AWARENESS | C28: Внимательность | D28: SELECTABLE_GENERAL | E28: PLAYER_HOST; SENTIENT_HOST; ADVISER_IF_GRANTED | F28: BONUS_LEVEL_FORMULA_CORE-165 | G28: Сбор информации, обнаружение, память; небоевое разрешение исключено | H28: NO_RULED_UPPER_LIMIT | I28: AWARENESS | M28: CORE-165; CORE-167 | N28: Q-CORE-024; Q-CORE-051 | O28: ACTIVE | P28: =COUNTIF($B$6:$B$50,B28) -> 1
A29: SKL-024 | B29: ANALYTICAL_THINKING | C29: Аналитическое мышление | D29: SELECTABLE_GENERAL | E29: PLAYER_HOST; SENTIENT_HOST; ADVISER_IF_GRANTED | F29: BONUS_LEVEL_FORMULA_CORE-165 | G29: Анализ, упреждающий удар; социальное сопротивление исключено | H29: NO_RULED_UPPER_LIMIT | I29: ANALYTICAL_THINKING | M29: CORE-165; CORE-167 | N29: Q-CORE-024; Q-CORE-051 | O29: ACTIVE | P29: =COUNTIF($B$6:$B$50,B29) -> 1
A30: SKL-025 | B30: INVENTION | C30: Изобретательство | D30: SELECTABLE_GENERAL | E30: PLAYER_HOST; SENTIENT_HOST; ADVISER_IF_GRANTED | F30: BONUS_LEVEL_FORMULA_CORE-165 | G30: Новое/улучшение/новое применение; разрешение исключено | H30: NO_RULED_UPPER_LIMIT | I30: INVENTION | M30: CORE-165; CORE-167 | N30: Q-CORE-024; Q-CORE-051 | O30: ACTIVE | P30: =COUNTIF($B$6:$B$50,B30) -> 1
A31: SKL-026 | B31: LITERACY | C31: Письмо и чтение | D31: SELECTABLE_GENERAL | E31: PLAYER_HOST; SENTIENT_HOST; ADVISER_IF_GRANTED | F31: BONUS_LEVEL_FORMULA_CORE-165 | G31: Грамотность; Единый/Вольный с W<8 без навыка неграмотен | H31: NO_RULED_UPPER_LIMIT | I31: LITERACY | M31: CORE-165; CORE-167 | N31: Q-CORE-024; Q-CORE-051 | O31: ACTIVE | P31: =COUNTIF($B$6:$B$50,B31) -> 1
A32: SKL-027 | B32: SEDUCTION | C32: Соблазнение | D32: SELECTABLE_GENERAL | E32: PLAYER_HOST; SENTIENT_HOST; ADVISER_IF_GRANTED | F32: BONUS_LEVEL_FORMULA_CORE-165 | G32: Социальное; разрешение исключено | H32: NO_RULED_UPPER_LIMIT | I32: SEDUCTION | M32: CORE-165; CORE-167 | N32: Q-CORE-024; Q-CORE-051 | O32: ACTIVE | P32: =COUNTIF($B$6:$B$50,B32) -> 1
A33: SKL-028 | B33: DECEPTION | C33: Обман | D33: SELECTABLE_GENERAL | E33: PLAYER_HOST; SENTIENT_HOST; ADVISER_IF_GRANTED | F33: BONUS_LEVEL_FORMULA_CORE-165 | G33: Социальное; разрешение исключено | H33: NO_RULED_UPPER_LIMIT | I33: DECEPTION | M33: CORE-165; CORE-167 | N33: Q-CORE-024; Q-CORE-051 | O33: ACTIVE | P33: =COUNTIF($B$6:$B$50,B33) -> 1
A34: SKL-029 | B34: ACTING | C34: Актёрское мастерство | D34: SELECTABLE_GENERAL | E34: PLAYER_HOST; SENTIENT_HOST; ADVISER_IF_GRANTED | F34: BONUS_LEVEL_FORMULA_CORE-165 | G34: Социальное; разрешение исключено | H34: NO_RULED_UPPER_LIMIT | I34: ACTING | M34: CORE-165; CORE-167 | N34: Q-CORE-024; Q-CORE-051 | O34: ACTIVE | P34: =COUNTIF($B$6:$B$50,B34) -> 1
A35: SKL-030 | B35: BARGAINING | C35: Торг | D35: SELECTABLE_GENERAL | E35: PLAYER_HOST; SENTIENT_HOST; ADVISER_IF_GRANTED | F35: BONUS_LEVEL_FORMULA_CORE-165 | G35: Социальное; разрешение исключено | H35: NO_RULED_UPPER_LIMIT | I35: BARGAINING | M35: CORE-165; CORE-167 | N35: Q-CORE-024; Q-CORE-051 | O35: ACTIVE | P35: =COUNTIF($B$6:$B$50,B35) -> 1
A36: SKL-031 | B36: EXECUTIONER | C36: Палач | D36: SELECTABLE_GENERAL | E36: PLAYER_HOST; SENTIENT_HOST; ADVISER_IF_GRANTED | F36: BONUS_LEVEL_FORMULA_CORE-165 | G36: Запугивание/допрос/пытки/связывание; разрешение исключено | H36: NO_RULED_UPPER_LIMIT | I36: EXECUTIONER | M36: CORE-165; CORE-167 | N36: Q-CORE-024; Q-CORE-051 | O36: ACTIVE | P36: =COUNTIF($B$6:$B$50,B36) -> 1
A37: SKL-032 | B37: WILDERNESS_SURVIVAL | C37: Выживание в дикой природе | D37: SELECTABLE_GENERAL | E37: PLAYER_HOST; SENTIENT_HOST; ADVISER_IF_GRANTED | F37: BONUS_LEVEL_FORMULA_CORE-165 | G37: Небоевые действия/маскировка; разрешение исключено | H37: NO_RULED_UPPER_LIMIT | I37: WILDERNESS_SURVIVAL | M37: CORE-165; CORE-167 | N37: Q-CORE-024; Q-CORE-051 | O37: ACTIVE | P37: =COUNTIF($B$6:$B$50,B37) -> 1
A38: SKL-033 | B38: LIGHTNING_REACTION | C38: Молниеносная реакция | D38: SELECTABLE_GENERAL | E38: PLAYER_HOST; SENTIENT_HOST; ADVISER_IF_GRANTED | F38: BONUS_LEVEL_FORMULA_CORE-165 | G38: Реакция на нападение и уклонение | H38: NO_RULED_UPPER_LIMIT | I38: LIGHTNING_REACTION | M38: CORE-165; CORE-167 | N38: Q-CORE-024; Q-CORE-051 | O38: ACTIVE | P38: =COUNTIF($B$6:$B$50,B38) -> 1
... A42: SKL-037 | B42: COOKING | C42: Кулинария | D42: SELECTABLE_GENERAL | E42: PLAYER_HOST; SENTIENT_HOST; ADVISER_IF_GRANTED | F42: BONUS_LEVEL_FORMULA_CORE-165 | G42: Пища/ингредиенты; разрешение исключено | H42: NO_RULED_UPPER_LIMIT | I42: COOKING | M42: CORE-165; CORE-167 | N42: Q-CORE-024; Q-CORE-051 | O42: ACTIVE | P42: =COUNTIF($B$6:$B$50,B42) -> 1
A43: SKL-038 | B43: MEDIC | C43: Медик | D43: SELECTABLE_GENERAL | E43: PLAYER_HOST; SENTIENT_HOST; ADVISER_IF_GRANTED | F43: BONUS_LEVEL_FORMULA_CORE-165 | G43: Медицинские манипуляции; Искатель исключён из штрафа отсутствия | H43: NO_RULED_UPPER_LIMIT | I43: MEDIC | L43: -10 | M43: CORE-165; CORE-167 | N43: Q-CORE-024; Q-CORE-051 | O43: ACTIVE | P43: =COUNTIF($B$6:$B$50,B43) -> 1
A44: SKL-039 | B44: ERUDITION | C44: Эрудиция | D44: SELECTABLE_GENERAL | E44: PLAYER_HOST; SENTIENT_HOST; ADVISER_IF_GRANTED | F44: BONUS_LEVEL_FORMULA_CORE-165 | G44: Вспоминание фактов; разрешение исключено | H44: NO_RULED_UPPER_LIMIT | I44: ERUDITION | M44: CORE-165; CORE-167 | N44: Q-CORE-024; Q-CORE-051 | O44: ACTIVE | P44: =COUNTIF($B$6:$B$50,B44) -> 1
A45: SKL-040 | B45: NATURAL_SCIENCE | C45: Естественнонаучные знания | D45: SELECTABLE_GENERAL | E45: PLAYER_HOST; SENTIENT_HOST; ADVISER_IF_GRANTED | F45: BONUS_LEVEL_FORMULA_CORE-165 | G45: Дополнительный модификатор изобретательства/крафта только при основном навыке | H45: NO_RULED_UPPER_LIMIT | I45: NATURAL_SCIENCE | M45: CORE-165; CORE-167 | N45: Q-CORE-024; Q-CORE-051 | O45: ACTIVE | P45: =COUNTIF($B$6:$B$50,B45) -> 1
A46: SKL-041 | B46: VETERAN_DRINKER | C46: Алкоголик со стажем | D46: SELECTABLE_GENERAL | E46: PLAYER_HOST; SENTIENT_HOST; ADVISER_IF_GRANTED | F46: BONUS_LEVEL_FORMULA_CORE-165 | G46: Дополнительный модификатор сопротивления опьянению; разрешение исключено | H46: NO_RULED_UPPER_LIMIT | I46: VETERAN_DRINKER | M46: CORE-165; CORE-167 | N46: Q-CORE-024; Q-CORE-051 | O46: ACTIVE | P46: =COUNTIF($B$6:$B$50,B46) -> 1
A47: SKL-042 | B47: FOLLOWING_PAIN | C47: Идущий вслед за болью | D47: FIXED_RACE_PASSIVE | E47: PLAYER_HOST; SENTIENT_HOST | F47: FIXED_0 | G47: Resistance to torture and self-control while burning. | H47: 15 | I47: FOLLOWING_PAIN | J47: UNITED | M47: CORE-004 | O47: ACTIVE | P47: =COUNTIF($B$6:$B$50,B47) -> 1
A48: SKL-043 | B48: PURE_SEEKER | C48: Искатель Последнего Рассвета | D48: FIXED_CLASS_PASSIVE | E48: PLAYER_HOST; SENTIENT_HOST | F48: FIXED_1 | G48: Study, pattern finding, craft, repair, invention, first aid, medical manipulation, wilderness survival and preemptive strike. Craft is stored but its creation action is not automated. | H48: 5 | I48: PURE_SEEKER | J48: PURE | K48: SEEKER | M48: CORE-009 | O48: ACTIVE | P48: =COUNTIF($B$6:$B$50,B48) -> 1
A49: SKL-044 | B49: PURE_STALKER | C49: Сталкер Последнего Рассвета | D49: FIXED_CLASS_PASSIVE | E49: PLAYER_HOST; SENTIENT_HOST | F49: FIXED_1 | G49: Route finding, tracking, detection, stealth, survival, inspection, lightning reaction, dodge and escape; no proficiency penalty for listed Pure weapons and Cesmor. | H49: 4 | I49: PURE_STALKER | J49: PURE | K49: STALKER | M49: CORE-010 | O49: ACTIVE | P49: =COUNTIF($B$6:$B$50,B49) -> 1
A50: SKL-045 | B50: PURE_SOLDIER | C50: Солдат Последнего Рассвета | D50: FIXED_CLASS_PASSIVE | E50: PLAYER_HOST; SENTIENT_HOST | F50: FIXED_1 | G50: Accuracy of unarmed attacks, grappling, one-/hand-and-a-half sword attacks, blocking and shield attacks; listed equipment proficiency; free melee-target switch. | H50: 3 | I50: PURE_SOLDIER | J50: PURE | K50: SOLDIER | M50: CORE-013 | O50: ACTIVE | P50: =COUNTIF($B$6:$B$50,B50) -> 1

Sheet 05_Требования_навыков
A1: Требования навыков
A2: Все условия одной RequirementSet соединяются AND и проверяются на skillStageStats: base + race + class, строго до бонусов симбионтов.
A5: RequirementID | B5: SkillKey | C5: RequirementSetID | D5: StatCode | E5: MinValue | F5: EvaluationStage | G5: BeforeSymbiontBonuses | H5: Rule ID | I5: Source Question ID | J5: ID unique
A6: REQ-UNARMED-S | B6: UNARMED | C6: REQSET-UNARMED-CREATION | D6: S | E6: 9 | F6: SKILL_STAGE_PRE_SYMBIONT | G6: =TRUE() -> TRUE | H6: CORE-167 | I6: Q-CORE-024 | J6: =COUNTIF($A$6:$A$89,A6) -> 1
A7: REQ-UNARMED-D | B7: UNARMED | C7: REQSET-UNARMED-CREATION | D7: D | E7: 11 | F7: SKILL_STAGE_PRE_SYMBIONT | G7: =TRUE() -> TRUE | H7: CORE-167 | I7: Q-CORE-024 | J7: =COUNTIF($A$6:$A$89,A7) -> 1
A8: REQ-GRAPPLING-S | B8: GRAPPLING | C8: REQSET-GRAPPLING-CREATION | D8: S | E8: 11 | F8: SKILL_STAGE_PRE_SYMBIONT | G8: =TRUE() -> TRUE | H8: CORE-167 | I8: Q-CORE-024 | J8: =COUNTIF($A$6:$A$89,A8) -> 1
A9: REQ-GRAPPLING-D | B9: GRAPPLING | C9: REQSET-GRAPPLING-CREATION | D9: D | E9: 9 | F9: SKILL_STAGE_PRE_SYMBIONT | G9: =TRUE() -> TRUE | H9: CORE-167 | I9: Q-CORE-024 | J9: =COUNTIF($A$6:$A$89,A9) -> 1
A10: REQ-GRAPPLING-I | B10: GRAPPLING | C10: REQSET-GRAPPLING-CREATION | D10: I | E10: 4 | F10: SKILL_STAGE_PRE_SYMBIONT | G10: =TRUE() -> TRUE | H10: CORE-167 | I10: Q-CORE-024 | J10: =COUNTIF($A$6:$A$89,A10) -> 1
A11: REQ-WEAPON_THROWING-S | B11: WEAPON_THROWING | C11: REQSET-WEAPON_THROWING-CREATION | D11: S | E11: 5 | F11: SKILL_STAGE_PRE_SYMBIONT | G11: =TRUE() -> TRUE | H11: CORE-167 | I11: Q-CORE-024 | J11: =COUNTIF($A$6:$A$89,A11) -> 1
A12: REQ-WEAPON_THROWING-D | B12: WEAPON_THROWING | C12: REQSET-WEAPON_THROWING-CREATION | D12: D | E12: 11 | F12: SKILL_STAGE_PRE_SYMBIONT | G12: =TRUE() -> TRUE | H12: CORE-167 | I12: Q-CORE-024 | J12: =COUNTIF($A$6:$A$89,A12) -> 1
A13: REQ-WEAPON_THROWING-I | B13: WEAPON_THROWING | C13: REQSET-WEAPON_THROWING-CREATION | D13: I | E13: 5 | F13: SKILL_STAGE_PRE_SYMBIONT | G13: =TRUE() -> TRUE | H13: CORE-167 | I13: Q-CORE-024 | J13: =COUNTIF($A$6:$A$89,A13) -> 1
A14: REQ-OBJECT_THROWING-S | B14: OBJECT_THROWING | C14: REQSET-OBJECT_THROWING-CREATION | D14: S | E14: 11 | F14: SKILL_STAGE_PRE_SYMBIONT | G14: =TRUE() -> TRUE | H14: CORE-167 | I14: Q-CORE-024 | J14: =COUNTIF($A$6:$A$89,A14) -> 1
A15: REQ-OBJECT_THROWING-D | B15: OBJECT_THROWING | C15: REQSET-OBJECT_THROWING-CREATION | D15: D | E15: 5 | F15: SKILL_STAGE_PRE_SYMBIONT | G15: =TRUE() -> TRUE | H15: CORE-167 | I15: Q-CORE-024 | J15: =COUNTIF($A$6:$A$89,A15) -> 1
A16: REQ-SHOOTING-S | B16: SHOOTING | C16: REQSET-SHOOTING-CREATION | D16: S | E16: 5 | F16: SKILL_STAGE_PRE_SYMBIONT | G16: =TRUE() -> TRUE | H16: CORE-167 | I16: Q-CORE-024 | J16: =COUNTIF($A$6:$A$89,A16) -> 1
A17: REQ-SHOOTING-D | B17: SHOOTING | C17: REQSET-SHOOTING-CREATION | D17: D | E17: 6 | F17: SKILL_STAGE_PRE_SYMBIONT | G17: =TRUE() -> TRUE | H17: CORE-167 | I17: Q-CORE-024 | J17: =COUNTIF($A$6:$A$89,A17) -> 1
... A89: REQ-VETERAN_DRINKER-Z | B89: VETERAN_DRINKER | C89: REQSET-VETERAN_DRINKER-CREATION | D89: Z | E89: 8 | F89: SKILL_STAGE_PRE_SYMBIONT | G89: =TRUE() -> TRUE | H89: CORE-167 | I89: Q-CORE-024 | J89: =COUNTIF($A$6:$A$89,A89) -> 1

Sheet 06_Модификаторы_персонажа
A1: Модификаторы персонажа
A2: Нормализованные расовые, классовые и профильные симбиотические дельты. Способностные и временные эффекты остаются в карточках способностей.
A5: ModifierID | B5: SourceType | C5: SourceID | D5: TargetKind | E5: TargetCode | F5: Operation | G5: Value | H5: ContextPredicate | I5: ApplicationStage | J5: StackPolicy | K5: Rule IDs | L5: ID unique
A6: MOD-RACE-FREE-MANUAL-S | B6: RACE | C6: FREE | D6: STAT | E6: S | F6: ADD | G6: -2 | H6: creationMode=MANUAL | I6: SKILL_STAGE | J6: ADD_ONCE_PER_SOURCE | K6: CORE-006 | L6: =COUNTIF($A$6:$A$48,A6) -> 1
A7: MOD-RACE-FREE-MANUAL-M | B7: RACE | C7: FREE | D7: STAT | E7: M | F7: ADD | G7: -2 | H7: creationMode=MANUAL | I7: SKILL_STAGE | J7: ADD_ONCE_PER_SOURCE | K7: CORE-006 | L7: =COUNTIF($A$6:$A$48,A7) -> 1
A8: MOD-RACE-FREE-MANUAL-Z | B8: RACE | C8: FREE | D8: STAT | E8: Z | F8: ADD | G8: -2 | H8: creationMode=MANUAL | I8: SKILL_STAGE | J8: ADD_ONCE_PER_SOURCE | K8: CORE-006 | L8: =COUNTIF($A$6:$A$48,A8) -> 1
A9: MOD-RACE-UNITED-RANDOM-S | B9: RACE | C9: UNITED | D9: STAT | E9: S | F9: ADD | G9: -3 | H9: creationMode=RANDOM | I9: SKILL_STAGE | J9: ADD_ONCE_PER_SOURCE | K9: CORE-001 | L9: =COUNTIF($A$6:$A$48,A9) -> 1
A10: MOD-RACE-UNITED-RANDOM-M | B10: RACE | C10: UNITED | D10: STAT | E10: M | F10: ADD | G10: -6 | H10: creationMode=RANDOM | I10: SKILL_STAGE | J10: ADD_ONCE_PER_SOURCE | K10: CORE-001 | L10: =COUNTIF($A$6:$A$48,A10) -> 1
A11: MOD-RACE-UNITED-RANDOM-Z | B11: RACE | C11: UNITED | D11: STAT | E11: Z | F11: ADD | G11: -6 | H11: creationMode=RANDOM | I11: SKILL_STAGE | J11: ADD_ONCE_PER_SOURCE | K11: CORE-001 | L11: =COUNTIF($A$6:$A$48,A11) -> 1
A12: MOD-RACE-UNITED-MANUAL-S | B12: RACE | C12: UNITED | D12: STAT | E12: S | F12: ADD | G12: -7 | H12: creationMode=MANUAL | I12: SKILL_STAGE | J12: ADD_ONCE_PER_SOURCE | K12: CORE-001 | L12: =COUNTIF($A$6:$A$48,A12) -> 1
A13: MOD-RACE-UNITED-MANUAL-M | B13: RACE | C13: UNITED | D13: STAT | E13: M | F13: ADD | G13: -10 | H13: creationMode=MANUAL | I13: SKILL_STAGE | J13: ADD_ONCE_PER_SOURCE | K13: CORE-001 | L13: =COUNTIF($A$6:$A$48,A13) -> 1
A14: MOD-RACE-UNITED-MANUAL-Z | B14: RACE | C14: UNITED | D14: STAT | E14: Z | F14: ADD | G14: -10 | H14: creationMode=MANUAL | I14: SKILL_STAGE | J14: ADD_ONCE_PER_SOURCE | K14: CORE-001 | L14: =COUNTIF($A$6:$A$48,A14) -> 1
A15: MOD-RACE-UNITED-C-VS-UNITED | B15: RACE | C15: UNITED | D15: STAT | E15: C | F15: ADD | G15: 5 | H15: socialTargetRace=UNITED | I15: CHECK_CONTEXT | J15: MOST_SPECIFIC_CONTEXT | K15: CORE-001 | L15: =COUNTIF($A$6:$A$48,A15) -> 1
A16: MOD-RACE-UNITED-C-VS-PURE | B16: RACE | C16: UNITED | D16: STAT | E16: C | F16: ADD | G16: -15 | H16: socialTargetRace=PURE | I16: CHECK_CONTEXT | J16: MOST_SPECIFIC_CONTEXT | K16: CORE-001 | L16: =COUNTIF($A$6:$A$48,A16) -> 1
A17: MOD-CLASS-SEEKER-S | B17: PURE_CLASS | C17: SEEKER | D17: STAT | E17: S | F17: ADD | G17: 2 | H17: ownerRace=PURE | I17: SKILL_STAGE | J17: ADD_ONCE_PER_SOURCE | K17: CORE-009 | L17: =COUNTIF($A$6:$A$48,A17) -> 1
... A48: MOD-SYMBIONT-PLAGUE_DOCTOR-I | B48: SYMBIONT_PROFILE | C48: PLAGUE_DOCTOR | D48: STAT | E48: I | F48: ADD | G48: 10 | H48: symbiontActive=true | I48: EFFECTIVE_STATS | J48: ADD_ONCE_PER_ACTIVE_SPECIES | K48: MON-040 | L48: =COUNTIF($A$6:$A$48,A48) -> 1

Sheet 07_Симбионты
A1: Каталог симбионтов
A2: 20 обычных видов и 3 симбиотических чудовища. LinkedStatCodes — машинный источник прямой маршрутизации XP; нормализованные пары приведены ниже. ADVISER каноничен, ADVISOR — только alias.
A5: SpeciesKey | B5: Название | C5: SymbiontKind | D5: SlotCost | E5: AllowedRaceCodes | F5: MaxL | G5: XPPolicy | H5: OEPolicy | I5: BranchPolicy | J5: AdditionalSlotPolicy | K5: MonsterProfileID | L5: ProfileRuleID | M5: Rule IDs | N5: Источник | O5: Status | P5: ID unique | Q5: LinkedStatCodes
A6: WEAVER | B6: Ткач | C6: ORDINARY | D6: 1 | E6: FREE; UNITED | F6: 6 | G6: SYM-021_AWARD; SYM-022_NODE_COST_EQUALS_NODE_LEVEL | H6: baseMaxOE=50×L; currentOE clamped to max; new instance full except transplant=0 | I6: XOR+OR | J6: NONE | L6: SYM-026 | M6: SYM-026; SYM-009; SYM-020; SYM-021; SYM-022; SYM-024 | N6: 7.5.1–7.5.1.1, стр. 115 (дерево прочитано визуально). | O6: ACTIVE | P6: =COUNTIF($A$6:$A$28,A6) -> 1 | Q6: I
A7: TAIPAN | B7: Тайпан | C7: ORDINARY | D7: 1 | E7: FREE; UNITED | F7: 7 | G7: SYM-021_AWARD; SYM-022_NODE_COST_EQUALS_NODE_LEVEL | H7: baseMaxOE=50×L; currentOE clamped to max; new instance full except transplant=0 | I7: LINEAR_OR_EXPLICIT_PARENTS | J7: NONE | L7: SYM-037 | M7: SYM-037; SYM-009; SYM-020; SYM-021; SYM-022; SYM-024 | N7: 7.5.2–7.5.2.1, стр. 118 (дерево прочитано визуально). | O7: ACTIVE | P7: =COUNTIF($A$6:$A$28,A7) -> 1 | Q7: D; W
A8: OWL | B8: Сова | C8: ORDINARY | D8: 1 | E8: FREE; UNITED | F8: 6 | G8: SYM-021_AWARD; SYM-022_NODE_COST_EQUALS_NODE_LEVEL | H8: baseMaxOE=10×L; currentOE clamped to max; new instance full except transplant=0 | I8: LINEAR_OR_EXPLICIT_PARENTS | J8: NONE | L8: SYM-046 | M8: SYM-046; SYM-009; SYM-020; SYM-021; SYM-022; SYM-024 | N8: 7.5.3–7.5.3.1, стр. 121 (дерево прочитано визуально). | O8: ACTIVE | P8: =COUNTIF($A$6:$A$28,A8) -> 1 | Q8: W
A9: TEACHER | B9: Учитель | C9: ORDINARY | D9: 1 | E9: FREE; UNITED | F9: 6 | G9: SYM-021_AWARD; SYM-022_NODE_COST_EQUALS_NODE_LEVEL | H9: baseMaxOE=20×L; currentOE clamped to max; new instance full except transplant=0 | I9: LINEAR_OR_EXPLICIT_PARENTS | J9: NONE | L9: SYM-053 | M9: SYM-053; SYM-009; SYM-020; SYM-021; SYM-022; SYM-024 | N9: 7.5.4–7.5.4.1, стр. 123 (дерево прочитано визуально). | O9: ACTIVE | P9: =COUNTIF($A$6:$A$28,A9) -> 1 | Q9: W
A10: ARMADILLO | B10: Броненосец | C10: ORDINARY | D10: 1 | E10: FREE; UNITED | F10: 6 | G10: SYM-021_AWARD; SYM-022_NODE_COST_EQUALS_NODE_LEVEL | H10: baseMaxOE=50×L; currentOE clamped to max; new instance full except transplant=0 | I10: LINEAR_OR_EXPLICIT_PARENTS | J10: NONE | L10: SYM-060 | M10: SYM-060; SYM-009; SYM-020; SYM-021; SYM-022; SYM-024 | N10: 7.5.5–7.5.5.1, стр. 125 (дерево прочитано визуально). | O10: ACTIVE | P10: =COUNTIF($A$6:$A$28,A10) -> 1 | Q10: M; Z
A11: DRAGON | B11: Дракон | C11: ORDINARY | D11: 1 | E11: FREE; UNITED | F11: 6 | G11: SYM-021_AWARD; SYM-022_NODE_COST_EQUALS_NODE_LEVEL | H11: baseMaxOE=30×L; currentOE clamped to max; new instance full except transplant=0 | I11: LINEAR_OR_EXPLICIT_PARENTS | J11: NONE | L11: SYM-067 | M11: SYM-067; SYM-009; SYM-020; SYM-021; SYM-022; SYM-024 | N11: 7.5.6–7.5.6.1, стр. 127 (дерево прочитано визуально). | O11: ACTIVE | P11: =COUNTIF($A$6:$A$28,A11) -> 1 | Q11: D; W
A12: TROGR | B12: Трогр | C12: ORDINARY | D12: 1 | E12: FREE; UNITED | F12: 6 | G12: SYM-021_AWARD; SYM-022_NODE_COST_EQUALS_NODE_LEVEL | H12: baseMaxOE=1000×L; currentOE clamped to max; new instance full except transplant=0 | I12: XOR | J12: NONE | L12: SYM-074 | M12: SYM-074; SYM-009; SYM-020; SYM-021; SYM-022; SYM-024 | N12: 7.5.7–7.5.7.1, стр. 129 (дерево прочитано визуально). | O12: ACTIVE | P12: =COUNTIF($A$6:$A$28,A12) -> 1 | Q12: S; D; M
A13: KEEPER | B13: Хранитель | C13: ORDINARY | D13: 1 | E13: FREE; UNITED | F13: 6 | G13: SYM-021_AWARD; SYM-022_NODE_COST_EQUALS_NODE_LEVEL | H13: baseMaxOE=100×L; currentOE clamped to max; new instance full except transplant=0; Кромсатель заменяет формулу на 200×L | I13: OR | J13: NONE | L13: SYM-083 | M13: SYM-083; SYM-009; SYM-020; SYM-021; SYM-022; SYM-024 | N13: 7.5.8–7.5.8.1, стр. 131 (дерево прочитано визуально). | O13: ACTIVE | P13: =COUNTIF($A$6:$A$28,A13) -> 1 | Q13: W; Z
A14: ADVISER | B14: Советник | C14: ORDINARY | D14: 1 | E14: FREE; UNITED | F14: 6 | G14: SYM-021_AWARD; SYM-022_NODE_COST_EQUALS_NODE_LEVEL | H14: baseMaxOE=20×L; currentOE clamped to max; new instance full except transplant=0 | I14: LINEAR_OR_EXPLICIT_PARENTS | J14: NONE | L14: SYM-095 | M14: SYM-095; SYM-009; SYM-020; SYM-021; SYM-022; SYM-024 | N14: 7.5.9–7.5.9.1, стр. 134 (дерево прочитано визуально). | O14: ACTIVE | P14: =COUNTIF($A$6:$A$28,A14) -> 1 | Q14: I; W
A15: TICK | B15: Клещ | C15: ORDINARY | D15: 1 | E15: FREE; UNITED | F15: 6 | G15: SYM-021_AWARD; SYM-022_NODE_COST_EQUALS_NODE_LEVEL | H15: baseMaxOE=50×L; currentOE clamped to max; new instance full except transplant=0 | I15: LINEAR_OR_EXPLICIT_PARENTS | J15: NONE | L15: SYM-102 | M15: SYM-102; SYM-009; SYM-020; SYM-021; SYM-022; SYM-024 | N15: 7.5.10–7.5.10.1, стр. 136 (дерево прочитано визуально). | O15: ACTIVE | P15: =COUNTIF($A$6:$A$28,A15) -> 1 | Q15: S; D
A16: CRICKET | B16: Сверчок | C16: ORDINARY | D16: 1 | E16: FREE; UNITED | F16: 6 | G16: SYM-021_AWARD; SYM-022_NODE_COST_EQUALS_NODE_LEVEL | H16: baseMaxOE=50×L; currentOE clamped to max; new instance full except transplant=0 | I16: LINEAR_OR_EXPLICIT_PARENTS | J16: NONE | L16: SYM-109 | M16: SYM-109; SYM-009; SYM-020; SYM-021; SYM-022; SYM-024 | N16: 7.5.11–7.5.11.1, стр. 138 (дерево прочитано визуально). | O16: ACTIVE | P16: =COUNTIF($A$6:$A$28,A16) -> 1 | Q16: D; M
A17: SPIDER | B17: Паук | C17: ORDINARY | D17: 1 | E17: FREE; UNITED | F17: 6 | G17: SYM-021_AWARD; SYM-022_NODE_COST_EQUALS_NODE_LEVEL | H17: baseMaxOE=50×L; currentOE clamped to max; new instance full except transplant=0 | I17: LINEAR_OR_EXPLICIT_PARENTS | J17: NONE | L17: SYM-116 | M17: SYM-116; SYM-009; SYM-020; SYM-021; SYM-022; SYM-024 | N17: 7.5.12–7.5.12.1, стр. 140 (дерево прочитано визуально). | O17: ACTIVE | P17: =COUNTIF($A$6:$A$28,A17) -> 1 | Q17: D; W
... A25: SKUNK | B25: Скунс | C25: ORDINARY | D25: 1 | E25: FREE; UNITED | F25: 6 | G25: SYM-021_AWARD; SYM-022_NODE_COST_EQUALS_NODE_LEVEL | H25: baseMaxOE=50×L; currentOE clamped to max; new instance full except transplant=0 | I25: LINEAR_OR_EXPLICIT_PARENTS | J25: NONE | L25: SYM-174 | M25: SYM-174; SYM-009; SYM-020; SYM-021; SYM-022; SYM-024 | N25: 7.5.20–7.5.20.1, стр. 160 (дерево прочитано визуально). | O25: ACTIVE | P25: =COUNTIF($A$6:$A$28,A25) -> 1 | Q25: D; M
A26: CHIMERA | B26: Химера | C26: SYMBIOTIC_MONSTER | D26: 4 | E26: UNITED | F26: 6 | G26: SYM-021_AWARD; SYM-022_NODE_COST_EQUALS_NODE_LEVEL | H26: baseMaxOE=400×L; currentOE clamped to max; new instance full except transplant=0 | I26: LINEAR_OR_EXPLICIT_PARENTS | J26: ONLY_CONFIRMED_DEVOURING; initial extraSlots=0; explicit devouringHistory; max +3 | K26: MON-002 | L26: MON-002 | M26: MON-002; SYM-009; SYM-020; SYM-021; SYM-022; SYM-024 | N26: §7.6.1, печ. стр. 163. | O26: ACTIVE | P26: =COUNTIF($A$6:$A$28,A26) -> 1 | Q26: Z; S; D
A27: PUPPETEER | B27: Кукловод | C27: SYMBIOTIC_MONSTER | D27: 4 | E27: UNITED | F27: 6 | G27: SYM-021_AWARD; SYM-022_NODE_COST_EQUALS_NODE_LEVEL | H27: baseMaxOE=400×L; currentOE clamped to max; new instance full except transplant=0 | I27: LINEAR_OR_EXPLICIT_PARENTS | J27: ORDINARY_ADDITIONAL_SYMBIONTS_FORBIDDEN | K27: MON-025 | L27: MON-025 | M27: MON-025; SYM-009; SYM-020; SYM-021; SYM-022; SYM-024 | N27: §7.6.2, печ. стр. 167. | O27: ACTIVE | P27: =COUNTIF($A$6:$A$28,A27) -> 1 | Q27: C; I; W
A28: PLAGUE_DOCTOR | B28: Чумной доктор | C28: SYMBIOTIC_MONSTER | D28: 4 | E28: UNITED | F28: 8 | G28: SYM-021_AWARD; SYM-022_NODE_COST_EQUALS_NODE_LEVEL | H28: baseMaxOE=400×L; currentOE clamped to max; new instance full except transplant=0 | I28: XOR | J28: ORDINARY_ADDITIONAL_SYMBIONTS_FORBIDDEN | K28: MON-040 | L28: MON-040 | M28: MON-040; SYM-009; SYM-020; SYM-021; SYM-022; SYM-024 | N28: §7.6.3, печ. стр. 170. | O28: ACTIVE | P28: =COUNTIF($A$6:$A$28,A28) -> 1 | Q28: Z; I; W
A31: Нормализованные связи SpeciesKey ↔ LinkedStatCode | B31: Нормализованные связи SpeciesKey ↔ LinkedStatCode | C31: Нормализованные связи SpeciesKey ↔ LinkedStatCode | D31: Нормализованные связи SpeciesKey ↔ LinkedStatCode | E31: Нормализованные связи SpeciesKey ↔ LinkedStatCode | F31: Нормализованные связи SpeciesKey ↔ LinkedStatCode | G31: Нормализованные связи SpeciesKey ↔ LinkedStatCode
A32: 48 отношений, дословно извлечённых из профильных карточек Rules v1.6. Модификатор характеристики профиля не считается связью. | B32: 48 отношений, дословно извлечённых из профильных карточек Rules v1.6. Модификатор характеристики профиля не считается связью. | C32: 48 отношений, дословно извлечённых из профильных карточек Rules v1.6. Модификатор характеристики профиля не считается связью. | D32: 48 отношений, дословно извлечённых из профильных карточек Rules v1.6. Модификатор характеристики профиля не считается связью. | E32: 48 отношений, дословно извлечённых из профильных карточек Rules v1.6. Модификатор характеристики профиля не считается связью. | F32: 48 отношений, дословно извлечённых из профильных карточек Rules v1.6. Модификатор характеристики профиля не считается связью. | G32: 48 отношений, дословно извлечённых из профильных карточек Rules v1.6. Модификатор характеристики профиля не считается связью.
A34: LinkID | B34: SpeciesKey | C34: LinkedStatCode | D34: StatOrder | E34: ProfileRuleID | F34: Status | G34: ID unique
A35: SYMSTAT-WEAVER-I | B35: WEAVER | C35: I | D35: 5 | E35: SYM-026 | F35: ACTIVE | G35: =COUNTIF($A$35:$A$80,A35) -> 1
A36: SYMSTAT-TAIPAN-D | B36: TAIPAN | C36: D | D36: 2 | E36: SYM-037 | F36: ACTIVE | G36: =COUNTIF($A$35:$A$80,A36) -> 1
A37: SYMSTAT-TAIPAN-W | B37: TAIPAN | C37: W | D37: 6 | E37: SYM-037 | F37: ACTIVE | G37: =COUNTIF($A$35:$A$80,A37) -> 1
A38: SYMSTAT-OWL-W | B38: OWL | C38: W | D38: 6 | E38: SYM-046 | F38: ACTIVE | G38: =COUNTIF($A$35:$A$80,A38) -> 1
A39: SYMSTAT-TEACHER-W | B39: TEACHER | C39: W | D39: 6 | E39: SYM-053 | F39: ACTIVE | G39: =COUNTIF($A$35:$A$80,A39) -> 1
A40: SYMSTAT-ARMADILLO-M | B40: ARMADILLO | C40: M | D40: 3 | E40: SYM-060 | F40: ACTIVE | G40: =COUNTIF($A$35:$A$80,A40) -> 1
A41: SYMSTAT-ARMADILLO-Z | B41: ARMADILLO | C41: Z | D41: 4 | E41: SYM-060 | F41: ACTIVE | G41: =COUNTIF($A$35:$A$80,A41) -> 1
A42: SYMSTAT-DRAGON-D | B42: DRAGON | C42: D | D42: 2 | E42: SYM-067 | F42: ACTIVE | G42: =COUNTIF($A$35:$A$80,A42) -> 1
A43: SYMSTAT-DRAGON-W | B43: DRAGON | C43: W | D43: 6 | E43: SYM-067 | F43: ACTIVE | G43: =COUNTIF($A$35:$A$80,A43) -> 1
A44: SYMSTAT-TROGR-S | B44: TROGR | C44: S | D44: 1 | E44: SYM-074 | F44: ACTIVE | G44: =COUNTIF($A$35:$A$80,A44) -> 1
A45: SYMSTAT-TROGR-D | B45: TROGR | C45: D | D45: 2 | E45: SYM-074 | F45: ACTIVE | G45: =COUNTIF($A$35:$A$80,A45) -> 1
A46: SYMSTAT-TROGR-M | B46: TROGR | C46: M | D46: 3 | E46: SYM-074 | F46: ACTIVE | G46: =COUNTIF($A$35:$A$80,A46) -> 1
... A80: SYMSTAT-PLAGUE_DOCTOR-Z | B80: PLAGUE_DOCTOR | C80: Z | D80: 4 | E80: MON-040 | F80: ACTIVE | G80: =COUNTIF($A$35:$A$80,A80) -> 1
A81: SYMSTAT-PLAGUE_DOCTOR-I | B81: PLAGUE_DOCTOR | C81: I | D81: 5 | E81: MON-040 | F81: ACTIVE | G81: 1
A82: SYMSTAT-PLAGUE_DOCTOR-W | B82: PLAGUE_DOCTOR | C82: W | D82: 6 | E82: MON-040 | F82: ACTIVE | G82: 1

Sheet 08_Уровни_симбионтов
A1: Уровни симбионтов
A2: Уровень 1 и все его узлы выдаются бесплатно; узел уровня N стоит N XP. MaxOE указан для базовой профильной формулы до частных замен.
A5: LevelProfileID | B5: SpeciesKey | C5: L | D5: XPThreshold / NodeCost | E5: Base MaxOE | F5: NodeUnlockCount | G5: RequiredPriorLevel | H5: Rule IDs | I5: ID unique
A6: LVL-WEAVER-1 | B6: WEAVER | C6: 1 | D6: 0 | E6: 50 | F6: 1 | H6: SYM-026; SYM-009; SYM-020; SYM-022; SYM-024 | I6: =COUNTIF($A$6:$A$149,A6) -> 1
A7: LVL-WEAVER-2 | B7: WEAVER | C7: 2 | D7: 2 | E7: 100 | F7: 2 | G7: 1 | H7: SYM-026; SYM-009; SYM-020; SYM-022; SYM-024 | I7: =COUNTIF($A$6:$A$149,A7) -> 1
A8: LVL-WEAVER-3 | B8: WEAVER | C8: 3 | D8: 3 | E8: 150 | F8: 2 | G8: 2 | H8: SYM-026; SYM-009; SYM-020; SYM-022; SYM-024 | I8: =COUNTIF($A$6:$A$149,A8) -> 1
A9: LVL-WEAVER-4 | B9: WEAVER | C9: 4 | D9: 4 | E9: 200 | F9: 2 | G9: 3 | H9: SYM-026; SYM-009; SYM-020; SYM-022; SYM-024 | I9: =COUNTIF($A$6:$A$149,A9) -> 1
A10: LVL-WEAVER-5 | B10: WEAVER | C10: 5 | D10: 5 | E10: 250 | F10: 2 | G10: 4 | H10: SYM-026; SYM-009; SYM-020; SYM-022; SYM-024 | I10: =COUNTIF($A$6:$A$149,A10) -> 1
A11: LVL-WEAVER-6 | B11: WEAVER | C11: 6 | D11: 6 | E11: 300 | F11: 1 | G11: 5 | H11: SYM-026; SYM-009; SYM-020; SYM-022; SYM-024 | I11: =COUNTIF($A$6:$A$149,A11) -> 1
A12: LVL-TAIPAN-1 | B12: TAIPAN | C12: 1 | D12: 0 | E12: 50 | F12: 1 | H12: SYM-037; SYM-009; SYM-020; SYM-022; SYM-024 | I12: =COUNTIF($A$6:$A$149,A12) -> 1
A13: LVL-TAIPAN-2 | B13: TAIPAN | C13: 2 | D13: 2 | E13: 100 | F13: 1 | G13: 1 | H13: SYM-037; SYM-009; SYM-020; SYM-022; SYM-024 | I13: =COUNTIF($A$6:$A$149,A13) -> 1
A14: LVL-TAIPAN-3 | B14: TAIPAN | C14: 3 | D14: 3 | E14: 150 | F14: 1 | G14: 2 | H14: SYM-037; SYM-009; SYM-020; SYM-022; SYM-024 | I14: =COUNTIF($A$6:$A$149,A14) -> 1
A15: LVL-TAIPAN-4 | B15: TAIPAN | C15: 4 | D15: 4 | E15: 200 | F15: 1 | G15: 3 | H15: SYM-037; SYM-009; SYM-020; SYM-022; SYM-024 | I15: =COUNTIF($A$6:$A$149,A15) -> 1
A16: LVL-TAIPAN-5 | B16: TAIPAN | C16: 5 | D16: 5 | E16: 250 | F16: 1 | G16: 4 | H16: SYM-037; SYM-009; SYM-020; SYM-022; SYM-024 | I16: =COUNTIF($A$6:$A$149,A16) -> 1
A17: LVL-TAIPAN-6 | B17: TAIPAN | C17: 6 | D17: 6 | E17: 300 | F17: 1 | G17: 5 | H17: SYM-037; SYM-009; SYM-020; SYM-022; SYM-024 | I17: =COUNTIF($A$6:$A$149,A17) -> 1
A18: LVL-TAIPAN-7 | B18: TAIPAN | C18: 7 | D18: 7 | E18: 350 | F18: 1 | G18: 6 | H18: SYM-037; SYM-009; SYM-020; SYM-022; SYM-024 | I18: =COUNTIF($A$6:$A$149,A18) -> 1
A19: LVL-OWL-1 | B19: OWL | C19: 1 | D19: 0 | E19: 10 | F19: 1 | H19: SYM-046; SYM-009; SYM-020; SYM-022; SYM-024 | I19: =COUNTIF($A$6:$A$149,A19) -> 1
A20: LVL-OWL-2 | B20: OWL | C20: 2 | D20: 2 | E20: 20 | F20: 1 | G20: 1 | H20: SYM-046; SYM-009; SYM-020; SYM-022; SYM-024 | I20: =COUNTIF($A$6:$A$149,A20) -> 1
A21: LVL-OWL-3 | B21: OWL | C21: 3 | D21: 3 | E21: 30 | F21: 1 | G21: 2 | H21: SYM-046; SYM-009; SYM-020; SYM-022; SYM-024 | I21: =COUNTIF($A$6:$A$149,A21) -> 1
A22: LVL-OWL-4 | B22: OWL | C22: 4 | D22: 4 | E22: 40 | F22: 1 | G22: 3 | H22: SYM-046; SYM-009; SYM-020; SYM-022; SYM-024 | I22: =COUNTIF($A$6:$A$149,A22) -> 1
A23: LVL-OWL-5 | B23: OWL | C23: 5 | D23: 5 | E23: 50 | F23: 1 | G23: 4 | H23: SYM-046; SYM-009; SYM-020; SYM-022; SYM-024 | I23: =COUNTIF($A$6:$A$149,A23) -> 1
A24: LVL-OWL-6 | B24: OWL | C24: 6 | D24: 6 | E24: 60 | F24: 1 | G24: 5 | H24: SYM-046; SYM-009; SYM-020; SYM-022; SYM-024 | I24: =COUNTIF($A$6:$A$149,A24) -> 1
A25: LVL-TEACHER-1 | B25: TEACHER | C25: 1 | D25: 0 | E25: 20 | F25: 1 | H25: SYM-053; SYM-009; SYM-020; SYM-022; SYM-024 | I25: =COUNTIF($A$6:$A$149,A25) -> 1
A26: LVL-TEACHER-2 | B26: TEACHER | C26: 2 | D26: 2 | E26: 40 | F26: 1 | G26: 1 | H26: SYM-053; SYM-009; SYM-020; SYM-022; SYM-024 | I26: =COUNTIF($A$6:$A$149,A26) -> 1
A27: LVL-TEACHER-3 | B27: TEACHER | C27: 3 | D27: 3 | E27: 60 | F27: 1 | G27: 2 | H27: SYM-053; SYM-009; SYM-020; SYM-022; SYM-024 | I27: =COUNTIF($A$6:$A$149,A27) -> 1
A28: LVL-TEACHER-4 | B28: TEACHER | C28: 4 | D28: 4 | E28: 80 | F28: 1 | G28: 3 | H28: SYM-053; SYM-009; SYM-020; SYM-022; SYM-024 | I28: =COUNTIF($A$6:$A$149,A28) -> 1
A29: LVL-TEACHER-5 | B29: TEACHER | C29: 5 | D29: 5 | E29: 100 | F29: 1 | G29: 4 | H29: SYM-053; SYM-009; SYM-020; SYM-022; SYM-024 | I29: =COUNTIF($A$6:$A$149,A29) -> 1
A30: LVL-TEACHER-6 | B30: TEACHER | C30: 6 | D30: 6 | E30: 120 | F30: 1 | G30: 5 | H30: SYM-053; SYM-009; SYM-020; SYM-022; SYM-024 | I30: =COUNTIF($A$6:$A$149,A30) -> 1
A31: LVL-ARMADILLO-1 | B31: ARMADILLO | C31: 1 | D31: 0 | E31: 50 | F31: 1 | H31: SYM-060; SYM-009; SYM-020; SYM-022; SYM-024 | I31: =COUNTIF($A$6:$A$149,A31) -> 1
A32: LVL-ARMADILLO-2 | B32: ARMADILLO | C32: 2 | D32: 2 | E32: 100 | F32: 1 | G32: 1 | H32: SYM-060; SYM-009; SYM-020; SYM-022; SYM-024 | I32: =COUNTIF($A$6:$A$149,A32) -> 1
A33: LVL-ARMADILLO-3 | B33: ARMADILLO | C33: 3 | D33: 3 | E33: 150 | F33: 1 | G33: 2 | H33: SYM-060; SYM-009; SYM-020; SYM-022; SYM-024 | I33: =COUNTIF($A$6:$A$149,A33) -> 1
A34: LVL-ARMADILLO-4 | B34: ARMADILLO | C34: 4 | D34: 4 | E34: 200 | F34: 1 | G34: 3 | H34: SYM-060; SYM-009; SYM-020; SYM-022; SYM-024 | I34: =COUNTIF($A$6:$A$149,A34) -> 1
A35: LVL-ARMADILLO-5 | B35: ARMADILLO | C35: 5 | D35: 5 | E35: 250 | F35: 1 | G35: 4 | H35: SYM-060; SYM-009; SYM-020; SYM-022; SYM-024 | I35: =COUNTIF($A$6:$A$149,A35) -> 1
A36: LVL-ARMADILLO-6 | B36: ARMADILLO | C36: 6 | D36: 6 | E36: 300 | F36: 1 | G36: 5 | H36: SYM-060; SYM-009; SYM-020; SYM-022; SYM-024 | I36: =COUNTIF($A$6:$A$149,A36) -> 1
A37: LVL-DRAGON-1 | B37: DRAGON | C37: 1 | D37: 0 | E37: 30 | F37: 1 | H37: SYM-067; SYM-009; SYM-020; SYM-022; SYM-024 | I37: =COUNTIF($A$6:$A$149,A37) -> 1
A38: LVL-DRAGON-2 | B38: DRAGON | C38: 2 | D38: 2 | E38: 60 | F38: 1 | G38: 1 | H38: SYM-067; SYM-009; SYM-020; SYM-022; SYM-024 | I38: =COUNTIF($A$6:$A$149,A38) -> 1
A39: LVL-DRAGON-3 | B39: DRAGON | C39: 3 | D39: 3 | E39: 90 | F39: 1 | G39: 2 | H39: SYM-067; SYM-009; SYM-020; SYM-022; SYM-024 | I39: =COUNTIF($A$6:$A$149,A39) -> 1
A40: LVL-DRAGON-4 | B40: DRAGON | C40: 4 | D40: 4 | E40: 120 | F40: 1 | G40: 3 | H40: SYM-067; SYM-009; SYM-020; SYM-022; SYM-024 | I40: =COUNTIF($A$6:$A$149,A40) -> 1
A41: LVL-DRAGON-5 | B41: DRAGON | C41: 5 | D41: 5 | E41: 150 | F41: 1 | G41: 4 | H41: SYM-067; SYM-009; SYM-020; SYM-022; SYM-024 | I41: =COUNTIF($A$6:$A$149,A41) -> 1
A42: LVL-DRAGON-6 | B42: DRAGON | C42: 6 | D42: 6 | E42: 180 | F42: 1 | G42: 5 | H42: SYM-067; SYM-009; SYM-020; SYM-022; SYM-024 | I42: =COUNTIF($A$6:$A$149,A42) -> 1
A43: LVL-TROGR-1 | B43: TROGR | C43: 1 | D43: 0 | E43: 1000 | F43: 1 | H43: SYM-074; SYM-009; SYM-020; SYM-022; SYM-024 | I43: =COUNTIF($A$6:$A$149,A43) -> 1
A44: LVL-TROGR-2 | B44: TROGR | C44: 2 | D44: 2 | E44: 2000 | F44: 1 | G44: 1 | H44: SYM-074; SYM-009; SYM-020; SYM-022; SYM-024 | I44: =COUNTIF($A$6:$A$149,A44) -> 1
A45: LVL-TROGR-3 | B45: TROGR | C45: 3 | D45: 3 | E45: 3000 | F45: 1 | G45: 2 | H45: SYM-074; SYM-009; SYM-020; SYM-022; SYM-024 | I45: =COUNTIF($A$6:$A$149,A45) -> 1
A46: LVL-TROGR-4 | B46: TROGR | C46: 4 | D46: 4 | E46: 4000 | F46: 1 | G46: 3 | H46: SYM-074; SYM-009; SYM-020; SYM-022; SYM-024 | I46: =COUNTIF($A$6:$A$149,A46) -> 1
A47: LVL-TROGR-5 | B47: TROGR | C47: 5 | D47: 5 | E47: 5000 | F47: 1 | G47: 4 | H47: SYM-074; SYM-009; SYM-020; SYM-022; SYM-024 | I47: =COUNTIF($A$6:$A$149,A47) -> 1
A48: LVL-TROGR-6 | B48: TROGR | C48: 6 | D48: 6 | E48: 6000 | F48: 2 | G48: 5 | H48: SYM-074; SYM-009; SYM-020; SYM-022; SYM-024 | I48: =COUNTIF($A$6:$A$149,A48) -> 1
A49: LVL-KEEPER-1 | B49: KEEPER | C49: 1 | D49: 0 | E49: 100 | F49: 1 | H49: SYM-083; SYM-009; SYM-020; SYM-022; SYM-024 | I49: =COUNTIF($A$6:$A$149,A49) -> 1
A50: LVL-KEEPER-2 | B50: KEEPER | C50: 2 | D50: 2 | E50: 200 | F50: 2 | G50: 1 | H50: SYM-083; SYM-009; SYM-020; SYM-022; SYM-024 | I50: =COUNTIF($A$6:$A$149,A50) -> 1
A51: LVL-KEEPER-3 | B51: KEEPER | C51: 3 | D51: 3 | E51: 300 | F51: 2 | G51: 2 | H51: SYM-083; SYM-009; SYM-020; SYM-022; SYM-024 | I51: =COUNTIF($A$6:$A$149,A51) -> 1
A52: LVL-KEEPER-4 | B52: KEEPER | C52: 4 | D52: 4 | E52: 400 | F52: 2 | G52: 3 | H52: SYM-083; SYM-009; SYM-020; SYM-022; SYM-024 | I52: =COUNTIF($A$6:$A$149,A52) -> 1
A53: LVL-KEEPER-5 | B53: KEEPER | C53: 5 | D53: 5 | E53: 500 | F53: 2 | G53: 4 | H53: SYM-083; SYM-009; SYM-020; SYM-022; SYM-024 | I53: =COUNTIF($A$6:$A$149,A53) -> 1
A54: LVL-KEEPER-6 | B54: KEEPER | C54: 6 | D54: 6 | E54: 600 | F54: 1 | G54: 5 | H54: SYM-083; SYM-009; SYM-020; SYM-022; SYM-024 | I54: =COUNTIF($A$6:$A$149,A54) -> 1
A55: LVL-ADVISER-1 | B55: ADVISER | C55: 1 | D55: 0 | E55: 20 | F55: 1 | H55: SYM-095; SYM-009; SYM-020; SYM-022; SYM-024 | I55: =COUNTIF($A$6:$A$149,A55) -> 1
A56: LVL-ADVISER-2 | B56: ADVISER | C56: 2 | D56: 2 | E56: 40 | F56: 1 | G56: 1 | H56: SYM-095; SYM-009; SYM-020; SYM-022; SYM-024 | I56: =COUNTIF($A$6:$A$149,A56) -> 1
A57: LVL-ADVISER-3 | B57: ADVISER | C57: 3 | D57: 3 | E57: 60 | F57: 1 | G57: 2 | H57: SYM-095; SYM-009; SYM-020; SYM-022; SYM-024 | I57: =COUNTIF($A$6:$A$149,A57) -> 1
A58: LVL-ADVISER-4 | B58: ADVISER | C58: 4 | D58: 4 | E58: 80 | F58: 1 | G58: 3 | H58: SYM-095; SYM-009; SYM-020; SYM-022; SYM-024 | I58: =COUNTIF($A$6:$A$149,A58) -> 1
A59: LVL-ADVISER-5 | B59: ADVISER | C59: 5 | D59: 5 | E59: 100 | F59: 1 | G59: 4 | H59: SYM-095; SYM-009; SYM-020; SYM-022; SYM-024 | I59: =COUNTIF($A$6:$A$149,A59) -> 1
A60: LVL-ADVISER-6 | B60: ADVISER | C60: 6 | D60: 6 | E60: 120 | F60: 1 | G60: 5 | H60: SYM-095; SYM-009; SYM-020; SYM-022; SYM-024 | I60: =COUNTIF($A$6:$A$149,A60) -> 1
A61: LVL-TICK-1 | B61: TICK | C61: 1 | D61: 0 | E61: 50 | F61: 1 | H61: SYM-102; SYM-009; SYM-020; SYM-022; SYM-024 | I61: =COUNTIF($A$6:$A$149,A61) -> 1
A62: LVL-TICK-2 | B62: TICK | C62: 2 | D62: 2 | E62: 100 | F62: 1 | G62: 1 | H62: SYM-102; SYM-009; SYM-020; SYM-022; SYM-024 | I62: =COUNTIF($A$6:$A$149,A62) -> 1
A63: LVL-TICK-3 | B63: TICK | C63: 3 | D63: 3 | E63: 150 | F63: 1 | G63: 2 | H63: SYM-102; SYM-009; SYM-020; SYM-022; SYM-024 | I63: =COUNTIF($A$6:$A$149,A63) -> 1
A64: LVL-TICK-4 | B64: TICK | C64: 4 | D64: 4 | E64: 200 | F64: 1 | G64: 3 | H64: SYM-102; SYM-009; SYM-020; SYM-022; SYM-024 | I64: =COUNTIF($A$6:$A$149,A64) -> 1
A65: LVL-TICK-5 | B65: TICK | C65: 5 | D65: 5 | E65: 250 | F65: 1 | G65: 4 | H65: SYM-102; SYM-009; SYM-020; SYM-022; SYM-024 | I65: =COUNTIF($A$6:$A$149,A65) -> 1
A66: LVL-TICK-6 | B66: TICK | C66: 6 | D66: 6 | E66: 300 | F66: 1 | G66: 5 | H66: SYM-102; SYM-009; SYM-020; SYM-022; SYM-024 | I66: =COUNTIF($A$6:$A$149,A66) -> 1
A67: LVL-CRICKET-1 | B67: CRICKET | C67: 1 | D67: 0 | E67: 50 | F67: 1 | H67: SYM-109; SYM-009; SYM-020; SYM-022; SYM-024 | I67: =COUNTIF($A$6:$A$149,A67) -> 1
A68: LVL-CRICKET-2 | B68: CRICKET | C68: 2 | D68: 2 | E68: 100 | F68: 1 | G68: 1 | H68: SYM-109; SYM-009; SYM-020; SYM-022; SYM-024 | I68: =COUNTIF($A$6:$A$149,A68) -> 1
A69: LVL-CRICKET-3 | B69: CRICKET | C69: 3 | D69: 3 | E69: 150 | F69: 1 | G69: 2 | H69: SYM-109; SYM-009; SYM-020; SYM-022; SYM-024 | I69: =COUNTIF($A$6:$A$149,A69) -> 1
A70: LVL-CRICKET-4 | B70: CRICKET | C70: 4 | D70: 4 | E70: 200 | F70: 1 | G70: 3 | H70: SYM-109; SYM-009; SYM-020; SYM-022; SYM-024 | I70: =COUNTIF($A$6:$A$149,A70) -> 1
A71: LVL-CRICKET-5 | B71: CRICKET | C71: 5 | D71: 5 | E71: 250 | F71: 1 | G71: 4 | H71: SYM-109; SYM-009; SYM-020; SYM-022; SYM-024 | I71: =COUNTIF($A$6:$A$149,A71) -> 1
A72: LVL-CRICKET-6 | B72: CRICKET | C72: 6 | D72: 6 | E72: 300 | F72: 1 | G72: 5 | H72: SYM-109; SYM-009; SYM-020; SYM-022; SYM-024 | I72: =COUNTIF($A$6:$A$149,A72) -> 1
A73: LVL-SPIDER-1 | B73: SPIDER | C73: 1 | D73: 0 | E73: 50 | F73: 1 | H73: SYM-116; SYM-009; SYM-020; SYM-022; SYM-024 | I73: =COUNTIF($A$6:$A$149,A73) -> 1
A74: LVL-SPIDER-2 | B74: SPIDER | C74: 2 | D74: 2 | E74: 100 | F74: 1 | G74: 1 | H74: SYM-116; SYM-009; SYM-020; SYM-022; SYM-024 | I74: =COUNTIF($A$6:$A$149,A74) -> 1
A75: LVL-SPIDER-3 | B75: SPIDER | C75: 3 | D75: 3 | E75: 150 | F75: 1 | G75: 2 | H75: SYM-116; SYM-009; SYM-020; SYM-022; SYM-024 | I75: =COUNTIF($A$6:$A$149,A75) -> 1
A76: LVL-SPIDER-4 | B76: SPIDER | C76: 4 | D76: 4 | E76: 200 | F76: 1 | G76: 3 | H76: SYM-116; SYM-009; SYM-020; SYM-022; SYM-024 | I76: =COUNTIF($A$6:$A$149,A76) -> 1
A77: LVL-SPIDER-5 | B77: SPIDER | C77: 5 | D77: 5 | E77: 250 | F77: 1 | G77: 4 | H77: SYM-116; SYM-009; SYM-020; SYM-022; SYM-024 | I77: =COUNTIF($A$6:$A$149,A77) -> 1
A78: LVL-SPIDER-6 | B78: SPIDER | C78: 6 | D78: 6 | E78: 300 | F78: 1 | G78: 5 | H78: SYM-116; SYM-009; SYM-020; SYM-022; SYM-024 | I78: =COUNTIF($A$6:$A$149,A78) -> 1
A79: LVL-CHAMELEON-1 | B79: CHAMELEON | C79: 1 | D79: 0 | E79: 60 | F79: 1 | H79: SYM-123; SYM-009; SYM-020; SYM-022; SYM-024 | I79: =COUNTIF($A$6:$A$149,A79) -> 1
A80: LVL-CHAMELEON-2 | B80: CHAMELEON | C80: 2 | D80: 2 | E80: 120 | F80: 1 | G80: 1 | H80: SYM-123; SYM-009; SYM-020; SYM-022; SYM-024 | I80: =COUNTIF($A$6:$A$149,A80) -> 1
A81: LVL-CHAMELEON-3 | B81: CHAMELEON | C81: 3 | D81: 3 | E81: 180 | F81: 1 | G81: 2 | H81: SYM-123; SYM-009; SYM-020; SYM-022; SYM-024 | I81: =COUNTIF($A$6:$A$149,A81) -> 1
A82: LVL-CHAMELEON-4 | B82: CHAMELEON | C82: 4 | D82: 4 | E82: 240 | F82: 1 | G82: 3 | H82: SYM-123; SYM-009; SYM-020; SYM-022; SYM-024 | I82: =COUNTIF($A$6:$A$149,A82) -> 1
A83: LVL-CHAMELEON-5 | B83: CHAMELEON | C83: 5 | D83: 5 | E83: 300 | F83: 1 | G83: 4 | H83: SYM-123; SYM-009; SYM-020; SYM-022; SYM-024 | I83: =COUNTIF($A$6:$A$149,A83) -> 1
A84: LVL-CHAMELEON-6 | B84: CHAMELEON | C84: 6 | D84: 6 | E84: 360 | F84: 1 | G84: 5 | H84: SYM-123; SYM-009; SYM-020; SYM-022; SYM-024 | I84: =COUNTIF($A$6:$A$149,A84) -> 1
A85: LVL-PENGUIN-1 | B85: PENGUIN | C85: 1 | D85: 0 | E85: 20 | F85: 1 | H85: SYM-130; SYM-009; SYM-020; SYM-022; SYM-024 | I85: =COUNTIF($A$6:$A$149,A85) -> 1
A86: LVL-PENGUIN-2 | B86: PENGUIN | C86: 2 | D86: 2 | E86: 40 | F86: 1 | G86: 1 | H86: SYM-130; SYM-009; SYM-020; SYM-022; SYM-024 | I86: =COUNTIF($A$6:$A$149,A86) -> 1
A87: LVL-PENGUIN-3 | B87: PENGUIN | C87: 3 | D87: 3 | E87: 60 | F87: 1 | G87: 2 | H87: SYM-130; SYM-009; SYM-020; SYM-022; SYM-024 | I87: =COUNTIF($A$6:$A$149,A87) -> 1
A88: LVL-PENGUIN-4 | B88: PENGUIN | C88: 4 | D88: 4 | E88: 80 | F88: 1 | G88: 3 | H88: SYM-130; SYM-009; SYM-020; SYM-022; SYM-024 | I88: =COUNTIF($A$6:$A$149,A88) -> 1
A89: LVL-PENGUIN-5 | B89: PENGUIN | C89: 5 | D89: 5 | E89: 100 | F89: 1 | G89: 4 | H89: SYM-130; SYM-009; SYM-020; SYM-022; SYM-024 | I89: =COUNTIF($A$6:$A$149,A89) -> 1
A90: LVL-PENGUIN-6 | B90: PENGUIN | C90: 6 | D90: 6 | E90: 120 | F90: 1 | G90: 5 | H90: SYM-130; SYM-009; SYM-020; SYM-022; SYM-024 | I90: =COUNTIF($A$6:$A$149,A90) -> 1
A91: LVL-PENGUIN-7 | B91: PENGUIN | C91: 7 | D91: 7 | E91: 140 | F91: 1 | G91: 6 | H91: SYM-130; SYM-009; SYM-020; SYM-022; SYM-024 | I91: =COUNTIF($A$6:$A$149,A91) -> 1
A92: LVL-EEL-1 | B92: EEL | C92: 1 | D92: 0 | E92: 60 | F92: 1 | H92: SYM-136; SYM-009; SYM-020; SYM-022; SYM-024 | I92: =COUNTIF($A$6:$A$149,A92) -> 1
A93: LVL-EEL-2 | B93: EEL | C93: 2 | D93: 2 | E93: 120 | F93: 1 | G93: 1 | H93: SYM-136; SYM-009; SYM-020; SYM-022; SYM-024 | I93: =COUNTIF($A$6:$A$149,A93) -> 1
A94: LVL-EEL-3 | B94: EEL | C94: 3 | D94: 3 | E94: 180 | F94: 1 | G94: 2 | H94: SYM-136; SYM-009; SYM-020; SYM-022; SYM-024 | I94: =COUNTIF($A$6:$A$149,A94) -> 1
A95: LVL-EEL-4 | B95: EEL | C95: 4 | D95: 4 | E95: 240 | F95: 1 | G95: 3 | H95: SYM-136; SYM-009; SYM-020; SYM-022; SYM-024 | I95: =COUNTIF($A$6:$A$149,A95) -> 1
A96: LVL-EEL-5 | B96: EEL | C96: 5 | D96: 5 | E96: 300 | F96: 1 | G96: 4 | H96: SYM-136; SYM-009; SYM-020; SYM-022; SYM-024 | I96: =COUNTIF($A$6:$A$149,A96) -> 1
A97: LVL-EEL-6 | B97: EEL | C97: 6 | D97: 6 | E97: 360 | F97: 1 | G97: 5 | H97: SYM-136; SYM-009; SYM-020; SYM-022; SYM-024 | I97: =COUNTIF($A$6:$A$149,A97) -> 1
A98: LVL-TOAD-1 | B98: TOAD | C98: 1 | D98: 0 | E98: 40 | F98: 1 | H98: SYM-143; SYM-009; SYM-020; SYM-022; SYM-024 | I98: =COUNTIF($A$6:$A$149,A98) -> 1
A99: LVL-TOAD-2 | B99: TOAD | C99: 2 | D99: 2 | E99: 80 | F99: 1 | G99: 1 | H99: SYM-143; SYM-009; SYM-020; SYM-022; SYM-024 | I99: =COUNTIF($A$6:$A$149,A99) -> 1
A100: LVL-TOAD-3 | B100: TOAD | C100: 3 | D100: 3 | E100: 120 | F100: 1 | G100: 2 | H100: SYM-143; SYM-009; SYM-020; SYM-022; SYM-024 | I100: =COUNTIF($A$6:$A$149,A100) -> 1
A101: LVL-TOAD-4 | B101: TOAD | C101: 4 | D101: 4 | E101: 160 | F101: 1 | G101: 3 | H101: SYM-143; SYM-009; SYM-020; SYM-022; SYM-024 | I101: =COUNTIF($A$6:$A$149,A101) -> 1
A102: LVL-TOAD-5 | B102: TOAD | C102: 5 | D102: 5 | E102: 200 | F102: 1 | G102: 4 | H102: SYM-143; SYM-009; SYM-020; SYM-022; SYM-024 | I102: =COUNTIF($A$6:$A$149,A102) -> 1
...

Sheet 09_Узлы_развития
A1: Узлы и ветви развития
A2: Полная топология из 182 узлов. Для 15 неавтоматизируемых узлов сохранены только имя, уровень, родители и ограничения — без исполняемого поведения.
A5: NodeRef | B5: SpeciesKey | C5: Название | D5: L | E5: BranchCode | F5: NodeKind | G5: ParentNodeRef | H5: ParentMode | I5: ChoiceGroupID | J5: AbilityID | K5: AutomationStatus | L5: SelectionConstraint | M5: Rule IDs | N5: Source Question IDs | O5: ID unique
A6: SYM-027 | B6: WEAVER | C6: Регенерация | D6: 1 | F6: AUTOMATED_ABILITY_NODE | H6: ALL | J6: SYM-027 | K6: AUTOMATED_ACCEPTED | L6: ROOT | M6: SYM-027 | O6: =COUNTIF($A$6:$A$187,A6) -> 1
A7: SYM-028 | B7: WEAVER | C7: Замена органа | D7: 2 | E7: SELF_REGENERATION | F7: AUTOMATED_ABILITY_NODE | G7: SYM-027 | H7: ALL | I7: WEAVER_L2_XOR | J7: SYM-028 | K7: AUTOMATED_ACCEPTED | L7: ALL(SYM-027); XOR:WEAVER_L2_XOR; BRANCH:SELF_REGENERATION | M7: SYM-028 | N7: Q-SYM-005; Q-SYM-007; Q-SYM-008 | O7: =COUNTIF($A$6:$A$187,A7) -> 1
A8: SYM-029 | B8: WEAVER | C8: Внешняя регенерация | D8: 2 | E8: EXTERNAL_REGENERATION | F8: AUTOMATED_ABILITY_NODE | G8: SYM-027 | H8: ALL | I8: WEAVER_L2_XOR | J8: SYM-029 | K8: AUTOMATED_ACCEPTED | L8: ALL(SYM-027); XOR:WEAVER_L2_XOR; BRANCH:EXTERNAL_REGENERATION | M8: SYM-029 | O8: =COUNTIF($A$6:$A$187,A8) -> 1
A9: SYM-030 | B9: WEAVER | C9: Дублирование органов | D9: 3 | E9: SELF_REGENERATION | F9: AUTOMATED_ABILITY_NODE | G9: SYM-028 | H9: ALL | J9: SYM-030 | K9: AUTOMATED_ACCEPTED | L9: ALL(SYM-028); BRANCH:SELF_REGENERATION | M9: SYM-030 | N9: Q-SYM-005; Q-SYM-009 | O9: =COUNTIF($A$6:$A$187,A9) -> 1
A10: SYM-032 | B10: WEAVER | C10: Анаболический форсаж | D10: 4 | E10: SELF_REGENERATION | F10: AUTOMATED_ABILITY_NODE | G10: SYM-030 | H10: ALL | J10: SYM-032 | K10: AUTOMATED_ACCEPTED | L10: ALL(SYM-030); BRANCH:SELF_REGENERATION | M10: SYM-032 | N10: Q-SYM-005; Q-SYM-011 | O10: =COUNTIF($A$6:$A$187,A10) -> 1
A11: SYM-034 | B11: WEAVER | C11: Абсолютная регенерация | D11: 5 | E11: SELF_REGENERATION | F11: AUTOMATED_ABILITY_NODE | G11: SYM-032 | H11: ALL | J11: SYM-034 | K11: AUTOMATED_ACCEPTED | L11: ALL(SYM-032); BRANCH:SELF_REGENERATION | M11: SYM-034 | N11: Q-SYM-005; Q-SYM-013; Q-SYM-014 | O11: =COUNTIF($A$6:$A$187,A11) -> 1
A12: SYM-031 | B12: WEAVER | C12: Выстрел регенерона | D12: 3 | E12: EXTERNAL_REGENERATION | F12: AUTOMATED_ABILITY_NODE | G12: SYM-029 | H12: ALL | J12: SYM-031 | K12: AUTOMATED_ACCEPTED | L12: ALL(SYM-029); BRANCH:EXTERNAL_REGENERATION | M12: SYM-031 | N12: Q-SYM-010 | O12: =COUNTIF($A$6:$A$187,A12) -> 1
A13: SYM-033 | B13: WEAVER | C13: Адреналиновая реанимация | D13: 4 | E13: EXTERNAL_REGENERATION | F13: AUTOMATED_ABILITY_NODE | G13: SYM-031 | H13: ALL | J13: SYM-033 | K13: AUTOMATED_ACCEPTED | L13: ALL(SYM-031); BRANCH:EXTERNAL_REGENERATION | M13: SYM-033 | N13: Q-SYM-010; Q-SYM-012 | O13: =COUNTIF($A$6:$A$187,A13) -> 1
A14: SYM-035 | B14: WEAVER | C14: Абсолютная реанимация | D14: 5 | E14: EXTERNAL_REGENERATION | F14: AUTOMATED_ABILITY_NODE | G14: SYM-033 | H14: ALL | J14: SYM-035 | K14: AUTOMATED_ACCEPTED | L14: ALL(SYM-033); BRANCH:EXTERNAL_REGENERATION | M14: SYM-035 | N14: Q-SYM-015 | O14: =COUNTIF($A$6:$A$187,A14) -> 1
A15: SYM-036 | B15: WEAVER | C15: Облако регенерона | D15: 6 | F15: AUTOMATED_ABILITY_NODE | G15: SYM-034; SYM-035 | H15: ANY | J15: SYM-036 | K15: AUTOMATED_ACCEPTED | L15: ANY(SYM-034,SYM-035) | M15: SYM-036 | O15: =COUNTIF($A$6:$A$187,A15) -> 1
A16: SYM-039 | B16: TAIPAN | C16: Смертельный яд | D16: 1 | F16: AUTOMATED_ABILITY_NODE | H16: ALL | J16: SYM-039 | K16: AUTOMATED_ACCEPTED | L16: ROOT | M16: SYM-039 | N16: Q-SYM-005; Q-SYM-017; Q-SYM-076; Q-APP-002 | O16: =COUNTIF($A$6:$A$187,A16) -> 1
A17: SYM-040 | B17: TAIPAN | C17: Проницаемая кожа | D17: 2 | F17: AUTOMATED_ABILITY_NODE | G17: SYM-039 | H17: ALL | J17: SYM-040 | K17: AUTOMATED_ACCEPTED | L17: ALL(SYM-039) | M17: SYM-040 | N17: Q-SYM-018 | O17: =COUNTIF($A$6:$A$187,A17) -> 1
A18: SYM-041 | B18: TAIPAN | C18: Плевок ядом | D18: 3 | F18: AUTOMATED_ABILITY_NODE | G18: SYM-040 | H18: ALL | J18: SYM-041 | K18: AUTOMATED_ACCEPTED | L18: ALL(SYM-040) | M18: SYM-041 | N18: Q-SYM-010; Q-SYM-075 | O18: =COUNTIF($A$6:$A$187,A18) -> 1
A19: SYM-042 | B19: TAIPAN | C19: Ослабляющий яд | D19: 4 | F19: AUTOMATED_ABILITY_NODE | G19: SYM-041 | H19: ALL | J19: SYM-042 | K19: AUTOMATED_ACCEPTED | L19: ALL(SYM-041) | M19: SYM-042 | N19: Q-SYM-005; Q-SYM-017; Q-SYM-019; Q-SYM-076; Q-APP-002 | O19: =COUNTIF($A$6:$A$187,A19) -> 1
A20: SYM-043 | B20: TAIPAN | C20: Ядовитый шип | D20: 5 | F20: AUTOMATED_ABILITY_NODE | G20: SYM-042 | H20: ALL | J20: SYM-043 | K20: AUTOMATED_ACCEPTED | L20: ALL(SYM-042) | M20: SYM-043 | N20: Q-SYM-010 | O20: =COUNTIF($A$6:$A$187,A20) -> 1
A21: SYM-044 | B21: TAIPAN | C21: Кумулятивный шип | D21: 6 | F21: AUTOMATED_ABILITY_NODE | G21: SYM-043 | H21: ALL | J21: SYM-044 | K21: AUTOMATED_ACCEPTED | L21: ALL(SYM-043) | M21: SYM-044 | N21: Q-SYM-010 | O21: =COUNTIF($A$6:$A$187,A21) -> 1
A22: SYM-045 | B22: TAIPAN | C22: Парализующий яд | D22: 7 | F22: AUTOMATED_ABILITY_NODE | G22: SYM-044 | H22: ALL | J22: SYM-045 | K22: AUTOMATED_ACCEPTED | L22: ALL(SYM-044) | M22: SYM-045 | N22: Q-SYM-005; Q-SYM-017; Q-SYM-020; Q-SYM-076; Q-APP-002 | O22: =COUNTIF($A$6:$A$187,A22) -> 1
A23: SYM-047 | B23: OWL | C23: Безупречное зрение | D23: 1 | F23: AUTOMATED_ABILITY_NODE | H23: ALL | J23: SYM-047 | K23: AUTOMATED_ACCEPTED | L23: ROOT | M23: SYM-047 | N23: Q-SYM-021 | O23: =COUNTIF($A$6:$A$187,A23) -> 1
A24: SYM-048 | B24: OWL | C24: Абсолютное ночное зрение | D24: 2 | F24: AUTOMATED_ABILITY_NODE | G24: SYM-047 | H24: ALL | J24: SYM-048 | K24: AUTOMATED_ACCEPTED | L24: ALL(SYM-047) | M24: SYM-048 | O24: =COUNTIF($A$6:$A$187,A24) -> 1
A25: SYM-049 | B25: OWL | C25: Абсолютное обоняние | D25: 3 | F25: AUTOMATED_ABILITY_NODE | G25: SYM-048 | H25: ALL | J25: SYM-049 | K25: AUTOMATED_ACCEPTED | L25: ALL(SYM-048) | M25: SYM-049 | O25: =COUNTIF($A$6:$A$187,A25) -> 1
A26: SYM-050 | B26: OWL | C26: Абсолютный слух | D26: 4 | F26: AUTOMATED_ABILITY_NODE | G26: SYM-049 | H26: ALL | J26: SYM-050 | K26: AUTOMATED_ACCEPTED | L26: ALL(SYM-049) | M26: SYM-050 | O26: =COUNTIF($A$6:$A$187,A26) -> 1
A27: SYM-051 | B27: OWL | C27: Звуковая картина | D27: 5 | F27: AUTOMATED_ABILITY_NODE | G27: SYM-050 | H27: ALL | J27: SYM-051 | K27: AUTOMATED_ACCEPTED | L27: ALL(SYM-050) | M27: SYM-051 | N27: Q-SYM-022 | O27: =COUNTIF($A$6:$A$187,A27) -> 1
A28: SYM-052 | B28: OWL | C28: Восприятие хищника | D28: 6 | F28: AUTOMATED_ABILITY_NODE | G28: SYM-051 | H28: ALL | J28: SYM-052 | K28: AUTOMATED_ACCEPTED | L28: ALL(SYM-051) | M28: SYM-052 | O28: =COUNTIF($A$6:$A$187,A28) -> 1
A29: SYM-054 | B29: TEACHER | C29: Развивайся, ученик | D29: 1 | F29: AUTOMATED_ABILITY_NODE | H29: ALL | J29: SYM-054 | K29: AUTOMATED_ACCEPTED | L29: ROOT | M29: SYM-054 | O29: =COUNTIF($A$6:$A$187,A29) -> 1
A30: SYM-055 | B30: TEACHER | C30: Век живи — век учись | D30: 2 | F30: AUTOMATED_ABILITY_NODE | G30: SYM-054 | H30: ALL | J30: SYM-055 | K30: AUTOMATED_ACCEPTED | L30: ALL(SYM-054) | M30: SYM-055 | N30: Q-SYM-085 | O30: =COUNTIF($A$6:$A$187,A30) -> 1
A31: SYM-056 | B31: TEACHER | C31: Практикуйтесь, ученики | D31: 3 | F31: AUTOMATED_ABILITY_NODE | G31: SYM-055 | H31: ALL | J31: SYM-056 | K31: AUTOMATED_ACCEPTED | L31: ALL(SYM-055) | M31: SYM-056 | O31: =COUNTIF($A$6:$A$187,A31) -> 1
A32: SYM-057 | B32: TEACHER | C32: Свети, ученик | D32: 4 | F32: AUTOMATED_ABILITY_NODE | G32: SYM-056 | H32: ALL | J32: SYM-057 | K32: AUTOMATED_ACCEPTED | L32: ALL(SYM-056) | M32: SYM-057 | N32: Q-SYM-023; Q-SYM-024 | O32: =COUNTIF($A$6:$A$187,A32) -> 1
A33: SYM-058 | B33: TEACHER | C33: Берегись невежд, ученик | D33: 5 | F33: AUTOMATED_ABILITY_NODE | G33: SYM-057 | H33: ALL | J33: SYM-058 | K33: AUTOMATED_ACCEPTED | L33: ALL(SYM-057) | M33: SYM-058 | O33: =COUNTIF($A$6:$A$187,A33) -> 1
A34: SYM-059 | B34: TEACHER | C34: Внимай, ученик | D34: 6 | F34: AUTOMATED_ABILITY_NODE | G34: SYM-058 | H34: ALL | J34: SYM-059 | K34: AUTOMATED_ACCEPTED | L34: ALL(SYM-058) | M34: SYM-059 | N34: Q-SYM-024; Q-SYM-025 | O34: =COUNTIF($A$6:$A$187,A34) -> 1
A35: SYM-061 | B35: ARMADILLO | C35: Подкожный панцирь | D35: 1 | F35: AUTOMATED_ABILITY_NODE | H35: ALL | J35: SYM-061 | K35: AUTOMATED_ACCEPTED | L35: ROOT | M35: SYM-061 | O35: =COUNTIF($A$6:$A$187,A35) -> 1
A36: SYM-062 | B36: ARMADILLO | C36: Здоров как буйвол | D36: 2 | F36: AUTOMATED_ABILITY_NODE | G36: SYM-061 | H36: ALL | J36: SYM-062 | K36: AUTOMATED_ACCEPTED | L36: ALL(SYM-061) | M36: SYM-062 | O36: =COUNTIF($A$6:$A$187,A36) -> 1
A37: SYM-063 | B37: ARMADILLO | C37: Не вырубишь! | D37: 3 | F37: AUTOMATED_ABILITY_NODE | G37: SYM-062 | H37: ALL | J37: SYM-063 | K37: AUTOMATED_ACCEPTED | L37: ALL(SYM-062) | M37: SYM-063 | O37: =COUNTIF($A$6:$A$187,A37) -> 1
A38: SYM-064 | B38: ARMADILLO | C38: Не подчиняюсь! | D38: 4 | F38: AUTOMATED_ABILITY_NODE | G38: SYM-063 | H38: ALL | J38: SYM-064 | K38: AUTOMATED_ACCEPTED | L38: ALL(SYM-063) | M38: SYM-064 | O38: =COUNTIF($A$6:$A$187,A38) -> 1
A39: SYM-065 | B39: ARMADILLO | C39: Не сдвинешь! | D39: 5 | F39: AUTOMATED_ABILITY_NODE | G39: SYM-064 | H39: ALL | J39: SYM-065 | K39: AUTOMATED_ACCEPTED | L39: ALL(SYM-064) | M39: SYM-065 | O39: =COUNTIF($A$6:$A$187,A39) -> 1
A40: SYM-066 | B40: ARMADILLO | C40: Поднять щиты! | D40: 6 | F40: AUTOMATED_ABILITY_NODE | G40: SYM-065 | H40: ALL | J40: SYM-066 | K40: AUTOMATED_ACCEPTED | L40: ALL(SYM-065) | M40: SYM-066 | N40: Q-SYM-026 | O40: =COUNTIF($A$6:$A$187,A40) -> 1
A41: SYM-068 | B41: DRAGON | C41: Горючая слюна | D41: 1 | F41: AUTOMATED_ABILITY_NODE | H41: ALL | J41: SYM-068 | K41: AUTOMATED_ACCEPTED | L41: ROOT | M41: SYM-068 | N41: Q-SYM-027 | O41: =COUNTIF($A$6:$A$187,A41) -> 1
A42: SYM-069 | B42: DRAGON | C42: Огнеупорная глотка | D42: 2 | F42: AUTOMATED_ABILITY_NODE | G42: SYM-068 | H42: ALL | J42: SYM-069 | K42: AUTOMATED_ACCEPTED | L42: ALL(SYM-068) | M42: SYM-069 | N42: Q-SYM-028 | O42: =COUNTIF($A$6:$A$187,A42) -> 1
A43: SYM-070 | B43: DRAGON | C43: Зубы-огниво | D43: 3 | F43: AUTOMATED_ABILITY_NODE | G43: SYM-069 | H43: ALL | J43: SYM-070 | K43: AUTOMATED_ACCEPTED | L43: ALL(SYM-069) | M43: SYM-070 | O43: =COUNTIF($A$6:$A$187,A43) -> 1
A44: SYM-071 | B44: DRAGON | C44: Нагнетатель давления | D44: 4 | F44: AUTOMATED_ABILITY_NODE | G44: SYM-070 | H44: ALL | J44: SYM-071 | K44: AUTOMATED_ACCEPTED | L44: ALL(SYM-070) | M44: SYM-071 | N44: Q-SYM-005; Q-SYM-029 | O44: =COUNTIF($A$6:$A$187,A44) -> 1
A45: SYM-072 | B45: DRAGON | C45: Долгое горение | D45: 5 | F45: AUTOMATED_ABILITY_NODE | G45: SYM-071 | H45: ALL | J45: SYM-072 | K45: AUTOMATED_ACCEPTED | L45: ALL(SYM-071) | M45: SYM-072 | N45: Q-SYM-077 | O45: =COUNTIF($A$6:$A$187,A45) -> 1
A46: SYM-073 | B46: DRAGON | C46: Огненный шар | D46: 6 | F46: AUTOMATED_ABILITY_NODE | G46: SYM-072 | H46: ALL | J46: SYM-073 | K46: AUTOMATED_ACCEPTED | L46: ALL(SYM-072) | M46: SYM-073 | N46: Q-SYM-030 | O46: =COUNTIF($A$6:$A$187,A46) -> 1
A47: SYM-076 | B47: TROGR | C47: Трогровость | D47: 1 | F47: AUTOMATED_ABILITY_NODE | H47: ALL | J47: SYM-076 | K47: AUTOMATED_ACCEPTED | L47: ROOT | M47: SYM-076 | N47: Q-SYM-032 | O47: =COUNTIF($A$6:$A$187,A47) -> 1
A48: SYM-077 | B48: TROGR | C48: Трогр крушить! | D48: 2 | F48: AUTOMATED_ABILITY_NODE | G48: SYM-076 | H48: ALL | J48: SYM-077 | K48: AUTOMATED_ACCEPTED | L48: ALL(SYM-076) | M48: SYM-077 | N48: Q-SYM-033 | O48: =COUNTIF($A$6:$A$187,A48) -> 1
A49: SYM-078 | B49: TROGR | C49: WAAAGH!!! | D49: 3 | F49: AUTOMATED_ABILITY_NODE | G49: SYM-077 | H49: ALL | J49: SYM-078 | K49: AUTOMATED_ACCEPTED | L49: ALL(SYM-077) | M49: SYM-078 | N49: Q-SYM-034 | O49: =COUNTIF($A$6:$A$187,A49) -> 1
A50: SYM-079 | B50: TROGR | C50: Мой дубина — твой башка! | D50: 4 | F50: AUTOMATED_ABILITY_NODE | G50: SYM-078 | H50: ALL | J50: SYM-079 | K50: AUTOMATED_ACCEPTED | L50: ALL(SYM-078) | M50: SYM-079 | O50: =COUNTIF($A$6:$A$187,A50) -> 1
A51: SYM-080 | B51: TROGR | C51: ЫЫЫ… | D51: 5 | F51: AUTOMATED_ABILITY_NODE | G51: SYM-079 | H51: ALL | J51: SYM-080 | K51: AUTOMATED_ACCEPTED | L51: ALL(SYM-079) | M51: SYM-080 | N51: Q-SYM-035 | O51: =COUNTIF($A$6:$A$187,A51) -> 1
A52: SYM-081 | B52: TROGR | C52: Утолщённые кости | D52: 6 | E52: THICKENED_BONES | F52: AUTOMATED_ABILITY_NODE | G52: SYM-080 | H52: ALL | I52: TROGR_L6_XOR | J52: SYM-081 | K52: AUTOMATED_ACCEPTED | L52: ALL(SYM-080); XOR:TROGR_L6_XOR; BRANCH:THICKENED_BONES | M52: SYM-081 | O52: =COUNTIF($A$6:$A$187,A52) -> 1
A53: SYM-082 | B53: TROGR | C53: Гениальная тупость | D53: 6 | E53: GENIUS_STUPIDITY | F53: AUTOMATED_ABILITY_NODE | G53: SYM-080 | H53: ALL | I53: TROGR_L6_XOR | J53: SYM-082 | K53: AUTOMATED_ACCEPTED | L53: ALL(SYM-080); XOR:TROGR_L6_XOR; BRANCH:GENIUS_STUPIDITY | M53: SYM-082 | N53: Q-COMBAT-CRIT-001 | O53: =COUNTIF($A$6:$A$187,A53) -> 1
A54: SYM-084 | B54: KEEPER | C54: Резервная копия | D54: 1 | F54: AUTOMATED_ABILITY_NODE | H54: ALL | J54: SYM-084 | K54: AUTOMATED_ACCEPTED | L54: ROOT | M54: SYM-084; SYM-085 | N54: Q-SYM-036; Q-SYM-074 | O54: =COUNTIF($A$6:$A$187,A54) -> 1
A55: SYM-086 | B55: KEEPER | C55: Парализующее жало | D55: 2 | E55: COMBAT_BODY | F55: AUTOMATED_ABILITY_NODE | G55: SYM-084 | H55: ALL | J55: SYM-086 | K55: AUTOMATED_ACCEPTED | L55: ALL(SYM-084); BRANCH:COMBAT_BODY | M55: SYM-086 | O55: =COUNTIF($A$6:$A$187,A55) -> 1
A56: SYM-087 | B56: KEEPER | C56: Оценка тела | D56: 2 | E56: MIGRATION | F56: AUTOMATED_ABILITY_NODE | G56: SYM-084 | H56: ALL | J56: SYM-087 | K56: AUTOMATED_ACCEPTED | L56: ALL(SYM-084); BRANCH:MIGRATION | M56: SYM-087 | N56: Q-SYM-009 | O56: =COUNTIF($A$6:$A$187,A56) -> 1
A57: SYM-088 | B57: KEEPER | C57: Присоски и коготки | D57: 3 | E57: COMBAT_BODY | F57: AUTOMATED_ABILITY_NODE | G57: SYM-086 | H57: ALL | J57: SYM-088 | K57: AUTOMATED_ACCEPTED | L57: ALL(SYM-086); BRANCH:COMBAT_BODY | M57: SYM-088 | O57: =COUNTIF($A$6:$A$187,A57) -> 1
A58: SYM-089 | B58: KEEPER | C58: Маскировка «Хамелеон» | D58: 3 | E58: MIGRATION | F58: AUTOMATED_ABILITY_NODE | G58: SYM-087 | H58: ALL | J58: SYM-089 | K58: AUTOMATED_ACCEPTED | L58: ALL(SYM-087); BRANCH:MIGRATION | M58: SYM-089 | N58: Q-SYM-009 | O58: =COUNTIF($A$6:$A$187,A58) -> 1
A59: SYM-090 | B59: KEEPER | C59: Кромсатель | D59: 4 | E59: COMBAT_BODY | F59: AUTOMATED_ABILITY_NODE | G59: SYM-088 | H59: ALL | J59: SYM-090 | K59: AUTOMATED_ACCEPTED | L59: ALL(SYM-088); BRANCH:COMBAT_BODY | M59: SYM-090 | O59: =COUNTIF($A$6:$A$187,A59) -> 1
A60: SYM-091 | B60: KEEPER | C60: Крылья | D60: 4 | E60: MIGRATION | F60: AUTOMATED_ABILITY_NODE | G60: SYM-089 | H60: ALL | J60: SYM-091 | K60: AUTOMATED_ACCEPTED | L60: ALL(SYM-089); BRANCH:MIGRATION | M60: SYM-091 | N60: Q-QA-003; Q-SYM-037 | O60: =COUNTIF($A$6:$A$187,A60) -> 1
A61: SYM-092 | B61: KEEPER | C61: Временное убежище | D61: 5 | E61: COMBAT_BODY | F61: STRUCTURAL_NODE_ONLY | G61: SYM-090 | H61: ALL | K61: NODE_ONLY_MANUAL | L61: ALL(SYM-090); BRANCH:COMBAT_BODY; Сохраняется только как узел дерева; Windows-команда исключена Q-SYM-038. | M61: SYM-092 | N61: Q-SYM-038 | O61: =COUNTIF($A$6:$A$187,A61) -> 1
A62: SYM-093 | B62: KEEPER | C62: Попутчики | D62: 5 | E62: MIGRATION | F62: AUTOMATED_ABILITY_NODE | G62: SYM-091 | H62: ALL | J62: SYM-093 | K62: AUTOMATED_ACCEPTED | L62: ALL(SYM-091); BRANCH:MIGRATION | M62: SYM-093 | N62: Q-SYM-039 | O62: =COUNTIF($A$6:$A$187,A62) -> 1
A63: SYM-094 | B63: KEEPER | C63: Кислотная пушка | D63: 6 | F63: AUTOMATED_ABILITY_NODE | G63: SYM-092; SYM-093 | H63: ANY | J63: SYM-094 | K63: AUTOMATED_ACCEPTED | L63: ANY(SYM-092,SYM-093) | M63: SYM-094 | N63: Q-SYM-009 | O63: =COUNTIF($A$6:$A$187,A63) -> 1
A64: SYM-096 | B64: ADVISER | C64: Личность | D64: 1 | F64: AUTOMATED_ABILITY_NODE | H64: ALL | J64: SYM-096 | K64: AUTOMATED_ACCEPTED | L64: ROOT | M64: SYM-096 | N64: Q-SYM-040 | O64: =COUNTIF($A$6:$A$187,A64) -> 1
A65: SYM-097 | B65: ADVISER | C65: Я здесь самый умный | D65: 2 | F65: AUTOMATED_ABILITY_NODE | G65: SYM-096 | H65: ALL | J65: SYM-097 | K65: AUTOMATED_ACCEPTED | L65: ALL(SYM-096) | M65: SYM-097 | O65: =COUNTIF($A$6:$A$187,A65) -> 1
A66: SYM-098 | B66: ADVISER | C66: Доступ к органам чувств | D66: 3 | F66: AUTOMATED_ABILITY_NODE | G66: SYM-097 | H66: ALL | J66: SYM-098 | K66: AUTOMATED_ACCEPTED | L66: ALL(SYM-097) | M66: SYM-098 | O66: =COUNTIF($A$6:$A$187,A66) -> 1
A67: SYM-099 | B67: ADVISER | C67: Принимаю управление | D67: 4 | F67: AUTOMATED_ABILITY_NODE | G67: SYM-098 | H67: ALL | J67: SYM-099 | K67: AUTOMATED_ACCEPTED | L67: ALL(SYM-098) | M67: SYM-099 | N67: Q-SYM-041 | O67: =COUNTIF($A$6:$A$187,A67) -> 1
A68: SYM-100 | B68: ADVISER | C68: Система устойчивости | D68: 5 | F68: AUTOMATED_ABILITY_NODE | G68: SYM-099 | H68: ALL | J68: SYM-100 | K68: AUTOMATED_ACCEPTED | L68: ALL(SYM-099) | M68: SYM-100 | O68: =COUNTIF($A$6:$A$187,A68) -> 1
A69: SYM-101 | B69: ADVISER | C69: Дар мудрости | D69: 6 | F69: AUTOMATED_ABILITY_NODE | G69: SYM-100 | H69: ALL | J69: SYM-101 | K69: AUTOMATED_ACCEPTED | L69: ALL(SYM-100) | M69: SYM-101 | N69: Q-SYM-042 | O69: =COUNTIF($A$6:$A$187,A69) -> 1
A70: SYM-103 | B70: TICK | C70: Кровопийца | D70: 1 | F70: AUTOMATED_ABILITY_NODE | H70: ALL | J70: SYM-103 | K70: AUTOMATED_ACCEPTED | L70: ROOT | M70: SYM-103 | N70: Q-SYM-043 | O70: =COUNTIF($A$6:$A$187,A70) -> 1
A71: SYM-104 | B71: TICK | C71: Вкус крови | D71: 2 | F71: AUTOMATED_ABILITY_NODE | G71: SYM-103 | H71: ALL | J71: SYM-104 | K71: AUTOMATED_ACCEPTED | L71: ALL(SYM-103) | M71: SYM-104 | N71: Q-SYM-022 | O71: =COUNTIF($A$6:$A$187,A71) -> 1
A72: SYM-105 | B72: TICK | C72: Выстрел кровью | D72: 3 | F72: AUTOMATED_ABILITY_NODE | G72: SYM-104 | H72: ALL | J72: SYM-105 | K72: AUTOMATED_ACCEPTED | L72: ALL(SYM-104) | M72: SYM-105 | O72: =COUNTIF($A$6:$A$187,A72) -> 1
A73: SYM-106 | B73: TICK | C73: Выпустить когти | D73: 4 | F73: AUTOMATED_ABILITY_NODE | G73: SYM-105 | H73: ALL | J73: SYM-106 | K73: AUTOMATED_ACCEPTED | L73: ALL(SYM-105) | M73: SYM-106 | N73: Q-SYM-044 | O73: =COUNTIF($A$6:$A$187,A73) -> 1
A74: SYM-107 | B74: TICK | C74: Гарпун | D74: 5 | F74: AUTOMATED_ABILITY_NODE | G74: SYM-106 | H74: ALL | J74: SYM-107 | K74: AUTOMATED_ACCEPTED | L74: ALL(SYM-106) | M74: SYM-107 | N74: Q-SYM-045 | O74: =COUNTIF($A$6:$A$187,A74) -> 1
A75: SYM-108 | B75: TICK | C75: Я — сила | D75: 6 | F75: AUTOMATED_ABILITY_NODE | G75: SYM-107 | H75: ALL | J75: SYM-108 | K75: AUTOMATED_ACCEPTED | L75: ALL(SYM-107) | M75: SYM-108 | O75: =COUNTIF($A$6:$A$187,A75) -> 1
A76: SYM-110 | B76: CRICKET | C76: Ноги сверчка | D76: 1 | F76: AUTOMATED_ABILITY_NODE | H76: ALL | J76: SYM-110 | K76: AUTOMATED_ACCEPTED | L76: ROOT | M76: SYM-110 | O76: =COUNTIF($A$6:$A$187,A76) -> 1
A77: SYM-111 | B77: CRICKET | C77: Чувствительные усы | D77: 2 | F77: AUTOMATED_ABILITY_NODE | G77: SYM-110 | H77: ALL | J77: SYM-111 | K77: AUTOMATED_ACCEPTED | L77: ALL(SYM-110) | M77: SYM-111 | O77: =COUNTIF($A$6:$A$187,A77) -> 1
A78: SYM-112 | B78: CRICKET | C78: Заряженный прыжок | D78: 3 | F78: AUTOMATED_ABILITY_NODE | G78: SYM-111 | H78: ALL | J78: SYM-112 | K78: AUTOMATED_ACCEPTED | L78: ALL(SYM-111) | M78: SYM-112 | N78: Q-SYM-046 | O78: =COUNTIF($A$6:$A$187,A78) -> 1
A79: SYM-113 | B79: CRICKET | C79: Маскировка под растение | D79: 4 | F79: AUTOMATED_ABILITY_NODE | G79: SYM-112 | H79: ALL | J79: SYM-113 | K79: AUTOMATED_ACCEPTED | L79: ALL(SYM-112) | M79: SYM-113 | O79: =COUNTIF($A$6:$A$187,A79) -> 1
A80: SYM-114 | B80: CRICKET | C80: Крылья | D80: 5 | F80: AUTOMATED_ABILITY_NODE | G80: SYM-113 | H80: ALL | J80: SYM-114 | K80: AUTOMATED_ACCEPTED | L80: ALL(SYM-113) | M80: SYM-114 | N80: Q-SYM-047 | O80: =COUNTIF($A$6:$A$187,A80) -> 1
A81: SYM-115 | B81: CRICKET | C81: Активные пилы | D81: 6 | F81: AUTOMATED_ABILITY_NODE | G81: SYM-114 | H81: ALL | J81: SYM-115 | K81: AUTOMATED_ACCEPTED | L81: ALL(SYM-114) | M81: SYM-115 | O81: =COUNTIF($A$6:$A$187,A81) -> 1
A82: SYM-117 | B82: SPIDER | C82: Паутинные железы | D82: 1 | F82: AUTOMATED_ABILITY_NODE | H82: ALL | J82: SYM-117 | K82: AUTOMATED_ACCEPTED | L82: ROOT | M82: SYM-117 | N82: Q-SYM-048; Q-PREDEV-010; USR-2026-07-30-WEB-001 | O82: =COUNTIF($A$6:$A$187,A82) -> 1
A83: SYM-118 | B83: SPIDER | C83: Перемещение по паутине | D83: 2 | F83: AUTOMATED_ABILITY_NODE | G83: SYM-117 | H83: ALL | J83: SYM-118 | K83: AUTOMATED_ACCEPTED | L83: ALL(SYM-117) | M83: SYM-118 | O83: =COUNTIF($A$6:$A$187,A83) -> 1
A84: SYM-119 | B84: SPIDER | C84: Точка крепления | D84: 3 | F84: STRUCTURAL_NODE_ONLY | G84: SYM-118 | H84: ALL | K84: NODE_ONLY_MANUAL | L84: ALL(SYM-118); Только узел дерева; не автоматизируется Q-SYM-049. | M84: SYM-119 | N84: Q-SYM-049 | O84: =COUNTIF($A$6:$A$187,A84) -> 1
A85: SYM-120 | B85: SPIDER | C85: Выстрел паутиной | D85: 4 | F85: AUTOMATED_ABILITY_NODE | G85: SYM-119 | H85: ALL | J85: SYM-120 | K85: AUTOMATED_ACCEPTED | L85: ALL(SYM-119) | M85: SYM-120 | N85: Q-SYM-050 | O85: =COUNTIF($A$6:$A$187,A85) -> 1
A86: SYM-121 | B86: SPIDER | C86: Ловчая сеть | D86: 5 | F86: AUTOMATED_ABILITY_NODE | G86: SYM-120 | H86: ALL | J86: SYM-121 | K86: AUTOMATED_ACCEPTED | L86: ALL(SYM-120) | M86: SYM-121 | N86: Q-SYM-050 | O86: =COUNTIF($A$6:$A$187,A86) -> 1
A87: SYM-122 | B87: SPIDER | C87: Паучья ловкость | D87: 6 | F87: AUTOMATED_ABILITY_NODE | G87: SYM-121 | H87: ALL | J87: SYM-122 | K87: AUTOMATED_ACCEPTED | L87: ALL(SYM-121) | M87: SYM-122 | O87: =COUNTIF($A$6:$A$187,A87) -> 1
A88: SYM-124 | B88: CHAMELEON | C88: Статическая маскировка | D88: 1 | F88: AUTOMATED_ABILITY_NODE | H88: ALL | J88: SYM-124 | K88: AUTOMATED_ACCEPTED | L88: ROOT | M88: SYM-124 | N88: Q-SYM-051 | O88: =COUNTIF($A$6:$A$187,A88) -> 1
A89: SYM-125 | B89: CHAMELEON | C89: Атака из засады | D89: 2 | F89: AUTOMATED_ABILITY_NODE | G89: SYM-124 | H89: ALL | J89: SYM-125 | K89: AUTOMATED_ACCEPTED | L89: ALL(SYM-124) | M89: SYM-125 | N89: Q-SYM-051 | O89: =COUNTIF($A$6:$A$187,A89) -> 1
A90: SYM-126 | B90: CHAMELEON | C90: Двойной фокус внимания | D90: 3 | F90: AUTOMATED_ABILITY_NODE | G90: SYM-125 | H90: ALL | J90: SYM-126 | K90: AUTOMATED_ACCEPTED | L90: ALL(SYM-125) | M90: SYM-126 | N90: Q-SYM-021 | O90: =COUNTIF($A$6:$A$187,A90) -> 1
A91: SYM-127 | B91: CHAMELEON | C91: Динамическая маскировка | D91: 4 | F91: AUTOMATED_ABILITY_NODE | G91: SYM-126 | H91: ALL | J91: SYM-127 | K91: AUTOMATED_ACCEPTED | L91: ALL(SYM-126) | M91: SYM-127 | O91: =COUNTIF($A$6:$A$187,A91) -> 1
A92: SYM-128 | B92: CHAMELEON | C92: Сокрытие оружия | D92: 5 | F92: AUTOMATED_ABILITY_NODE | G92: SYM-127 | H92: ALL | J92: SYM-128 | K92: AUTOMATED_ACCEPTED | L92: ALL(SYM-127) | M92: SYM-128 | O92: =COUNTIF($A$6:$A$187,A92) -> 1
A93: SYM-129 | B93: CHAMELEON | C93: Внешняя фотосеть | D93: 6 | F93: AUTOMATED_ABILITY_NODE | G93: SYM-128 | H93: ALL | J93: SYM-129 | K93: AUTOMATED_ACCEPTED | L93: ALL(SYM-128) | M93: SYM-129 | N93: Q-SYM-052 | O93: =COUNTIF($A$6:$A$187,A93) -> 1
A94: SYM-131#MI_MI_MI | B94: PENGUIN | C94: Ми-ми-ми | D94: 1 | F94: AUTOMATED_ABILITY_NODE | H94: ALL | J94: SYM-131#MI_MI_MI | K94: AUTOMATED_ACCEPTED | L94: ROOT | M94: SYM-131 | N94: Q-SYM-053 | O94: =COUNTIF($A$6:$A$187,A94) -> 1
A95: SYM-131#OH_NICE | B95: PENGUIN | C95: Oh nice! | D95: 2 | F95: AUTOMATED_ABILITY_NODE | G95: SYM-131#MI_MI_MI | H95: ALL | J95: SYM-131#OH_NICE | K95: AUTOMATED_ACCEPTED | L95: ALL(SYM-131#MI_MI_MI) | M95: SYM-131 | N95: Q-SYM-053 | O95: =COUNTIF($A$6:$A$187,A95) -> 1
A96: SYM-131#BLACK_WHITE_FEAR | B96: PENGUIN | C96: Чёрно-белый страх | D96: 3 | F96: AUTOMATED_ABILITY_NODE | G96: SYM-131#OH_NICE | H96: ALL | J96: SYM-131#BLACK_WHITE_FEAR | K96: AUTOMATED_ACCEPTED | L96: ALL(SYM-131#OH_NICE) | M96: SYM-131 | N96: Q-SYM-053 | O96: =COUNTIF($A$6:$A$187,A96) -> 1
A97: SYM-132 | B97: PENGUIN | C97: Чёрно-белая ярость | D97: 4 | F97: AUTOMATED_ABILITY_NODE | G97: SYM-131#BLACK_WHITE_FEAR | H97: ALL | J97: SYM-132 | K97: AUTOMATED_ACCEPTED | L97: ALL(SYM-131#BLACK_WHITE_FEAR) | M97: SYM-132 | N97: Q-SYM-005; Q-SYM-011; Q-SYM-054 | O97: =COUNTIF($A$6:$A$187,A97) -> 1
A98: SYM-133 | B98: PENGUIN | C98: Чёрно-белый контроль | D98: 5 | F98: AUTOMATED_ABILITY_NODE | G98: SYM-132 | H98: ALL | J98: SYM-133 | K98: AUTOMATED_ACCEPTED | L98: ALL(SYM-132) | M98: SYM-133 | N98: Q-SYM-053 | O98: =COUNTIF($A$6:$A$187,A98) -> 1
A99: SYM-134 | B99: PENGUIN | C99: Чёрно-белое смещение | D99: 6 | F99: AUTOMATED_ABILITY_NODE | G99: SYM-133 | H99: ALL | J99: SYM-134 | K99: AUTOMATED_ACCEPTED | L99: ALL(SYM-133) | M99: SYM-134 | N99: Q-SYM-005 | O99: =COUNTIF($A$6:$A$187,A99) -> 1
A100: SYM-135 | B100: PENGUIN | C100: Чёрно-белое доминирование | D100: 7 | F100: AUTOMATED_ABILITY_NODE | G100: SYM-134 | H100: ALL | J100: SYM-135 | K100: AUTOMATED_ACCEPTED | L100: ALL(SYM-134) | M100: SYM-135 | N100: Q-SYM-005; Q-SYM-055 | O100: =COUNTIF($A$6:$A$187,A100) -> 1
A101: SYM-137 | B101: EEL | C101: Контактный шокер | D101: 1 | F101: AUTOMATED_ABILITY_NODE | H101: ALL | J101: SYM-137 | K101: AUTOMATED_ACCEPTED | L101: ROOT | M101: SYM-137 | N101: Q-SYM-056 | O101: =COUNTIF($A$6:$A$187,A101) -> 1
A102: SYM-138 | B102: EEL | C102: Проводник | D102: 2 | F102: AUTOMATED_ABILITY_NODE | G102: SYM-137 | H102: ALL | J102: SYM-138 | K102: AUTOMATED_ACCEPTED | L102: ALL(SYM-137) | M102: SYM-138 | O102: =COUNTIF($A$6:$A$187,A102) -> 1
...

Sheet 10_Способности
A1: Автоматизируемые способности симбионтов
A2: Только 167 способностей, принятых для исполнения приложением. Флаги Combat/Peace отделены от доступности команды игроку, чтобы пассивы и автотриггеры не становились ручными кнопками.
A5: AbilityID | B5: SpeciesKey | C5: NodeRef | D5: Название | E5: AbilityKind | F5: AutomationStatus | G5: CombatAllowed | H5: PlayerCommandCombat | I5: PeaceAllowed | J5: PlayerCommandPeace | K5: CombatBehavior | L5: PeaceBehavior | M5: Source Rule IDs | N5: Source Question IDs | O5: Priority | P5: Status | Q5: ID unique
A6: SYM-027 | B6: WEAVER | C6: SYM-027 | D6: Регенерация | E6: PLAYER_COMMAND | F6: AUTOMATED_ACCEPTED | G6: =TRUE() -> TRUE | H6: =TRUE() -> TRUE | I6: =TRUE() -> TRUE | J6: =TRUE() -> TRUE | K6: Разрешается по агрегированным карточкам canonicalBehaviorCards; в бою учитываются указанная цена действий, боевые защиты, координаты и ходы. [SYM-027] Регенерация R=1: носитель без сознания 30 минут/до конца боя. R=2–4: нет лечения. R=5–17: HP += 2R. R=18–19: восстановить 50 HP и удалить все травмы. R=20: восстановить HP полностью, удалить все травмы и косметические дефекты, снижающие C. | L6: Мирная операция/пассив разрешены явно. Для активной команды применяется Q-APP-001/002: отдельный пул боевых действий не создаётся, ОЭ и иные ресурсы списываются атомарно, немоделируемые контакт/дистанцию подтверждает мастер; боевой алгоритм карточки сохраняется в непротиворечащей части. [SYM-027] Регенерация R=1: носитель без сознания 30 минут/до конца боя. R=2–4: нет лечения. R=5–17: HP += 2R. R=18–19: восстановить 50 HP и удалить все травмы. R=20: восстановить HP полностью, удалить все травмы и косметические дефекты, снижающие C. | M6: SYM-027 | O6: 10 | P6: ACTIVE | Q6: =COUNTIF($A$6:$A$172,A6) -> 1
A7: SYM-028 | B7: WEAVER | C7: SYM-028 | D7: Замена органа | E7: HYBRID_COMMAND_AND_TRIGGER | F7: AUTOMATED_ACCEPTED | G7: =TRUE() -> TRUE | H7: =TRUE() -> TRUE | I7: =TRUE() -> TRUE | J7: =TRUE() -> TRUE | K7: Разрешается по агрегированным карточкам canonicalBehaviorCards; в бою учитываются указанная цена действий, боевые защиты, координаты и ходы. [SYM-028] Замена органа Нормативная база (действует во всей непротиворечащей части): R=1: Ткач отключён на 30 минут/4 хода. R=2: активация неуспешна. R≥3: клетки заменяют функцию органа на R/3 ходов; носитель сохраняет дееспособность в тяжёлом ранении, время до смерти ×4. При R≥15 после окончания должен быть полностью восстановлен орган и лечение тяжёлого ранения не требуется. Приоритетные авторские дельты (заменяют только прямо пересекающиеся ветви): [Q-SYM-005] Все дробные результаты округляются до ближайшего целого по математическим правилам; значение ровно 0,5 округляется вверх. Для количества ходов, минут, целей и создаваемых объектов действует минимум 1, если формула дала положительное значение; нулевой или отрицательный срок не создаёт продолжающегося эффекта. [Q-SYM-007] «Замена органа» автоматически объявляется сразу после входа носителя в тяжёлое ранение и потери сознания, если способность изучена и имеется 50 ОЭ; стоимость списывается, затем бросается чистый R20. На 1 эффект не возникает и Ткач отключается на 4 хода; на 2 эффекта нет; на 3–14 функция органа заменяется на R20/3 личных хода, носитель сохраняет дееспособность, а исходный таймер смерти один раз умножается на 4 без гарантии дожить до конца замены. На 15+ таймер устанавливается равным max(исходный таймер×4, длительность эффекта) и не обнуляется раньше; если до окончания не было новой потери HP, орган восстанавливается, тяжёлое ранение и таймер снимаются, HP=1. Сам Ткач остаётся в теле. Любая новая потеря хотя бы 1 HP во время тяжёлого ранения вызывает окончательную смерть. [Q-SYM-008] Способность немедленно и без расходования действий носителя объявляется при потере сознания от тяжёлого ранения; 50 ОЭ списываются и выполняется обычная проверка способности. Выбор органа – игровая условность, не отыгрываемая через приложение. Приложение учитывает только сам эффект: способность действовать в состоянии тяжелого ранения и при выпадении 15+ - отсутствие необходимости лечить его, чтобы не погибнуть. | L7: Мирная операция/пассив разрешены явно. Для активной команды применяется Q-APP-001/002: отдельный пул боевых действий не создаётся, ОЭ и иные ресурсы списываются атомарно, немоделируемые контакт/дистанцию подтверждает мастер; боевой алгоритм карточки сохраняется в непротиворечащей части. [SYM-028] Замена органа Нормативная база (действует во всей непротиворечащей части): R=1: Ткач отключён на 30 минут/4 хода. R=2: активация неуспешна. R≥3: клетки заменяют функцию органа на R/3 ходов; носитель сохраняет дееспособность в тяжёлом ранении, время до смерти ×4. При R≥15 после окончания должен быть полностью восстановлен орган и лечение тяжёлого ранения не требуется. Приоритетные авторские дельты (заменяют только прямо пересекающиеся ветви): [Q-SYM-005] Все дробные результаты округляются до ближайшего целого по математическим правилам; значение ровно 0,5 округляется вверх. Для количества ходов, минут, целей и создаваемых объектов действует минимум 1, если формула дала положительное значение; нулевой или отрицательный срок не создаёт продолжающегося эффекта. [Q-SYM-007] «Замена органа» автоматически объявляется сразу после входа носителя в тяжёлое ранение и потери сознания, если способность изучена и имеется 50 ОЭ; стоимость списывается, затем бросается чистый R20. На 1 эффект не возникает и Ткач отключается на 4 хода; на 2 эффекта нет; на 3–14 функция органа заменяется на R20/3 личных хода, носитель сохраняет дееспособность, а исходный таймер смерти один раз умножается на 4 без гарантии дожить до конца замены. На 15+ таймер устанавливается равным max(исходный таймер×4, длительность эффекта) и не обнуляется раньше; если до окончания не было новой потери HP, орган восстанавливается, тяжёлое ранение и таймер снимаются, HP=1. Сам Ткач остаётся в теле. Любая новая потеря хотя бы 1 HP во время тяжёлого ранения вызывает окончательную смерть. [Q-SYM-008] Способность немедленно и без расходования действий носителя объявляется при потере сознания от тяжёлого ранения; 50 ОЭ списываются и выполняется обычная проверка способности. Выбор органа – игровая условность, не отыгрываемая через приложение. Приложение учитывает только сам эффект: способность действовать в состоянии тяжелого ранения и при выпадении 15+ - отсутствие необходимости лечить его, чтобы не погибнуть. | M7: SYM-028 | N7: Q-SYM-005; Q-SYM-007; Q-SYM-008 | O7: 10 | P7: ACTIVE | Q7: =COUNTIF($A$6:$A$172,A7) -> 1
A8: SYM-029 | B8: WEAVER | C8: SYM-029 | D8: Внешняя регенерация | E8: PLAYER_COMMAND | F8: AUTOMATED_ACCEPTED | G8: =TRUE() -> TRUE | H8: =TRUE() -> TRUE | I8: =TRUE() -> TRUE | J8: =TRUE() -> TRUE | K8: Разрешается по агрегированным карточкам canonicalBehaviorCards; в бою учитываются указанная цена действий, боевые защиты, координаты и ходы. [SYM-029] Внешняя регенерация R=1: цель теряет 10 HP. R=2–4: нет эффекта. R=5–19: цель восстанавливает 2R HP. R=20: цель восстанавливает 50 HP, все травмы и косметические дефекты, снижающие C. | L8: Мирная операция/пассив разрешены явно. Для активной команды применяется Q-APP-001/002: отдельный пул боевых действий не создаётся, ОЭ и иные ресурсы списываются атомарно, немоделируемые контакт/дистанцию подтверждает мастер; боевой алгоритм карточки сохраняется в непротиворечащей части. [SYM-029] Внешняя регенерация R=1: цель теряет 10 HP. R=2–4: нет эффекта. R=5–19: цель восстанавливает 2R HP. R=20: цель восстанавливает 50 HP, все травмы и косметические дефекты, снижающие C. | M8: SYM-029 | O8: 10 | P8: ACTIVE | Q8: =COUNTIF($A$6:$A$172,A8) -> 1
A9: SYM-030 | B9: WEAVER | C9: SYM-030 | D9: Дублирование органов | E9: PLAYER_COMMAND | F9: AUTOMATED_ACCEPTED | G9: =TRUE() -> TRUE | H9: =TRUE() -> TRUE | I9: =FALSE() -> FALSE | J9: =FALSE() -> FALSE | K9: Разрешается по агрегированным карточкам canonicalBehaviorCards; в бою учитываются указанная цена действий, боевые защиты, координаты и ходы. [SYM-030] Дублирование органов Нормативная база (действует во всей непротиворечащей части): R≥2: наложить «Задвоенные органы» на R/2 ходов. Если при эффекте HP должны стать ≤0, вместо тяжёлого ранения установить HP=1 и снять эффект. R=1: дополнительно сжечь 100 ОЭ; если 100 больше оставшегося запаса, установить недееспособность Ткача до 4 часов сна. Приоритетные авторские дельты (заменяют только прямо пересекающиеся ветви): [Q-SYM-005] Все дробные результаты округляются до ближайшего целого по математическим правилам; значение ровно 0,5 округляется вверх. Для количества ходов, минут, целей и создаваемых объектов действует минимум 1, если формула дала положительное значение; нулевой или отрицательный срок не создаёт продолжающегося эффекта. [Q-SYM-009] При обязательной потере ОЭ текущий запас уменьшается не ниже 0; энергетический долг не создаётся. Дополнительное отключение наступает только там, где оно прямо указано, в частности у Ткача при неудаче «Дублирования органов». | L9: Игрок не может воспользоваться способностью в мирной ситуации; активная команда доступна только в бою либо эффект не определён вне боя. | M9: SYM-030 | N9: Q-SYM-005; Q-SYM-009 | O9: 10 | P9: ACTIVE | Q9: =COUNTIF($A$6:$A$172,A9) -> 1
A10: SYM-032 | B10: WEAVER | C10: SYM-032 | D10: Анаболический форсаж | E10: PLAYER_COMMAND | F10: AUTOMATED_ACCEPTED | G10: =TRUE() -> TRUE | H10: =TRUE() -> TRUE | I10: =TRUE() -> TRUE | J10: =TRUE() -> TRUE | K10: Разрешается по агрегированным карточкам canonicalBehaviorCards; в бою учитываются указанная цена действий, боевые защиты, координаты и ходы. [SYM-032] Анаболический форсаж Нормативная база (действует во всей непротиворечащей части): A≥2: S += A/2, D += A/2 на T/4 ходов. A=1: вместо этого S +=20, D +=20 на 5 ходов и каждый ход носитель атакует случайную цель в поле зрения. Приоритетные авторские дельты (заменяют только прямо пересекающиеся ветви): [Q-SYM-005] Все дробные результаты округляются до ближайшего целого по математическим правилам; значение ровно 0,5 округляется вверх. Для количества ходов, минут, целей и создаваемых объектов действует минимум 1, если формула дала положительное значение; нулевой или отрицательный срок не создаёт продолжающегося эффекта. [Q-SYM-011] Применяется общее правило Q-CORE-023: одноимённые эффекты не суммируются, каждый сохраняет собственный срок, а действует сильнейшее ещё не истёкшее значение. После его окончания начинает действовать следующее. Прямое указание способности «обновляет длительность» имеет приоритет: для такого эффекта старый пакет заменяется новым по специальному тексту. [AQ3-002] При применении вне боевой ситуации натуральная 1 не создаёт специальную ветвь эффекта: нет бонуса +20 к S/D, пятиминутного таймера и обязательных атак; бой не открывается. 100 ОЭ остаются израсходованными, повторного броска нет. В бою ветвь натуральной 1 действует по CQA-007. В бою при натуральной 1 обязательная случайная атака и выбор цели разрешаются только по CQA-007. Вне боя специальная ветвь не возникает; затраты 100 ОЭ не возвращаются. | L10: Мирная атомарная операция по Q-APP-001/002; цена, бросок и положительный эффект — по SYM-032. Натуральная 1 вне боя не исполняется (Q-APP-004). [SYM-032] Анаболический форсаж Нормативная база (действует во всей непротиворечащей части): A≥2: S += A/2, D += A/2 на T/4 ходов. A=1: вместо этого S +=20, D +=20 на 5 ходов и каждый ход носитель атакует случайную цель в поле зрения. Приоритетные авторские дельты (заменяют только прямо пересекающиеся ветви): [Q-SYM-005] Все дробные результаты округляются до ближайшего целого по математическим правилам; значение ровно 0,5 округляется вверх. Для количества ходов, минут, целей и создаваемых объектов действует минимум 1, если формула дала положительное значение; нулевой или отрицательный срок не создаёт продолжающегося эффекта. [Q-SYM-011] Применяется общее правило Q-CORE-023: одноимённые эффекты не суммируются, каждый сохраняет собственный срок, а действует сильнейшее ещё не истёкшее значение. После его окончания начинает действовать следующее. Прямое указание способности «обновляет длительность» имеет приоритет: для такого эффекта старый пакет заменяется новым по специальному тексту. [AQ3-002] При применении вне боевой ситуации натуральная 1 не создаёт специальную ветвь эффекта: нет бонуса +20 к S/D, пятиминутного таймера и обязательных атак; бой не открывается. 100 ОЭ остаются израсходованными, повторного броска нет. В бою ветвь натуральной 1 действует по CQA-007. В бою при натуральной 1 обязательная случайная атака и выбор цели разрешаются только по CQA-007. Вне боя специальная ветвь не возникает; затраты 100 ОЭ не возвращаются. | M10: SYM-032 | N10: Q-SYM-005; Q-SYM-011 | O10: 60 | P10: ACTIVE | Q10: =COUNTIF($A$6:$A$172,A10) -> 1
A11: SYM-034 | B11: WEAVER | C11: SYM-034 | D11: Абсолютная регенерация | E11: PLAYER_COMMAND | F11: AUTOMATED_ACCEPTED | G11: =TRUE() -> TRUE | H11: =TRUE() -> TRUE | I11: =FALSE() -> FALSE | J11: =FALSE() -> FALSE | K11: Разрешается по агрегированным карточкам canonicalBehaviorCards; в бою учитываются указанная цена действий, боевые защиты, координаты и ходы. [SYM-034] Абсолютная регенерация Нормативная база (действует во всей непротиворечащей части): R=2–3: нет основного эффекта, вся энергия потрачена. R≥4: на R/4 ходов установить количество HP носителя 1000, запретить потерю дееспособности; каждая рана регенерирует через 2 хода. R=1: Ткач отключён на сутки и деградирует до L=4. Приоритетные авторские дельты (заменяют только прямо пересекающиеся ветви): [Q-SYM-005] Все дробные результаты округляются до ближайшего целого по математическим правилам; значение ровно 0,5 округляется вверх. Для количества ходов, минут, целей и создаваемых объектов действует минимум 1, если формула дала положительное значение; нулевой или отрицательный срок не создаёт продолжающегося эффекта. [Q-SYM-013] После окончания способности временное значение 1000 снимается, а текущие HP становятся равны min(текущие HP при эффекте, обычный максимум HP). Каждая полученная во время способности рана и травма исчезает через два хода после получения; незавершённые двухходовые таймеры продолжаются и после окончания способности. [Q-SYM-014] Деградация постоянна. Ткач становится 4 уровня; изученные узлы 5–6 уровней помечаются утраченными и недоступны, ранее потраченный на них опыт не возвращается. Для восстановления развития эти узлы необходимо последовательно изучить и оплатить заново по обычным правилам дерева. | L11: Игрок не может воспользоваться способностью в мирной ситуации; активная команда доступна только в бою либо эффект не определён вне боя. | M11: SYM-034 | N11: Q-SYM-005; Q-SYM-013; Q-SYM-014 | O11: 10 | P11: ACTIVE | Q11: =COUNTIF($A$6:$A$172,A11) -> 1
A12: SYM-031 | B12: WEAVER | C12: SYM-031 | D12: Выстрел регенерона | E12: PLAYER_COMMAND | F12: AUTOMATED_ACCEPTED | G12: =TRUE() -> TRUE | H12: =TRUE() -> TRUE | I12: =FALSE() -> FALSE | J12: =FALSE() -> FALSE | K12: Разрешается по агрегированным карточкам canonicalBehaviorCards; в бою учитываются указанная цена действий, боевые защиты, координаты и ходы. [SYM-031] Выстрел регенерона Нормативная база (действует во всей непротиворечащей части): R=2–4: нет эффекта. R≥5 и попадание: голая кожа → +2R HP; проницаемая одежда → +R HP; герметичная одежда → 0. R=1: вместо лечения кристаллизованная колючка наносит 2×R_damage урона, пробитие = R_penetration. Приоритетные авторские дельты (заменяют только прямо пересекающиеся ветви): [Q-SYM-010] Для дальней способности без указанной максимальной дальности используется стандартная дальность 50 метров. Требования поля зрения, точности, защиты и пробития сохраняются. | L12: Игрок не может воспользоваться способностью в мирной ситуации; активная команда доступна только в бою либо эффект не определён вне боя. | M12: SYM-031 | N12: Q-SYM-010 | O12: 10 | P12: ACTIVE | Q12: =COUNTIF($A$6:$A$172,A12) -> 1
A13: SYM-033 | B13: WEAVER | C13: SYM-033 | D13: Адреналиновая реанимация | E13: PLAYER_COMMAND | F13: AUTOMATED_ACCEPTED | G13: =TRUE() -> TRUE | H13: =TRUE() -> TRUE | I13: =TRUE() -> TRUE | J13: =TRUE() -> TRUE | K13: Разрешается по агрегированным карточкам canonicalBehaviorCards; в бою учитываются указанная цена действий, боевые защиты, координаты и ходы. [SYM-033] Адреналиновая реанимация Нормативная база (действует во всей непротиворечащей части): R=2–4: активация неуспешна. R≥5: выполнить попадание и пробитие; если шип достиг плоти, вывести цель из тяжёлого ранения, установить HP=1. R=1: «добить цель». Приоритетные авторские дельты (заменяют только прямо пересекающиеся ветви): [Q-SYM-010] Для дальней способности без указанной максимальной дальности используется стандартная дальность 50 метров. Требования поля зрения, точности, защиты и пробития сохраняются. [Q-SYM-012] Натуральная 1 заменяет реанимацию добиванием: цель в состоянии тяжёлого ранения немедленно умирает, только если шип успешно попал и достиг плоти после проверки брони. При промахе или непробитии добивание не происходит. | L13: Мирная операция/пассив разрешены явно. Для активной команды применяется Q-APP-001/002: отдельный пул боевых действий не создаётся, ОЭ и иные ресурсы списываются атомарно, немоделируемые контакт/дистанцию подтверждает мастер; боевой алгоритм карточки сохраняется в непротиворечащей части. [SYM-033] Адреналиновая реанимация Нормативная база (действует во всей непротиворечащей части): R=2–4: активация неуспешна. R≥5: выполнить попадание и пробитие; если шип достиг плоти, вывести цель из тяжёлого ранения, установить HP=1. R=1: «добить цель». Приоритетные авторские дельты (заменяют только прямо пересекающиеся ветви): [Q-SYM-010] Для дальней способности без указанной максимальной дальности используется стандартная дальность 50 метров. Требования поля зрения, точности, защиты и пробития сохраняются. [Q-SYM-012] Натуральная 1 заменяет реанимацию добиванием: цель в состоянии тяжёлого ранения немедленно умирает, только если шип успешно попал и достиг плоти после проверки брони. При промахе или непробитии добивание не происходит. | M13: SYM-033 | N13: Q-SYM-010; Q-SYM-012 | O13: 10 | P13: ACTIVE | Q13: =COUNTIF($A$6:$A$172,A13) -> 1
A14: SYM-035 | B14: WEAVER | C14: SYM-035 | D14: Абсолютная реанимация | E14: PLAYER_COMMAND | F14: AUTOMATED_ACCEPTED | G14: =TRUE() -> TRUE | H14: =TRUE() -> TRUE | I14: =TRUE() -> TRUE | J14: =TRUE() -> TRUE | K14: Разрешается по агрегированным карточкам canonicalBehaviorCards; в бою учитываются указанная цена действий, боевые защиты, координаты и ходы. [SYM-035] Абсолютная реанимация Нормативная база (действует во всей непротиворечащей части): если R=1, цель любой степени повреждения воскресает с I=1 независимо от формулы. Иначе воскрешение успешно только если R − 4T > 0. Приоритетные авторские дельты (заменяют только прямо пересекающиеся ветви): [Q-SYM-015] Сохранение мозга и части тела не проверяется – это игровая условность; цель воскресает с 1 HP вне тяжёлого ранения, Ткач сохраняется в носителе. При натуральной 1 I цели становится 1. T считается в ходах в бою и полных минутах вне боя по правилу перехода режимов Q-CORE-063. | L14: Мирная операция/пассив разрешены явно. Для активной команды применяется Q-APP-001/002: отдельный пул боевых действий не создаётся, ОЭ и иные ресурсы списываются атомарно, немоделируемые контакт/дистанцию подтверждает мастер; боевой алгоритм карточки сохраняется в непротиворечащей части. [SYM-035] Абсолютная реанимация Нормативная база (действует во всей непротиворечащей части): если R=1, цель любой степени повреждения воскресает с I=1 независимо от формулы. Иначе воскрешение успешно только если R − 4T > 0. Приоритетные авторские дельты (заменяют только прямо пересекающиеся ветви): [Q-SYM-015] Сохранение мозга и части тела не проверяется – это игровая условность; цель воскресает с 1 HP вне тяжёлого ранения, Ткач сохраняется в носителе. При натуральной 1 I цели становится 1. T считается в ходах в бою и полных минутах вне боя по правилу перехода режимов Q-CORE-063. | M14: SYM-035 | N14: Q-SYM-015 | O14: 10 | P14: ACTIVE | Q14: =COUNTIF($A$6:$A$172,A14) -> 1
A15: SYM-036 | B15: WEAVER | C15: SYM-036 | D15: Облако регенерона | E15: PLAYER_COMMAND | F15: AUTOMATED_ACCEPTED | G15: =TRUE() -> TRUE | H15: =TRUE() -> TRUE | I15: =FALSE() -> FALSE | J15: =FALSE() -> FALSE | K15: Разрешается по агрегированным карточкам canonicalBehaviorCards; в бою учитываются указанная цена действий, боевые защиты, координаты и ходы. [SYM-036] Облако регенерона создать мгновенную область радиусом R20 метров от носителя; всем живым существам восстановить 50 HP; находившимся в тяжёлом ранении установить HP=1 и вернуть сознание/дееспособность по общему правилу. | L15: Игрок не может воспользоваться способностью в мирной ситуации; активная команда доступна только в бою либо эффект не определён вне боя. | M15: SYM-036 | O15: 10 | P15: ACTIVE | Q15: =COUNTIF($A$6:$A$172,A15) -> 1
A16: SYM-039 | B16: TAIPAN | C16: SYM-039 | D16: Смертельный яд | E16: PLAYER_COMMAND | F16: AUTOMATED_ACCEPTED | G16: =TRUE() -> TRUE | H16: =TRUE() -> TRUE | I16: =TRUE() -> TRUE | J16: =TRUE() -> TRUE | K16: Разрешается по агрегированным карточкам canonicalBehaviorCards; в бою учитываются указанная цена действий, боевые защиты, координаты и ходы. [SYM-039] Смертельный яд Нормативная база (действует во всей непротиворечащей части): носитель иммунен к смертельному яду Тайпана. Цель получает за ход R20/5 + L урона в течение R20/2 ходов. При нанесении на оружие урон за ход делится пополам; остальные параметры неизменны. Приоритетные авторские дельты (заменяют только прямо пересекающиеся ветви): [Q-SYM-005] Все дробные результаты округляются до ближайшего целого по математическим правилам; значение ровно 0,5 округляется вверх. Для количества ходов, минут, целей и создаваемых объектов действует минимум 1, если формула дала положительное значение; нулевой или отрицательный срок не создаёт продолжающегося эффекта. [Q-SYM-017] Нанесение одной дозы яда на одно оружие или снаряд требует 1 боевого действия; доза сохраняется до первого успешного попадания, после чего расходуется. Первый периодический тик происходит в конце следующего хода отравленной цели; повтор того же яда не складывается, а заменяет силу и длительность новыми бросками и запускает срок заново. [SYM-181] Переключение типа яда Тайпана Нормативная база (действует во всей непротиворечащей части): одновременно вырабатывать один тип из {смертельный, ослабляющий, парализующий}; смена завершается через 1 игровой час/6 боевых ходов. Приоритетные авторские дельты (заменяют только прямо пересекающиеся ветви): [Q-SYM-076] Игрок опционально задаёт новый изученный вид яда в начале своего хода без отдельного действия (для этого у него отображается вариант действия «Сменить тип яда»). В течение следующего часа/6 полных ходов продолжает вырабатываться прежний яд, обычные действия носителя свободны. По окончании таймера активным становится новый вид. Отключение Тайпана или новая команда сбрасывает прогресс и оставляет прежний вид до завершения нового полного таймера. [SYM-183] Нанесение активного яда на предмет или пищу Без расхода ОЭ выполнить одну атомарную мирную операцию и зафиксировать на выбранном экземпляре одну дозу текущего яда. На оружии или снаряде доза хранится до первого успешного попадания и затем расходуется; эффективность уменьшается вдвое по профильному правилу, остальные проверки и параметры не меняются. В пище доза хранится до употребления и после проглатывания применяет полный профиль яда. | L16: Вне боя игрок может мгновенной мирной командой выбрать этот изученный тип яда по SYM-181 и нанести активный яд на допустимый предмет или пищу по SYM-183/Q-APP-002. Контакт и допустимость цели подтверждает мастер; эффект конкретного яда разрешается по карточке узла. [SYM-039] Смертельный яд Нормативная база (действует во всей непротиворечащей части): носитель иммунен к смертельному яду Тайпана. Цель получает за ход R20/5 + L урона в течение R20/2 ходов. При нанесении на оружие урон за ход делится пополам; остальные параметры неизменны. Приоритетные авторские дельты (заменяют только прямо пересекающиеся ветви): [Q-SYM-005] Все дробные результаты округляются до ближайшего целого по математическим правилам; значение ровно 0,5 округляется вверх. Для количества ходов, минут, целей и создаваемых объектов действует минимум 1, если формула дала положительное значение; нулевой или отрицательный срок не создаёт продолжающегося эффекта. [Q-SYM-017] Нанесение одной дозы яда на одно оружие или снаряд требует 1 боевого действия; доза сохраняется до первого успешного попадания, после чего расходуется. Первый периодический тик происходит в конце следующего хода отравленной цели; повтор того же яда не складывается, а заменяет силу и длительность новыми бросками и запускает срок заново. [SYM-181] Переключение типа яда Тайпана Нормативная база (действует во всей непротиворечащей части): одновременно вырабатывать один тип из {смертельный, ослабляющий, парализующий}; смена завершается через 1 игровой час/6 боевых ходов. Приоритетные авторские дельты (заменяют только прямо пересекающиеся ветви): [Q-SYM-076] Игрок опционально задаёт новый изученный вид яда в начале своего хода без отдельного действия (для этого у него отображается вариант действия «Сменить тип яда»). В течение следующего часа/6 полных ходов продолжает вырабатываться прежний яд, обычные действия носителя свободны. По окончании таймера активным становится новый вид. Отключение Тайпана или новая команда сбрасывает прогресс и оставляет прежний вид до завершения нового полного таймера. [SYM-183] Нанесение активного яда на предмет или пищу Без расхода ОЭ выполнить одну атомарную мирную операцию и зафиксировать на выбранном экземпляре одну дозу текущего яда. На оружии или снаряде доза хранится до первого успешного попадания и затем расходуется; эффективность уменьшается вдвое по профильному правилу, остальные проверки и параметры не меняются. В пище доза хранится до употребления и после проглатывания применяет полный профиль яда. | M16: SYM-039 | N16: Q-SYM-005; Q-SYM-017; Q-SYM-076; Q-APP-002 | O16: 10 | P16: ACTIVE | Q16: =COUNTIF($A$6:$A$172,A16) -> 1
A17: SYM-040 | B17: TAIPAN | C17: SYM-040 | D17: Проницаемая кожа | E17: PLAYER_COMMAND | F17: AUTOMATED_ACCEPTED | G17: =TRUE() -> TRUE | H17: =TRUE() -> TRUE | I17: =TRUE() -> TRUE | J17: =TRUE() -> TRUE | K17: Разрешается по агрегированным карточкам canonicalBehaviorCards; в бою учитываются указанная цена действий, боевые защиты, координаты и ходы. [SYM-040] Проницаемая кожа Нормативная база (действует во всей непротиворечащей части): R≥4: выбранная область пропускает текущий яд; при контакте этой области с голой кожей цели применить текущий яд. R=2–3: нет эффекта. R=1: носитель получает −1 к серии приёмов на 1 час/до конца боя. Приоритетные авторские дельты (заменяют только прямо пересекающиеся ветви): [Q-SYM-018] После успешной активации за 10 ОЭ Проницаемая кожа остаётся включённой без ограничения срока, пока носитель добровольно её не отключит, Тайпан не станет недееспособным или не будет удалён. Дополнительные контакты не требуют новой активации и не расходуют ОЭ. Один раз за каждую успешную безоружную атаку или успешную проверку борьбы цели накладывается яд, активный в крови носителя в момент контакта. Атаки оружием эффект не передают. После завершения перехода Тайпана к другому типу яда дальнейшие контакты используют новый яд. | L17: Мирная операция/пассив разрешены явно. Для активной команды применяется Q-APP-001/002: отдельный пул боевых действий не создаётся, ОЭ и иные ресурсы списываются атомарно, немоделируемые контакт/дистанцию подтверждает мастер; боевой алгоритм карточки сохраняется в непротиворечащей части. [SYM-040] Проницаемая кожа Нормативная база (действует во всей непротиворечащей части): R≥4: выбранная область пропускает текущий яд; при контакте этой области с голой кожей цели применить текущий яд. R=2–3: нет эффекта. R=1: носитель получает −1 к серии приёмов на 1 час/до конца боя. Приоритетные авторские дельты (заменяют только прямо пересекающиеся ветви): [Q-SYM-018] После успешной активации за 10 ОЭ Проницаемая кожа остаётся включённой без ограничения срока, пока носитель добровольно её не отключит, Тайпан не станет недееспособным или не будет удалён. Дополнительные контакты не требуют новой активации и не расходуют ОЭ. Один раз за каждую успешную безоружную атаку или успешную проверку борьбы цели накладывается яд, активный в крови носителя в момент контакта. Атаки оружием эффект не передают. После завершения перехода Тайпана к другому типу яда дальнейшие контакты используют новый яд. | M17: SYM-040 | N17: Q-SYM-018 | O17: 10 | P17: ACTIVE | Q17: =COUNTIF($A$6:$A$172,A17) -> 1
A18: SYM-041 | B18: TAIPAN | C18: SYM-041 | D18: Плевок ядом | E18: PLAYER_COMMAND | F18: AUTOMATED_ACCEPTED | G18: =TRUE() -> TRUE | H18: =TRUE() -> TRUE | I18: =FALSE() -> FALSE | J18: =FALSE() -> FALSE | K18: Разрешается по агрегированным карточкам canonicalBehaviorCards; в бою учитываются указанная цена действий, боевые защиты, координаты и ходы. [SYM-041] Плевок ядом Нормативная база (действует во всей непротиворечащей части): R20≥4: выполнить дальнюю атаку; пробитие=R12; если сгусток достиг кожи, наложить текущий яд. R20=2–3: нет эффекта. R20=1: носитель теряет 10 HP. Приоритетные авторские дельты (заменяют только прямо пересекающиеся ветви): [Q-SYM-010] Для дальней способности без указанной максимальной дальности используется стандартная дальность 50 метров. Требования поля зрения, точности, защиты и пробития сохраняются. [Q-SYM-075] При попадании Плевка ядом немедленно уничтожается внешний элемент обычной одежды или лёгкой брони со спасброском не выше R6. Уничтоженными могут быть только носимые элементы брони (подкожный панцирь симбионта, вшитая броня химеры и т. д. не могут быть уничтожены) Если после этого кожа открыта, яд достигает её тем же попаданием; более тяжёлая броня не разъедается, а уничтоженный элемент требует обычного ремонта или замены. | L18: Игрок не может воспользоваться способностью в мирной ситуации; активная команда доступна только в бою либо эффект не определён вне боя. | M18: SYM-041 | N18: Q-SYM-010; Q-SYM-075 | O18: 10 | P18: ACTIVE | Q18: =COUNTIF($A$6:$A$172,A18) -> 1
A19: SYM-042 | B19: TAIPAN | C19: SYM-042 | D19: Ослабляющий яд | E19: PLAYER_COMMAND | F19: AUTOMATED_ACCEPTED | G19: =TRUE() -> TRUE | H19: =TRUE() -> TRUE | I19: =TRUE() -> TRUE | J19: =TRUE() -> TRUE | K19: Разрешается по агрегированным карточкам canonicalBehaviorCards; в бою учитываются указанная цена действий, боевые защиты, координаты и ходы. [SYM-042] Ослабляющий яд Нормативная база (действует во всей непротиворечащей части): носитель иммунен. Рассчитать K=R20+L−Z_target; снизить S,D,M цели на K, но ни одну не ниже 1; срок R20/2 ходов. На оружии K делится пополам. Повторное применение обновляет длительность. Приоритетные авторские дельты (заменяют только прямо пересекающиеся ветви): [Q-SYM-005] Все дробные результаты округляются до ближайшего целого по математическим правилам; значение ровно 0,5 округляется вверх. Для количества ходов, минут, целей и создаваемых объектов действует минимум 1, если формула дала положительное значение; нулевой или отрицательный срок не создаёт продолжающегося эффекта. [Q-SYM-017] Нанесение одной дозы яда на одно оружие или снаряд требует 1 боевого действия; доза сохраняется до первого успешного попадания, после чего расходуется. Первый периодический тик происходит в конце следующего хода отравленной цели; повтор того же яда не складывается, а заменяет силу и длительность новыми бросками и запускает срок заново. [Q-SYM-019] Сила снижения K рассчитывается как max(0, R20 + L − Z). При K=0 яд считается попавшим, но характеристики цели не изменяются. [SYM-181] Переключение типа яда Тайпана Нормативная база (действует во всей непротиворечащей части): одновременно вырабатывать один тип из {смертельный, ослабляющий, парализующий}; смена завершается через 1 игровой час/6 боевых ходов. Приоритетные авторские дельты (заменяют только прямо пересекающиеся ветви): [Q-SYM-076] Игрок опционально задаёт новый изученный вид яда в начале своего хода без отдельного действия (для этого у него отображается вариант действия «Сменить тип яда»). В течение следующего часа/6 полных ходов продолжает вырабатываться прежний яд, обычные действия носителя свободны. По окончании таймера активным становится новый вид. Отключение Тайпана или новая команда сбрасывает прогресс и оставляет прежний вид до завершения нового полного таймера. [SYM-183] Нанесение активного яда на предмет или пищу Без расхода ОЭ выполнить одну атомарную мирную операцию и зафиксировать на выбранном экземпляре одну дозу текущего яда. На оружии или снаряде доза хранится до первого успешного попадания и затем расходуется; эффективность уменьшается вдвое по профильному правилу, остальные проверки и параметры не меняются. В пище доза хранится до употребления и после проглатывания применяет полный профиль яда. | L19: Вне боя игрок может мгновенной мирной командой выбрать этот изученный тип яда по SYM-181 и нанести активный яд на допустимый предмет или пищу по SYM-183/Q-APP-002. Контакт и допустимость цели подтверждает мастер; эффект конкретного яда разрешается по карточке узла. [SYM-042] Ослабляющий яд Нормативная база (действует во всей непротиворечащей части): носитель иммунен. Рассчитать K=R20+L−Z_target; снизить S,D,M цели на K, но ни одну не ниже 1; срок R20/2 ходов. На оружии K делится пополам. Повторное применение обновляет длительность. Приоритетные авторские дельты (заменяют только прямо пересекающиеся ветви): [Q-SYM-005] Все дробные результаты округляются до ближайшего целого по математическим правилам; значение ровно 0,5 округляется вверх. Для количества ходов, минут, целей и создаваемых объектов действует минимум 1, если формула дала положительное значение; нулевой или отрицательный срок не создаёт продолжающегося эффекта. [Q-SYM-017] Нанесение одной дозы яда на одно оружие или снаряд требует 1 боевого действия; доза сохраняется до первого успешного попадания, после чего расходуется. Первый периодический тик происходит в конце следующего хода отравленной цели; повтор того же яда не складывается, а заменяет силу и длительность новыми бросками и запускает срок заново. [Q-SYM-019] Сила снижения K рассчитывается как max(0, R20 + L − Z). При K=0 яд считается попавшим, но характеристики цели не изменяются. [SYM-181] Переключение типа яда Тайпана Нормативная база (действует во всей непротиворечащей части): одновременно вырабатывать один тип из {смертельный, ослабляющий, парализующий}; смена завершается через 1 игровой час/6 боевых ходов. Приоритетные авторские дельты (заменяют только прямо пересекающиеся ветви): [Q-SYM-076] Игрок опционально задаёт новый изученный вид яда в начале своего хода без отдельного действия (для этого у него отображается вариант действия «Сменить тип яда»). В течение следующего часа/6 полных ходов продолжает вырабатываться прежний яд, обычные действия носителя свободны. По окончании таймера активным становится новый вид. Отключение Тайпана или новая команда сбрасывает прогресс и оставляет прежний вид до завершения нового полного таймера. [SYM-183] Нанесение активного яда на предмет или пищу Без расхода ОЭ выполнить одну атомарную мирную операцию и зафиксировать на выбранном экземпляре одну дозу текущего яда. На оружии или снаряде доза хранится до первого успешного попадания и затем расходуется; эффективность уменьшается вдвое по профильному правилу, остальные проверки и параметры не меняются. В пище доза хранится до употребления и после проглатывания применяет полный профиль яда. | M19: SYM-042 | N19: Q-SYM-005; Q-SYM-017; Q-SYM-019; Q-SYM-076; Q-APP-002 | O19: 10 | P19: ACTIVE | Q19: =COUNTIF($A$6:$A$172,A19) -> 1
A20: SYM-043 | B20: TAIPAN | C20: SYM-043 | D20: Ядовитый шип | E20: PLAYER_COMMAND | F20: AUTOMATED_ACCEPTED | G20: =TRUE() -> TRUE | H20: =TRUE() -> TRUE | I20: =FALSE() -> FALSE | J20: =FALSE() -> FALSE | K20: Разрешается по агрегированным карточкам canonicalBehaviorCards; в бою учитываются указанная цена действий, боевые защиты, координаты и ходы. [SYM-043] Ядовитый шип Нормативная база (действует во всей непротиворечащей части): R≥4: дальняя атака, пробитие=R+L, урон=R+L одной проверкой; если нанесён урон, наложить текущий яд. R=2–3: нет эффекта. R=1: Тайпан отключён на 1 час/6 ходов. Приоритетные авторские дельты (заменяют только прямо пересекающиеся ветви): [Q-SYM-010] Для дальней способности без указанной максимальной дальности используется стандартная дальность 50 метров. Требования поля зрения, точности, защиты и пробития сохраняются. | L20: Игрок не может воспользоваться способностью в мирной ситуации; активная команда доступна только в бою либо эффект не определён вне боя. | M20: SYM-043 | N20: Q-SYM-010 | O20: 10 | P20: ACTIVE | Q20: =COUNTIF($A$6:$A$172,A20) -> 1
A21: SYM-044 | B21: TAIPAN | C21: SYM-044 | D21: Кумулятивный шип | E21: PLAYER_COMMAND | F21: AUTOMATED_ACCEPTED | G21: =TRUE() -> TRUE | H21: =TRUE() -> TRUE | I21: =FALSE() -> FALSE | J21: =FALSE() -> FALSE | K21: Разрешается по агрегированным карточкам canonicalBehaviorCards; в бою учитываются указанная цена действий, боевые защиты, координаты и ходы. [SYM-044] Кумулятивный шип Нормативная база (действует во всей непротиворечащей части): A≥4: пробитие=(A+L)×2, урон=D+L; при нанесении урона наложить текущий яд. A=2–3: нет эффекта. A=1: носитель получает 20 урона и оглушение на 40 минут/3 хода. Приоритетные авторские дельты (заменяют только прямо пересекающиеся ветви): [Q-SYM-010] Для дальней способности без указанной максимальной дальности используется стандартная дальность 50 метров. Требования поля зрения, точности, защиты и пробития сохраняются. | L21: Игрок не может воспользоваться способностью в мирной ситуации; активная команда доступна только в бою либо эффект не определён вне боя. | M21: SYM-044 | N21: Q-SYM-010 | O21: 10 | P21: ACTIVE | Q21: =COUNTIF($A$6:$A$172,A21) -> 1
A22: SYM-045 | B22: TAIPAN | C22: SYM-045 | D22: Парализующий яд | E22: PLAYER_COMMAND | F22: AUTOMATED_ACCEPTED | G22: =TRUE() -> TRUE | H22: =TRUE() -> TRUE | I22: =TRUE() -> TRUE | J22: =TRUE() -> TRUE | K22: Разрешается по агрегированным карточкам canonicalBehaviorCards; в бою учитываются указанная цена действий, боевые защиты, координаты и ходы. [SYM-045] Парализующий яд Нормативная база (действует во всей непротиворечащей части): носитель иммунен. Если R20+L > Z_target, случайно выбрать D4 одну действующую конечность; уже онемевшие перебрасывать; наложить запрет действий конечностью на R20/3 ходов. На оружии длительность делится пополам. Если действующих конечностей нет, новое онемение не возникает. Приоритетные авторские дельты (заменяют только прямо пересекающиеся ветви): [Q-SYM-005] Все дробные результаты округляются до ближайшего целого по математическим правилам; значение ровно 0,5 округляется вверх. Для количества ходов, минут, целей и создаваемых объектов действует минимум 1, если формула дала положительное значение; нулевой или отрицательный срок не создаёт продолжающегося эффекта. [Q-SYM-017] Нанесение одной дозы яда на одно оружие или снаряд требует 1 боевого действия; доза сохраняется до первого успешного попадания, после чего расходуется. Первый периодический тик происходит в конце следующего хода отравленной цели; повтор того же яда не складывается, а заменяет силу и длительность новыми бросками и запускает срок заново. [Q-SYM-020] Нестандартная анатомия - игровая условность, мы не учитываем ее в приложении. При атаке не гуманоидного существа область тела просто не выбирается. Попадание в любую часть тела обсчитывается как попадание в корпус [SYM-181] Переключение типа яда Тайпана Нормативная база (действует во всей непротиворечащей части): одновременно вырабатывать один тип из {смертельный, ослабляющий, парализующий}; смена завершается через 1 игровой час/6 боевых ходов. Приоритетные авторские дельты (заменяют только прямо пересекающиеся ветви): [Q-SYM-076] Игрок опционально задаёт новый изученный вид яда в начале своего хода без отдельного действия (для этого у него отображается вариант действия «Сменить тип яда»). В течение следующего часа/6 полных ходов продолжает вырабатываться прежний яд, обычные действия носителя свободны. По окончании таймера активным становится новый вид. Отключение Тайпана или новая команда сбрасывает прогресс и оставляет прежний вид до завершения нового полного таймера. [SYM-183] Нанесение активного яда на предмет или пищу Без расхода ОЭ выполнить одну атомарную мирную операцию и зафиксировать на выбранном экземпляре одну дозу текущего яда. На оружии или снаряде доза хранится до первого успешного попадания и затем расходуется; эффективность уменьшается вдвое по профильному правилу, остальные проверки и параметры не меняются. В пище доза хранится до употребления и после проглатывания применяет полный профиль яда. | L22: Вне боя игрок может мгновенной мирной командой выбрать этот изученный тип яда по SYM-181 и нанести активный яд на допустимый предмет или пищу по SYM-183/Q-APP-002. Контакт и допустимость цели подтверждает мастер; эффект конкретного яда разрешается по карточке узла. [SYM-045] Парализующий яд Нормативная база (действует во всей непротиворечащей части): носитель иммунен. Если R20+L > Z_target, случайно выбрать D4 одну действующую конечность; уже онемевшие перебрасывать; наложить запрет действий конечностью на R20/3 ходов. На оружии длительность делится пополам. Если действующих конечностей нет, новое онемение не возникает. Приоритетные авторские дельты (заменяют только прямо пересекающиеся ветви): [Q-SYM-005] Все дробные результаты округляются до ближайшего целого по математическим правилам; значение ровно 0,5 округляется вверх. Для количества ходов, минут, целей и создаваемых объектов действует минимум 1, если формула дала положительное значение; нулевой или отрицательный срок не создаёт продолжающегося эффекта. [Q-SYM-017] Нанесение одной дозы яда на одно оружие или снаряд требует 1 боевого действия; доза сохраняется до первого успешного попадания, после чего расходуется. Первый периодический тик происходит в конце следующего хода отравленной цели; повтор того же яда не складывается, а заменяет силу и длительность новыми бросками и запускает срок заново. [Q-SYM-020] Нестандартная анатомия - игровая условность, мы не учитываем ее в приложении. При атаке не гуманоидного существа область тела просто не выбирается. Попадание в любую часть тела обсчитывается как попадание в корпус [SYM-181] Переключение типа яда Тайпана Нормативная база (действует во всей непротиворечащей части): одновременно вырабатывать один тип из {смертельный, ослабляющий, парализующий}; смена завершается через 1 игровой час/6 боевых ходов. Приоритетные авторские дельты (заменяют только прямо пересекающиеся ветви): [Q-SYM-076] Игрок опционально задаёт новый изученный вид яда в начале своего хода без отдельного действия (для этого у него отображается вариант действия «Сменить тип яда»). В течение следующего часа/6 полных ходов продолжает вырабатываться прежний яд, обычные действия носителя свободны. По окончании таймера активным становится новый вид. Отключение Тайпана или новая команда сбрасывает прогресс и оставляет прежний вид до завершения нового полного таймера. [SYM-183] Нанесение активного яда на предмет или пищу Без расхода ОЭ выполнить одну атомарную мирную операцию и зафиксировать на выбранном экземпляре одну дозу текущего яда. На оружии или снаряде доза хранится до первого успешного попадания и затем расходуется; эффективность уменьшается вдвое по профильному правилу, остальные проверки и параметры не меняются. В пище доза хранится до употребления и после проглатывания применяет полный профиль яда. | M22: SYM-045 | N22: Q-SYM-005; Q-SYM-017; Q-SYM-020; Q-SYM-076; Q-APP-002 | O22: 10 | P22: ACTIVE | Q22: =COUNTIF($A$6:$A$172,A22) -> 1
A23: SYM-047 | B23: OWL | C23: SYM-047 | D23: Безупречное зрение | E23: PASSIVE_OR_AUTOMATIC | F23: AUTOMATED_ACCEPTED | G23: =TRUE() -> TRUE | H23: =FALSE() -> FALSE | I23: =TRUE() -> TRUE | J23: =FALSE() -> FALSE | K23: Разрешается по агрегированным карточкам canonicalBehaviorCards; в бою учитываются указанная цена действий, боевые защиты, координаты и ходы. [SYM-047] Безупречное зрение и подавление Двойного фокуса Нормативная база (действует во всей непротиворечащей части): добавить +10 к осмотру/слежке/дальнему визуальному обнаружению днём. Если изучен «Двойной фокус внимания» Хамелеона, не применять его бонус и физические изменения. Приоритетные авторские дельты (заменяют только прямо пересекающиеся ветви): [Q-SYM-021] Пока Сова активна в теле, «Двойной фокус внимания» полностью подавлен. После удаления, гибели или отключения Совы изученная способность Хамелеона автоматически начинает давать бонус и необходимые физические изменения без повторного изучения; при возвращении активной Совы снова подавляется. | L23: Мирная операция/пассив разрешены явно. Для активной команды применяется Q-APP-001/002: отдельный пул боевых действий не создаётся, ОЭ и иные ресурсы списываются атомарно, немоделируемые контакт/дистанцию подтверждает мастер; боевой алгоритм карточки сохраняется в непротиворечащей части. [SYM-047] Безупречное зрение и подавление Двойного фокуса Нормативная база (действует во всей непротиворечащей части): добавить +10 к осмотру/слежке/дальнему визуальному обнаружению днём. Если изучен «Двойной фокус внимания» Хамелеона, не применять его бонус и физические изменения. Приоритетные авторские дельты (заменяют только прямо пересекающиеся ветви): [Q-SYM-021] Пока Сова активна в теле, «Двойной фокус внимания» полностью подавлен. После удаления, гибели или отключения Совы изученная способность Хамелеона автоматически начинает давать бонус и необходимые физические изменения без повторного изучения; при возвращении активной Совы снова подавляется. | M23: SYM-047 | N23: Q-SYM-021 | O23: 10 | P23: ACTIVE | Q23: =COUNTIF($A$6:$A$172,A23) -> 1
A24: SYM-048 | B24: OWL | C24: SYM-048 | D24: Абсолютное ночное зрение | E24: PASSIVE_OR_AUTOMATIC | F24: AUTOMATED_ACCEPTED | G24: =TRUE() -> TRUE | H24: =FALSE() -> FALSE | I24: =TRUE() -> TRUE | J24: =FALSE() -> FALSE | K24: Разрешается по агрегированным карточкам canonicalBehaviorCards; в бою учитываются указанная цена действий, боевые защиты, координаты и ходы. [SYM-048] Абсолютное ночное зрение удалить штраф к осмотру, вызванный временем суток или тёмным помещением. | L24: Мирная операция/пассив разрешены явно. Для активной команды применяется Q-APP-001/002: отдельный пул боевых действий не создаётся, ОЭ и иные ресурсы списываются атомарно, немоделируемые контакт/дистанцию подтверждает мастер; боевой алгоритм карточки сохраняется в непротиворечащей части. [SYM-048] Абсолютное ночное зрение удалить штраф к осмотру, вызванный временем суток или тёмным помещением. | M24: SYM-048 | O24: 10 | P24: ACTIVE | Q24: =COUNTIF($A$6:$A$172,A24) -> 1
A25: SYM-049 | B25: OWL | C25: SYM-049 | D25: Абсолютное обоняние | E25: PASSIVE_OR_AUTOMATIC | F25: AUTOMATED_ACCEPTED | G25: =TRUE() -> TRUE | H25: =FALSE() -> FALSE | I25: =FALSE() -> FALSE | J25: =FALSE() -> FALSE | K25: Разрешается по агрегированным карточкам canonicalBehaviorCards; в бою учитываются указанная цена действий, боевые защиты, координаты и ходы. [SYM-049] Абсолютное обоняние добавить +15. | L25: Игрок не может воспользоваться способностью в мирной ситуации; активная команда доступна только в бою либо эффект не определён вне боя. | M25: SYM-049 | O25: 10 | P25: ACTIVE | Q25: =COUNTIF($A$6:$A$172,A25) -> 1
A26: SYM-050 | B26: OWL | C26: SYM-050 | D26: Абсолютный слух | E26: PASSIVE_OR_AUTOMATIC | F26: AUTOMATED_ACCEPTED | G26: =TRUE() -> TRUE | H26: =FALSE() -> FALSE | I26: =FALSE() -> FALSE | J26: =FALSE() -> FALSE | K26: Разрешается по агрегированным карточкам canonicalBehaviorCards; в бою учитываются указанная цена действий, боевые защиты, координаты и ходы. [SYM-050] Абсолютный слух добавить +15 к слуху. | L26: Игрок не может воспользоваться способностью в мирной ситуации; активная команда доступна только в бою либо эффект не определён вне боя. | M26: SYM-050 | O26: 10 | P26: ACTIVE | Q26: =COUNTIF($A$6:$A$172,A26) -> 1
A27: SYM-051 | B27: OWL | C27: SYM-051 | D27: Звуковая картина | E27: PLAYER_COMMAND | F27: AUTOMATED_ACCEPTED | G27: =TRUE() -> TRUE | H27: =TRUE() -> TRUE | I27: =TRUE() -> TRUE | J27: =TRUE() -> TRUE | K27: Разрешается по агрегированным карточкам canonicalBehaviorCards; в бою учитываются указанная цена действий, боевые защиты, координаты и ходы. [SYM-051] Звуковая картина Нормативная база (действует во всей непротиворечащей части): пассивно ориентироваться на слух без штрафов. Активно: R=1–3 — нет данных; R=4–10 — местоположение; R=11–17 — местоположение и все характеристики; R=18–20 — также виды симбионтов. Приоритетные авторские дельты (заменяют только прямо пересекающиеся ветви): [Q-SYM-022] Раскрываются текущие итоговые значения семи характеристик S, D, M, Z, I, W и C с учётом действующих модификаторов. Базовые значения, текущие и максимальные HP/ОЭ не раскрываются, если способность не называет их отдельно. | L27: Мирная операция/пассив разрешены явно. Для активной команды применяется Q-APP-001/002: отдельный пул боевых действий не создаётся, ОЭ и иные ресурсы списываются атомарно, немоделируемые контакт/дистанцию подтверждает мастер; боевой алгоритм карточки сохраняется в непротиворечащей части. [SYM-051] Звуковая картина Нормативная база (действует во всей непротиворечащей части): пассивно ориентироваться на слух без штрафов. Активно: R=1–3 — нет данных; R=4–10 — местоположение; R=11–17 — местоположение и все характеристики; R=18–20 — также виды симбионтов. Приоритетные авторские дельты (заменяют только прямо пересекающиеся ветви): [Q-SYM-022] Раскрываются текущие итоговые значения семи характеристик S, D, M, Z, I, W и C с учётом действующих модификаторов. Базовые значения, текущие и максимальные HP/ОЭ не раскрываются, если способность не называет их отдельно. | M27: SYM-051 | N27: Q-SYM-022 | O27: 10 | P27: ACTIVE | Q27: =COUNTIF($A$6:$A$172,A27) -> 1
A28: SYM-052 | B28: OWL | C28: SYM-052 | D28: Восприятие хищника | E28: PASSIVE_OR_AUTOMATIC | F28: AUTOMATED_ACCEPTED | G28: =TRUE() -> TRUE | H28: =FALSE() -> FALSE | I28: =TRUE() -> TRUE | J28: =FALSE() -> FALSE | K28: Разрешается по агрегированным карточкам canonicalBehaviorCards; в бою учитываются указанная цена действий, боевые защиты, координаты и ходы. [SYM-052] Восприятие хищника исключить из расчёта все модификаторы маскировки обнаруживаемой цели; саму проверку обнаружения сохранить. | L28: Мирная операция/пассив разрешены явно. Для активной команды применяется Q-APP-001/002: отдельный пул боевых действий не создаётся, ОЭ и иные ресурсы списываются атомарно, немоделируемые контакт/дистанцию подтверждает мастер; боевой алгоритм карточки сохраняется в непротиворечащей части. [SYM-052] Восприятие хищника исключить из расчёта все модификаторы маскировки обнаруживаемой цели; саму проверку обнаружения сохранить. | M28: SYM-052 | O28: 10 | P28: ACTIVE | Q28: =COUNTIF($A$6:$A$172,A28) -> 1
A29: SYM-054 | B29: TEACHER | C29: SYM-054 | D29: Развивайся, ученик | E29: PASSIVE_OR_AUTOMATIC | F29: AUTOMATED_ACCEPTED | G29: =TRUE() -> TRUE | H29: =FALSE() -> FALSE | I29: =TRUE() -> TRUE | J29: =FALSE() -> FALSE | K29: Разрешается по агрегированным карточкам canonicalBehaviorCards; в бою учитываются указанная цена действий, боевые защиты, координаты и ходы. [SYM-054] Развивайся, ученик W_bonus=max(0,min(4L,20−W_base)); W=W_base+W_bonus. Если Учитель — единственный симбионт, I_bonus=max(0,min(4L,20−I_base)), I=I_base+I_bonus. | L29: Мирная операция/пассив разрешены явно. Для активной команды применяется Q-APP-001/002: отдельный пул боевых действий не создаётся, ОЭ и иные ресурсы списываются атомарно, немоделируемые контакт/дистанцию подтверждает мастер; боевой алгоритм карточки сохраняется в непротиворечащей части. [SYM-054] Развивайся, ученик W_bonus=max(0,min(4L,20−W_base)); W=W_base+W_bonus. Если Учитель — единственный симбионт, I_bonus=max(0,min(4L,20−I_base)), I=I_base+I_bonus. | M29: SYM-054 | O29: 10 | P29: ACTIVE | Q29: =COUNTIF($A$6:$A$172,A29) -> 1
A30: SYM-055 | B30: TEACHER | C30: SYM-055 | D30: Век живи — век учись | E30: PASSIVE_OR_AUTOMATIC | F30: AUTOMATED_ACCEPTED | G30: =FALSE() -> FALSE | H30: =FALSE() -> FALSE | I30: =TRUE() -> TRUE | J30: =FALSE() -> FALSE | K30: Игрок не может воспользоваться способностью в боевой ситуации; контекст запрещён. | L30: Мирная операция/пассив разрешены явно. Для активной команды применяется Q-APP-001/002: отдельный пул боевых действий не создаётся, ОЭ и иные ресурсы списываются атомарно, немоделируемые контакт/дистанцию подтверждает мастер; боевой алгоритм карточки сохраняется в непротиворечащей части. [SYM-055] Век живи — век учись Приложение не определяет словесную ролевую игру автоматически. После ручного подтверждения часа равновероятно выбрать один присутствующий симбионт, кроме Учителя, и начислить ему 1 XP. Отключённое состояние не исключает симбионта из выбора. Если других симбионтов нет, XP не создаётся. | M30: SYM-055 | N30: Q-SYM-085 | O30: 10 | P30: ACTIVE | Q30: =COUNTIF($A$6:$A$172,A30) -> 1
A31: SYM-056 | B31: TEACHER | C31: SYM-056 | D31: Практикуйтесь, ученики | E31: PLAYER_COMMAND | F31: AUTOMATED_ACCEPTED | G31: =TRUE() -> TRUE | H31: =TRUE() -> TRUE | I31: =TRUE() -> TRUE | J31: =TRUE() -> TRUE | K31: Разрешается по агрегированным карточкам canonicalBehaviorCards; в бою учитываются указанная цена действий, боевые защиты, координаты и ходы. [SYM-056] Практикуйтесь, ученики каждому прочему симбионту установить currentOE=maxOE. | L31: Мирная операция/пассив разрешены явно. Для активной команды применяется Q-APP-001/002: отдельный пул боевых действий не создаётся, ОЭ и иные ресурсы списываются атомарно, немоделируемые контакт/дистанцию подтверждает мастер; боевой алгоритм карточки сохраняется в непротиворечащей части. [SYM-056] Практикуйтесь, ученики каждому прочему симбионту установить currentOE=maxOE. | M31: SYM-056 | O31: 10 | P31: ACTIVE | Q31: =COUNTIF($A$6:$A$172,A31) -> 1
A32: SYM-057 | B32: TEACHER | C32: SYM-057 | D32: Свети, ученик | E32: PASSIVE_OR_AUTOMATIC | F32: AUTOMATED_ACCEPTED | G32: =TRUE() -> TRUE | H32: =FALSE() -> FALSE | I32: =FALSE() -> FALSE | J32: =FALSE() -> FALSE | K32: Разрешается по агрегированным карточкам canonicalBehaviorCards; в бою учитываются указанная цена действий, боевые защиты, координаты и ходы. [SYM-057] Свети, ученик Нормативная база (действует во всей непротиворечащей части): R≥5: поставить на цель одноразовый маркер; при следующей попытке цели применить способность своего симбионта вместо неё случайно выбрать разрешимую активную способность одного из симбионтов носителя Учителя и случайную допустимую цель. При R=1 полностью обнулить ОЭ всех симбионтов носителя Учителя. Копия использует L Учителя, характеристики его носителя, правила целей/проверок/защит/единицы исходной способности; самоповреждение получает носитель Учителя. Приоритетные авторские дельты (заменяют только прямо пересекающиеся ветви): [Q-SYM-023] При наложении Учитель платит 40 ОЭ; маркер действует без срока до первого подходящего применения. При триггере заявленное целью действие расходуется, но ОЭ её отменённой способности не списываются. Копия выбирается только среди способностей, разницу до большей цены которых активный Учитель может доплатить. Если Учитель удалён или отключён либо допустимых копий нет, маркер снимается, а исходная способность цели разрешается обычно с её обычной оплатой. [Q-SYM-024] Из копирования исключаются способности с ценой «вся энергия», HP, жертвой, поддержанием за интервал, многоэтапной оплатой или иной нефиксированной ценой. Копировать можно только способность с единой фиксированной ценой в ОЭ и разрешимым эффектом. | L32: Игрок не может воспользоваться способностью в мирной ситуации; активная команда доступна только в бою либо эффект не определён вне боя. | M32: SYM-057 | N32: Q-SYM-023; Q-SYM-024 | O32: 10 | P32: ACTIVE | Q32: =COUNTIF($A$6:$A$172,A32) -> 1
A33: SYM-058 | B33: TEACHER | C33: SYM-058 | D33: Берегись невежд, ученик | E33: PLAYER_COMMAND | F33: AUTOMATED_ACCEPTED | G33: =TRUE() -> TRUE | H33: =TRUE() -> TRUE | I33: =FALSE() -> FALSE | J33: =FALSE() -> FALSE | K33: Разрешается по агрегированным карточкам canonicalBehaviorCards; в бою учитываются указанная цена действий, боевые защиты, координаты и ходы. [SYM-058] Берегись невежд, ученик гарантированно обнаружить всех носителей Трогра в радиусе 5R метров, игнорируя любые препятствия. | L33: Игрок не может воспользоваться способностью в мирной ситуации; активная команда доступна только в бою либо эффект не определён вне боя. | M33: SYM-058 | O33: 10 | P33: ACTIVE | Q33: =COUNTIF($A$6:$A$172,A33) -> 1
A34: SYM-059 | B34: TEACHER | C34: SYM-059 | D34: Внимай, ученик | E34: PLAYER_COMMAND | F34: AUTOMATED_ACCEPTED | G34: =TRUE() -> TRUE | H34: =TRUE() -> TRUE | I34: =TRUE() -> TRUE | J34: =TRUE() -> TRUE | K34: Разрешается по агрегированным карточкам canonicalBehaviorCards; в бою учитываются указанная цена действий, боевые защиты, координаты и ходы. [SYM-059] Внимай, ученик Нормативная база (действует во всей непротиворечащей части): применить последнюю активную способность любого симбионта цели; L=уровень Учителя, проверки — характеристиками его носителя; оплатить большую из цен (не сумму); затем отключить Учителя на сутки. Цели, проверки, защиты, единица и самоповреждение — по оригиналу. Приоритетные авторские дельты (заменяют только прямо пересекающиеся ветви): [Q-SYM-024] Из копирования исключаются способности с ценой «вся энергия», HP, жертвой, поддержанием за интервал, многоэтапной оплатой или иной нефиксированной ценой. Копировать можно только способность с единой фиксированной ценой в ОЭ и разрешимым эффектом. [Q-SYM-025] Если у цели нет последней использованной допустимой активной способности, «Внимай, ученик» объявить нельзя: ОЭ не расходуются и Учитель не отключается. Более ранние способности цели не просматриваются. | L34: Мирная операция/пассив разрешены явно. Для активной команды применяется Q-APP-001/002: отдельный пул боевых действий не создаётся, ОЭ и иные ресурсы списываются атомарно, немоделируемые контакт/дистанцию подтверждает мастер; боевой алгоритм карточки сохраняется в непротиворечащей части. [SYM-059] Внимай, ученик Нормативная база (действует во всей непротиворечащей части): применить последнюю активную способность любого симбионта цели; L=уровень Учителя, проверки — характеристиками его носителя; оплатить большую из цен (не сумму); затем отключить Учителя на сутки. Цели, проверки, защиты, единица и самоповреждение — по оригиналу. Приоритетные авторские дельты (заменяют только прямо пересекающиеся ветви): [Q-SYM-024] Из копирования исключаются способности с ценой «вся энергия», HP, жертвой, поддержанием за интервал, многоэтапной оплатой или иной нефиксированной ценой. Копировать можно только способность с единой фиксированной ценой в ОЭ и разрешимым эффектом. [Q-SYM-025] Если у цели нет последней использованной допустимой активной способности, «Внимай, ученик» объявить нельзя: ОЭ не расходуются и Учитель не отключается. Более ранние способности цели не просматриваются. | M34: SYM-059 | N34: Q-SYM-024; Q-SYM-025 | O34: 10 | P34: ACTIVE | Q34: =COUNTIF($A$6:$A$172,A34) -> 1
A35: SYM-061 | B35: ARMADILLO | C35: SYM-061 | D35: Подкожный панцирь | E35: PASSIVE_OR_AUTOMATIC | F35: AUTOMATED_ACCEPTED | G35: =TRUE() -> TRUE | H35: =FALSE() -> FALSE | I35: =TRUE() -> TRUE | J35: =FALSE() -> FALSE | K35: Разрешается по агрегированным карточкам canonicalBehaviorCards; в бою учитываются указанная цена действий, боевые защиты, координаты и ходы. [SYM-061] Подкожный панцирь добавить L к броне поражённой зоны, складывая с носимой бронёй. | L35: Мирная операция/пассив разрешены явно. Для активной команды применяется Q-APP-001/002: отдельный пул боевых действий не создаётся, ОЭ и иные ресурсы списываются атомарно, немоделируемые контакт/дистанцию подтверждает мастер; боевой алгоритм карточки сохраняется в непротиворечащей части. [SYM-061] Подкожный панцирь добавить L к броне поражённой зоны, складывая с носимой бронёй. | M35: SYM-061 | O35: 10 | P35: ACTIVE | Q35: =COUNTIF($A$6:$A$172,A35) -> 1
A36: SYM-062 | B36: ARMADILLO | C36: SYM-062 | D36: Здоров как буйвол | E36: PASSIVE_OR_AUTOMATIC | F36: AUTOMATED_ACCEPTED | G36: =TRUE() -> TRUE | H36: =FALSE() -> FALSE | I36: =TRUE() -> TRUE | J36: =FALSE() -> FALSE | K36: Разрешается по агрегированным карточкам canonicalBehaviorCards; в бою учитываются указанная цена действий, боевые защиты, координаты и ходы. [SYM-062] Здоров как буйвол Z = Z_base + L; при гибели/удалении вернуть базовое. | L36: Мирная операция/пассив разрешены явно. Для активной команды применяется Q-APP-001/002: отдельный пул боевых действий не создаётся, ОЭ и иные ресурсы списываются атомарно, немоделируемые контакт/дистанцию подтверждает мастер; боевой алгоритм карточки сохраняется в непротиворечащей части. [SYM-062] Здоров как буйвол Z = Z_base + L; при гибели/удалении вернуть базовое. | M36: SYM-062 | O36: 10 | P36: ACTIVE | Q36: =COUNTIF($A$6:$A$172,A36) -> 1
A37: SYM-063 | B37: ARMADILLO | C37: SYM-063 | D37: Не вырубишь! | E37: PASSIVE_OR_AUTOMATIC | F37: AUTOMATED_ACCEPTED | G37: =TRUE() -> TRUE | H37: =FALSE() -> FALSE | I37: =TRUE() -> TRUE | J37: =FALSE() -> FALSE | K37: Разрешается по агрегированным карточкам canonicalBehaviorCards; в бою учитываются указанная цена действий, боевые защиты, координаты и ходы. [SYM-063] Не вырубишь! отменить наложение оглушения. | L37: Мирная операция/пассив разрешены явно. Для активной команды применяется Q-APP-001/002: отдельный пул боевых действий не создаётся, ОЭ и иные ресурсы списываются атомарно, немоделируемые контакт/дистанцию подтверждает мастер; боевой алгоритм карточки сохраняется в непротиворечащей части. [SYM-063] Не вырубишь! отменить наложение оглушения. | M37: SYM-063 | O37: 10 | P37: ACTIVE | Q37: =COUNTIF($A$6:$A$172,A37) -> 1
A38: SYM-064 | B38: ARMADILLO | C38: SYM-064 | D38: Не подчиняюсь! | E38: PASSIVE_OR_AUTOMATIC | F38: AUTOMATED_ACCEPTED | G38: =TRUE() -> TRUE | H38: =FALSE() -> FALSE | I38: =TRUE() -> TRUE | J38: =FALSE() -> FALSE | K38: Разрешается по агрегированным карточкам canonicalBehaviorCards; в бою учитываются указанная цена действий, боевые защиты, координаты и ходы. [SYM-064] Не подчиняюсь! добавить +5. | L38: Мирная операция/пассив разрешены явно. Для активной команды применяется Q-APP-001/002: отдельный пул боевых действий не создаётся, ОЭ и иные ресурсы списываются атомарно, немоделируемые контакт/дистанцию подтверждает мастер; боевой алгоритм карточки сохраняется в непротиворечащей части. [SYM-064] Не подчиняюсь! добавить +5. | M38: SYM-064 | O38: 10 | P38: ACTIVE | Q38: =COUNTIF($A$6:$A$172,A38) -> 1
A39: SYM-065 | B39: ARMADILLO | C39: SYM-065 | D39: Не сдвинешь! | E39: PASSIVE_OR_AUTOMATIC | F39: AUTOMATED_ACCEPTED | G39: =TRUE() -> TRUE | H39: =FALSE() -> FALSE | I39: =TRUE() -> TRUE | J39: =FALSE() -> FALSE | K39: Разрешается по агрегированным карточкам canonicalBehaviorCards; в бою учитываются указанная цена действий, боевые защиты, координаты и ходы. [SYM-065] Не сдвинешь! добавить +10. | L39: Мирная операция/пассив разрешены явно. Для активной команды применяется Q-APP-001/002: отдельный пул боевых действий не создаётся, ОЭ и иные ресурсы списываются атомарно, немоделируемые контакт/дистанцию подтверждает мастер; боевой алгоритм карточки сохраняется в непротиворечащей части. [SYM-065] Не сдвинешь! добавить +10. | M39: SYM-065 | O39: 10 | P39: ACTIVE | Q39: =COUNTIF($A$6:$A$172,A39) -> 1
A40: SYM-066 | B40: ARMADILLO | C40: SYM-066 | D40: Поднять щиты! | E40: PLAYER_COMMAND | F40: AUTOMATED_ACCEPTED | G40: =TRUE() -> TRUE | H40: =TRUE() -> TRUE | I40: =FALSE() -> FALSE | J40: =FALSE() -> FALSE | K40: Разрешается по агрегированным карточкам canonicalBehaviorCards; в бою учитываются указанная цена действий, боевые защиты, координаты и ходы. [SYM-066] Поднять щиты! Нормативная база (действует во всей непротиворечащей части): R≥4: сформировать полусферический щит внешней площадью 8 м² на время отражения и полностью отменить атаку любой силы/критичности. R=2–3: защита не срабатывает. R=1: сковать обе руки персонажа. Приоритетные авторские дельты (заменяют только прямо пересекающиеся ветви): [Q-SYM-026] Щит имеет радиус 3 метра. Он прикрывает носителя и другие союзные цели, чьи силуэты попадают в радиус действия способности (по ним нельзя заявлять атаки, пока щит действует). При натуральной 1 персонаж не может заявлять никаких действий кроме освобождения рук, которое потребует 1 боевое действие или 1 минуту на их освобождение. | L40: Игрок не может воспользоваться способностью в мирной ситуации; активная команда доступна только в бою либо эффект не определён вне боя. | M40: SYM-066 | N40: Q-SYM-026 | O40: 10 | P40: ACTIVE | Q40: =COUNTIF($A$6:$A$172,A40) -> 1
A41: SYM-068 | B41: DRAGON | C41: SYM-068 | D41: Горючая слюна | E41: PLAYER_COMMAND | F41: AUTOMATED_ACCEPTED | G41: =TRUE() -> TRUE | H41: =TRUE() -> TRUE | I41: =TRUE() -> TRUE | J41: =TRUE() -> TRUE | K41: Разрешается по агрегированным карточкам canonicalBehaviorCards; в бою учитываются указанная цена действий, боевые защиты, координаты и ходы. [SYM-068] Горючая слюна Нормативная база (действует во всей непротиворечащей части): слюна вырабатывается в L раз больше обычной; стартовое горение 3 минуты/3 хода. При точности 19+ удар/выстрел покрытым оружием передаёт цели горение на оставшееся время только что нанесённой слюны. Приоритетные авторские дельты (заменяют только прямо пересекающиеся ветви): [Q-SYM-027] Для передачи горения достаточно успешного попадания с итогом точности 19+; наносить урон или пробивать броню не требуется. | L41: Мирная операция/пассив разрешены явно. Для активной команды применяется Q-APP-001/002: отдельный пул боевых действий не создаётся, ОЭ и иные ресурсы списываются атомарно, немоделируемые контакт/дистанцию подтверждает мастер; боевой алгоритм карточки сохраняется в непротиворечащей части. [SYM-068] Горючая слюна Нормативная база (действует во всей непротиворечащей части): слюна вырабатывается в L раз больше обычной; стартовое горение 3 минуты/3 хода. При точности 19+ удар/выстрел покрытым оружием передаёт цели горение на оставшееся время только что нанесённой слюны. Приоритетные авторские дельты (заменяют только прямо пересекающиеся ветви): [Q-SYM-027] Для передачи горения достаточно успешного попадания с итогом точности 19+; наносить урон или пробивать броню не требуется. | M41: SYM-068 | N41: Q-SYM-027 | O41: 10 | P41: ACTIVE | Q41: =COUNTIF($A$6:$A$172,A41) -> 1
A42: SYM-069 | B42: DRAGON | C42: SYM-069 | D42: Огнеупорная глотка | E42: PASSIVE_OR_AUTOMATIC | F42: AUTOMATED_ACCEPTED | G42: =TRUE() -> TRUE | H42: =FALSE() -> FALSE | I42: =TRUE() -> TRUE | J42: =FALSE() -> FALSE | K42: Разрешается по агрегированным карточкам canonicalBehaviorCards; в бою учитываются указанная цена действий, боевые защиты, координаты и ходы. [SYM-069] Огнеупорная глотка Нормативная база (действует во всей непротиворечащей части): указанные зоны не получают повреждений от температуры пламени до 4 минут/4 ходов; слюна не прилипает внутри рта. Приоритетные авторские дельты (заменяют только прямо пересекающиеся ветви): [Q-SYM-028] Четыре минуты/четыре боевых хода считаются отдельно для каждого непрерывного эпизода воздействия огня на рот и глотку. После прекращения воздействия счётчик сбрасывается; начиная с пятого интервала огонь действует по обычным правилам. | L42: Мирная операция/пассив разрешены явно. Для активной команды применяется Q-APP-001/002: отдельный пул боевых действий не создаётся, ОЭ и иные ресурсы списываются атомарно, немоделируемые контакт/дистанцию подтверждает мастер; боевой алгоритм карточки сохраняется в непротиворечащей части. [SYM-069] Огнеупорная глотка Нормативная база (действует во всей непротиворечащей части): указанные зоны не получают повреждений от температуры пламени до 4 минут/4 ходов; слюна не прилипает внутри рта. Приоритетные авторские дельты (заменяют только прямо пересекающиеся ветви): [Q-SYM-028] Четыре минуты/четыре боевых хода считаются отдельно для каждого непрерывного эпизода воздействия огня на рот и глотку. После прекращения воздействия счётчик сбрасывается; начиная с пятого интервала огонь действует по обычным правилам. | M42: SYM-069 | N42: Q-SYM-028 | O42: 10 | P42: ACTIVE | Q42: =COUNTIF($A$6:$A$172,A42) -> 1
A43: SYM-070 | B43: DRAGON | C43: SYM-070 | D43: Зубы-огниво | E43: PLAYER_COMMAND | F43: AUTOMATED_ACCEPTED | G43: =TRUE() -> TRUE | H43: =TRUE() -> TRUE | I43: =TRUE() -> TRUE | J43: =TRUE() -> TRUE | K43: Разрешается по агрегированным карточкам canonicalBehaviorCards; в бою учитываются указанная цена действий, боевые защиты, координаты и ходы. [SYM-070] Зубы-огниво гарантированно зажечь слюну без проверки. | L43: Мирная операция/пассив разрешены явно. Для активной команды применяется Q-APP-001/002: отдельный пул боевых действий не создаётся, ОЭ и иные ресурсы списываются атомарно, немоделируемые контакт/дистанцию подтверждает мастер; боевой алгоритм карточки сохраняется в непротиворечащей части. [SYM-070] Зубы-огниво гарантированно зажечь слюну без проверки. | M43: SYM-070 | O43: 10 | P43: ACTIVE | Q43: =COUNTIF($A$6:$A$172,A43) -> 1
A44: SYM-071 | B44: DRAGON | C44: SYM-071 | D44: Нагнетатель давления | E44: PLAYER_COMMAND | F44: AUTOMATED_ACCEPTED | G44: =TRUE() -> TRUE | H44: =TRUE() -> TRUE | I44: =FALSE() -> FALSE | J44: =FALSE() -> FALSE | K44: Разрешается по агрегированным карточкам canonicalBehaviorCards; в бою учитываются указанная цена действий, боевые защиты, координаты и ходы. [SYM-071] Нагнетатель давления Нормативная база (действует во всей непротиворечащей части): A≥4: длина струи A/4+L м; на каждую цель под струёй наложить горение на R6 элементов экипировки; при R6=6 горит вся экипировка, включая рюкзак. A=2–3: нет эффекта. A=1: обнулить все ОЭ Дракона и запретить восстановление симбиотическим отваром 1 час. Приоритетные авторские дельты (заменяют только прямо пересекающиеся ветви): [Q-SYM-005] Все дробные результаты округляются до ближайшего целого по математическим правилам; значение ровно 0,5 округляется вверх. Для количества ходов, минут, целей и создаваемых объектов действует минимум 1, если формула дала положительное значение; нулевой или отрицательный срок не создаёт продолжающегося эффекта. [Q-SYM-029] После успешной активации строится отрезок от позиции носителя длиной R20/4+L метров и шириной 1 метр. Все участники, кроме самого носителя, чьи точки позиции находятся не далее 0,5 метра от этого отрезка, поражаются независимо от стороны. Активная защита от струи не выполняется. Каждый поражённый получает один двоичный статус горения Дракона с начальной длительностью 3 хода либо 6 ходов при изученном Долгом горении; бросок R6 по экипировке не выполняется. Повторное возгорание разрешается по Q-CORE-030. | L44: Игрок не может воспользоваться способностью в мирной ситуации; активная команда доступна только в бою либо эффект не определён вне боя. | M44: SYM-071 | N44: Q-SYM-005; Q-SYM-029 | O44: 10 | P44: ACTIVE | Q44: =COUNTIF($A$6:$A$172,A44) -> 1
A45: SYM-072 | B45: DRAGON | C45: SYM-072 | D45: Долгое горение | E45: PASSIVE_OR_AUTOMATIC | F45: AUTOMATED_ACCEPTED | G45: =TRUE() -> TRUE | H45: =FALSE() -> FALSE | I45: =TRUE() -> TRUE | J45: =FALSE() -> FALSE | K45: Разрешается по агрегированным карточкам canonicalBehaviorCards; в бою учитываются указанная цена действий, боевые защиты, координаты и ходы. [SYM-072] Долгое горение Нормативная база (действует во всей непротиворечащей части): заменить стартовую длительность на 6 ходов. Приоритетные авторские дельты (заменяют только прямо пересекающиеся ветви): [Q-SYM-077] Строка «Стоимость: 30 ОЭ» считается опечаткой. После изучения «Долгое горение» действует постоянно и бесплатно: каждое новое возгорание от слюны Дракона получает стартовую длительность 6 ходов вместо 3. | L45: Мирная операция/пассив разрешены явно. Для активной команды применяется Q-APP-001/002: отдельный пул боевых действий не создаётся, ОЭ и иные ресурсы списываются атомарно, немоделируемые контакт/дистанцию подтверждает мастер; боевой алгоритм карточки сохраняется в непротиворечащей части. [SYM-072] Долгое горение Нормативная база (действует во всей непротиворечащей части): заменить стартовую длительность на 6 ходов. Приоритетные авторские дельты (заменяют только прямо пересекающиеся ветви): [Q-SYM-077] Строка «Стоимость: 30 ОЭ» считается опечаткой. После изучения «Долгое горение» действует постоянно и бесплатно: каждое новое возгорание от слюны Дракона получает стартовую длительность 6 ходов вместо 3. | M45: SYM-072 | N45: Q-SYM-077 | O45: 10 | P45: ACTIVE | Q45: =COUNTIF($A$6:$A$172,A45) -> 1
A46: SYM-073 | B46: DRAGON | C46: SYM-073 | D46: Огненный шар | E46: PLAYER_COMMAND | F46: AUTOMATED_ACCEPTED | G46: =TRUE() -> TRUE | H46: =TRUE() -> TRUE | I46: =FALSE() -> FALSE | J46: =FALSE() -> FALSE | K46: Разрешается по агрегированным карточкам canonicalBehaviorCards; в бою учитываются указанная цена действий, боевые защиты, координаты и ходы. [SYM-073] Огненный шар Нормативная база (действует во всей непротиворечащей части): A≥4: max дальность 2A+L м; радиус R м; штраф каждой цели на уклонение из зоны = R; при поражении нанести чистый урон D+L без проверки травмы и наложить горение на все элементы экипировки; если в зоне тела нет одежды/экипировки, горит кожа. A=2–3: эффекта нет. A=1: применить под ноги носителя с «максимальной мощностью и радиусом». Приоритетные авторские дельты (заменяют только прямо пересекающиеся ветви): [Q-SYM-030] При натуральной 1 центр взрыва находится в точке носителя, радиус автоматически равен 12 метрам, а чистый урон — 20+L. На всех попавших в радиус, включая носителя, накладывается обычное горение от Огненного шара. | L46: Игрок не может воспользоваться способностью в мирной ситуации; активная команда доступна только в бою либо эффект не определён вне боя. | M46: SYM-073 | N46: Q-SYM-030 | O46: 10 | P46: ACTIVE | Q46: =COUNTIF($A$6:$A$172,A46) -> 1
A47: SYM-076 | B47: TROGR | C47: SYM-076 | D47: Трогровость | E47: PASSIVE_OR_AUTOMATIC | F47: AUTOMATED_ACCEPTED | G47: =TRUE() -> TRUE | H47: =FALSE() -> FALSE | I47: =TRUE() -> TRUE | J47: =FALSE() -> FALSE | K47: Разрешается по агрегированным карточкам canonicalBehaviorCards; в бою учитываются указанная цена действий, боевые защиты, координаты и ходы. [SYM-076] Трогровость Нормативная база (действует во всей непротиворечащей части): за каждый L добавить +6 к S,D,M,Z до потолка 25 у Единого/35 у Вольного; добавить 20L к maxHP; уменьшить I,W,C на 6L, но не ниже 1. Если поглощён Учитель, минимум I и W=4 (складывается с «подавленным советником»). После поглощения одного из {Учитель, Дельфин} slotCost=2; обоих — 3. Поглощение Дельфина немедленно устанавливает L=5. Приоритетные авторские дельты (заменяют только прямо пересекающиеся ветви): [Q-SYM-032] После поглощения Дельфина уровень Трогра становится не ниже 5, а все обязательные способности его линейной ветви уровней 2–5 считаются изученными бесплатно. Опыт за это не начисляется и компенсация уже развитому Трогру не выдаётся. | L47: Мирная операция/пассив разрешены явно. Для активной команды применяется Q-APP-001/002: отдельный пул боевых действий не создаётся, ОЭ и иные ресурсы списываются атомарно, немоделируемые контакт/дистанцию подтверждает мастер; боевой алгоритм карточки сохраняется в непротиворечащей части. [SYM-076] Трогровость Нормативная база (действует во всей непротиворечащей части): за каждый L добавить +6 к S,D,M,Z до потолка 25 у Единого/35 у Вольного; добавить 20L к maxHP; уменьшить I,W,C на 6L, но не ниже 1. Если поглощён Учитель, минимум I и W=4 (складывается с «подавленным советником»). После поглощения одного из {Учитель, Дельфин} slotCost=2; обоих — 3. Поглощение Дельфина немедленно устанавливает L=5. Приоритетные авторские дельты (заменяют только прямо пересекающиеся ветви): [Q-SYM-032] После поглощения Дельфина уровень Трогра становится не ниже 5, а все обязательные способности его линейной ветви уровней 2–5 считаются изученными бесплатно. Опыт за это не начисляется и компенсация уже развитому Трогру не выдаётся. | M47: SYM-076 | N47: Q-SYM-032 | O47: 10 | P47: ACTIVE | Q47: =COUNTIF($A$6:$A$172,A47) -> 1
A48: SYM-077 | B48: TROGR | C48: SYM-077 | D48: Трогр крушить! | E48: PASSIVE_OR_AUTOMATIC | F48: AUTOMATED_ACCEPTED | G48: =TRUE() -> TRUE | H48: =FALSE() -> FALSE | I48: =FALSE() -> FALSE | J48: =FALSE() -> FALSE | K48: Разрешается по агрегированным карточкам canonicalBehaviorCards; в бою учитываются указанная цена действий, боевые защиты, координаты и ходы. [SYM-077] Трогр крушить! Нормативная база (действует во всей непротиворечащей части): бонус к S = floor(totalLostHP/10); сбросить в конце схватки. Приоритетные авторские дельты (заменяют только прямо пересекающиеся ветви): [Q-SYM-033] Считается суммарное количество фактически потерянных HP за текущую схватку, включая повторную потерю восстановленных HP. За каждые полные 10 накопленных потерь даётся +1 S; лечение бонус не уменьшает, а в конце схватки счётчик и бонус обнуляются. | L48: Игрок не может воспользоваться способностью в мирной ситуации; активная команда доступна только в бою либо эффект не определён вне боя. | M48: SYM-077 | N48: Q-SYM-033 | O48: 10 | P48: ACTIVE | Q48: =COUNTIF($A$6:$A$172,A48) -> 1
A49: SYM-078 | B49: TROGR | C49: SYM-078 | D49: WAAAGH!!! | E49: PLAYER_COMMAND | F49: AUTOMATED_ACCEPTED | G49: =TRUE() -> TRUE | H49: =TRUE() -> TRUE | I49: =FALSE() -> FALSE | J49: =FALSE() -> FALSE | K49: Разрешается по агрегированным карточкам canonicalBehaviorCards; в бою учитываются указанная цена действий, боевые защиты, координаты и ходы. [SYM-078] WAAAGH!!! Нормативная база (действует во всей непротиворечащей части): если A≤B, нет эффекта. Разница 1–8: глухота 30 минут/6 ходов. 9–18: глухота + «страх» (−1 действие в серии) на тот же срок. >18: бессознательность 5 минут/1 ход. Приоритетные авторские дельты (заменяют только прямо пересекающиеся ветви): [Q-SYM-034] WAAAGH!!! выбирает одну цель на расстоянии не более 5 метров, приложение не высчитывает слышимость, способность применяется не зависимо от слышимости. Линия видимости не требуется. Доступна любая цель. | L49: Игрок не может воспользоваться способностью в мирной ситуации; активная команда доступна только в бою либо эффект не определён вне боя. | M49: SYM-078 | N49: Q-SYM-034 | O49: 10 | P49: ACTIVE | Q49: =COUNTIF($A$6:$A$172,A49) -> 1
A50: SYM-079 | B50: TROGR | C50: SYM-079 | D50: Мой дубина — твой башка! | E50: PASSIVE_OR_AUTOMATIC | F50: AUTOMATED_ACCEPTED | G50: =TRUE() -> TRUE | H50: =FALSE() -> FALSE | I50: =TRUE() -> TRUE | J50: =FALSE() -> FALSE | K50: Разрешается по агрегированным карточкам canonicalBehaviorCards; в бою учитываются указанная цена действий, боевые защиты, координаты и ходы. [SYM-079] Мой дубина — твой башка! если навыка нет — выдать высокий уровень без занятия слота; если есть — повысить на 3, не выше абсолютного. | L50: Мирная операция/пассив разрешены явно. Для активной команды применяется Q-APP-001/002: отдельный пул боевых действий не создаётся, ОЭ и иные ресурсы списываются атомарно, немоделируемые контакт/дистанцию подтверждает мастер; боевой алгоритм карточки сохраняется в непротиворечащей части. [SYM-079] Мой дубина — твой башка! если навыка нет — выдать высокий уровень без занятия слота; если есть — повысить на 3, не выше абсолютного. | M50: SYM-079 | O50: 10 | P50: ACTIVE | Q50: =COUNTIF($A$6:$A$172,A50) -> 1
A51: SYM-080 | B51: TROGR | C51: SYM-080 | D51: ЫЫЫ… | E51: PLAYER_COMMAND | F51: AUTOMATED_ACCEPTED | G51: =TRUE() -> TRUE | H51: =TRUE() -> TRUE | I51: =FALSE() -> FALSE | J51: =FALSE() -> FALSE | K51: Разрешается по агрегированным карточкам canonicalBehaviorCards; в бою учитываются указанная цена действий, боевые защиты, координаты и ходы. [SYM-080] ЫЫЫ… Нормативная база (действует во всей непротиворечащей части): если итог <10, носитель не чувствует боль любой силы и отключает эффект «Трогр крушить!». Приоритетные авторские дельты (заменяют только прямо пересекающиеся ветви): [Q-SYM-035] Эффект действует до конца текущей схватки. Его обязательное механическое последствие — немедленно обнулить и до конца эффекта запретить накопление бонуса «Трогр крушить!». Невосприимчивость к боли остаётся нарративной и отменяет иной механический эффект только тогда, когда описание этого эффекта прямо говорит, что он вызывается исключительно болью. | L51: Игрок не может воспользоваться способностью в мирной ситуации; активная команда доступна только в бою либо эффект не определён вне боя. | M51: SYM-080 | N51: Q-SYM-035 | O51: 10 | P51: ACTIVE | Q51: =COUNTIF($A$6:$A$172,A51) -> 1
A52: SYM-081 | B52: TROGR | C52: SYM-081 | D52: Утолщённые кости | E52: PASSIVE_OR_AUTOMATIC | F52: AUTOMATED_ACCEPTED | G52: =TRUE() -> TRUE | H52: =FALSE() -> FALSE | I52: =TRUE() -> TRUE | J52: =FALSE() -> FALSE | K52: Разрешается по агрегированным карточкам canonicalBehaviorCards; в бою учитываются указанная цена действий, боевые защиты, координаты и ходы. [SYM-081] Утолщённые кости добавить +4 к спасброску брони; сложить с носимыми доспехами. | L52: Мирная операция/пассив разрешены явно. Для активной команды применяется Q-APP-001/002: отдельный пул боевых действий не создаётся, ОЭ и иные ресурсы списываются атомарно, немоделируемые контакт/дистанцию подтверждает мастер; боевой алгоритм карточки сохраняется в непротиворечащей части. [SYM-081] Утолщённые кости добавить +4 к спасброску брони; сложить с носимыми доспехами. | M52: SYM-081 | O52: 10 | P52: ACTIVE | Q52: =COUNTIF($A$6:$A$172,A52) -> 1
A53: SYM-082 | B53: TROGR | C53: SYM-082 | D53: Гениальная тупость | E53: PASSIVE_OR_AUTOMATIC | F53: AUTOMATED_ACCEPTED | G53: =TRUE() -> TRUE | H53: =FALSE() -> FALSE | I53: =TRUE() -> TRUE | J53: =FALSE() -> FALSE | K53: Разрешается по агрегированным карточкам canonicalBehaviorCards; в бою учитываются указанная цена действий, боевые защиты, координаты и ходы. [SYM-082] Гениальная тупость При выбранной XOR-ветви natural 1 проверки I локально заменяет фактический исход на положительный Crit первой градации. В бою эта ability-assigned градация передаётся CORE-229 как criticalPolarity=SUCCESS, grade=1, source=ABILITY_OVERRIDE и участвует в приоритетном разрешении. Для этого же rawFace отрицательная цепочка CORE-084 не запускается. | L53: Мирная операция/пассив разрешены явно. Для активной команды применяется Q-APP-001/002: отдельный пул боевых действий не создаётся, ОЭ и иные ресурсы списываются атомарно, немоделируемые контакт/дистанцию подтверждает мастер; боевой алгоритм карточки сохраняется в непротиворечащей части. [SYM-082] Гениальная тупость При выбранной XOR-ветви natural 1 проверки I локально заменяет фактический исход на положительный Crit первой градации. В бою эта ability-assigned градация передаётся CORE-229 как criticalPolarity=SUCCESS, grade=1, source=ABILITY_OVERRIDE и участвует в приоритетном разрешении. Для этого же rawFace отрицательная цепочка CORE-084 не запускается. | M53: SYM-082 | N53: Q-COMBAT-CRIT-001 | O53: 80 | P53: ACTIVE | Q53: =COUNTIF($A$6:$A$172,A53) -> 1
A54: SYM-084 | B54: KEEPER | C54: SYM-084 | D54: Резервная копия | E54: HYBRID_COMMAND_AND_TRIGGER | F54: AUTOMATED_ACCEPTED | G54: =TRUE() -> TRUE | H54: =TRUE() -> TRUE | I54: =TRUE() -> TRUE | J54: =TRUE() -> TRUE | K54: Разрешается по агрегированным карточкам canonicalBehaviorCards; в бою учитываются указанная цена действий, боевые защиты, координаты и ходы. [SYM-084] Резервная копия: выход и параметры вне тела вывести Хранителя из тела; создать отдельного персонажа с HP=5L, каждой характеристикой =2L, сроком жизни вне тела L суток; ОЭ вне подходящего тела не восстанавливать. [SYM-085] Резервная копия: захват нового тела Нормативная база (действует во всей непротиворечащей части): для занятия ниши Хранитель должен иметь запас ОЭ строго больше запаса выбранного симбионта, убить его и уменьшить собственные ОЭ на запас ОЭ жертвы до восстановления. После 4-часового сна нового тела и полного восстановления ОЭ за сутки стереть его личность; установить I,W,C от исходного хозяина, остальные характеристики — от нового тела. Приоритетные авторские дельты (заменяют только прямо пересекающиеся ветви): [Q-SYM-036] Проникновение в добровольного, бессознательного или полностью обездвиженного Единого/Вольного занимает 1 действие. Тело без симбионтов непригодно; свободный слот заранее не нужен. После победы над выбранным симбионтом Хранитель занимает его слот, но до завершения первого полноценного четырёхчасового сна телом управляет прежняя личность. После сна начинается 24-часовая перезапись, на время которой тело недееспособно; затем управление получает личность исходного хозяина Хранителя. [Q-SYM-074] Сравниваются текущие ОЭ обоих симбионтов непосредственно перед боем. Хранитель побеждает только при строго большем текущем запасе и после победы вычитает из своих текущих ОЭ текущие ОЭ поверженного; максимальные запасы в расчёте не участвуют. | L54: Мирная операция/пассив разрешены явно. Для активной команды применяется Q-APP-001/002: отдельный пул боевых действий не создаётся, ОЭ и иные ресурсы списываются атомарно, немоделируемые контакт/дистанцию подтверждает мастер; боевой алгоритм карточки сохраняется в непротиворечащей части. [SYM-084] Резервная копия: выход и параметры вне тела вывести Хранителя из тела; создать отдельного персонажа с HP=5L, каждой характеристикой =2L, сроком жизни вне тела L суток; ОЭ вне подходящего тела не восстанавливать. [SYM-085] Резервная копия: захват нового тела Нормативная база (действует во всей непротиворечащей части): для занятия ниши Хранитель должен иметь запас ОЭ строго больше запаса выбранного симбионта, убить его и уменьшить собственные ОЭ на запас ОЭ жертвы до восстановления. После 4-часового сна нового тела и полного восстановления ОЭ за сутки стереть его личность; установить I,W,C от исходного хозяина, остальные характеристики — от нового тела. Приоритетные авторские дельты (заменяют только прямо пересекающиеся ветви): [Q-SYM-036] Проникновение в добровольного, бессознательного или полностью обездвиженного Единого/Вольного занимает 1 действие. Тело без симбионтов непригодно; свободный слот заранее не нужен. После победы над выбранным симбионтом Хранитель занимает его слот, но до завершения первого полноценного четырёхчасового сна телом управляет прежняя личность. После сна начинается 24-часовая перезапись, на время которой тело недееспособно; затем управление получает личность исходного хозяина Хранителя. [Q-SYM-074] Сравниваются текущие ОЭ обоих симбионтов непосредственно перед боем. Хранитель побеждает только при строго большем текущем запасе и после победы вычитает из своих текущих ОЭ текущие ОЭ поверженного; максимальные запасы в расчёте не участвуют. | M54: SYM-084; SYM-085 | N54: Q-SYM-036; Q-SYM-074 | O54: 10 | P54: ACTIVE | Q54: =COUNTIF($A$6:$A$172,A54) -> 1
A55: SYM-086 | B55: KEEPER | C55: SYM-086 | D55: Парализующее жало | E55: PLAYER_COMMAND | F55: AUTOMATED_ACCEPTED | G55: =TRUE() -> TRUE | H55: =TRUE() -> TRUE | I55: =FALSE() -> FALSE | J55: =FALSE() -> FALSE | K55: Разрешается по агрегированным карточкам canonicalBehaviorCards; в бою учитываются указанная цена действий, боевые защиты, координаты и ходы. [SYM-086] Парализующее жало выполнить атаку; пробитие=R12; если броня пробита и R20+10>Z_target, полностью обездвижить цель на 2 хода/2 минуты. | L55: Игрок не может воспользоваться способностью в мирной ситуации; активная команда доступна только в бою либо эффект не определён вне боя. | M55: SYM-086 | O55: 10 | P55: ACTIVE | Q55: =COUNTIF($A$6:$A$172,A55) -> 1
A56: SYM-087 | B56: KEEPER | C56: SYM-087 | D56: Оценка тела | E56: HYBRID_COMMAND_AND_TRIGGER | F56: AUTOMATED_ACCEPTED | G56: =TRUE() -> TRUE | H56: =TRUE() -> TRUE | I56: =TRUE() -> TRUE | J56: =TRUE() -> TRUE | K56: Разрешается по агрегированным карточкам canonicalBehaviorCards; в бою учитываются указанная цена действий, боевые защиты, координаты и ходы. [SYM-087] Оценка тела Нормативная база (действует во всей непротиворечащей части): R≥5: раскрыть S,D,M,Z цели; R=2–4: данных нет; R=1: дополнительно потерять 100 ОЭ. Приоритетные авторские дельты (заменяют только прямо пересекающиеся ветви): [Q-SYM-009] При обязательной потере ОЭ текущий запас уменьшается не ниже 0; энергетический долг не создаётся. Дополнительное отключение наступает только там, где оно прямо указано, в частности у Ткача при неудаче «Дублирования органов». | L56: Мирная операция/пассив разрешены явно. Для активной команды применяется Q-APP-001/002: отдельный пул боевых действий не создаётся, ОЭ и иные ресурсы списываются атомарно, немоделируемые контакт/дистанцию подтверждает мастер; боевой алгоритм карточки сохраняется в непротиворечащей части. [SYM-087] Оценка тела Нормативная база (действует во всей непротиворечащей части): R≥5: раскрыть S,D,M,Z цели; R=2–4: данных нет; R=1: дополнительно потерять 100 ОЭ. Приоритетные авторские дельты (заменяют только прямо пересекающиеся ветви): [Q-SYM-009] При обязательной потере ОЭ текущий запас уменьшается не ниже 0; энергетический долг не создаётся. Дополнительное отключение наступает только там, где оно прямо указано, в частности у Ткача при неудаче «Дублирования органов». | M56: SYM-087 | N56: Q-SYM-009 | O56: 10 | P56: ACTIVE | Q56: =COUNTIF($A$6:$A$172,A56) -> 1
A57: SYM-088 | B57: KEEPER | C57: SYM-088 | D57: Присоски и коготки | E57: PASSIVE_OR_AUTOMATIC | F57: AUTOMATED_ACCEPTED | G57: =TRUE() -> TRUE | H57: =FALSE() -> FALSE | I57: =TRUE() -> TRUE | J57: =FALSE() -> FALSE | K57: Разрешается по агрегированным карточкам canonicalBehaviorCards; в бою учитываются указанная цена действий, боевые защиты, координаты и ходы. [SYM-088] Присоски и коготки разрешить безопасное перемещение по любой поверхности в любой плоскости, включая стены и потолок. | L57: Мирная операция/пассив разрешены явно. Для активной команды применяется Q-APP-001/002: отдельный пул боевых действий не создаётся, ОЭ и иные ресурсы списываются атомарно, немоделируемые контакт/дистанцию подтверждает мастер; боевой алгоритм карточки сохраняется в непротиворечащей части. [SYM-088] Присоски и коготки разрешить безопасное перемещение по любой поверхности в любой плоскости, включая стены и потолок. | M57: SYM-088 | O57: 10 | P57: ACTIVE | Q57: =COUNTIF($A$6:$A$172,A57) -> 1
A58: SYM-089 | B58: KEEPER | C58: SYM-089 | D58: Маскировка «Хамелеон» | E58: PLAYER_COMMAND | F58: AUTOMATED_ACCEPTED | G58: =TRUE() -> TRUE | H58: =TRUE() -> TRUE | I58: =TRUE() -> TRUE | J58: =TRUE() -> TRUE | K58: Разрешается по агрегированным карточкам canonicalBehaviorCards; в бою учитываются указанная цена действий, боевые защиты, координаты и ходы. [SYM-089] Маскировка «Хамелеон» Хранителя Нормативная база (действует во всей непротиворечащей части): R≥4: проверки обнаружения против Хранителя получают −15; эффект держится до движения или применения другой способности. R=2–3: эффекта нет. R=1: дополнительно потерять 200 ОЭ. Приоритетные авторские дельты (заменяют только прямо пересекающиеся ветви): [Q-SYM-009] При обязательной потере ОЭ текущий запас уменьшается не ниже 0; энергетический долг не создаётся. Дополнительное отключение наступает только там, где оно прямо указано, в частности у Ткача при неудаче «Дублирования органов». | L58: Мирная операция/пассив разрешены явно. Для активной команды применяется Q-APP-001/002: отдельный пул боевых действий не создаётся, ОЭ и иные ресурсы списываются атомарно, немоделируемые контакт/дистанцию подтверждает мастер; боевой алгоритм карточки сохраняется в непротиворечащей части. [SYM-089] Маскировка «Хамелеон» Хранителя Нормативная база (действует во всей непротиворечащей части): R≥4: проверки обнаружения против Хранителя получают −15; эффект держится до движения или применения другой способности. R=2–3: эффекта нет. R=1: дополнительно потерять 200 ОЭ. Приоритетные авторские дельты (заменяют только прямо пересекающиеся ветви): [Q-SYM-009] При обязательной потере ОЭ текущий запас уменьшается не ниже 0; энергетический долг не создаётся. Дополнительное отключение наступает только там, где оно прямо указано, в частности у Ткача при неудаче «Дублирования органов». | M58: SYM-089 | N58: Q-SYM-009 | O58: 10 | P58: ACTIVE | Q58: =COUNTIF($A$6:$A$172,A58) -> 1
A59: SYM-090 | B59: KEEPER | C59: SYM-090 | D59: Кромсатель | E59: PASSIVE_OR_AUTOMATIC | F59: AUTOMATED_ACCEPTED | G59: =TRUE() -> TRUE | H59: =FALSE() -> FALSE | I59: =TRUE() -> TRUE | J59: =FALSE() -> FALSE | K59: Разрешается по агрегированным карточкам canonicalBehaviorCards; в бою учитываются указанная цена действий, боевые защиты, координаты и ходы. [SYM-090] Кромсатель заменить формулу максимума на maxOE=200×L; текущий ОЭ не восстанавливать. | L59: Мирная операция/пассив разрешены явно. Для активной команды применяется Q-APP-001/002: отдельный пул боевых действий не создаётся, ОЭ и иные ресурсы списываются атомарно, немоделируемые контакт/дистанцию подтверждает мастер; боевой алгоритм карточки сохраняется в непротиворечащей части. [SYM-090] Кромсатель заменить формулу максимума на maxOE=200×L; текущий ОЭ не восстанавливать. | M59: SYM-090 | O59: 10 | P59: ACTIVE | Q59: =COUNTIF($A$6:$A$172,A59) -> 1
A60: SYM-091 | B60: KEEPER | C60: SYM-091 | D60: Крылья | E60: PLAYER_COMMAND | F60: AUTOMATED_ACCEPTED | G60: =TRUE() -> TRUE | H60: =TRUE() -> TRUE | I60: =TRUE() -> TRUE | J60: =TRUE() -> TRUE | K60: Разрешается по агрегированным карточкам canonicalBehaviorCards; в бою учитываются указанная цена действий, боевые защиты, координаты и ходы. [SYM-091] Крылья Хранителя Нормативная база (действует во всей непротиворечащей части): за каждую минуту/боевой ход полёта списывать 20 ОЭ; в полёте добавить +10 к уклонению от ближней атаки и +20 от дальней. Приоритетные авторские дельты (заменяют только прямо пересекающиеся ветви): [Q-SYM-037] Взлёт и посадка требуют по 1 боевому действию. При взлёте сразу списываются 20 ОЭ, затем 20 ОЭ списываются в начале каждого следующего хода Хранителя; если полной суммы нет, полёт прекращается до действий и Хранитель приземляется, а при отсутствии безопасной точки падает. Финальная приоритетная нормализация: При любой причине состояние полёта снимается немедленно до новых действий. Сущность либо её труп сохраняет текущую 2D-координату (x, y); высота, траектория, падение и дополнительный урон приложением не моделируются. Если точка занята после изменения состава сущностей, мастер до продолжения выбирает ближайшую свободную точку. Восстановление дееспособности само по себе полёт не возобновляет. | L60: Мирная операция/пассив разрешены явно. Для активной команды применяется Q-APP-001/002: отдельный пул боевых действий не создаётся, ОЭ и иные ресурсы списываются атомарно, немоделируемые контакт/дистанцию подтверждает мастер; боевой алгоритм карточки сохраняется в непротиворечащей части. [SYM-091] Крылья Хранителя Нормативная база (действует во всей непротиворечащей части): за каждую минуту/боевой ход полёта списывать 20 ОЭ; в полёте добавить +10 к уклонению от ближней атаки и +20 от дальней. Приоритетные авторские дельты (заменяют только прямо пересекающиеся ветви): [Q-SYM-037] Взлёт и посадка требуют по 1 боевому действию. При взлёте сразу списываются 20 ОЭ, затем 20 ОЭ списываются в начале каждого следующего хода Хранителя; если полной суммы нет, полёт прекращается до действий и Хранитель приземляется, а при отсутствии безопасной точки падает. Финальная приоритетная нормализация: При любой причине состояние полёта снимается немедленно до новых действий. Сущность либо её труп сохраняет текущую 2D-координату (x, y); высота, траектория, падение и дополнительный урон приложением не моделируются. Если точка занята после изменения состава сущностей, мастер до продолжения выбирает ближайшую свободную точку. Восстановление дееспособности само по себе полёт не возобновляет. | M60: SYM-091 | N60: Q-QA-003; Q-SYM-037 | O60: 60 | P60: ACTIVE | Q60: =COUNTIF($A$6:$A$172,A60) -> 1
A61: SYM-093 | B61: KEEPER | C61: SYM-093 | D61: Попутчики | E61: PASSIVE_OR_AUTOMATIC | F61: AUTOMATED_ACCEPTED | G61: =TRUE() -> TRUE | H61: =FALSE() -> FALSE | I61: =FALSE() -> FALSE | J61: =FALSE() -> FALSE | K61: Разрешается по агрегированным карточкам canonicalBehaviorCards; в бою учитываются указанная цена действий, боевые защиты, координаты и ходы. [SYM-093] Попутчики Нормативная база (действует во всей непротиворечащей части): сохранить материал исходного набора. При заселении Единого и уничтожении всех его симбионтов заново вырастить исходный набор в освобождённых слотах, сохранив уровни. При заселении Вольного материал потерять. Приоритетные авторские дельты (заменяют только прямо пересекающиеся ветви): [Q-SYM-039] Попутчики начинают восстанавливаться только после заселения в тело Единого и уничтожения в нём всех прежних симбионтов. После следующего полноценного отдыха выращиваются сохранённые виды с прежними изученными способностями и уровнями; Хранитель не дублируется, текущие ОЭ новых симбионтов равны 0 и тем же отдыхом не восстанавливаются. Соблюдаются уникальность видов и вместимость | L61: Игрок не может воспользоваться способностью в мирной ситуации; активная команда доступна только в бою либо эффект не определён вне боя. | M61: SYM-093 | N61: Q-SYM-039 | O61: 10 | P61: ACTIVE | Q61: =COUNTIF($A$6:$A$172,A61) -> 1
A62: SYM-094 | B62: KEEPER | C62: SYM-094 | D62: Кислотная пушка | E62: PLAYER_COMMAND | F62: AUTOMATED_ACCEPTED | G62: =TRUE() -> TRUE | H62: =TRUE() -> TRUE | I62: =FALSE() -> FALSE | J62: =FALSE() -> FALSE | K62: Разрешается по агрегированным карточкам canonicalBehaviorCards; в бою учитываются указанная цена действий, боевые защиты, координаты и ходы. [SYM-094] Кислотная пушка Нормативная база (действует во всей непротиворечащей части): A≥3: стандартная дальняя атака, пробитие=A, урон=D+L; A=2: нет эффекта; A=1: дополнительно потерять 200 ОЭ. Приоритетные авторские дельты (заменяют только прямо пересекающиеся ветви): [Q-SYM-009] При обязательной потере ОЭ текущий запас уменьшается не ниже 0; энергетический долг не создаётся. Дополнительное отключение наступает только там, где оно прямо указано, в частности у Ткача при неудаче «Дублирования органов». | L62: Игрок не может воспользоваться способностью в мирной ситуации; активная команда доступна только в бою либо эффект не определён вне боя. | M62: SYM-094 | N62: Q-SYM-009 | O62: 10 | P62: ACTIVE | Q62: =COUNTIF($A$6:$A$172,A62) -> 1
A63: SYM-096 | B63: ADVISER | C63: SYM-096 | D63: Личность | E63: PASSIVE_OR_AUTOMATIC | F63: AUTOMATED_ACCEPTED | G63: =TRUE() -> TRUE | H63: =FALSE() -> FALSE | I63: =TRUE() -> TRUE | J63: =FALSE() -> FALSE | K63: Разрешается по агрегированным карточкам canonicalBehaviorCards; в бою учитываются указанная цена действий, боевые защиты, координаты и ходы. [SYM-096] Личность Советника Нормативная база (действует во всей непротиворечащей части): определить собственные I=R20+8, затем W=отдельный R20+8; игрок выбирает отдельный набор навыков; число слотов рассчитывается по W Советника как у носителя. Приоритетные авторские дельты (заменяют только прямо пересекающиеся ветви): [Q-SYM-040] Строка «Стоимость: 30 ОЭ» считается опечаткой. «Личность» бесплатно и автоматически создаёт характеристики и навыки Советника при получении симбионта. | L63: Мирная операция/пассив разрешены явно. Для активной команды применяется Q-APP-001/002: отдельный пул боевых действий не создаётся, ОЭ и иные ресурсы списываются атомарно, немоделируемые контакт/дистанцию подтверждает мастер; боевой алгоритм карточки сохраняется в непротиворечащей части. [SYM-096] Личность Советника Нормативная база (действует во всей непротиворечащей части): определить собственные I=R20+8, затем W=отдельный R20+8; игрок выбирает отдельный набор навыков; число слотов рассчитывается по W Советника как у носителя. Приоритетные авторские дельты (заменяют только прямо пересекающиеся ветви): [Q-SYM-040] Строка «Стоимость: 30 ОЭ» считается опечаткой. «Личность» бесплатно и автоматически создаёт характеристики и навыки Советника при получении симбионта. | M63: SYM-096 | N63: Q-SYM-040 | O63: 10 | P63: ACTIVE | Q63: =COUNTIF($A$6:$A$172,A63) -> 1
A64: SYM-097 | B64: ADVISER | C64: SYM-097 | D64: Я здесь самый умный | E64: PASSIVE_OR_AUTOMATIC | F64: AUTOMATED_ACCEPTED | G64: =TRUE() -> TRUE | H64: =FALSE() -> FALSE | I64: =TRUE() -> TRUE | J64: =FALSE() -> FALSE | K64: Разрешается по агрегированным карточкам canonicalBehaviorCards; в бою учитываются указанная цена действий, боевые защиты, координаты и ходы. [SYM-097] Я здесь самый умный I_adviser=I_base+L. | L64: Мирная операция/пассив разрешены явно. Для активной команды применяется Q-APP-001/002: отдельный пул боевых действий не создаётся, ОЭ и иные ресурсы списываются атомарно, немоделируемые контакт/дистанцию подтверждает мастер; боевой алгоритм карточки сохраняется в непротиворечащей части. [SYM-097] Я здесь самый умный I_adviser=I_base+L. | M64: SYM-097 | O64: 10 | P64: ACTIVE | Q64: =COUNTIF($A$6:$A$172,A64) -> 1
A65: SYM-098 | B65: ADVISER | C65: SYM-098 | D65: Доступ к органам чувств | E65: PASSIVE_OR_AUTOMATIC | F65: AUTOMATED_ACCEPTED | G65: =TRUE() -> TRUE | H65: =FALSE() -> FALSE | I65: =TRUE() -> TRUE | J65: =FALSE() -> FALSE | K65: Разрешается по агрегированным карточкам canonicalBehaviorCards; в бою учитываются указанная цена действий, боевые защиты, координаты и ходы. [SYM-098] Доступ к органам чувств разрешить Советнику отдельную от носителя проверку восприятия. | L65: Мирная операция/пассив разрешены явно. Для активной команды применяется Q-APP-001/002: отдельный пул боевых действий не создаётся, ОЭ и иные ресурсы списываются атомарно, немоделируемые контакт/дистанцию подтверждает мастер; боевой алгоритм карточки сохраняется в непротиворечащей части. [SYM-098] Доступ к органам чувств разрешить Советнику отдельную от носителя проверку восприятия. | M65: SYM-098 | O65: 10 | P65: ACTIVE | Q65: =COUNTIF($A$6:$A$172,A65) -> 1
A66: SYM-099 | B66: ADVISER | C66: SYM-099 | D66: Принимаю управление | E66: PLAYER_COMMAND | F66: AUTOMATED_ACCEPTED | G66: =TRUE() -> TRUE | H66: =TRUE() -> TRUE | I66: =TRUE() -> TRUE | J66: =TRUE() -> TRUE | K66: Разрешается по агрегированным карточкам canonicalBehaviorCards; в бою учитываются указанная цена действий, боевые защиты, координаты и ходы. [SYM-099] Принимаю управление Нормативная база (действует во всей непротиворечащей части): на время контроля заменить набор навыков тела на набор Советника; каждые 5 минут/1 боевой ход списывать 10 ОЭ. Возврат против воли Советника занимает 5 минут/1 ход. Приоритетные авторские дельты (заменяют только прямо пересекающиеся ветви): [Q-SYM-041] Добровольная передача в начале хода бесплатна по действиям, но немедленно требует 10 ОЭ; затем 10 ОЭ списываются в начале каждого следующего хода управления. При нехватке первой суммы передача невозможна, при нехватке последующей контроль возвращается носителю до действий. Добровольный возврат в начале хода бесплатен, принудительный занимает полный ход/5 минут. Автоматическое управление от «Системы устойчивости» ОЭ не расходует и прекращается при возвращении ясного сознания носителя. | L66: Мирная операция/пассив разрешены явно. Для активной команды применяется Q-APP-001/002: отдельный пул боевых действий не создаётся, ОЭ и иные ресурсы списываются атомарно, немоделируемые контакт/дистанцию подтверждает мастер; боевой алгоритм карточки сохраняется в непротиворечащей части. [SYM-099] Принимаю управление Нормативная база (действует во всей непротиворечащей части): на время контроля заменить набор навыков тела на набор Советника; каждые 5 минут/1 боевой ход списывать 10 ОЭ. Возврат против воли Советника занимает 5 минут/1 ход. Приоритетные авторские дельты (заменяют только прямо пересекающиеся ветви): [Q-SYM-041] Добровольная передача в начале хода бесплатна по действиям, но немедленно требует 10 ОЭ; затем 10 ОЭ списываются в начале каждого следующего хода управления. При нехватке первой суммы передача невозможна, при нехватке последующей контроль возвращается носителю до действий. Добровольный возврат в начале хода бесплатен, принудительный занимает полный ход/5 минут. Автоматическое управление от «Системы устойчивости» ОЭ не расходует и прекращается при возвращении ясного сознания носителя. | M66: SYM-099 | N66: Q-SYM-041 | O66: 10 | P66: ACTIVE | Q66: =COUNTIF($A$6:$A$172,A66) -> 1
A67: SYM-100 | B67: ADVISER | C67: SYM-100 | D67: Система устойчивости | E67: PASSIVE_OR_AUTOMATIC | F67: AUTOMATED_ACCEPTED | G67: =TRUE() -> TRUE | H67: =FALSE() -> FALSE | I67: =FALSE() -> FALSE | J67: =FALSE() -> FALSE | K67: Разрешается по агрегированным карточкам canonicalBehaviorCards; в бою учитываются указанная цена действий, боевые защиты, координаты и ходы. [SYM-100] Система устойчивости автоматически передать управление Советнику без расхода ОЭ до возвращения ясного сознания носителя. | L67: Игрок не может воспользоваться способностью в мирной ситуации; активная команда доступна только в бою либо эффект не определён вне боя. | M67: SYM-100 | O67: 10 | P67: ACTIVE | Q67: =COUNTIF($A$6:$A$172,A67) -> 1
A68: SYM-101 | B68: ADVISER | C68: SYM-101 | D68: Дар мудрости | E68: HYBRID_COMMAND_AND_TRIGGER | F68: AUTOMATED_ACCEPTED | G68: =TRUE() -> TRUE | H68: =TRUE() -> TRUE | I68: =TRUE() -> TRUE | J68: =TRUE() -> TRUE | K68: Разрешается по агрегированным карточкам canonicalBehaviorCards; в бою учитываются указанная цена действий, боевые защиты, координаты и ходы. [SYM-101] Дар мудрости Нормативная база (действует во всей непротиворечащей части): передать интеллект Советника на одну проверку, затем отключить Советника на 12 часов. Приоритетные авторские дельты (заменяют только прямо пересекающиеся ветви): [Q-SYM-042] Для одной объявленной проверки Интеллекта значение I носителя складывается с текущим значением I Советника. Навык и остальные модификаторы используются у носителя; после проверки Советник отключается на 12 часов. | L68: Мирная операция/пассив разрешены явно. Для активной команды применяется Q-APP-001/002: отдельный пул боевых действий не создаётся, ОЭ и иные ресурсы списываются атомарно, немоделируемые контакт/дистанцию подтверждает мастер; боевой алгоритм карточки сохраняется в непротиворечащей части. [SYM-101] Дар мудрости Нормативная база (действует во всей непротиворечащей части): передать интеллект Советника на одну проверку, затем отключить Советника на 12 часов. Приоритетные авторские дельты (заменяют только прямо пересекающиеся ветви): [Q-SYM-042] Для одной объявленной проверки Интеллекта значение I носителя складывается с текущим значением I Советника. Навык и остальные модификаторы используются у носителя; после проверки Советник отключается на 12 часов. | M68: SYM-101 | N68: Q-SYM-042 | O68: 10 | P68: ACTIVE | Q68: =COUNTIF($A$6:$A$172,A68) -> 1
A69: SYM-103 | B69: TICK | C69: SYM-103 | D69: Кровопийца | E69: PASSIVE_OR_AUTOMATIC | F69: AUTOMATED_ACCEPTED | G69: =TRUE() -> TRUE | H69: =FALSE() -> FALSE | I69: =FALSE() -> FALSE | J69: =FALSE() -> FALSE | K69: Разрешается по агрегированным карточкам canonicalBehaviorCards; в бою учитываются указанная цена действий, боевые защиты, координаты и ходы. [SYM-103] Кровопийца Нормативная база (действует во всей непротиворечащей части): добавить L к урону. Приоритетные авторские дельты (заменяют только прямо пересекающиеся ветви): [Q-SYM-043] Бонус +L к урону получает любая успешная рукопашная атака, в которой правая рука непосредственно наносит удар или удерживает оружие, включая двуручное. Бонус применяется после попадания и пробития; атаки без участия правой руки его не получают. | L69: Игрок не может воспользоваться способностью в мирной ситуации; активная команда доступна только в бою либо эффект не определён вне боя. | M69: SYM-103 | N69: Q-SYM-043 | O69: 10 | P69: ACTIVE | Q69: =COUNTIF($A$6:$A$172,A69) -> 1
A70: SYM-104 | B70: TICK | C70: SYM-104 | D70: Вкус крови | E70: PLAYER_COMMAND | F70: AUTOMATED_ACCEPTED | G70: =TRUE() -> TRUE | H70: =TRUE() -> TRUE | I70: =TRUE() -> TRUE | J70: =TRUE() -> TRUE | K70: Разрешается по агрегированным карточкам canonicalBehaviorCards; в бою учитываются указанная цена действий, боевые защиты, координаты и ходы. [SYM-104] Вкус крови Нормативная база (действует во всей непротиворечащей части): без проверки раскрыть расу, значения всех характеристик, навыки, виды и уровни симбионтов. Приоритетные авторские дельты (заменяют только прямо пересекающиеся ветви): [Q-SYM-022] Раскрываются текущие итоговые значения семи характеристик S, D, M, Z, I, W и C с учётом действующих модификаторов. Базовые значения, текущие и максимальные HP/ОЭ не раскрываются, если способность не называет их отдельно. | L70: Мирная операция/пассив разрешены явно. Для активной команды применяется Q-APP-001/002: отдельный пул боевых действий не создаётся, ОЭ и иные ресурсы списываются атомарно, немоделируемые контакт/дистанцию подтверждает мастер; боевой алгоритм карточки сохраняется в непротиворечащей части. [SYM-104] Вкус крови Нормативная база (действует во всей непротиворечащей части): без проверки раскрыть расу, значения всех характеристик, навыки, виды и уровни симбионтов. Приоритетные авторские дельты (заменяют только прямо пересекающиеся ветви): [Q-SYM-022] Раскрываются текущие итоговые значения семи характеристик S, D, M, Z, I, W и C с учётом действующих модификаторов. Базовые значения, текущие и максимальные HP/ОЭ не раскрываются, если способность не называет их отдельно. | M70: SYM-104 | N70: Q-SYM-022 | O70: 10 | P70: ACTIVE | Q70: =COUNTIF($A$6:$A$172,A70) -> 1
A71: SYM-105 | B71: TICK | C71: SYM-105 | D71: Выстрел кровью | E71: PLAYER_COMMAND | F71: AUTOMATED_ACCEPTED | G71: =TRUE() -> TRUE | H71: =TRUE() -> TRUE | I71: =FALSE() -> FALSE | J71: =FALSE() -> FALSE | K71: Разрешается по агрегированным карточкам canonicalBehaviorCards; в бою учитываются указанная цена действий, боевые защиты, координаты и ходы. [SYM-105] Выстрел кровью R≥3: стандартная дальняя атака, пробитие=R+L, урон=R+L одной проверкой. R=2: нет эффекта. R=1: Клещ отключён на 1 час/6 ходов. | L71: Игрок не может воспользоваться способностью в мирной ситуации; активная команда доступна только в бою либо эффект не определён вне боя. | M71: SYM-105 | O71: 10 | P71: ACTIVE | Q71: =COUNTIF($A$6:$A$172,A71) -> 1
A72: SYM-106 | B72: TICK | C72: SYM-106 | D72: Выпустить когти | E72: PLAYER_COMMAND | F72: AUTOMATED_ACCEPTED | G72: =TRUE() -> TRUE | H72: =TRUE() -> TRUE | I72: =TRUE() -> TRUE | J72: =TRUE() -> TRUE | K72: Разрешается по агрегированным карточкам canonicalBehaviorCards; в бою учитываются указанная цена действий, боевые защиты, координаты и ходы. [SYM-106] Выпустить когти Нормативная база (действует во всей непротиворечащей части): по завершении вывести 5 когтей; для каждой атаки урон=R20+S_mod, пробитие=отдельный R20+L, точность модифицировать D, общий модификатор — рукопашный бой; без навыка штраф не применять. Разрешить втянуть когти без ОЭ. Приоритетные авторские дельты (заменяют только прямо пересекающиеся ветви): [Q-SYM-044] Выпускание когтей занимает одну полную минуту вне боя или весь боевой ход и стоит 30 ОЭ; дополнительное действие не добавляется. Когти остаются выпущенными до втягивания, которое бесплатно и возможно в любой момент; новое выпускание снова требует полной цены и времени. | L72: Мирная операция/пассив разрешены явно. Для активной команды применяется Q-APP-001/002: отдельный пул боевых действий не создаётся, ОЭ и иные ресурсы списываются атомарно, немоделируемые контакт/дистанцию подтверждает мастер; боевой алгоритм карточки сохраняется в непротиворечащей части. [SYM-106] Выпустить когти Нормативная база (действует во всей непротиворечащей части): по завершении вывести 5 когтей; для каждой атаки урон=R20+S_mod, пробитие=отдельный R20+L, точность модифицировать D, общий модификатор — рукопашный бой; без навыка штраф не применять. Разрешить втянуть когти без ОЭ. Приоритетные авторские дельты (заменяют только прямо пересекающиеся ветви): [Q-SYM-044] Выпускание когтей занимает одну полную минуту вне боя или весь боевой ход и стоит 30 ОЭ; дополнительное действие не добавляется. Когти остаются выпущенными до втягивания, которое бесплатно и возможно в любой момент; новое выпускание снова требует полной цены и времени. | M72: SYM-106 | N72: Q-SYM-044 | O72: 10 | P72: ACTIVE | Q72: =COUNTIF($A$6:$A$172,A72) -> 1
A73: SYM-107 | B73: TICK | C73: SYM-107 | D73: Гарпун | E73: PASSIVE_OR_AUTOMATIC | F73: AUTOMATED_ACCEPTED | G73: =TRUE() -> TRUE | H73: =FALSE() -> FALSE | I73: =FALSE() -> FALSE | J73: =FALSE() -> FALSE | K73: Разрешается по агрегированным карточкам canonicalBehaviorCards; в бою учитываются указанная цена действий, боевые защиты, координаты и ходы. [SYM-107] Гарпун Нормативная база (действует во всей непротиворечащей части): R≥3: выпустить гарпун; грузоподъёмность S×L кг; после попадания отдельным действием выбрать втянуть гарпун, подтянуть носителя либо попытаться притянуть цель. R=2: нет эффекта. R=1: выстрелить в случайную другую цель подходящей дальности, включая носителя. При потере гарпуна восстановление 8−L суток. Приоритетные авторские дельты (заменяют только прямо пересекающиеся ветви): [Q-SYM-045] После успешной активации Гарпун разрешается как стандартная дальняя атака с обычной проверкой точности. Прямого урона и отдельного пробития нет: при попадании он закрепляется на внешней поверхности цели или твёрдом объекте. За 1 действие можно втянуть пустой гарпун, подтянуть носителя к неподвижной опоре либо попытаться притянуть сопротивляющуюся цель встречной проверкой Силы. Объект тяжелее S×L кг переместить нельзя. | L73: Игрок не может воспользоваться способностью в мирной ситуации; активная команда доступна только в бою либо эффект не определён вне боя. | M73: SYM-107 | N73: Q-SYM-045 | O73: 10 | P73: ACTIVE | Q73: =COUNTIF($A$6:$A$172,A73) -> 1
