Workbook

Sheet 00_Паспорт
A1: SYMBIOSIS V7 — Effects & Diseases Registry v1.2
A2: Дополняющий реестр состояний, сочетаний и runtime-схем • 2026-07-31 • окончательные решения по COMB-031 и GAP-030
A4: Параметр | B4: Значение | C4: Статус | D4: Параметр | E4: Значение | F4: Статус | G4: Параметр | H4: Значение | I4: Статус | J4: Примечание
A5: Версия | B5: v1.2 | C5: PASS | D5: Семейств | E5: 24 | F5: PASS | G5: Типов эффектов | H5: 67 | I5: PASS | J5: Стабильные supplemental ID: 66 моделируемых типов + 1 явная граница NOT_MODELED
A6: Болезней | B6: 10 | C6: PASS | D6: Профилей ядов | E6: 8 | F6: PASS | G6: Травм/ран | H6: 8 | I6: PASS | J6: Неполные модели помечены явно
A7: Правил сочетаний | B7: 67 | C7: PASS | D7: Пар в матрице | E7: 300 | F7: PASS | G7: QA | H7: 98/98 PASS | I7: PASS | J7: Все исходные и новые сценарии пройдены
A8: Rules source index | B8: 306 | C8: PASS | D8: Payload JSON | E8: 185 | F8: PASS | G8: Baseline files | H8: 9 | I8: PASS | J8: Байты согласованных файлов не меняются
A9: Роль | B9: SUPPLEMENTAL_NORMATIVE_REGISTRY | C9: PASS | D9: Manifest v1.1 | E9: NOT_MODIFIED | F9: PASS | G9: Baseline tuple | H9: Rules v1.6 | Character-Skills-Symbionts v1.1 | Items v1.5_with_icons | Bestiary v1.3 | Sentient v1.2 | I9: PASS | J9: Реестр не включён задним числом в согласованный манифест
A10: Неразрешённые GAP | B10: 0 | C10: PASS | D10: Прочие локальные ветви | E10: 0 | F10: PASS | G10: Нарративный текст | H10: NO_MECHANICAL_EFFECT | I10: PASS | J10: Все авторские развилки закрыты; слепота явно исключена из модели приложения
A11: Итог | B11: READY_AS_SUPPLEMENT_V1.2 | C11: PASS | D11: Формат | E11: XLSX | F11: PASS | G11: Дата | H11: 2026-07-31 | I11: PASS | J11: Единый машинно-читаемый контракт
A13: Нормативные границы
A14: 1 | B14: Все девять файлов базовой линии являются неизменяемыми согласованными входами.
A15: 2 | B15: Этот реестр вводит ID, схему экземпляра и разрешители сочетаний, но не переписывает исходные Rule ID.
A16: 3 | B16: При расхождении приоритет имеет конкретная карточка согласованного Rules/Q&A; строка source index служит навигацией.
A17: 4 | B17: Авторских решений не требуется; NOT_MODELED является явной границей приложения, а не незакрытым GAP.

Sheet 01_Семейства
A1: Семейства состояний
A2: Закрытый уровень классификации для матрицы сочетаний. Он не заменяет конкретные EffectTypeID и частные Rule ID.
A4: FamilyCode | B4: Название | C4: Область | D4: State bucket | E4: Композиция по умолчанию | F4: Стадия ответа | G4: Rule refs | H4: ID count
A5: FAM-LIFECYCLE | B5: Жизненный цикл | C5: Тяжёлое ранение, таймер смерти, окончательная смерть | D5: actorFlags / currentEffects | E5: TERMINAL_OR_SOURCE_SPECIFIC | F5: AFTER_DAMAGE_RECALC | G5: CORE-152–156; CORE-182; CORE-222 | H5: =COUNTIF($A$5:$A$28,A5) -> 1
A6: FAM-CONSCIOUSNESS | B6: Сознание | C6: Бессознательность и сон | D6: actorFlags / currentEffects | E6: RESTRICTIONS_UNION | F6: AFTER_EACH_CONSEQUENCE | G6: CORE-061; CORE-103; MON-075 | H6: =COUNTIF($A$5:$A$28,A6) -> 1
A7: FAM-PHYSICAL_CONTROL | B7: Физический контроль | C7: Паралич, оглушение, захват, удержание, опутывание, кокон | D7: currentEffects | E7: RESTRICTIONS_UNION; MAX_ACTION_PENALTY; SOURCES_INDEPENDENT | F7: BEFORE_APPLY_CONTROL | G7: CORE-103; CORE-138; CORE-141; CORE-143–144 | H7: =COUNTIF($A$5:$A$28,A7) -> 1
A8: FAM-MENTAL_CONTROL | B8: Ментальный контроль | C8: Принуждение, бегство, внешний контроллер | D8: currentEffects / controlLease | E8: ONE_EFFECTIVE_CONTROLLER_BY_PRIORITY | F8: BEFORE_APPLY_CONTROL | G8: CORE-178; CORE-181; CORE-221; MON-038 | H8: =COUNTIF($A$5:$A$28,A8) -> 1
A9: FAM-MOBILITY_POSITION | B9: Положение и мобильность | C9: Сбит с ног, выгодная позиция, вынужденное перемещение | D9: currentEffects | E9: RESTRICTIONS_UNION | F9: COMMAND_FILTER | G9: CORE-138–144; MON-165 | H9: =COUNTIF($A$5:$A$28,A9) -> 1
A10: FAM-ACTION_ECONOMY | B10: Действия и серия | C10: Бонусы и штрафы действий, пропуск хода, следующий ход/серия | D10: currentEffects | E10: SOURCE_SPECIFIC; MIN_ZERO | F10: TURN_START_OR_CONSUME | G10: CORE-031; CORE-043–048; CORE-070; MON-150; MON-160 | H10: =COUNTIF($A$5:$A$28,A10) -> 1
A11: FAM-TRAUMA | B11: Травмы | C11: Зональные травмы и отключение конечности | D11: currentTraumas / derivedProjection | E11: SAME_ZONE_ADDITIVE; DIFFERENT_ZONE_INDEPENDENT | F11: AFTER_ACTUAL_DAMAGE | G11: CORE-117; CORE-119–121 | H11: =COUNTIF($A$5:$A$28,A11) -> 1
A12: FAM-WOUND_BLEEDING | B12: Раны и кровотечения | C12: Формализованная рана, кровотечение и профилактика через рану | D12: currentWounds | E12: PER_EVENT_PER_REGION; BLEEDING_PER_WOUND | F12: SOURCE_SPECIFIC | G12: CORE-059; CORE-063 | H12: =COUNTIF($A$5:$A$28,A12) -> 1
A13: FAM-DISEASE | B13: Болезни | C13: Назначенные мастером заболевания и их модификаторы | D13: currentEffects | E13: SAME_DISEASE_NO_STACK; DIFFERENT_DISEASE_ADD | F13: ASSIGN_REMOVE_RECALC | G13: MON-075–087; CQA-060 | H13: =COUNTIF($A$5:$A$28,A13) -> 1
A14: FAM-POISON | B14: Яды | C14: POISON payload, урон, дебафф, счётчик и зональный паралич | D14: currentEffects / activeCoatings | E14: PROFILE_SPECIFIC | F14: IMMUNITY_BEFORE_ROLL | G14: CORE-109; CORE-228; SYM-039; SYM-042; SYM-045 | H14: =COUNTIF($A$5:$A$28,A14) -> 1
A15: FAM-FIRE | B15: Огонь и горение | C15: Бинарное горение персонажа и огненные ответы | D15: currentEffects | E15: ONE_BINARY_STATE; MAX_REMAINING_DURATION | F15: BEFORE_APPLY_BURN | G15: CORE-112; CORE-114 | H15: =COUNTIF($A$5:$A$28,A15) -> 1
A16: FAM-PERIODIC_DAMAGE | B16: Периодический урон | C16: Автономные и поддерживаемые тики урона | D16: currentEffects | E16: PER_INSTANCE; ORDER_BY_CREATED_AT_UUID | F16: TIME_PHASE_1 | G16: CORE-101; AQA-024 | H16: =COUNTIF($A$5:$A$28,A16) -> 1
... A28: FAM-NARRATIVE | B28: Нарративная пометка | C28: Текст без механического изменения | D28: narrativeMarkers | E28: NO_MECHANICAL_EFFECT | F28: NONE | G28: AQ2-009; AQA-045 | H28: =COUNTIF($A$5:$A$28,A28) -> 1

Sheet 02_Типы_эффектов
A1: Каталог типов эффектов
A2: Стабильные EffectTypeID, целевой bucket, stack/removal policy и граница автоматизации.
A4: EffectTypeID | B4: Название | C4: FamilyCode | D4: State bucket | E4: Stack policy | F4: Timer policy | G4: Removal policy | H4: Семантика | I4: State writes | J4: Rule refs | K4: Automation | L4: Schema status | M4: ID count
A5: EFF-LIFE-DEAD | B5: Окончательная смерть | C5: FAM-LIFECYCLE | D5: actorFlags | E5: TERMINAL_SINGLETON | F5: SOURCE_SPECIFIC_OR_EXPLICIT | G5: NONE | H5: Терминальное состояние; обычное лечение и снятие эффекта не воскрешают | I5: dead=true | J5: CORE-155–156; CQA-001 | K5: AUTOMATED | L5: DEFINED | M5: =COUNTIF($A$5:$A$71,A5) -> 1
A6: EFF-LIFE-SEVERE_WOUND | B6: Тяжёлое ранение | C6: FAM-LIFECYCLE | D6: actorFlags | E6: SINGLETON | F6: SOURCE_SPECIFIC_OR_EXPLICIT | G6: SOURCE_OR_REANIMATION | H6: HP=0; специальная дееспособность возможна только по прямому источнику | I6: severeWound=true | J6: CORE-152; CORE-182; CORE-222 | K6: AUTOMATED | L6: DEFINED | M6: =COUNTIF($A$5:$A$71,A6) -> 1
A7: EFF-LIFE-DEATH_TIMER | B7: Таймер смерти | C7: FAM-LIFECYCLE | D7: currentEffects | E7: SINGLETON_BY_ACTOR | F7: SOURCE_SPECIFIC_OR_EXPLICIT | G7: EXPLICIT_REANIMATION_OR_EXPIRY | H7: Точный остаток хранится без округления интерфейсом | I7: deathTimer | J7: CORE-153–156 | K7: AUTOMATED | L7: DEFINED | M7: =COUNTIF($A$5:$A$71,A7) -> 1
A8: EFF-CONSCIOUS-UNCONSCIOUS | B8: Без сознания | C8: FAM-CONSCIOUSNESS | D8: actorFlags | E8: BINARY_SOURCE_TRACKED | F8: SOURCE_SPECIFIC_OR_EXPLICIT | G8: SOURCE_SPECIFIC | H8: Нет действий, реакций и активной защиты; броня работает | I8: unconscious=true | J8: CORE-103; MON-075; CORE-222 | K8: AUTOMATED | L8: DEFINED | M8: =COUNTIF($A$5:$A$71,A8) -> 1
A9: EFF-CONSCIOUS-SLEEP | B9: Сон | C9: FAM-CONSCIOUSNESS | D9: currentEffects | E9: PER_SOURCE | F9: SOURCE_SPECIFIC_OR_EXPLICIT | G9: DAMAGE_OR_SPECIFIC_ANTIDOTE | H9: Фармацевтический сон снимается любым уроном либо CORE-060 | I9: currentEffects[] | J9: CORE-061; CORE-103 | K9: AUTOMATED | L9: DEFINED | M9: =COUNTIF($A$5:$A$71,A9) -> 1
A10: EFF-CONTROL-PARALYSIS | B10: Паралич | C10: FAM-PHYSICAL_CONTROL | D10: currentEffects | E10: PER_SOURCE | F10: SOURCE_SPECIFIC_OR_EXPLICIT | G10: SOURCE_SPECIFIC | H10: Нет физических действий и активной защиты; чисто ментальные действия условно возможны | I10: currentEffects[] | J10: CORE-062; CORE-103; MON-150 | K10: AUTOMATED | L10: DEFINED | M10: =COUNTIF($A$5:$A$71,A10) -> 1
A11: EFF-CONTROL-STUN | B11: Оглушение | C11: FAM-PHYSICAL_CONTROL | D11: currentEffects | E11: PER_SOURCE | F11: SOURCE_SPECIFIC_OR_EXPLICIT | G11: EXPIRY_OR_CONTROL_CLEANSE | H11: Пропуск указанных ходов и реакций; частное правило может сохранить защиты | I11: currentEffects[] | J11: CORE-031; CORE-103 | K11: AUTOMATED | L11: DEFINED | M11: =COUNTIF($A$5:$A$71,A11) -> 1
A12: EFF-CONTROL-TURN_SKIP | B12: Пропуск хода | C12: FAM-ACTION_ECONOMY | D12: currentEffects | E12: PER_SOURCE | F12: SOURCE_SPECIFIC_OR_EXPLICIT | G12: CONSUME_NAMED_TURNS | H12: Нет боевых и небоевых действий; защита вне хода только по прямому разрешению | I12: currentEffects[] | J12: CORE-103; MON-124 | K12: AUTOMATED | L12: DEFINED | M12: =COUNTIF($A$5:$A$71,A12) -> 1
A13: EFF-CONTROL-GRAPPLE | B13: Захват | C13: FAM-PHYSICAL_CONTROL | D13: currentEffects | E13: PER_SOURCE_TARGET | F13: SOURCE_SPECIFIC_OR_EXPLICIT | G13: RELEASE_OR_SOURCE_BREAK | H13: Модификаторы CORE-138; число параллельных захватов ограничено свободными хватательными конечностями | I13: CaptureState | J13: CORE-138; MON-117; MON-127; MON-133 | K13: AUTOMATED | L13: DEFINED | M13: =COUNTIF($A$5:$A$71,A13) -> 1
A14: EFF-CONTROL-LIMB_HOLD | B14: Удержание конечности | C14: FAM-PHYSICAL_CONTROL | D14: currentEffects | E14: PER_SOURCE_LIMB | F14: SOURCE_SPECIFIC_OR_EXPLICIT | G14: CONTESTED_RELEASE | H14: Предусловие для травмирующего/болевого приёма | I14: currentEffects[] | J14: CORE-141 | K14: AUTOMATED | L14: DEFINED | M14: =COUNTIF($A$5:$A$71,A14) -> 1
A15: EFF-CONTROL-PAIN_HOLD | B15: Болевой приём | C15: FAM-PHYSICAL_CONTROL | D15: currentEffects | E15: PER_SOURCE | F15: SOURCE_SPECIFIC_OR_EXPLICIT | G15: CONTESTED_RELEASE | H15: При неуспешном самообладании доступны только защитные действия борьбы | I15: currentEffects[] | J15: CORE-143 | K15: AUTOMATED | L15: DEFINED | M15: =COUNTIF($A$5:$A$71,A15) -> 1
A16: EFF-CONTROL-CHOKE_HOLD | B16: Удушающий приём | C16: FAM-PHYSICAL_CONTROL | D16: currentEffects | E16: PER_SOURCE | F16: SOURCE_SPECIFIC_OR_EXPLICIT | G16: BREAK_GRAPPLE_OR_RELEASE | H16: Требует цепочки захват → выгодная позиция → удушение | I16: currentEffects[] | J16: CORE-144 | K16: AUTOMATED | L16: DEFINED | M16: =COUNTIF($A$5:$A$71,A16) -> 1
... A71: EFF-EQUIPMENT-STUCK | B71: Застрявшее оружие | C71: FAM-ITEM_STATE | D71: currentEffects | E71: PER_ITEM_TARGET | F71: SOURCE_SPECIFIC_OR_EXPLICIT | G71: ACTION_AND_CHECK | H71: Освобождение по конкретной карточке | I71: itemLink | J71: MON-129 | K71: AUTOMATED | L71: DEFINED | M71: =COUNTIF($A$5:$A$71,A71) -> 1

Sheet 03_Болезни
A1: Канонический каталог болезней
A2: Назначение и снятие выполняет мастер; disease modifiers могут опускать effectiveStat ниже 1, после чего применяется MON-075.
A4: DiseaseID | B4: Название | C4: Status | D4: Assignment | E4: Duration | F4: Stat modifiers JSON | G4: Check modifiers JSON | H4: Periodic | I4: Stacking | J4: Unconscious projection | K4: Effect family | L4: Is poison | M4: Rule refs | N4: Locator | O4: Примечание | P4: ID count
A5: DIS-POISONING | B5: Отравление | C5: ACTIVE | D5: GM_ASSIGN_REMOVE | E5: UNTIL_GM_REMOVE_OR_SPECIFIC_CURE | F5: {"S":-2,"M":-2} | G5: {} | H5: NONE | I5: NO_STACK_SAME_ID | J5: FOR_EACH_REDUCED_STAT_IF_EFFECTIVE_X_PLUS_EFFECTIVE_Z_LT_1 | K5: DISEASE | L5: false | M5: MON-076 | N5: Реестр правил!B230:AH230 | O5: Название не делает болезнь POISON | P5: =COUNTIF($A$5:$A$14,A5) -> 1
A6: DIS-RHINITIS | B6: Насморк | C6: ACTIVE | D6: GM_ASSIGN_REMOVE | E6: UNTIL_GM_REMOVE_OR_SPECIFIC_CURE | F6: {"M":-2} | G6: {} | H6: NONE | I6: NO_STACK_SAME_ID | J6: FOR_EACH_REDUCED_STAT_IF_EFFECTIVE_X_PLUS_EFFECTIVE_Z_LT_1 | K6: DISEASE | L6: false | M6: MON-077 | N6: Реестр правил!B231:AH231 | P6: =COUNTIF($A$5:$A$14,A6) -> 1
A7: DIS-FEVER | B7: Жар | C7: ACTIVE | D7: GM_ASSIGN_REMOVE | E7: UNTIL_GM_REMOVE_OR_SPECIFIC_CURE | F7: {"M":-10} | G7: {} | H7: NONE | I7: NO_STACK_SAME_ID | J7: FOR_EACH_REDUCED_STAT_IF_EFFECTIVE_X_PLUS_EFFECTIVE_Z_LT_1 | K7: DISEASE | L7: false | M7: MON-078 | N7: Реестр правил!B232:AH232 | P7: =COUNTIF($A$5:$A$14,A7) -> 1
A8: DIS-SCABIES | B8: Чесотка | C8: ACTIVE | D8: GM_ASSIGN_REMOVE | E8: UNTIL_GM_REMOVE_OR_SPECIFIC_CURE | F8: {"I":-4,"C":-4,"D":-2} | G8: {} | H8: NONE | I8: NO_STACK_SAME_ID | J8: FOR_EACH_REDUCED_STAT_IF_EFFECTIVE_X_PLUS_EFFECTIVE_Z_LT_1 | K8: DISEASE | L8: false | M8: MON-079 | N8: Реестр правил!B233:AH233 | P8: =COUNTIF($A$5:$A$14,A8) -> 1
A9: DIS-PNEUMONIA | B9: Пневмония | C9: ACTIVE | D9: GM_ASSIGN_REMOVE | E9: UNTIL_GM_REMOVE_OR_SPECIFIC_CURE | F9: {"M":-14,"S":-12,"D":-12} | G9: {} | H9: HP_MINUS_10_EACH_FULL_DAY | I9: NO_STACK_SAME_ID | J9: FOR_EACH_REDUCED_STAT_IF_EFFECTIVE_X_PLUS_EFFECTIVE_Z_LT_1 | K9: DISEASE | L9: false | M9: MON-080; MON-087 | N9: Реестр правил!B234:AH234 | O9: Периодический урон явно разрешён | P9: =COUNTIF($A$5:$A$14,A9) -> 1
A10: DIS-MIGRAINE | B10: Мигрень | C10: ACTIVE | D10: GM_ASSIGN_REMOVE | E10: UNTIL_GM_REMOVE_OR_SPECIFIC_CURE | F10: {"I":-6,"C":-2} | G10: {} | H10: NONE | I10: NO_STACK_SAME_ID | J10: FOR_EACH_REDUCED_STAT_IF_EFFECTIVE_X_PLUS_EFFECTIVE_Z_LT_1 | K10: DISEASE | L10: false | M10: MON-081 | N10: Реестр правил!B235:AH235 | P10: =COUNTIF($A$5:$A$14,A10) -> 1
A11: DIS-FLATULENCE | B11: Метеоризм | C11: ACTIVE | D11: GM_ASSIGN_REMOVE | E11: UNTIL_GM_REMOVE_OR_SPECIFIC_CURE | F11: {"C":-5} | G11: {"STEALTH":-5} | H11: NONE | I11: NO_STACK_SAME_ID | J11: FOR_EACH_REDUCED_STAT_IF_EFFECTIVE_X_PLUS_EFFECTIVE_Z_LT_1 | K11: DISEASE | L11: false | M11: MON-082 | N11: Реестр правил!B236:AH236 | P11: =COUNTIF($A$5:$A$14,A11) -> 1
A12: DIS-SKIN_GROWTHS | B12: Образования на коже | C12: ACTIVE | D12: GM_ASSIGN_REMOVE | E12: UNTIL_GM_REMOVE_OR_SPECIFIC_CURE | F12: {"C":-6} | G12: {} | H12: NONE | I12: NO_STACK_SAME_ID | J12: FOR_EACH_REDUCED_STAT_IF_EFFECTIVE_X_PLUS_EFFECTIVE_Z_LT_1 | K12: DISEASE | L12: false | M12: MON-083 | N12: Реестр правил!B237:AH237 | P12: =COUNTIF($A$5:$A$14,A12) -> 1
A13: DIS-ITCHY_SKIN_GROWTHS | B13: Чешущиеся образования на коже | C13: ACTIVE | D13: GM_ASSIGN_REMOVE | E13: UNTIL_GM_REMOVE_OR_SPECIFIC_CURE | F13: {"D":-3,"C":-6} | G13: {} | H13: NONE | I13: NO_STACK_SAME_ID | J13: FOR_EACH_REDUCED_STAT_IF_EFFECTIVE_X_PLUS_EFFECTIVE_Z_LT_1 | K13: DISEASE | L13: false | M13: MON-084 | N13: Реестр правил!B238:AH238 | P13: =COUNTIF($A$5:$A$14,A13) -> 1
A14: DIS-PESTILENCE | B14: Поветрие | C14: TRACE_ONLY | D14: SOURCE_SPECIFIC_TREATMENT | E14: SOURCE_RULE | F14: {"S":-3,"D":-3,"M":-3} | G14: {} | H14: DAILY_DEGRADATION; FLOWER_ON_DEATH | I14: SOURCE_SPECIFIC | J14: FOR_EACH_REDUCED_STAT_IF_EFFECTIVE_X_PLUS_EFFECTIVE_Z_LT_1 | K14: DISEASE | L14: false | M14: MON-058–060 | N14: Реестр правил (MON-058–060) | O14: Не автоматизируется; при любом S/D/M<1 тяжёлая рана | P14: =COUNTIF($A$5:$A$14,A14) -> 1

Sheet 04_Яды
A1: Профили ядов
A2: POISON отделён от болезни «Отравление». Абсолютный иммунитет применяется до бросков и payload.
A4: PoisonProfileID | B4: Название | C4: Effect family | D4: Source kind | E4: Payload kind | F4: Payload | G4: Repeat policy | H4: Stacking key | I4: Immunity stage | J4: Blocked payload | K4: Rule refs | L4: Примечание | M4: ID count
A5: POI-TAIPAN-DEADLY | B5: Смертельный яд Тайпана | C5: POISON | D5: SYMBIOTIC | E5: PERIODIC_DAMAGE | F5: R20/5+L per turn; duration R20/2 | G5: REPLACE_STRENGTH_AND_DURATION_RESTART | H5: TARGET | I5: IMMUNE_BEFORE_ROLL | J5: damage,state,counter,secondary effects | K5: SYM-039 | L5: Первый тик в конце следующего хода цели; оружие даёт половину урона за тик | M5: =COUNTIF($A$5:$A$12,A5) -> 1
A6: POI-TAIPAN-WEAKENING | B6: Ослабляющий яд Тайпана | C6: POISON | D6: SYMBIOTIC | E6: STAT_DEBUFF | F6: K=max(0,R20+L−Z); S/D/M decrease, each not below 1; duration R20/2 | G6: REPLACE_STRENGTH_AND_DURATION | H6: TARGET | I6: IMMUNE_BEFORE_ROLL | J6: absolute immunity: all; SYM-144: poison damage/control only | K6: SYM-042 | L6: Ослабление характеристик SYM-042 не является уроном или контролем и проходит через SYM-144 | M6: =COUNTIF($A$5:$A$12,A6) -> 1
A7: POI-TAIPAN-PARALYTIC | B7: Парализующий яд Тайпана | C7: POISON | D7: SYMBIOTIC | E7: LIMB_DISABLE | F7: if R20+L>Z: humanoid active limb; duration R20/3; nonhumanoid secondary paralysis skipped | G7: PER_DISTINCT_LIMB | H7: TARGET_LIMB | I7: IMMUNE_BEFORE_ROLL | J7: damage,state,counter,secondary effects | K7: SYM-045 | L7: На негуманоида паралич не действует; попадание и остальные последствия сохраняются При травме той же конечности числовые штрафы не складываются: применяется наиболее строгий; ограничения и снятие источников независимы. | M7: =COUNTIF($A$5:$A$12,A7) -> 1
A8: POI-VIVISECTOR-ENTRY | B8: Слизь Вивисектора при входе | C8: POISON | D8: CANONICAL | E8: DIRECT_POISON_DAMAGE | F8: R12+8 once on entry | G8: ONE_EVENT_DEDUP | H8: SOURCE_TARGET_ENTRY | I8: IMMUNE_BEFORE_ROLL | J8: damage,state,counter,secondary effects | K8: MON-098; MON-100 | L8: Дублирующие описания не должны дать двойной урон | M8: =COUNTIF($A$5:$A$12,A8) -> 1
A9: POI-VIVISECTOR-FUMES | B9: Ядовитые пары Вивисектора | C9: POISON | D9: CANONICAL | E9: POISON_DAMAGE_CHECK | F9: end target turn in 6m; R20+Z vs R20+12; fail R12 damage | G9: PER_SOURCE_TARGET_TURN | H9: SOURCE_TARGET | I9: IMMUNE_BEFORE_ROLL | J9: damage,state,counter,secondary effects | K9: MON-099 | L9: По одной проверке на каждого Вивисектора в конце хода цели; источники разрешаются отдельно в стабильном порядке | M9: =COUNTIF($A$5:$A$12,A9) -> 1
A10: POI-SWADDLER-SEQUENCE | B10: Яд Пеленальщицы | C10: POISON | D10: CANONICAL | E10: FAIL_COUNTER_CONTROL | F10: first fail −2 next series; second consecutive fail paralysis 5 own turns | G10: SUCCESS_RESETS; SECOND_REPLACES_FIRST | H10: SOURCE_TARGET | I10: IMMUNE_BEFORE_ROLL | J10: damage,state,counter,secondary effects | K10: MON-150 | L10: Счётчик отдельный для пары sourceId+targetId; успех сбрасывает только этот счётчик | M10: =COUNTIF($A$5:$A$12,A10) -> 1
A11: POI-FELIDA-NUMBING | B11: Плевок Фелиды-Тайпана | C11: POISON | D11: CANONICAL | E11: LIMB_DISABLE | F11: R20+7>Z; random active limb; duration round_half_up(R20/3), min 1 | G11: PER_LIMB | H11: TARGET_LIMB | I11: IMMUNE_BEFORE_ROLL | J11: damage,state,counter,secondary effects | K11: MON-169 | L11: Округление до ближайшего целого, ровно 0,5 вверх; положительная длительность минимум 1 ход При травме той же конечности числовые штрафы не складываются: применяется наиболее строгий; ограничения и снятие источников независимы. | M11: =COUNTIF($A$5:$A$12,A11) -> 1
A12: POI-FOOD_ALCOHOL | B12: Пищевое/алкогольное отравление | C12: POISON | D12: ORDINARY | E12: SOURCE_SPECIFIC | F12: By CORE-110 | G12: SOURCE_SPECIFIC | H12: TARGET | I12: IMMUNE_BEFORE_ROLL | J12: damage,state,counter,secondary effects | K12: CORE-110 | L12: Не смешивать с болезнью DIS-POISONING | M12: =COUNTIF($A$5:$A$12,A12) -> 1

Sheet 05_Травмы_и_раны
A1: Травмы, тяжёлые ранения и открытые раневые состояния
A2: Чётко разделены автоматизируемые травмы и состояния, для которых канон пока задаёт только снятие/упоминание.
A4: InjuryID | B4: Название | C4: Kind | D4: State bucket | E4: Trigger | F4: Payload | G4: Stacking | H4: Consequence | I4: Recovery | J4: Rule refs | K4: Примечание | L4: ID count
A5: TRM-LIMB | B5: Травма конечности | C5: TRAUMA | D5: currentTraumas | E5: R20+Z < actualDamage | F5: injury=max(0,round_math(R12−Z/3)) | G5: ADDITIVE_SAME_LIMB | H5: DISABLED_IF_TOTAL_GT_6 | I5: EXPLICIT_ABILITY_PROCEDURE_OR_GM | J5: CORE-117; CORE-119 | K5: Автоматического восстановления нет При временном онемении той же конечности применяется наиболее строгий числовой штраф; ограничения объединяются, снятие одного состояния не снимает другое. | L5: =COUNTIF($A$5:$A$12,A5) -> 1
A6: TRM-HEAD | B6: Травма головы | C6: TRAUMA | D6: currentTraumas | E6: R20+Z < actualDamage | F6: CORE-120 | G6: PER_EVENT | H6: SOURCE_SPECIFIC | I6: EXPLICIT_ABILITY_PROCEDURE_OR_GM | J6: CORE-117; CORE-120 | K6: Травма головы не создаёт слепоту: потеря зрения исключена из модели приложения | L6: =COUNTIF($A$5:$A$12,A6) -> 1
A7: TRM-TORSO | B7: Травма корпуса | C7: TRAUMA | D7: currentTraumas | E7: R20+Z < actualDamage | F7: one-time extra HP loss | G7: PER_EVENT | H7: NO_RECURSIVE_TRAUMA | I7: EXPLICIT_ABILITY_PROCEDURE_OR_GM | J7: CORE-117; CORE-121 | L7: =COUNTIF($A$5:$A$12,A7) -> 1
A8: TRM-MULTILIMB | B8: Травма многоконечного существа | C8: TRAUMA | D8: currentTraumas | E8: SOURCE_SPECIFIC | F8: not automated | G8: TRACE_ONLY | H8: UNSUPPORTED_ANATOMY_POLICY | I8: EXPLICIT_ABILITY_PROCEDURE_OR_GM | J8: CORE-122–124 | K8: Не автоматизируется | L8: =COUNTIF($A$5:$A$12,A8) -> 1
A9: WND-SEVERE | B9: Тяжёлое ранение | C9: WOUND | D9: actorFlags | E9: HP reaches 0 after protections | F9: severeWound=true; death timer | G9: SINGLETON | H9: NEW_HP_LOSS_GT_0_CAUSES_DEATH | I9: SOURCE_SPECIFIC | J9: CORE-152–156; CORE-182 | K9: Для обычных монстров одновременно unconscious | L9: =COUNTIF($A$5:$A$12,A9) -> 1
A10: WND-DEATH_TIMER | B10: Таймер смерти | C10: WOUND_TIMER | D10: currentEffects | E10: severe wound created | F10: D6 turns or D6×5m; exact remainder | G10: SINGLETON | H10: EXPIRE_TO_DEAD_OR_REANIMATE | I10: SOURCE_SPECIFIC | J10: CORE-153 | K10: Дубль ×4 применяется один раз | L10: =COUNTIF($A$5:$A$12,A10) -> 1
A11: WND-GENERIC | B11: Рана | C11: WOUND | D11: currentWounds | E11: SOURCE_HAS_CREATES_WOUND_OR_GM | F11: one wound per event with regionId | G11: PER_EVENT_AND_REGION | H11: FORMAL_WOUND_FOR_TARGETED_TREATMENT | I11: EXPLICIT_TREATMENT_OR_GM_ONLY | J11: CORE-059 | K11: Автоматического заживления нет | L11: =COUNTIF($A$5:$A$12,A11) -> 1
A12: WND-BLEEDING | B12: Кровотечение | C12: WOUND | D12: currentWounds | E12: SOURCE_EXPLICIT_DAMAGE_PER_TICK | F12: damagePerTick; tick=end_of_target_turn | G12: PER_WOUND_INSTANCE | H12: CORE-063_REMOVES_ALL | I12: CORE-063_OR_EXPLICIT_TREATMENT_OR_GM | J12: CORE-063 | K12: Значение урона по умолчанию не вводится | L12: =COUNTIF($A$5:$A$12,A12) -> 1

Sheet 06_Карта_источников
A1: Индекс источников состояний Rules v1.6
A2: 306 релевантных карточек. Нормализация FamilyCode служит поиску; исходная карточка остаётся нормативной.
A4: SourceMapID | B4: Rule ID | C4: Название | D4: Статус | E4: Режим реализации | F4: Категория | G4: Normalized family | H4: Mapping confidence | I4: State result | J4: Algorithm excerpt | K4: Exceptions excerpt | L4: Source ref | M4: Locator | N4: Source record SHA-256 | O4: Mapping role
A5: SRCMAP-001 | B5: CORE-004 | C5: Навык Единого «Идущий вслед за болью» | D5: Активно | E5: Реализовать в игровом ядре | F5: раса / пассивный навык. | G5: FAM-NARRATIVE | H5: LOW_CONFIDENCE_INDEX_ONLY | I5: постоянный навык и модификатор. | J5: навык добавляется автоматически, не занимает слот; к указанным проверкам +15. | K5: социальная механика пыток вне охвата; бонус к самообладанию при пожаре применяется по CORE-114. | L5: §3.2.6.1.1, стр. 48. | M5: Реестр правил!B3:AH3 | N5: b0e9fcdd3f9f348f8329b5b04d16a567fa4e8b245fd7240f04908993286d9e0d | O5: DISCOVERY_INDEX_ONLY; SOURCE_RULE_REMAINS_NORMATIVE
A6: SRCMAP-002 | B6: CORE-060 | C6: Отвар, приводящий в сознание | D6: Активно | E6: Реализовать в игровом ядре | F6: фармацевтика / реанимация. | G6: FAM-LIFECYCLE | H6: EXPLICIT | I6: цель в сознании, HP 1 при реанимации. | J6: снять тяжёлое ранение и установить HP=1; прекратить снотворное и паралитик без проверок; остановить таймер смерти. | K6: окончательную смерть не отменяет. | L6: §4.6, таблица 5, стр. 83–84; §5.5, стр. 104. | M6: Реестр правил!B29:AH29 | N6: 601c8f1bdcd89b6be61ee1a6222b775ed165e8fbd19da37184033efb39bcf3bf | O6: DISCOVERY_INDEX_ONLY; SOURCE_RULE_REMAINS_NORMATIVE
A7: SRCMAP-003 | B7: CORE-064 | C7: Восстанавливающий отвар | D7: Активно | E7: Реализовать в игровом ядре | F7: фармацевтика / лечение. | G7: FAM-PERIODIC_HEAL | H7: EXPLICIT | I7: восстановление HP. | J7: HP=min(maxHP,HP+25). | K7: не реанимирует CORE-156. | L7: §4.6, таблица 5, стр. 84. | M7: Реестр правил!B30:AH30 | N7: 028eace02932bf398b081979ef5258aa25bf25895fa1c3b411f3c9170345b094 | O7: DISCOVERY_INDEX_ONLY; SOURCE_RULE_REMAINS_NORMATIVE
A8: SRCMAP-004 | B8: CORE-066 | C8: Таблетка ночного зрения | D8: Активно | E8: Реализовать в игровом ядре | F8: фармацевтика / восприятие. | G8: FAM-SENSE_VISIBILITY | H8: EXPLICIT | I8: временный флаг зрения. | J8: на 2 часа видеть в темноте как днём; повтор обновляет 2 часа. | K8: числовые штрафы темноты в анализируемых разделах не заданы. | L8: §4.6, таблица 5, стр. 84. | M8: Реестр правил!B31:AH31 | N8: ed731903f84fe610458451f98e85f83f91c837935c1fcfdb0d79f7cb3bf46541 | O8: DISCOVERY_INDEX_ONLY; SOURCE_RULE_REMAINS_NORMATIVE
A9: SRCMAP-005 | B9: CORE-067 | C9: Таблетка бритвенных рефлексов | D9: Активно | E9: Реализовать в игровом ядре | F9: фармацевтика / бой. | G9: FAM-CHECK_MODIFIER | H9: EXPLICIT | I9: временный эффект. | J9: длительность max(1,round_math(R20/3)) личных ходов; на срок +3 к уклонению и парированию; повтор не складывает, обновляет срок. | K9: общая длительность CORE-101. | L9: §4.6, таблица 5, стр. 84. | M9: Реестр правил!B32:AH32 | N9: bcec27675d19ce1dd5adb2d541b3c32b0f60d214d84cb9ead460994d3382dff9 | O9: DISCOVERY_INDEX_ONLY; SOURCE_RULE_REMAINS_NORMATIVE
A10: SRCMAP-006 | B10: CORE-070 | C10: Таблетка куража | D10: Активно | E10: Реализовать в игровом ядре | F10: фармацевтика / серия. | G10: FAM-ACTION_ECONOMY | H10: EXPLICIT | I10: +1 боевое действие в текущем и каждом следующем личном ходу этого боя. | J10: seriesBonus=+1 до конца боя; если первая доза принята в собственный текущий ход после расчёта серии, немедленно увеличить combatActionsRemaining на 1; повтор не увеличивает бонус/остаток, лишь обновляет эффект (практически до того же конца боя). | K10: может увеличить серию выше 5. | L10: §4.6, таблица 5, стр. 84. | M10: Реестр правил!B33:AH33 | N10: 1666b9ad8f9b32be0bf6debe12627829e7ba9b383911ffcec37b741fb4bd88b3 | O10: DISCOVERY_INDEX_ONLY; SOURCE_RULE_REMAINS_NORMATIVE
A11: SRCMAP-007 | B11: CORE-071 | C11: Восстанавливающая таблетка | D11: Активно | E11: Реализовать в игровом ядре | F11: фармацевтика / периодическое лечение. | G11: FAM-PERIODIC_HEAL | H11: EXPLICIT | I11: периодический эффект. | J11: до конца боя в конце каждого хода HP=min(maxHP,HP+5); повтор не складывает. | K11: обычное лечение не действует в тяжёлом ранении. | L11: §4.6, таблица 5, стр. 84; §5.4.2.5, стр. 95. | M11: Реестр правил!B34:AH34 | N11: 6e11e3910324408b608761565f50dfe1a2f89fe07787d1e89f2847be923c5fe9 | O11: DISCOVERY_INDEX_ONLY; SOURCE_RULE_REMAINS_NORMATIVE
A12: SRCMAP-008 | B12: CORE-077 | C12: Границы HP и ОЭ | D12: Активно | E12: Реализовать в игровом ядре | F12: ресурс. | G12: FAM-NARRATIVE | H12: EXPLICIT | I12: валидный ресурс. | J12: clamp текущего в [0,currentMax]; избыточное восстановление пропадает; при временном снижении max текущий снизить до нового max, если выше; увеличение max само не восстанавливает текущий запас. | K12: тяжёлое ранение срабатывает при HP=0. | L12: §5.1, стр. 86. | M12: Реестр правил!B39:AH39 | N12: f0f2e107bea3271fe561a8333ad17850d762866599f264632582317be9e910ee | O12: DISCOVERY_INDEX_ONLY; SOURCE_RULE_REMAINS_NORMATIVE
A13: SRCMAP-009 | B13: CORE-079 | C13: Порядок применения модификаторов характеристики | D13: Активно | E13: Реализовать в игровом ядре | F13: характеристика / вычисление. | G13: FAM-STAT_MODIFIER | H13: EXPLICIT | I13: итоговая характеристика. | J13: 1) постоянное значение; 2) временные прибавки/штрафы; 3) умножение/деление; 4) точная установка и явно названные min/max. «Становится равной/до» применяется после обычных модификаторов. | K13: при несовместимых установках — более конкретная, при равной конкретности более ограничительная. | L13: §5.1, стр. 87. | M13: Реестр правил!B41:AH41 | N13: 882daef991d1af28f3c507c642a828526e6a1214872f70b7e0c6350ffec41305 | O13: DISCOVERY_INDEX_ONLY; SOURCE_RULE_REMAINS_NORMATIVE
A14: SRCMAP-010 | B14: CORE-086 | C14: Начало и окончание боя | D14: Активно | E14: Реализовать в игровом ядре | F14: бой / жизненный цикл. | G14: FAM-LIFECYCLE | H14: EXPLICIT | I14: combat.active и границы эффектов «до конца боя». | J14: открыть бой; завершить, если полный круг никто не совершал и не готовил враждебных действий либо одна сторона утратила возможность или намерение продолжать. | K14: решение о завершении сцены принимает мастер. | L14: §5.4.1, стр. 92–93. | M14: Реестр правил!B45:AH45 | N14: 55256a39e88ca9bc9b7e267da6efc1538417f4f85df7d22821e51ebcc35d4d9e | O14: DISCOVERY_INDEX_ONLY; SOURCE_RULE_REMAINS_NORMATIVE
A15: SRCMAP-011 | B15: CORE-103 | C15: Состояния без сознания, паралич, оглушение, пропуск | D15: Активно | E15: Реализовать в игровом ядре | F15: бой / состояние. | G15: FAM-CONSCIOUSNESS | H15: EXPLICIT | I15: фильтр допустимых команд и таймер. | J15: без сознания — нет действий, реакций, активных защит, броня работает; парализован — нет физических действий/активных защит, ментальные возможны только без речи/движения/управления телом; оглушён — пропускает указанные собственные ходы и реакции, если эффект не разрешил защиты; «пропускает ход» — не получает боевых/небоевых, защиты вне хода только при прямом разрешении. | K15: конкретный эффект может сохранить дееспособность. | L15: §5.4.2.5, стр. 95–96. | M15: Реестр правил!B57:AH57 | N15: 071cedd0f66688a1eaf597bbec9eaf47c0c25457965bc261f12c90258b80398b | O15: DISCOVERY_INDEX_ONLY; SOURCE_RULE_REMAINS_NORMATIVE
... A310: SRCMAP-306 | B310: CORE-228 | C310: Типизация яда и абсолютный иммунитет | D310: Активно | E310: Реализовать в игровом ядре | F310: эффект / яд. | G310: FAM-IMMUNITY_RESISTANCE | H310: EXPLICIT | I310: Симбиотический яд не обходит абсолютный иммунитет. | J310: Каждый яд обязан иметь effectFamily=POISON и poisonSourceKind=ORDINARY|NATURAL|ARTIFICIAL|SYMBIOTIC|CANONICAL. Ответ IMMUNE_BEFORE_ROLL с SourceScope=ANY полностью отклоняет прямой урон, состояние, счётчик и вторичные ядовитые эффекты до бросков. Крысюк и Гигантская жаба имеют такой ответ ко всем источникам. | K310: Болезнь с названием «Отравление» без effectFamily=POISON остаётся болезнью; облако Скунса не считается ядом без явного тега. | L310: Предразработочный QA и прямые ответы пользователя 2026-07-29 | M310: Реестр правил!B734:AH734 | N310: 9cdf3f652540a435de8ba35d3dd5dc9a26e1c9ef97358ab7010b2ced23b1eed2 | O310: DISCOVERY_INDEX_ONLY; SOURCE_RULE_REMAINS_NORMATIVE

Sheet 07_Правила_сочетаний
A1: Явные правила сочетаний состояний
A2: Частные разрешители сильнее общего coexistence. Все авторские ветви определены; исключённые механики имеют статус NOT_MODELED.
A4: CombinationRuleID | B4: Левый селектор | C4: Правый селектор | D4: Результат | E4: Приоритет | F4: Stack / timer | G4: Removal / transition / note | H4: Rule refs | I4: Left family | J4: Right family | K4: Automation | L4: Status | M4: ID count
A5: COMB-001 | B5: same effect name, numeric | C5: same effect name, numeric | D5: STRONGEST_MAGNITUDE_APPLIES; TIMERS_INDEPENDENT | E5: SPECIFIC_RULE_OVERRIDES_DEFAULT_COEXISTENCE | F5: STRONGEST_MAGNITUDE_APPLIES; TIMERS_INDEPENDENT | G5: После сильнейшего автоматически действует следующий активный | H5: CORE-080 | I5: FAM-STAT_MODIFIER | J5: FAM-STAT_MODIFIER | K5: AUTOMATED | L5: DEFINED | M5: =COUNTIF($A$5:$A$69,A5) -> 1
A6: COMB-002 | B6: same pharmaceutical effect | C6: repeat dose | D6: REFRESH_DURATION; DO_NOT_INCREASE_VALUE | E6: SPECIFIC_RULE_OVERRIDES_DEFAULT_COEXISTENCE | F6: REFRESH_DURATION; DO_NOT_INCREASE_VALUE | G6: Специальное правило сильнее общего стека | H6: CORE-058 | I6: FAM-PREPARED_EFFECT | J6: FAM-STAT_MODIFIER | K6: AUTOMATED | L6: DEFINED | M6: =COUNTIF($A$5:$A$69,A6) -> 1
A7: COMB-003 | B7: same diseaseId | C7: same diseaseId | D7: NO_DUPLICATE_PENALTIES | E7: SPECIFIC_RULE_OVERRIDES_DEFAULT_COEXISTENCE | F7: NO_DUPLICATE_PENALTIES | G7: Один экземпляр/один набор штрафов | H7: MON-085 | I7: FAM-DISEASE | J7: FAM-DISEASE | K7: AUTOMATED | L7: DEFINED | M7: =COUNTIF($A$5:$A$69,A7) -> 1
A8: COMB-004 | B8: different diseaseId | C8: different diseaseId | D8: COEXIST; MODIFIERS_ADD | E8: SPECIFIC_RULE_OVERRIDES_DEFAULT_COEXISTENCE | F8: COEXIST; MODIFIERS_ADD | G8: Периодика каждой болезни остаётся собственной | H8: MON-085 | I8: FAM-DISEASE | J8: FAM-DISEASE | K8: AUTOMATED | L8: DEFINED | M8: =COUNTIF($A$5:$A$69,A8) -> 1
A9: COMB-005 | B9: disease modifiers | C9: other stat modifiers | D9: APPLY_CORE_079_PIPELINE; RECALC_DERIVED_STATES | E9: SPECIFIC_RULE_OVERRIDES_DEFAULT_COEXISTENCE | F9: APPLY_CORE_079_PIPELINE; RECALC_DERIVED_STATES | G9: Порог бессознательности проверяется после пересчёта | H9: CORE-079; MON-075 | I9: FAM-DISEASE | J9: FAM-STAT_MODIFIER | K9: AUTOMATED | L9: DEFINED | M9: =COUNTIF($A$5:$A$69,A9) -> 1
A10: COMB-006 | B10: DIS-POISONING | C10: POISON immunity | D10: DISEASE_REMAINS; NOT_A_POISON_WITHOUT_TAG | E10: SPECIFIC_RULE_OVERRIDES_DEFAULT_COEXISTENCE | F10: DISEASE_REMAINS; NOT_A_POISON_WITHOUT_TAG | G10: Совпадение бытового названия не меняет effectFamily | H10: CORE-228; MON-076 | I10: FAM-DISEASE | J10: FAM-IMMUNITY_RESISTANCE | K10: AUTOMATED | L10: DEFINED | M10: =COUNTIF($A$5:$A$69,A10) -> 1
A11: COMB-007 | B11: physical hit payload | C11: poison payload with absolute immunity | D11: KEEP_VALID_PHYSICAL_PAYLOAD; DROP_POISON_DAMAGE_STATE_COUNTER_SECONDARY | E11: SPECIFIC_RULE_OVERRIDES_DEFAULT_COEXISTENCE | F11: KEEP_VALID_PHYSICAL_PAYLOAD; DROP_POISON_DAMAGE_STATE_COUNTER_SECONDARY | G11: Иммунитет обрабатывается до бросков яда | H11: CORE-228 | I11: FAM-POISON | J11: FAM-IMMUNITY_RESISTANCE | K11: AUTOMATED | L11: DEFINED | M11: =COUNTIF($A$5:$A$69,A11) -> 1
A12: COMB-008 | B12: existing poison | C12: newly gained poison immunity | D12: NO_AUTOMATIC_CLEANSE_UNLESS_SOURCE_SAYS_SO | E12: SPECIFIC_RULE_OVERRIDES_DEFAULT_COEXISTENCE | F12: NO_AUTOMATIC_CLEANSE_UNLESS_SOURCE_SAYS_SO | G12: Иммунитет по умолчанию предотвращает наложение | H12: CORE-228; CORE-080 | I12: FAM-POISON | J12: FAM-IMMUNITY_RESISTANCE | K12: AUTOMATED | L12: DEFINED | M12: =COUNTIF($A$5:$A$69,A12) -> 1
A13: COMB-009 | B13: Taipan deadly/weakening poison | C13: same poison again | D13: REPLACE_STRENGTH_AND_DURATION; RESTART_TIMER | E13: SPECIFIC_RULE_OVERRIDES_DEFAULT_COEXISTENCE | F13: REPLACE_STRENGTH_AND_DURATION; RESTART_TIMER | G13: Не складывать два пакета одного профиля | H13: SYM-039; SYM-042 | I13: FAM-POISON | J13: FAM-POISON | K13: AUTOMATED | L13: DEFINED | M13: =COUNTIF($A$5:$A$69,A13) -> 1
A14: COMB-010 | B14: Taipan paralytic poison on limb A | C14: same profile on limb B | D14: COEXIST_PER_DISTINCT_LIMB | E14: SPECIFIC_RULE_OVERRIDES_DEFAULT_COEXISTENCE | F14: COEXIST_PER_DISTINCT_LIMB | G14: Уже онемевшая конечность исключается из выбора | H14: SYM-045 | I14: FAM-POISON | J14: FAM-TRAUMA | K14: AUTOMATED | L14: DEFINED | M14: =COUNTIF($A$5:$A$69,A14) -> 1
A15: COMB-011 | B15: Taipan suppressed/disabled | C15: already injected poison | D15: POISON_CONTINUES_TO_EXPIRY | E15: SPECIFIC_RULE_OVERRIDES_DEFAULT_COEXISTENCE | F15: POISON_CONTINUES_TO_EXPIRY | G15: Подавление прекращает производство, не автономный payload | H15: SYM-038; CQA-002 | I15: FAM-SYMBIONT_STATE | J15: FAM-POISON | K15: AUTOMATED | L15: DEFINED | M15: =COUNTIF($A$5:$A$69,A15) -> 1
A16: COMB-012 | B16: burning | C16: new burning | D16: ONE_BINARY_STATE; remaining=max(current,new); damagePerTick=max(current,new); NO_INSTANT_SECOND_TICK | E16: SPECIFIC_RULE_OVERRIDES_DEFAULT_COEXISTENCE | F16: ONE_BINARY_STATE; remaining=max(current,new); damagePerTick=max(current,new); NO_INSTANT_SECOND_TICK | G16: Повторное горение не создаёт немедленный тик | H16: CORE-112 | I16: FAM-FIRE | J16: FAM-FIRE | K16: AUTOMATED | L16: DEFINED | M16: =COUNTIF($A$5:$A$69,A16) -> 1
... A69: COMB-065 | B69: dead actor | C69: stored effects on corpse/resurrection | D69: ON_FINAL_DEATH TERMINATE_TEMPORARY_AND_CONTROL; PRESERVE_TRAUMAS_WOUNDS_ITEM_STATE_INVENTORY_SYMBIONTS; NO_RESUME_ON_RESURRECTION | E69: SPECIFIC_RULE_OVERRIDES_DEFAULT_COEXISTENCE | F69: ON_FINAL_DEATH TERMINATE_TEMPORARY_AND_CONTROL; PRESERVE_TRAUMAS_WOUNDS_ITEM_STATE_INVENTORY_SYMBIONTS; NO_RESUME_ON_RESURRECTION | G69: Сохранённые состояния трупа не возобновляют завершённые временные эффекты | H69: CQA-001; AQA-024 | I69: FAM-LIFECYCLE | J69: FAM-SOURCE_LINK | K69: AUTOMATED | L69: DEFINED | M69: =COUNTIF($A$5:$A$69,A69) -> 1
A70: COMB-066 | B70: multiple MON-159 psi-protection charges | C70: same defensive check | D70: CONSUME_ONE_EARLIEST_CHARGE; OTHER_SOURCE_CHARGES_REMAIN | E70: SPECIFIC_RULE_OVERRIDES_DEFAULT_COEXISTENCE | F70: CONSUME_ONE_EARLIEST_CHARGE; OTHER_SOURCE_CHARGES_REMAIN | G70: Бонусы не складываются на одной проверке | H70: MON-159 | I70: FAM-CHECK_MODIFIER | J70: FAM-CHECK_MODIFIER | K70: AUTOMATED | L70: DEFINED | M70: =COUNTIF($A$5:$A$71,A70) -> 1
A71: COMB-067 | B71: multiple Vivisector fumes | C71: same target at end of target turn | D71: ONE_CHECK_PER_SOURCE; STABLE_CREATED_AT_THEN_UUID; NO_ZONE_MERGE | E71: SPECIFIC_RULE_OVERRIDES_DEFAULT_COEXISTENCE | F71: ONE_CHECK_PER_SOURCE; STABLE_CREATED_AT_THEN_UUID; NO_ZONE_MERGE | G71: Урон и зоны каждого источника разрешаются отдельно | H71: MON-099; AQA-024 | I71: FAM-POISON | J71: FAM-POISON | K71: AUTOMATED | L71: DEFINED | M71: =COUNTIF($A$5:$A$71,A71) -> 1

Sheet 08_Матрица_семейств
A1: Полная матрица сочетаний семейств
A2: 24 семейств → 300 неупорядоченных пар с диагональю. Без override разные семейства сосуществуют и проходят обычные pipelines.
A4: PairID | B4: Left family | C4: Right family | D4: Default outcome | E4: Resolver | F4: CombinationRuleIDs | G4: Canonical basis | H4: Automation | I4: Status | J4: Pair count
A5: PAIR-001 | B5: FAM-LIFECYCLE | C5: FAM-LIFECYCLE | D5: TYPE_AND_SOURCE_SPECIFIC | E5: APPLY_LISTED_COMBINATION_RULES | F5: COMB-023 | G5: CORE-154 | H5: DEFAULT_OR_EXPLICIT | I5: DEFINED | J5: =COUNTIFS($B$5:$B$304,B5,$C$5:$C$304,C5) -> 1
A6: PAIR-002 | B6: FAM-LIFECYCLE | C6: FAM-CONSCIOUSNESS | D6: COEXIST_AND_COMPOSE_BY_DEFAULT | E6: APPLY_LISTED_COMBINATION_RULES | F6: COMB-060; COMB-061 | G6: CORE-222; CORE-152; CORE-103 | H6: DEFAULT_OR_EXPLICIT | I6: DEFINED | J6: =COUNTIFS($B$5:$B$304,B6,$C$5:$C$304,C6) -> 1
A7: PAIR-003 | B7: FAM-LIFECYCLE | C7: FAM-PHYSICAL_CONTROL | D7: COEXIST_AND_COMPOSE_BY_DEFAULT | E7: UNION_RESTRICTIONS_AND_RUN_NORMAL_PIPELINES | G7: CORE-079; CORE-080 | H7: DEFAULT_OR_EXPLICIT | I7: DEFINED | J7: =COUNTIFS($B$5:$B$304,B7,$C$5:$C$304,C7) -> 1
A8: PAIR-004 | B8: FAM-LIFECYCLE | C8: FAM-MENTAL_CONTROL | D8: COEXIST_AND_COMPOSE_BY_DEFAULT | E8: UNION_RESTRICTIONS_AND_RUN_NORMAL_PIPELINES | G8: CORE-079; CORE-080 | H8: DEFAULT_OR_EXPLICIT | I8: DEFINED | J8: =COUNTIFS($B$5:$B$304,B8,$C$5:$C$304,C8) -> 1
A9: PAIR-005 | B9: FAM-LIFECYCLE | C9: FAM-MOBILITY_POSITION | D9: COEXIST_AND_COMPOSE_BY_DEFAULT | E9: UNION_RESTRICTIONS_AND_RUN_NORMAL_PIPELINES | G9: CORE-079; CORE-080 | H9: DEFAULT_OR_EXPLICIT | I9: DEFINED | J9: =COUNTIFS($B$5:$B$304,B9,$C$5:$C$304,C9) -> 1
A10: PAIR-006 | B10: FAM-LIFECYCLE | C10: FAM-ACTION_ECONOMY | D10: COEXIST_AND_COMPOSE_BY_DEFAULT | E10: UNION_RESTRICTIONS_AND_RUN_NORMAL_PIPELINES | G10: CORE-079; CORE-080 | H10: DEFAULT_OR_EXPLICIT | I10: DEFINED | J10: =COUNTIFS($B$5:$B$304,B10,$C$5:$C$304,C10) -> 1
A11: PAIR-007 | B11: FAM-LIFECYCLE | C11: FAM-TRAUMA | D11: COEXIST_AND_COMPOSE_BY_DEFAULT | E11: APPLY_LISTED_COMBINATION_RULES | F11: COMB-062 | G11: CORE-219; CORE-222 | H11: DEFAULT_OR_EXPLICIT | I11: DEFINED | J11: =COUNTIFS($B$5:$B$304,B11,$C$5:$C$304,C11) -> 1
A12: PAIR-008 | B12: FAM-LIFECYCLE | C12: FAM-WOUND_BLEEDING | D12: COEXIST_AND_COMPOSE_BY_DEFAULT | E12: UNION_RESTRICTIONS_AND_RUN_NORMAL_PIPELINES | G12: CORE-079; CORE-080 | H12: DEFAULT_OR_EXPLICIT | I12: DEFINED | J12: =COUNTIFS($B$5:$B$304,B12,$C$5:$C$304,C12) -> 1
A13: PAIR-009 | B13: FAM-LIFECYCLE | C13: FAM-DISEASE | D13: COEXIST_AND_COMPOSE_BY_DEFAULT | E13: UNION_RESTRICTIONS_AND_RUN_NORMAL_PIPELINES | G13: CORE-079; CORE-080 | H13: DEFAULT_OR_EXPLICIT | I13: DEFINED | J13: =COUNTIFS($B$5:$B$304,B13,$C$5:$C$304,C13) -> 1
A14: PAIR-010 | B14: FAM-LIFECYCLE | C14: FAM-POISON | D14: COEXIST_AND_COMPOSE_BY_DEFAULT | E14: UNION_RESTRICTIONS_AND_RUN_NORMAL_PIPELINES | G14: CORE-079; CORE-080 | H14: DEFAULT_OR_EXPLICIT | I14: DEFINED | J14: =COUNTIFS($B$5:$B$304,B14,$C$5:$C$304,C14) -> 1
A15: PAIR-011 | B15: FAM-LIFECYCLE | C15: FAM-FIRE | D15: COEXIST_AND_COMPOSE_BY_DEFAULT | E15: UNION_RESTRICTIONS_AND_RUN_NORMAL_PIPELINES | G15: CORE-079; CORE-080 | H15: DEFAULT_OR_EXPLICIT | I15: DEFINED | J15: =COUNTIFS($B$5:$B$304,B15,$C$5:$C$304,C15) -> 1
A16: PAIR-012 | B16: FAM-LIFECYCLE | C16: FAM-PERIODIC_DAMAGE | D16: COEXIST_AND_COMPOSE_BY_DEFAULT | E16: APPLY_LISTED_COMBINATION_RULES | F16: COMB-025; COMB-028 | G16: CORE-155; AQA-024 | H16: DEFAULT_OR_EXPLICIT | I16: DEFINED | J16: =COUNTIFS($B$5:$B$304,B16,$C$5:$C$304,C16) -> 1
A17: PAIR-013 | B17: FAM-LIFECYCLE | C17: FAM-PERIODIC_HEAL | D17: COEXIST_AND_COMPOSE_BY_DEFAULT | E17: APPLY_LISTED_COMBINATION_RULES | F17: COMB-021; COMB-026; COMB-057 | G17: CORE-071; CORE-156; CORE-156; AQA-028; CORE-071 | H17: DEFAULT_OR_EXPLICIT | I17: DEFINED | J17: =COUNTIFS($B$5:$B$304,B17,$C$5:$C$304,C17) -> 1
A18: PAIR-014 | B18: FAM-LIFECYCLE | C18: FAM-STAT_MODIFIER | D18: COEXIST_AND_COMPOSE_BY_DEFAULT | E18: UNION_RESTRICTIONS_AND_RUN_NORMAL_PIPELINES | G18: CORE-079; CORE-080 | H18: DEFAULT_OR_EXPLICIT | I18: DEFINED | J18: =COUNTIFS($B$5:$B$304,B18,$C$5:$C$304,C18) -> 1
A19: PAIR-015 | B19: FAM-LIFECYCLE | C19: FAM-CHECK_MODIFIER | D19: COEXIST_AND_COMPOSE_BY_DEFAULT | E19: APPLY_LISTED_COMBINATION_RULES | F19: COMB-024 | G19: CORE-069 | H19: DEFAULT_OR_EXPLICIT | I19: DEFINED | J19: =COUNTIFS($B$5:$B$304,B19,$C$5:$C$304,C19) -> 1
A20: PAIR-016 | B20: FAM-LIFECYCLE | C20: FAM-SENSE_VISIBILITY | D20: COEXIST_AND_COMPOSE_BY_DEFAULT | E20: UNION_RESTRICTIONS_AND_RUN_NORMAL_PIPELINES | G20: CORE-079; CORE-080 | H20: DEFAULT_OR_EXPLICIT | I20: DEFINED | J20: =COUNTIFS($B$5:$B$304,B20,$C$5:$C$304,C20) -> 1
A21: PAIR-017 | B21: FAM-LIFECYCLE | C21: FAM-FORM_MODE | D21: COEXIST_AND_COMPOSE_BY_DEFAULT | E21: UNION_RESTRICTIONS_AND_RUN_NORMAL_PIPELINES | G21: CORE-079; CORE-080 | H21: DEFAULT_OR_EXPLICIT | I21: DEFINED | J21: =COUNTIFS($B$5:$B$304,B21,$C$5:$C$304,C21) -> 1
A22: PAIR-018 | B22: FAM-LIFECYCLE | C22: FAM-SYMBIONT_STATE | D22: COEXIST_AND_COMPOSE_BY_DEFAULT | E22: UNION_RESTRICTIONS_AND_RUN_NORMAL_PIPELINES | G22: CORE-079; CORE-080 | H22: DEFAULT_OR_EXPLICIT | I22: DEFINED | J22: =COUNTIFS($B$5:$B$304,B22,$C$5:$C$304,C22) -> 1
A23: PAIR-019 | B23: FAM-LIFECYCLE | C23: FAM-IMMUNITY_RESISTANCE | D23: COEXIST_AND_COMPOSE_BY_DEFAULT | E23: UNION_RESTRICTIONS_AND_RUN_NORMAL_PIPELINES | G23: CORE-079; CORE-080 | H23: DEFAULT_OR_EXPLICIT | I23: DEFINED | J23: =COUNTIFS($B$5:$B$304,B23,$C$5:$C$304,C23) -> 1
A24: PAIR-020 | B24: FAM-LIFECYCLE | C24: FAM-INFECTION | D24: COEXIST_AND_COMPOSE_BY_DEFAULT | E24: UNION_RESTRICTIONS_AND_RUN_NORMAL_PIPELINES | G24: CORE-079; CORE-080 | H24: DEFAULT_OR_EXPLICIT | I24: DEFINED | J24: =COUNTIFS($B$5:$B$304,B24,$C$5:$C$304,C24) -> 1
A25: PAIR-021 | B25: FAM-LIFECYCLE | C25: FAM-PREPARED_EFFECT | D25: COEXIST_AND_COMPOSE_BY_DEFAULT | E25: APPLY_LISTED_COMBINATION_RULES | F25: COMB-022; COMB-027; COMB-046 | G25: CORE-060; CORE-156; MON-114–115; CORE-222; Q-CORE-063; CORE-153 | H25: DEFAULT_OR_EXPLICIT | I25: DEFINED | J25: =COUNTIFS($B$5:$B$304,B25,$C$5:$C$304,C25) -> 1
A26: PAIR-022 | B26: FAM-LIFECYCLE | C26: FAM-SOURCE_LINK | D26: COEXIST_AND_COMPOSE_BY_DEFAULT | E26: APPLY_LISTED_COMBINATION_RULES | F26: COMB-040; COMB-065 | G26: CQA-002; AQ2-020; CQA-001; AQA-024 | H26: DEFAULT_OR_EXPLICIT | I26: DEFINED | J26: =COUNTIFS($B$5:$B$304,B26,$C$5:$C$304,C26) -> 1
A27: PAIR-023 | B27: FAM-LIFECYCLE | C27: FAM-ITEM_STATE | D27: COEXIST_AND_COMPOSE_BY_DEFAULT | E27: UNION_RESTRICTIONS_AND_RUN_NORMAL_PIPELINES | G27: CORE-079; CORE-080 | H27: DEFAULT_OR_EXPLICIT | I27: DEFINED | J27: =COUNTIFS($B$5:$B$304,B27,$C$5:$C$304,C27) -> 1
A28: PAIR-024 | B28: FAM-LIFECYCLE | C28: FAM-NARRATIVE | D28: COEXIST_AND_COMPOSE_BY_DEFAULT | E28: UNION_RESTRICTIONS_AND_RUN_NORMAL_PIPELINES | G28: CORE-079; CORE-080 | H28: DEFAULT_OR_EXPLICIT | I28: DEFINED | J28: =COUNTIFS($B$5:$B$304,B28,$C$5:$C$304,C28) -> 1
A29: PAIR-025 | B29: FAM-CONSCIOUSNESS | C29: FAM-CONSCIOUSNESS | D29: TYPE_AND_SOURCE_SPECIFIC | E29: APPLY_EFFECT_TYPE_STACK_POLICY | G29: CORE-079; CORE-080 | H29: DEFAULT_OR_EXPLICIT | I29: DEFINED | J29: =COUNTIFS($B$5:$B$304,B29,$C$5:$C$304,C29) -> 1
A30: PAIR-026 | B30: FAM-CONSCIOUSNESS | C30: FAM-PHYSICAL_CONTROL | D30: COEXIST_AND_COMPOSE_BY_DEFAULT | E30: APPLY_LISTED_COMBINATION_RULES | F30: COMB-018; COMB-019 | G30: CORE-061–062; CORE-103; CORE-103 | H30: DEFAULT_OR_EXPLICIT | I30: DEFINED | J30: =COUNTIFS($B$5:$B$304,B30,$C$5:$C$304,C30) -> 1
A31: PAIR-027 | B31: FAM-CONSCIOUSNESS | C31: FAM-MENTAL_CONTROL | D31: COEXIST_AND_COMPOSE_BY_DEFAULT | E31: APPLY_LISTED_COMBINATION_RULES | F31: COMB-020 | G31: SYM-100; CORE-181 | H31: DEFAULT_OR_EXPLICIT | I31: DEFINED | J31: =COUNTIFS($B$5:$B$304,B31,$C$5:$C$304,C31) -> 1
A32: PAIR-028 | B32: FAM-CONSCIOUSNESS | C32: FAM-MOBILITY_POSITION | D32: COEXIST_AND_COMPOSE_BY_DEFAULT | E32: UNION_RESTRICTIONS_AND_RUN_NORMAL_PIPELINES | G32: CORE-079; CORE-080 | H32: DEFAULT_OR_EXPLICIT | I32: DEFINED | J32: =COUNTIFS($B$5:$B$304,B32,$C$5:$C$304,C32) -> 1
A33: PAIR-029 | B33: FAM-CONSCIOUSNESS | C33: FAM-ACTION_ECONOMY | D33: COEXIST_AND_COMPOSE_BY_DEFAULT | E33: UNION_RESTRICTIONS_AND_RUN_NORMAL_PIPELINES | G33: CORE-079; CORE-080 | H33: DEFAULT_OR_EXPLICIT | I33: DEFINED | J33: =COUNTIFS($B$5:$B$304,B33,$C$5:$C$304,C33) -> 1
A34: PAIR-030 | B34: FAM-CONSCIOUSNESS | C34: FAM-TRAUMA | D34: COEXIST_AND_COMPOSE_BY_DEFAULT | E34: UNION_RESTRICTIONS_AND_RUN_NORMAL_PIPELINES | G34: CORE-079; CORE-080 | H34: DEFAULT_OR_EXPLICIT | I34: DEFINED | J34: =COUNTIFS($B$5:$B$304,B34,$C$5:$C$304,C34) -> 1
A35: PAIR-031 | B35: FAM-CONSCIOUSNESS | C35: FAM-WOUND_BLEEDING | D35: COEXIST_AND_COMPOSE_BY_DEFAULT | E35: UNION_RESTRICTIONS_AND_RUN_NORMAL_PIPELINES | G35: CORE-079; CORE-080 | H35: DEFAULT_OR_EXPLICIT | I35: DEFINED | J35: =COUNTIFS($B$5:$B$304,B35,$C$5:$C$304,C35) -> 1
A36: PAIR-032 | B36: FAM-CONSCIOUSNESS | C36: FAM-DISEASE | D36: COEXIST_AND_COMPOSE_BY_DEFAULT | E36: UNION_RESTRICTIONS_AND_RUN_NORMAL_PIPELINES | G36: CORE-079; CORE-080 | H36: DEFAULT_OR_EXPLICIT | I36: DEFINED | J36: =COUNTIFS($B$5:$B$304,B36,$C$5:$C$304,C36) -> 1
A37: PAIR-033 | B37: FAM-CONSCIOUSNESS | C37: FAM-POISON | D37: COEXIST_AND_COMPOSE_BY_DEFAULT | E37: UNION_RESTRICTIONS_AND_RUN_NORMAL_PIPELINES | G37: CORE-079; CORE-080 | H37: DEFAULT_OR_EXPLICIT | I37: DEFINED | J37: =COUNTIFS($B$5:$B$304,B37,$C$5:$C$304,C37) -> 1
A38: PAIR-034 | B38: FAM-CONSCIOUSNESS | C38: FAM-FIRE | D38: COEXIST_AND_COMPOSE_BY_DEFAULT | E38: APPLY_LISTED_COMBINATION_RULES | F38: COMB-014 | G38: CORE-103; CQA-002 | H38: DEFAULT_OR_EXPLICIT | I38: DEFINED | J38: =COUNTIFS($B$5:$B$304,B38,$C$5:$C$304,C38) -> 1
A39: PAIR-035 | B39: FAM-CONSCIOUSNESS | C39: FAM-PERIODIC_DAMAGE | D39: COEXIST_AND_COMPOSE_BY_DEFAULT | E39: APPLY_LISTED_COMBINATION_RULES | F39: COMB-016 | G39: CORE-061 | H39: DEFAULT_OR_EXPLICIT | I39: DEFINED | J39: =COUNTIFS($B$5:$B$304,B39,$C$5:$C$304,C39) -> 1
A40: PAIR-036 | B40: FAM-CONSCIOUSNESS | C40: FAM-PERIODIC_HEAL | D40: COEXIST_AND_COMPOSE_BY_DEFAULT | E40: UNION_RESTRICTIONS_AND_RUN_NORMAL_PIPELINES | G40: CORE-079; CORE-080 | H40: DEFAULT_OR_EXPLICIT | I40: DEFINED | J40: =COUNTIFS($B$5:$B$304,B40,$C$5:$C$304,C40) -> 1
A41: PAIR-037 | B41: FAM-CONSCIOUSNESS | C41: FAM-STAT_MODIFIER | D41: COEXIST_AND_COMPOSE_BY_DEFAULT | E41: UNION_RESTRICTIONS_AND_RUN_NORMAL_PIPELINES | G41: CORE-079; CORE-080 | H41: DEFAULT_OR_EXPLICIT | I41: DEFINED | J41: =COUNTIFS($B$5:$B$304,B41,$C$5:$C$304,C41) -> 1
A42: PAIR-038 | B42: FAM-CONSCIOUSNESS | C42: FAM-CHECK_MODIFIER | D42: COEXIST_AND_COMPOSE_BY_DEFAULT | E42: UNION_RESTRICTIONS_AND_RUN_NORMAL_PIPELINES | G42: CORE-079; CORE-080 | H42: DEFAULT_OR_EXPLICIT | I42: DEFINED | J42: =COUNTIFS($B$5:$B$304,B42,$C$5:$C$304,C42) -> 1
A43: PAIR-039 | B43: FAM-CONSCIOUSNESS | C43: FAM-SENSE_VISIBILITY | D43: COEXIST_AND_COMPOSE_BY_DEFAULT | E43: UNION_RESTRICTIONS_AND_RUN_NORMAL_PIPELINES | G43: CORE-079; CORE-080 | H43: DEFAULT_OR_EXPLICIT | I43: DEFINED | J43: =COUNTIFS($B$5:$B$304,B43,$C$5:$C$304,C43) -> 1
A44: PAIR-040 | B44: FAM-CONSCIOUSNESS | C44: FAM-FORM_MODE | D44: COEXIST_AND_COMPOSE_BY_DEFAULT | E44: UNION_RESTRICTIONS_AND_RUN_NORMAL_PIPELINES | G44: CORE-079; CORE-080 | H44: DEFAULT_OR_EXPLICIT | I44: DEFINED | J44: =COUNTIFS($B$5:$B$304,B44,$C$5:$C$304,C44) -> 1
A45: PAIR-041 | B45: FAM-CONSCIOUSNESS | C45: FAM-SYMBIONT_STATE | D45: COEXIST_AND_COMPOSE_BY_DEFAULT | E45: UNION_RESTRICTIONS_AND_RUN_NORMAL_PIPELINES | G45: CORE-079; CORE-080 | H45: DEFAULT_OR_EXPLICIT | I45: DEFINED | J45: =COUNTIFS($B$5:$B$304,B45,$C$5:$C$304,C45) -> 1
A46: PAIR-042 | B46: FAM-CONSCIOUSNESS | C46: FAM-IMMUNITY_RESISTANCE | D46: COEXIST_AND_COMPOSE_BY_DEFAULT | E46: UNION_RESTRICTIONS_AND_RUN_NORMAL_PIPELINES | G46: CORE-079; CORE-080 | H46: DEFAULT_OR_EXPLICIT | I46: DEFINED | J46: =COUNTIFS($B$5:$B$304,B46,$C$5:$C$304,C46) -> 1
A47: PAIR-043 | B47: FAM-CONSCIOUSNESS | C47: FAM-INFECTION | D47: COEXIST_AND_COMPOSE_BY_DEFAULT | E47: UNION_RESTRICTIONS_AND_RUN_NORMAL_PIPELINES | G47: CORE-079; CORE-080 | H47: DEFAULT_OR_EXPLICIT | I47: DEFINED | J47: =COUNTIFS($B$5:$B$304,B47,$C$5:$C$304,C47) -> 1
A48: PAIR-044 | B48: FAM-CONSCIOUSNESS | C48: FAM-PREPARED_EFFECT | D48: COEXIST_AND_COMPOSE_BY_DEFAULT | E48: UNION_RESTRICTIONS_AND_RUN_NORMAL_PIPELINES | G48: CORE-079; CORE-080 | H48: DEFAULT_OR_EXPLICIT | I48: DEFINED | J48: =COUNTIFS($B$5:$B$304,B48,$C$5:$C$304,C48) -> 1
A49: PAIR-045 | B49: FAM-CONSCIOUSNESS | C49: FAM-SOURCE_LINK | D49: COEXIST_AND_COMPOSE_BY_DEFAULT | E49: UNION_RESTRICTIONS_AND_RUN_NORMAL_PIPELINES | G49: CORE-079; CORE-080 | H49: DEFAULT_OR_EXPLICIT | I49: DEFINED | J49: =COUNTIFS($B$5:$B$304,B49,$C$5:$C$304,C49) -> 1
A50: PAIR-046 | B50: FAM-CONSCIOUSNESS | C50: FAM-ITEM_STATE | D50: COEXIST_AND_COMPOSE_BY_DEFAULT | E50: UNION_RESTRICTIONS_AND_RUN_NORMAL_PIPELINES | G50: CORE-079; CORE-080 | H50: DEFAULT_OR_EXPLICIT | I50: DEFINED | J50: =COUNTIFS($B$5:$B$304,B50,$C$5:$C$304,C50) -> 1
A51: PAIR-047 | B51: FAM-CONSCIOUSNESS | C51: FAM-NARRATIVE | D51: COEXIST_AND_COMPOSE_BY_DEFAULT | E51: UNION_RESTRICTIONS_AND_RUN_NORMAL_PIPELINES | G51: CORE-079; CORE-080 | H51: DEFAULT_OR_EXPLICIT | I51: DEFINED | J51: =COUNTIFS($B$5:$B$304,B51,$C$5:$C$304,C51) -> 1
A52: PAIR-048 | B52: FAM-PHYSICAL_CONTROL | C52: FAM-PHYSICAL_CONTROL | D52: TYPE_AND_SOURCE_SPECIFIC | E52: APPLY_LISTED_COMBINATION_RULES | F52: COMB-032; COMB-033 | G52: CORE-144; CORE-138; MON-136; MON-149 | H52: DEFAULT_OR_EXPLICIT | I52: DEFINED | J52: =COUNTIFS($B$5:$B$304,B52,$C$5:$C$304,C52) -> 1
A53: PAIR-049 | B53: FAM-PHYSICAL_CONTROL | C53: FAM-MENTAL_CONTROL | D53: COEXIST_AND_COMPOSE_BY_DEFAULT | E53: UNION_RESTRICTIONS_AND_RUN_NORMAL_PIPELINES | G53: CORE-079; CORE-080 | H53: DEFAULT_OR_EXPLICIT | I53: DEFINED | J53: =COUNTIFS($B$5:$B$304,B53,$C$5:$C$304,C53) -> 1
A54: PAIR-050 | B54: FAM-PHYSICAL_CONTROL | C54: FAM-MOBILITY_POSITION | D54: COEXIST_AND_COMPOSE_BY_DEFAULT | E54: UNION_RESTRICTIONS_AND_RUN_NORMAL_PIPELINES | G54: CORE-079; CORE-080 | H54: DEFAULT_OR_EXPLICIT | I54: DEFINED | J54: =COUNTIFS($B$5:$B$304,B54,$C$5:$C$304,C54) -> 1
A55: PAIR-051 | B55: FAM-PHYSICAL_CONTROL | C55: FAM-ACTION_ECONOMY | D55: COEXIST_AND_COMPOSE_BY_DEFAULT | E55: UNION_RESTRICTIONS_AND_RUN_NORMAL_PIPELINES | G55: CORE-079; CORE-080 | H55: DEFAULT_OR_EXPLICIT | I55: DEFINED | J55: =COUNTIFS($B$5:$B$304,B55,$C$5:$C$304,C55) -> 1
A56: PAIR-052 | B56: FAM-PHYSICAL_CONTROL | C56: FAM-TRAUMA | D56: COEXIST_AND_COMPOSE_BY_DEFAULT | E56: APPLY_LISTED_COMBINATION_RULES | F56: COMB-064 | G56: Bestiary 05A/06A | H56: DEFAULT_OR_EXPLICIT | I56: DEFINED | J56: =COUNTIFS($B$5:$B$304,B56,$C$5:$C$304,C56) -> 1
A57: PAIR-053 | B57: FAM-PHYSICAL_CONTROL | C57: FAM-WOUND_BLEEDING | D57: COEXIST_AND_COMPOSE_BY_DEFAULT | E57: UNION_RESTRICTIONS_AND_RUN_NORMAL_PIPELINES | G57: CORE-079; CORE-080 | H57: DEFAULT_OR_EXPLICIT | I57: DEFINED | J57: =COUNTIFS($B$5:$B$304,B57,$C$5:$C$304,C57) -> 1
A58: PAIR-054 | B58: FAM-PHYSICAL_CONTROL | C58: FAM-DISEASE | D58: COEXIST_AND_COMPOSE_BY_DEFAULT | E58: UNION_RESTRICTIONS_AND_RUN_NORMAL_PIPELINES | G58: CORE-079; CORE-080 | H58: DEFAULT_OR_EXPLICIT | I58: DEFINED | J58: =COUNTIFS($B$5:$B$304,B58,$C$5:$C$304,C58) -> 1
A59: PAIR-055 | B59: FAM-PHYSICAL_CONTROL | C59: FAM-POISON | D59: COEXIST_AND_COMPOSE_BY_DEFAULT | E59: APPLY_LISTED_COMBINATION_RULES | F59: COMB-034 | G59: MON-149–150 | H59: DEFAULT_OR_EXPLICIT | I59: DEFINED | J59: =COUNTIFS($B$5:$B$304,B59,$C$5:$C$304,C59) -> 1
A60: PAIR-056 | B60: FAM-PHYSICAL_CONTROL | C60: FAM-FIRE | D60: COEXIST_AND_COMPOSE_BY_DEFAULT | E60: UNION_RESTRICTIONS_AND_RUN_NORMAL_PIPELINES | G60: CORE-079; CORE-080 | H60: DEFAULT_OR_EXPLICIT | I60: DEFINED | J60: =COUNTIFS($B$5:$B$304,B60,$C$5:$C$304,C60) -> 1
A61: PAIR-057 | B61: FAM-PHYSICAL_CONTROL | C61: FAM-PERIODIC_DAMAGE | D61: COEXIST_AND_COMPOSE_BY_DEFAULT | E61: APPLY_LISTED_COMBINATION_RULES | F61: COMB-017 | G61: CORE-062 | H61: DEFAULT_OR_EXPLICIT | I61: DEFINED | J61: =COUNTIFS($B$5:$B$304,B61,$C$5:$C$304,C61) -> 1
A62: PAIR-058 | B62: FAM-PHYSICAL_CONTROL | C62: FAM-PERIODIC_HEAL | D62: COEXIST_AND_COMPOSE_BY_DEFAULT | E62: UNION_RESTRICTIONS_AND_RUN_NORMAL_PIPELINES | G62: CORE-079; CORE-080 | H62: DEFAULT_OR_EXPLICIT | I62: DEFINED | J62: =COUNTIFS($B$5:$B$304,B62,$C$5:$C$304,C62) -> 1
A63: PAIR-059 | B63: FAM-PHYSICAL_CONTROL | C63: FAM-STAT_MODIFIER | D63: COEXIST_AND_COMPOSE_BY_DEFAULT | E63: UNION_RESTRICTIONS_AND_RUN_NORMAL_PIPELINES | G63: CORE-079; CORE-080 | H63: DEFAULT_OR_EXPLICIT | I63: DEFINED | J63: =COUNTIFS($B$5:$B$304,B63,$C$5:$C$304,C63) -> 1
A64: PAIR-060 | B64: FAM-PHYSICAL_CONTROL | C64: FAM-CHECK_MODIFIER | D64: COEXIST_AND_COMPOSE_BY_DEFAULT | E64: UNION_RESTRICTIONS_AND_RUN_NORMAL_PIPELINES | G64: CORE-079; CORE-080 | H64: DEFAULT_OR_EXPLICIT | I64: DEFINED | J64: =COUNTIFS($B$5:$B$304,B64,$C$5:$C$304,C64) -> 1
A65: PAIR-061 | B65: FAM-PHYSICAL_CONTROL | C65: FAM-SENSE_VISIBILITY | D65: COEXIST_AND_COMPOSE_BY_DEFAULT | E65: UNION_RESTRICTIONS_AND_RUN_NORMAL_PIPELINES | G65: CORE-079; CORE-080 | H65: DEFAULT_OR_EXPLICIT | I65: DEFINED | J65: =COUNTIFS($B$5:$B$304,B65,$C$5:$C$304,C65) -> 1
A66: PAIR-062 | B66: FAM-PHYSICAL_CONTROL | C66: FAM-FORM_MODE | D66: COEXIST_AND_COMPOSE_BY_DEFAULT | E66: UNION_RESTRICTIONS_AND_RUN_NORMAL_PIPELINES | G66: CORE-079; CORE-080 | H66: DEFAULT_OR_EXPLICIT | I66: DEFINED | J66: =COUNTIFS($B$5:$B$304,B66,$C$5:$C$304,C66) -> 1
A67: PAIR-063 | B67: FAM-PHYSICAL_CONTROL | C67: FAM-SYMBIONT_STATE | D67: COEXIST_AND_COMPOSE_BY_DEFAULT | E67: UNION_RESTRICTIONS_AND_RUN_NORMAL_PIPELINES | G67: CORE-079; CORE-080 | H67: DEFAULT_OR_EXPLICIT | I67: DEFINED | J67: =COUNTIFS($B$5:$B$304,B67,$C$5:$C$304,C67) -> 1
A68: PAIR-064 | B68: FAM-PHYSICAL_CONTROL | C68: FAM-IMMUNITY_RESISTANCE | D68: COEXIST_AND_COMPOSE_BY_DEFAULT | E68: APPLY_LISTED_COMBINATION_RULES | F68: COMB-038 | G68: CQA-043; MON-020 | H68: DEFAULT_OR_EXPLICIT | I68: DEFINED | J68: =COUNTIFS($B$5:$B$304,B68,$C$5:$C$304,C68) -> 1
A69: PAIR-065 | B69: FAM-PHYSICAL_CONTROL | C69: FAM-INFECTION | D69: COEXIST_AND_COMPOSE_BY_DEFAULT | E69: UNION_RESTRICTIONS_AND_RUN_NORMAL_PIPELINES | G69: CORE-079; CORE-080 | H69: DEFAULT_OR_EXPLICIT | I69: DEFINED | J69: =COUNTIFS($B$5:$B$304,B69,$C$5:$C$304,C69) -> 1
A70: PAIR-066 | B70: FAM-PHYSICAL_CONTROL | C70: FAM-PREPARED_EFFECT | D70: COEXIST_AND_COMPOSE_BY_DEFAULT | E70: APPLY_LISTED_COMBINATION_RULES | F70: COMB-036 | G70: MON-151 | H70: DEFAULT_OR_EXPLICIT | I70: DEFINED | J70: =COUNTIFS($B$5:$B$304,B70,$C$5:$C$304,C70) -> 1
A71: PAIR-067 | B71: FAM-PHYSICAL_CONTROL | C71: FAM-SOURCE_LINK | D71: COEXIST_AND_COMPOSE_BY_DEFAULT | E71: UNION_RESTRICTIONS_AND_RUN_NORMAL_PIPELINES | G71: CORE-079; CORE-080 | H71: DEFAULT_OR_EXPLICIT | I71: DEFINED | J71: =COUNTIFS($B$5:$B$304,B71,$C$5:$C$304,C71) -> 1
A72: PAIR-068 | B72: FAM-PHYSICAL_CONTROL | C72: FAM-ITEM_STATE | D72: COEXIST_AND_COMPOSE_BY_DEFAULT | E72: UNION_RESTRICTIONS_AND_RUN_NORMAL_PIPELINES | G72: CORE-079; CORE-080 | H72: DEFAULT_OR_EXPLICIT | I72: DEFINED | J72: =COUNTIFS($B$5:$B$304,B72,$C$5:$C$304,C72) -> 1
A73: PAIR-069 | B73: FAM-PHYSICAL_CONTROL | C73: FAM-NARRATIVE | D73: COEXIST_AND_COMPOSE_BY_DEFAULT | E73: UNION_RESTRICTIONS_AND_RUN_NORMAL_PIPELINES | G73: CORE-079; CORE-080 | H73: DEFAULT_OR_EXPLICIT | I73: DEFINED | J73: =COUNTIFS($B$5:$B$304,B73,$C$5:$C$304,C73) -> 1
A74: PAIR-070 | B74: FAM-MENTAL_CONTROL | C74: FAM-MENTAL_CONTROL | D74: TYPE_AND_SOURCE_SPECIFIC | E74: APPLY_LISTED_COMBINATION_RULES | F74: COMB-048 | G74: CORE-181; CORE-221 | H74: DEFAULT_OR_EXPLICIT | I74: DEFINED | J74: =COUNTIFS($B$5:$B$304,B74,$C$5:$C$304,C74) -> 1
A75: PAIR-071 | B75: FAM-MENTAL_CONTROL | C75: FAM-MOBILITY_POSITION | D75: COEXIST_AND_COMPOSE_BY_DEFAULT | E75: UNION_RESTRICTIONS_AND_RUN_NORMAL_PIPELINES | G75: CORE-079; CORE-080 | H75: DEFAULT_OR_EXPLICIT | I75: DEFINED | J75: =COUNTIFS($B$5:$B$304,B75,$C$5:$C$304,C75) -> 1
A76: PAIR-072 | B76: FAM-MENTAL_CONTROL | C76: FAM-ACTION_ECONOMY | D76: COEXIST_AND_COMPOSE_BY_DEFAULT | E76: UNION_RESTRICTIONS_AND_RUN_NORMAL_PIPELINES | G76: CORE-079; CORE-080 | H76: DEFAULT_OR_EXPLICIT | I76: DEFINED | J76: =COUNTIFS($B$5:$B$304,B76,$C$5:$C$304,C76) -> 1
A77: PAIR-073 | B77: FAM-MENTAL_CONTROL | C77: FAM-TRAUMA | D77: COEXIST_AND_COMPOSE_BY_DEFAULT | E77: UNION_RESTRICTIONS_AND_RUN_NORMAL_PIPELINES | G77: CORE-079; CORE-080 | H77: DEFAULT_OR_EXPLICIT | I77: DEFINED | J77: =COUNTIFS($B$5:$B$304,B77,$C$5:$C$304,C77) -> 1
A78: PAIR-074 | B78: FAM-MENTAL_CONTROL | C78: FAM-WOUND_BLEEDING | D78: COEXIST_AND_COMPOSE_BY_DEFAULT | E78: UNION_RESTRICTIONS_AND_RUN_NORMAL_PIPELINES | G78: CORE-079; CORE-080 | H78: DEFAULT_OR_EXPLICIT | I78: DEFINED | J78: =COUNTIFS($B$5:$B$304,B78,$C$5:$C$304,C78) -> 1
A79: PAIR-075 | B79: FAM-MENTAL_CONTROL | C79: FAM-DISEASE | D79: COEXIST_AND_COMPOSE_BY_DEFAULT | E79: UNION_RESTRICTIONS_AND_RUN_NORMAL_PIPELINES | G79: CORE-079; CORE-080 | H79: DEFAULT_OR_EXPLICIT | I79: DEFINED | J79: =COUNTIFS($B$5:$B$304,B79,$C$5:$C$304,C79) -> 1
A80: PAIR-076 | B80: FAM-MENTAL_CONTROL | C80: FAM-POISON | D80: COEXIST_AND_COMPOSE_BY_DEFAULT | E80: UNION_RESTRICTIONS_AND_RUN_NORMAL_PIPELINES | G80: CORE-079; CORE-080 | H80: DEFAULT_OR_EXPLICIT | I80: DEFINED | J80: =COUNTIFS($B$5:$B$304,B80,$C$5:$C$304,C80) -> 1
A81: PAIR-077 | B81: FAM-MENTAL_CONTROL | C81: FAM-FIRE | D81: COEXIST_AND_COMPOSE_BY_DEFAULT | E81: UNION_RESTRICTIONS_AND_RUN_NORMAL_PIPELINES | G81: CORE-079; CORE-080 | H81: DEFAULT_OR_EXPLICIT | I81: DEFINED | J81: =COUNTIFS($B$5:$B$304,B81,$C$5:$C$304,C81) -> 1
A82: PAIR-078 | B82: FAM-MENTAL_CONTROL | C82: FAM-PERIODIC_DAMAGE | D82: COEXIST_AND_COMPOSE_BY_DEFAULT | E82: UNION_RESTRICTIONS_AND_RUN_NORMAL_PIPELINES | G82: CORE-079; CORE-080 | H82: DEFAULT_OR_EXPLICIT | I82: DEFINED | J82: =COUNTIFS($B$5:$B$304,B82,$C$5:$C$304,C82) -> 1
A83: PAIR-079 | B83: FAM-MENTAL_CONTROL | C83: FAM-PERIODIC_HEAL | D83: COEXIST_AND_COMPOSE_BY_DEFAULT | E83: UNION_RESTRICTIONS_AND_RUN_NORMAL_PIPELINES | G83: CORE-079; CORE-080 | H83: DEFAULT_OR_EXPLICIT | I83: DEFINED | J83: =COUNTIFS($B$5:$B$304,B83,$C$5:$C$304,C83) -> 1
A84: PAIR-080 | B84: FAM-MENTAL_CONTROL | C84: FAM-STAT_MODIFIER | D84: COEXIST_AND_COMPOSE_BY_DEFAULT | E84: UNION_RESTRICTIONS_AND_RUN_NORMAL_PIPELINES | G84: CORE-079; CORE-080 | H84: DEFAULT_OR_EXPLICIT | I84: DEFINED | J84: =COUNTIFS($B$5:$B$304,B84,$C$5:$C$304,C84) -> 1
A85: PAIR-081 | B85: FAM-MENTAL_CONTROL | C85: FAM-CHECK_MODIFIER | D85: COEXIST_AND_COMPOSE_BY_DEFAULT | E85: UNION_RESTRICTIONS_AND_RUN_NORMAL_PIPELINES | G85: CORE-079; CORE-080 | H85: DEFAULT_OR_EXPLICIT | I85: DEFINED | J85: =COUNTIFS($B$5:$B$304,B85,$C$5:$C$304,C85) -> 1
A86: PAIR-082 | B86: FAM-MENTAL_CONTROL | C86: FAM-SENSE_VISIBILITY | D86: COEXIST_AND_COMPOSE_BY_DEFAULT | E86: UNION_RESTRICTIONS_AND_RUN_NORMAL_PIPELINES | G86: CORE-079; CORE-080 | H86: DEFAULT_OR_EXPLICIT | I86: DEFINED | J86: =COUNTIFS($B$5:$B$304,B86,$C$5:$C$304,C86) -> 1
... A88: PAIR-084 | B88: FAM-MENTAL_CONTROL | C88: FAM-SYMBIONT_STATE | D88: COEXIST_AND_COMPOSE_BY_DEFAULT | E88: UNION_RESTRICTIONS_AND_RUN_NORMAL_PIPELINES | G88: CORE-079; CORE-080 | H88: DEFAULT_OR_EXPLICIT | I88: DEFINED | J88: =COUNTIFS($B$5:$B$304,B88,$C$5:$C$304,C88) -> 1
A89: PAIR-085 | B89: FAM-MENTAL_CONTROL | C89: FAM-IMMUNITY_RESISTANCE | D89: COEXIST_AND_COMPOSE_BY_DEFAULT | E89: APPLY_LISTED_COMBINATION_RULES | F89: COMB-037 | G89: CQA-050 | H89: DEFAULT_OR_EXPLICIT | I89: DEFINED | J89: =COUNTIFS($B$5:$B$304,B89,$C$5:$C$304,C89) -> 1
A90: PAIR-086 | B90: FAM-MENTAL_CONTROL | C90: FAM-INFECTION | D90: COEXIST_AND_COMPOSE_BY_DEFAULT | E90: UNION_RESTRICTIONS_AND_RUN_NORMAL_PIPELINES | G90: CORE-079; CORE-080 | H90: DEFAULT_OR_EXPLICIT | I90: DEFINED | J90: =COUNTIFS($B$5:$B$304,B90,$C$5:$C$304,C90) -> 1
A91: PAIR-087 | B91: FAM-MENTAL_CONTROL | C91: FAM-PREPARED_EFFECT | D91: COEXIST_AND_COMPOSE_BY_DEFAULT | E91: UNION_RESTRICTIONS_AND_RUN_NORMAL_PIPELINES | G91: CORE-079; CORE-080 | H91: DEFAULT_OR_EXPLICIT | I91: DEFINED | J91: =COUNTIFS($B$5:$B$304,B91,$C$5:$C$304,C91) -> 1
A92: PAIR-088 | B92: FAM-MENTAL_CONTROL | C92: FAM-SOURCE_LINK | D92: COEXIST_AND_COMPOSE_BY_DEFAULT | E92: UNION_RESTRICTIONS_AND_RUN_NORMAL_PIPELINES | G92: CORE-079; CORE-080 | H92: DEFAULT_OR_EXPLICIT | I92: DEFINED | J92: =COUNTIFS($B$5:$B$304,B92,$C$5:$C$304,C92) -> 1
A93: PAIR-089 | B93: FAM-MENTAL_CONTROL | C93: FAM-ITEM_STATE | D93: COEXIST_AND_COMPOSE_BY_DEFAULT | E93: UNION_RESTRICTIONS_AND_RUN_NORMAL_PIPELINES | G93: CORE-079; CORE-080 | H93: DEFAULT_OR_EXPLICIT | I93: DEFINED | J93: =COUNTIFS($B$5:$B$304,B93,$C$5:$C$304,C93) -> 1
A94: PAIR-090 | B94: FAM-MENTAL_CONTROL | C94: FAM-NARRATIVE | D94: COEXIST_AND_COMPOSE_BY_DEFAULT | E94: UNION_RESTRICTIONS_AND_RUN_NORMAL_PIPELINES | G94: CORE-079; CORE-080 | H94: DEFAULT_OR_EXPLICIT | I94: DEFINED | J94: =COUNTIFS($B$5:$B$304,B94,$C$5:$C$304,C94) -> 1
A95: PAIR-091 | B95: FAM-MOBILITY_POSITION | C95: FAM-MOBILITY_POSITION | D95: TYPE_AND_SOURCE_SPECIFIC | E95: APPLY_EFFECT_TYPE_STACK_POLICY | G95: CORE-079; CORE-080 | H95: DEFAULT_OR_EXPLICIT | I95: DEFINED | J95: =COUNTIFS($B$5:$B$304,B95,$C$5:$C$304,C95) -> 1
A96: PAIR-092 | B96: FAM-MOBILITY_POSITION | C96: FAM-ACTION_ECONOMY | D96: COEXIST_AND_COMPOSE_BY_DEFAULT | E96: UNION_RESTRICTIONS_AND_RUN_NORMAL_PIPELINES | G96: CORE-079; CORE-080 | H96: DEFAULT_OR_EXPLICIT | I96: DEFINED | J96: =COUNTIFS($B$5:$B$304,B96,$C$5:$C$304,C96) -> 1
A97: PAIR-093 | B97: FAM-MOBILITY_POSITION | C97: FAM-TRAUMA | D97: COEXIST_AND_COMPOSE_BY_DEFAULT | E97: UNION_RESTRICTIONS_AND_RUN_NORMAL_PIPELINES | G97: CORE-079; CORE-080 | H97: DEFAULT_OR_EXPLICIT | I97: DEFINED | J97: =COUNTIFS($B$5:$B$304,B97,$C$5:$C$304,C97) -> 1
A98: PAIR-094 | B98: FAM-MOBILITY_POSITION | C98: FAM-WOUND_BLEEDING | D98: COEXIST_AND_COMPOSE_BY_DEFAULT | E98: UNION_RESTRICTIONS_AND_RUN_NORMAL_PIPELINES | G98: CORE-079; CORE-080 | H98: DEFAULT_OR_EXPLICIT | I98: DEFINED | J98: =COUNTIFS($B$5:$B$304,B98,$C$5:$C$304,C98) -> 1
A99: PAIR-095 | B99: FAM-MOBILITY_POSITION | C99: FAM-DISEASE | D99: COEXIST_AND_COMPOSE_BY_DEFAULT | E99: UNION_RESTRICTIONS_AND_RUN_NORMAL_PIPELINES | G99: CORE-079; CORE-080 | H99: DEFAULT_OR_EXPLICIT | I99: DEFINED | J99: =COUNTIFS($B$5:$B$304,B99,$C$5:$C$304,C99) -> 1
A100: PAIR-096 | B100: FAM-MOBILITY_POSITION | C100: FAM-POISON | D100: COEXIST_AND_COMPOSE_BY_DEFAULT | E100: UNION_RESTRICTIONS_AND_RUN_NORMAL_PIPELINES | G100: CORE-079; CORE-080 | H100: DEFAULT_OR_EXPLICIT | I100: DEFINED | J100: =COUNTIFS($B$5:$B$304,B100,$C$5:$C$304,C100) -> 1
A101: PAIR-097 | B101: FAM-MOBILITY_POSITION | C101: FAM-FIRE | D101: COEXIST_AND_COMPOSE_BY_DEFAULT | E101: UNION_RESTRICTIONS_AND_RUN_NORMAL_PIPELINES | G101: CORE-079; CORE-080 | H101: DEFAULT_OR_EXPLICIT | I101: DEFINED | J101: =COUNTIFS($B$5:$B$304,B101,$C$5:$C$304,C101) -> 1
... A114: PAIR-110 | B114: FAM-MOBILITY_POSITION | C114: FAM-NARRATIVE | D114: COEXIST_AND_COMPOSE_BY_DEFAULT | E114: UNION_RESTRICTIONS_AND_RUN_NORMAL_PIPELINES | G114: CORE-079; CORE-080 | H114: DEFAULT_OR_EXPLICIT | I114: DEFINED | J114: =COUNTIFS($B$5:$B$304,B114,$C$5:$C$304,C114) -> 1
...

Sheet 09_Профили_дееспособности
A1: Проекции дееспособности для значимых сочетаний
A2: Это производные профили интерфейса и фильтра команд; активные исходные EffectInstance не удаляются.
A4: ProfileID | B4: Активные состояния | C4: Физические действия | D4: Ментальные действия | E4: Реакции | F4: Активная защита | G4: Перемещение | H4: Броня | I4: Таймеры / автономные эффекты | J4: Контроллер | K4: Выход | L4: Rule refs | M4: Status
A5: PRF-CLEAN | B5: — | C5: YES | D5: YES | E5: YES | F5: YES | G5: YES | H5: YES | I5: Normal | J5: owningController | K5: — | L5: AQA-009 | M5: DEFINED
A6: PRF-UNCONSCIOUS | B6: EFF-CONSCIOUS-UNCONSCIOUS | C6: NO | D6: NO | E6: NO | F6: NO | G6: NO | H6: YES | I6: Autonomous effects continue | J6: owningController unless specific override | K6: Remove source condition | L6: CORE-103 | M6: DEFINED
A7: PRF-SLEEP | B7: EFF-CONSCIOUS-SLEEP | C7: NO | D7: NO | E7: NO | F7: NO | G7: NO | H7: YES | I7: Autonomous effects continue | J7: owningController | K7: Damage or CORE-060 | L7: CORE-061; CORE-103 | M7: DEFINED
A8: PRF-PARALYZED | B8: EFF-CONTROL-PARALYSIS | C8: NO | D8: CONDITIONAL_NO_SPEECH_MOVEMENT_BODY | E8: NO_PHYSICAL | F8: NO_ACTIVE_PHYSICAL | G8: NO | H8: YES | I8: Autonomous effects continue | J8: owningController | K8: Expiry or source removal | L8: CORE-062; CORE-103 | M8: DEFINED
A9: PRF-STUNNED | B9: EFF-CONTROL-STUN | C9: NO_NAMED_TURNS | D9: SOURCE_SPECIFIC | E9: NO | F9: SOURCE_SPECIFIC | G9: NO_NAMED_TURNS | H9: YES | I9: Autonomous effects continue | J9: owningController | K9: Consume named turns / cleanse | L9: CORE-103 | M9: DEFINED
A10: PRF-GRAPPLED | B10: EFF-CONTROL-GRAPPLE | C10: YES_WITH_MINUS_5 | D10: YES | E10: YES_WITH_MODS | F10: NO_DODGE; OTHER_BY_RULE | G10: PAIR_MOVE_ONLY | H10: YES | I10: Normal | J10: owningController | K10: Release contest / source release | L10: CORE-138 | M10: DEFINED
A11: PRF-RESTRAINED | B11: EFF-CONTROL-RESTRAINED | C11: YES_WITH_SOURCE_PENALTY | D11: YES | E11: YES_WITH_SOURCE_PENALTY | F11: YES_WITH_SOURCE_PENALTY | G11: SOURCE_SPECIFIC | H11: YES | I11: Normal | J11: owningController | K11: Source-specific check | L11: MON-136; MON-149 | M11: DEFINED
A12: PRF-SEVERE-PC | B12: EFF-LIFE-SEVERE_WOUND | C12: NO_BY_DEFAULT | D12: NO_BY_DEFAULT | E12: NO | F12: NO | G12: NO | H12: YES | I12: Death timer; heal blocked | J12: owningController | K12: Explicit reanimation only | L12: CORE-152–156 | M12: DEFINED
A13: PRF-SEVERE-DUPLICATE | B13: EFF-LIFE-SEVERE_WOUND + EFF-CAPABILITY-SEVERE_WOUND | C13: YES | D13: YES | E13: YES | F13: YES | G13: YES | H13: YES | I13: Timer ×4 once; new damage kills | J13: owningController | K13: Source completion/reanimation/death | L13: CORE-154; SYM-028 | M13: DEFINED
A14: PRF-SEVERE-TABLET | B14: EFF-LIFE-SEVERE_WOUND + CORE-069 capability | C14: YES_UNTIL_COMBAT_END | D14: YES | E14: YES | F14: YES | G14: YES | H14: YES | I14: Timer; periodic heal still blocked | J14: owningController | K14: Combat end/reanimation/death | L14: CORE-069 | M14: DEFINED
A15: PRF-DEAD | B15: EFF-LIFE-DEAD | C15: NO | D15: NO | E15: NO | F15: NO | G15: NO | H15: N/A | I15: Cancel remaining personal events; death-triggered events may run | J15: NONE | K15: Explicit resurrection only | L15: AQA-024; CORE-156 | M15: DEFINED
... A25: PRF-FIRE-FLEA-DETONATING-DEAD | B25: dead + prepared detonation | C25: NO | D25: NO | E25: NO | F25: NO | G25: NO | H25: N/A | I25: Detonation still resolves | J25: NONE | K25: Special neutralization/trigger | L25: MON-114–115; CORE-222 | M25: DEFINED

Sheet 10_Иммунитеты
A1: Профили ответов, иммунитетов и сопротивлений
A2: Ответ не создаёт отсутствующую проверку. IMMUNE_BEFORE_ROLL отбрасывает только соответствующий payload.
A4: ResponseProfileID | B4: Provider | C4: Effect family | D4: Source scope | E4: Response | F4: Modifier | G4: Blocked payload | H4: Existing effect policy / note | I4: Rule refs
A5: RSP-KRYSYUK-POISON | B5: CBT-KRYSYUK | C5: POISON | D5: ANY | E5: IMMUNE_BEFORE_ROLL | F5: — | G5: damage,state,counter,secondary effects | H5: No automatic cleanse | I5: MON-104; CORE-228
A6: RSP-KRYSYUK-DISEASE | B6: CBT-KRYSYUK | C6: DISEASE | D6: ANY | E6: CHECK_MODIFIER | F6: +5 | G6: — | H6: Only an existing check | I6: MON-104
A7: RSP-KRYSYUK-EXHAUSTION | B7: CBT-KRYSYUK | C7: EXHAUSTION | D7: ANY | E7: CHECK_MODIFIER | F7: +5 | G7: — | H7: Mechanic otherwise orphaned | I7: MON-104
A8: RSP-GIANT-TOAD-POISON | B8: CBT-GIANT-TOAD | C8: POISON | D8: ANY | E8: IMMUNE_BEFORE_ROLL | F8: — | G8: damage,state,counter,secondary effects | H8: No automatic cleanse | I8: MON-155; CORE-228
A9: RSP-GIANT-TOAD-DISEASE | B9: CBT-GIANT-TOAD | C9: DISEASE | D9: ANY | E9: CHECK_MODIFIER | F9: +10 | G9: — | H9: No exhaustion bonus | I9: MON-155
A10: RSP-VIVISECTOR-SELF | B10: CBT-VIVISECTOR | C10: POISON | D10: OWN_SLIME_OR_FUMES | E10: IMMUNE | F10: — | G10: own poison payload | H10: No own effect created | I10: MON-101
A11: RSP-VIVISECTOR-NATURAL | B11: CBT-VIVISECTOR | C11: POISON | D11: NATURAL | E11: CHECK_MODIFIER | F11: +10 | G11: — | H11: Artificial/symbiotic normal | I11: MON-101
A12: RSP-VIVISECTOR-FIRE | B12: CBT-VIVISECTOR | C12: FIRE | D12: ORDINARY | E12: DAMAGE_MULTIPLIER | F12: ×0.5 | G12: — | H12: Burn may still apply | I12: MON-101
A13: RSP-FIRE-FLEA-FIRE | B13: CBT-FIRE-FLEA | C13: FIRE | D13: ORDINARY | E13: IMMUNE_STANDARD_FIRE | F13: — | G13: standard fire damage/burn | H13: Specific explosion rules separate | I13: MON-113
A14: RSP-NAIT-INHALED | B14: ITEM:ITM-ARM-005 sealed | C14: INHALED_CHEMICAL_OR_INFECTION | D14: EXTERNAL | E14: BLOCK_APPLICATION | F14: — | G14: fumes, pheromones, infected vapor | H14: Does not cleanse existing | I14: CORE-053
A15: RSP-NAIT-CHECK | B15: ITEM:ITM-ARM-005 sealed | C15: DISEASE|SYMBIONT_INFECTION|EXTERNAL_CHEMICAL | D15: EXTERNAL | E15: CHECK_MODIFIER | F15: +20 | G15: — | H15: Only while sealed | I15: CORE-053
... A24: RSP-BUBUI-ALCOHOL | B24: CBT-BUBUI | C24: ALCOHOL | D24: ANY | E24: IGNORE_SELECTED_PENALTIES | F24: — | G24: S/D/I penalties only | H24: Other alcohol effects remain | I24: MON-095

Sheet 11_Таймеры_порядок
A1: Таймеры и транзакционный порядок
A2: AQA-024 используется как поздняя детальная семантика обработки одной временной метки.
A4: PolicyID | B4: Название | C4: Code | D4: Контекст | E4: Алгоритм / инвариант | F4: Rule refs
A5: TIME-001 | B5: Личный ход | C5: PERSONAL_TURN | D5: Источник или цель по карточке | E5: Срок N начинается немедленно и завершается в конце N-го последующего хода источника | F5: CORE-101
A6: TIME-002 | B6: Круг инициативы | C6: INITIATIVE_ROUND | D6: Глобальный боевой круг | E6: Используется, если нет личного источника либо карточка прямо говорит круг | F6: CORE-101; CORE-176
A7: TIME-003 | B7: До конца боя | C7: COMBAT_BOUND | D7: Активная угроза | E7: Не сохраняется только ради формального состояния без угрозы | F7: CORE-086; CORE-101
A8: TIME-004 | B8: Часы/минуты | C8: WORLD_TIME | D8: Календарь кампании | E8: Хранить точные отметки времени | F8: CORE-101; Q-CORE-063
A9: TIME-005 | B9: Полные сутки | C9: FULL_DAY_TICK | D9: 24 часа эффекта | E9: Пневмония тикает только за полные сутки | F9: MON-080
A10: TIME-006 | B10: Тяжёлое ранение | C10: SEVERE_WOUND_TIMER | D10: Личная/мировая шкала | E10: 1 боевой ход остатка = 5 минут вне боя | F10: CORE-153; Q-CORE-063
A11: TIME-007 | B11: Обычный остаток | C11: NORMAL_CONVERSION | D11: Смена бой↔мир | E11: 1 оставшийся ход = 1 минута | F11: Q-CORE-063
A12: TIME-008 | B12: Точный остаток | C12: EXACT_REMAINDER | D12: Хранилище | E12: Округление вверх допустимо только для отображения | F12: Q-CORE-063
A13: TIME-009 | B13: Список событий метки | C13: EVENT_SNAPSHOT | D13: Одна временная метка | E13: Сначала фиксируется неизменяемый список существовавших событий | F13: AQA-024
A14: TIME-010 | B14: Фаза 1 | C14: COSTS_AND_TICKS | D14: Одна временная метка | E14: Обязательные цены и периодические тики | F14: AQA-024
A15: TIME-011 | B15: Немедленный пересчёт | C15: RECALC_AFTER_EACH_TICK | D15: После каждого тика | E15: Тяжёлая рана, сознание, смерть и немедленные триггеры | F15: AQA-024
... A25: TIME-021 | B25: Дробная длительность R20/3 | C25: ROUND_NEAREST_HALF_UP_MIN_ONE | D25: Фелида и иные явно совместимые источники | E25: Округлить до ближайшего целого; ровно 0,5 вверх; положительный результат минимум 1; результат ≤0 не создаёт эффект | F25: MON-169; авторское решение GAP-018

Sheet 12_Runtime_контракты
A1: Runtime-контракты эффектов и болезней
A2: Схема заполняет существующие currentEffects/currentTraumas/currentWounds без изменения согласованных файлов.
A4: Entity | B4: Field | C4: Type | D4: Required | E4: Семантика / инвариант | F4: Источник / статус
A5: EffectDefinition | B5: effectTypeId | C5: string | D5: YES | E5: Стабильный ID из 02_Типы_эффектов | F5: NEW_SUPPLEMENT_SCHEMA
A6: EffectDefinition | B6: familyCode | C6: enum | D6: YES | E6: FK на 01_Семейства | F6: NEW_SUPPLEMENT_SCHEMA
A7: EffectDefinition | B7: displayName | C7: string | D7: YES | E7: Пользовательское имя | F7: NEW_SUPPLEMENT_SCHEMA
A8: EffectDefinition | B8: stateBucket | C8: enum | D8: YES | E8: currentEffects/currentTraumas/currentWounds/actorFlags/item/source/narrative | F8: NEW_SUPPLEMENT_SCHEMA
A9: EffectDefinition | B9: defaultStackPolicy | C9: enum | D9: YES | E9: Не заменяет частную карточку источника | F9: NEW_SUPPLEMENT_SCHEMA
A10: EffectDefinition | B10: defaultSourceLifecycle | C10: enum | D10: YES | E10: SOURCE_MAINTAINED/AUTONOMOUS/SOURCE_SPECIFIC | F10: NEW_SUPPLEMENT_SCHEMA
A11: EffectDefinition | B11: automationStatus | C11: enum | D11: YES | E11: AUTOMATED/PARTIAL/TRACE_ONLY/BLOCKED/NOT_MODELED | F11: NEW_SUPPLEMENT_SCHEMA
A12: EffectInstance | B12: effectInstanceId | C12: UUID | D12: YES | E12: Уникален в mutable graph; новый UUID при клонировании | F12: REQUIRED
A13: EffectInstance | B13: effectTypeId | C13: string | D13: YES | E13: FK EffectDefinition | F13: REQUIRED
A14: EffectInstance | B14: familyCode | C14: enum | D14: YES | E14: Дублируется для быстрого ответа и валидируется по типу | F14: REQUIRED
A15: EffectInstance | B15: targetActorId | C15: UUID | D15: YES | E15: Владелец состояния | F15: REQUIRED
... A73: DerivedStateProjection | B73: regionPenaltyById | C73: map<regionId,number> | D73: YES | E73: Для одной зоны действует наиболее строгий числовой штраф из травмы/онемения; источники хранятся раздельно, самостоятельные ограничения объединяются, после снятия выполняется пересчёт | F73: CORE-119; MON-169; SYM-045; COMB-031; Author decision 2026-07-31

Sheet 13_Операции
A1: Атомарные операции приложения
A2: Каждая операция валидирует источник, ответ, анатомию и stack policy до изменения mutable state.
A4: OperationID | B4: Inputs | C4: Алгоритм | D4: State writes | E4: Idempotency / audit | F4: Failure policy | G4: Rule refs
A5: APPLY_EFFECT | B5: EffectDefinition + source payload + target | C5: Validate response → anatomy → known EffectTypeID; reject BLOCKED/NOT_MODELED; then aggregateKey/stack policy → create or aggregate | D5: currentEffects/source bucket; audit | E5: IDEMPOTENCY_KEY | F5: REJECT_BLOCKED_OR_NOT_MODELED | G5: CORE-080; CORE-228
A6: REMOVE_EFFECT | B6: effectInstanceId + authorized reason | C6: Validate specific removal permission | D6: status=REMOVED; recalc | E6: effectInstanceId+revision | F6: REJECT_TERMINAL_DEAD_CLEAR | G6: AQA-028; AQA-045
A7: REPLACE_EFFECT | B7: old instance + new payload | C7: End old version and create new atomically | D7: old=REPLACED; new revision | E7: commandId | F7: NO_ROLLBACK | G7: AQA-045
A8: REFRESH_EFFECT | B8: effectInstanceId + new duration | C8: Only if source profile says refresh | D8: Update through replacement/versioning | E8: commandId | F8: REJECT_IF_STACK_POLICY_DIFFERS | G8: CORE-058; AQA-045
A9: ADVANCE_TIME | B9: target timestamp / combat boundary | C9: Build stable event snapshot and execute phases | D9: ticks, recalc, recovery, expiry, GM requests | E9: timeAdvanceId | F9: ROLLBACK_TRANSACTION_ON_ERROR | G9: AQA-024
A10: RESOLVE_EFFECT_TICK | B10: effectInstanceId + tick occurrence | C10: Revalidate active/applicable; execute exactly once | D10: resource/state delta + nextTick | E10: effectInstanceId+tickAt | F10: SKIP_IF_DEAD_OR_INAPPLICABLE | G10: AQA-024
A11: ASSIGN_DISEASE | B11: actorId + diseaseId + GM authority | C11: No automatic disease selection; apply if not same active disease | D11: EFF-DISEASE-INSTANCE | E11: actorId+diseaseId+commandId | F11: BLOCK_UNKNOWN_DISEASE | G11: CQA-060; MON-085
A12: REMOVE_DISEASE | B12: actorId + disease instance + GM authority | C12: Remove named disease and recalc | D12: status=REMOVED | E12: commandId | F12: NO_AUTOMATIC_TREATMENT | G12: CQA-060
A13: APPLY_POISON | B13: poison profile + delivery + source + target | C13: Run IMMUNE_BEFORE_ROLL; then profile algorithm | D13: PoisonInstance/counter/damage | E13: originEventId+profile | F13: DROP_POISON_PAYLOAD_ON_ABSOLUTE_IMMUNITY | G13: CORE-228
A14: APPLY_BURNING | B14: target + duration + damagePerTick + source | C14: Create binary status or set max duration and max damagePerTick; no immediate second tick | D14: EFF-FIRE-BURNING | E14: originEventId | F14: REJECT_MISSING_DAMAGE_PER_TICK | G14: CORE-112
A15: EXTINGUISH_BURNING | B15: target + source/GM command | C15: Validate explicit extinguisher or GM scene resolution | D15: remove burn | E15: commandId | F15: SOURCE_SPECIFIC | G15: CORE-112; CORE-114
... A29: FINALIZE_DEATH_STATE | B29: actor state graph | C29: Terminate temporary/control effects; preserve traumas, wounds, item state, inventory and symbionts | D29: effect statuses; corpse state | E29: deathEventId | F29: NO_RESUME_ON_RESURRECTION | G29: CQA-001; AQA-024; GAP-006

Sheet 14_Пробелы_и_решения
A1: Неполные параметры, конфликты и безопасная граница
A2: Авторские решения v1.1 и v1.2 закрывают все развилки; неавтоматизируемые и исключённые механики имеют явную границу.
A4: GapID | B4: Severity | C4: Область | D4: Пробел / расхождение | E4: Rule refs | F4: Действующая политика / решение | G4: Статус
A5: GAP-001 | B5: BLOCKER | C5: Раны | D5: Нет создания, стека и естественного заживления formal wound | E5: CORE-059 | F5: Рану создаёт только CREATES_WOUND или мастер; одно событие = одна рана с зоной; лечение/снятие только явно | G5: RESOLVED_BY_AUTHOR_2026-07-30
A6: GAP-002 | B6: BLOCKER | C6: Кровотечение | D6: Есть снятие всех кровотечений, но нет источника, тика и стека | E6: CORE-063 | F6: Кровотечение создаёт только явный источник с damagePerTick; отдельно на рану; тик в конце хода цели; CORE-063 снимает все | G6: RESOLVED_BY_AUTHOR_2026-07-30
A7: GAP-003 | B7: HIGH | C7: Травмы | D7: Нет общей модели восстановления/лечения травм | E7: CORE-119–121 | F7: Автоматического восстановления нет; только прямая способность, описанная процедура или команда мастера | G7: RESOLVED_BY_AUTHOR_2026-07-30
A8: GAP-004 | B8: HIGH | C8: Бинарные эффекты | D8: CORE-080 описывает числовой strongest, но не identity одинакового бинарного эффекта | E8: CORE-080 | F8: Бинарная идентичность = EffectTypeID + variantKey + affectedRegion; источники/таймеры раздельны, механика действует один раз | G8: RESOLVED_BY_AUTHOR_2026-07-30
A9: GAP-005 | B9: HIGH | C9: Горение | D9: Не задан выбор damagePerTick при повторном горении с разными значениями | E9: CORE-112 | F9: Повтор: remaining=max(current,new), damagePerTick=max(current,new), без мгновенного дополнительного тика | G9: RESOLVED_BY_AUTHOR_2026-07-30
A10: GAP-006 | B10: HIGH | C10: Труп/воскрешение | D10: Не определено хранение/удаление/возврат эффектов трупа | E10: CQA-001; AQA-024 | F10: Смерть завершает временные эффекты и контроль; сохраняет травмы, раны, предметы, инвентарь и симбионтов; воскрешение не возобновляет | G10: RESOLVED_BY_AUTHOR_2026-07-30
A11: GAP-007 | B11: HIGH | C11: Яд Жабы | D11: SYM-144 не отвечает, блокирует ли ослабляющий stat debuff SYM-042 | E11: SYM-144; SYM-042 | F11: SYM-144 не блокирует ослабление характеристик SYM-042; блокируются только урон и контроль от яда | G11: RESOLVED_BY_AUTHOR_2026-07-30
A12: GAP-008 | B12: MEDIUM | C12: Контроль | D12: Перечень CONTROL открыт | E12: CORE-072; MON-020 | F12: CONTROL определяется только явным тегом CONTROL из закрытой карты; непомеченный эффект контролем не считается | G12: RESOLVED_BY_AUTHOR_2026-07-30
A13: GAP-009 | B13: MEDIUM | C13: Усталость | D13: CORE-002/003 не автоматизируются | E13: CORE-002–003 | F13: TRACE_ONLY | G13: KNOWN_NON_AUTOMATED
A14: GAP-010 | B14: MEDIUM | C14: Истощение | D14: MON-104 имеет ответ, но базовой механики нет | E14: MON-104 | F14: Хранить response profile; не создавать проверки | G14: ORPHANED
A15: GAP-011 | B15: HIGH | C15: Покрытия | D15: Не определены лимит, совместимость и порядок нескольких activeCoatings | E15: Items 07_Модель_экземпляра; SYM-183 | F15: Одно расходуемое покрытие на поверхность/отдельный снаряд; замена после подтверждения. Обычные снаряды стакаются, отравленные хранятся отдельно | G15: RESOLVED_BY_AUTHOR_2026-07-30
... A38: GAP-034 | B38: HIGH | C38: Коррозия Тайпана | D38: Для коррозии одежды/лёгкой брони SYM-041 нет величины, срока и снятия | E38: SYM-041 | F38: По Q-SYM-075 внешний элемент обычной одежды/лёгкой брони со спасброском ≤R6 уничтожается немедленно; не периодический эффект | G38: RESOLVED_BY_EXISTING_QA

Sheet 15_Трассировка
A1: Трассировка ключевой семантики
A2: Точные артефакты и диапазоны; полный индекс релевантных Rule ID находится на листе 06.
A4: TraceID | B4: Область | C4: Rule / contract | D4: Артефакт | E4: Локатор | F4: Нормализованная семантика | G4: Status
A5: TRACE-001 | B5: Initial clean state | C5: AQA-009 | D5: Rules v1.6 | E5: Реестр правил!B372:AH372 | F5: Нет ран, травм, кровотечения, горения, болезней, ядов и временных эффектов | G5: PASS
A6: TRACE-002 | B6: Modifier pipeline | C6: CORE-079 | D6: Rules v1.6 | E6: Реестр правил!B41:AH41 | F6: Постоянное → временное ± → ×/÷ → exact/min/max | G6: PASS
A7: TRACE-003 | B7: Effect stacking | C7: CORE-080 | D7: Rules v1.6 | E7: Реестр правил!B482:AH482 | F7: Одноимённые числовые: сильнейший, таймеры независимы | G7: PASS
A8: TRACE-004 | B8: Timers | C8: CORE-101 | D8: Rules v1.6 | E8: Реестр правил!B489:AH489 | F8: Общие длительности и периодика | G8: PASS
A9: TRACE-005 | B9: Transaction order | C9: AQA-024 | D9: Rules v1.6 | E9: Реестр правил!B387:AH387 | F9: Стабильные фазы и пересчёт после каждого тика | G9: PASS
A10: TRACE-006 | B10: Source lifecycle | C10: CQA-002 | D10: Rules v1.6 | E10: Реестр правил!B305:AH305 | F10: Поддерживаемый vs автономный эффект | G10: PASS
A11: TRACE-007 | B11: Capabilities | C11: CORE-103 | D11: Rules v1.6 | E11: Реестр правил!B57:AH57 | F11: Сознание, паралич, оглушение, пропуск | G11: PASS
A12: TRACE-008 | B12: Symbiont disabled | C12: CORE-104 | D12: Rules v1.6 | E12: Реестр правил!B58:AH58 | F12: Механические эффекты и XP выключены | G12: PASS
A13: TRACE-009 | B13: Trauma trigger | C13: CORE-117 | D13: Rules v1.6 | E13: Реестр правил!B65:AH65 | F13: Строгое сравнение R20+Z < actualDamage | G13: PASS
A14: TRACE-010 | B14: Limb trauma | C14: CORE-119 | D14: Rules v1.6 | E14: Реестр правил!B496:AH496 | F14: Сумма по конечности; disabled >6 | G14: PASS
A15: TRACE-011 | B15: Torso trauma | C15: CORE-121 | D15: Rules v1.6 | E15: Реестр правил!B67:AH67 | F15: Однократный extra HP, без рекурсии | G15: PASS
... A32: TRACE-028 | B32: Application boundary | C32: CORE-143; Q-CORE-045; GAP-030 | D32: Rules v1.6; Q&A v1.1; Effects Registry v1.2 | E32: 02_Типы_эффектов; 06_Карта_источников; 13_Операции; 14_Пробелы_и_решения | F32: Слепота, выдавливание глаз и физическая потеря зрения не создают runtime-состояние приложения | G32: PASS

Sheet 16_QA
A1: QA сочетаний, схемы и совместимости
A2: 98/98 PASS. Исходные сценарии и 38 проверок авторских решений; любой FAIL останавливает экспорт.
A4: ScenarioID | B4: Путь | C4: Given | D4: When | E4: Expected | F4: Actual | G4: Rule / contract | H4: Result
A5: EFF-QA-001 | B5: Структура | C5: Семейства | D5: Проверка уникальности ID | E5: 24 | F5: 24 | G5: Registry | H5: PASS
A6: EFF-QA-002 | B6: Структура | C6: Типы эффектов | D6: Проверка уникальности ID | E6: 67 | F6: 67 | G6: Registry | H6: PASS
A7: EFF-QA-003 | B7: Структура | C7: Болезни | D7: Проверка уникальности ID | E7: 10 | F7: 10 | G7: Registry | H7: PASS
A8: EFF-QA-004 | B8: Структура | C8: Яды | D8: Проверка уникальности ID | E8: 8 | F8: 8 | G8: Registry | H8: PASS
A9: EFF-QA-005 | B9: Матрица | C9: 24 семейств | D9: Полная неупорядоченная матрица с диагональю | E9: 300 | F9: 300 | G9: Registry | H9: PASS
A10: EFF-QA-006 | B10: Матрица | C10: Пары | D10: Проверка уникальности | E10: 300 | F10: 300 | G10: Registry | H10: PASS
A11: EFF-QA-007 | B11: Стек | C11: Одноимённые числовые 3, 5, 2 | D11: Применить CORE-080 | E11: 5 | F11: 5 | G11: CORE-080 | H11: PASS
A12: EFF-QA-008 | B12: Болезни | C12: DIS-RHINITIS дважды | D12: Сложить активные болезни | E12: {"M":-2} | F12: {"M":-2} | G12: MON-085 | H12: PASS
A13: EFF-QA-009 | B13: Болезни | C13: DIS-RHINITIS + DIS-FEVER | D13: Сложить активные болезни | E13: {"M":-12} | F13: {"M":-12} | G13: MON-085 | H13: PASS
A14: EFF-QA-010 | B14: Болезни | C14: DIS-SCABIES + DIS-MIGRAINE | D14: Сложить активные болезни | E14: {"C":-6,"D":-2,"I":-10} | F14: {"C":-6,"D":-2,"I":-10} | G14: MON-085 | H14: PASS
A15: EFF-QA-011 | B15: Болезни | C15: DIS-POISONING | D15: Проверить effectFamily | E15: DISEASE | F15: DISEASE | G15: CORE-228; MON-076 | H15: PASS
... A50: EFF-QA-046 | B50: Payload | C50: Canonical payload rows | D50: Validate SHA length | E50: 0 | F50: 0 | G50: Registry | H50: PASS
A51: EFF-QA-047 | B51: Payload | C51: Payload IDs | D51: Validate uniqueness | E51: 185 | F51: 185 | G51: Registry | H51: PASS
A52: EFF-QA-048 | B52: Семейства | C52: Effect definitions | D52: Validate every family FK | E52: 0 | F52: 0 | G52: Registry | H52: PASS
A53: EFF-QA-049 | B53: Сочетания | C53: Combination rules | D53: Validate both family FK | E53: 0 | F53: 0 | G53: Registry | H53: PASS
A54: EFF-QA-050 | B54: Болезни | C54: DIS-PNEUMONIA | D54: Validate explicit tick | E54: HP_MINUS_10_EACH_FULL_DAY | F54: HP_MINUS_10_EACH_FULL_DAY | G54: MON-080 | H54: PASS
A55: EFF-QA-051 | B55: Болезни | C55: Other named active diseases | D55: Reject implicit ticks | E55: 0 | F55: 0 | G55: MON-087 | H55: PASS
A56: EFF-QA-052 | B56: Яды | C56: All poison profiles | D56: Validate family tag | E56: 0 | F56: 0 | G56: CORE-228 | H56: PASS
A57: EFF-QA-053 | B57: Профили | C57: PRF-DEAD | D57: Validate physical actions | E57: NO | F57: NO | G57: CORE-156 | H57: PASS
A58: EFF-QA-054 | B58: Профили | C58: PRF-UNCONSCIOUS | D58: Validate armor | E58: YES | F58: YES | G58: CORE-103 | H58: PASS
A59: EFF-QA-055 | B59: Профили | C59: PRF-PARALYZED | D59: Validate mental conditional | E59: true | F59: true | G59: CORE-103 | H59: PASS
A60: EFF-QA-056 | B60: Матрица | C60: Family pairs | D60: Surface blocked interactions | E60: true | F60: true | G60: Registry | H60: PASS
A61: EFF-QA-057 | B61: Операции | C61: ASSIGN_DISEASE | D61: Reject unknown disease | E61: true | F61: true | G61: CQA-060 | H61: PASS
A62: EFF-QA-058 | B62: Операции | C62: CREATE_WOUND | D62: Block generic creation | E62: true | F62: true | G62: Registry | H62: PASS
A63: EFF-QA-059 | B63: Операции | C63: CLONE_RUNTIME_STATE | D63: Generate new UUID | E63: true | F63: true | G63: Bestiary 09_Контракты | H63: PASS
... A102: EFF-QA-098 | B102: Слепота | C102: Попытка универсального снятия слепоты | D102: Remove effect | E102: NOT_APPLICABLE; no modeled state | F102: NOT_APPLICABLE; no modeled state | G102: GAP-030 | H102: PASS

Sheet 17_Справочники
A1: Runtime-справочники
A2: Закрытые коды для сериализации; SOURCE_SPECIFIC не разрешает придумывать неизвестную механику.
A4: Dictionary | B4: Value | C4: Определение | D4: Rule refs
A5: EFFECT_FAMILY | B5: FAM-LIFECYCLE | C5: Жизненный цикл | D5: CORE-152–156; CORE-182; CORE-222
A6: EFFECT_FAMILY | B6: FAM-CONSCIOUSNESS | C6: Сознание | D6: CORE-061; CORE-103; MON-075
A7: EFFECT_FAMILY | B7: FAM-PHYSICAL_CONTROL | C7: Физический контроль | D7: CORE-103; CORE-138; CORE-141; CORE-143–144
A8: EFFECT_FAMILY | B8: FAM-MENTAL_CONTROL | C8: Ментальный контроль | D8: CORE-178; CORE-181; CORE-221; MON-038
A9: EFFECT_FAMILY | B9: FAM-MOBILITY_POSITION | C9: Положение и мобильность | D9: CORE-138–144; MON-165
A10: EFFECT_FAMILY | B10: FAM-ACTION_ECONOMY | C10: Действия и серия | D10: CORE-031; CORE-043–048; CORE-070; MON-150; MON-160
A11: EFFECT_FAMILY | B11: FAM-TRAUMA | C11: Травмы | D11: CORE-117; CORE-119–121
A12: EFFECT_FAMILY | B12: FAM-WOUND_BLEEDING | C12: Раны и кровотечения | D12: CORE-059; CORE-063
A13: EFFECT_FAMILY | B13: FAM-DISEASE | C13: Болезни | D13: MON-075–087; CQA-060
A14: EFFECT_FAMILY | B14: FAM-POISON | C14: Яды | D14: CORE-109; CORE-228; SYM-039; SYM-042; SYM-045
A15: EFFECT_FAMILY | B15: FAM-FIRE | C15: Огонь и горение | D15: CORE-112; CORE-114
... A93: STACK_POLICY | B93: MAX_PENALTY_SAME_REGION_RESTRICTIONS_UNION | C93: Для одной зоны действует наиболее строгий числовой штраф; самостоятельные ограничения и сроки сохраняются | D93: COMB-031

Sheet 18_Payload_JSON
A1: Canonical payload JSON и SHA-256 — v1.2
A2: Стабильно отсортированный компактный JSON для семейств, типов, болезней, ядов, травм, сочетаний и runtime-схемы.
A4: PayloadID | B4: EntityType | C4: EntityID | D4: Canonical JSON | E4: SHA-256 | F4: UTF-8 bytes | G4: Status
A5: PAY-001 | B5: EffectFamily | C5: FAM-LIFECYCLE | D5: {"bucket":"actorFlags / currentEffects","defaultComposition":"TERMINAL_OR_SOURCE_SPECIFIC","id":"FAM-LIFECYCLE","name":"Жизненный цикл","refs":"CORE-152–156; CORE-182; CORE-222","responseStage":"AFTER_DAMAGE_RECALC","scope":"Тяжёлое ранение, таймер смерти, окончательная смерть"} | E5: 87e6730a09779d98290311e9546040f08f7c859b8a929f36b53d81e0211ea1b1 | F5: 339 | G5: PASS
A6: PAY-002 | B6: EffectFamily | C6: FAM-CONSCIOUSNESS | D6: {"bucket":"actorFlags / currentEffects","defaultComposition":"RESTRICTIONS_UNION","id":"FAM-CONSCIOUSNESS","name":"Сознание","refs":"CORE-061; CORE-103; MON-075","responseStage":"AFTER_EACH_CONSEQUENCE","scope":"Бессознательность и сон"} | E6: 60513cbd9b72e8570574c9089a94564a3a162143b678b813b56833b1e24f850d | F6: 266 | G6: PASS
A7: PAY-003 | B7: EffectFamily | C7: FAM-PHYSICAL_CONTROL | D7: {"bucket":"currentEffects","defaultComposition":"RESTRICTIONS_UNION; MAX_ACTION_PENALTY; SOURCES_INDEPENDENT","id":"FAM-PHYSICAL_CONTROL","name":"Физический контроль","refs":"CORE-103; CORE-138; CORE-141; CORE-143–144","responseStage":"BEFORE_APPLY_CONTROL","scope":"Паралич, оглушение, захват, удержание, опутывание, кокон"} | E7: e9417a26409b0541bcc779b400d6b8f70e4b5d0673fc302ebde04b2f5f47ec12 | F7: 391 | G7: PASS
A8: PAY-004 | B8: EffectFamily | C8: FAM-MENTAL_CONTROL | D8: {"bucket":"currentEffects / controlLease","defaultComposition":"ONE_EFFECTIVE_CONTROLLER_BY_PRIORITY","id":"FAM-MENTAL_CONTROL","name":"Ментальный контроль","refs":"CORE-178; CORE-181; CORE-221; MON-038","responseStage":"BEFORE_APPLY_CONTROL","scope":"Принуждение, бегство, внешний контроллер"} | E8: 3a6eb4beda668d7ab33e68a0d04a573023c62f8bab47e7e67b197fa05615205a | F8: 347 | G8: PASS
A9: PAY-005 | B9: EffectFamily | C9: FAM-MOBILITY_POSITION | D9: {"bucket":"currentEffects","defaultComposition":"RESTRICTIONS_UNION","id":"FAM-MOBILITY_POSITION","name":"Положение и мобильность","refs":"CORE-138–144; MON-165","responseStage":"COMMAND_FILTER","scope":"Сбит с ног, выгодная позиция, вынужденное перемещение"} | E9: 89ebb97e76ce0bb2134fafc5deb2263bc5e618c98e1b0d0ac4332cea75ca6a78 | F9: 327 | G9: PASS
A10: PAY-006 | B10: EffectFamily | C10: FAM-ACTION_ECONOMY | D10: {"bucket":"currentEffects","defaultComposition":"SOURCE_SPECIFIC; MIN_ZERO","id":"FAM-ACTION_ECONOMY","name":"Действия и серия","refs":"CORE-031; CORE-043–048; CORE-070; MON-150; MON-160","responseStage":"TURN_START_OR_CONSUME","scope":"Бонусы и штрафы действий, пропуск хода, следующий ход/серия"} | E10: c63e28643d89b8a39e54895b9e482f343765ab253e34ad118b46df510ca46807 | F10: 363 | G10: PASS
A11: PAY-007 | B11: EffectFamily | C11: FAM-TRAUMA | D11: {"bucket":"currentTraumas / derivedProjection","defaultComposition":"SAME_ZONE_ADDITIVE; DIFFERENT_ZONE_INDEPENDENT","id":"FAM-TRAUMA","name":"Травмы","refs":"CORE-117; CORE-119–121","responseStage":"AFTER_ACTUAL_DAMAGE","scope":"Зональные травмы и отключение конечности"} | E11: 3aa619f12a18b440af00273921ca88d6a27d301ee1b436556b165ec1a7fe3556 | F11: 316 | G11: PASS
A12: PAY-008 | B12: EffectFamily | C12: FAM-WOUND_BLEEDING | D12: {"bucket":"currentWounds","defaultComposition":"PER_EVENT_PER_REGION; BLEEDING_PER_WOUND","id":"FAM-WOUND_BLEEDING","name":"Раны и кровотечения","refs":"CORE-059; CORE-063","responseStage":"SOURCE_SPECIFIC","scope":"Формализованная рана, кровотечение и профилактика через рану"} | E12: add69ea3de0cba1c434c3f74b0f4da4eea0314e7ce888157f35dc5ff6878155a | F12: 348 | G12: PASS
A13: PAY-009 | B13: EffectFamily | C13: FAM-DISEASE | D13: {"bucket":"currentEffects","defaultComposition":"SAME_DISEASE_NO_STACK; DIFFERENT_DISEASE_ADD","id":"FAM-DISEASE","name":"Болезни","refs":"MON-075–087; CQA-060","responseStage":"ASSIGN_REMOVE_RECALC","scope":"Назначенные мастером заболевания и их модификаторы"} | E13: a8ff8d9f9f7b4319da5e9960479076c8fd2de00ad2ea8170f9152ea71bcf7af3 | F13: 315 | G13: PASS
A14: PAY-010 | B14: EffectFamily | C14: FAM-POISON | D14: {"bucket":"currentEffects / activeCoatings","defaultComposition":"PROFILE_SPECIFIC","id":"FAM-POISON","name":"Яды","refs":"CORE-109; CORE-228; SYM-039; SYM-042; SYM-045","responseStage":"IMMUNITY_BEFORE_ROLL","scope":"POISON payload, урон, дебафф, счётчик и зональный паралич"} | E14: 6adde4468a9ac553519c6d283d0230f0a0c0a7dc3902ebd4e5ac6c411546676b | F14: 314 | G14: PASS
A15: PAY-011 | B15: EffectFamily | C15: FAM-FIRE | D15: {"bucket":"currentEffects","defaultComposition":"ONE_BINARY_STATE; MAX_REMAINING_DURATION","id":"FAM-FIRE","name":"Огонь и горение","refs":"CORE-112; CORE-114","responseStage":"BEFORE_APPLY_BURN","scope":"Бинарное горение персонажа и огненные ответы"} | E15: c8a688f50669286e22b21bda17f50bf2117600cef5ff6d33144c410484b9f9e4 | F15: 303 | G15: PASS
A16: PAY-012 | B16: EffectFamily | C16: FAM-PERIODIC_DAMAGE | D16: {"bucket":"currentEffects","defaultComposition":"PER_INSTANCE; ORDER_BY_CREATED_AT_UUID","id":"FAM-PERIODIC_DAMAGE","name":"Периодический урон","refs":"CORE-101; AQA-024","responseStage":"TIME_PHASE_1","scope":"Автономные и поддерживаемые тики урона"} | E16: 343be1070d0f798b908f25641847920eb31fd458f9aa0eebb7d7f09b4abda79b | F16: 302 | G16: PASS
... A189: PAY-185 | B189: RuntimeSchema | C189: EFFECT_RUNTIME_SCHEMA_V1_2 | D189: {"contracts":[["EffectDefinition","effectTypeId","string","YES","Стабильный ID из 02_Типы_эффектов","NEW_SUPPLEMENT_SCHEMA"],["EffectDefinition","familyCode","enum","YES","FK на 01_Семейства","NEW_SUPPLEMENT_SCHEMA"],["EffectDefinition","displayName","string","YES","Пользовательское имя","NEW_SUPPLEMENT_SCHEMA"],["EffectDefinition","stateBucket","enum","YES","currentEffects/currentTraumas/currentWounds/actorFlags/item/source/narrative","NEW_SUPPLEMENT_SCHEMA"],["EffectDefinition","defaultStackPolicy","enum","YES","Не заменяет частную карточку источника","NEW_SUPPLEMENT_SCHEMA"],["EffectDefinition","defaultSourceLifecycle","enum","YES","SOURCE_MAINTAINED/AUTONOMOUS/SOURCE_SPECIFIC","NEW_SUPPLEMENT_SCHEMA"],["EffectDefinition","automationStatus","enum","YES","AUTOMATED/PARTIAL/TRACE_ONLY/BLOCKED/NOT_MODELED","NEW_SUPPLEMENT_SCHEMA"],["EffectInstance","effectInstanceId","UUID","YES","Уникален в mutable graph; новый UUID при клонировании","REQUIRED"],["EffectInstance","effectTypeId","string","YES","FK EffectDefinition","REQUIRED"],["EffectInstance","familyCode","enum","YES","Дублируется для быстрого ответа и валидируется по типу","REQUIRED"],["EffectInstance","targetActorId","UUID","YES","Владелец состояния","REQUIRED"],["EffectInstance","targetRegionId","string|null","CONDITIONAL","Обязателен для конечности/зоны","REQUIRED_IF_REGION"],["EffectInstance","sourceRuleIds","string[]","YES","Нормативные Rule ID","REQUIRED"],["EffectInstance","sourceEntityId","UUID|null","CONDITIONAL","Актор/объект источника","SOURCE_SPECIFIC"],["EffectInstance","sourceInstanceId","UUID|string|null","CONDITIONAL","Способность, предмет, зона, покрытие или связь","SOURCE_SPECIFIC"],["EffectInstance","sourceSnapshot","object|null","CONDITIONAL","Последний читаемый уровень/параметры для автономного эффекта","CQA-002"],["EffectInstance","sourceLifecyclePolicy","enum","YES","SOURCE_MAINTAINED/AUTONOMOUS/SOURCE_SPECIFIC","REQUIRED"],["EffectInstance","stackingKey","string","YES","Не выводить молча из displayName; брать из типа/источника","REQUIRED"],["EffectInstance","payload","object","YES","Типизированные значения конкретного эффекта","REQUIRED"],["EffectInstance","magnitude","number|object|null","CONDITIONAL","Число для CORE-080 либо структурированный пакет","SOURCE_SPECIFIC"],["EffectInstance","tags","string[]","YES","CONTROL/POISON/DISEASE и другие явно подтверждённые теги","REQUIRED"],["EffectInstance","createdAt","timestamp","YES","Для стабильного порядка","AQA-024"],["EffectInstance","startsAt","timestamp|turnRef","YES","Момент начала","REQUIRED"],["EffectInstance","expiresAt","timestamp|turnRef|null","CONDITIONAL","NULL только для бессрочного/условного","REQUIRED_IF_TIMED"],["EffectInstance","remainingExact","decimal|null","CONDITIONAL","Точный остаток при конвертации","Q-CORE-063"],["EffectInstance","durationUnit","enum|null","CONDITIONAL","TURN/ROUND/MINUTE/HOUR/DAY/COMBAT/CONDITION","REQUIRED_IF_TIMED"],["EffectInstance","tickSchedule","object|null","CONDITIONAL","Фаза, период и nextTickAt","REQUIRED_IF_PERIODIC"],["EffectInstance","lastTickAt","timestamp|turnRef|null","NO","Аудит дедупликации тика","PERIODIC"],["EffectInstance","status","enum","YES","PENDING/ACTIVE/SUSPENDED/EXPIRED/REMOVED/REPLACED/BLOCKED","REQUIRED"],["EffectInstance","revision","integer>=1","YES","Изменение мастером создаёт новую версию, старую завершает","AQA-045"],["EffectInstance","removalReason","enum|null","NO","EXPIRY/CURE/CLEANSE/DAMAGE/SOURCE_INVALID/REPLACED/GM/DEATH","AUDIT"],["EffectInstance","createdBy","enum","YES","RULE/PLAYER_COMMAND/GM/SYSTEM","AUDIT"],["DiseaseInstance","diseaseId","string","YES","FK 03_Болезни; effectTypeId=EFF-DISEASE-INSTANCE","REQUIRED"],["DiseaseInstance","assignedByGM","boolean","YES","Для приложения true по CQA-060","CQA-060"],["DiseaseInstance","modifierComponents","object[]","YES","Статовые и проверочные модификаторы","MON-076–084"],["DiseaseInstance","dailyTick","object|null","CONDITIONAL","Только если прямо задано","MON-080; MON-087"],["PoisonInstance","poisonProfileId","string","YES","FK 04_Яды","REQUIRED"],["PoisonInstance","poisonSourceKind","enum","YES","ORDINARY/NATURAL/ARTIFICIAL/SYMBIOTIC/CANONICAL","CORE-228"],["PoisonInstance","deliveryKind","enum","YES","CONTACT/INHALED/INGESTED/INJECTED/COATING/SOURCE_SPECIFIC","REQUIRED"],["TraumaInstance","traumaInstanceId","UUID","YES","Элемент currentTraumas","REQUIRED"],["TraumaInstance","regionId","string","YES","Зона анатомии","REQUIRED"],["TraumaInstance","traumaValue","number","YES","Суммируется по одной конечности по CORE-119","CORE-119"],["WoundInstance","woundInstanceId","UUID","YES","Элемент currentWounds","REQUIRED"],["WoundInstance","woundType","enum","YES","GENERIC/BLEEDING; создание только SOURCE_CREATES_WOUND_OR_GM","REQUIRED"],["EffectResponse","responseProfileId","string","YES","Стабильный ID 10_Иммунитеты","REQUIRED"],["EffectResponse","effectFamily","enum","YES","Семейство входящего payload","REQUIRED"],["EffectResponse","sourceScope","enum","YES","ANY/NATURAL/EXTERNAL/OWN_SOURCE/...","REQUIRED"],["EffectResponse","response","enum","YES","IMMUNE_BEFORE_ROLL/CHECK_MODIFIER/DAMAGE_REDUCTION/...","REQUIRED"],["DerivedStateProjection","canPhysicalAct","boolean","YES","Пересчитывается из активных состояний","DERIVED"],["DerivedStateProjection","canMentalAct","boolean|conditional","YES","С учётом речи/движения/контроля тела","DERIVED"],["DerivedStateProjection","canReact","boolean","YES","Пересчитывается","DERIVED"],["DerivedStateProjection","canActiveDefend","boolean","YES","Броня отдельно","DERIVED"],["DerivedStateProjection","effectiveControllerId","UUID|string|null","YES","Результат CORE-181/221","DERIVED"],["DerivedStateProjection","regionPenaltyById","map<regionId,number>","YES","Для одной зоны действует наиболее строгий числовой штраф из травмы/онемения; штрафы не складываются, самостоятельные ограничения объединяются","COMB-031"],["EffectInstance","variantKey","string","YES","Явный вариант эффекта; пустая строка допустима для единственного варианта","GAP-004"],["EffectInstance","aggregateKey","string","YES","Для бинарных эффектов: effectTypeId|variantKey|targetRegionId; источники и таймеры остаются отдельными","GAP-004"],["EffectInstance","deathDisposition","enum","YES","TERMINATE_ON_DEATH/PRESERVE_ON_CORPSE/SOURCE_SPECIFIC","GAP-006"],["PoisonInstance","secondaryControlApplicable","boolean","YES","false для парализующего яда на негуманоиде; остальной payload сохраняется","GAP-017"],["WoundInstance","regionId","string","YES","Зона одной раны, созданной одним событием","GAP-001"],["WoundInstance","creationPolicy","enum","YES","SOURCE_CREATES_WOUND_OR_GM","GAP-001"],["WoundInstance","damagePerTick","number|null","CONDITIONAL","Обязателен только для BLEEDING; значения по умолчанию нет","GAP-002"],["WoundInstance","tickPhase","enum|null","CONDITIONAL","END_OF_TARGET_TURN для BLEEDING","GAP-002"],["WoundInstance","healingPolicy","enum","YES","EXPLICIT_TREATMENT_OR_GM_ONLY","GAP-001–003"],["PreparedCoatingInstance","coatingInstanceId","UUID","YES","Уникальный экземпляр расходуемого покрытия","GAP-011"],["PreparedCoatingInstance","hostItemInstanceId","UUID","YES","Экземпляр предмета либо отдельного отравленного снаряда","GAP-011"],["PreparedCoatingInstance","surfaceKey","string","YES","Одна поражающая поверхность; одновременно одно расходуемое покрытие","GAP-011"],["PreparedCoatingInstance","inventoryMode","enum","YES","STACKABLE_UNCOATED_PROJECTILES/INDIVIDUAL_POISONED_PROJECTILE/INDIVIDUAL_ITEM_COATING","GAP-011"],["PreparedCoatingInstance","consumptionState","enum","YES","ACTIVE/CONSUMED/REPLACED","GAP-011"],["PreparedCoatingInstance","replacesCoatingId","UUID|null","NO","Заполняется после подтверждённой замены покрытия","GAP-011"]]} | E189: 1620fcec05d3e0e82e57f84b68b6790fd8f275d7b7ff2bd03a9a797ceba36eb3 | F189: 9237 | G189: PASS

Sheet 19_Зависимости
A1: Неизменяемые зависимости
A2: Контрольные суммы вычислены непосредственно перед сборкой. Реестр является новым дополнением и не меняет Manifest v1.1.
A4: Файл | B4: Версия | C4: Роль | D4: Размер, байт | E4: SHA-256 | F4: Mutation policy | G4: Dependency tuple | H4: Status
A5: Symbiosis_V7_Executable_Rules_Registry_v1.6.xlsx | B5: v1.6 | C5: NORMATIVE_RULES | D5: 920352 | E5: 7fe8939403bced0436a009c80fd97830b96a3b2dbf58c9271970e2a8869c3c35 | F5: IMMUTABLE_AGREED_INPUT | G5: Rules v1.6 | Character-Skills-Symbionts v1.1 | Items v1.5_with_icons | Bestiary v1.3 | Sentient v1.2 | H5: PASS
A6: Symbiosis_V7_Character_Skills_Symbionts_Registry_v1.1.xlsx | B6: v1.1 | C6: NORMATIVE_CHARACTER | D6: 697755 | E6: cdc31421568695e9d88c794179918567c551576756b8a2252b1de74c32245dba | F6: IMMUTABLE_AGREED_INPUT | G6: Rules v1.6 | Character-Skills-Symbionts v1.1 | Items v1.5_with_icons | Bestiary v1.3 | Sentient v1.2 | H6: PASS
A7: Symbiosis_V7_Item_Registry_v1.5_with_icons.xlsx | B7: v1.5_with_icons | C7: NORMATIVE_ITEMS | D7: 1102446 | E7: 09d5e2a5386e318eeb87d4f7b81b3aebb6f9e1669638042f8c58dc9fd92ac19d | F7: IMMUTABLE_AGREED_INPUT | G7: Rules v1.6 | Character-Skills-Symbionts v1.1 | Items v1.5_with_icons | Bestiary v1.3 | Sentient v1.2 | H7: PASS
A8: Symbiosis_V7_Canonical_Bestiary_Registry_v1.3.xlsx | B8: v1.3 | C8: NORMATIVE_BESTIARY | D8: 5888594 | E8: 53253a350673932367812a4f221297a1d6bdbd979a82585df1ab37709be77ae3 | F8: IMMUTABLE_AGREED_INPUT | G8: Rules v1.6 | Character-Skills-Symbionts v1.1 | Items v1.5_with_icons | Bestiary v1.3 | Sentient v1.2 | H8: PASS
A9: Symbiosis_V7_Default_Sentient_Enemy_Registry_v1.2.xlsx | B9: v1.2 | C9: NORMATIVE_SENTIENT | D9: 17138567 | E9: b4c8ff7199e8a9798e5e4928599ee63c9efba3b4244b9c412666a70111ad175f | F9: IMMUTABLE_AGREED_INPUT | G9: Rules v1.6 | Character-Skills-Symbionts v1.1 | Items v1.5_with_icons | Bestiary v1.3 | Sentient v1.2 | H9: PASS
A10: Symbiosis_V7_Default_Sentient_Enemy_Runtime_Pack_v1.2.zip | B10: v1.2 | C10: DERIVED_RUNTIME_PACK | D10: 17051280 | E10: 614f0da1c3128aebbb28d67a68a89ccd189a067c57d407c92536425e46072cdc | F10: IMMUTABLE_AGREED_INPUT | G10: Rules v1.6 | Character-Skills-Symbionts v1.1 | Items v1.5_with_icons | Bestiary v1.3 | Sentient v1.2 | H10: PASS
A11: Symbiosis_V7_All_Questions_and_Answers_Registry_v1.1.xlsx | B11: v1.1 | C11: AUTHORITATIVE_QA | D11: 185292 | E11: cc780d920d3f2c08626b66e2f32e2a0b7f3012513b0c84563c2ed3c72387d1c1 | F11: IMMUTABLE_AGREED_INPUT | G11: Rules v1.6 | Character-Skills-Symbionts v1.1 | Items v1.5_with_icons | Bestiary v1.3 | Sentient v1.2 | H11: PASS
A12: Symbiosis_V7_Cross_Registry_Audit_Report_v1.1.xlsx | B12: v1.1 | C12: AUDIT | D12: 33567 | E12: 4704a9d8a1af5d8d9b60e3fd26e21334ab484b5fcedc8f8e25674023882b1ae2 | F12: IMMUTABLE_AGREED_INPUT | G12: Rules v1.6 | Character-Skills-Symbionts v1.1 | Items v1.5_with_icons | Bestiary v1.3 | Sentient v1.2 | H12: PASS
A13: Symbiosis_V7_Development_Baseline_Manifest_v1.1.xlsx | B13: v1.1 | C13: BASELINE_MANIFEST | D13: 26329 | E13: e813b5b3beac184708345489c24e472f73e069765a69a291898de96fef529787 | F13: IMMUTABLE_AGREED_INPUT | G13: Rules v1.6 | Character-Skills-Symbionts v1.1 | Items v1.5_with_icons | Bestiary v1.3 | Sentient v1.2 | H13: PASS

Sheet 20_Контроль
A1: Формульный контроль выпуска
A2: Actual и Result вычисляются формулами по таблицам реестра. Любой FAIL является блокером.
A4: ControlID | B4: Проверка | C4: Expected | D4: Actual | E4: Result | F4: Источник
A5: CTRL-001 | B5: Family count | C5: 24 | D5: =COUNTA('01_Семейства'!$A$5:$A$28) -> 24 | E5: =IF(C5=D5,"PASS","FAIL") -> PASS | F5: 01_Семейства
A6: CTRL-002 | B6: Effect type count | C6: 67 | D6: =COUNTA('02_Типы_эффектов'!$A$5:$A$71) -> 67 | E6: =IF(C6=D6,"PASS","FAIL") -> PASS | F6: 02_Типы_эффектов
A7: CTRL-003 | B7: Disease count | C7: 10 | D7: =COUNTA('03_Болезни'!$A$5:$A$14) -> 10 | E7: =IF(C7=D7,"PASS","FAIL") -> PASS | F7: 03_Болезни
A8: CTRL-004 | B8: Poison profile count | C8: 8 | D8: =COUNTA('04_Яды'!$A$5:$A$12) -> 8 | E8: =IF(C8=D8,"PASS","FAIL") -> PASS | F8: 04_Яды
A9: CTRL-005 | B9: Injury/wound count | C9: 8 | D9: =COUNTA('05_Травмы_и_раны'!$A$5:$A$12) -> 8 | E9: =IF(C9=D9,"PASS","FAIL") -> PASS | F9: 05_Травмы_и_раны
A10: CTRL-006 | B10: Rules source index | C10: 306 | D10: =COUNTA('06_Карта_источников'!$A$5:$A$310) -> 306 | E10: =IF(C10=D10,"PASS","FAIL") -> PASS | F10: 06_Карта_источников
A11: CTRL-007 | B11: Combination rule count | C11: 67 | D11: =COUNTA('07_Правила_сочетаний'!$A$5:$A$71) -> 67 | E11: =IF(C11=D11,"PASS","FAIL") -> PASS | F11: 07_Правила_сочетаний
A12: CTRL-008 | B12: Family matrix expected | C12: 300 | D12: =COUNTA('08_Матрица_семейств'!$A$5:$A$304) -> 300 | E12: =IF(C12=D12,"PASS","FAIL") -> PASS | F12: 08_Матрица_семейств
A13: CTRL-009 | B13: Capability profile count | C13: 21 | D13: =COUNTA('09_Профили_дееспособности'!$A$5:$A$25) -> 21 | E13: =IF(C13=D13,"PASS","FAIL") -> PASS | F13: 09_Профили_дееспособности
A14: CTRL-010 | B14: Response profile count | C14: 20 | D14: =COUNTA('10_Иммунитеты'!$A$5:$A$24) -> 20 | E14: =IF(C14=D14,"PASS","FAIL") -> PASS | F14: 10_Иммунитеты
A15: CTRL-011 | B15: Time policy count | C15: 21 | D15: =COUNTA('11_Таймеры_порядок'!$A$5:$A$25) -> 21 | E15: =IF(C15=D15,"PASS","FAIL") -> PASS | F15: 11_Таймеры_порядок
A16: CTRL-012 | B16: Runtime field count | C16: 69 | D16: =COUNTA('12_Runtime_контракты'!$A$5:$A$73) -> 69 | E16: =IF(C16=D16,"PASS","FAIL") -> PASS | F16: 12_Runtime_контракты
A17: CTRL-013 | B17: Operation count | C17: 25 | D17: =COUNTA('13_Операции'!$A$5:$A$29) -> 25 | E17: =IF(C17=D17,"PASS","FAIL") -> PASS | F17: 13_Операции
A18: CTRL-014 | B18: Gap count | C18: 34 | D18: =COUNTA('14_Пробелы_и_решения'!$A$5:$A$38) -> 34 | E18: =IF(C18=D18,"PASS","FAIL") -> PASS | F18: 14_Пробелы_и_решения
A19: CTRL-015 | B19: Trace count | C19: 28 | D19: =COUNTA('15_Трассировка'!$A$5:$A$32) -> 28 | E19: =IF(C19=D19,"PASS","FAIL") -> PASS | F19: 15_Трассировка
A20: CTRL-016 | B20: QA total | C20: 98 | D20: =COUNTA('16_QA'!$A$5:$A$102) -> 98 | E20: =IF(C20=D20,"PASS","FAIL") -> PASS | F20: 16_QA
A21: CTRL-017 | B21: QA PASS | C21: 98 | D21: =COUNTIF('16_QA'!$H$5:$H$102,"PASS") -> 98 | E21: =IF(C21=D21,"PASS","FAIL") -> PASS | F21: 16_QA
A22: CTRL-018 | B22: Dictionary count | C22: 89 | D22: =COUNTA('17_Справочники'!$A$5:$A$93) -> 89 | E22: =IF(C22=D22,"PASS","FAIL") -> PASS | F22: 17_Справочники
A23: CTRL-019 | B23: Payload count | C23: 185 | D23: =COUNTA('18_Payload_JSON'!$A$5:$A$189) -> 185 | E23: =IF(C23=D23,"PASS","FAIL") -> PASS | F23: 18_Payload_JSON
A24: CTRL-020 | B24: Dependency count | C24: 9 | D24: =COUNTA('19_Зависимости'!$A$5:$A$13) -> 9 | E24: =IF(C24=D24,"PASS","FAIL") -> PASS | F24: 19_Зависимости
A25: CTRL-021 | B25: Open GAP decisions | C25: 0 | D25: =COUNTIF('14_Пробелы_и_решения'!$G$5:$G$38,"AUTHOR_DECISION_REQUIRED") -> 0 | E25: =IF(C25=D25,"PASS","FAIL") -> PASS | F25: 14_Пробелы_и_решения
A26: CTRL-022 | B26: Unresolved combination branches | C26: 0 | D26: =COUNTIF('07_Правила_сочетаний'!$L$5:$L$71,"AUTHOR_DECISION_REQUIRED") -> 0 | E26: =IF(C26=D26,"PASS","FAIL") -> PASS | F26: 07_Правила_сочетаний
A27: CTRL-023 | B27: Explicitly excluded blindness definitions | C27: 1 | D27: =COUNTIFS('02_Типы_эффектов'!$K$5:$K$71,"NOT_MODELED",'02_Типы_эффектов'!$L$5:$L$71,"EXCLUDED_FROM_RUNTIME") -> 1 | E27: =IF(C27=D27,"PASS","FAIL") -> PASS | F27: 02_Типы_эффектов
A28: CTRL-024 | B28: Payload SHA rows PASS | C28: 185 | D28: =COUNTIF('18_Payload_JSON'!$G$5:$G$189,"PASS") -> 185 | E28: =IF(C28=D28,"PASS","FAIL") -> PASS | F28: 18_Payload_JSON

Sheet 21_Изменения_v1.0
A1: Журнал выпуска v1.0
A2: Новый самостоятельный артефакт; согласованные входы и их манифест не редактировались.
A4: № | B4: Область | C4: Изменение | D4: Основание | E4: Результат | F4: Совместимость
A5: 1 | B5: Схема | C5: Введены 24 семейства и стабильные EffectTypeID | D5: Отсутствие общего словаря состояний | E5: 67 типов | F5: PASS
A6: 2 | B6: Болезни | C6: Нормализованы девять активных болезней и Поветрие TRACE_ONLY | D6: MON-076–085; MON-058–060 | E6: 10 DiseaseID | F6: PASS
A7: 3 | B7: Яды | C7: Разделены poison profiles и болезнь «Отравление» | D7: CORE-228 | E7: 8 профилей | F7: PASS
A8: 4 | B8: Сочетания | C8: Добавлены явные resolvers и полная матрица семейств | D8: CORE-079–080 + частные правила | E8: 65 правил / 300 пар | F8: PASS
A9: 5 | B9: Дееспособность | C9: Добавлены производные профили сложных состояний | D9: CORE-103; CORE-181 | E9: 21 профилей | F9: PASS
A10: 6 | B10: Runtime | C10: Определена entry schema существующих state arrays | D10: Sentient/Bestiary gaps | E10: 53 полей | F10: PASS
A11: 7 | B11: Безопасность | C11: Неопределённые ветви помечены и локально блокируются | D11: Запрет авторских допущений | E11: 34 записей | F11: PASS
A12: 8 | B12: Трассировка | C12: Проиндексированы релевантные карточки Rules | D12: Rules v1.6 read-only extraction | E12: 306 строк | F12: PASS
A13: 9 | B13: Payload | C13: Сформированы canonical JSON и SHA-256 | D13: Runtime delivery | E13: 183 payload | F13: PASS
A14: 10 | B14: QA | C14: Проверены структура, стек, болезни, таймеры, ответы и сочетания | D14: Release gate | E14: 60/60 PASS | F14: PASS
A15: 11 | B15: Совместимость | C15: Зафиксированы SHA-256 девяти неизменяемых входов | D15: Прямой запрос пользователя | E15: 9 артефактов | F15: PASS
A16: 12 | B16: Manifest | C16: Development Baseline Manifest v1.1 не изменён | D16: Запрет менять согласованные артефакты | E16: Supplement only | F16: PASS

Sheet 22_Изменения_v1.1
A1: Журнал выпуска v1.1
A2: Авторские ответы закрывают 21 GAP; согласованная базовая линия остаётся неизменной.
A4: № | B4: Область | C4: Изменение | D4: Основание | E4: Результат | F4: Совместимость
A5: 1 | B5: Раны | C5: Формализовано создание, зона и явное снятие ран | D5: GAP-001 | E5: DEFINED | F5: PASS
A6: 2 | B6: Кровотечение | C6: Введены явный damagePerTick, per-wound экземпляры и end-of-turn tick | D6: GAP-002 | E6: DEFINED | F6: PASS
A7: 3 | B7: Травмы | C7: Зафиксировано отсутствие автоматического восстановления | D7: GAP-003; GAP-029 | E7: DEFINED | F7: PASS
A8: 4 | B8: Стек | C8: Определены binary aggregate key, горение, контроль и щит | D8: GAP-004–005; GAP-012–013 | E8: DEFINED | F8: PASS
A9: 5 | B9: Смерть | C9: Определено завершение и сохранение состояний трупа | D9: GAP-006 | E9: DEFINED | F9: PASS
A10: 6 | B10: Иммунитет | C10: SYM-144 пропускает stat debuff SYM-042 | D10: GAP-007 | E10: DEFINED | F10: PASS
A11: 7 | B11: CONTROL | C11: Явный закрытый тег стал единственным классификатором | D11: GAP-008 | E11: DEFINED | F11: PASS
A12: 8 | B12: Покрытия | C12: Один coating на поверхность; обычные снаряды stackable, отравленные individual | D12: GAP-011 | E12: DEFINED | F12: PASS
A13: 9 | B13: Мульти-источник | C13: Пеленальщица, Жаба и Вивисектор получили per-source правила | D13: GAP-014–016 | E13: DEFINED | F13: PASS
A14: 10 | B14: Негуманоиды | C14: Парализующий яд не создаёт paralysis secondary, остальные последствия сохраняются | D14: GAP-017 | E14: DEFINED | F14: PASS
A15: 11 | B15: Округление | C15: Введена half-up/min-one политика R20/3 | D15: GAP-018 | E15: DEFINED | F15: PASS
A16: 12 | B16: Нэйт | C16: Добавлена GM-операция восстановления герметичности вне боя | D16: GAP-019 | E16: DEFINED | F16: PASS
... A26: 22 | B26: Дата | C26: Дата выпуска зафиксирована | D26: 2026-07-30 | E26: 2026-07-30 | F26: PASS

Sheet 23_Изменения_v1.2
A1: Журнал выпуска v1.2
A2: Закрыты две последние локальные развилки; согласованная базовая линия остаётся неизменной.
A4: № | B4: Область | C4: Изменение | D4: Основание | E4: Результат | F4: Совместимость
A5: 1 | B5: Травма+онемение | C5: Для одной конечности числовые штрафы не складываются; действует наиболее строгий | D5: Прямой ответ пользователя 2026-07-31 | E5: DEFINED | F5: PASS
A6: 2 | B6: Ограничения | C6: Самостоятельные нефункциональные ограничения объединяются | D6: COMB-031 | E6: DEFINED | F6: PASS
A7: 3 | B7: Снятие | C7: Снятие онемения не устраняет травму; снятие травмы не завершает онемение | D7: COMB-031 | E7: DEFINED | F7: PASS
A8: 4 | B8: Слепота | C8: Выдавливание глаз и иная потеря зрения исключены из модели приложения | D8: Q-CORE-045; прямой ответ пользователя 2026-07-31 | E8: NOT_MODELED | F8: PASS
A9: 5 | B9: CORE-143 | C9: В приложении сохраняется только исполнимая ветвь болевого приёма | D9: GAP-030 | E9: DEFINED | F9: PASS
A10: 6 | B10: Runtime | C10: Добавлены NOT_MODELED и DerivedStateProjection.regionPenaltyById | D10: COMB-031; GAP-030 | E10: 69 fields | F10: PASS
A11: 7 | B11: GM-операции | C11: SET_GM_FORMAL_STATE отклоняет BLOCKED и NOT_MODELED | D11: Automation boundary | E11: DEFINED | F11: PASS
A12: 8 | B12: QA | C12: Добавлены 8 обязательных сценариев окончательных решений | D12: Release gate | E12: 98/98 PASS | F12: PASS
A13: 9 | B13: Payload | C13: Пересобраны canonical JSON и SHA-256; счётчики исправлены до фактических UTF-8 bytes | D13: Runtime delivery | E13: 185/185 PASS | F13: PASS
A14: 10 | B14: Контроль | C14: Все формульные проверки переведены на окончательные границы | D14: Release gate | E14: 24/24 PASS | F14: PASS
A15: 11 | B15: Совместимость | C15: Девять согласованных входов и Manifest v1.1 не изменялись | D15: User instruction | E15: Supplement only | F15: PASS
A16: 12 | B16: Версия | C16: Выпущен самостоятельный Effects & Diseases Registry v1.2 | D16: Author answers 2026-07-31 | E16: READY | F16: PASS
A17: 13 | B17: Дата | C17: Дата выпуска зафиксирована | D17: 2026-07-31 | E17: 2026-07-31 | F17: PASS
