Workbook

Sheet Сводка
A1: СИМБИОЗ V7 — итоговый исполняемый реестр правил
A2: Версия 1.7 — неизменяемое мастерское XP, восстановленный генератор групп и исправленный формульный контроль
A4: Показатель | B4: Значение | C4: Назначение | E4: Модель применения правил
A5: Всего runtime-правил | B5: 739 | C5: Уникальные карточки игрового реестра | E5: 1. META-001: базовые поля остаются нормативными в непротиворечащей части.
A6: Активно | B6: 699 | C6: Включить в игровое ядро | E6: v1.7=110 > v1.6=100 > v1.5=90 > v1.4=80 > v1.3=70 > v1.2=60 > v1.1=50 > QA 2.0=40 > QA 1.0=30 > база=10
A7: Не автоматизируется | B7: 40 | C7: Tombstone: хранить для трассировки, не реализовывать | E7: 3. Локальное исключение сильнее общего порядка.
A8: Базовые правила | B8: 539 | C8: CORE / SYM / MON | E8: 4. Полное исключение возможно только при явном статусе «Не автоматизируется».
A9: QA-решения | B9: 139 | C9: CQA / AQA / AQ2 / AQ3 | E9: 5. В листе «Реестр правил» уже записана итоговая композиция; повторно накладывать ответы не нужно.
A10: Новые согласованные карточки | B10: 61 | C10: CORE-230..234 и синхронизированные карточки; generator patch v1.7 | E10: 6. Устаревший набор QA-тестов не использовался как источник правил.
A11: Новые предразработочные решения | B11: 18 | C11: Закрытый пакет Pre-development QA v1.4
A12: Нормализованные QA-карточки | B12: 139 | C12: Конкретные runtime-поля | E12: Как использовать книгу при разработке Windows-приложения
A13: Ответы пользователя | B13: 444 | C13: Q-GM-XP-001 и Q-SOUND-NIGHT-001 закрыты; Q&A v1.2 восстановлен до полного состава | E13: «Реестр правил» — нормативная строка на каждый Rule ID.
A14: Открытые вопросы | B14: 0 | C14: Должно оставаться 0 | E14: «Параметры» — нормализованные вычисления, ресурсы, сроки и ручные решения.
A15: Проверка | B15: Формула | C15: Ожидаемо | E15: «Связи» — зависимости и приоритетные уточнения для графа правил.
A16: Строк правил | B16: =COUNTA('Реестр правил'!B2:B740) -> 739 | C16: 739 | E16: «Источники» и «Решения QA» — трассировка к утверждённым ответам.
A17: Активных правил | B17: =COUNTIF('Реестр правил'!C2:C740,"Активно") -> 699 | C17: 699 | E17: Листы изменений сохраняют историю; v1.7 фиксирует GM_DIRECT, генератор 80–150% и честные проверки выпуска.
A18: Исключённых правил | B18: =COUNTIF('Реестр правил'!C2:C740,"Не автоматизируется") -> 40 | C18: 40 | E18: «Контроль» — формулы целостности перед импортом в кодовую базу.
A19: Дубликатов ID | B19: =COUNTIF('Реестр правил'!AI2:AI740,">1") -> 0 | C19: 0
A20: Открытых вопросов | B20: =COUNTIF('Решения QA'!F2:F445,"Открыт") -> 0 | C20: 0
A22: Контексты runtime-правил
A23: Контекст | B23: Правил
A24: Боевая ситуация | B24: =COUNTIF('Реестр правил'!$F$2:$F$740,A24) -> 264
A25: Болезни и состояния | B25: =COUNTIF('Реестр правил'!$F$2:$F$740,A25) -> 33
A26: Инвентарь и предметы | B26: =COUNTIF('Реестр правил'!$F$2:$F$740,A26) -> 4
A27: Кампания | B27: =COUNTIF('Реестр правил'!$F$2:$F$740,A27) -> 9
A28: Мастер и НПС | B28: =COUNTIF('Реестр правил'!$F$2:$F$740,A28) -> 18
A29: Отдых и дозор | B29: =COUNTIF('Реестр правил'!$F$2:$F$740,A29) -> 28
A30: Перемещение и карта | B30: =COUNTIF('Реестр правил'!$F$2:$F$740,A30) -> 13
A31: Симбионты | B31: =COUNTIF('Реестр правил'!$F$2:$F$740,A31) -> 89
A32: Смерть и мародерство | B32: =COUNTIF('Реестр правил'!$F$2:$F$740,A32) -> 4
A33: Создание персонажа | B33: =COUNTIF('Реестр правил'!$F$2:$F$740,A33) -> 277

Sheet Реестр правил
A1: № | B1: Rule ID | C1: Статус | D1: Режим реализации | E1: Тип правила | F1: Функциональный контекст | G1: Компонент приложения | H1: Нормативный раздел | I1: Подраздел | J1: Название | K1: Категория | L1: Логический актор | M1: Субъект | N1: Объект / цель | O1: Runtime-триггер | P1: Предусловия | Q1: Входы / параметры | R1: Итоговый алгоритм | S1: Изменения состояния / результат | T1: Исключения / приоритет | U1: Стоимость действия / времени | V1: Стоимость ресурсов | W1: Броски / формулы | X1: Недопустимый исход | Y1: Длительность / кулдаун | Z1: Ручной выбор мастера | AA1: Атомарность / аудит | AB1: Приоритет источника | AC1: Источник карточки | AD1: ID вопросов | AE1: Связанные правила | AF1: База + поздние дельты | AG1: QA-поля нормализованы | AH1: Финальная правка | AI1: Контроль уникальности ID
A2: 1 | B2: CORE-001 | C2: Активно | D2: Реализовать в игровом ядре | E2: Базовое правило | F2: Создание персонажа | G2: Персонажи | H2: 2. Персонаж, предметы и базовая механика | I2: Раса и класс | J2: Поправки Единого при создании | K2: раса / создание персонажа. | L2: Игрок / персонаж | M2: создаваемый персонаж расы Единый | N2: S, M, Z, C. | O2: выбор расы и способа выбора симбионтов. | P2: раса = Единый. | Q2: selectionMode ∈ {random, manual}, раса собеседника для C. | R2: random: S−=3, M−=6, Z−=6; manual: S−=7, M−=10, Z−=10; при проверке общения C_eff=C+5 против Единого, C_eff=C−15 против Чистого. | S2: постоянные расовые поправки; контекстный модификатор C. | T2: итоговые постоянные характеристики не ниже 1 по CORE-164; социальное разрешение проверки вне охвата. | W2: раса = Единый. random: S−=3, M−=6, Z−=6; manual: S−=7, M−=10, Z−=10; при проверке общения C_eff=C+5 против Единого, C_eff=C−15 против Чистого. | AB2: 10 | AC2: §3.2.6.1, стр. 48. | AE2: CORE-164 | AF2: Нет | AI2: =COUNTIF($B$2:$B$740,B2) -> 1
A3: 2 | B3: CORE-004 | C3: Активно | D3: Реализовать в игровом ядре | E3: Базовое правило | F3: Создание персонажа | G3: Персонажи | H3: 2. Персонаж, предметы и базовая механика | I3: Раса и класс | J3: Навык Единого «Идущий вслед за болью» | K3: раса / пассивный навык. | L3: Система / игровая сущность | M3: Единый | N3: проверки сопротивления пыткам и самообладания при горении. | O3: создание Единого; соответствующая проверка. | P3: раса = Единый, пассивный источник активен. | Q3: базовый результат проверки. | R3: навык добавляется автоматически, не занимает слот; к указанным проверкам +15. | S3: постоянный навык и модификатор. | T3: социальная механика пыток вне охвата; бонус к самообладанию при пожаре применяется по CORE-114. | W3: раса = Единый, пассивный источник активен. | AB3: 10 | AC3: §3.2.6.1.1, стр. 48. | AE3: CORE-114 | AF3: Нет | AI3: =COUNTIF($B$2:$B$740,B3) -> 1
A4: 3 | B4: CORE-005 | C4: Активно | D4: Реализовать в игровом ядре | E4: Базовое правило | F4: Создание персонажа | G4: Персонажи | H4: 2. Персонаж, предметы и базовая механика | I4: Раса и класс | J4: Слоты симбионтов Единого | K4: раса / симбионты. | L4: Система / игровая сущность | M4: Единый | N4: контейнер симбионтов. | O4: создание или изменение состава симбионтов. | P4: раса = Единый. | Q4: виды добавляемых симбионтов. | R4: вместимость = 4 слота; обычный симбионт занимает установленное его каталогом число слотов; «Симбиотическое чудовище» занимает все 4 и доступно только Единому. | S4: валидированный состав симбионтов. | T4: случайное получение чудовища — CORE-170. | W4: раса = Единый. вместимость = 4 слота; обычный симбионт занимает установленное его каталогом число слотов; «Симбиотическое чудовище» занимает все 4 и доступно только Единому. | AB4: 10 | AC4: §3.2.6.2, стр. 48. | AE4: CORE-170 | AF4: Нет | AI4: =COUNTIF($B$2:$B$740,B4) -> 1
A5: 4 | B5: CORE-006 | C5: Активно | D5: Реализовать в игровом ядре | E5: Базовое правило | F5: Создание персонажа | G5: Персонажи | H5: 2. Персонаж, предметы и базовая механика | I5: Раса и класс | J5: Поправки Вольного при создании | K5: раса / создание персонажа. | L5: Игрок / персонаж | M5: создаваемый Вольный | N5: S, M, Z. | O5: выбор способа выбора симбионта. | P5: раса = Вольный. | Q5: selectionMode. | R5: random: без расовой поправки; manual: S−=2, M−=2, Z−=2. | S5: постоянные расовые поправки. | T5: минимумы создания CORE-164. | W5: раса = Вольный. random: без расовой поправки; manual: S−=2, M−=2, Z−=2. | AB5: 10 | AC5: §3.3.6.1, стр. 55. | AE5: CORE-164 | AF5: Нет | AI5: =COUNTIF($B$2:$B$740,B5) -> 1
A6: 5 | B6: CORE-007 | C6: Активно | D6: Реализовать в игровом ядре | E6: Базовое правило | F6: Создание персонажа | G6: Персонажи | H6: 2. Персонаж, предметы и базовая механика | I6: Раса и класс | J6: Симбионт и опыт Вольного | K6: раса / симбионты. | L6: Система / игровая сущность | M6: Вольный | N6: симбионт и начисление его XP. | O6: создание; любое начисление XP симбионту. | P6: раса = Вольный. | Q6: awardSource=DIRECT_SYMBIONT|ALLOCATED_UNASSIGNED|PASSIVE_RULE|GM_DIRECT; baseXP; multiplierAlreadyApplied=false. | R6: Если XP фактически начисляется симбионту Вольного, применить multiplier=2 ровно один раз. Это включает прямое неизменяемое начисление мастером GM_DIRECT. Баллы symbiontXpProgressPoints и конвертация 3→1 не удваиваются и в GM_DIRECT не участвуют. | S6: directAward=baseXP×2; allocatedAward=allocatedUnits×2; gmDirectAward=baseXP×2; counterPoints и unallocatedSymbiontXp создаются только обычным игровым маршрутом в базовом размере. | T6: Не удваивать eventPoints до маршрутизации и не применять ×2 повторно после записи XP. | W6: effectiveSymbiontXP=baseXP×2; progressPointsMultiplier=1; conversionRate=3:1. | AA6: Записывать baseXP, awardSource, применённый multiplier и итог XP; один award — один множитель. GM_DIRECT дополнительно хранит мастера, обязательную причину и неизменяемый awardId. | AB6: 100 | AC6: §3.3.6.2, стр. 55. Прямое авторское решение Q-SYMBIONT-XP-001 — опыт симбионтов за natural 20/1, 2026-07-30 Q-GM-XP-001 — мастерское начисление XP, 2026-08-01 | AD6: Q-SYMBIONT-XP-001 Q-GM-XP-001 | AE6: CORE-171 CORE-230 CORE-231 CORE-232 SYM-021 SYM-055 | AF6: Нет | AG6: Да | AH6: Патч v1.7 (GM_DIRECT) | AI6: =COUNTIF($B$2:$B$740,B6) -> 1
A7: 6 | B7: CORE-009 | C7: Активно | D7: Реализовать в игровом ядре | E7: Базовое правило | F7: Создание персонажа | G7: Персонажи | H7: 2. Персонаж, предметы и базовая механика | I7: Раса и класс | J7: Чистый Искатель | K7: класс / характеристики и пассив. | L7: Игрок / система | M7: Чистый Искатель | N7: характеристики и проверки. | O7: выбор класса; соответствующая проверка. | P7: раса Чистый, класс Искатель. | Q7: базовые характеристики/проверка. | R7: Нормативная база (действует во всей непротиворечащей части): S+2, D+2, I+7, Z+5; контекстно C+5 с Чистыми, C−15 с Едиными; автоматически навык «Искатель Последнего Рассвета» (1 слот); +5 к изучению, поиску закономерности, крафту, ремонту, изобретательству, первой помощи, медицинским манипуляциям, выживанию в дикой природе и упреждающему удару. Приоритетные авторские дельты (заменяют только прямо пересекающиеся ветви): [Обязательная правка] Эта формулировка имеет приоритет над исходным текстом карточки. Бонус к «Крафту» хранится в листе персонажа, но приложение не предоставляет runtime-действие создания предмета по Q-CORE-059. | S7: постоянные поправки и навык. | T7: разрешение небоевых/социальных действий вне охвата; боевые модификаторы применяются. Поздние дельты применяются по приоритету AQ3 > AQ2 > AQA/CQA > базовая карточка; локальное исключение сильнее общего. | U7: Нормативная база (действует во всей непротиворечащей части): Бонус к «Крафту» хранится в листе персонажа, но приложение не предоставляет runtime-действие создания предмета по Q-CORE-059. разрешение небоевых/социальных действий вне охвата; боевые модификаторы применяются. | W7: [Обязательная правка] Эта формулировка имеет приоритет над исходным текстом карточки. | Y7: Нормативная база (действует во всей непротиворечащей части): | AB7: 10 | AC7: §3.4.7.1, стр. 65. | AE7: CORE-059 | AF7: Нет | AI7: =COUNTIF($B$2:$B$740,B7) -> 1
A8: 7 | B8: CORE-010 | C8: Активно | D8: Реализовать в игровом ядре | E8: Базовое правило | F8: Создание персонажа | G8: Персонажи | H8: 2. Персонаж, предметы и базовая механика | I8: Раса и класс | J8: Чистый Сталкер: характеристики и пассив | K8: класс / характеристики и пассив. | L8: Система / игровая сущность | M8: Чистый Сталкер. | O8: выбор класса; соответствующая проверка/экипировка. | P8: раса Чистый, класс Сталкер. | Q8: проверка, тип оружия/доспеха. | R8: S+2, D+5, M+5, Z+5; C+5 с Чистыми, C−10 с Едиными; навык «Сталкер Последнего Рассвета» занимает 1 слот и даёт +4 к прокладыванию маршрута, выслеживанию, обнаружению, скрытности, выживанию, осмотру, молниеносной реакции, уклонению, освобождению из пут; бесштрафное владение Кенси/Эривел/Эстрефорд/Айнцберн и Цесмором. | S8: постоянные поправки, бонусы и исключение штрафов владения. | T8: небоевые проверки хранятся как параметры, их разрешение вне охвата. | U8: C+5 с Чистыми, C−10 с Едиными; навык «Сталкер Последнего Рассвета» занимает 1 слот и даёт +4 к прокладыванию маршрута, выслеживанию, обнаружению, скрытности, выживанию, осмотру, молниеносной реакции, уклонению, освобождению из пут; бесштрафное владение Кенси/Эривел/Эстрефорд/Айнцберн и Цесмором. | AB8: 10 | AC8: §3.4.7.2.1–3.4.7.2.2, стр. 65. | AF8: Нет | AI8: =COUNTIF($B$2:$B$740,B8) -> 1
A9: 8 | B9: CORE-013 | C9: Активно | D9: Реализовать в игровом ядре | E9: Базовое правило | F9: Создание персонажа | G9: Персонажи | H9: 2. Персонаж, предметы и базовая механика | I9: Раса и класс | J9: Чистый Солдат | K9: класс / характеристики и пассив. | L9: Система / игровая сущность | M9: Чистый Солдат. | O9: выбор класса; соответствующее боевое действие. | P9: раса Чистый, класс Солдат. | Q9: проверка, оружие/броня, смена цели. | R9: S+5, D+2, M+5, Z+5; C+5 с Чистыми, C−20 с Едиными; навык «Солдат Последнего Рассвета» занимает 1 слот и даёт +3 к точности ударов руками/ногами, борьбе, точности одноручного/полуторного меча, блокированию и точности ударов щитом; бесштрафны Кастелькросс/Цесмор/Гленхейм, Корнадора/Бларадэ, Кенси/Эривел/Эстрефорд/Айнцберн; смена цели ближней атаки не расходует действие. | S9: постоянные поправки и боевые исключения. | T9: необходимое перемещение к новой цели оплачивается обычными действиями. | U9: выбор класса; соответствующее боевое действие. C+5 с Чистыми, C−20 с Едиными; навык «Солдат Последнего Рассвета» занимает 1 слот и даёт +3 к точности ударов руками/ногами, борьбе, точности одноручного/полуторного меча, блокированию и точности ударов щитом; бесштрафны Кастелькросс/Цесмор/Гленхейм, Корнадора/Бларадэ, Кенси/Эривел/Эстрефорд/Айнцберн; смена цели ближней атаки не расходует действие. необходимое перемещение к новой цели оплачивается обычными действиями. | AB9: 10 | AC9: §3.4.7.3, стр. 65–66. | AF9: Нет | AI9: =COUNTIF($B$2:$B$740,B9) -> 1
A10: 9 | B10: CORE-015 | C10: Не автоматизируется | D10: Не реализовывать в Windows-приложении | E10: Базовое правило | F10: Создание персонажа | G10: Персонажи | H10: 2. Персонаж, предметы и базовая механика | I10: Общие правила предметов и крафта | J10: Время, ресурсы и успех крафта | K10: предмет / крафт. | L10: Система / игровая сущность | M10: изготовитель | N10: материалы и время. | O10: подтверждение начала работы. | P10: требуемые материалы и инструменты доступны. | Q10: W изготовителя, отдельный срок из описания (если есть). | R10: Нормативная база (действует во всей непротиворечащей части): по умолчанию craftHours=max(1,50−W); материалы списать атомарно в начале; отдельной проверки успешности нет; по окончании создать предмет с параметрами CORE-014. Приоритетные авторские дельты (заменяют только прямо пересекающиеся ветви): [Исключение из реализации] Карточка сохранена как tombstone и не исполняется приложением. крафт как игровое действие исключён Q-CORE-059 | S10: материалы потрачены, таймер, затем предмет. | T10: иной явно заданный срок имеет приоритет. Поздние дельты применяются по приоритету AQ3 > AQ2 > AQA/CQA > базовая карточка; локальное исключение сильнее общего. Прямое уточнение 2026-07-28 не восстанавливает изготовление, время, материалы или проверку Крафта. | U10: Нормативная база (действует во всей непротиворечащей части): крафт как игровое действие исключён Q-CORE-059 | V10: требуемые материалы и инструменты доступны. по умолчанию craftHours=max(1,50−W); материалы списать атомарно в начале; отдельной проверки успешности нет; по окончании создать предмет с параметрами CORE-014. материалы потрачены, таймер, затем предмет. | W10: по умолчанию craftHours=max(1,50−W); материалы списать атомарно в начале; отдельной проверки успешности нет; по окончании создать предмет с параметрами CORE-014. | Y10: W изготовителя, отдельный срок из описания (если есть). Нормативная база (действует во всей непротиворечащей части): иной явно заданный срок имеет приоритет. | AA10: по умолчанию craftHours=max(1,50−W); материалы списать атомарно в начале; отдельной проверки успешности нет; по окончании создать предмет с параметрами CORE-014. | AB10: 60 | AC10: §4.1, стр. 67. Прямое уточнение пользователя 2026-07-28 | AD10: Q-CORE-059 | AE10: CORE-014 CORE-183 CORE-185 | AF10: Да | AH10: Патч v1.2 | AI10: =COUNTIF($B$2:$B$740,B10) -> 1
A11: 10 | B11: CORE-017 | C11: Активно | D11: Реализовать в игровом ядре | E11: Базовое правило | F11: Создание персонажа | G11: Персонажи | H11: 2. Персонаж, предметы и базовая механика | I11: Общие правила предметов и крафта | J11: Специальные серии ударов оружием | K11: оружие / стоимость действия. | L11: Система / игровая сущность | M11: атакующий | N11: оружие с двумя или тремя ударами. | O11: заявление специальной атаки. | P11: выполнен требуемый уровень навыка. | Q11: число ударов свойства, доступные действия, цели. | R11: формулировка «два/три удара за один ход» = одна особая атака за 1 боевое действие, не чаще 1 раза за личный ход; каждый удар полностью разрешается отдельно. Формулировка «за одно боевое действие» без «раз за ход» доступна за каждое имеющееся действие. | S11: списано действие, отдельно списаны боеприпасы/разрешены попадания. | T11: Кенси и парные кинжалы/кастеты используют лимит раз за ход. | U11: число ударов свойства, доступные действия, цели. формулировка «два/три удара за один ход» = одна особая атака за 1 боевое действие, не чаще 1 раза за личный ход; каждый удар полностью разрешается отдельно. Формулировка «за одно боевое действие» без «раз за ход» доступна за каждое имеющееся действие. списано действие, отдельно списаны боеприпасы/разрешены попадания. | W11: формулировка «два/три удара за один ход» = одна особая атака за 1 боевое действие, не чаще 1 раза за личный ход; каждый удар полностью разрешается отдельно. Формулировка «за одно боевое действие» без «раз за ход» доступна за каждое имеющееся действие. | Y11: формулировка «два/три удара за один ход» = одна особая атака за 1 боевое действие, не чаще 1 раза за личный ход; каждый удар полностью разрешается отдельно. Формулировка «за одно боевое действие» без «раз за ход» доступна за каждое имеющееся действие. Кенси и парные кинжалы/кастеты используют лимит раз за ход. | AB11: 10 | AC11: таблицы §4.2 и §4.4, стр. 69, 74, 76. | AF11: Нет | AI11: =COUNTIF($B$2:$B$740,B11) -> 1
A12: 11 | B12: CORE-018 | C12: Активно | D12: Реализовать в игровом ядре | E12: Базовое правило | F12: Создание персонажа | G12: Персонажи | H12: 2. Персонаж, предметы и базовая механика | I12: Общие правила предметов и крафта | J12: Общая работа щита | K12: щит / защита и прочность. | L12: Система / игровая сущность | M12: владелец щита | N12: щит. | O12: успешный блок щитом. | P12: щит в руках, HP щита >0. | Q12: обычный урон остановленной атаки, текущий HP щита. | R12: атака не достигает носителя; определить обычный урон атаки без отдельного спасброска брони щита; shieldHP=max(0,shieldHP−damage); избыточный урон при разрушении не переносить на носителя; при 0 HP щит уничтожен и не даёт бонусов до ремонта. | S12: изменена прочность/состояние щита. | T12: пассивная броня носителя не проверяется, поскольку атака его не достигает. | V12: щит в руках, HP щита >0. обычный урон остановленной атаки, текущий HP щита. атака не достигает носителя; определить обычный урон атаки без отдельного спасброска брони щита; shieldHP=max(0,shieldHP−damage); избыточный урон при разрушении не переносить на носителя; при 0 HP щит уничтожен и не даёт бонусов до ремонта. | W12: атака не достигает носителя; определить обычный урон атаки без отдельного спасброска брони щита; shieldHP=max(0,shieldHP−damage); избыточный урон при разрушении не переносить на носителя; при 0 HP щит уничтожен и не даёт бонусов до ремонта. | AB12: 10 | AC12: §4.4, стр. 77–80. | AF12: Нет | AI12: =COUNTIF($B$2:$B$740,B12) -> 1
A13: 12 | B13: CORE-019 | C13: Активно | D13: Реализовать в игровом ядре | E13: Базовое правило | F13: Создание персонажа | G13: Персонажи | H13: 2. Персонаж, предметы и базовая механика | I13: Общие правила предметов и крафта | J13: Владение щитом | K13: щит / модификаторы. | L13: Система / игровая сущность | M13: пользователь щита | N13: атака и блок. | O13: удар щитом или блок. | P13: щит в руках. | Q13: наличие/бонус навыка «Владение щитом», бонус щита. | R13: при навыке прибавить его бонус к атаке/блоку; без навыка применить −5 к атаке и один общий −5 к проверке блока; постоянный +3 самого щита сохраняется, отдельный −3 не добавлять. | S13: итоговая проверка. | T13: «Солдат Последнего Рассвета» добавляется там, где прямо указан. | AB13: 10 | AC13: §4.4, стр. 77–80; §6.2, стр. 106. | AF13: Нет | AI13: =COUNTIF($B$2:$B$740,B13) -> 1
A14: 13 | B14: CORE-021 | C14: Активно | D14: Реализовать в игровом ядре | E14: Базовое правило | F14: Создание персонажа | G14: Персонажи | H14: 2. Персонаж, предметы и базовая механика | I14: Каталог оружия | J14: Лёгкий арбалет | K14: оружие / арбалет. | L14: Система / игровая сущность | M14: изготовитель и стрелок | N14: экземпляр лёгкого арбалета. | O14: создание; выстрел; перезарядка. | P14: для бесштрафной точности — «Стрельба» либо классовый навык Сталкера/Солдата. | Q14: независимые дайсы, L,Lw; параметры пользователя. | R14: при создании: Dm=R12+L; затем Rn=R12+Dm+L; затем Rs=ceil(Dm×Rn/(R20+3×Lw)), минимум 1; затем Rd=ceil(2×Rn/Lw), минимум 1. На каждом выстреле Pr=R12, урон = созданный Dm, предел дальности = Rn; перезарядка = 1 боевое действие. Без указанного владения −5 к точности. | S14: созданные параметры; при выстреле разряжен, после действия снова заряжен. | T14: общие требования/стрельба/броня CORE-016, CORE-126, CORE-150. Формула создания используется только для точной проверки достижимости готового профиля игрока по CORE-185; крафт не автоматизируется. Боевые выражения активного профиля разрешаются по CORE-189. | U14: На каждом выстреле Pr=R12, урон = созданный Dm, предел дальности = Rn; перезарядка = 1 боевое действие. созданные параметры; при выстреле разряжен, после действия снова заряжен. | W14: при создании: Dm=R12+L; затем Rn=R12+Dm+L; затем Rs=ceil(Dm×Rn/(R20+3×Lw)), минимум 1; затем Rd=ceil(2×Rn/Lw), минимум 1. На каждом выстреле Pr=R12, урон = созданный Dm, предел дальности = Rn; перезарядка = 1 боевое действие. FORMULA_MODE=VALIDATION_ONLY; generationEnabled=false. Производственные дайсы не бросаются. | AB14: 60 | AC14: §4.2, таблица 1, стр. 68. Прямое уточнение пользователя 2026-07-28 | AE14: CORE-016 CORE-126 CORE-150 CORE-183 CORE-184 CORE-185 CORE-189 | AF14: Да | AH14: Патч v1.2 | AI14: =COUNTIF($B$2:$B$740,B14) -> 1
A15: 14 | B15: CORE-022 | C15: Активно | D15: Реализовать в игровом ядре | E15: Базовое правило | F15: Создание персонажа | G15: Персонажи | H15: 2. Персонаж, предметы и базовая механика | I15: Каталог оружия | J15: Тяжёлый арбалет | K15: оружие / арбалет. | L15: Система / игровая сущность | M15: изготовитель и стрелок | N15: тяжёлый арбалет. | O15: создание; выстрел; перезарядка. | P15: «Стрельба» или классовый навык Сталкера/Солдата для отсутствия штрафа. | Q15: независимые дайсы, L,Lw. | R15: Dm=R20+L; Rn=R12+Dm+L; Rs=ceil(Dm×Rn/(R20+2×Lw)), минимум 1; Rd=ceil(2×Rn/Lw), минимум 1; на выстреле Pr=R20, урон = Dm; перезарядка 1 действие; без владения −5 к точности. | S15: фиксированные Dm/Rn/Rs/Rd, динамическое пробитие и заряженность. | T15: общие правила стрельбы. Формула создания используется только для точной проверки достижимости готового профиля игрока по CORE-185; крафт не автоматизируется. Боевые выражения активного профиля разрешаются по CORE-189. | U15: Rd=ceil(2×Rn/Lw), минимум 1; на выстреле Pr=R20, урон = Dm; перезарядка 1 действие; без владения −5 к точности. | W15: Dm=R20+L Rn=R12+Dm+L Rs=ceil(Dm×Rn/(R20+2×Lw)), минимум 1 Rd=ceil(2×Rn/Lw), минимум 1; на выстреле Pr=R20, урон = Dm; перезарядка 1 действие; без владения −5 к точности. FORMULA_MODE=VALIDATION_ONLY; generationEnabled=false. Производственные дайсы не бросаются. | AB15: 60 | AC15: §4.2, таблица 1, стр. 69. Прямое уточнение пользователя 2026-07-28 | AE15: CORE-183 CORE-184 CORE-185 CORE-189 | AF15: Да | AH15: Патч v1.2 | AI15: =COUNTIF($B$2:$B$740,B15) -> 1
A16: 15 | B16: CORE-023 | C16: Активно | D16: Реализовать в игровом ядре | E16: Базовое правило | F16: Создание персонажа | G16: Персонажи | H16: 2. Персонаж, предметы и базовая механика | I16: Каталог оружия | J16: Кенси | K16: оружие / заводской арбалет. | L16: Система / игровая сущность | M16: стрелок | N16: Кенси. | O16: экипировка; выстрел; замена магазина. | P16: S≥8,D≥19; для отсутствия специального штрафа — навык Сталкера/Солдата. | Q16: магазин, цель, навык «Стрельба». | R16: имеет канонический шаблон, фиксированный для заявки игрока; мастер может изменить конкретный экземпляр по CORE-187/CORE-188. Вне такого override оружие создаётся только на конвейерной линии оружейного завода Кенси: магазин 8 болтов, дальность 20 м, урон 10, Pr=R12 на выстрел; замена магазина = 1 действие; без классового навыка −15 к точности. При «Стрельбе» высокого уровня можно один раз за личный ход за 1 действие выстрелить из двух Кенси (каждый выстрел отдельно); с совершенного уровня каждому назначается собственная цель. | S16: расход по 1 болту с каждого использованного арбалета; попадания разрешены независимо. | T16: особая серия CORE-017. PLAYER_REQUEST=TEMPLATE_FIXED: игрок не меняет характеристики оружия Чистых. MASTER_OVERRIDE конкретного экземпляра разрешён по CORE-187/CORE-188 и не изменяет глобальный шаблон. | U16: всегда имеет фиксированные параметры и создаётся только на конвейерной линии оружейного завода Кенси: магазин 8 болтов, дальность 20 м, урон 10, Pr=R12 на выстрел; замена магазина = 1 действие; без классового навыка −15 к точности. При «Стрельбе» высокого уровня можно один раз за личный ход за 1 действие выстрелить из двух Кенси (каждый выстрел отдельно); с совершенного уровня каждому назначается собственная цель. | W16: всегда имеет фиксированные параметры и создаётся только на конвейерной линии оружейного завода Кенси: магазин 8 болтов, дальность 20 м, урон 10, Pr=R12 на выстрел; замена магазина = 1 действие; без классового навыка −15 к точности. | Y16: При «Стрельбе» высокого уровня можно один раз за личный ход за 1 действие выстрелить из двух Кенси (каждый выстрел отдельно); с совершенного уровня каждому назначается собственная цель. | AA16: При «Стрельбе» высокого уровня можно один раз за личный ход за 1 действие выстрелить из двух Кенси (каждый выстрел отдельно); с совершенного уровня каждому назначается собственная цель. | AB16: 60 | AC16: §4.2, таблица 1, стр. 69. Прямое уточнение пользователя 2026-07-28 | AE16: CORE-017 CORE-186 CORE-187 CORE-188 CORE-189 CORE-190 | AF16: Да | AH16: Патч v1.2 | AI16: =COUNTIF($B$2:$B$740,B16) -> 1
A17: 16 | B17: CORE-024 | C17: Активно | D17: Реализовать в игровом ядре | E17: Базовое правило | F17: Создание персонажа | G17: Персонажи | H17: 2. Персонаж, предметы и базовая механика | I17: Каталог оружия | J17: Эривел | K17: оружие / заводской арбалет. | L17: Система / игровая сущность | M17: стрелок | N17: Эривел. | O17: выстрел или замена магазина. | P17: S≥16,D≥12; классовый навык Сталкера/Солдата для отсутствия −15. | Q17: магазин, отдельные R20 пробития и урона. | R17: имеет канонический шаблон, фиксированный для заявки игрока; мастер может изменить конкретный экземпляр по CORE-187/CORE-188. Вне такого override оружие создаётся только на конвейерной линии оружейного завода Эривела: магазин 4 болта; замена = 1 действие; дальность 30 м; на каждом выстреле Pr=R20, damage=2×R20; без классового навыка −15 к точности. | S17: расход 1 болта; динамические Pr/damage. | T17: каждый символ дайса независим. PLAYER_REQUEST=TEMPLATE_FIXED: игрок не меняет характеристики оружия Чистых. MASTER_OVERRIDE конкретного экземпляра разрешён по CORE-187/CORE-188 и не изменяет глобальный шаблон. | U17: всегда имеет фиксированные параметры и создаётся только на конвейерной линии оружейного завода Эривела: магазин 4 болта; замена = 1 действие; дальность 30 м; на каждом выстреле Pr=R20, damage=2×R20; без классового навыка −15 к точности. | W17: магазин, отдельные R20 пробития и урона. всегда имеет фиксированные параметры и создаётся только на конвейерной линии оружейного завода Эривела: магазин 4 болта; замена = 1 действие; дальность 30 м; на каждом выстреле Pr=R20, damage=2×R20; без классового навыка −15 к точности. | AB17: 60 | AC17: §4.2, таблица 1, стр. 69. Прямое уточнение пользователя 2026-07-28 | AE17: CORE-186 CORE-187 CORE-188 CORE-189 CORE-190 | AF17: Да | AH17: Патч v1.2 | AI17: =COUNTIF($B$2:$B$740,B17) -> 1
A18: 17 | B18: CORE-025 | C18: Активно | D18: Реализовать в игровом ядре | E18: Базовое правило | F18: Создание персонажа | G18: Персонажи | H18: 2. Персонаж, предметы и базовая механика | I18: Каталог оружия | J18: Эстрефорд | K18: оружие / заводской арбалет. | L18: Система / игровая сущность | M18: стрелок | N18: Эстрефорд. | O18: выстрел/перезарядка. | P18: S≥19,D≥14; классовый навык Сталкера/Солдата для отсутствия −15. | Q18: заряженность, цель. | R18: имеет канонический шаблон, фиксированный для заявки игрока; мастер может изменить конкретный экземпляр по CORE-187/CORE-188. Вне такого override оружие создаётся только на конвейерной линии оружейного завода Эстрефорда: дальность 30 м, Pr=16, damage=30, перезарядка 1 действие; без классового навыка −15 к точности. | S18: после выстрела разряжен. | T18: общие правила. PLAYER_REQUEST=TEMPLATE_FIXED: игрок не меняет характеристики оружия Чистых. MASTER_OVERRIDE конкретного экземпляра разрешён по CORE-187/CORE-188 и не изменяет глобальный шаблон. | U18: всегда имеет фиксированные параметры и создаётся только на конвейерной линии оружейного завода Эстрефорда: дальность 30 м, Pr=16, damage=30, перезарядка 1 действие; без классового навыка −15 к точности. | W18: всегда имеет фиксированные параметры и создаётся только на конвейерной линии оружейного завода Эстрефорда: дальность 30 м, Pr=16, damage=30, перезарядка 1 действие; без классового навыка −15 к точности. | AB18: 60 | AC18: §4.2, таблица 1, стр. 70. Прямое уточнение пользователя 2026-07-28 | AE18: CORE-186 CORE-187 CORE-188 CORE-189 CORE-190 | AF18: Да | AH18: Патч v1.2 | AI18: =COUNTIF($B$2:$B$740,B18) -> 1
A19: 18 | B19: CORE-032 | C19: Активно | D19: Реализовать в игровом ядре | E19: Базовое правило | F19: Создание персонажа | G19: Персонажи | H19: 2. Персонаж, предметы и базовая механика | I19: Каталог оружия | J19: Одноручный меч | K19: оружие / ближний бой. | L19: Система / игровая сущность | M19: изготовитель и атакующий | N19: одноручный меч. | O19: создание; атака. | P19: «Фехтование» либо −5. | Q19: L,Lw,Ls, S,D, дайсы атаки. | R19: Rs=max(9,ceil((80−(Lw+Ls)/2)/(R6+L))); Rd по той же формуле и минимуму; точность D, урон S, навык «Фехтование»; Pr=R12, базовый damage=R20. | S19: обычная оружейная атака. | T19: CORE-020. Формула создания используется только для точной проверки достижимости готового профиля игрока по CORE-185; крафт не автоматизируется. Боевые выражения активного профиля разрешаются по CORE-189. | W19: Rs=max(9,ceil((80−(Lw+Ls)/2)/(R6+L))) Rd по той же формуле и минимуму; точность D, урон S, навык «Фехтование» Pr=R12, базовый damage=R20. FORMULA_MODE=VALIDATION_ONLY; generationEnabled=false. Производственные дайсы не бросаются. | AB19: 60 | AC19: §4.4, таблица 3, стр. 73. Прямое уточнение пользователя 2026-07-28 | AE19: CORE-020 CORE-183 CORE-184 CORE-185 CORE-189 | AF19: Да | AH19: Патч v1.2 | AI19: =COUNTIF($B$2:$B$740,B19) -> 1
A20: 19 | B20: CORE-034 | C20: Активно | D20: Реализовать в игровом ядре | E20: Базовое правило | F20: Создание персонажа | G20: Персонажи | H20: 2. Персонаж, предметы и базовая механика | I20: Каталог оружия | J20: Двуручный меч | K20: оружие / ближний бой. | L20: Система / игровая сущность | M20: изготовитель и атакующий | N20: двуручный меч. | O20: создание; атака/метание. | P20: «Фехтование» либо −5. | Q20: L,Lw,Ls. | R20: Rs=max(12,ceil((100−(Lw+Ls)/2)/(R4+L))); Rd=max(9,ceil((80−(Lw+Ls)/2)/(R6+L))); Pr=R20+5, базовый damage=R20+5; S — урон, D — точность; при метании дополнительный −10 к проверкам метания. | S20: обычная атака. | T20: штрафы метания CORE-128/CORE-129 складываются. Формула создания используется только для точной проверки достижимости готового профиля игрока по CORE-185; крафт не автоматизируется. Боевые выражения активного профиля разрешаются по CORE-189. | W20: Rs=max(12,ceil((100−(Lw+Ls)/2)/(R4+L))) Rd=max(9,ceil((80−(Lw+Ls)/2)/(R6+L))) Pr=R20+5, базовый damage=R20+5 FORMULA_MODE=VALIDATION_ONLY; generationEnabled=false. Производственные дайсы не бросаются. | AB20: 60 | AC20: §4.4, таблица 3, стр. 74. Прямое уточнение пользователя 2026-07-28 | AE20: CORE-128 CORE-129 CORE-183 CORE-184 CORE-185 CORE-189 | AF20: Да | AH20: Патч v1.2 | AI20: =COUNTIF($B$2:$B$740,B20) -> 1
A21: 20 | B21: CORE-035 | C21: Активно | D21: Реализовать в игровом ядре | E21: Базовое правило | F21: Создание персонажа | G21: Персонажи | H21: 2. Персонаж, предметы и базовая механика | I21: Каталог оружия | J21: Шпага | K21: оружие / ближний бой. | L21: Система / игровая сущность | M21: изготовитель и атакующий | N21: шпага. | O21: создание; атака/парирование/метание. | P21: «Фехтование» либо −5. | Q21: L,Lw,Ls, D. | R21: Rs=max(5,ceil((50−(Lw+Ls)/2)/(R6+L))); Rd=max(12,ceil((100−(Lw+Ls)/2)/(R4+L))); +5 к парированию; Pr=R12, базовый damage=R12; D модифицирует точность и урон; метание получает −10. | S21: атака или защитный бонус. | T21: парирование CORE-147. Формула создания используется только для точной проверки достижимости готового профиля игрока по CORE-185; крафт не автоматизируется. Боевые выражения активного профиля разрешаются по CORE-189. | W21: Rs=max(5,ceil((50−(Lw+Ls)/2)/(R6+L))) Rd=max(12,ceil((100−(Lw+Ls)/2)/(R4+L))); +5 к парированию Pr=R12, базовый damage=R12 FORMULA_MODE=VALIDATION_ONLY; generationEnabled=false. Производственные дайсы не бросаются. | AB21: 60 | AC21: §4.4, таблица 3, стр. 74. Прямое уточнение пользователя 2026-07-28 | AE21: CORE-147 CORE-183 CORE-184 CORE-185 CORE-189 | AF21: Да | AH21: Патч v1.2 | AI21: =COUNTIF($B$2:$B$740,B21) -> 1
A22: 21 | B22: CORE-036 | C22: Активно | D22: Реализовать в игровом ядре | E22: Базовое правило | F22: Создание персонажа | G22: Персонажи | H22: 2. Персонаж, предметы и базовая механика | I22: Каталог оружия | J22: Копьё | K22: оружие / ближний бой. | L22: Система / игровая сущность | M22: изготовитель и атакующий | N22: копьё. | O22: создание; атака/упреждение. | P22: «Владение копьём» либо −2. | Q22: L,Lw,Ls, S,D. | R22: Rs=max(7,ceil((70−(Lw+Ls)/2)/(R6+L))); Rd=max(6,ceil((70−(Lw+Ls)/2)/(R6+L))); +3 к проверке упреждающего удара; Pr=R12, базовый damage=R12; D точность, S урон. | S22: атака/защитный бонус. | T22: упреждающий удар CORE-148. Формула создания используется только для точной проверки достижимости готового профиля игрока по CORE-185; крафт не автоматизируется. Боевые выражения активного профиля разрешаются по CORE-189. | W22: Rs=max(7,ceil((70−(Lw+Ls)/2)/(R6+L))) Rd=max(6,ceil((70−(Lw+Ls)/2)/(R6+L))); +3 к проверке упреждающего удара Pr=R12, базовый damage=R12 FORMULA_MODE=VALIDATION_ONLY; generationEnabled=false. Производственные дайсы не бросаются. | AB22: 60 | AC22: §4.4, таблица 3, стр. 74. Прямое уточнение пользователя 2026-07-28 | AE22: CORE-148 CORE-183 CORE-184 CORE-185 CORE-189 | AF22: Да | AH22: Патч v1.2 | AI22: =COUNTIF($B$2:$B$740,B22) -> 1
A23: 22 | B23: CORE-042 | C23: Активно | D23: Реализовать в игровом ядре | E23: Базовое правило | F23: Создание персонажа | G23: Персонажи | H23: 2. Персонаж, предметы и базовая механика | I23: Каталог оружия | J23: Кастет | K23: оружие / рукопашный бой. | L23: Система / игровая сущность | M23: изготовитель и атакующий | N23: кастет. | O23: создание; атака/метание. | P23: навык «Рукопашный бой» для специальной серии; без навыка применяется общий штраф рукопашного боя. | Q23: L,Lw,Ls, S,D, уровень навыка. | R23: Rs=max(9,ceil((60−(Lw+Ls)/2)/(R4+L))); Rd=max(12,ceil((80−(Lw+Ls)/2)/(R4+L))); Pr=R6, базовый damage=R6; S урон, D точность; высокий навык — два удара за одно действие не чаще раза за ход, абсолютный — добавить удар ногой без пробития; метание −10. | S23: до трёх независимо разрешаемых ударов. | T23: специальная серия CORE-017; обычные удары рукой/ногой CORE-136. Формула создания используется только для точной проверки достижимости готового профиля игрока по CORE-185; крафт не автоматизируется. Боевые выражения активного профиля разрешаются по CORE-189. | U23: S урон, D точность; высокий навык — два удара за одно действие не чаще раза за ход, абсолютный — добавить удар ногой без пробития; метание −10. | W23: Rs=max(9,ceil((60−(Lw+Ls)/2)/(R4+L))) Rd=max(12,ceil((80−(Lw+Ls)/2)/(R4+L))) Pr=R6, базовый damage=R6 FORMULA_MODE=VALIDATION_ONLY; generationEnabled=false. Производственные дайсы не бросаются. | Y23: S урон, D точность; высокий навык — два удара за одно действие не чаще раза за ход, абсолютный — добавить удар ногой без пробития; метание −10. | AB23: 60 | AC23: §4.4, таблица 3, стр. 76. Прямое уточнение пользователя 2026-07-28 | AE23: CORE-017 CORE-136 CORE-183 CORE-184 CORE-185 CORE-189 | AF23: Да | AH23: Патч v1.2 | AI23: =COUNTIF($B$2:$B$740,B23) -> 1
A24: 23 | B24: CORE-049 | C24: Активно | D24: Реализовать в игровом ядре | E24: Базовое правило | F24: Создание персонажа | G24: Персонажи | H24: 2. Персонаж, предметы и базовая механика | I24: Доспехи | J24: Кожаный доспех | K24: броня / элемент. | L24: Игрок / персонаж | M24: носитель | N24: элемент кожаного доспеха. | O24: экипировка; попадание в закрытую зону. | P24: на каждый элемент требуется S=2. | Q24: закрытая зона, R6 брони. | R24: Нормативная база (действует во всей непротиворечащей части): каждый слой/элемент даёт R6 к общей броне зоны; шлем не закрывает лицо и не даёт иммунитет к болевым приёмам на лице/выдавливанию глаз. Приоритетные авторские дельты (заменяют только прямо пересекающиеся ветви): [Обязательная правка] Эта формулировка имеет приоритет над исходным текстом карточки. удалить неисполняемую оговорку о выдавливании глаз; оставить защиту лица/болевых приёмов | S24: слой брони зоны. | T24: наслаивание CORE-151. Поздние дельты применяются по приоритету AQ3 > AQ2 > AQA/CQA > базовая карточка; локальное исключение сильнее общего. | U24: Нормативная база (действует во всей непротиворечащей части): | W24: на каждый элемент требуется S=2. закрытая зона, R6 брони. каждый слой/элемент даёт R6 к общей броне зоны; шлем не закрывает лицо и не даёт иммунитет к болевым приёмам на лице/выдавливанию глаз. [Обязательная правка] Эта формулировка имеет приоритет над исходным текстом карточки. | Y24: Нормативная база (действует во всей непротиворечащей части): | AB24: 10 | AC24: §4.5, таблица 4, стр. 81. | AE24: CORE-151 | AF24: Нет | AI24: =COUNTIF($B$2:$B$740,B24) -> 1
A25: 24 | B25: CORE-052 | C25: Активно | D25: Реализовать в игровом ядре | E25: Базовое правило | F25: Создание персонажа | G25: Персонажи | H25: 2. Персонаж, предметы и базовая механика | I25: Доспехи | J25: Латы | K25: броня / элементы. | L25: Игрок / персонаж | M25: носитель | N25: латы. | O25: экипировка, попадание, удушение, бег/акробатика. | P25: S=4 за элемент. | Q25: зоны и число элементов. | R25: каждый слой зоны armor+=R20; голова+корпус дают иммунитет к удушающему приёму; −2 к бегу/акробатике за элемент; если элементов >2, M−=5 один раз. | S25: броня, штрафы, иммунитет. | T25: наслаивание CORE-151. | W25: S=4 за элемент. каждый слой зоны armor+=R20; голова+корпус дают иммунитет к удушающему приёму; −2 к бегу/акробатике за элемент; если элементов >2, M−=5 один раз. | AA25: каждый слой зоны armor+=R20; голова+корпус дают иммунитет к удушающему приёму; −2 к бегу/акробатике за элемент; если элементов >2, M−=5 один раз. | AB25: 10 | AC25: §4.5, таблица 4, стр. 82. | AE25: CORE-151 | AF25: Нет | AI25: =COUNTIF($B$2:$B$740,B25) -> 1
A26: 25 | B26: CORE-054 | C26: Активно | D26: Реализовать в игровом ядре | E26: Базовое правило | F26: Создание персонажа | G26: Персонажи | H26: 2. Персонаж, предметы и базовая механика | I26: Доспехи | J26: Кастелькросс | K26: броня / цельный костюм. | L26: Игрок / персонаж | M26: носитель | N26: Кастелькросс. | O26: экипировка, попадание, псионика, перемещение. | P26: S≥20; цельный; без «Солдата Последнего Рассвета» −15 к перемещениям. | Q26: R20 брони, вид воздействия. | R26: armor=R20; псионический урон уменьшить на 5 и к встречным проверкам против псионического контроля/чтения/иллюзий +5; иммунитет к удушающему приёму; −6 к бегу/акробатике; M−=3; псионическая защита не защищает от химических феромонов. | S26: броня/сопротивление/штрафы. | T26: конкретная способность может устанавливать иммунитет или не действовать при любой защите. | W26: R20 брони, вид воздействия. armor=R20; псионический урон уменьшить на 5 и к встречным проверкам против псионического контроля/чтения/иллюзий +5; иммунитет к удушающему приёму; −6 к бегу/акробатике M−=3; псионическая защита не защищает от химических феромонов. | AB26: 10 | AC26: §4.5, таблица 4, стр. 82; §5.4.3.6, стр. 97–98. | AF26: Нет | AI26: =COUNTIF($B$2:$B$740,B26) -> 1
A27: 26 | B27: CORE-055 | C27: Активно | D27: Реализовать в игровом ядре | E27: Базовое правило | F27: Создание персонажа | G27: Персонажи | H27: 2. Персонаж, предметы и базовая механика | I27: Доспехи | J27: Цесмор | K27: броня / цельный костюм. | L27: Игрок / персонаж | M27: носитель | N27: Цесмор. | O27: экипировка, попадание, перемещение. | P27: S≥14; цельный; без навыка Сталкера/Солдата −15 к перемещениям. | Q27: R20 брони. | R27: закрытые зоны получают armor=R20; применить специальный штраф при отсутствии класса. | S27: броня и модификатор движения. | T27: классы CORE-010/013 отменяют специальный штраф. | W27: R20 брони. закрытые зоны получают armor=R20; применить специальный штраф при отсутствии класса. | AB27: 10 | AC27: §4.5, таблица 4, стр. 82. | AE27: CORE-010 | AF27: Нет | AI27: =COUNTIF($B$2:$B$740,B27) -> 1
A28: 27 | B28: CORE-056 | C28: Активно | D28: Реализовать в игровом ядре | E28: Базовое правило | F28: Создание персонажа | G28: Персонажи | H28: 2. Персонаж, предметы и базовая механика | I28: Доспехи | J28: Гленхейм | K28: броня / цельный костюм. | L28: Игрок / персонаж | M28: носитель | N28: Гленхейм. | O28: экипировка, попадание, движение, попытка борьбы. | P28: S≥24; цельный; без «Солдата Последнего Рассвета» −15 к перемещениям. | Q28: один R20 брони. | R28: armor=2×R20+5; −12 к бегу/акробатике, −6 к уклонению, M−=5; «фиксированный ход суставов» даёт иммунитет к попыткам травмирующего и удушающего приёма. | S28: высокая броня, штрафы, иммунитеты. | T28: обычная травма от пробившей атаки не отменяется. | W28: один R20 брони. armor=2×R20+5; −12 к бегу/акробатике, −6 к уклонению, M−=5; «фиксированный ход суставов» даёт иммунитет к попыткам травмирующего и удушающего приёма. | Y28: armor=2×R20+5; −12 к бегу/акробатике, −6 к уклонению, M−=5; «фиксированный ход суставов» даёт иммунитет к попыткам травмирующего и удушающего приёма. | AB28: 10 | AC28: §4.5, таблица 4, стр. 83. | AF28: Нет | AI28: =COUNTIF($B$2:$B$740,B28) -> 1
A29: 28 | B29: CORE-060 | C29: Активно | D29: Реализовать в игровом ядре | E29: Базовое правило | F29: Создание персонажа | G29: Персонажи | H29: 2. Персонаж, предметы и базовая механика | I29: Фармацевтика | J29: Отвар, приводящий в сознание | K29: фармацевтика / реанимация. | L29: Система / игровая сущность | M29: цель | N29: тяжёлое ранение, сон, паралич. | O29: допустимый приём дозы. | P29: не более 3 доз за скользящие 24 часа. | Q29: состояния цели. | R29: снять тяжёлое ранение и установить HP=1; прекратить снотворное и паралитик без проверок; остановить таймер смерти. | S29: цель в сознании, HP 1 при реанимации. | T29: окончательную смерть не отменяет. | U29: не более 3 доз за скользящие 24 часа. | V29: допустимый приём дозы. не более 3 доз за скользящие 24 часа. снять тяжёлое ранение и установить HP=1; прекратить снотворное и паралитик без проверок; остановить таймер смерти. цель в сознании, HP 1 при реанимации. | W29: снять тяжёлое ранение и установить HP=1; прекратить снотворное и паралитик без проверок; остановить таймер смерти. | Y29: не более 3 доз за скользящие 24 часа. | AB29: 10 | AC29: §4.6, таблица 5, стр. 83–84; §5.5, стр. 104. | AF29: Нет | AI29: =COUNTIF($B$2:$B$740,B29) -> 1
A30: 29 | B30: CORE-064 | C30: Активно | D30: Реализовать в игровом ядре | E30: Базовое правило | F30: Создание персонажа | G30: Персонажи | H30: 2. Персонаж, предметы и базовая механика | I30: Фармацевтика | J30: Восстанавливающий отвар | K30: фармацевтика / лечение. | L30: Система / игровая сущность | M30: цель | N30: HP. | O30: допустимый приём. | P30: ≤2 доз/24ч; цель не в тяжёлом ранении либо эффект прямо выводит — здесь не выводит. | Q30: текущие/максимальные HP. | R30: HP=min(maxHP,HP+25). | S30: восстановление HP. | T30: не реанимирует CORE-156. | V30: ≤2 доз/24ч; цель не в тяжёлом ранении либо эффект прямо выводит — здесь не выводит. текущие/максимальные HP. HP=min(maxHP,HP+25). восстановление HP. | W30: HP=min(maxHP,HP+25). | AB30: 10 | AC30: §4.6, таблица 5, стр. 84. | AE30: CORE-156 | AF30: Нет | AI30: =COUNTIF($B$2:$B$740,B30) -> 1
A31: 30 | B31: CORE-066 | C31: Активно | D31: Реализовать в игровом ядре | E31: Базовое правило | F31: Создание персонажа | G31: Персонажи | H31: 2. Персонаж, предметы и базовая механика | I31: Фармацевтика | J31: Таблетка ночного зрения | K31: фармацевтика / восприятие. | L31: Система / игровая сущность | M31: Чистый | N31: зрение. | O31: приём. | P31: раса Чистый; ≤2 доз/24ч. | Q31: время. | R31: на 2 часа видеть в темноте как днём; повтор обновляет 2 часа. | S31: временный флаг зрения. | T31: числовые штрафы темноты в анализируемых разделах не заданы. | U31: на 2 часа видеть в темноте как днём; повтор обновляет 2 часа. | V31: раса Чистый; ≤2 доз/24ч. | Y31: на 2 часа видеть в темноте как днём; повтор обновляет 2 часа. | AB31: 10 | AC31: §4.6, таблица 5, стр. 84. | AF31: Нет | AI31: =COUNTIF($B$2:$B$740,B31) -> 1
A32: 31 | B32: CORE-067 | C32: Активно | D32: Реализовать в игровом ядре | E32: Базовое правило | F32: Создание персонажа | G32: Персонажи | H32: 2. Персонаж, предметы и базовая механика | I32: Фармацевтика | J32: Таблетка бритвенных рефлексов | K32: фармацевтика / бой. | L32: Система / игровая сущность | M32: Чистый | N32: уклонение и парирование. | O32: приём. | P32: раса Чистый; ≤3 доз/24ч. | Q32: независимый R20 длительности. | R32: длительность max(1,round_math(R20/3)) личных ходов; на срок +3 к уклонению и парированию; повтор не складывает, обновляет срок. | S32: временный эффект. | T32: общая длительность CORE-101. | V32: раса Чистый; ≤3 доз/24ч. | W32: независимый R20 длительности. длительность max(1,round_math(R20/3)) личных ходов; на срок +3 к уклонению и парированию; повтор не складывает, обновляет срок. | Y32: длительность max(1,round_math(R20/3)) личных ходов; на срок +3 к уклонению и парированию; повтор не складывает, обновляет срок. | AB32: 10 | AC32: §4.6, таблица 5, стр. 84. | AE32: CORE-101 | AF32: Нет | AI32: =COUNTIF($B$2:$B$740,B32) -> 1
A33: 32 | B33: CORE-070 | C33: Активно | D33: Реализовать в игровом ядре | E33: Базовое правило | F33: Создание персонажа | G33: Персонажи | H33: 2. Персонаж, предметы и базовая механика | I33: Фармацевтика | J33: Таблетка куража | K33: фармацевтика / серия. | L33: Система / игровая сущность | M33: Чистый | N33: серия приёмов. | O33: приём в существующей боевой ситуации. | P33: раса Чистый; ≤4 доз/24ч. | Q33: текущий бой. | R33: seriesBonus=+1 до конца боя; если первая доза принята в собственный текущий ход после расчёта серии, немедленно увеличить combatActionsRemaining на 1; повтор не увеличивает бонус/остаток, лишь обновляет эффект (практически до того же конца боя). | S33: +1 боевое действие в текущем и каждом следующем личном ходу этого боя. | T33: может увеличить серию выше 5. | U33: +1 боевое действие в текущем и каждом следующем личном ходу этого боя. | V33: раса Чистый; ≤4 доз/24ч. seriesBonus=+1 до конца боя; если первая доза принята в собственный текущий ход после расчёта серии, немедленно увеличить combatActionsRemaining на 1; повтор не увеличивает бонус/остаток, лишь обновляет эффект (практически до того же конца боя). | W33: seriesBonus=+1 до конца боя; если первая доза принята в собственный текущий ход после расчёта серии, немедленно увеличить combatActionsRemaining на 1; повтор не увеличивает бонус/остаток, лишь обновляет эффект (практически до того же конца боя). | Y33: seriesBonus=+1 до конца боя; если первая доза принята в собственный текущий ход после расчёта серии, немедленно увеличить combatActionsRemaining на 1; повтор не увеличивает бонус/остаток, лишь обновляет эффект (практически до того же конца боя). +1 боевое действие в текущем и каждом следующем личном ходу этого боя. | AB33: 10 | AC33: §4.6, таблица 5, стр. 84. | AF33: Нет | AI33: =COUNTIF($B$2:$B$740,B33) -> 1
A34: 33 | B34: CORE-071 | C34: Активно | D34: Реализовать в игровом ядре | E34: Базовое правило | F34: Создание персонажа | G34: Персонажи | H34: 2. Персонаж, предметы и базовая механика | I34: Фармацевтика | J34: Восстанавливающая таблетка | K34: фармацевтика / периодическое лечение. | L34: Система / игровая сущность | M34: Чистый | N34: HP. | O34: приём; конец каждого личного хода цели. | P34: раса Чистый; ≤5 доз/24ч; существующий бой. | Q34: HP/maxHP. | R34: до конца боя в конце каждого хода HP=min(maxHP,HP+5); повтор не складывает. | S34: периодический эффект. | T34: обычное лечение не действует в тяжёлом ранении. | V34: раса Чистый; ≤5 доз/24ч; существующий бой. HP/maxHP. до конца боя в конце каждого хода HP=min(maxHP,HP+5); повтор не складывает. | W34: до конца боя в конце каждого хода HP=min(maxHP,HP+5); повтор не складывает. | Y34: приём; конец каждого личного хода цели. до конца боя в конце каждого хода HP=min(maxHP,HP+5); повтор не складывает. | AB34: 10 | AC34: §4.6, таблица 5, стр. 84; §5.4.2.5, стр. 95. | AF34: Нет | AI34: =COUNTIF($B$2:$B$740,B34) -> 1
A35: 34 | B35: CORE-073 | C35: Активно | D35: Реализовать в игровом ядре | E35: Базовое правило | F35: Создание персонажа | G35: Персонажи | H35: 2. Персонаж, предметы и базовая механика | I35: Базовые проверки, значения и критичность | J35: Проверка характеристики | K35: базовая механика / проверка. | L35: Мастер / игрок / система | M35: действующий персонаж | N35: заявленное действие. | O35: мастер назначил проверку. | P35: игрок до броска заявил намерение и способ; мастер назвал характеристику, навык, сложность и очевидные последствия провала. | Q35: R20, значение характеристики, применимые навыки/эффекты. [Боевой override] combat.active, allowCritical, rawFace, criticalPolarity, criticalGrade и снимок разрешённых модификаторов. originRollId, rollSource, dieType, rawFace, rollKind, actorType. | R35: Сначала зафиксировать ordinaryTotal=R20+characteristic+allowedModifiers. Если combat.active=true и проверка допускает критичность, сырая грань R20 проходит CORE-082–084 и CORE-229 до сравнения с difficulty: подтверждённый критический успех автоматически успешно разрешает текущую проверку независимо от ordinaryTotal; подтверждённый критический провал автоматически проваливает её. При grade=0 применяется обычное result≥difficulty. Вне боевой ситуации действует прежнее математическое сравнение; критическая градация сама по себе не меняет обычный исход. После фиксации исходной натуральной грани передать оригинальный D20 в CORE-230; итог формулы 1/20 без rawFace не является событием прогрессии. | S35: finalCheckSuccess, ordinaryTotal, criticalPolarity, criticalGrade и причина разрешения. Создаётся не более одного symbiontXpEvent на originRollId. | T35: чистые проверки CORE-074; критическая процедура CORE-082–CORE-085. Боевой override применяется только к допускающей критичность проверке по CORE-229; исключённые виды бросков CORE-074/082 остаются исключёнными. Manual и Auto используют одну серверную ветвь; броски подтверждения и подстановки исключены. | W35: R20, значение характеристики, применимые навыки/эффекты. result=R20+characteristic+allowedModifiers; против фиксированной сложности result≥difficulty = успех. | X35: Шкала по умолчанию: 10 простое, 15 обычное, 20 трудное, 25 очень трудное, 30 исключительное, 35 почти невозможное; мастер может назначить иное. В бою сначала сравнить ordinaryTotal с difficulty и из-за этого не запустить подтверждение натуральной 20/1. | AB35: 100 | AC35: §5.1, стр. 85–86. Прямое уточнение пользователя 2026-07-29 — боевой приоритет критов Прямое авторское решение Q-SYMBIONT-XP-001 — опыт симбионтов за natural 20/1, 2026-07-30 | AD35: Q-COMBAT-CRIT-001 Q-SYMBIONT-XP-001 | AE35: CORE-074 CORE-082 CORE-085 CORE-229 CORE-083 CORE-084 CORE-230 | AF35: Да | AG35: Да | AH35: Патч v1.6 (опыт симбионтов) | AI35: =COUNTIF($B$2:$B$740,B35) -> 1
A36: 35 | B36: CORE-074 | C36: Активно | D36: Реализовать в игровом ядре | E36: Базовое правило | F36: Создание персонажа | G36: Персонажи | H36: 2. Персонаж, предметы и базовая механика | I36: Базовые проверки, значения и критичность | J36: Чистый результат и чистая проверка | K36: базовая механика / тип броска. | L36: Система / игровая сущность | M36: любой бросающий | N36: результат. | O36: правило требует «чистый» бросок/результат. | P36: нет. | Q36: дайс, явно записанные фиксированные числа/множители. | R36: чистый результат = грань дайса до модификаторов; чистая проверка не прибавляет характеристику/навык, но сохраняет числа и множители формулы (R20+5 остаётся чистой). Чистый математический итог не создаёт прогрессию; только rawFace оригинального D20 передаётся CORE-230. | S36: числовой результат. | T36: броски урона/пробития/брони/длительности/зоны/таблиц не являются проверками действия без прямого указания. Формульное значение 1 или 20 не заменяет натуральную грань. | U36: броски урона/пробития/брони/длительности/зоны/таблиц не являются проверками действия без прямого указания. | W36: чистый результат = грань дайса до модификаторов; чистая проверка не прибавляет характеристику/навык, но сохраняет числа и множители формулы (R20+5 остаётся чистой). | AA36: Сохранять rawFace отдельно от ordinaryTotal. | AB36: 100 | AC36: §5.1, стр. 86. Прямое авторское решение Q-SYMBIONT-XP-001 — опыт симбионтов за natural 20/1, 2026-07-30 | AD36: Q-SYMBIONT-XP-001 | AE36: CORE-230 | AF36: Нет | AG36: Да | AH36: Патч v1.6 (опыт симбионтов) | AI36: =COUNTIF($B$2:$B$740,B36) -> 1
A37: 36 | B37: CORE-075 | C37: Активно | D37: Реализовать в игровом ядре | E37: Базовое правило | F37: Создание персонажа | G37: Персонажи | H37: 2. Персонаж, предметы и базовая механика | I37: Базовые проверки, значения и критичность | J37: Встречная проверка и равенство | K37: базовая механика / сравнение. | L37: Система / игровая сущность | M37: инициатор и противодействующая цель. | O37: действие требует превысить результат цели. | P37: цель может и желает выполнять встречную проверку. | Q37: ordinaryTotal и снимок модификаторов каждой стороны; rawFace, criticalPolarity и criticalGrade каждой стороны; DefenseChoice. originRollId и собственная rawFace каждого участника. | R37: Вне боевой ситуации изменение по-прежнему происходит только при строгом initiatorTotal>opponentTotal; равенство сохраняет положение. В боевой встречной проверке сначала применить CORE-229. Порядок: (1) единственный подтверждённый критический успех выигрывает текущую проверку независимо от итогов и критического провала другой стороны; (2) при двух критических успехах сравниваются только градации; (3) при равных положительных градациях без нового броска пересчитать оба ordinaryTotal из исходных снимков так, как если бы rawFace каждой стороны был равен 20, criticalGrade=0 и подтверждения не было, затем применить строгое сравнение, причём равенство сохраняет защиту/status quo; (4) если положительных критов нет, проверка с подтверждённым критическим провалом автоматически провалена; при критическом провале обеих сторон обе проверки провалены и инициирующее изменение не происходит; (5) если подтверждённых критов нет, применяется обычное строгое сравнение. DefenseChoice=NONE разрешается по CORE-217. Прогрессия определяется отдельно по собственной грани участника до выбора победителя; проигрыш встречной проверки событие не отменяет. | S37: winner=INITIATOR|OPPONENT|STATUS_QUO, resolutionMode, ordinaryTotals, criticalGrades. | T37: конкретное правило может задать фиксированную сложность/автоматический успех. Локальный прямой автоматический исход конкретной способности сильнее общего порядка; SYM-066 отражает допустимую атаку независимо от её критичности. | U37: действие требует превысить результат цели. | W37: equalPositiveGrade: replayRoll=false; comparisonFaceInitiator=20; comparisonFaceOpponent=20; затем initiatorTotal>opponentTotal. | X37: Если цель не выполняет встречную проверку, её броска нет; атака попадает после остальных условий, пассивная броня остаётся. Сравнить обычные суммы раньше критических градаций; выполнить новый бросок при равных градациях; объявить успешной проверку с подтверждённым критическим провалом. | AA37: Не объединять originRollId противостоящих сторон. | AB37: 100 | AC37: §5.1, стр. 86; §5.4.6, стр. 102. Предразработочный QA и прямые ответы пользователя 2026-07-29 Прямое уточнение пользователя 2026-07-29 — боевой приоритет критов Прямое авторское решение Q-SYMBIONT-XP-001 — опыт симбионтов за natural 20/1, 2026-07-30 | AD37: Q-PREDEV-002 Q-COMBAT-CRIT-001 Q-SYMBIONT-XP-001 | AE37: CORE-217 CORE-229 SYM-066 CORE-230 | AF37: Да | AG37: Да | AH37: Патч v1.6 (опыт симбионтов) | AI37: =COUNTIF($B$2:$B$740,B37) -> 1
A38: 37 | B38: CORE-076 | C38: Активно | D38: Реализовать в игровом ядре | E38: Базовое правило | F38: Создание персонажа | G38: Персонажи | H38: 2. Персонаж, предметы и базовая механика | I38: Базовые проверки, значения и критичность | J38: Общие правила округления и нижних границ | K38: вычисления. | L38: Система / игровая сущность | M38: любая формула. | O38: формула даёт дробный/отрицательный результат. | P38: свой способ округления не указан. | Q38: конечный результат формулы. | R38: округлять только конечный результат математически (<.5 вниз, ≥.5 вверх); положительная длительность/число ходов/действий/целей/объектов после деления минимум 1; явно рассчитанные ≤0 расстояние, урон, штраф или бонус =0; проценты числа существ округлять вверх. | S38: нормализованное число. | T38: требования предметов всегда округляются вверх; формула, где эффект при ≤0 «не возникает», имеет приоритет. | U38: округлять только конечный результат математически (<.5 вниз, ≥.5 вверх); положительная длительность/число ходов/действий/целей/объектов после деления минимум 1; явно рассчитанные ≤0 расстояние, урон, штраф или бонус =0; проценты числа существ округлять вверх. | W38: формула даёт дробный/отрицательный результат. конечный результат формулы. округлять только конечный результат математически (<.5 вниз, ≥.5 вверх); положительная длительность/число ходов/действий/целей/объектов после деления минимум 1; явно рассчитанные ≤0 расстояние, урон, штраф или бонус =0; проценты числа существ округлять вверх. требования предметов всегда округляются вверх; формула, где эффект при ≤0 «не возникает», имеет приоритет. | X38: требования предметов всегда округляются вверх; формула, где эффект при ≤0 «не возникает», имеет приоритет. | Y38: округлять только конечный результат математически (<.5 вниз, ≥.5 вверх); положительная длительность/число ходов/действий/целей/объектов после деления минимум 1; явно рассчитанные ≤0 расстояние, урон, штраф или бонус =0; проценты числа существ округлять вверх. | AB38: 10 | AC38: §5.1, стр. 86. | AF38: Нет | AI38: =COUNTIF($B$2:$B$740,B38) -> 1
A39: 38 | B39: CORE-077 | C39: Активно | D39: Реализовать в игровом ядре | E39: Базовое правило | F39: Создание персонажа | G39: Персонажи | H39: 2. Персонаж, предметы и базовая механика | I39: Базовые проверки, значения и критичность | J39: Границы HP и ОЭ | K39: ресурс. | L39: Игрок / персонаж | M39: персонаж/симбионт | N39: HP, ОЭ. | O39: любое изменение текущего или максимального запаса. | P39: нет. | Q39: delta/set, текущий максимум. | R39: clamp текущего в [0,currentMax]; избыточное восстановление пропадает; при временном снижении max текущий снизить до нового max, если выше; увеличение max само не восстанавливает текущий запас. | S39: валидный ресурс. | T39: тяжёлое ранение срабатывает при HP=0. | V39: валидный ресурс. тяжёлое ранение срабатывает при HP=0. | W39: тяжёлое ранение срабатывает при HP=0. | AB39: 10 | AC39: §5.1, стр. 86. | AF39: Нет | AI39: =COUNTIF($B$2:$B$740,B39) -> 1
A40: 39 | B40: CORE-078 | C40: Активно | D40: Реализовать в игровом ядре | E40: Базовое правило | F40: Создание персонажа | G40: Персонажи | H40: 2. Персонаж, предметы и базовая механика | I40: Базовые проверки, значения и критичность | J40: Постоянные характеристики и пределы | K40: характеристика / значение. | L40: Игрок / персонаж | M40: персонаж | N40: S,D,M,C,W,I,Z. | O40: создание или изменение характеристики. | P40: нет. | Q40: базовое значение, постоянные/временные эффекты. | R40: постоянное значение не ниже 1; ручное распределение до расовых/симбиотических поправок — не более 20 в одну характеристику; случайные значения, криты, раса, симбионты и развитие могут дать >20; временный штраф может сделать итог проверки отрицательным, но не саму характеристику, если эффект не говорит иное. | S40: валидная характеристика. | T40: специальное последствие снижения ниже 1 сначала срабатывает, затем для расчётов значение 1. | Z40: постоянное значение не ниже 1; ручное распределение до расовых/симбиотических поправок — не более 20 в одну характеристику; случайные значения, криты, раса, симбионты и развитие могут дать >20; временный штраф может сделать итог проверки отрицательным, но не саму характеристику, если эффект не говорит иное. | AB40: 10 | AC40: §5.1, стр. 86–87; §6.1, стр. 105. | AF40: Нет | AI40: =COUNTIF($B$2:$B$740,B40) -> 1
A41: 40 | B41: CORE-079 | C41: Активно | D41: Реализовать в игровом ядре | E41: Базовое правило | F41: Создание персонажа | G41: Персонажи | H41: 2. Персонаж, предметы и базовая механика | I41: Базовые проверки, значения и критичность | J41: Порядок применения модификаторов характеристики | K41: характеристика / вычисление. | L41: Игрок / персонаж | M41: персонаж | N41: итоговое значение характеристики. | O41: пересчёт. | P41: имеются эффекты. | Q41: база, раса, постоянное развитие/симбионты, временные ±, ×/÷, установки/min/max. | R41: 1) постоянное значение; 2) временные прибавки/штрафы; 3) умножение/деление; 4) точная установка и явно названные min/max. «Становится равной/до» применяется после обычных модификаторов. | S41: итоговая характеристика. | T41: при несовместимых установках — более конкретная, при равной конкретности более ограничительная. | W41: база, раса, постоянное развитие/симбионты, временные ±, ×/÷, установки/min/max. | AB41: 10 | AC41: §5.1, стр. 87. | AF41: Нет | AI41: =COUNTIF($B$2:$B$740,B41) -> 1
A42: 41 | B42: CORE-082 | C42: Активно | D42: Реализовать в игровом ядре | E42: Базовое правило | F42: Создание персонажа | G42: Персонажи | H42: 2. Персонаж, предметы и базовая механика | I42: Базовые проверки, значения и критичность | J42: Инициация критической проверки | K42: крит / триггер. | L42: Система / игровая сущность | M42: значимая проверка | N42: натуральная 1 или 20. | O42: В бою: натуральная 20 или натуральная 1 на допускающей критичность проверке — до математического определения успеха. Вне боя: натуральная 20 при обычном успехе либо натуральная 1 при обычном провале. | P42: Это заранее назначенная значимая проверка действия, атаки, защиты или сопротивления с allowCritical=true. Для боевого override дополнительно combat.active=true. | Q42: combat.active, checkKind, allowCritical, rawFace, ordinaryTotal и снимок модификаторов. | R42: Если combat.active=true, allowCritical=true и rawFace=20, запустить положительную цепочку CORE-083 до математического сравнения; если rawFace=1 — отрицательную цепочку CORE-084. Предварительный ordinaryTotal не блокирует подтверждение. Если первая проверка подтверждения не прошла, criticalGrade=0 и натуральная 20/1 разрешается обычной математикой. Вне боевой ситуации сохраняется прежний порядок: подтверждение запускается только для натуральной 20 на уже успешной обычной проверке или натуральной 1 на уже проваленной. Безопасное бессмысленное повторение не считается проверкой. В базовой MONSTER_ATTACK критичность относится только к accuracy-R20. Натуральная 20 и натуральная 1 оригинального D20 передаются в CORE-230 независимо от подтверждения; подтверждение только определяет eventPoints исходного броска. | S42: criticalPolarity=SUCCESS|FAILURE|NONE, criticalGrade=0..5, confirmed=true|false либо обычный исход. confirmationRoll не создаёт самостоятельного symbiontXpEvent. | T42: Не применяется к урону, пробитию, броне, лечению, длительности, количеству, зоне, инициативе и случайным таблицам; специальный эффект способности на чистой 1/20 действует независимо; создание характеристик имеет исключение CORE-163, случайное получение симбиотического чудовища — CORE-170. SYM-082 является локальным ability override. NO_DIRECT_BUT_POOL не запускает цепочку критичности и при rawFace 1/20 создаёт 1 балл. | U42: это проверка действия, атаки, защиты или сопротивления, назначенная мастером до броска и имеющая риск/последствия. | W42: combat.active: rawFace=20 → confirmSuccessChain; rawFace=1 → confirmFailureChain; trigger не зависит от ordinaryTotal. grade=0 → ordinary resolution. | X42: натуральные 1/20 сами не меняют обычный исход; только соответствующий обычный исход запускает подтверждение CORE-083/084. В бою не запускать подтверждение только потому, что natural 20 математически не достигла сложности, либо natural 1 математически достигла её. | AB42: 100 | AC42: §5.2, стр. 87–88. Прямое уточнение пользователя 2026-07-28 — шаблоны врагов v1.3 Прямое уточнение пользователя 2026-07-29 — боевой приоритет критов Прямое авторское решение Q-SYMBIONT-XP-001 — опыт симбионтов за natural 20/1, 2026-07-30 | AD42: Q-ENEMY-B7 Q-COMBAT-CRIT-001 Q-SYMBIONT-XP-001 | AE42: CORE-083 CORE-163 CORE-170 CORE-208 CORE-210 CORE-229 CORE-074 CORE-084 SYM-082 CORE-230 | AF42: Да | AG42: Да | AH42: Патч v1.6 (опыт симбионтов) | AI42: =COUNTIF($B$2:$B$740,B42) -> 1
A43: 42 | B43: CORE-083 | C43: Активно | D43: Реализовать в игровом ядре | E43: Базовое правило | F43: Создание персонажа | G43: Персонажи | H43: 2. Персонаж, предметы и базовая механика | I43: Базовые проверки, значения и критичность | J43: Критический успех | K43: крит / успех. | L43: Система / игровая сущность | M43: успешная проверка с натуральной 20. | O43: CORE-082. | P43: В бою — допускающая критичность проверка с natural 20 независимо от ordinaryTotal; вне боя — ordinary outcome уже успешен. | Q43: последовательность независимых R20 подтверждения. originRollId исходного броска; isConfirmationRoll=true для подтверждающих D20. | R43: Первый независимый R20 подтверждения 15–20 даёт Crit; каждый следующий подряд 15–20 повышает градацию: Double, Triple, Ultra, максимум Rampage; первый результат вне 15–20 завершает цепь. Неподтверждённая 20 получает grade=0 и остаётся обычным результатом. В бою подтверждённый positive grade передаётся CORE-229 и автоматически успешно разрешает только текущую проверку, если ему не противостоит подтверждённый критический успех другой стороны. Градация 1..5 назначает eventPoints исходному originRollId; сами подтверждающие броски маршрутизируются NEVER_PROGRESSION. | S43: confirmed=true, criticalPolarity=SUCCESS, grade=1..5; в бою finalCheckSuccess определяется CORE-229. Один progression event на исходный D20. | T43: Автоматический успех относится только к текущей проверке: он не отменяет законность цели, дистанцию, оплату действия/ОЭ/боеприпаса, пробитие, броню, урон и иные независимые этапы. Локальное прямое исключение способности сильнее. | W43: последовательность независимых R20 подтверждения. | X43: В бою потребовать предварительный математический успех либо перенести автоматический успех на последующие независимые этапы. | AA43: Цепочку подтверждения хранить как дочерние rollId без отдельной прогрессии. | AB43: 100 | AC43: §5.2–5.2.1, стр. 87–88. Прямое уточнение пользователя 2026-07-29 — боевой приоритет критов Прямое авторское решение Q-SYMBIONT-XP-001 — опыт симбионтов за natural 20/1, 2026-07-30 | AD43: Q-COMBAT-CRIT-001 Q-SYMBIONT-XP-001 | AE43: CORE-082 CORE-229 CORE-075 CORE-125 SYM-066 CORE-230 | AF43: Да | AG43: Да | AH43: Патч v1.6 (опыт симбионтов) | AI43: =COUNTIF($B$2:$B$740,B43) -> 1
A44: 43 | B44: CORE-084 | C44: Активно | D44: Реализовать в игровом ядре | E44: Базовое правило | F44: Создание персонажа | G44: Персонажи | H44: 2. Персонаж, предметы и базовая механика | I44: Базовые проверки, значения и критичность | J44: Критический провал | K44: крит / провал. | L44: Система / игровая сущность | M44: проваленная проверка с натуральной 1. | O44: CORE-082. | P44: В бою — допускающая критичность проверка с natural 1 независимо от ordinaryTotal; вне боя — ordinary outcome уже провален. | Q44: последовательность R20. originRollId исходного броска; isConfirmationRoll=true для подтверждающих D20. | R44: Первый независимый R20 подтверждения 1–5 даёт Crit; каждый следующий подряд 1–5 повышает градацию до Rampage; первый выход из диапазона завершает цепь. Неподтверждённая 1 получает grade=0 и остаётся обычным результатом. В бою подтверждённый negative grade передаётся CORE-229 и автоматически проваливает только текущую проверку независимо от ordinaryTotal. Если обе стороны встречной проверки получили подтверждённый критический провал, обе проверки провалены и инициирующее изменение не происходит. Градация 1..5 назначает eventPoints исходному originRollId; сами подтверждающие броски маршрутизируются NEVER_PROGRESSION. | S44: confirmed=true, criticalPolarity=FAILURE, grade=1..5; в бою finalCheckSuccess=false. Один progression event на исходный D20. | T44: Автоматический провал не возвращает уже списанные ресурсы и не отменяет специальные последствия natural 1. SYM-082 может локально заменить свою natural 1 на положительный Crit первой градации. | W44: последовательность R20. | X44: В бою потребовать предварительный математический провал либо спасти подтверждённый критический провал модификаторами. | AA44: Цепочку подтверждения хранить как дочерние rollId без отдельной прогрессии. | AB44: 100 | AC44: §5.2–5.2.1, стр. 87–88. Прямое уточнение пользователя 2026-07-29 — боевой приоритет критов Прямое авторское решение Q-SYMBIONT-XP-001 — опыт симбионтов за natural 20/1, 2026-07-30 | AD44: Q-COMBAT-CRIT-001 Q-SYMBIONT-XP-001 | AE44: CORE-082 CORE-083 CORE-229 CORE-075 CORE-125 SYM-082 CORE-230 | AF44: Да | AG44: Да | AH44: Патч v1.6 (опыт симбионтов) | AI44: =COUNTIF($B$2:$B$740,B44) -> 1
A45: 44 | B45: CORE-086 | C45: Активно | D45: Реализовать в игровом ядре | E45: Базовое правило | F45: Создание персонажа | G45: Персонажи | H45: 2. Персонаж, предметы и базовая механика | I45: Боевая ситуация, инициатива и действия | J45: Начало и окончание боя | K45: бой / жизненный цикл. | L45: Система / игровая сущность | M45: все стороны | N45: боевая ситуация. | O45: объявление нападения или непосредственные враждебные действия. | P45: минимум две противостоящие стороны. | Q45: действия круга, возможность/намерение сторон. | R45: открыть бой; завершить, если полный круг никто не совершал и не готовил враждебных действий либо одна сторона утратила возможность или намерение продолжать. | S45: combat.active и границы эффектов «до конца боя». | T45: решение о завершении сцены принимает мастер. | U45: объявление нападения или непосредственные враждебные действия. действия круга, возможность/намерение сторон. открыть бой; завершить, если полный круг никто не совершал и не готовил враждебных действий либо одна сторона утратила возможность или намерение продолжать. | Y45: действия круга, возможность/намерение сторон. открыть бой; завершить, если полный круг никто не совершал и не готовил враждебных действий либо одна сторона утратила возможность или намерение продолжать. combat.active и границы эффектов «до конца боя». | AB45: 10 | AC45: §5.4.1, стр. 92–93. | AF45: Нет | AI45: =COUNTIF($B$2:$B$740,B45) -> 1
A46: 45 | B46: CORE-087 | C46: Активно | D46: Реализовать в игровом ядре | E46: Базовое правило | F46: Создание персонажа | G46: Персонажи | H46: 2. Персонаж, предметы и базовая механика | I46: Боевая ситуация, инициатива и действия | J46: Обычная инициатива | K46: бой / инициатива. | L46: Система / игровая сущность | M46: каждый участник | N46: порядок ходов. | O46: обычное начало боя либо конец сцены нападения; вход нового участника. | P46: участник вступил в бой. | Q46: чистый R20 каждого. originRollId, rawFace. | R46: сортировать по убыванию; ничью перебрасывают только связанные участники до развязки; порядок сохраняется до конца боя. Инициатива чистая, если способность прямо не модифицирует. INITIATIVE относится к NO_DIRECT_BUT_POOL: rawFace 1/20 даёт ровно 1 балл, прямой XP запрещён. | S46: фиксированная очередь. progressionRoute=CHARACTER_PROGRESS_COUNTER или NEVER. | T46: сцена нападения CORE-088. | W46: чистый R20 каждого. | Y46: сортировать по убыванию; ничью перебрасывают только связанные участники до развязки; порядок сохраняется до конца боя. | AB46: 100 | AC46: §5.4.1, стр. 93. Прямое авторское решение Q-SYMBIONT-XP-001 — опыт симбионтов за natural 20/1, 2026-07-30 | AD46: Q-SYMBIONT-XP-001 | AE46: CORE-088 CORE-230 | AF46: Нет | AG46: Да | AH46: Патч v1.6 (опыт симбионтов) | AI46: =COUNTIF($B$2:$B$740,B46) -> 1
A47: 46 | B47: CORE-089 | C47: Активно | D47: Реализовать в игровом ядре | E47: Базовое правило | F47: Создание персонажа | G47: Персонажи | H47: 2. Персонаж, предметы и базовая механика | I47: Боевая ситуация, инициатива и действия | J47: Упреждение неожиданного нападения | K47: бой / реакция. | L47: Игрок / система | M47: персонаж с разрешающим навыком/способностью. | O47: начало сцены нападения. | P47: источник прямо разрешает среагировать. | Q47: R20+все бонусы реакции. | R47: итог ≥18 даёт одно упреждающее боевое действие до нападающих; несколько успешных действуют по убыванию результата, ничья — чистый R20. Чумной доктор с «Распределением сил» автоматически успешен; порядок с другими — чистый R20. | S47: одно действие вне очереди. | T47: это не упреждающий удар как защита CORE-148. | U47: R20+все бонусы реакции. итог ≥18 даёт одно упреждающее боевое действие до нападающих; несколько успешных действуют по убыванию результата, ничья — чистый R20. одно действие вне очереди. | W47: R20+все бонусы реакции. итог ≥18 даёт одно упреждающее боевое действие до нападающих; несколько успешных действуют по убыванию результата, ничья — чистый R20. Чумной доктор с «Распределением сил» автоматически успешен; порядок с другими — чистый R20. | AB47: 10 | AC47: §5.4.1, стр. 93–94. | AE47: CORE-148 | AF47: Нет | AI47: =COUNTIF($B$2:$B$740,B47) -> 1
A48: 47 | B48: CORE-092 | C48: Активно | D48: Реализовать в игровом ядре | E48: Базовое правило | F48: Создание персонажа | G48: Персонажи | H48: 2. Персонаж, предметы и базовая механика | I48: Боевая ситуация, инициатива и действия | J48: Режим одновременных D20/D12/D6 | K48: бой / режим бросков. | L48: Система / игровая сущность | M48: группа | N48: боевое действие. | O48: до начала игры выбран ускоренный режим; начинается действие. | P48: договорённость группы сохранена в настройках кампании. | Q48: один D20, D12, D6. | R48: каждый результат назначается только первому по порядку этапу текущего действия, которому нужен такой дайс; второй дайс того же вида бросить отдельно; один результат нельзя переиспользовать; порядок и вероятности этапов не меняются. Если предбросок затем потреблён как оригинальный D20 проверки, именно в момент потребления ему назначается originRollId и выполняется CORE-230; при хранении предброска события нет. | S48: пул предварительных результатов действия. Повторное потребление того же предброска блокируется CORE-233. | T48: не объединяет независимые проверки. | U48: до начала игры выбран ускоренный режим; начинается действие. каждый результат назначается только первому по порядку этапу текущего действия, которому нужен такой дайс; второй дайс того же вида бросить отдельно; один результат нельзя переиспользовать; порядок и вероятности этапов не меняются. пул предварительных результатов действия. | W48: один D20, D12, D6. | X48: каждый результат назначается только первому по порядку этапу текущего действия, которому нужен такой дайс; второй дайс того же вида бросить отдельно; один результат нельзя переиспользовать; порядок и вероятности этапов не меняются. | Y48: до начала игры выбран ускоренный режим; начинается действие. | AB48: 100 | AC48: §5.4.2, стр. 94. Прямое авторское решение Q-SYMBIONT-XP-001 — опыт симбионтов за natural 20/1, 2026-07-30 | AD48: Q-SYMBIONT-XP-001 | AE48: CORE-230 | AF48: Нет | AG48: Да | AH48: Патч v1.6 (опыт симбионтов) | AI48: =COUNTIF($B$2:$B$740,B48) -> 1
A49: 48 | B49: CORE-094 | C49: Активно | D49: Реализовать в игровом ядре | E49: Базовое правило | F49: Создание персонажа | G49: Персонажи | H49: 2. Персонаж, предметы и базовая механика | I49: Боевая ситуация, инициатива и действия | J49: Бег «несмотря ни на что» | K49: бой / действие и реакции. | L49: Система / игровая сущность | M49: бегущий | N49: соседние враги. | O49: заявление специального бега. | P49: расход 1 боевого действия; En>0 допустим. | Q49: R20,D, список соседних врагов. | R49: дистанция max(0,R20+D) (с дальнейшим делением местности); до движения каждый соседний враг получает ровно одну немедленную рукопашную атаку без расхода действий; активная защита от них запрещена, броня/пассивы работают; затем движение, если бегущий жив/способен. | S49: реакции, затем позиция. | T49: реакция не порождает реакцию без прямого разрешения CORE-102. | U49: расход 1 боевого действия дистанция max(0,R20+D) (с дальнейшим делением местности); до движения каждый соседний враг получает ровно одну немедленную рукопашную атаку без расхода действий; активная защита от них запрещена, броня/пассивы работают; затем движение, если бегущий жив/способен. реакции, затем позиция. реакция не порождает реакцию без прямого разрешения CORE-102. | W49: R20,D, список соседних врагов. дистанция max(0,R20+D) (с дальнейшим делением местности); до движения каждый соседний враг получает ровно одну немедленную рукопашную атаку без расхода действий; активная защита от них запрещена, броня/пассивы работают; затем движение, если бегущий жив/способен. | X49: дистанция max(0,R20+D) (с дальнейшим делением местности); до движения каждый соседний враг получает ровно одну немедленную рукопашную атаку без расхода действий; активная защита от них запрещена, броня/пассивы работают; затем движение, если бегущий жив/способен. | AB49: 10 | AC49: §5.4.2.1, стр. 94. | AE49: CORE-102 | AF49: Нет | AI49: =COUNTIF($B$2:$B$740,B49) -> 1
A50: 49 | B50: CORE-095 | C50: Активно | D50: Реализовать в игровом ядре | E50: Базовое правило | F50: Создание персонажа | G50: Персонажи | H50: 2. Персонаж, предметы и базовая механика | I50: Боевая ситуация, инициатива и действия | J50: Базовая серия приёмов | K50: бой / действия хода. | L50: Система / игровая сущность | M50: участник | N50: боевые и небоевое действия. | O50: начало личного хода. | P50: это обычный ход, не сцена нападения/полный пропуск. | Q50: чистый R20 серии, бонусы/штрафы. | R50: Нормативная база (действует во всей непротиворечащей части): чистая грань 1–7→1, 8–12→2, 13–17→3, 18–19→4, 20→5 базовых боевых действий; затем бонусы/штрафы, итог может быть 0 или >5; дополнительно 1 небоевое действие. Приоритетные авторские дельты (заменяют только прямо пересекающиеся ветви): [Обязательная правка] Эта формулировка имеет приоритет над исходным текстом карточки. удалить ссылку на исключённую усталость CORE-002 | S50: combatActionsRemaining, nonCombatActionsRemaining=1. | T50: усталость CORE-002, Кураж CORE-070; крит серии не проверяется. Поздние дельты применяются по приоритету AQ3 > AQ2 > AQA/CQA > базовая карточка; локальное исключение сильнее общего. | U50: Нормативная база (действует во всей непротиворечащей части): чистая грань 1–7→1, 8–12→2, 13–17→3, 18–19→4, 20→5 базовых боевых действий; затем бонусы/штрафы, итог может быть 0 или >5; дополнительно 1 небоевое действие. | W50: чистый R20 серии, бонусы/штрафы. [Обязательная правка] Эта формулировка имеет приоритет над исходным текстом карточки. combatActionsRemaining, nonCombatActionsRemaining=1. | Y50: начало личного хода. это обычный ход, не сцена нападения/полный пропуск. Нормативная база (действует во всей непротиворечащей части): | AB50: 10 | AC50: §5.4.2.2, стр. 94–95. | AE50: CORE-002 CORE-070 | AF50: Нет | AI50: =COUNTIF($B$2:$B$740,B50) -> 1
A51: 50 | B51: CORE-096 | C51: Активно | D51: Реализовать в игровом ядре | E51: Базовое правило | F51: Создание персонажа | G51: Персонажи | H51: 2. Персонаж, предметы и базовая механика | I51: Боевая ситуация, инициатива и действия | J51: Стоимость обычных боевых действий | K51: бой / стоимость. | L51: Система / игровая сущность | M51: действующий | N51: действие. | O51: заявление действия, непосредственно влияющего на бой. | P51: доступно действие. | Q51: тип. | R51: если не указано иное, 1 боевое действие стоят: обычная атака, одно перемещение, активная способность симбионта, смена оружия в руках, вставание, освобождение из захвата и иное прямое боевое действие. | S51: combatActionsRemaining−=1. | T51: специальная цена/бесплатная реакция имеет приоритет. | U51: заявление действия, непосредственно влияющего на бой. доступно действие. если не указано иное, 1 боевое действие стоят: обычная атака, одно перемещение, активная способность симбионта, смена оружия в руках, вставание, освобождение из захвата и иное прямое боевое действие. специальная цена/бесплатная реакция имеет приоритет. | V51: специальная цена/бесплатная реакция имеет приоритет. | W51: combatActionsRemaining−=1. | AB51: 10 | AC51: §5.4.2.2, стр. 94–95. | AF51: Нет | AI51: =COUNTIF($B$2:$B$740,B51) -> 1
A52: 51 | B52: CORE-097 | C52: Активно | D52: Реализовать в игровом ядре | E52: Базовое правило | F52: Создание персонажа | G52: Персонажи | H52: 2. Персонаж, предметы и базовая механика | I52: Боевая ситуация, инициатива и действия | J52: Небоевое действие в бою | K52: бой / действие. | L52: Система / игровая сущность | M52: действующий | N52: небоевое действие. | O52: короткая фраза, самоприём препарата, доступный мелкий предмет, простое окружение. | P52: действие не заменяет атаку, лечение, перемещение или иную непосредственную процедуру. | Q52: заявка. | R52: расходовать единственное небоевое действие; не разрешать им лечение, движение или атаку. | S52: nonCombatActionsRemaining=0 и косвенное изменение. | T52: передача/принудительное введение препарата — боевое действие. | U52: действие не заменяет атаку, лечение, перемещение или иную непосредственную процедуру. расходовать единственное небоевое действие; не разрешать им лечение, движение или атаку. передача/принудительное введение препарата — боевое действие. | W52: nonCombatActionsRemaining=0 и косвенное изменение. | AB52: 10 | AC52: §5.4.2.2, стр. 94–95. | AF52: Нет | AI52: =COUNTIF($B$2:$B$740,B52) -> 1
A53: 52 | B53: CORE-098 | C53: Активно | D53: Реализовать в игровом ядре | E53: Базовое правило | F53: Создание персонажа | G53: Персонажи | H53: 2. Персонаж, предметы и базовая механика | I53: Боевая ситуация, инициатива и действия | J53: Подготовленное действие | K53: бой / реакция. | L53: Игрок / персонаж | M53: готовящийся персонаж | N53: резерв действий. | O53: в свой ход заявлен наблюдаемый триггер и конкретное действие. | P53: хватает действий на полную цену. | Q53: trigger predicate, command, actionCost, initiative. | R53: сразу зарезервировать действия; при наступлении триггера выполнить до завершения вызвавшего действия; несколько подготовок — по более высокой инициативе; потратить резерв один раз; неиспользованный сгорает в конце текущего круга. | S53: подготовка/выполненная команда/сгоревший резерв. | T53: наблюдаемость и точность триггера валидирует мастер. | U53: в свой ход заявлен наблюдаемый триггер и конкретное действие. хватает действий на полную цену. сразу зарезервировать действия; при наступлении триггера выполнить до завершения вызвавшего действия; несколько подготовок — по более высокой инициативе; потратить резерв один раз; неиспользованный сгорает в конце текущего круга. | V53: хватает действий на полную цену. | Y53: в свой ход заявлен наблюдаемый триггер и конкретное действие. сразу зарезервировать действия; при наступлении триггера выполнить до завершения вызвавшего действия; несколько подготовок — по более высокой инициативе; потратить резерв один раз; неиспользованный сгорает в конце текущего круга. | AA53: сразу зарезервировать действия; при наступлении триггера выполнить до завершения вызвавшего действия; несколько подготовок — по более высокой инициативе; потратить резерв один раз; неиспользованный сгорает в конце текущего круга. | AB53: 10 | AC53: §5.4.2.3, стр. 95. | AF53: Нет | AI53: =COUNTIF($B$2:$B$740,B53) -> 1
A54: 53 | B54: CORE-099 | C54: Активно | D54: Реализовать в игровом ядре | E54: Базовое правило | F54: Создание персонажа | G54: Персонажи | H54: 2. Персонаж, предметы и базовая механика | I54: Боевая ситуация, инициатива и действия | J54: Лимиты защит и дополнительных атак | K54: бой / лимиты реакций. | L54: Игрок / система | M54: защищающийся | N54: круг. | O54: защита/ответная атака. | P54: защита доступна. | Q54: вид защиты и круговые счётчики. | R54: уклонение/блок не требуют подготовки и доступны в пределах их описаний; парирование и упреждающий удар не расходуют боевые действия, но максимум по одной попытке каждого за круг; на одну атаку выбрать одну защиту; все немедленные дополнительные атаки от защит одного персонажа вместе срабатывают максимум один раз за круг. | S54: обновить счётчики. | T54: конкретная способность может задать иной предел. | U54: уклонение/блок не требуют подготовки и доступны в пределах их описаний; парирование и упреждающий удар не расходуют боевые действия, но максимум по одной попытке каждого за круг; на одну атаку выбрать одну защиту; все немедленные дополнительные атаки от защит одного персонажа вместе срабатывают максимум один раз за круг. | Y54: вид защиты и круговые счётчики. уклонение/блок не требуют подготовки и доступны в пределах их описаний; парирование и упреждающий удар не расходуют боевые действия, но максимум по одной попытке каждого за круг; на одну атаку выбрать одну защиту; все немедленные дополнительные атаки от защит одного персонажа вместе срабатывают максимум один раз за круг. | AA54: уклонение/блок не требуют подготовки и доступны в пределах их описаний; парирование и упреждающий удар не расходуют боевые действия, но максимум по одной попытке каждого за круг; на одну атаку выбрать одну защиту; все немедленные дополнительные атаки от защит одного персонажа вместе срабатывают максимум один раз за круг. | AB54: 10 | AC54: §5.4.2.3, стр. 95. | AF54: Нет | AI54: =COUNTIF($B$2:$B$740,B54) -> 1
A55: 54 | B55: CORE-100 | C55: Активно | D55: Реализовать в игровом ядре | E55: Базовое правило | F55: Создание персонажа | G55: Персонажи | H55: 2. Персонаж, предметы и базовая механика | I55: Боевая ситуация, инициатива и действия | J55: Смена цели ближнего боя | K55: бой / действие. | L55: Система / игровая сущность | M55: атакующий | N55: текущая цель. | O55: выбор иной цели ближних атак. | P55: текущая цель сохраняется и нет исключения. | Q55: причины смены, класс. | R55: по умолчанию списать 1 боевое действие. Бесплатно, если старая цель тяжело ранена, убегает, исчезла из поля зрения, вышла из боя либо атакующий — Солдат Последнего Рассвета. | S55: новая текущая цель. | T55: перемещение к ней оплачивается всегда. | U55: по умолчанию списать 1 боевое действие. | AB55: 10 | AC55: §5.4.2.4, стр. 95; §3.4.7.3.2, стр. 66. | AF55: Нет | AI55: =COUNTIF($B$2:$B$740,B55) -> 1
A56: 55 | B56: CORE-102 | C56: Активно | D56: Реализовать в игровом ядре | E56: Базовое правило | F56: Создание персонажа | G56: Персонажи | H56: 2. Персонаж, предметы и базовая механика | I56: Боевая ситуация, инициатива и действия | J56: Типы действий вне хода и запрет цепочки | K56: бой / реакция. | L56: Система / игровая сущность | M56: участник | N56: атака или событие. | O56: разрешённый ответ вне собственного хода. | P56: правило прямо разрешает. | Q56: вид реакции. | R56: защитное действие отвечает на конкретную атаку и не расходует боевые действия; реакция охватывает упреждение, парирование, подготовку и немедленные ответы; один эффект не порождает реакцию на другую реакцию без прямого разрешения. | S56: разрешённая/запрещённая команда. | T56: подготовка расходует заранее зарезервированные действия. | U56: вид реакции. защитное действие отвечает на конкретную атаку и не расходует боевые действия; реакция охватывает упреждение, парирование, подготовку и немедленные ответы; один эффект не порождает реакцию на другую реакцию без прямого разрешения. подготовка расходует заранее зарезервированные действия. | X56: разрешённая/запрещённая команда. | Y56: разрешённый ответ вне собственного хода. | AB56: 10 | AC56: §5.4.2.5, стр. 95. | AF56: Нет | AI56: =COUNTIF($B$2:$B$740,B56) -> 1
A57: 56 | B57: CORE-103 | C57: Активно | D57: Реализовать в игровом ядре | E57: Базовое правило | F57: Создание персонажа | G57: Персонажи | H57: 2. Персонаж, предметы и базовая механика | I57: Боевая ситуация, инициатива и действия | J57: Состояния без сознания, паралич, оглушение, пропуск | K57: бой / состояние. | L57: Игрок / персонаж | M57: поражённый персонаж | N57: доступные действия. | O57: наложение состояния. | P57: состояние активно. | Q57: тип и срок. | R57: без сознания — нет действий, реакций, активных защит, броня работает; парализован — нет физических действий/активных защит, ментальные возможны только без речи/движения/управления телом; оглушён — пропускает указанные собственные ходы и реакции, если эффект не разрешил защиты; «пропускает ход» — не получает боевых/небоевых, защиты вне хода только при прямом разрешении. | S57: фильтр допустимых команд и таймер. | T57: конкретный эффект может сохранить дееспособность. | U57: без сознания — нет действий, реакций, активных защит, броня работает; парализован — нет физических действий/активных защит, ментальные возможны только без речи/движения/управления телом; оглушён — пропускает указанные собственные ходы и реакции, если эффект не разрешил защиты; «пропускает ход» — не получает боевых/небоевых, защиты вне хода только при прямом разрешении. | Y57: тип и срок. без сознания — нет действий, реакций, активных защит, броня работает; парализован — нет физических действий/активных защит, ментальные возможны только без речи/движения/управления телом; оглушён — пропускает указанные собственные ходы и реакции, если эффект не разрешил защиты; «пропускает ход» — не получает боевых/небоевых, защиты вне хода только при прямом разрешении. | AB57: 10 | AC57: §5.4.2.5, стр. 95–96. | AF57: Нет | AI57: =COUNTIF($B$2:$B$740,B57) -> 1
A58: 57 | B58: CORE-104 | C58: Активно | D58: Реализовать в игровом ядре | E58: Базовое правило | F58: Создание персонажа | G58: Персонажи | H58: 2. Персонаж, предметы и базовая механика | I58: Боевая ситуация, инициатива и действия | J58: Отключённый симбионт | K58: симбионт / состояние. | L58: Игрок / персонаж | M58: симбионт и носитель. | O58: эффект отключения. | P58: симбионт активен до события. | Q58: длительность/условие восстановления. | R58: запретить активные способности, пассивные механические эффекты и получение XP; анатомические изменения сохраняются физически, но не дают бонусов. Для DIRECT_SYMBIONT и распределения неактивный/отключённый экземпляр обычно не является кандидатом. | S58: symbiont.disabled=true. | T58: условия включения задаёт источник. Локальные исключения: SYM-055 остаётся самостоятельным пассивным источником; Penguin под подавлением Trogr сохраняет прогрессию по SYM-075/SYM-130. | W58: symbiont.disabled=true. | AB58: 100 | AC58: §5.4.2.5, стр. 96. Прямое авторское решение Q-SYMBIONT-XP-001 — опыт симбионтов за natural 20/1, 2026-07-30 | AD58: Q-SYMBIONT-XP-001 | AE58: CORE-230 CORE-232 SYM-055 SYM-075 SYM-130 | AF58: Нет | AG58: Да | AH58: Патч v1.6 (опыт симбионтов) | AI58: =COUNTIF($B$2:$B$740,B58) -> 1
A59: 58 | B59: CORE-105 | C59: Активно | D59: Реализовать в игровом ядре | E59: Базовое правило | F59: Создание персонажа | G59: Персонажи | H59: 2. Персонаж, предметы и базовая механика | I59: Виды урона, раны и травмы | J59: Ударный физический урон | K59: урон / физический. | L59: Система / игровая сущность | M59: источник физической атаки | N59: цель. | O59: попадание оружием, рукой/ногой, обычной физической способностью или физическим объектом без иного типа. | P59: попадание и, для защищённой зоны, пробитие. | Q59: конечный урон, броня, зона. | R59: Нормативная база (действует во всей непротиворечащей части): неуказанный физический урон считать ударным; его блокирует любая физическая броня кроме Нэйта; после фактического урона запустить одну проверку травмы CORE-117. Приоритетные авторские дельты (заменяют только прямо пересекающиеся ветви): [Обязательная правка] Эта формулировка имеет приоритет над исходным текстом карточки. удалить создание/результат шрама; оставить ударный урон и травму | S59: уменьшение HP, возможная травма/шрам. | T59: прямой/чистый урон игнорирует броню и сам не травмирует; конкретный тип сильнее. Поздние дельты применяются по приоритету AQ3 > AQ2 > AQA/CQA > базовая карточка; локальное исключение сильнее общего. | U59: Нормативная база (действует во всей непротиворечащей части): | V59: уменьшение HP, возможная травма/шрам. | W59: [Обязательная правка] Эта формулировка имеет приоритет над исходным текстом карточки. | Y59: Нормативная база (действует во всей непротиворечащей части): | AB59: 10 | AC59: §5.4.3.1, стр. 96; уточнение §5.4.3.6, стр. 98. | AE59: CORE-117 | AF59: Нет | AI59: =COUNTIF($B$2:$B$740,B59) -> 1
A60: 59 | B60: CORE-107 | C60: Активно | D60: Реализовать в игровом ядре | E60: Базовое правило | F60: Создание персонажа | G60: Персонажи | H60: 2. Персонаж, предметы и базовая механика | I60: Виды урона, раны и травмы | J60: Физический урон борьбы | K60: урон / борьба. | L60: Система / игровая сущность | M60: борец | N60: цель приёма. | O60: успешная опция борьбы наносит урон. | P60: урон прямо указан опцией. | Q60: значение опции. | R60: уменьшить HP, полностью игнорируя броню; не запускать обычную проверку травмы, кроме опции, которая её прямо требует. | S60: потеря HP и, возможно, специальная травма. | T60: травмирующий приём CORE-142 прямо требует травму. | V60: уменьшить HP, полностью игнорируя броню; не запускать обычную проверку травмы, кроме опции, которая её прямо требует. потеря HP и, возможно, специальная травма. | AB60: 10 | AC60: §5.4.3.2, стр. 96. | AE60: CORE-142 | AF60: Нет | AI60: =COUNTIF($B$2:$B$740,B60) -> 1
A61: 60 | B61: CORE-108 | C61: Активно | D61: Реализовать в игровом ядре | E61: Базовое правило | F61: Создание персонажа | G61: Персонажи | H61: 2. Персонаж, предметы и базовая механика | I61: Виды урона, раны и травмы | J61: Прямой/чистый урон и отсутствие пробития | K61: урон / общая семантика. | L61: Система / игровая сущность | M61: источник | N61: цель. | O61: описание называет урон прямым/чистым или физическая атака не имеет Pr. | P61: попадание/условие эффекта выполнено. | Q61: damage, броня. | R61: прямой/чистый урон уменьшает HP, игнорирует броню и не травмирует без прямого указания; физическая атака без Pr получает Pr=0: ранит незащищённую зону, но не пробивает положительную броню; урон clamp ≥0 и не лечит. | S61: HP. | T61: дополнительный урон применяется лишь после попадания и пробития, если не сказано, что игнорирует броню. | V61: прямой/чистый урон уменьшает HP, игнорирует броню и не травмирует без прямого указания; физическая атака без Pr получает Pr=0: ранит незащищённую зону, но не пробивает положительную броню; урон clamp ≥0 и не лечит. | W61: прямой/чистый урон уменьшает HP, игнорирует броню и не травмирует без прямого указания; физическая атака без Pr получает Pr=0: ранит незащищённую зону, но не пробивает положительную броню; урон clamp ≥0 и не лечит. | AB61: 10 | AC61: уточнение §5.4.3.6, стр. 98. | AF61: Нет | AI61: =COUNTIF($B$2:$B$740,B61) -> 1
A62: 61 | B62: CORE-109 | C62: Активно | D62: Реализовать в игровом ядре | E62: Базовое правило | F62: Создание персонажа | G62: Персонажи | H62: 2. Персонаж, предметы и базовая механика | I62: Виды урона, раны и травмы | J62: Периодический и прямой яд | K62: урон / яд. | L62: Система / игровая сущность | M62: яд | N62: отравленная цель. | O62: контакт или периодический тик. | P62: эффект активен. | Q62: параметры источника. | R62: прямой яд наносится в момент контакта; периодический в бою — в конце хода цели; броню игнорирует, травму не запускает; параметры способности/болезни берутся из её описания; яд болезни действует, пока болезнь не вылечена. | S62: HP/эффект отравления. | T62: Нэйт может защищать от ядовитых испарений, но не определённо от уже попавшего яда. | V62: HP/эффект отравления. | Y62: прямой яд наносится в момент контакта; периодический в бою — в конце хода цели; броню игнорирует, травму не запускает; параметры способности/болезни берутся из её описания; яд болезни действует, пока болезнь не вылечена. | AB62: 10 | AC62: §5.4.3.3, стр. 96. | AF62: Нет | AI62: =COUNTIF($B$2:$B$740,B62) -> 1
A63: 62 | B63: CORE-113 | C63: Не автоматизируется | D63: Не реализовывать в Windows-приложении | E63: Базовое правило | F63: Создание персонажа | G63: Персонажи | H63: 2. Персонаж, предметы и базовая механика | I63: Виды урона, раны и травмы | J63: Сброс горящего элемента | K63: огонь / действие. | L63: Мастер / игрок / система | M63: горящий персонаж | N63: отдельный элемент экипировки. | O63: персонаж пытается сбросить до распространения. | P63: горит не вся экипировка; доступно действие. | Q63: R20+D+mods персонажа, R20+10 мастера. | R63: Нормативная база (действует во всей непротиворечащей части): за каждый элемент отдельное действие и встречная проверка; при строгом превышении мастера элемент сброшен. Приоритетные авторские дельты (заменяют только прямо пересекающиеся ветви): [Исключение из реализации] Карточка сохранена как tombstone и не исполняется приложением. покомпонентное горение/сброс предмета заменены Q-CORE-030 | S63: элемент больше не на носителе; его собственное горение может продолжаться. | T63: цена «действия» в бою принимается боевой по CORE-096. Поздние дельты применяются по приоритету AQ3 > AQ2 > AQA/CQA > базовая карточка; локальное исключение сильнее общего. | U63: горит не вся экипировка; доступно действие. Нормативная база (действует во всей непротиворечащей части): за каждый элемент отдельное действие и встречная проверка; при строгом превышении мастера элемент сброшен. цена «действия» в бою принимается боевой по CORE-096. | V63: цена «действия» в бою принимается боевой по CORE-096. | W63: R20+D+mods персонажа, R20+10 мастера. | Y63: Нормативная база (действует во всей непротиворечащей части): | AB63: 10 | AC63: §5.4.3.5, стр. 97. | AD63: Q-CORE-030 | AE63: CORE-096 | AF63: Нет | AI63: =COUNTIF($B$2:$B$740,B63) -> 1
A64: 63 | B64: CORE-116 | C64: Активно | D64: Реализовать в игровом ядре | E64: Базовое правило | F64: Создание персонажа | G64: Персонажи | H64: 2. Персонаж, предметы и базовая механика | I64: Виды урона, раны и травмы | J64: Ментальный урон и защита | K64: урон / псионика. | L64: Система / игровая сущность | M64: ментальный источник | N64: цель. | O64: порция ментального урона или встречная псионическая проверка. | P64: эффект действует на цель. | Q64: damage, защита Нэйт 20/Кастелькросс 5. | R64: игнорировать остальную броню; каждую порцию уменьшить на сумму применимой защиты (не ниже 0); травму не проверять; то же значение прибавить к встречной проверке против контроля, чтения мыслей, иллюзии и сходного эффекта. | S64: уменьшенный урон/бонус сопротивления. | T64: «не действует при любой защите» полностью запрещает только конкретную способность; конкретный иммунитет сильнее. | X64: «не действует при любой защите» полностью запрещает только конкретную способность; конкретный иммунитет сильнее. | AB64: 10 | AC64: §5.4.3.6, стр. 97–98. | AF64: Нет | AI64: =COUNTIF($B$2:$B$740,B64) -> 1
A65: 64 | B65: CORE-117 | C65: Активно | D65: Реализовать в игровом ядре | E65: Базовое правило | F65: Создание персонажа | G65: Персонажи | H65: 2. Персонаж, предметы и базовая механика | I65: Виды урона, раны и травмы | J65: Проверка получения травмы | K65: травма / триггер. | L65: Система / игровая сущность | M65: получившая травмирующий урон цель | N65: поражённая зона. | O65: фактически получен урон типа, способного травмировать. | P65: damage>0. | Q65: R20+Z+mods, фактический урон. | R65: Нормативная база (действует во всей непротиворечащей части): если проверка Z строго ниже урона, создать травму зоны и применить CORE-119–124; равенство травму не даёт. Приоритетные авторские дельты (заменяют только прямо пересекающиеся ветви): [Обязательная правка] Эта формулировка имеет приоритет над исходным текстом карточки. после исключения сложной анатомии ссылаться только на травмы классической анатомии; generic flee вынести отдельно [v1.3] Для EntityKind=CUSTOM_MONSTER targetZone всегда TORSO; травма маршрутизируется как травма корпуса без таблицы зон. Канонические зональные механики не меняются. [v1.4] Канонический монстр маршрутизирует зону по CORE-220: обычный statblock — CANONICAL_BODY; Трясинник по умолчанию BODY, BACK только явно; Вольмер по умолчанию OTHER_BODY, HEAD/OPEN_MOUTH только явно и при валидных условиях. Атака без зоны не уменьшает headHP. | S65: новая травма/эффект. | T65: дополнительный урон травмы не запускает новую травму/шрам/повтор. Поздние дельты применяются по приоритету AQ3 > AQ2 > AQA/CQA > базовая карточка; локальное исключение сильнее общего. | U65: Нормативная база (действует во всей непротиворечащей части): | W65: R20+Z+mods, фактический урон. [Обязательная правка] Эта формулировка имеет приоритет над исходным текстом карточки. | Y65: Нормативная база (действует во всей непротиворечащей части): | AB65: 80 | AC65: §5.4.4, стр. 98–99. Прямое уточнение пользователя 2026-07-28 — шаблоны врагов v1.3 Предразработочный QA и прямые ответы пользователя 2026-07-29 | AD65: Q-ENEMY-B12 Q-PREDEV-004 | AE65: CORE-119 CORE-211 CORE-220 | AF65: Да | AH65: Патч v1.4 | AI65: =COUNTIF($B$2:$B$740,B65) -> 1
A66: 65 | B66: CORE-118 | C66: Активно | D66: Реализовать в игровом ядре | E66: Базовое правило | F66: Создание персонажа | G66: Персонажи | H66: 2. Персонаж, предметы и базовая механика | I66: Виды урона, раны и травмы | J66: Зоны гуманоидов и четвероногих | K66: анатомия / зона. | L66: Игрок / персонаж | M66: гуманоид/персонаж/четвероногое | N66: зона попадания. | O66: случайная зона стрельбы или другого правила D6. | P66: оружие не задаёт иное. | Q66: чистый D6. | R66: Нормативная база (действует во всей непротиворечащей части): 1 корпус; 2 левая нога/задняя лапа; 3 правая; 4 левая рука/передняя лапа; 5 правая; 6 голова. Приоритетные авторские дельты (заменяют только прямо пересекающиеся ветви): [Обязательная правка] Эта формулировка имеет приоритет над исходным текстом карточки. удалить ссылку на исключённый CORE-122; оставить D6 гуманоида/четвероногого [v1.4] Канонический монстр маршрутизирует зону по CORE-220: обычный statblock — CANONICAL_BODY; Трясинник по умолчанию BODY, BACK только явно; Вольмер по умолчанию OTHER_BODY, HEAD/OPEN_MOUTH только явно и при валидных условиях. Атака без зоны не уменьшает headHP. | S66: targetZone. | T66: ближняя атака объявляет зону; таблица зон многоконечного существа — CORE-122. Поздние дельты применяются по приоритету AQ3 > AQ2 > AQA/CQA > базовая карточка; локальное исключение сильнее общего. | U66: Нормативная база (действует во всей непротиворечащей части): | W66: случайная зона стрельбы или другого правила D6. чистый D6. [Обязательная правка] Эта формулировка имеет приоритет над исходным текстом карточки. удалить ссылку на исключённый CORE-122; оставить D6 гуманоида/четвероногого | Y66: Нормативная база (действует во всей непротиворечащей части): | AB66: 80 | AC66: §5.4.4.1, стр. 98. Предразработочный QA и прямые ответы пользователя 2026-07-29 | AD66: Q-PREDEV-004 | AE66: CORE-122 CORE-220 | AF66: Да | AH66: Патч v1.4 | AI66: =COUNTIF($B$2:$B$740,B66) -> 1
A67: 66 | B67: CORE-121 | C67: Активно | D67: Реализовать в игровом ядре | E67: Базовое правило | F67: Создание персонажа | G67: Персонажи | H67: 2. Персонаж, предметы и базовая механика | I67: Виды урона, раны и травмы | J67: Травма корпуса гуманоида | K67: травма / корпус. | L67: Система / игровая сущность | M67: атакующий | N67: цель. | O67: CORE-117 по корпусу. | P67: исходная атака нанесла урон. | Q67: extra=max(0,round_math(R12−Z/3)). | R67: Нормативная база (действует во всей непротиворечащей части): один раз дополнительно уменьшить HP цели на extra; не запускать новую травму, шрам или повтор этого эффекта. Приоритетные авторские дельты (заменяют только прямо пересекающиеся ветви): [Обязательная правка] Эта формулировка имеет приоритет над исходным текстом карточки. удалить упоминание шрама из запрета рекурсивных триггеров | S67: дополнительная потеря HP. | T67: тяжёлое ранение/смерть после дополнительного урона проверяются обычно. Поздние дельты применяются по приоритету AQ3 > AQ2 > AQA/CQA > базовая карточка; локальное исключение сильнее общего. | U67: Нормативная база (действует во всей непротиворечащей части): | V67: один раз дополнительно уменьшить HP цели на extra; не запускать новую травму, шрам или повтор этого эффекта. дополнительная потеря HP. | W67: extra=max(0,round_math(R12−Z/3)). [Обязательная правка] Эта формулировка имеет приоритет над исходным текстом карточки. | Y67: Нормативная база (действует во всей непротиворечащей части): | AA67: один раз дополнительно уменьшить HP цели на extra; не запускать новую травму, шрам или повтор этого эффекта. | AB67: 10 | AC67: §5.4.4.1.3, стр. 98; уточнение стр. 99. | AE67: CORE-117 | AF67: Нет | AI67: =COUNTIF($B$2:$B$740,B67) -> 1
A68: 67 | B68: CORE-125 | C68: Активно | D68: Реализовать в игровом ядре | E68: Базовое правило | F68: Создание персонажа | G68: Персонажи | H68: 2. Персонаж, предметы и базовая механика | I68: Атаки, борьба, защита и броня | J68: Единый конвейер атаки | K68: бой / транзакция атаки. | L68: Система / игровая сущность | M68: атакующий | N68: цель. | O68: объявление атаки. | P68: команда допустима и ресурсы доступны. | Q68: цель, тип, предмет/способность, зона, цена, боеприпас/ОЭ. снимок активной версии профиля выбранного экземпляра и attackVariantId. DefenseChoice допускает NONE; armorLayerState=NO_LAYERS|PRESENT. Для этапов активации/меткости/защиты: rawFace, allowCritical, criticalPolarity, criticalGrade и снимки модификаторов. originRollId атакующего, rawFace, modifierStatCodes. | R68: Нормативная база (действует во всей непротиворечащей части): 1) объявить всё до бросков; 2) атомарно списать действие, ОЭ, боеприпас и расходники; 3) если нужна активация — проверить; 4) точность должна строго превысить одну выбранную защиту живой цели/сложность неживой; 5) при попадании Pr должен строго превысить броню; 6) определить урон, сопротивления, HP; 7) после фактического урона ровно один раз проверить травму, тяжёлое ранение и прочие последствия. Провал этапа прекращает следующие; ресурсы не возвращаются. Приоритетные авторские дельты (заменяют только прямо пересекающиеся ветви): [Обязательная правка] Эта формулировка имеет приоритет над исходным текстом карточки. убрать ветку сложности неживой цели; неживой объект недопустим как combat target До бросков зафиксировать активную версию профиля оружия. Требования, дальность, accuracyBonus, damageDefinition и penetrationDefinition читаются из этого снимка; мастерский patch экземпляра имеет приоритет над шаблонным значением. Результаты runtime-бросков сохраняются только в AttackResolution/боевом журнале. [v1.3] Источник снимка выбирается по категории: WEAPON_ATTACK фиксирует WeaponProfileVersion; MONSTER_ATTACK — MonsterAttackProfileVersion; SYMBIONT_ATTACK — правило способности. Результаты Runtime хранятся только в AttackResolution и журнале. [v1.4] Контроллер цели выбирает ровно одну доступную защиту. При отсутствии доступных защит применяется CORE-217. Этап пробития разрешается по CORE-226: NO_LAYERS пропускает любой Pr, включая 0; при PRESENT требуется строго Pr>totalArmor. [Боевой приоритет критов] На каждом допускающем критичность этапе проверки после броска, но до числового сравнения применить CORE-229. Его результат завершает только текущую проверку/этап. Даже автоматическое попадание не пропускает отдельные этапы пробития, брони, урона и последствий; уже списанные действия, ОЭ, боеприпасы и расходники не возвращаются. ATTACK/CHECK допускает прямой маршрут при значимой проверке и связанном активном симбионте; событие принадлежит бросившему персонажу и не зависит от победы. | S68: журнал этапов и конечное состояние. | T68: прямой урон/игнорирование брони и конкретные последствия провала. Поздние дельты применяются по приоритету AQ3 > AQ2 > AQA/CQA > базовая карточка; локальное исключение сильнее общего. CORE-229 не делает критическими runtime-броски урона, пробития и брони; частное прямое защитное исключение, включая SYM-066, сильнее. | U68: Нормативная база (действует во всей непротиворечащей части): 2) атомарно списать действие, ОЭ, боеприпас и расходники | V68: команда допустима и ресурсы доступны. цель, тип, предмет/способность, зона, цена, боеприпас/ОЭ. 2) атомарно списать действие, ОЭ, боеприпас и расходники 6) определить урон, сопротивления, HP Провал этапа прекращает следующие; ресурсы не возвращаются. | W68: [Обязательная правка] Эта формулировка имеет приоритет над исходным текстом карточки. | Y68: Нормативная база (действует во всей непротиворечащей части): | AA68: 2) атомарно списать действие, ОЭ, боеприпас и расходники 7) после фактического урона ровно один раз проверить травму, тяжёлое ранение и прочие последствия. журнал этапов и конечное состояние. AttackResolution хранит criticalResolution отдельно для каждого допускающего критичность этапа. Отдельные D20 попадания, урона и пробития получают разные originRollId и rollKind. | AB68: 100 | AC68: §5.4.5.5.3, уточнение стр. 102; §5.4.6–5.4.7, стр. 102–103. Прямое уточнение пользователя 2026-07-28 Прямое уточнение пользователя 2026-07-28 — шаблоны врагов v1.3 Предразработочный QA и прямые ответы пользователя 2026-07-29 Прямое уточнение пользователя 2026-07-29 — боевой приоритет критов Прямое авторское решение Q-SYMBIONT-XP-001 — опыт симбионтов за natural 20/1, 2026-07-30 | AD68: Q-ENEMY-B5 Q-ENEMY-B6 Q-PREDEV-002 Q-PREDEV-018 Q-COMBAT-CRIT-001 Q-SYMBIONT-XP-001 | AE68: CORE-188 CORE-189 CORE-190 CORE-206 CORE-207 CORE-208 CORE-210 CORE-217 CORE-226 CORE-229 CORE-074 SYM-066 CORE-230 | AF68: Да | AG68: Да | AH68: Патч v1.6 (опыт симбионтов) | AI68: =COUNTIF($B$2:$B$740,B68) -> 1
A69: 68 | B69: CORE-126 | C69: Активно | D69: Реализовать в игровом ядре | E69: Базовое правило | F69: Создание персонажа | G69: Персонажи | H69: 2. Персонаж, предметы и базовая механика | I69: Атаки, борьба, защита и броня | J69: Стрельба по живой цели | K69: атака / стрельба. | L69: Система / игровая сущность | M69: стрелок | N69: живая цель. | O69: расход действия и боеприпаса. | P69: оружие заряжено, цель допустима. | Q69: D6/D4 зоны, снимок активной версии профиля, accuracy=R20+D+навык+mods+accuracyBonus, защита, damageDefinition, penetrationDefinition, armor. | R69: сначала случайно определить зону по анатомии, если оружие не говорит иное; затем точность строго превышает выбранную защиту; затем разрешить penetrationDefinition и damageDefinition снимка активной версии профиля по CORE-189, сравнить пробитие с бронёй и применить урон. [v1.3] Если цель — CustomMonster, случайно определённая зона немедленно нормализуется в TORSO по CORE-211. Для канонического монстра действует его статблок. [v1.4] Канонический монстр маршрутизирует зону по CORE-220: обычный statblock — CANONICAL_BODY; Трясинник по умолчанию BODY, BACK только явно; Вольмер по умолчанию OTHER_BODY, HEAD/OPEN_MOUTH только явно и при валидных условиях. Атака без зоны не уменьшает headHP. | S69: попадание в заранее известную зону, HP/последствия. | T69: луки используют навык «Стрельба из лука» по каталогу; Кенси/Айнцберн имеют специальные навыки. | U69: расход действия и боеприпаса. | V69: попадание в заранее известную зону, HP/последствия. | W69: D6/D4 зоны, accuracy=R20+D+Стрельба+mods, защита, Pr, armor, damage. | AB69: 80 | AC69: §5.4.5.1, стр. 99; §5.4.4, стр. 98–99. Прямое уточнение пользователя 2026-07-28 Прямое уточнение пользователя 2026-07-28 — шаблоны врагов v1.3 Предразработочный QA и прямые ответы пользователя 2026-07-29 | AD69: Q-ENEMY-B12 Q-PREDEV-004 | AE69: CORE-188 CORE-189 CORE-190 CORE-211 CORE-220 | AF69: Да | AH69: Патч v1.4 | AI69: =COUNTIF($B$2:$B$740,B69) -> 1
A70: 69 | B70: CORE-130 | C70: Активно | D70: Реализовать в игровом ядре | E70: Базовое правило | F70: Создание персонажа | G70: Персонажи | H70: 2. Персонаж, предметы и базовая механика | I70: Атаки, борьба, защита и броня | J70: Бросание предмета: допустимость и дальность | K70: атака / бросание. | L70: Система / игровая сущность | M70: бросающий | N70: предмет. | O70: заявление броска. | P70: масса Mkg≤2×S. | Q70: Mkg, S, бонус «Бросания» L, R12. | R70: range=max(0,R12+L+S−Mkg+penalties); без навыка «Бросание» результаты всех проверок в рамках бросания −2. | S70: дальность полёта. | T70: предметы <0.3 кг не наносят урон, но могут попасть. | W70: масса Mkg≤2×S. Mkg, S, бонус «Бросания» L, R12. range=max(0,R12+L+S−Mkg+penalties); без навыка «Бросание» результаты всех проверок в рамках бросания −2. | AB70: 10 | AC70: §5.4.5.3, стр. 100–102. | AF70: Нет | AI70: =COUNTIF($B$2:$B$740,B70) -> 1
A71: 70 | B71: CORE-131 | C71: Активно | D71: Реализовать в игровом ядре | E71: Базовое правило | F71: Создание персонажа | G71: Персонажи | H71: 2. Персонаж, предметы и базовая механика | I71: Атаки, борьба, защита и броня | J71: Бросание предмета: точность и урон | K71: атака / бросание. | L71: Система / игровая сущность | M71: бросающий | N71: живая или неживая цель. | O71: предмет долетает. | P71: CORE-130. | Q71: зона D6/D4, accuracy=R20+L+(S+D)/2−Mkg, защита/сложность. | R71: Нормативная база (действует во всей непротиворечащей части): определить случайную зону живой цели; попасть при строгом превышении; при живой цели считать предмет грубым оружием: Pr=R12, damage=S+Mkg, если масса ≥0.3 кг; без навыка применить −2 ко всем проверкам (не к броску урона, который проверкой не является). Приоритетные авторские дельты (заменяют только прямо пересекающиеся ветви): [Обязательная правка] Эта формулировка имеет приоритет над исходным текстом карточки. убрать неживую цель; сохранить бросок в живую цель и жизненный цикл объекта карты [v1.3] Для цели-CustomMonster любая заявленная зона атаки считается TORSO; отдельные конечности недоступны. Канонические уязвимые зоны сохраняются. [v1.4] Канонический монстр маршрутизирует зону по CORE-220: обычный statblock — CANONICAL_BODY; Трясинник по умолчанию BODY, BACK только явно; Вольмер по умолчанию OTHER_BODY, HEAD/OPEN_MOUTH только явно и при валидных условиях. Атака без зоны не уменьшает headHP. | S71: урон/положение предмета. | T71: дробный урон/масса округляются только в конце по CORE-076. Поздние дельты применяются по приоритету AQ3 > AQ2 > AQA/CQA > базовая карточка; локальное исключение сильнее общего. | U71: Нормативная база (действует во всей непротиворечащей части): | W71: зона D6/D4, accuracy=R20+L+(S+D)/2−Mkg, защита/сложность. определить случайную зону живой цели; попасть при строгом превышении; при живой цели считать предмет грубым оружием: Pr=R12, damage=S+Mkg, если масса ≥0.3 кг; без навыка применить −2 ко всем проверкам (не к броску урона, который проверкой не является). [Обязательная правка] Эта формулировка имеет приоритет над исходным текстом карточки. | Y71: Нормативная база (действует во всей непротиворечащей части): | AB71: 80 | AC71: §5.4.5.3, стр. 100. Прямое уточнение пользователя 2026-07-28 — шаблоны врагов v1.3 Предразработочный QA и прямые ответы пользователя 2026-07-29 | AD71: Q-ENEMY-B12 Q-PREDEV-004 | AE71: CORE-076 CORE-130 CORE-211 CORE-220 | AF71: Да | AH71: Патч v1.4 | AI71: =COUNTIF($B$2:$B$740,B71) -> 1
A72: 71 | B72: CORE-132 | C72: Активно | D72: Реализовать в игровом ядре | E72: Базовое правило | F72: Создание персонажа | G72: Персонажи | H72: 2. Персонаж, предметы и базовая механика | I72: Атаки, борьба, защита и броня | J72: Обычный плевок | K72: бросание / без урона. | L72: Система / игровая сущность | M72: плюющий | N72: цель. | O72: плевок без способности. | P72: масса слюны=0. | Q72: обычная формула бросания. | R72: рассчитать дальность с M=0 и затем разделить итог на 2; точность по бросанию; урон=0. | S72: факт попадания. | T72: активная способность использует своё описание. | W72: масса слюны=0. обычная формула бросания. рассчитать дальность с M=0 и затем разделить итог на 2; точность по бросанию; урон=0. | AB72: 10 | AC72: §5.4.5.3, стр. 100, уточнение стр. 102. | AF72: Нет | AI72: =COUNTIF($B$2:$B$740,B72) -> 1
A73: 72 | B73: CORE-134 | C73: Активно | D73: Реализовать в игровом ядре | E73: Базовое правило | F73: Создание персонажа | G73: Персонажи | H73: 2. Персонаж, предметы и базовая механика | I73: Атаки, борьба, защита и броня | J73: Дальняя атака активной способностью симбионта | K73: атака / симбионт. | L73: Система / игровая сущность | M73: симбионт-источник | N73: цель. | O73: активная дальняя способность. | P73: способность не задаёт иной порядок, активна и оплачена. | Q73: R20, бонус «Стрельбы» (0 если нет), уровень симбионта, max(D,I,W), описание способности. | R73: разрешить по стрельбе; accuracy=R20+ShootingBonus+symbiontLevel+max(D,I,W)+mods; отсутствие «Стрельбы» не даёт штрафа; зона/защита/Pr/damage по общей процедуре и способности. [v1.3] Запрет дальности относится только к базовой MONSTER_ATTACK. Дальняя атака симбионта разрешается по её карточке; ShootingBonus CustomMonster равен 0. | S73: атака/эффект. | T73: описание способности имеет приоритет. | W73: R20, бонус «Стрельбы» (0 если нет), уровень симбионта, max(D,I,W), описание способности. разрешить по стрельбе; accuracy=R20+ShootingBonus+symbiontLevel+max(D,I,W)+mods; отсутствие «Стрельбы» не даёт штрафа; зона/защита/Pr/damage по общей процедуре и способности. | AB73: 70 | AC73: §5.4.5.4, стр. 101. Прямое уточнение пользователя 2026-07-28 — шаблоны врагов v1.3 | AD73: Q-ENEMY-B8 | AE73: CORE-209 | AF73: Да | AH73: Патч v1.3 | AI73: =COUNTIF($B$2:$B$740,B73) -> 1
A74: 73 | B74: CORE-135 | C74: Активно | D74: Реализовать в игровом ядре | E74: Базовое правило | F74: Создание персонажа | G74: Персонажи | H74: 2. Персонаж, предметы и базовая механика | I74: Атаки, борьба, защита и броня | J74: Ближняя атака оружием | K74: атака / ближний бой. | L74: Система / игровая сущность | M74: атакующий | N74: цель. | O74: расход действия. | P74: цель на ближней дистанции; оружие в руках. | Q74: объявленная зона, снимок активной версии профиля, R20+D+weaponSkill+classMods+accuracyBonus, защита, penetrationDefinition, броня, damageDefinition. | R74: объявить зону; точность строго превышает защиту; затем penetrationDefinition/damageDefinition снимка активной версии профиля по CORE-189 и броня; уменьшить HP/последствия. [v1.3] Если цель — CustomMonster, объявленная зона нормализуется в TORSO. Для канонического монстра действует собственная анатомия статблока. Эта оружейная формула не используется атакующим CustomMonster для MONSTER_ATTACK. [v1.4] Канонический монстр маршрутизирует зону по CORE-220: обычный statblock — CANONICAL_BODY; Трясинник по умолчанию BODY, BACK только явно; Вольмер по умолчанию OTHER_BODY, HEAD/OPEN_MOUTH только явно и при валидных условиях. Атака без зоны не уменьшает headHP. | S74: атака по выбранной зоне. | T74: текст «спасбросок цели» трактуется как выбранная защита по общему порядку. | U74: расход действия. | V74: объявить зону; точность строго превышает защиту; затем каталог Pr/damage и броня; уменьшить HP/последствия. | W74: объявленная зона, R20+D+weaponSkill+classMods, защита, Pr, броня, урон. | AB74: 80 | AC74: §5.4.5.5.1, стр. 101. Прямое уточнение пользователя 2026-07-28 Прямое уточнение пользователя 2026-07-28 — шаблоны врагов v1.3 Предразработочный QA и прямые ответы пользователя 2026-07-29 | AD74: Q-ENEMY-B6 Q-ENEMY-B12 Q-PREDEV-004 | AE74: CORE-188 CORE-189 CORE-190 CORE-208 CORE-211 CORE-220 | AF74: Да | AH74: Патч v1.4 | AI74: =COUNTIF($B$2:$B$740,B74) -> 1
A75: 74 | B75: CORE-136 | C75: Активно | D75: Реализовать в игровом ядре | E75: Базовое правило | F75: Создание персонажа | G75: Персонажи | H75: 2. Персонаж, предметы и базовая механика | I75: Атаки, борьба, защита и броня | J75: Удары кулаками и ногами | K75: атака / рукопашный бой. | L75: Система / игровая сущность | M75: атакующий | N75: цель. | O75: рукопашная атака. | P75: действующая конечность. | Q75: точность R20+D+Рукопашный бой+Солдат+mods; damage; зона. | R75: кулак: базовый R6, Pr=0; нога: базовый R12, Pr=0; S к урону, D к точности, «Рукопашный бой» указан как общий модификатор удара, «Солдат» даёт +3 к точности; без обоих навыков −5 к ударам; с высоким+ рукопашным боем одна атака за действие включает два отдельно разрешаемых удара кулаками. [v1.3] Базовая MONSTER_ATTACK не является безоружным ударом или «Рукопашным боем»; навыковые бонусы и штраф −5 не применяются. | S75: один/два удара. | T75: формулировка даёт два кулака за каждое действие по CORE-017; кастет имеет разовый лимит. | U75: S к урону, D к точности, «Рукопашный бой» указан как общий модификатор удара, «Солдат» даёт +3 к точности; без обоих навыков −5 к ударам; с высоким+ рукопашным боем одна атака за действие включает два отдельно разрешаемых удара кулаками. формулировка даёт два кулака за каждое действие по CORE-017; кастет имеет разовый лимит. | W75: точность R20+D+Рукопашный бой+Солдат+mods; damage; зона. кулак: базовый R6, Pr=0; нога: базовый R12, Pr=0 формулировка даёт два кулака за каждое действие по CORE-017; кастет имеет разовый лимит. | AB75: 70 | AC75: §5.4.5.5.2, стр. 101. Прямое уточнение пользователя 2026-07-28 — шаблоны врагов v1.3 | AD75: Q-ENEMY-B6 | AE75: CORE-017 CORE-207 CORE-208 | AF75: Да | AH75: Патч v1.3 | AI75: =COUNTIF($B$2:$B$740,B75) -> 1
A76: 75 | B76: CORE-141 | C76: Активно | D76: Реализовать в игровом ядре | E76: Базовое правило | F76: Создание персонажа | G76: Персонажи | H76: 2. Персонаж, предметы и базовая механика | I76: Атаки, борьба, защита и броня | J76: Удержание конечности | K76: борьба / состояние. | L76: Система / игровая сущность | M76: борец | N76: конечность захваченной цели. | O76: успешная опция. | P76: цель захвачена. | Q76: limbId, встречная борьба. | R76: установить удержание выбранной конечности; разрешить последующий травмирующий/болевой приём; освобождение =1 действие и встречная борьба, равенство сохраняет. | S76: link на конечность. | T76: самостоятельные штрафы удержания не заданы. | U76: установить удержание выбранной конечности; разрешить последующий травмирующий/болевой приём; освобождение =1 действие и встречная борьба, равенство сохраняет. | W76: установить удержание выбранной конечности; разрешить последующий травмирующий/болевой приём; освобождение =1 действие и встречная борьба, равенство сохраняет. | AB76: 10 | AC76: §5.4.5.5.3(4), стр. 102. | AF76: Нет | AI76: =COUNTIF($B$2:$B$740,B76) -> 1
A77: 76 | B77: CORE-142 | C77: Активно | D77: Реализовать в игровом ядре | E77: Базовое правило | F77: Создание персонажа | G77: Персонажи | H77: 2. Персонаж, предметы и базовая механика | I77: Атаки, борьба, защита и броня | J77: Травмирующий приём | K77: борьба / урон и травма. | L77: Система / игровая сущность | M77: борец | N77: удерживаемая конечность. | O77: успешная проверка опции. | P77: удержание конечности. | Q77: цель/конечность. | R77: нанести 10 урона борьбы, игнорируя броню; затем принудительно выполнить проверку травмы именно этой конечности. | S77: HP и возможная травма. | T77: эта травма — прямое исключение CORE-107. | V77: HP и возможная травма. | AB77: 10 | AC77: §5.4.5.5.3(5), стр. 102. | AE77: CORE-107 | AF77: Нет | AI77: =COUNTIF($B$2:$B$740,B77) -> 1
A78: 77 | B78: CORE-145 | C78: Активно | D78: Реализовать в игровом ядре | E78: Базовое правило | F78: Создание персонажа | G78: Персонажи | H78: 2. Персонаж, предметы и базовая механика | I78: Атаки, борьба, защита и броня | J78: Защита от стрельбы и дальних способностей | K78: защита / дальняя. | L78: Система / игровая сущность | M78: цель | N78: конкретная атака. | O78: по цели идёт стрельба/дальняя способность. | P78: цель способна на активную защиту. | Q78: уклонение или блок. rawFace защиты, ordinaryDefenseTotal, criticalPolarity, criticalGrade и снимок модификаторов. originRollId, rawFace, rollKind. | R78: уклонение: нужен I≥6, R20+D+Молниеносная реакция−10+mods, безлимитно за круг. Блок при щите: R20+(S+D)/2+Владение щитом+Солдат+щитБонус−8+mods, безлимитно; успех при defense≥accuracy. [Боевой override] До сравнения defenseTotal с accuracy передать обе проверки CORE-229. Подтверждённый критический успех защиты автоматически выигрывает текущий этап, если ему не противостоит положительный крит атаки; подтверждённый критический провал защиты автоматически проваливает защиту. Равные положительные градации разрешаются без нового броска с rawFace=20 и теми же снимками модификаторов; равенство обычных итогов остаётся в пользу защиты. Количественный D20 этого правила классифицировать NO_DIRECT_BUT_POOL; rawFace 1/20 даёт 1 балл счётчика без цепочки критичности. | S78: промах либо CORE-018. criticalResolution выбранной защиты и исход текущего этапа атаки. | T78: одна защита на атаку. Не путать количественный бросок с отдельной значимой проверкой действия. | U78: уклонение: нужен I≥6, R20+D+Молниеносная реакция−10+mods, безлимитно за круг. | W78: уклонение: нужен I≥6, R20+D+Молниеносная реакция−10+mods, безлимитно за круг. Блок при щите: R20+(S+D)/2+Владение щитом+Солдат+щитБонус−8+mods, безлимитно; успех при defense≥accuracy. | Y78: уклонение: нужен I≥6, R20+D+Молниеносная реакция−10+mods, безлимитно за круг. | AB78: 100 | AC78: §5.4.6.1, стр. 103. Прямое уточнение пользователя 2026-07-29 — боевой приоритет критов Прямое авторское решение Q-SYMBIONT-XP-001 — опыт симбионтов за natural 20/1, 2026-07-30 | AD78: Q-COMBAT-CRIT-001 Q-SYMBIONT-XP-001 | AE78: CORE-018 CORE-229 CORE-075 CORE-125 CORE-230 | AF78: Да | AG78: Да | AH78: Патч v1.6 (опыт симбионтов) | AI78: =COUNTIF($B$2:$B$740,B78) -> 1
A79: 78 | B79: CORE-146 | C79: Активно | D79: Реализовать в игровом ядре | E79: Базовое правило | F79: Создание персонажа | G79: Персонажи | H79: 2. Персонаж, предметы и базовая механика | I79: Атаки, борьба, защита и броня | J79: Уклонение и блок в ближнем бою | K79: защита / ближняя. | L79: Система / игровая сущность | M79: цель | N79: ближняя атака. | O79: атака. | P79: активная защита разрешена. | Q79: вид защиты. rawFace защиты, ordinaryDefenseTotal, criticalPolarity, criticalGrade и снимок модификаторов. originRollId, rawFace, rollKind. | R79: уклонение: I≥3, R20+D+Молниеносная реакция−4+mods, безлимитно. Блок: R20+(S+D)/2+appropriateSkill+mods−3; без щита skill=Рукопашный бой, при успехе сначала обычное пробитие носимой брони, а если пробита — конечный урон /2 с округлением; со щитом skill=Владение щитом плюс Солдат, урон получает щит; безлимитно. [Боевой override] До сравнения defenseTotal с accuracy передать обе проверки CORE-229. Подтверждённый критический успех защиты автоматически выигрывает текущий этап, если ему не противостоит положительный крит атаки; подтверждённый критический провал защиты автоматически проваливает защиту. Равные положительные градации разрешаются без нового броска с rawFace=20 и теми же снимками модификаторов; равенство обычных итогов остаётся в пользу защиты. Количественный D20 этого правила классифицировать NO_DIRECT_BUT_POOL; rawFace 1/20 даёт 1 балл счётчика без цепочки критичности. | S79: промах/половина урона/износ щита. criticalResolution выбранной защиты и исход текущего этапа атаки. | T79: окружение CORE-091. Не путать количественный бросок с отдельной значимой проверкой действия. | U79: уклонение: I≥3, R20+D+Молниеносная реакция−4+mods, безлимитно. | W79: уклонение: I≥3, R20+D+Молниеносная реакция−4+mods, безлимитно. Блок: R20+(S+D)/2+appropriateSkill+mods−3; без щита skill=Рукопашный бой, при успехе сначала обычное пробитие носимой брони, а если пробита — конечный урон /2 с округлением; со щитом skill=Владение щитом плюс Солдат, урон получает щит; безлимитно. | AB79: 100 | AC79: §5.4.6.2, стр. 103. Прямое уточнение пользователя 2026-07-29 — боевой приоритет критов Прямое авторское решение Q-SYMBIONT-XP-001 — опыт симбионтов за natural 20/1, 2026-07-30 | AD79: Q-COMBAT-CRIT-001 Q-SYMBIONT-XP-001 | AE79: CORE-091 CORE-229 CORE-075 CORE-125 CORE-230 | AF79: Да | AG79: Да | AH79: Патч v1.6 (опыт симбионтов) | AI79: =COUNTIF($B$2:$B$740,B79) -> 1
A80: 79 | B80: CORE-149 | C80: Активно | D80: Реализовать в игровом ядре | E80: Базовое правило | F80: Создание персонажа | G80: Персонажи | H80: 2. Персонаж, предметы и базовая механика | I80: Атаки, борьба, защита и броня | J80: Защита от метания и бросания | K80: защита / метательное. | L80: Система / игровая сущность | M80: цель | N80: метание или бросание. | O80: соответствующая атака. | P80: активная защита возможна. | Q80: уклонение/блок. rawFace защиты, ordinaryDefenseTotal, criticalPolarity, criticalGrade и снимок модификаторов. originRollId, rawFace, rollKind. | R80: уклонение I≥4, R20+D+Молниеносная реакция−4+mods, безлимитно; блок R20+(S+D)/2+appropriateSkill−3+mods, безлимитно; без щита при успехе обычная броня, затем половина прошедшего урона; со щитом урон щиту. [Боевой override] До сравнения defenseTotal с accuracy передать обе проверки CORE-229. Подтверждённый критический успех защиты автоматически выигрывает текущий этап, если ему не противостоит положительный крит атаки; подтверждённый критический провал защиты автоматически проваливает защиту. Равные положительные градации разрешаются без нового броска с rawFace=20 и теми же снимками модификаторов; равенство обычных итогов остаётся в пользу защиты. Количественный D20 этого правила классифицировать NO_DIRECT_BUT_POOL; rawFace 1/20 даёт 1 балл счётчика без цепочки критичности. | S80: защита. criticalResolution выбранной защиты и исход текущего этапа атаки. | T80: одна защита на атаку. Не путать количественный бросок с отдельной значимой проверкой действия. | U80: уклонение I≥4, R20+D+Молниеносная реакция−4+mods, безлимитно; блок R20+(S+D)/2+appropriateSkill−3+mods, безлимитно; без щита при успехе обычная броня, затем половина прошедшего урона; со щитом урон щиту. | W80: уклонение I≥4, R20+D+Молниеносная реакция−4+mods, безлимитно; блок R20+(S+D)/2+appropriateSkill−3+mods, безлимитно; без щита при успехе обычная броня, затем половина прошедшего урона; со щитом урон щиту. | AB80: 100 | AC80: §5.4.6.3, стр. 103. Прямое уточнение пользователя 2026-07-29 — боевой приоритет критов Прямое авторское решение Q-SYMBIONT-XP-001 — опыт симбионтов за natural 20/1, 2026-07-30 | AD80: Q-COMBAT-CRIT-001 Q-SYMBIONT-XP-001 | AE80: CORE-229 CORE-075 CORE-125 CORE-230 | AF80: Да | AG80: Да | AH80: Патч v1.6 (опыт симбионтов) | AI80: =COUNTIF($B$2:$B$740,B80) -> 1
A81: 80 | B81: CORE-150 | C81: Активно | D81: Реализовать в игровом ядре | E81: Базовое правило | F81: Создание персонажа | G81: Персонажи | H81: 2. Персонаж, предметы и базовая механика | I81: Атаки, борьба, защита и броня | J81: Суммарная броня и пробитие | K81: броня / разрешение попадания. | L81: Система / игровая сущность | M81: атака | N81: все слои поражённой зоны. | O81: попадание, требующее пробития. | P81: зона определена. | Q81: все независимые дайсы и константы слоёв; penetrationDefinition снимка активной версии профиля оружия; остальные компоненты Pr. originRollId, rawFace, rollKind=PENETRATION|ARMOR. | R81: один раз бросить каждый дайс каждого слоя, сложить с константами; один раз собрать Pr; урон проходит только если Pr>armor; равенство останавливает; обычное попадание не повреждает броню без свойства целостности. Базовое пробитие оружия разрешается по penetrationDefinition активного снимка CORE-189; результат не записывается обратно в оружие. [v1.3] Для MONSTER_ATTACK пробитие читается из MonsterAttackProfileVersion. naturalArmorDefinition цели образует отдельный равномерный внутренний слой и разрешается заново для каждой входящей проверки пробития; предметных слоёв у CustomMonster нет. [v1.4] armorLayers=[] означает NO_LAYERS, а не числовой слой 0: этап пробития автоматически успешен при любом Pr, включая 0. Если присутствует хотя бы один слой, требуется строго Pr>Σarmor; равенство останавливает. PENETRATION и ARMOR относятся к NO_DIRECT_BUT_POOL. Событие принадлежит игроку, который бросил данный D20; rawFace 1/20 даёт 1 балл. | S81: пробито/остановлено. | T81: грубое оружие наносит половину даже без пробития; прямой урон игнорирует. Не запускать CORE-083/084 и не выдавать прямой XP. | AA81: один раз бросить каждый дайс каждого слоя, сложить с константами; один раз собрать Pr; урон проходит только если Pr>armor; равенство останавливает; обычное попадание не повреждает броню без свойства целостности. | AB81: 100 | AC81: §5.4.7, стр. 103. Прямое уточнение пользователя 2026-07-28 Прямое уточнение пользователя 2026-07-28 — шаблоны врагов v1.3 Предразработочный QA и прямые ответы пользователя 2026-07-29 Прямое авторское решение Q-SYMBIONT-XP-001 — опыт симбионтов за natural 20/1, 2026-07-30 | AD81: Q-ENEMY-B5 Q-ENEMY-P14 Q-PREDEV-018 Q-SYMBIONT-XP-001 | AE81: CORE-188 CORE-189 CORE-190 CORE-206 CORE-208 CORE-210 CORE-226 CORE-230 | AF81: Да | AG81: Да | AH81: Патч v1.6 (опыт симбионтов) | AI81: =COUNTIF($B$2:$B$740,B81) -> 1
A82: 81 | B82: CORE-155 | C82: Активно | D82: Реализовать в игровом ядре | E82: Базовое правило | F82: Создание персонажа | G82: Персонажи | H82: 2. Персонаж, предметы и базовая механика | I82: Тяжёлое ранение и смерть | J82: Добивание тяжело раненного | K82: смерть / урон. | L82: Система / игровая сущность | M82: любой источник | N82: тяжело раненный. | O82: после защит/сопротивлений теряется хотя бы 1 HP. | P82: severelyWounded=true. | Q82: фактическая новая потеря HP. | R82: немедленно установить окончательную смерть; если порция после защит =0, не убивает. | S82: dead=true. | T82: дееспособность/дубль не предотвращают. | V82: после защит/сопротивлений теряется хотя бы 1 HP. фактическая новая потеря HP. | W82: severelyWounded=true. немедленно установить окончательную смерть; если порция после защит =0, не убивает. dead=true. | AB82: 10 | AC82: §5.5, стр. 104. | AF82: Нет | AI82: =COUNTIF($B$2:$B$740,B82) -> 1
A83: 82 | B83: CORE-156 | C83: Активно | D83: Реализовать в игровом ядре | E83: Базовое правило | F83: Создание персонажа | G83: Персонажи | H83: 2. Персонаж, предметы и базовая механика | I83: Тяжёлое ранение и смерть | J83: Реанимация | K83: смерть / восстановление. | L83: Система / игровая сущность | M83: предмет/способность | N83: тяжело раненный. | O83: эффект прямо выводит из тяжёлого ранения. | P83: окончательная смерть ещё не наступила. | Q83: установленное эффектом HP. | R83: остановить таймер; снять тяжёлое ранение; HP установить указанным значением, иначе 1. Обычное лечение HP без прямого указания не действует. | S83: жив, не тяжело ранен. | T83: отвар CORE-060. | V83: установленное эффектом HP. HP установить указанным значением, иначе 1. Обычное лечение HP без прямого указания не действует. | AB83: 10 | AC83: §5.5, стр. 104. | AE83: CORE-060 | AF83: Нет | AI83: =COUNTIF($B$2:$B$740,B83) -> 1
A84: 83 | B84: CORE-157 | C84: Активно | D84: Реализовать в игровом ядре | E84: Базовое правило | F84: Создание персонажа | G84: Персонажи | H84: 2. Персонаж, предметы и базовая механика | I84: Тяжёлое ранение и смерть | J84: Приоритет толкования | K84: метаправило / конфликт. | L84: Мастер / система | M84: движок/мастер | N84: конфликтующие правила. | O84: правила расходятся. | P84: конфликт невозможно снять обычной композицией. | Q84: специфичность/ограничительность правил. | R84: конкретное исключение расы/предмета/существа/способности сильнее общего; пассив действует пока источник активен, активный — по заявлению и с ценой; отсутствующее преимущество не подразумевается; при равной конкретности выбрать более узкое/ограничительное; мастер решает до броска одинаково для всех. | S84: выбранная трактовка. | T84: временное правило последней ясности CORE-158. | X84: конфликт невозможно снять обычной композицией. | Z84: конкретное исключение расы/предмета/существа/способности сильнее общего; пассив действует пока источник активен, активный — по заявлению и с ценой; отсутствующее преимущество не подразумевается; при равной конкретности выбрать более узкое/ограничительное; мастер решает до броска одинаково для всех. | AB84: 10 | AC84: §5.5, стр. 104. | AE84: CORE-158 | AF84: Нет | AI84: =COUNTIF($B$2:$B$740,B84) -> 1
A85: 84 | B85: CORE-158 | C85: Активно | D85: Реализовать в игровом ядре | E85: Базовое правило | F85: Создание персонажа | G85: Персонажи | H85: 2. Персонаж, предметы и базовая механика | I85: Тяжёлое ранение и смерть | J85: Правило последней ясности | K85: метаправило / мастерское решение. | L85: Мастер / система | M85: мастер | N85: отсутствующее правило. | O85: ответ всё ещё отсутствует. | P85: до броска. | Q85: одно предложение временного правила. | R85: правило обязано сохранять потраченные ресурсы, не давать дополнительных действий/целей и одинаково действовать на PC/NPC; после сцены записать и применять до новой редакции. | S85: versioned houseRule. | T85: не автоматизируется без мастерского ввода. | U85: правило обязано сохранять потраченные ресурсы, не давать дополнительных действий/целей и одинаково действовать на PC/NPC; после сцены записать и применять до новой редакции. | V85: правило обязано сохранять потраченные ресурсы, не давать дополнительных действий/целей и одинаково действовать на PC/NPC; после сцены записать и применять до новой редакции. | AB85: 10 | AC85: §5.5, стр. 104. | AF85: Нет | AI85: =COUNTIF($B$2:$B$740,B85) -> 1
A86: 85 | B86: CORE-164 | C86: Активно | D86: Реализовать в игровом ядре | E86: Базовое правило | F86: Создание персонажа | G86: Персонажи | H86: 2. Персонаж, предметы и базовая механика | I86: Создание персонажа | J86: Проверка допустимости характеристик после поправок | K86: создание / валидация. | L86: Игрок / персонаж | M86: создаваемый персонаж | N86: все 7 характеристик. | O86: применение всех расовых/классовых/симбиотических поправок. | P86: базовый набор выбран. | Q86: итоговые постоянные значения, способ выбора симбионтов. | R86: персонаж валиден, только если каждая ≥1; единственное исключение: при случайном выборе симбионта отрицательная поправка симбионта не опускает характеристику ниже 1 (clamp 1). Расовые поправки такого исключения не получают. [v1.3] Для двух пользовательских типов лимит 1–35 проверяет только семь введённых базовых значений до постоянных модификаторов. Итог может превышать 35; действующий постоянный минимум 1 сохраняется. | S86: валидный персонаж либо блок сохранения. | T86: постоянный минимум 1. | AB86: 70 | AC86: §6.1, стр. 105; §5.1, стр. 86. Прямое уточнение пользователя 2026-07-28 — шаблоны врагов v1.3 | AD86: Q-ENEMY-B1 | AE86: CORE-197 CORE-200 | AF86: Да | AH86: Патч v1.3 | AI86: =COUNTIF($B$2:$B$740,B86) -> 1
A87: 86 | B87: CORE-165 | C87: Активно | D87: Реализовать в игровом ядре | E87: Базовое правило | F87: Создание персонажа | G87: Персонажи | H87: 2. Персонаж, предметы и базовая механика | I87: Создание персонажа | J87: Выбор и стоимость уровней навыка | K87: создание/развитие / навык. | L87: Игрок / персонаж | M87: персонаж | N87: навык. | O87: изучение/повышение. | P87: выполнены все требования каталога, хватает слотов соответствующего пула. | Q87: уровень/число плюсов. | R87: Базовый +1 занимает 1 слот; Средний +2 — 2; Высокий +3 — 3; Совершенный +4 — 4; Абсолютный +5 — 5. После абсолютного каждый + добавляет ещё +1 к бонусу и стоит 2 дополнительных слота: slotCost=5+2×plusCount, bonus=5+plusCount. | S87: навык, бонус, занятые слоты. | T87: верхний предел плюсов не задан. | W87: После абсолютного каждый + добавляет ещё +1 к бонусу и стоит 2 дополнительных слота: slotCost=5+2×plusCount, bonus=5+plusCount. | AB87: 10 | AC87: §6.2, стр. 105–106. | AF87: Нет | AI87: =COUNTIF($B$2:$B$740,B87) -> 1
A88: 87 | B88: CORE-167 | C88: Активно | D88: Реализовать в игровом ядре | E88: Базовое правило | F88: Создание персонажа | G88: Персонажи | H88: 2. Персонаж, предметы и базовая механика | I88: Создание персонажа | J88: Каталог навыков, доступных при создании | K88: создание / каталог навыков. | L88: Игрок / персонаж | M88: персонаж | N88: выбранный навык. | O88: просмотр, изучение, применение. | P88: требования строки; стоимость CORE-165. | Q88: характеристики и контекст действия. | R88: Нормативная база (действует во всей непротиворечащей части): валидировать требования; добавлять итоговый бонус навыка к перечисленным действиям; применять штраф без навыка только где указан. Приоритетные авторские дельты (заменяют только прямо пересекающиеся ветви): [Обязательная правка] Эта формулировка имеет приоритет над исходным текстом карточки. Навык «Крафт» можно выбрать и хранить как характеристику листа, но его действие создания предметов приложением не исполняется по Q-CORE-059. | S88: структурированная запись навыка. Каталог: • Навык — Требования (все одновременно) — Механически значимый охват / штраф без навыка • Рукопашный бой — S9, D11 — удары руками/ногами, блок без щита; без навыка −5 • Борьба — S11, D9, I4 — борцовские приёмы; без навыка −5 • Метание — S5, D11, I5 — метание оружия; без навыка −3 • Бросание — S11, D5 — бросание предметов; без навыка −2 • Стрельба — S5, D6, I4 — точность атак «Стрельба» • Стрельба из лука — S8, D12, I5 — точность лука; без навыка −5 • Владение грубым оружием — S14, D6 — урон/точность грубого оружия и тяжёлых подручных средств; без навыка −3 • Фехтование — S10, D10, I3 — урон/точность длинного клинкового, парирование; без навыка −5 • Владение копьём — S10, D10 — урон/точность копья; без навыка −2 • Владение коротким оружием — S6, D12, I3 — урон/точность короткого клинкового, его метание, сходные предметы; без навыка −5 • Владение топорами — S12, D10, I2 — урон/точность топоров; без навыка −5 • Владение щитом — S10, D8, I2 — урон/точность щитом и блок щитом; без навыка −5 • Наездник — S4, D5, I5 — управление скакуном; без навыка −5 (разрешение небоевого действия исключено) • Скрытность — D12, I5 — маскировка, сокрытие, схроны, скрытые перемещения (разрешение §5.3 исключено) • Вор — D13, I8 — кражи, замки, обыск, городская маскировка (разрешение исключено) • Акробатика — D14 — лазание, прыжки, кувырки, сложные маршруты, паркур • Ориентирование — I11 — маршрут/путь/картина вслепую (разрешение исключено) • Ученик — I12 — обучение навыку (разрешение §5.3.2 исключено) • Учитель — I13, C10 — обучение/объяснение (исключено) • Крафт — I12, W14 — создание; без навыка −5 • Ремонт — I10, W12 — ремонт; без навыка −5 • Выслеживание — I9, W11 — следы/направление/обнаружение (небоевое разрешение исключено) • Внимательность — W16 — прямой сбор информации, обнаружение, память (небоевое разрешение исключено) • Аналитическое мышление — I16 — анализ, упреждающий удар; социальное сопротивление C исключено • Изобретательство — I18 — новое/улучшение/новое применение (разрешение исключено) • Письмо и чтение — I10, W8 — грамотность; без навыка Единый/Вольный с W<8 неграмотен (небоевое) • Соблазнение — C13 — социальное — разрешение исключено • Обман — C11 — социальное — исключено • Актёрское мастерство — C14 — социальное — исключено • Торг — C11, I10 — социальное — исключено • Палач — C11, S6 — запугивание/допрос/пытки/связывание — §5.3 исключён • Выживание в дикой природе — I10, W12, S8, D8 — небоевые действия/маскировка — разрешение исключено • Молниеносная реакция — D16, I14, W14 — реакция на нападение и уклонение • Управление техникой — I18, W16 — сложная техника — небоевое разрешение исключено • Здоровый образ жизни — Z14, I8, W8 — сопротивление болезням и ядам • Проницательность — C15, I15 — вытягивание сведений/ложь; абсолютный убирает −10 — социальное исключено • Кулинария — W7 — пища/ингредиенты — исключено • Медик — I14, W12 — медицинские манипуляции; без навыка −10, кроме Искателя — §5.3 исключён • Эрудиция — I10, W12 — вспоминание фактов — исключено • Естественнонаучные знания — I14, W10 — дополнительный модификатор изобретательства/крафта только при наличии основного навыка • Алкоголик со стажем — Z8 — дополнительный модификатор сопротивления опьянению — §5.3 исключён | T88: социальные/мирные проверки не реализуются этим реестром, но выбор/требования навыков необходимы для полной процедуры создания. Поздние дельты применяются по приоритету AQ3 > AQ2 > AQA/CQA > базовая карточка; локальное исключение сильнее общего. | U88: характеристики и контекст действия. Нормативная база (действует во всей непротиворечащей части): валидировать требования; добавлять итоговый бонус навыка к перечисленным действиям; применять штраф без навыка только где указан. Навык «Крафт» можно выбрать и хранить как характеристику листа, но его действие создания предметов приложением не исполняется по Q-CORE-059. Каталог: • Навык — Требования (все одновременно) — Механически значимый охват / штраф без навыка • Рукопашный бой — S9, D11 — удары руками/ногами, блок без щита; без навыка −5 • Борьба — S11, D9, I4 — борцовские приёмы; без навыка −5 • Метание — S5, D11, I5 — метание оружия; без навыка −3 • Бросание — S11, D5 — бросание предметов; без навыка −2 • Стрельба — S5, D6, I4 — точность атак «Стрельба» • Стрельба из лука — S8, D12, I5 — точность лука; без навыка −5 • Владение грубым оружием — S14, D6 — урон/точность грубого оружия и тяжёлых подручных средств; без навыка −3 • Фехтование — S10, D10, I3 — урон/точность длинного клинкового, парирование; без навыка −5 • Владение копьём — S10, D10 — урон/точность копья; без навыка −2 • Владение коротким оружием — S6, D12, I3 — урон/точность короткого клинкового, его метание, сходные предметы; без навыка −5 • Владение топорами — S12, D10, I2 — урон/точность топоров; без навыка −5 • Владение щитом — S10, D8, I2 — урон/точность щитом и блок щитом; без навыка −5 • Наездник — S4, D5, I5 — управление скакуном; без навыка −5 (разрешение небоевого действия исключено) • Скрытность — D12, I5 — маскировка, сокрытие, схроны, скрытые перемещения (разрешение §5.3 исключено) • Вор — D13, I8 — кражи, замки, обыск, городская маскировка (разрешение исключено) • Акробатика — D14 — лазание, прыжки, кувырки, сложные маршруты, паркур • Ориентирование — I11 — маршрут/путь/картина вслепую (разрешение исключено) • Ученик — I12 — обучение навыку (разрешение §5.3.2 исключено) • Учитель — I13, C10 — обучение/объяснение (исключено) • Крафт — I12, W14 — создание; без навыка −5 • Ремонт — I10, W12 — ремонт; без навыка −5 • Выслеживание — I9, W11 — следы/направление/обнаружение (небоевое разрешение исключено) • Внимательность — W16 — прямой сбор информации, обнаружение, память (небоевое разрешение исключено) • Аналитическое мышление — I16 — анализ, упреждающий удар; социальное сопротивление C исключено • Изобретательство — I18 — новое/улучшение/новое применение (разрешение исключено) • Письмо и чтение — I10, W8 — грамотность; без навыка Единый/Вольный с W<8 неграмотен (небоевое) • Соблазнение — C13 — социальное — разрешение исключено • Обман — C11 — социальное — исключено • Актёрское мастерство — C14 — социальное — исключено • Торг — C11, I10 — социальное — исключено • Палач — C11, S6 — запугивание/допрос/пытки/связывание — §5.3 исключён • Выживание в дикой природе — I10, W12, S8, D8 — небоевые действия/маскировка — разрешение исключено • Молниеносная реакция — D16, I14, W14 — реакция на нападение и уклонение • Управление техникой — I18, W16 — сложная техника — небоевое разрешение исключено • Здоровый образ жизни — Z14, I8, W8 — сопротивление болезням и ядам • Проницательность — C15, I15 — вытягивание сведений/ложь; абсолютный убирает −10 — социальное исключено • Кулинария — W7 — пища/ингредиенты — исключено • Медик — I14, W12 — медицинские манипуляции; без навыка −10, кроме Искателя — §5.3 исключён • Эрудиция — I10, W12 — вспоминание фактов — исключено • Естественнонаучные знания — I14, W10 — дополнительный модификатор изобретательства/крафта только при наличии основного навыка • Алкоголик со стажем — Z8 — дополнительный модификатор сопротивления опьянению — §5.3 исключён | V88: требования строки; стоимость CORE-165. | W88: [Обязательная правка] Эта формулировка имеет приоритет над исходным текстом карточки. Каталог: • Навык — Требования (все одновременно) — Механически значимый охват / штраф без навыка • Рукопашный бой — S9, D11 — удары руками/ногами, блок без щита; без навыка −5 • Борьба — S11, D9, I4 — борцовские приёмы; без навыка −5 • Метание — S5, D11, I5 — метание оружия; без навыка −3 • Бросание — S11, D5 — бросание предметов; без навыка −2 • Стрельба — S5, D6, I4 — точность атак «Стрельба» • Стрельба из лука — S8, D12, I5 — точность лука; без навыка −5 • Владение грубым оружием — S14, D6 — урон/точность грубого оружия и тяжёлых подручных средств; без навыка −3 • Фехтование — S10, D10, I3 — урон/точность длинного клинкового, парирование; без навыка −5 • Владение копьём — S10, D10 — урон/точность копья; без навыка −2 • Владение коротким оружием — S6, D12, I3 — урон/точность короткого клинкового, его метание, сходные предметы; без навыка −5 • Владение топорами — S12, D10, I2 — урон/точность топоров; без навыка −5 • Владение щитом — S10, D8, I2 — урон/точность щитом и блок щитом; без навыка −5 • Наездник — S4, D5, I5 — управление скакуном; без навыка −5 (разрешение небоевого действия исключено) • Скрытность — D12, I5 — маскировка, сокрытие, схроны, скрытые перемещения (разрешение §5.3 исключено) • Вор — D13, I8 — кражи, замки, обыск, городская маскировка (разрешение исключено) • Акробатика — D14 — лазание, прыжки, кувырки, сложные маршруты, паркур • Ориентирование — I11 — маршрут/путь/картина вслепую (разрешение исключено) • Ученик — I12 — обучение навыку (разрешение §5.3.2 исключено) • Учитель — I13, C10 — обучение/объяснение (исключено) • Крафт — I12, W14 — создание; без навыка −5 • Ремонт — I10, W12 — ремонт; без навыка −5 • Выслеживание — I9, W11 — следы/направление/обнаружение (небоевое разрешение исключено) • Внимательность — W16 — прямой сбор информации, обнаружение, память (небоевое разрешение исключено) • Аналитическое мышление — I16 — анализ, упреждающий удар; социальное сопротивление C исключено • Изобретательство — I18 — новое/улучшение/новое применение (разрешение исключено) • Письмо и чтение — I10, W8 — грамотность; без навыка Единый/Вольный с W<8 неграмотен (небоевое) • Соблазнение — C13 — социальное — разрешение исключено • Обман — C11 — социальное — исключено • Актёрское мастерство — C14 — социальное — исключено • Торг — C11, I10 — социальное — исключено • Палач — C11, S6 — запугивание/допрос/пытки/связывание — §5.3 исключён • Выживание в дикой природе — I10, W12, S8, D8 — небоевые действия/маскировка — разрешение исключено • Молниеносная реакция — D16, I14, W14 — реакция на нападение и уклонение • Управление техникой — I18, W16 — сложная техника — небоевое разрешение исключено • Здоровый образ жизни — Z14, I8, W8 — сопротивление болезням и ядам • Проницательность — C15, I15 — вытягивание сведений/ложь; абсолютный убирает −10 — социальное исключено • Кулинария — W7 — пища/ингредиенты — исключено • Медик — I14, W12 — медицинские манипуляции; без навыка −10, кроме Искателя — §5.3 исключён • Эрудиция — I10, W12 — вспоминание фактов — исключено • Естественнонаучные знания — I14, W10 — дополнительный модификатор изобретательства/крафта только при наличии основного навыка • Алкоголик со стажем — Z8 — дополнительный модификатор сопротивления опьянению — §5.3 исключён | Y88: Нормативная база (действует во всей непротиворечащей части): | AB88: 10 | AC88: §6.2, таблица 6, стр. 106–108. | AE88: CORE-059 CORE-165 | AF88: Нет | AI88: =COUNTIF($B$2:$B$740,B88) -> 1
A89: 88 | B89: CORE-168 | C89: Активно | D89: Реализовать в игровом ядре | E89: Базовое правило | F89: Создание персонажа | G89: Персонажи | H89: 2. Персонаж, предметы и базовая механика | I89: Создание персонажа | J89: Случайный выбор симбионта | K89: создание / симбионт. | L89: Система / игровая сущность | M89: Вольный или Единый | N89: слот(ы). | O89: выбран random mode. | P89: раса Вольный/Единый. | Q89: последовательные чистые D20 и подтверждения критов. | R89: Вольный выполняет 1 результат; Единый последовательно до 4, если не получил чудовище; каждый некритический/не заменённый результат отображается CORE-169; дубликат перебрасывается; применяются меньшие расовые штрафы и пол характеристик CORE-164. | S89: выбранные виды. | T89: Чистые в §6.3 симбионтов не выбирают. | W89: последовательные чистые D20 и подтверждения критов. | AB89: 10 | AC89: §6.3, стр. 108–109. | AE89: CORE-164 CORE-169 | AF89: Нет | AI89: =COUNTIF($B$2:$B$740,B89) -> 1
A90: 89 | B90: CORE-169 | C90: Активно | D90: Реализовать в игровом ядре | E90: Базовое правило | F90: Создание персонажа | G90: Персонажи | H90: 2. Персонаж, предметы и базовая механика | I90: Создание персонажа | J90: Таблица случайных симбионтов | K90: создание / случайная таблица. | L90: Система / игровая сущность | M90: результат D20 | N90: вид симбионта. | O90: CORE-168. | P90: результат не заменён чудовищем. | Q90: D20. | R90: 1 Ткач; 2 Тайпан; 3 Сова; 4 Учитель; 5 Броненосец; 6 Дракон; 7 Трогр; 8 Хранитель; 9 Советник; 10 Клещ; 11 Сверчок; 12 Паук; 13 Хамелеон; 14 Пингвин; 15 Угорь; 16 Жаба; 17 Крыса; 18 Дельфин; 19 Богомол; 20 Скунс. | S90: candidate symbiontType. | T90: подтверждённый крит первого результата Единого — CORE-170. | W90: D20. | AB90: 10 | AC90: §6.3, таблица 7, стр. 108–109. | AE90: CORE-168 CORE-170 | AF90: Нет | AI90: =COUNTIF($B$2:$B$740,B90) -> 1
A91: 90 | B91: CORE-170 | C91: Активно | D91: Реализовать в игровом ядре | E91: Базовое правило | F91: Создание персонажа | G91: Персонажи | H91: 2. Персонаж, предметы и базовая механика | I91: Создание персонажа | J91: Симбиотическое чудовище при случайном выборе | K91: создание / критический результат. | L91: Система / игровая сущность | M91: Единый | N91: все четыре слота. | O91: подтверждённый критический успех или провал первого обрабатываемого D20 выбора. | P91: у Единого ещё нет ни одного обычного симбионта. | Q91: подтверждение 20/1; выбор игрока из списка §7.5.21. | R91: заменить табличный результат выбранным чудовищем; занять 4 слота; прекратить остальные броски. Если уже есть обычный симбионт, подтверждённая 1/20 не даёт чудовище и используется обычная таблица. | S91: один symbioticMonster. | T91: каталог чудовищ вне охваченных разделов. | W91: подтверждённый критический успех или провал первого обрабатываемого D20 выбора. | AB91: 10 | AC91: §6.3, стр. 109; §3.2.6.2, стр. 48. | AF91: Нет | AI91: =COUNTIF($B$2:$B$740,B91) -> 1
A92: 91 | B92: CORE-171 | C92: Активно | D92: Реализовать в игровом ядре | E92: Базовое правило | F92: Создание персонажа | G92: Персонажи | H92: 2. Персонаж, предметы и базовая механика | I92: Создание персонажа | J92: Запрет дубликата симбионта | K92: симбионт / ограничение. | L92: Игрок / персонаж | M92: носитель | N92: новый симбионт. | O92: заражение, случайный выбор, операция/пересадка. | P92: вид уже присутствует. | Q92: множество видов. | R92: в одном теле максимум один симбионт вида; при случайном повторе перебрасывать до свободного допустимого вида; если свободных допустимых видов нет — заражение/выбор не происходит. | S92: уникальный набор. | T92: чудовище занимает все слоты. | AB92: 10 | AC92: §6.3, стр. 109. | AF92: Нет | AI92: =COUNTIF($B$2:$B$740,B92) -> 1
A93: 92 | B93: CORE-173 | C93: Активно | D93: Реализовать в игровом ядре | E93: Базовое правило | F93: Создание персонажа | G93: Персонажи | H93: 2. Персонаж, предметы и базовая механика | I93: Создание персонажа | J93: Пять заявленных стартовых предметов | K93: создание / имущество. | L93: Мастер / игрок / система | M93: игрок | N93: 5 кандидатов. | O93: после базовых категорий. | P93: мастер объявил доступность по месту происхождения. | Q93: ровно 5 заявок и отдельный D20 каждой. | R93: Нормативная база (действует во всей непротиворечащей части): для каждого независимо определить наличие/качество; если таблицы кампании нет: 1–4 отсутствует/непригоден; 5–9 плохое; 10–14 обычное; 15–18 хорошее; 19 исключительное; 20 редкое. Нельзя переносить результат между предметами. Приоритетные авторские дельты (заменяют только прямо пересекающиеся ветви): [Обязательная правка] Эта формулировка имеет приоритет над исходным текстом карточки. стартовые предметы включить в процедуру мастерского согласования Q-CORE-052 Отдельная стартовая операция оружия хранит выбранный тип/вариант и готовый профиль; качество остаётся рекомендацией и не заменяет профиль. | S93: до 5 созданных записей имущества. | T93: шкала не отменяет требования и без мастера не создаёт уникальный артефакт. Поздние дельты применяются по приоритету AQ3 > AQ2 > AQA/CQA > базовая карточка; локальное исключение сильнее общего. | U93: Нормативная база (действует во всей непротиворечащей части): | W93: ровно 5 заявок и отдельный D20 каждой. [Обязательная правка] Эта формулировка имеет приоритет над исходным текстом карточки. | X93: шкала не отменяет требования и без мастера не создаёт уникальный артефакт. | Y93: Нормативная база (действует во всей непротиворечащей части): | AB93: 60 | AC93: §6.4, стр. 110. Прямое уточнение пользователя 2026-07-28 | AE93: CORE-052 CORE-184 CORE-185 CORE-186 CORE-187 CORE-188 | AF93: Да | AH93: Патч v1.2 | AI93: =COUNTIF($B$2:$B$740,B93) -> 1
A94: 93 | B94: CORE-174 | C94: Активно | D94: Реализовать в игровом ядре | E94: Базовое правило | F94: Создание персонажа | G94: Персонажи | H94: 2. Персонаж, предметы и базовая механика | I94: Создание персонажа | J94: Древние недоступны как игровая раса | K94: создание / доступность расы. | L94: Игрок / персонаж | M94: игрок | N94: выбор расы. | O94: создание персонажа. | P94: нет. | Q94: выбранная raceId. | R94: не показывать Древних как доступную игровую расу; отклонять создание персонажа с raceId=Ancient. | S94: доступны только игровые расы, разрешённые правилами. | T94: мастерские НПС не затрагиваются этим запретом, если отдельное правило кампании не говорит иное. | W94: не показывать Древних как доступную игровую расу; отклонять создание персонажа с raceId=Ancient. | X94: не показывать Древних как доступную игровую расу; отклонять создание персонажа с raceId=Ancient. | AB94: 10 | AC94: §3.1 (механическое указание), стр. 43. | AF94: Нет | AI94: =COUNTIF($B$2:$B$740,B94) -> 1
A95: 94 | B95: CORE-176 | C95: Активно | D95: Реализовать в игровом ядре | E95: Базовое правило | F95: Создание персонажа | G95: Персонажи | H95: 2. Персонаж, предметы и базовая механика | I95: Создание персонажа | J95: Термины хода, круга и сцены | K95: бой / временная модель. | L95: Мастер / игрок / система | M95: боевая ситуация | N95: таймеры и очередь. | O95: создание боя и интерпретация срока. | P95: нет. | Q95: очередь участников и формулировка правила. | R95: ход персонажа = его одно место в инициативе; «ход»/«боевой ход» без уточнения = личный ход, не круг. Круг инициативы = полный цикл, где каждый участник получает ход. Формулировка «до конца хода (круга инициативы)» означает конец текущего круга. Сцена = непрерывный эпизод в одном месте/времени, её завершение вводит мастер. | S95: однозначные time anchors для эффектов. | T95: конкретный эффект с собственным моментом тика сильнее. | W95: очередь участников и формулировка правила. ход персонажа = его одно место в инициативе; «ход»/«боевой ход» без уточнения = личный ход, не круг. Круг инициативы = полный цикл, где каждый участник получает ход. Формулировка «до конца хода (круга инициативы)» означает конец текущего круга. Сцена = непрерывный эпизод в одном месте/времени, её завершение вводит мастер. | Y95: создание боя и интерпретация срока. ход персонажа = его одно место в инициативе; «ход»/«боевой ход» без уточнения = личный ход, не круг. Круг инициативы = полный цикл, где каждый участник получает ход. Формулировка «до конца хода (круга инициативы)» означает конец текущего круга. | AB95: 10 | AC95: §5.4.1, стр. 93. | AF95: Нет | AI95: =COUNTIF($B$2:$B$740,B95) -> 1
A96: 95 | B96: CORE-178 | C96: Активно | D96: Реализовать в игровом ядре | E96: Базовое правило | F96: Создание персонажа | G96: Персонажи | H96: 2. Персонаж, предметы и базовая механика | I96: Создание персонажа | J96: Автомат состояния «бегство» | K96: контроль поведения / выход из боя. | L96: Система / игровая сущность | M96: любой живой участник | N96: собственные действия. | O96: добровольный выбор в начале личного хода либо принудительный эффект правила | P96: участник находится в бою; при принудительном триггере отказ невозможен | Q96: двумерные координаты, ближайшие противники, D, En, серия доступных действий | R96: Установить fleeing=true. В начале каждого личного хода запретить атаки и автоматически расходовать все боевые действия на обычные перемещения по прямой от ближайшего противника; каждое перемещение равно max(0,R20+D−En×10). Ближайший противник пересчитывается перед каждым перемещением, равенство разрешается случайно. Режим «бежать несмотря ни на что» не включается. Защитные реакции сохраняются. После достижения дистанции более 150 м до ближайшего противника немедленно исключить участника из боя. | S96: участник либо остаётся в состоянии бегства, либо удалён из текущей боевой ситуации | T96: прямой эффект, отменяющий бегство, снимает флаг; препятствия, безопасный путь и высота не моделируются | U96: двумерные координаты, ближайшие противники, D, En, серия доступных действий В начале каждого личного хода запретить атаки и автоматически расходовать все боевые действия на обычные перемещения по прямой от ближайшего противника; каждое перемещение равно max(0,R20+D−En×10). Защитные реакции сохраняются. | W96: Установить fleeing=true. В начале каждого личного хода запретить атаки и автоматически расходовать все боевые действия на обычные перемещения по прямой от ближайшего противника; каждое перемещение равно max(0,R20+D−En×10). | X96: участник находится в бою; при принудительном триггере отказ невозможен | Y96: добровольный выбор в начале личного хода либо принудительный эффект правила В начале каждого личного хода запретить атаки и автоматически расходовать все боевые действия на обычные перемещения по прямой от ближайшего противника; каждое перемещение равно max(0,R20+D−En×10). | AB96: 10 | AC96: Q-CORE-037 (Round 2); §5.4.4.2.3, стр. 99. | AD96: Q-CORE-037 | AF96: Нет | AI96: =COUNTIF($B$2:$B$740,B96) -> 1
A97: 96 | B97: SYM-001 | C97: Активно | D97: Реализовать в игровом ядре | E97: Базовое правило | F97: Создание персонажа | G97: Персонажи | H97: 3. Обыкновенные симбионты | I97: Общие правила симбионтов и развития | J97: Ограничение одного симбионта каждого вида | K97: состав носителя. | L97: Игрок / персонаж | M97: персонаж | N97: добавляемый симбионт. | O97: попытка заражения, пересадки или создания набора симбионтов. | P97: вид симбионта определён. | Q97: host.symbionts, candidate.type. | R97: отклонить добавление, если в теле уже есть симбионт с type = candidate.type. | S97: состав не меняется; причина отказа «вид уже занят». | T97: специальных исключений в 7.1–7.5.20 нет. | W97: отклонить добавление, если в теле уже есть симбионт с type = candidate.type. | X97: отклонить добавление, если в теле уже есть симбионт с type = candidate.type. состав не меняется; причина отказа «вид уже занят». | AB97: 10 | AC97: 7.1, стр. 111. | AF97: Нет | AI97: =COUNTIF($B$2:$B$740,B97) -> 1
A98: 97 | B98: SYM-002 | C98: Активно | D98: Реализовать в игровом ядре | E98: Базовое правило | F98: Симбионты | G98: Симбионты | H98: 3. Обыкновенные симбионты | I98: Общие правила симбионтов и развития | J98: Вместимость симбиотических слотов | K98: состав носителя. | L98: Игрок / персонаж | M98: носитель | N98: новый обыкновенный симбионт. | O98: добавление симбионта или изменение его занимаемых слотов. | P98: известны свободные слоты и размер симбионта. | Q98: slotCapacity, occupiedSlots; для обыкновенного симбионта slotCost=1, если специальное правило не меняет стоимость. | R98: добавление допустимо, только если occupiedSlots + slotCost <= slotCapacity. | S98: при успехе занять слоты; при нехватке новый симбионт не поселяется. | T98: Трогр после поглощения Учителя/Дельфина меняет slotCost по SYM-076. | V98: slotCapacity, occupiedSlots; для обыкновенного симбионта slotCost=1, если специальное правило не меняет стоимость. | W98: slotCapacity, occupiedSlots; для обыкновенного симбионта slotCost=1, если специальное правило не меняет стоимость. добавление допустимо, только если occupiedSlots + slotCost <= slotCapacity. | X98: slotCapacity, occupiedSlots; для обыкновенного симбионта slotCost=1, если специальное правило не меняет стоимость. | AB98: 10 | AC98: 7.1, стр. 111; 7.5, стр. 115. | AE98: SYM-076 | AF98: Нет | AI98: =COUNTIF($B$2:$B$740,B98) -> 1
A99: 98 | B99: SYM-003 | C99: Активно | D99: Реализовать в игровом ядре | E99: Базовое правило | F99: Симбионты | G99: Симбионты | H99: 3. Обыкновенные симбионты | I99: Общие правила симбионтов и развития | J99: Иммунитет Чистых к естественному заражению | K99: заражение. | L99: Мастер / игрок / система | M99: персонаж расы Чистые | N99: проверка естественного заражения. | O99: наступление момента проверки заражения. | P99: race=Чистый. | Q99: раса персонажа. | R99: Нормативная база (действует во всей непротиворечащей части): проверку не выполнять; заражение не возникает. Приоритетные авторские дельты (заменяют только прямо пересекающиеся ветви): [AQ2-GM-SYM] Операции мастера по добавлению, удалению, замене, пересадке и изменению уровня симбионта определены карточками AQ2-013–AQ2-025. Прежняя помета о неопределённости пересадки в конфликтующей части не применяется. | S99: состав симбионтов неизменен. | T99: правило относится к естественному заражению; операции пересадки здесь не определены. Поздние дельты применяются по приоритету AQ3 > AQ2 > AQA/CQA > базовая карточка; локальное исключение сильнее общего. | U99: Нормативная база (действует во всей непротиворечащей части): Прежняя помета о неопределённости пересадки в конфликтующей части не применяется. | W99: race=Чистый. | X99: проверку не выполнять; заражение не возникает. | Y99: Нормативная база (действует во всей непротиворечащей части): Прежняя помета о неопределённости пересадки в конфликтующей части не применяется. | AB99: 10 | AC99: 7.1, стр. 111. | AE99: AQ2-013 AQ2-025 | AF99: Нет | AI99: =COUNTIF($B$2:$B$740,B99) -> 1
A100: 99 | B100: SYM-006 | C100: Активно | D100: Реализовать в игровом ядре | E100: Базовое правило | F100: Симбионты | G100: Симбионты | H100: 3. Обыкновенные симбионты | I100: Общие правила симбионтов и развития | J100: Состояние пересаженного симбионта | K100: пересадка / сохранение прогресса. | L100: Игрок / персонаж | M100: пересаживаемый симбионт | N100: новый носитель. | O100: успешное завершение операции пересадки. | P100: пересадка допустима по слотам и уникальности вида. | Q100: уровень, изученные способности, текущие ОЭ симбионта. | R100: сохранить приобретённый уровень и изученные способности; установить currentOE=0. | S100: симбионт переносится без потери прогресса, но без текущей энергии. | T100: восстановление ОЭ — только обычным отдыхом. | V100: уровень, изученные способности, текущие ОЭ симбионта. восстановление ОЭ — только обычным отдыхом. | W100: сохранить приобретённый уровень и изученные способности; установить currentOE=0. | AB100: 10 | AC100: 7.1, стр. 111. | AF100: Нет | AI100: =COUNTIF($B$2:$B$740,B100) -> 1
...

Sheet Параметры
A1: Parameter ID | B1: Rule ID | C1: Компонент приложения | D1: Контекст | E1: Группа параметра | F1: Нормативное значение / условие | G1: Статус правила | H1: Приоритет источника
A2: PAR-00001 | B2: CORE-001 | C2: Персонажи | D2: Создание персонажа | E2: Броски / формулы | F2: раса = Единый. | G2: Активно | H2: 10
A3: PAR-00002 | B3: CORE-001 | C3: Персонажи | D3: Создание персонажа | E3: Броски / формулы | F3: random: S−=3, M−=6, Z−=6; manual: S−=7, M−=10, Z−=10; при проверке общения C_eff=C+5 против Единого, C_eff=C−15 против Чистого. | G3: Активно | H3: 10
A4: PAR-00003 | B4: CORE-004 | C4: Персонажи | D4: Создание персонажа | E4: Броски / формулы | F4: раса = Единый, пассивный источник активен. | G4: Активно | H4: 10
A5: PAR-00004 | B5: CORE-005 | C5: Персонажи | D5: Создание персонажа | E5: Броски / формулы | F5: раса = Единый. | G5: Активно | H5: 10
A6: PAR-00005 | B6: CORE-005 | C6: Персонажи | D6: Создание персонажа | E6: Броски / формулы | F6: вместимость = 4 слота; обычный симбионт занимает установленное его каталогом число слотов; «Симбиотическое чудовище» занимает все 4 и доступно только Единому. | G6: Активно | H6: 10
A7: PAR-00006 | B7: CORE-006 | C7: Персонажи | D7: Создание персонажа | E7: Броски / формулы | F7: раса = Вольный. | G7: Активно | H7: 10
A8: PAR-00007 | B8: CORE-006 | C8: Персонажи | D8: Создание персонажа | E8: Броски / формулы | F8: random: без расовой поправки; manual: S−=2, M−=2, Z−=2. | G8: Активно | H8: 10
A9: PAR-00008 | B9: CORE-007 | C9: Персонажи | D9: Создание персонажа | E9: Броски / формулы | F9: раса = Вольный. | G9: Активно | H9: 10
A10: PAR-00009 | B10: CORE-007 | C10: Персонажи | D10: Создание персонажа | E10: Броски / формулы | F10: доступен 1 слот; фактическое начисление symbiontXP += 2×baseXP. | G10: Активно | H10: 10
A11: PAR-00010 | B11: CORE-009 | C11: Персонажи | D11: Создание персонажа | E11: Стоимость действия / времени | F11: Нормативная база (действует во всей непротиворечащей части): | G11: Активно | H11: 10
A12: PAR-00011 | B12: CORE-009 | C12: Персонажи | D12: Создание персонажа | E12: Стоимость действия / времени | F12: Бонус к «Крафту» хранится в листе персонажа, но приложение не предоставляет runtime-действие создания предмета по Q-CORE-059. | G12: Активно | H12: 10
A13: PAR-00012 | B13: CORE-009 | C13: Персонажи | D13: Создание персонажа | E13: Стоимость действия / времени | F13: разрешение небоевых/социальных действий вне охвата; боевые модификаторы применяются. | G13: Активно | H13: 10
... A4622: PAR-04621 | B4622: CORE-215 | C4622: Кампании | D4622: Кампания | E4622: Group generator boundary | F4622: Preview/regenerate/accept only; no combat AI, auto-targeting, cross-campaign library or hidden clamp. | G4622: Активно | H4622: 110

Sheet Связи
A1: Source Rule ID | B1: Тип связи | C1: Target Rule ID | D1: Контекст источника | E1: Примечание
A2: AQ2-001 | B2: Ссылается / зависит | C2: MON-045 | D2: Создание персонажа
A3: AQ2-001 | B3: Ссылается / зависит | C3: MON-054 | D3: Создание персонажа
A4: AQ2-001 | B4: Ссылается / зависит | C4: MON-082 | D4: Создание персонажа
A5: AQ2-001 | B5: Ссылается / зависит | C5: MON-083 | D5: Создание персонажа
A6: AQ2-004 | B6: Ссылается / зависит | C6: CORE-052 | D6: Создание персонажа
A7: AQ2-004 | B7: Ссылается / зависит | C7: CORE-172 | D7: Создание персонажа
A8: AQ2-012 | B8: Ссылается / зависит | C8: MON-004 | D8: Отдых и дозор
A9: AQ2-012 | B9: Ссылается / зависит | C9: MON-010 | D9: Отдых и дозор
A10: AQ2-012 | B10: Ссылается / зависит | C10: MON-032 | D10: Отдых и дозор
A11: AQ2-012 | B11: Ссылается / зависит | C11: MON-048 | D11: Отдых и дозор
A12: AQ2-012 | B12: Ссылается / зависит | C12: MON-050 | D12: Отдых и дозор
A13: AQ2-012 | B13: Ссылается / зависит | C13: MON-051 | D13: Отдых и дозор
... A95: AQA-038 | B95: Ссылается / зависит | C95: CORE-178 | D95: Создание персонажа
A96: AQA-044 | B96: Уточняет / имеет приоритет | C96: AQA-033 | D96: Мастер и НПС | E96: Позднее согласованное правило заменяет пересекающуюся ветвь.
A97: AQA-044 | B97: Уточняет / имеет приоритет | C97: AQA-035 | D97: Мастер и НПС | E97: Позднее согласованное правило заменяет пересекающуюся ветвь.
A98: AQA-044 | B98: Уточняет / имеет приоритет | C98: AQA-040 | D98: Мастер и НПС | E98: Позднее согласованное правило заменяет пересекающуюся ветвь.
A99: AQA-044 | B99: Уточняет / имеет приоритет | C99: AQA-043 | D99: Мастер и НПС | E99: Позднее согласованное правило заменяет пересекающуюся ветвь.
A100: AQA-045 | B100: Уточняет / имеет приоритет | C100: AQ2-009 | D100: Мастер и НПС | E100: Позднее согласованное правило заменяет пересекающуюся ветвь.
A101: AQA-045 | B101: Уточняет / имеет приоритет | C101: AQA-028 | D101: Мастер и НПС | E101: Позднее согласованное правило заменяет пересекающуюся ветвь.
A102: AQA-045 | B102: Уточняет / имеет приоритет | C102: AQA-029 | D102: Мастер и НПС | E102: Позднее согласованное правило заменяет пересекающуюся ветвь.
A103: CORE-001 | B103: Ссылается / зависит | C103: CORE-164 | D103: Создание персонажа
A104: CORE-003 | B104: Ссылается / зависит | C104: CORE-002 | D104: Создание персонажа
A105: CORE-004 | B105: Ссылается / зависит | C105: CORE-114 | D105: Создание персонажа
A106: CORE-005 | B106: Ссылается / зависит | C106: CORE-170 | D106: Создание персонажа
A107: CORE-006 | B107: Ссылается / зависит | C107: CORE-164 | D107: Создание персонажа
A108: CORE-007 | B108: Ссылается / зависит | C108: CORE-171 | D108: Создание персонажа
A109: CORE-008 | B109: Ссылается / зависит | C109: CORE-009 | D109: Создание персонажа
A110: CORE-009 | B110: Ссылается / зависит | C110: CORE-059 | D110: Создание персонажа
A111: CORE-015 | B111: Ссылается / зависит | C111: CORE-014 | D111: Создание персонажа
A112: CORE-020 | B112: Ссылается / зависит | C112: CORE-128 | D112: Создание персонажа
A113: CORE-020 | B113: Ссылается / зависит | C113: CORE-129 | D113: Создание персонажа
A114: CORE-021 | B114: Ссылается / зависит | C114: CORE-016 | D114: Создание персонажа
... A193: CORE-175 | B193: Ссылается / зависит | C193: CORE-171 | D193: Создание персонажа
A194: CORE-179 | B194: Уточняет / имеет приоритет | C194: AQA-019 | D194: Боевая ситуация | E194: Позднее согласованное правило заменяет пересекающуюся ветвь.
A195: CORE-179 | B195: Уточняет / имеет приоритет | C195: AQA-035 | D195: Боевая ситуация | E195: Позднее согласованное правило заменяет пересекающуюся ветвь.
A196: CORE-179 | B196: Уточняет / имеет приоритет | C196: CORE-087 | D196: Боевая ситуация | E196: Позднее согласованное правило заменяет пересекающуюся ветвь.
A197: CORE-179 | B197: Уточняет / имеет приоритет | C197: CORE-090 | D197: Боевая ситуация | E197: Позднее согласованное правило заменяет пересекающуюся ветвь.
A198: CORE-180 | B198: Уточняет / имеет приоритет | C198: AQA-032 | D198: Инвентарь и предметы | E198: Позднее согласованное правило заменяет пересекающуюся ветвь.
A199: CORE-180 | B199: Уточняет / имеет приоритет | C199: CORE-128 | D199: Инвентарь и предметы | E199: Позднее согласованное правило заменяет пересекающуюся ветвь.
A200: CORE-181 | B200: Уточняет / имеет приоритет | C200: CORE-103 | D200: Боевая ситуация | E200: Позднее согласованное правило заменяет пересекающуюся ветвь.
A201: CORE-181 | B201: Уточняет / имеет приоритет | C201: CQA-049 | D201: Боевая ситуация | E201: Позднее согласованное правило заменяет пересекающуюся ветвь.
A202: CORE-181 | B202: Уточняет / имеет приоритет | C202: MON-038 | D202: Боевая ситуация | E202: Позднее согласованное правило заменяет пересекающуюся ветвь.
A203: CORE-181 | B203: Уточняет / имеет приоритет | C203: SYM-099 | D203: Боевая ситуация | E203: Позднее согласованное правило заменяет пересекающуюся ветвь.
A204: CORE-181 | B204: Уточняет / имеет приоритет | C204: SYM-100 | D204: Боевая ситуация | E204: Позднее согласованное правило заменяет пересекающуюся ветвь.
A205: CORE-181 | B205: Уточняет / имеет приоритет | C205: SYM-132 | D205: Боевая ситуация | E205: Позднее согласованное правило заменяет пересекающуюся ветвь.
... A210: CORE-182 | B210: Уточняет / имеет приоритет | C210: SYM-030 | D210: Смерть и мародерство | E210: Позднее согласованное правило заменяет пересекающуюся ветвь.
A211: CQA-002 | B211: Ссылается / зависит | C211: SYM-006 | D211: Создание персонажа
A212: CQA-013 | B212: Ссылается / зависит | C212: SYM-024 | D212: Создание персонажа
A213: CQA-015 | B213: Ссылается / зависит | C213: SYM-092 | D213: Боевая ситуация
A214: CQA-019 | B214: Ссылается / зависит | C214: SYM-074 | D214: Боевая ситуация
A215: CQA-021 | B215: Ссылается / зависит | C215: SYM-039 | D215: Боевая ситуация
A216: CQA-021 | B216: Ссылается / зависит | C216: SYM-074 | D216: Боевая ситуация
A217: CQA-021 | B217: Ссылается / зависит | C217: SYM-088 | D217: Боевая ситуация
A218: CQA-040 | B218: Ссылается / зависит | C218: SYM-070 | D218: Боевая ситуация
A219: CQA-045 | B219: Ссылается / зависит | C219: MON-009 | D219: Боевая ситуация
A220: CQA-059 | B220: Ссылается / зависит | C220: MON-020 | D220: Боевая ситуация
A221: CQA-061 | B221: Уточняет / имеет приоритет | C221: AQA-032 | D221: Смерть и мародерство | E221: Позднее согласованное правило заменяет пересекающуюся ветвь.
A222: CQA-061 | B222: Уточняет / имеет приоритет | C222: CQA-001 | D222: Смерть и мародерство | E222: Позднее согласованное правило заменяет пересекающуюся ветвь.
A223: CQA-061 | B223: Уточняет / имеет приоритет | C223: SYM-035 | D223: Смерть и мародерство | E223: Позднее согласованное правило заменяет пересекающуюся ветвь.
A224: MON-009 | B224: Уточняет / имеет приоритет | C224: CORE-154 | D224: Болезни и состояния | E224: Позднее согласованное правило заменяет пересекающуюся ветвь.
A225: MON-029 | B225: Ссылается / зависит | C225: MON-030 | D225: Болезни и состояния
A226: MON-042 | B226: Ссылается / зависит | C226: MON-045 | D226: Симбионты
A227: MON-042 | B227: Ссылается / зависит | C227: MON-055 | D227: Симбионты
A228: MON-044 | B228: Ссылается / зависит | C228: MON-043 | D228: Боевая ситуация
A229: MON-045 | B229: Ссылается / зависит | C229: AQ2-001 | D229: Симбионты
A230: MON-054 | B230: Ссылается / зависит | C230: AQ2-001 | D230: Боевая ситуация
A231: MON-056 | B231: Ссылается / зависит | C231: CORE-030 | D231: Симбионты
A232: MON-062 | B232: Ссылается / зависит | C232: MON-063 | D232: Боевая ситуация
A233: MON-063 | B233: Ссылается / зависит | C233: MON-045 | D233: Боевая ситуация
A234: MON-064 | B234: Ссылается / зависит | C234: MON-065 | D234: Создание персонажа
A235: MON-071 | B235: Ссылается / зависит | C235: MON-072 | D235: Боевая ситуация
A236: MON-076 | B236: Ссылается / зависит | C236: MON-074 | D236: Болезни и состояния
... A278: SYM-026 | B278: Ссылается / зависит | C278: SYM-023 | D278: Симбионты
A279: SYM-032 | B279: Уточняет / имеет приоритет | C279: AQ3-002 | D279: Боевая ситуация | E279: Позднее согласованное правило заменяет пересекающуюся ветвь.
A280: SYM-032 | B280: Уточняет / имеет приоритет | C280: CORE-023 | D280: Боевая ситуация | E280: Позднее согласованное правило заменяет пересекающуюся ветвь.
A281: SYM-032 | B281: Уточняет / имеет приоритет | C281: CQA-007 | D281: Боевая ситуация | E281: Позднее согласованное правило заменяет пересекающуюся ветвь.
A282: SYM-035 | B282: Ссылается / зависит | C282: CORE-063 | D282: Боевая ситуация
A283: SYM-037 | B283: Ссылается / зависит | C283: SYM-038 | D283: Симбионты
A284: SYM-046 | B284: Ссылается / зависит | C284: SYM-047 | D284: Симбионты
A285: SYM-071 | B285: Ссылается / зависит | C285: CORE-030 | D285: Боевая ситуация
A286: SYM-074 | B286: Ссылается / зависит | C286: SYM-076 | D286: Симбионты
A287: SYM-080 | B287: Ссылается / зависит | C287: SYM-077 | D287: Боевая ситуация
A288: SYM-081 | B288: Ссылается / зависит | C288: SYM-082 | D288: Симбионты
A289: SYM-082 | B289: Ссылается / зависит | C289: SYM-081 | D289: Симбионты
A290: SYM-090 | B290: Ссылается / зависит | C290: SYM-009 | D290: Симбионты
A291: SYM-091 | B291: Уточняет / имеет приоритет | C291: CORE-093 | D291: Боевая ситуация | E291: Позднее согласованное правило заменяет пересекающуюся ветвь.
A292: SYM-091 | B292: Уточняет / имеет приоритет | C292: CQA-002 | D292: Боевая ситуация | E292: Позднее согласованное правило заменяет пересекающуюся ветвь.
A293: SYM-095 | B293: Ссылается / зависит | C293: SYM-075 | D293: Симбионты
A294: SYM-118 | B294: Ссылается / зависит | C294: SYM-117 | D294: Перемещение и карта
A295: SYM-132 | B295: Ссылается / зависит | C295: CORE-023 | D295: Боевая ситуация
A296: SYM-139 | B296: Ссылается / зависит | C296: CORE-062 | D296: Боевая ситуация
A297: SYM-139 | B297: Ссылается / зависит | C297: SYM-137 | D297: Боевая ситуация
A298: SYM-140 | B298: Ссылается / зависит | C298: SYM-137 | D298: Боевая ситуация
A299: SYM-143 | B299: Ссылается / зависит | C299: SYM-038 | D299: Симбионты
A300: SYM-145 | B300: Ссылается / зависит | C300: SYM-007 | D300: Симбионты
A301: SYM-168 | B301: Ссылается / зависит | C301: AQ3-001 | D301: Боевая ситуация
A302: SYM-178 | B302: Ссылается / зависит | C302: SYM-175 | D302: Боевая ситуация
A303: SYM-182 | B303: Ссылается / зависит | C303: CORE-001 | D303: Создание персонажа
A304: SYM-182 | B304: Ссылается / зависит | C304: CORE-006 | D304: Создание персонажа
...

Sheet Источники
A1: Rule ID | B1: Тип правила | C1: Статус | D1: Приоритет | E1: Источник карточки | F1: ID вопросов | G1: Вопрос-источник / назначение | H1: Композиция базы | I1: Финальная правка
A2: CORE-001 | B2: Базовое правило | C2: Активно | D2: 10 | E2: §3.2.6.1, стр. 48. | H2: Нет
A3: CORE-004 | B3: Базовое правило | C3: Активно | D3: 10 | E3: §3.2.6.1.1, стр. 48. | H3: Нет
A4: CORE-005 | B4: Базовое правило | C4: Активно | D4: 10 | E4: §3.2.6.2, стр. 48. | H4: Нет
A5: CORE-006 | B5: Базовое правило | C5: Активно | D5: 10 | E5: §3.3.6.1, стр. 55. | H5: Нет
A6: CORE-007 | B6: Базовое правило | C6: Активно | D6: 100 | E6: §3.3.6.2, стр. 55. Прямое авторское решение Q-SYMBIONT-XP-001 — опыт симбионтов за natural 20/1, 2026-07-30 | F6: Q-SYMBIONT-XP-001 | G6: Синхронизация маршрутизации и опыта симбионтов v1.6. | H6: Нет | I6: Патч v1.6 (опыт симбионтов)
A7: CORE-009 | B7: Базовое правило | C7: Активно | D7: 10 | E7: §3.4.7.1, стр. 65. | H7: Нет
A8: CORE-010 | B8: Базовое правило | C8: Активно | D8: 10 | E8: §3.4.7.2.1–3.4.7.2.2, стр. 65. | H8: Нет
A9: CORE-013 | B9: Базовое правило | C9: Активно | D9: 10 | E9: §3.4.7.3, стр. 65–66. | H9: Нет
A10: CORE-015 | B10: Базовое правило | C10: Не автоматизируется | D10: 60 | E10: §4.1, стр. 67. Прямое уточнение пользователя 2026-07-28 | F10: Q-CORE-059 | G10: Синхронизация профиля оружия v1.2. | H10: Да | I10: Патч v1.2
A11: CORE-017 | B11: Базовое правило | C11: Активно | D11: 10 | E11: таблицы §4.2 и §4.4, стр. 69, 74, 76. | H11: Нет
A12: CORE-018 | B12: Базовое правило | C12: Активно | D12: 10 | E12: §4.4, стр. 77–80. | H12: Нет
A13: CORE-019 | B13: Базовое правило | C13: Активно | D13: 10 | E13: §4.4, стр. 77–80; §6.2, стр. 106. | H13: Нет
A14: CORE-021 | B14: Базовое правило | C14: Активно | D14: 60 | E14: §4.2, таблица 1, стр. 68. Прямое уточнение пользователя 2026-07-28 | G14: Синхронизация профиля оружия v1.2. | H14: Да | I14: Патч v1.2
A15: CORE-022 | B15: Базовое правило | C15: Активно | D15: 60 | E15: §4.2, таблица 1, стр. 69. Прямое уточнение пользователя 2026-07-28 | G15: Синхронизация профиля оружия v1.2. | H15: Да | I15: Патч v1.2
A16: CORE-023 | B16: Базовое правило | C16: Активно | D16: 60 | E16: §4.2, таблица 1, стр. 69. Прямое уточнение пользователя 2026-07-28 | G16: Синхронизация профиля оружия v1.2. | H16: Да | I16: Патч v1.2
A17: CORE-024 | B17: Базовое правило | C17: Активно | D17: 60 | E17: §4.2, таблица 1, стр. 69. Прямое уточнение пользователя 2026-07-28 | G17: Синхронизация профиля оружия v1.2. | H17: Да | I17: Патч v1.2
A18: CORE-025 | B18: Базовое правило | C18: Активно | D18: 60 | E18: §4.2, таблица 1, стр. 70. Прямое уточнение пользователя 2026-07-28 | G18: Синхронизация профиля оружия v1.2. | H18: Да | I18: Патч v1.2
A19: CORE-032 | B19: Базовое правило | C19: Активно | D19: 60 | E19: §4.4, таблица 3, стр. 73. Прямое уточнение пользователя 2026-07-28 | G19: Синхронизация профиля оружия v1.2. | H19: Да | I19: Патч v1.2
A20: CORE-034 | B20: Базовое правило | C20: Активно | D20: 60 | E20: §4.4, таблица 3, стр. 74. Прямое уточнение пользователя 2026-07-28 | G20: Синхронизация профиля оружия v1.2. | H20: Да | I20: Патч v1.2
A21: CORE-035 | B21: Базовое правило | C21: Активно | D21: 60 | E21: §4.4, таблица 3, стр. 74. Прямое уточнение пользователя 2026-07-28 | G21: Синхронизация профиля оружия v1.2. | H21: Да | I21: Патч v1.2
A22: CORE-036 | B22: Базовое правило | C22: Активно | D22: 60 | E22: §4.4, таблица 3, стр. 74. Прямое уточнение пользователя 2026-07-28 | G22: Синхронизация профиля оружия v1.2. | H22: Да | I22: Патч v1.2
A23: CORE-042 | B23: Базовое правило | C23: Активно | D23: 60 | E23: §4.4, таблица 3, стр. 76. Прямое уточнение пользователя 2026-07-28 | G23: Синхронизация профиля оружия v1.2. | H23: Да | I23: Патч v1.2
A24: CORE-049 | B24: Базовое правило | C24: Активно | D24: 10 | E24: §4.5, таблица 4, стр. 81. | H24: Нет
A25: CORE-052 | B25: Базовое правило | C25: Активно | D25: 10 | E25: §4.5, таблица 4, стр. 82. | H25: Нет
A26: CORE-054 | B26: Базовое правило | C26: Активно | D26: 10 | E26: §4.5, таблица 4, стр. 82; §5.4.3.6, стр. 97–98. | H26: Нет
A27: CORE-055 | B27: Базовое правило | C27: Активно | D27: 10 | E27: §4.5, таблица 4, стр. 82. | H27: Нет
A28: CORE-056 | B28: Базовое правило | C28: Активно | D28: 10 | E28: §4.5, таблица 4, стр. 83. | H28: Нет
A29: CORE-060 | B29: Базовое правило | C29: Активно | D29: 10 | E29: §4.6, таблица 5, стр. 83–84; §5.5, стр. 104. | H29: Нет
A30: CORE-064 | B30: Базовое правило | C30: Активно | D30: 10 | E30: §4.6, таблица 5, стр. 84. | H30: Нет
A31: CORE-066 | B31: Базовое правило | C31: Активно | D31: 10 | E31: §4.6, таблица 5, стр. 84. | H31: Нет
A32: CORE-067 | B32: Базовое правило | C32: Активно | D32: 10 | E32: §4.6, таблица 5, стр. 84. | H32: Нет
A33: CORE-070 | B33: Базовое правило | C33: Активно | D33: 10 | E33: §4.6, таблица 5, стр. 84. | H33: Нет
A34: CORE-071 | B34: Базовое правило | C34: Активно | D34: 10 | E34: §4.6, таблица 5, стр. 84; §5.4.2.5, стр. 95. | H34: Нет
A35: CORE-073 | B35: Базовое правило | C35: Активно | D35: 100 | E35: §5.1, стр. 85–86. Прямое уточнение пользователя 2026-07-29 — боевой приоритет критов Прямое авторское решение Q-SYMBIONT-XP-001 — опыт симбионтов за natural 20/1, 2026-07-30 | F35: Q-COMBAT-CRIT-001 Q-SYMBIONT-XP-001 | G35: Синхронизация с CORE-229: автоматическое боевое разрешение подтверждённых критов, порядок противостояния и прогрессия. Синхронизация маршрутизации и опыта симбионтов v1.6. | H35: Да | I35: Патч v1.6 (опыт симбионтов)
A36: CORE-074 | B36: Базовое правило | C36: Активно | D36: 100 | E36: §5.1, стр. 86. Прямое авторское решение Q-SYMBIONT-XP-001 — опыт симбионтов за natural 20/1, 2026-07-30 | F36: Q-SYMBIONT-XP-001 | G36: Синхронизация маршрутизации и опыта симбионтов v1.6. | H36: Нет | I36: Патч v1.6 (опыт симбионтов)
A37: CORE-075 | B37: Базовое правило | C37: Активно | D37: 100 | E37: §5.1, стр. 86; §5.4.6, стр. 102. Предразработочный QA и прямые ответы пользователя 2026-07-29 Прямое уточнение пользователя 2026-07-29 — боевой приоритет критов Прямое авторское решение Q-SYMBIONT-XP-001 — опыт симбионтов за natural 20/1, 2026-07-30 | F37: Q-PREDEV-002 Q-COMBAT-CRIT-001 Q-SYMBIONT-XP-001 | G37: Патч v1.4 Синхронизация с CORE-229: автоматическое боевое разрешение подтверждённых критов, порядок противостояния и прогрессия. Синхронизация маршрутизации и опыта симбионтов v1.6. | H37: Да | I37: Патч v1.6 (опыт симбионтов)
A38: CORE-076 | B38: Базовое правило | C38: Активно | D38: 10 | E38: §5.1, стр. 86. | H38: Нет
A39: CORE-077 | B39: Базовое правило | C39: Активно | D39: 10 | E39: §5.1, стр. 86. | H39: Нет
A40: CORE-078 | B40: Базовое правило | C40: Активно | D40: 10 | E40: §5.1, стр. 86–87; §6.1, стр. 105. | H40: Нет
A41: CORE-079 | B41: Базовое правило | C41: Активно | D41: 10 | E41: §5.1, стр. 87. | H41: Нет
A42: CORE-082 | B42: Базовое правило | C42: Активно | D42: 100 | E42: §5.2, стр. 87–88. Прямое уточнение пользователя 2026-07-28 — шаблоны врагов v1.3 Прямое уточнение пользователя 2026-07-29 — боевой приоритет критов Прямое авторское решение Q-SYMBIONT-XP-001 — опыт симбионтов за natural 20/1, 2026-07-30 | F42: Q-ENEMY-B7 Q-COMBAT-CRIT-001 Q-SYMBIONT-XP-001 | G42: Синхронизация конструкторов и шаблонов врагов v1.3. Синхронизация с CORE-229: автоматическое боевое разрешение подтверждённых критов, порядок противостояния и прогрессия. Синхронизация маршрутизации и опыта симбионтов v1.6. | H42: Да | I42: Патч v1.6 (опыт симбионтов)
A43: CORE-083 | B43: Базовое правило | C43: Активно | D43: 100 | E43: §5.2–5.2.1, стр. 87–88. Прямое уточнение пользователя 2026-07-29 — боевой приоритет критов Прямое авторское решение Q-SYMBIONT-XP-001 — опыт симбионтов за natural 20/1, 2026-07-30 | F43: Q-COMBAT-CRIT-001 Q-SYMBIONT-XP-001 | G43: Синхронизация с CORE-229: автоматическое боевое разрешение подтверждённых критов, порядок противостояния и прогрессия. Синхронизация маршрутизации и опыта симбионтов v1.6. | H43: Да | I43: Патч v1.6 (опыт симбионтов)
A44: CORE-084 | B44: Базовое правило | C44: Активно | D44: 100 | E44: §5.2–5.2.1, стр. 87–88. Прямое уточнение пользователя 2026-07-29 — боевой приоритет критов Прямое авторское решение Q-SYMBIONT-XP-001 — опыт симбионтов за natural 20/1, 2026-07-30 | F44: Q-COMBAT-CRIT-001 Q-SYMBIONT-XP-001 | G44: Синхронизация с CORE-229: автоматическое боевое разрешение подтверждённых критов, порядок противостояния и прогрессия. Синхронизация маршрутизации и опыта симбионтов v1.6. | H44: Да | I44: Патч v1.6 (опыт симбионтов)
A45: CORE-086 | B45: Базовое правило | C45: Активно | D45: 10 | E45: §5.4.1, стр. 92–93. | H45: Нет
A46: CORE-087 | B46: Базовое правило | C46: Активно | D46: 100 | E46: §5.4.1, стр. 93. Прямое авторское решение Q-SYMBIONT-XP-001 — опыт симбионтов за natural 20/1, 2026-07-30 | F46: Q-SYMBIONT-XP-001 | G46: Синхронизация маршрутизации и опыта симбионтов v1.6. | H46: Нет | I46: Патч v1.6 (опыт симбионтов)
A47: CORE-089 | B47: Базовое правило | C47: Активно | D47: 10 | E47: §5.4.1, стр. 93–94. | H47: Нет
A48: CORE-092 | B48: Базовое правило | C48: Активно | D48: 100 | E48: §5.4.2, стр. 94. Прямое авторское решение Q-SYMBIONT-XP-001 — опыт симбионтов за natural 20/1, 2026-07-30 | F48: Q-SYMBIONT-XP-001 | G48: Синхронизация маршрутизации и опыта симбионтов v1.6. | H48: Нет | I48: Патч v1.6 (опыт симбионтов)
A49: CORE-094 | B49: Базовое правило | C49: Активно | D49: 10 | E49: §5.4.2.1, стр. 94. | H49: Нет
A50: CORE-095 | B50: Базовое правило | C50: Активно | D50: 10 | E50: §5.4.2.2, стр. 94–95. | H50: Нет
A51: CORE-096 | B51: Базовое правило | C51: Активно | D51: 10 | E51: §5.4.2.2, стр. 94–95. | H51: Нет
A52: CORE-097 | B52: Базовое правило | C52: Активно | D52: 10 | E52: §5.4.2.2, стр. 94–95. | H52: Нет
A53: CORE-098 | B53: Базовое правило | C53: Активно | D53: 10 | E53: §5.4.2.3, стр. 95. | H53: Нет
A54: CORE-099 | B54: Базовое правило | C54: Активно | D54: 10 | E54: §5.4.2.3, стр. 95. | H54: Нет
A55: CORE-100 | B55: Базовое правило | C55: Активно | D55: 10 | E55: §5.4.2.4, стр. 95; §3.4.7.3.2, стр. 66. | H55: Нет
A56: CORE-102 | B56: Базовое правило | C56: Активно | D56: 10 | E56: §5.4.2.5, стр. 95. | H56: Нет
A57: CORE-103 | B57: Базовое правило | C57: Активно | D57: 10 | E57: §5.4.2.5, стр. 95–96. | H57: Нет
A58: CORE-104 | B58: Базовое правило | C58: Активно | D58: 100 | E58: §5.4.2.5, стр. 96. Прямое авторское решение Q-SYMBIONT-XP-001 — опыт симбионтов за natural 20/1, 2026-07-30 | F58: Q-SYMBIONT-XP-001 | G58: Синхронизация маршрутизации и опыта симбионтов v1.6. | H58: Нет | I58: Патч v1.6 (опыт симбионтов)
A59: CORE-105 | B59: Базовое правило | C59: Активно | D59: 10 | E59: §5.4.3.1, стр. 96; уточнение §5.4.3.6, стр. 98. | H59: Нет
A60: CORE-107 | B60: Базовое правило | C60: Активно | D60: 10 | E60: §5.4.3.2, стр. 96. | H60: Нет
A61: CORE-108 | B61: Базовое правило | C61: Активно | D61: 10 | E61: уточнение §5.4.3.6, стр. 98. | H61: Нет
A62: CORE-109 | B62: Базовое правило | C62: Активно | D62: 10 | E62: §5.4.3.3, стр. 96. | H62: Нет
A63: CORE-113 | B63: Базовое правило | C63: Не автоматизируется | D63: 10 | E63: §5.4.3.5, стр. 97. | F63: Q-CORE-030 | H63: Нет
A64: CORE-116 | B64: Базовое правило | C64: Активно | D64: 10 | E64: §5.4.3.6, стр. 97–98. | H64: Нет
A65: CORE-117 | B65: Базовое правило | C65: Активно | D65: 80 | E65: §5.4.4, стр. 98–99. Прямое уточнение пользователя 2026-07-28 — шаблоны врагов v1.3 Предразработочный QA и прямые ответы пользователя 2026-07-29 | F65: Q-ENEMY-B12 Q-PREDEV-004 | G65: Синхронизация конструкторов и шаблонов врагов v1.3. Патч v1.4 | H65: Да | I65: Патч v1.4
A66: CORE-118 | B66: Базовое правило | C66: Активно | D66: 80 | E66: §5.4.4.1, стр. 98. Предразработочный QA и прямые ответы пользователя 2026-07-29 | F66: Q-PREDEV-004 | G66: Патч v1.4 | H66: Да | I66: Патч v1.4
A67: CORE-121 | B67: Базовое правило | C67: Активно | D67: 10 | E67: §5.4.4.1.3, стр. 98; уточнение стр. 99. | H67: Нет
A68: CORE-125 | B68: Базовое правило | C68: Активно | D68: 100 | E68: §5.4.5.5.3, уточнение стр. 102; §5.4.6–5.4.7, стр. 102–103. Прямое уточнение пользователя 2026-07-28 Прямое уточнение пользователя 2026-07-28 — шаблоны врагов v1.3 Предразработочный QA и прямые ответы пользователя 2026-07-29 Прямое уточнение пользователя 2026-07-29 — боевой приоритет критов Прямое авторское решение Q-SYMBIONT-XP-001 — опыт симбионтов за natural 20/1, 2026-07-30 | F68: Q-ENEMY-B5 Q-ENEMY-B6 Q-PREDEV-002 Q-PREDEV-018 Q-COMBAT-CRIT-001 Q-SYMBIONT-XP-001 | G68: Синхронизация профиля оружия v1.2. Синхронизация конструкторов и шаблонов врагов v1.3. Патч v1.4 Синхронизация с CORE-229: автоматическое боевое разрешение подтверждённых критов, порядок противостояния и прогрессия. Синхронизация маршрутизации и опыта симбионтов v1.6. | H68: Да | I68: Патч v1.6 (опыт симбионтов)
A69: CORE-126 | B69: Базовое правило | C69: Активно | D69: 80 | E69: §5.4.5.1, стр. 99; §5.4.4, стр. 98–99. Прямое уточнение пользователя 2026-07-28 Прямое уточнение пользователя 2026-07-28 — шаблоны врагов v1.3 Предразработочный QA и прямые ответы пользователя 2026-07-29 | F69: Q-ENEMY-B12 Q-PREDEV-004 | G69: Синхронизация профиля оружия v1.2. Синхронизация конструкторов и шаблонов врагов v1.3. Патч v1.4 | H69: Да | I69: Патч v1.4
A70: CORE-130 | B70: Базовое правило | C70: Активно | D70: 10 | E70: §5.4.5.3, стр. 100–102. | H70: Нет
A71: CORE-131 | B71: Базовое правило | C71: Активно | D71: 80 | E71: §5.4.5.3, стр. 100. Прямое уточнение пользователя 2026-07-28 — шаблоны врагов v1.3 Предразработочный QA и прямые ответы пользователя 2026-07-29 | F71: Q-ENEMY-B12 Q-PREDEV-004 | G71: Синхронизация конструкторов и шаблонов врагов v1.3. Патч v1.4 | H71: Да | I71: Патч v1.4
A72: CORE-132 | B72: Базовое правило | C72: Активно | D72: 10 | E72: §5.4.5.3, стр. 100, уточнение стр. 102. | H72: Нет
A73: CORE-134 | B73: Базовое правило | C73: Активно | D73: 70 | E73: §5.4.5.4, стр. 101. Прямое уточнение пользователя 2026-07-28 — шаблоны врагов v1.3 | F73: Q-ENEMY-B8 | G73: Синхронизация конструкторов и шаблонов врагов v1.3. | H73: Да | I73: Патч v1.3
A74: CORE-135 | B74: Базовое правило | C74: Активно | D74: 80 | E74: §5.4.5.5.1, стр. 101. Прямое уточнение пользователя 2026-07-28 Прямое уточнение пользователя 2026-07-28 — шаблоны врагов v1.3 Предразработочный QA и прямые ответы пользователя 2026-07-29 | F74: Q-ENEMY-B6 Q-ENEMY-B12 Q-PREDEV-004 | G74: Синхронизация профиля оружия v1.2. Синхронизация конструкторов и шаблонов врагов v1.3. Патч v1.4 | H74: Да | I74: Патч v1.4
A75: CORE-136 | B75: Базовое правило | C75: Активно | D75: 70 | E75: §5.4.5.5.2, стр. 101. Прямое уточнение пользователя 2026-07-28 — шаблоны врагов v1.3 | F75: Q-ENEMY-B6 | G75: Синхронизация конструкторов и шаблонов врагов v1.3. | H75: Да | I75: Патч v1.3
A76: CORE-141 | B76: Базовое правило | C76: Активно | D76: 10 | E76: §5.4.5.5.3(4), стр. 102. | H76: Нет
A77: CORE-142 | B77: Базовое правило | C77: Активно | D77: 10 | E77: §5.4.5.5.3(5), стр. 102. | H77: Нет
A78: CORE-145 | B78: Базовое правило | C78: Активно | D78: 100 | E78: §5.4.6.1, стр. 103. Прямое уточнение пользователя 2026-07-29 — боевой приоритет критов Прямое авторское решение Q-SYMBIONT-XP-001 — опыт симбионтов за natural 20/1, 2026-07-30 | F78: Q-COMBAT-CRIT-001 Q-SYMBIONT-XP-001 | G78: Синхронизация с CORE-229: автоматическое боевое разрешение подтверждённых критов, порядок противостояния и прогрессия. Синхронизация маршрутизации и опыта симбионтов v1.6. | H78: Да | I78: Патч v1.6 (опыт симбионтов)
A79: CORE-146 | B79: Базовое правило | C79: Активно | D79: 100 | E79: §5.4.6.2, стр. 103. Прямое уточнение пользователя 2026-07-29 — боевой приоритет критов Прямое авторское решение Q-SYMBIONT-XP-001 — опыт симбионтов за natural 20/1, 2026-07-30 | F79: Q-COMBAT-CRIT-001 Q-SYMBIONT-XP-001 | G79: Синхронизация с CORE-229: автоматическое боевое разрешение подтверждённых критов, порядок противостояния и прогрессия. Синхронизация маршрутизации и опыта симбионтов v1.6. | H79: Да | I79: Патч v1.6 (опыт симбионтов)
A80: CORE-149 | B80: Базовое правило | C80: Активно | D80: 100 | E80: §5.4.6.3, стр. 103. Прямое уточнение пользователя 2026-07-29 — боевой приоритет критов Прямое авторское решение Q-SYMBIONT-XP-001 — опыт симбионтов за natural 20/1, 2026-07-30 | F80: Q-COMBAT-CRIT-001 Q-SYMBIONT-XP-001 | G80: Синхронизация с CORE-229: автоматическое боевое разрешение подтверждённых критов, порядок противостояния и прогрессия. Синхронизация маршрутизации и опыта симбионтов v1.6. | H80: Да | I80: Патч v1.6 (опыт симбионтов)
A81: CORE-150 | B81: Базовое правило | C81: Активно | D81: 100 | E81: §5.4.7, стр. 103. Прямое уточнение пользователя 2026-07-28 Прямое уточнение пользователя 2026-07-28 — шаблоны врагов v1.3 Предразработочный QA и прямые ответы пользователя 2026-07-29 Прямое авторское решение Q-SYMBIONT-XP-001 — опыт симбионтов за natural 20/1, 2026-07-30 | F81: Q-ENEMY-B5 Q-ENEMY-P14 Q-PREDEV-018 Q-SYMBIONT-XP-001 | G81: Синхронизация профиля оружия v1.2. Синхронизация конструкторов и шаблонов врагов v1.3. Патч v1.4 Синхронизация маршрутизации и опыта симбионтов v1.6. | H81: Да | I81: Патч v1.6 (опыт симбионтов)
A82: CORE-155 | B82: Базовое правило | C82: Активно | D82: 10 | E82: §5.5, стр. 104. | H82: Нет
A83: CORE-156 | B83: Базовое правило | C83: Активно | D83: 10 | E83: §5.5, стр. 104. | H83: Нет
A84: CORE-157 | B84: Базовое правило | C84: Активно | D84: 10 | E84: §5.5, стр. 104. | H84: Нет
A85: CORE-158 | B85: Базовое правило | C85: Активно | D85: 10 | E85: §5.5, стр. 104. | H85: Нет
A86: CORE-164 | B86: Базовое правило | C86: Активно | D86: 70 | E86: §6.1, стр. 105; §5.1, стр. 86. Прямое уточнение пользователя 2026-07-28 — шаблоны врагов v1.3 | F86: Q-ENEMY-B1 | G86: Синхронизация конструкторов и шаблонов врагов v1.3. | H86: Да | I86: Патч v1.3
A87: CORE-165 | B87: Базовое правило | C87: Активно | D87: 10 | E87: §6.2, стр. 105–106. | H87: Нет
A88: CORE-167 | B88: Базовое правило | C88: Активно | D88: 10 | E88: §6.2, таблица 6, стр. 106–108. | H88: Нет
A89: CORE-168 | B89: Базовое правило | C89: Активно | D89: 10 | E89: §6.3, стр. 108–109. | H89: Нет
A90: CORE-169 | B90: Базовое правило | C90: Активно | D90: 10 | E90: §6.3, таблица 7, стр. 108–109. | H90: Нет
A91: CORE-170 | B91: Базовое правило | C91: Активно | D91: 10 | E91: §6.3, стр. 109; §3.2.6.2, стр. 48. | H91: Нет
A92: CORE-171 | B92: Базовое правило | C92: Активно | D92: 10 | E92: §6.3, стр. 109. | H92: Нет
A93: CORE-173 | B93: Базовое правило | C93: Активно | D93: 60 | E93: §6.4, стр. 110. Прямое уточнение пользователя 2026-07-28 | G93: Синхронизация профиля оружия v1.2. | H93: Да | I93: Патч v1.2
A94: CORE-174 | B94: Базовое правило | C94: Активно | D94: 10 | E94: §3.1 (механическое указание), стр. 43. | H94: Нет
A95: CORE-176 | B95: Базовое правило | C95: Активно | D95: 10 | E95: §5.4.1, стр. 93. | H95: Нет
