Workbook

Sheet 00_Паспорт
A1: Symbiosis V7 — реестр предметов для Windows-приложения
A2: Версия 1.6 · актуализировано 2026-08-01 · Rules v1.7 | Character-Skills-Symbionts v1.2 | Items v1.6_with_icons | Bestiary v1.4 | Sentient v1.2 · исходные каталоги, баланс, формулы и 64 иконки не изменены; синхронизированы только границы группового генератора.
A4: Контрольный показатель | B4: Значение | D4: Нормативная модель выдачи готового предмета
A5: Канонические предметы (A) | B5: 49 | D5: 1 | E5: Игрок выбирает оружие только при создании собственного персонажа. | F5: Не-Чистое оружие: редактируются только формульно выводимые поля; оружие Чистых отображается только для чтения.
A6: Явные предметные сущности (B) | B6: 15 | D6: 2 | E6: Приложение не бросает производственные дайсы и не создаёт предмет. | F6: Валидатор ищет единый witness по L/Lw/Ls и независимым дайсам для всего заявленного профиля.
A7: Всего строк основного каталога | B7: 64 | D7: 3 | E7: Успешная заявка создаёт неизменяемую WeaponProfileVersion. | F7: Сохраняются formulaId, formulaVersion и validationWitness; statSource=PLAYER_FORMULA_VALIDATED.
A8: Оружие/щиты/комплекты | B8: 27 | D8: 4 | E8: Мастер выдаёт или изменяет конкретный экземпляр оружия игрока либо НПС. | F8: Разрешено всё оружие, включая шесть шаблонов Чистых; глобальный шаблон и другие экземпляры не меняются.
A9: Броня | B9: 8 | D9: 5 | E9: MASTER_OVERRIDE обходит формульную область, но не структурную валидацию. | F9: Закрытая грамматика дайсов, положительность значений, actor/reason/time и неизменяемые before/after обязательны.
A10: Фармацевтика | B10: 14 | D10: 6 | E10: Изменение профиля атомарно и версионируется. | F10: Новая версия действует со следующей отдельно разрешаемой атаки; уже начатая атака использует прежний снимок.
A11: Формульные типы оружия | B11: 21 | D11: 7 | E11: Боевые DAMAGE/PENETRATION читаются из снимка активной версии. | F11: PER_ATTACK_ROLL означает новый бросок на каждую отдельно разрешаемую атаку; ItemInstance не получает результат.
A12: Профили формул с учётом 2 хватов | B12: 22 | D12: 8 | E12: Неполные и нарративные сущности не получают выдуманную механику. | F12: Их оформляет мастер как story/custom item.
A13: Автоматизация создания предметов | B13: НЕТ
A14: Формулы изготовления в приложении | B14: Только VALIDATION_ONLY
A15: Player request | B15: Только создание персонажа: FORMULA_VALIDATED или PURE TEMPLATE_FIXED
A16: Master override | B16: Все 27 видов оружия; instance-level patch без formula bounds
A17: Нормализованные боевые значения | B17: 65
A18: Runtime-результаты в экземпляре | B18: НЕ СОХРАНЯЮТСЯ
A19: Ключевые границы применения
A20: Область | B20: Решение | C20: Область | D20: Решение | E20: Область | F20: Решение | G20: Область | H20: Решение
A21: Крафт | B21: Не исполняется | C21: Цены | D21: Не заданы | E21: Масса | F21: Nullable/мастер | G21: Вместимость | H21: Не автоматизировать
A22: Стек | B22: UI-группа по stackKey; перед состоянием расщепить | C22: Броня | D22: 6 зон, слои | E22: Щиты | F22: Отдельный HP | G22: Нэйт | H22: Бинарная герметичность
A23: Боеприпас | B23: Расходуется при атаке | C23: Магазин | D23: Статус неполный | E23: Ремонт | F23: Manual only | G23: Горение | H23: Не по каждому предмету
A24: Описательный предмет | B24: Без механики | C24: Custom item | D24: 1 положительный бонус | E24: Владение | F24: Ровно один owner/scene | G24: Лут | H24: Частичный стек q
A25: Pure-only препарат | B25: Можно хранить/передать | C25: Применение | D25: Блок другой расе | E25: Качество | F25: Рекомендация мастеру | G25: Экипировка | H25: Не автоматическая
A26: Игрок | B26: Только создание; formula outputs | C26: Мастер | D26: Все оружие; patch экземпляра | E26: Оружие Чистых | F26: Игрок read-only, мастер override | G26: Формульный шаблон | H26: Exact joint validator
A27: Приоритет | B27: Rules v1.7 > v1.6 > v1.5 > v1.4 > v1.3 > v1.2 > tombstone/base | C27: Источник | D27: Источник | E27: Rules Registry v1.7 + Character Registry v1.2 + Bestiary v1.4 + PDF Atlas v1.1 | F27: MONSTER_ATTACK и naturalArmor не являются ItemType | G27: Аудит | H27: Профиль + AttackResolution + clone provenance
A28: Иконки | B28: 64 PNG 96×96; только 64 выбираемых ItemTypeID | C28: Паутина Паука | D28: CustomMonster не создаёт ItemInstance или MapObject | E28: Лут монстра | F28: NOT_LOOTABLE проверяется до контейнера | G28: Системный SentientEnemy | H28: Системный SentientEnemy: NO_XP_PROGRESSION; независимый item graph без новых ItemType/иконок

Sheet 01_Каталог
A1: Основной каталог предметов
A2: Каталог задаёт канонический шаблон. Эффективный профиль оружия читается из активной WeaponProfileVersion: TEMPLATE_FIXED блокирует изменение только игроку, но мастер вправе patch-ить любой конкретный экземпляр по CORE-187/188.
A4: ItemTypeID | B4: Rule ID | C4: Название | D4: Категория | E4: Подкатегория | F4: Класс каталога | G4: Полнота механики | H4: Можно в инвентарь | I4: Физически взаимозаменяем | J4: UI-группировка по stackKey | K4: Единица | L4: Экипируется | M4: Составной | N4: Источник готовых параметров экземпляра | O4: Политика заявки игрока | P4: Master profile override allowed | Q4: Formula ID | R4: Generation enabled | S4: Источник | T4: Примечание | U4: ID уникален
A5: ITM-WPN-001 | B5: CORE-021 | C5: Лёгкий арбалет | D5: Оружие | E5: Арбалет | F5: A_CANONICAL | G5: FULL | H5: =TRUE() -> TRUE | I5: =FALSE() -> FALSE | J5: =TRUE() -> TRUE | K5: экземпляр | L5: =TRUE() -> TRUE | M5: =FALSE() -> FALSE | N5: INSTANCE_RESOLVED | O5: EXACT_JOINT_FORMULA | P5: =TRUE() -> TRUE | Q5: F-WPN-001 | R5: =FALSE() -> FALSE | S5: PDF §4, с. 68; CORE-021 | U5: =IF(COUNTIF($A$5:$A$68,A5)=1,"PASS","DUPLICATE") -> PASS
A6: ITM-WPN-002 | B6: CORE-022 | C6: Тяжёлый арбалет | D6: Оружие | E6: Арбалет | F6: A_CANONICAL | G6: FULL | H6: =TRUE() -> TRUE | I6: =FALSE() -> FALSE | J6: =TRUE() -> TRUE | K6: экземпляр | L6: =TRUE() -> TRUE | M6: =FALSE() -> FALSE | N6: INSTANCE_RESOLVED | O6: EXACT_JOINT_FORMULA | P6: =TRUE() -> TRUE | Q6: F-WPN-002 | R6: =FALSE() -> FALSE | S6: PDF §4, с. 69; CORE-022 | U6: =IF(COUNTIF($A$5:$A$68,A6)=1,"PASS","DUPLICATE") -> PASS
A7: ITM-WPN-003 | B7: CORE-023 | C7: Кенси | D7: Оружие | E7: Арбалет | F7: A_CANONICAL | G7: FULL | H7: =TRUE() -> TRUE | I7: =FALSE() -> FALSE | J7: =TRUE() -> TRUE | K7: экземпляр | L7: =TRUE() -> TRUE | M7: =FALSE() -> FALSE | N7: TEMPLATE_FIXED | O7: TEMPLATE_FIXED | P7: =TRUE() -> TRUE | R7: =FALSE() -> FALSE | S7: PDF §4, с. 69; CORE-023 | U7: =IF(COUNTIF($A$5:$A$68,A7)=1,"PASS","DUPLICATE") -> PASS
A8: ITM-WPN-004 | B8: CORE-024 | C8: Эривел | D8: Оружие | E8: Арбалет | F8: A_CANONICAL | G8: FULL | H8: =TRUE() -> TRUE | I8: =FALSE() -> FALSE | J8: =TRUE() -> TRUE | K8: экземпляр | L8: =TRUE() -> TRUE | M8: =FALSE() -> FALSE | N8: TEMPLATE_FIXED | O8: TEMPLATE_FIXED | P8: =TRUE() -> TRUE | R8: =FALSE() -> FALSE | S8: PDF §4, с. 69; CORE-024 | U8: =IF(COUNTIF($A$5:$A$68,A8)=1,"PASS","DUPLICATE") -> PASS
A9: ITM-WPN-005 | B9: CORE-025 | C9: Эстрефорд | D9: Оружие | E9: Арбалет | F9: A_CANONICAL | G9: FULL | H9: =TRUE() -> TRUE | I9: =FALSE() -> FALSE | J9: =TRUE() -> TRUE | K9: экземпляр | L9: =TRUE() -> TRUE | M9: =FALSE() -> FALSE | N9: TEMPLATE_FIXED | O9: TEMPLATE_FIXED | P9: =TRUE() -> TRUE | R9: =FALSE() -> FALSE | S9: PDF §4, с. 70; CORE-025 | U9: =IF(COUNTIF($A$5:$A$68,A9)=1,"PASS","DUPLICATE") -> PASS
A10: ITM-WPN-006 | B10: CORE-026 | C10: Айнцберн | D10: Оружие | E10: Арбалет | F10: A_CANONICAL | G10: FULL | H10: =TRUE() -> TRUE | I10: =FALSE() -> FALSE | J10: =TRUE() -> TRUE | K10: экземпляр | L10: =TRUE() -> TRUE | M10: =FALSE() -> FALSE | N10: TEMPLATE_FIXED | O10: TEMPLATE_FIXED | P10: =TRUE() -> TRUE | R10: =FALSE() -> FALSE | S10: PDF §4, с. 70; CORE-026 | U10: =IF(COUNTIF($A$5:$A$68,A10)=1,"PASS","DUPLICATE") -> PASS
A11: ITM-WPN-007 | B11: CORE-027 | C11: Лёгкий лук | D11: Оружие | E11: Лук | F11: A_CANONICAL | G11: FULL | H11: =TRUE() -> TRUE | I11: =FALSE() -> FALSE | J11: =TRUE() -> TRUE | K11: экземпляр | L11: =TRUE() -> TRUE | M11: =FALSE() -> FALSE | N11: INSTANCE_RESOLVED | O11: EXACT_JOINT_FORMULA | P11: =TRUE() -> TRUE | Q11: F-WPN-003 | R11: =FALSE() -> FALSE | S11: PDF §4, с. 71; CORE-027 | U11: =IF(COUNTIF($A$5:$A$68,A11)=1,"PASS","DUPLICATE") -> PASS
A12: ITM-WPN-008 | B12: CORE-028 | C12: Тяжёлый лук | D12: Оружие | E12: Лук | F12: A_CANONICAL | G12: FULL | H12: =TRUE() -> TRUE | I12: =FALSE() -> FALSE | J12: =TRUE() -> TRUE | K12: экземпляр | L12: =TRUE() -> TRUE | M12: =FALSE() -> FALSE | N12: INSTANCE_RESOLVED | O12: EXACT_JOINT_FORMULA | P12: =TRUE() -> TRUE | Q12: F-WPN-004 | R12: =FALSE() -> FALSE | S12: PDF §4, с. 71; CORE-028 | U12: =IF(COUNTIF($A$5:$A$68,A12)=1,"PASS","DUPLICATE") -> PASS
A13: ITM-WPN-009 | B13: CORE-029 | C13: Длинный лук | D13: Оружие | E13: Лук | F13: A_CANONICAL | G13: FULL | H13: =TRUE() -> TRUE | I13: =FALSE() -> FALSE | J13: =TRUE() -> TRUE | K13: экземпляр | L13: =TRUE() -> TRUE | M13: =FALSE() -> FALSE | N13: INSTANCE_RESOLVED | O13: EXACT_JOINT_FORMULA | P13: =TRUE() -> TRUE | Q13: F-WPN-005 | R13: =FALSE() -> FALSE | S13: PDF §4, с. 72; CORE-029 | U13: =IF(COUNTIF($A$5:$A$68,A13)=1,"PASS","DUPLICATE") -> PASS
A14: ITM-WPN-010 | B14: CORE-031 | C14: Грубое оружие | D14: Оружие | E14: Ближнее оружие | F14: A_CANONICAL | G14: FULL | H14: =TRUE() -> TRUE | I14: =FALSE() -> FALSE | J14: =TRUE() -> TRUE | K14: экземпляр | L14: =TRUE() -> TRUE | M14: =FALSE() -> FALSE | N14: INSTANCE_RESOLVED | O14: EXACT_JOINT_FORMULA | P14: =TRUE() -> TRUE | Q14: F-WPN-006 | R14: =FALSE() -> FALSE | S14: PDF §4, с. 73; CORE-031 | T14: Примеры: дубина, дрын, булава, кистень, молот. | U14: =IF(COUNTIF($A$5:$A$68,A14)=1,"PASS","DUPLICATE") -> PASS
A15: ITM-WPN-011 | B15: CORE-032 | C15: Одноручный меч | D15: Оружие | E15: Ближнее оружие | F15: A_CANONICAL | G15: FULL | H15: =TRUE() -> TRUE | I15: =FALSE() -> FALSE | J15: =TRUE() -> TRUE | K15: экземпляр | L15: =TRUE() -> TRUE | M15: =FALSE() -> FALSE | N15: INSTANCE_RESOLVED | O15: EXACT_JOINT_FORMULA | P15: =TRUE() -> TRUE | Q15: F-WPN-007 | R15: =FALSE() -> FALSE | S15: PDF §4, с. 73; CORE-032 | U15: =IF(COUNTIF($A$5:$A$68,A15)=1,"PASS","DUPLICATE") -> PASS
A16: ITM-WPN-012 | B16: CORE-033 | C16: Полуторный меч | D16: Оружие | E16: Ближнее оружие | F16: A_CANONICAL | G16: FULL | H16: =TRUE() -> TRUE | I16: =FALSE() -> FALSE | J16: =TRUE() -> TRUE | K16: экземпляр | L16: =TRUE() -> TRUE | M16: =FALSE() -> FALSE | N16: INSTANCE_RESOLVED | O16: EXACT_JOINT_FORMULA | P16: =TRUE() -> TRUE | Q16: F-WPN-008A; F-WPN-008B | R16: =FALSE() -> FALSE | S16: PDF §4, с. 73; CORE-033 | T16: Хват 1/2 руки фиксируется при заявке или выдаче; позднее не переключается. | U16: =IF(COUNTIF($A$5:$A$68,A16)=1,"PASS","DUPLICATE") -> PASS
A17: ITM-WPN-013 | B17: CORE-034 | C17: Двуручный меч | D17: Оружие | E17: Ближнее оружие | F17: A_CANONICAL | G17: FULL | H17: =TRUE() -> TRUE | I17: =FALSE() -> FALSE | J17: =TRUE() -> TRUE | K17: экземпляр | L17: =TRUE() -> TRUE | M17: =FALSE() -> FALSE | N17: INSTANCE_RESOLVED | O17: EXACT_JOINT_FORMULA | P17: =TRUE() -> TRUE | Q17: F-WPN-009 | R17: =FALSE() -> FALSE | S17: PDF §4, с. 74; CORE-034 | U17: =IF(COUNTIF($A$5:$A$68,A17)=1,"PASS","DUPLICATE") -> PASS
A18: ITM-WPN-014 | B18: CORE-035 | C18: Шпага | D18: Оружие | E18: Ближнее оружие | F18: A_CANONICAL | G18: FULL | H18: =TRUE() -> TRUE | I18: =FALSE() -> FALSE | J18: =TRUE() -> TRUE | K18: экземпляр | L18: =TRUE() -> TRUE | M18: =FALSE() -> FALSE | N18: INSTANCE_RESOLVED | O18: EXACT_JOINT_FORMULA | P18: =TRUE() -> TRUE | Q18: F-WPN-010 | R18: =FALSE() -> FALSE | S18: PDF §4, с. 74; CORE-035 | U18: =IF(COUNTIF($A$5:$A$68,A18)=1,"PASS","DUPLICATE") -> PASS
A19: ITM-WPN-015 | B19: CORE-036 | C19: Копьё | D19: Оружие | E19: Ближнее оружие | F19: A_CANONICAL | G19: FULL | H19: =TRUE() -> TRUE | I19: =FALSE() -> FALSE | J19: =TRUE() -> TRUE | K19: экземпляр | L19: =TRUE() -> TRUE | M19: =FALSE() -> FALSE | N19: INSTANCE_RESOLVED | O19: EXACT_JOINT_FORMULA | P19: =TRUE() -> TRUE | Q19: F-WPN-011 | R19: =FALSE() -> FALSE | S19: PDF §4, с. 74; CORE-036 | U19: =IF(COUNTIF($A$5:$A$68,A19)=1,"PASS","DUPLICATE") -> PASS
A20: ITM-WPN-016 | B20: CORE-037 | C20: Кинжал | D20: Оружие | E20: Ближнее оружие | F20: A_CANONICAL | G20: FULL | H20: =TRUE() -> TRUE | I20: =FALSE() -> FALSE | J20: =TRUE() -> TRUE | K20: экземпляр | L20: =TRUE() -> TRUE | M20: =FALSE() -> FALSE | N20: INSTANCE_RESOLVED | O20: EXACT_JOINT_FORMULA | P20: =TRUE() -> TRUE | Q20: F-WPN-012 | R20: =FALSE() -> FALSE | S20: PDF §4, с. 74; CORE-037 | U20: =IF(COUNTIF($A$5:$A$68,A20)=1,"PASS","DUPLICATE") -> PASS
A21: ITM-WPN-017 | B21: CORE-038 | C21: Мизерикордия | D21: Оружие | E21: Ближнее оружие | F21: A_CANONICAL | G21: FULL | H21: =TRUE() -> TRUE | I21: =FALSE() -> FALSE | J21: =TRUE() -> TRUE | K21: экземпляр | L21: =TRUE() -> TRUE | M21: =FALSE() -> FALSE | N21: INSTANCE_RESOLVED | O21: EXACT_JOINT_FORMULA | P21: =TRUE() -> TRUE | Q21: F-WPN-013 | R21: =FALSE() -> FALSE | S21: PDF §4, с. 75; CORE-038 | U21: =IF(COUNTIF($A$5:$A$68,A21)=1,"PASS","DUPLICATE") -> PASS
A22: ITM-WPN-018 | B22: CORE-039 | C22: Одноручный топор | D22: Оружие | E22: Ближнее оружие | F22: A_CANONICAL | G22: FULL | H22: =TRUE() -> TRUE | I22: =FALSE() -> FALSE | J22: =TRUE() -> TRUE | K22: экземпляр | L22: =TRUE() -> TRUE | M22: =FALSE() -> FALSE | N22: INSTANCE_RESOLVED | O22: EXACT_JOINT_FORMULA | P22: =TRUE() -> TRUE | Q22: F-WPN-014 | R22: =FALSE() -> FALSE | S22: PDF §4, с. 75; CORE-039 | U22: =IF(COUNTIF($A$5:$A$68,A22)=1,"PASS","DUPLICATE") -> PASS
A23: ITM-WPN-019 | B23: CORE-040 | C23: Клевец | D23: Оружие | E23: Ближнее оружие | F23: A_CANONICAL | G23: FULL | H23: =TRUE() -> TRUE | I23: =FALSE() -> FALSE | J23: =TRUE() -> TRUE | K23: экземпляр | L23: =TRUE() -> TRUE | M23: =FALSE() -> FALSE | N23: INSTANCE_RESOLVED | O23: EXACT_JOINT_FORMULA | P23: =TRUE() -> TRUE | Q23: F-WPN-015 | R23: =FALSE() -> FALSE | S23: PDF §4, с. 75; CORE-040 | U23: =IF(COUNTIF($A$5:$A$68,A23)=1,"PASS","DUPLICATE") -> PASS
A24: ITM-WPN-020 | B24: CORE-041 | C24: Двуручный топор | D24: Оружие | E24: Ближнее оружие | F24: A_CANONICAL | G24: FULL | H24: =TRUE() -> TRUE | I24: =FALSE() -> FALSE | J24: =TRUE() -> TRUE | K24: экземпляр | L24: =TRUE() -> TRUE | M24: =FALSE() -> FALSE | N24: INSTANCE_RESOLVED | O24: EXACT_JOINT_FORMULA | P24: =TRUE() -> TRUE | Q24: F-WPN-016 | R24: =FALSE() -> FALSE | S24: PDF §4, с. 75; CORE-041 | U24: =IF(COUNTIF($A$5:$A$68,A24)=1,"PASS","DUPLICATE") -> PASS
A25: ITM-WPN-021 | B25: CORE-042 | C25: Кастет | D25: Оружие | E25: Ближнее оружие | F25: A_CANONICAL | G25: FULL | H25: =TRUE() -> TRUE | I25: =FALSE() -> FALSE | J25: =TRUE() -> TRUE | K25: экземпляр | L25: =TRUE() -> TRUE | M25: =FALSE() -> FALSE | N25: INSTANCE_RESOLVED | O25: EXACT_JOINT_FORMULA | P25: =TRUE() -> TRUE | Q25: F-WPN-017 | R25: =FALSE() -> FALSE | S25: PDF §4, с. 76; CORE-042 | U25: =IF(COUNTIF($A$5:$A$68,A25)=1,"PASS","DUPLICATE") -> PASS
A26: ITM-WPN-022 | B26: CORE-043 | C26: Деревянный круглый щит | D26: Оружие | E26: Щит | F26: A_CANONICAL | G26: FULL | H26: =TRUE() -> TRUE | I26: =FALSE() -> FALSE | J26: =TRUE() -> TRUE | K26: экземпляр | L26: =TRUE() -> TRUE | M26: =FALSE() -> FALSE | N26: INSTANCE_RESOLVED | O26: EXACT_JOINT_FORMULA | P26: =TRUE() -> TRUE | Q26: F-WPN-018 | R26: =FALSE() -> FALSE | S26: PDF §4, с. 77; CORE-043 | U26: =IF(COUNTIF($A$5:$A$68,A26)=1,"PASS","DUPLICATE") -> PASS
A27: ITM-WPN-023 | B27: CORE-044 | C27: Железный круглый щит | D27: Оружие | E27: Щит | F27: A_CANONICAL | G27: FULL | H27: =TRUE() -> TRUE | I27: =FALSE() -> FALSE | J27: =TRUE() -> TRUE | K27: экземпляр | L27: =TRUE() -> TRUE | M27: =FALSE() -> FALSE | N27: INSTANCE_RESOLVED | O27: EXACT_JOINT_FORMULA | P27: =TRUE() -> TRUE | Q27: F-WPN-019 | R27: =FALSE() -> FALSE | S27: PDF §4, с. 77; CORE-044 | U27: =IF(COUNTIF($A$5:$A$68,A27)=1,"PASS","DUPLICATE") -> PASS
A28: ITM-WPN-024 | B28: CORE-045 | C28: Деревянный треугольный щит | D28: Оружие | E28: Щит | F28: A_CANONICAL | G28: FULL | H28: =TRUE() -> TRUE | I28: =FALSE() -> FALSE | J28: =TRUE() -> TRUE | K28: экземпляр | L28: =TRUE() -> TRUE | M28: =FALSE() -> FALSE | N28: INSTANCE_RESOLVED | O28: EXACT_JOINT_FORMULA | P28: =TRUE() -> TRUE | Q28: F-WPN-020 | R28: =FALSE() -> FALSE | S28: PDF §4, с. 78; CORE-045 | U28: =IF(COUNTIF($A$5:$A$68,A28)=1,"PASS","DUPLICATE") -> PASS
A29: ITM-WPN-025 | B29: CORE-046 | C29: Железный треугольный щит | D29: Оружие | E29: Щит | F29: A_CANONICAL | G29: FULL | H29: =TRUE() -> TRUE | I29: =FALSE() -> FALSE | J29: =TRUE() -> TRUE | K29: экземпляр | L29: =TRUE() -> TRUE | M29: =FALSE() -> FALSE | N29: INSTANCE_RESOLVED | O29: EXACT_JOINT_FORMULA | P29: =TRUE() -> TRUE | Q29: F-WPN-021 | R29: =FALSE() -> FALSE | S29: PDF §4, с. 78; CORE-046 | U29: =IF(COUNTIF($A$5:$A$68,A29)=1,"PASS","DUPLICATE") -> PASS
A30: ITM-WPN-026 | B30: CORE-047 | C30: Корнадора | D30: Оружие | E30: Составной комплект | F30: A_CANONICAL | G30: FULL | H30: =TRUE() -> TRUE | I30: =FALSE() -> FALSE | J30: =TRUE() -> TRUE | K30: экземпляр | L30: =TRUE() -> TRUE | M30: =TRUE() -> TRUE | N30: TEMPLATE_FIXED | O30: TEMPLATE_FIXED | P30: =TRUE() -> TRUE | R30: =FALSE() -> FALSE | S30: PDF §4, с. 79; CORE-047 | T30: Комплект из меча и щита; компоненты имеют самостоятельные runtime-состояния. | U30: =IF(COUNTIF($A$5:$A$68,A30)=1,"PASS","DUPLICATE") -> PASS
A31: ITM-WPN-027 | B31: CORE-048 | C31: Бларадэ | D31: Оружие | E31: Составной комплект | F31: A_CANONICAL | G31: FULL | H31: =TRUE() -> TRUE | I31: =FALSE() -> FALSE | J31: =TRUE() -> TRUE | K31: экземпляр | L31: =TRUE() -> TRUE | M31: =TRUE() -> TRUE | N31: TEMPLATE_FIXED | O31: TEMPLATE_FIXED | P31: =TRUE() -> TRUE | R31: =FALSE() -> FALSE | S31: PDF §4, с. 80; CORE-048 | T31: Комплект из шпаги и щита; компоненты имеют самостоятельные runtime-состояния. | U31: =IF(COUNTIF($A$5:$A$68,A31)=1,"PASS","DUPLICATE") -> PASS
A32: ITM-ARM-001 | B32: CORE-049 | C32: Кожаный доспех | D32: Броня | E32: Зональный элемент | F32: A_CANONICAL | G32: FULL | H32: =TRUE() -> TRUE | I32: =FALSE() -> FALSE | J32: =TRUE() -> TRUE | K32: экземпляр | L32: =TRUE() -> TRUE | M32: =FALSE() -> FALSE | N32: INSTANCE_ZONE | O32: TEMPLATE_FIXED | P32: =FALSE() -> FALSE | R32: =FALSE() -> FALSE | S32: PDF §4, с. 81; CORE-049 | U32: =IF(COUNTIF($A$5:$A$68,A32)=1,"PASS","DUPLICATE") -> PASS
A33: ITM-ARM-002 | B33: CORE-050 | C33: Бригантина | D33: Броня | E33: Зональный элемент | F33: A_CANONICAL | G33: FULL | H33: =TRUE() -> TRUE | I33: =FALSE() -> FALSE | J33: =TRUE() -> TRUE | K33: экземпляр | L33: =TRUE() -> TRUE | M33: =FALSE() -> FALSE | N33: INSTANCE_ZONE | O33: TEMPLATE_FIXED | P33: =FALSE() -> FALSE | R33: =FALSE() -> FALSE | S33: PDF §4, с. 81; CORE-050 | U33: =IF(COUNTIF($A$5:$A$68,A33)=1,"PASS","DUPLICATE") -> PASS
A34: ITM-ARM-003 | B34: CORE-051 | C34: Кольчуга | D34: Броня | E34: Зональный элемент | F34: A_CANONICAL | G34: FULL | H34: =TRUE() -> TRUE | I34: =FALSE() -> FALSE | J34: =TRUE() -> TRUE | K34: экземпляр | L34: =TRUE() -> TRUE | M34: =FALSE() -> FALSE | N34: INSTANCE_ZONE | O34: TEMPLATE_FIXED | P34: =FALSE() -> FALSE | R34: =FALSE() -> FALSE | S34: PDF §4, с. 81; CORE-051 | U34: =IF(COUNTIF($A$5:$A$68,A34)=1,"PASS","DUPLICATE") -> PASS
A35: ITM-ARM-004 | B35: CORE-052 | C35: Латы | D35: Броня | E35: Зональный элемент | F35: A_CANONICAL | G35: FULL | H35: =TRUE() -> TRUE | I35: =FALSE() -> FALSE | J35: =TRUE() -> TRUE | K35: экземпляр | L35: =TRUE() -> TRUE | M35: =FALSE() -> FALSE | N35: INSTANCE_ZONE | O35: TEMPLATE_FIXED | P35: =FALSE() -> FALSE | R35: =FALSE() -> FALSE | S35: PDF §4, с. 82; CORE-052 | U35: =IF(COUNTIF($A$5:$A$68,A35)=1,"PASS","DUPLICATE") -> PASS
A36: ITM-ARM-005 | B36: CORE-053 | C36: Нэйт | D36: Броня | E36: Цельный костюм | F36: A_CANONICAL | G36: FULL | H36: =TRUE() -> TRUE | I36: =FALSE() -> FALSE | J36: =TRUE() -> TRUE | K36: экземпляр | L36: =TRUE() -> TRUE | M36: =FALSE() -> FALSE | N36: TEMPLATE_FIXED | O36: TEMPLATE_FIXED | P36: =FALSE() -> FALSE | R36: =FALSE() -> FALSE | S36: PDF §4, с. 82; CORE-053 | U36: =IF(COUNTIF($A$5:$A$68,A36)=1,"PASS","DUPLICATE") -> PASS
A37: ITM-ARM-006 | B37: CORE-054 | C37: Кастелькросс | D37: Броня | E37: Цельный доспех | F37: A_CANONICAL | G37: FULL | H37: =TRUE() -> TRUE | I37: =FALSE() -> FALSE | J37: =TRUE() -> TRUE | K37: экземпляр | L37: =TRUE() -> TRUE | M37: =FALSE() -> FALSE | N37: TEMPLATE_FIXED | O37: TEMPLATE_FIXED | P37: =FALSE() -> FALSE | R37: =FALSE() -> FALSE | S37: PDF §4, с. 82; CORE-054 | U37: =IF(COUNTIF($A$5:$A$68,A37)=1,"PASS","DUPLICATE") -> PASS
A38: ITM-ARM-007 | B38: CORE-055 | C38: Цесмор | D38: Броня | E38: Цельный доспех | F38: A_CANONICAL | G38: FULL | H38: =TRUE() -> TRUE | I38: =FALSE() -> FALSE | J38: =TRUE() -> TRUE | K38: экземпляр | L38: =TRUE() -> TRUE | M38: =FALSE() -> FALSE | N38: TEMPLATE_FIXED | O38: TEMPLATE_FIXED | P38: =FALSE() -> FALSE | R38: =FALSE() -> FALSE | S38: PDF §4, с. 82; CORE-055 | U38: =IF(COUNTIF($A$5:$A$68,A38)=1,"PASS","DUPLICATE") -> PASS
A39: ITM-ARM-008 | B39: CORE-056 | C39: Гленхейм | D39: Броня | E39: Цельный доспех | F39: A_CANONICAL | G39: FULL | H39: =TRUE() -> TRUE | I39: =FALSE() -> FALSE | J39: =TRUE() -> TRUE | K39: экземпляр | L39: =TRUE() -> TRUE | M39: =FALSE() -> FALSE | N39: TEMPLATE_FIXED | O39: TEMPLATE_FIXED | P39: =FALSE() -> FALSE | R39: =FALSE() -> FALSE | S39: PDF §4, с. 83; CORE-056 | U39: =IF(COUNTIF($A$5:$A$68,A39)=1,"PASS","DUPLICATE") -> PASS
A40: ITM-PHA-001 | B40: CORE-059 | C40: Антисептик | D40: Фармацевтика | E40: Отвар/средство | F40: A_CANONICAL | G40: FULL | H40: =TRUE() -> TRUE | I40: =TRUE() -> TRUE | J40: =TRUE() -> TRUE | K40: доза | L40: =FALSE() -> FALSE | M40: =FALSE() -> FALSE | N40: TEMPLATE_FIXED | O40: TEMPLATE_FIXED | P40: =FALSE() -> FALSE | R40: =FALSE() -> FALSE | S40: PDF §4, с. 83; CORE-059 | U40: =IF(COUNTIF($A$5:$A$68,A40)=1,"PASS","DUPLICATE") -> PASS
A41: ITM-PHA-002 | B41: CORE-060 | C41: Отвар, приводящий в сознание | D41: Фармацевтика | E41: Отвар/средство | F41: A_CANONICAL | G41: FULL | H41: =TRUE() -> TRUE | I41: =TRUE() -> TRUE | J41: =TRUE() -> TRUE | K41: доза | L41: =FALSE() -> FALSE | M41: =FALSE() -> FALSE | N41: TEMPLATE_FIXED | O41: TEMPLATE_FIXED | P41: =FALSE() -> FALSE | R41: =FALSE() -> FALSE | S41: PDF §4, с. 83; CORE-060 | U41: =IF(COUNTIF($A$5:$A$68,A41)=1,"PASS","DUPLICATE") -> PASS
A42: ITM-PHA-003 | B42: CORE-061 | C42: Снотворное | D42: Фармацевтика | E42: Отвар/средство | F42: A_CANONICAL | G42: FULL | H42: =TRUE() -> TRUE | I42: =TRUE() -> TRUE | J42: =TRUE() -> TRUE | K42: доза | L42: =FALSE() -> FALSE | M42: =FALSE() -> FALSE | N42: TEMPLATE_FIXED | O42: TEMPLATE_FIXED | P42: =FALSE() -> FALSE | R42: =FALSE() -> FALSE | S42: PDF §4, с. 84; CORE-061 | U42: =IF(COUNTIF($A$5:$A$68,A42)=1,"PASS","DUPLICATE") -> PASS
A43: ITM-PHA-004 | B43: CORE-062 | C43: Отвар-паралитик | D43: Фармацевтика | E43: Отвар/средство | F43: A_CANONICAL | G43: FULL | H43: =TRUE() -> TRUE | I43: =TRUE() -> TRUE | J43: =TRUE() -> TRUE | K43: доза | L43: =FALSE() -> FALSE | M43: =FALSE() -> FALSE | N43: TEMPLATE_FIXED | O43: TEMPLATE_FIXED | P43: =FALSE() -> FALSE | R43: =FALSE() -> FALSE | S43: PDF §4, с. 84; CORE-062 | U43: =IF(COUNTIF($A$5:$A$68,A43)=1,"PASS","DUPLICATE") -> PASS
A44: ITM-PHA-005 | B44: CORE-063 | C44: Кровоостанавливающий отвар | D44: Фармацевтика | E44: Отвар/средство | F44: A_CANONICAL | G44: FULL | H44: =TRUE() -> TRUE | I44: =TRUE() -> TRUE | J44: =TRUE() -> TRUE | K44: доза | L44: =FALSE() -> FALSE | M44: =FALSE() -> FALSE | N44: TEMPLATE_FIXED | O44: TEMPLATE_FIXED | P44: =FALSE() -> FALSE | R44: =FALSE() -> FALSE | S44: PDF §4, с. 84; CORE-063 | U44: =IF(COUNTIF($A$5:$A$68,A44)=1,"PASS","DUPLICATE") -> PASS
A45: ITM-PHA-006 | B45: CORE-064 | C45: Восстанавливающий отвар | D45: Фармацевтика | E45: Отвар/средство | F45: A_CANONICAL | G45: FULL | H45: =TRUE() -> TRUE | I45: =TRUE() -> TRUE | J45: =TRUE() -> TRUE | K45: доза | L45: =FALSE() -> FALSE | M45: =FALSE() -> FALSE | N45: TEMPLATE_FIXED | O45: TEMPLATE_FIXED | P45: =FALSE() -> FALSE | R45: =FALSE() -> FALSE | S45: PDF §4, с. 84; CORE-064 | U45: =IF(COUNTIF($A$5:$A$68,A45)=1,"PASS","DUPLICATE") -> PASS
A46: ITM-PHA-007 | B46: CORE-065 | C46: Симбиотический отвар | D46: Фармацевтика | E46: Отвар/средство | F46: A_CANONICAL | G46: FULL | H46: =TRUE() -> TRUE | I46: =TRUE() -> TRUE | J46: =TRUE() -> TRUE | K46: доза | L46: =FALSE() -> FALSE | M46: =FALSE() -> FALSE | N46: TEMPLATE_FIXED | O46: TEMPLATE_FIXED | P46: =FALSE() -> FALSE | R46: =FALSE() -> FALSE | S46: PDF §4, с. 84; CORE-065 | U46: =IF(COUNTIF($A$5:$A$68,A46)=1,"PASS","DUPLICATE") -> PASS
A47: ITM-PHA-008 | B47: CORE-066 | C47: Таблетка ночного зрения | D47: Фармацевтика | E47: Таблетка | F47: A_CANONICAL | G47: FULL | H47: =TRUE() -> TRUE | I47: =TRUE() -> TRUE | J47: =TRUE() -> TRUE | K47: доза | L47: =FALSE() -> FALSE | M47: =FALSE() -> FALSE | N47: TEMPLATE_FIXED | O47: TEMPLATE_FIXED | P47: =FALSE() -> FALSE | R47: =FALSE() -> FALSE | S47: PDF §4, с. 84; CORE-066 | U47: =IF(COUNTIF($A$5:$A$68,A47)=1,"PASS","DUPLICATE") -> PASS
A48: ITM-PHA-009 | B48: CORE-067 | C48: Таблетка бритвенных рефлексов | D48: Фармацевтика | E48: Таблетка | F48: A_CANONICAL | G48: FULL | H48: =TRUE() -> TRUE | I48: =TRUE() -> TRUE | J48: =TRUE() -> TRUE | K48: доза | L48: =FALSE() -> FALSE | M48: =FALSE() -> FALSE | N48: TEMPLATE_FIXED | O48: TEMPLATE_FIXED | P48: =FALSE() -> FALSE | R48: =FALSE() -> FALSE | S48: PDF §4, с. 84; CORE-067 | U48: =IF(COUNTIF($A$5:$A$68,A48)=1,"PASS","DUPLICATE") -> PASS
A49: ITM-PHA-010 | B49: CORE-068 | C49: Таблетка ледяного спокойствия | D49: Фармацевтика | E49: Таблетка | F49: A_CANONICAL | G49: FULL | H49: =TRUE() -> TRUE | I49: =TRUE() -> TRUE | J49: =TRUE() -> TRUE | K49: доза | L49: =FALSE() -> FALSE | M49: =FALSE() -> FALSE | N49: TEMPLATE_FIXED | O49: TEMPLATE_FIXED | P49: =FALSE() -> FALSE | R49: =FALSE() -> FALSE | S49: PDF §4, с. 84; CORE-068 | U49: =IF(COUNTIF($A$5:$A$68,A49)=1,"PASS","DUPLICATE") -> PASS
A50: ITM-PHA-011 | B50: CORE-069 | C50: Таблетка взрывной мощи | D50: Фармацевтика | E50: Таблетка | F50: A_CANONICAL | G50: FULL | H50: =TRUE() -> TRUE | I50: =TRUE() -> TRUE | J50: =TRUE() -> TRUE | K50: доза | L50: =FALSE() -> FALSE | M50: =FALSE() -> FALSE | N50: TEMPLATE_FIXED | O50: TEMPLATE_FIXED | P50: =FALSE() -> FALSE | R50: =FALSE() -> FALSE | S50: PDF §4, с. 84; CORE-069 | U50: =IF(COUNTIF($A$5:$A$68,A50)=1,"PASS","DUPLICATE") -> PASS
A51: ITM-PHA-012 | B51: CORE-070 | C51: Таблетка куража | D51: Фармацевтика | E51: Таблетка | F51: A_CANONICAL | G51: FULL | H51: =TRUE() -> TRUE | I51: =TRUE() -> TRUE | J51: =TRUE() -> TRUE | K51: доза | L51: =FALSE() -> FALSE | M51: =FALSE() -> FALSE | N51: TEMPLATE_FIXED | O51: TEMPLATE_FIXED | P51: =FALSE() -> FALSE | R51: =FALSE() -> FALSE | S51: PDF §4, с. 84; CORE-070 | U51: =IF(COUNTIF($A$5:$A$68,A51)=1,"PASS","DUPLICATE") -> PASS
... A53: ITM-PHA-014 | B53: CORE-072 | C53: Таблетка неудержимости | D53: Фармацевтика | E53: Таблетка | F53: A_CANONICAL | G53: FULL | H53: =TRUE() -> TRUE | I53: =TRUE() -> TRUE | J53: =TRUE() -> TRUE | K53: доза | L53: =FALSE() -> FALSE | M53: =FALSE() -> FALSE | N53: TEMPLATE_FIXED | O53: TEMPLATE_FIXED | P53: =FALSE() -> FALSE | R53: =FALSE() -> FALSE | S53: PDF §4, с. 84; CORE-072 | U53: =IF(COUNTIF($A$5:$A$68,A53)=1,"PASS","DUPLICATE") -> PASS
A54: RES-AMM-001 | B54: CORE-125; AQA-011 | C54: Арбалетный болт | D54: Боеприпасы | E54: Боеприпасы | F54: B_EXPLICIT | G54: PARTIAL | H54: =TRUE() -> TRUE | I54: =TRUE() -> TRUE | J54: =TRUE() -> TRUE | K54: штука | L54: =FALSE() -> FALSE | M54: =FALSE() -> FALSE | N54: MASTER_DEFINED_OR_PARTIAL | O54: TEMPLATE_OR_DESCRIPTION_ONLY | P54: =FALSE() -> FALSE | R54: =FALSE() -> FALSE | S54: PDF с. 69, 102; CORE-125; AQA-011 | T54: Расходуется при атаке; совместимость с конкретными арбалетами не формализована. | U54: =IF(COUNTIF($A$5:$A$68,A54)=1,"PASS","DUPLICATE") -> PASS
A55: RES-MAG-001 | B55: CORE-023 | C55: Магазин Кенси | D55: Боеприпасы | E55: Боеприпасы | F55: B_EXPLICIT | G55: PARTIAL | H55: UNKNOWN | I55: =FALSE() -> FALSE | J55: =TRUE() -> TRUE | K55: магазин | L55: =FALSE() -> FALSE | M55: =FALSE() -> FALSE | N55: MASTER_DEFINED_OR_PARTIAL | O55: TEMPLATE_OR_DESCRIPTION_ONLY | P55: =FALSE() -> FALSE | R55: =FALSE() -> FALSE | S55: PDF с. 69; CORE-023 | T55: Ёмкость 8 болтов; неясно, отдельный ли это инвентарный предмет. | U55: =IF(COUNTIF($A$5:$A$68,A55)=1,"PASS","DUPLICATE") -> PASS
A56: RES-MAG-002 | B56: CORE-024 | C56: Магазин Эривела | D56: Боеприпасы | E56: Боеприпасы | F56: B_EXPLICIT | G56: PARTIAL | H56: UNKNOWN | I56: =FALSE() -> FALSE | J56: =TRUE() -> TRUE | K56: магазин | L56: =FALSE() -> FALSE | M56: =FALSE() -> FALSE | N56: MASTER_DEFINED_OR_PARTIAL | O56: TEMPLATE_OR_DESCRIPTION_ONLY | P56: =FALSE() -> FALSE | R56: =FALSE() -> FALSE | S56: PDF с. 69; CORE-024 | T56: Ёмкость 4 болта; неясно, отдельный ли это инвентарный предмет. | U56: =IF(COUNTIF($A$5:$A$68,A56)=1,"PASS","DUPLICATE") -> PASS
A57: RES-AMM-002 | B57: CORE-125; SYM-183 | C57: Стрела | D57: Боеприпасы | E57: Боеприпасы | F57: B_EXPLICIT | G57: PARTIAL | H57: =TRUE() -> TRUE | I57: =TRUE() -> TRUE | J57: =TRUE() -> TRUE | K57: штука | L57: =FALSE() -> FALSE | M57: =FALSE() -> FALSE | N57: MASTER_DEFINED_OR_PARTIAL | O57: TEMPLATE_OR_DESCRIPTION_ONLY | P57: =FALSE() -> FALSE | R57: =FALSE() -> FALSE | S57: PDF с. 98–102, 119, 128; CORE-125; SYM-183 | T57: Расходуется при атаке; может иметь покрытие. | U57: =IF(COUNTIF($A$5:$A$68,A57)=1,"PASS","DUPLICATE") -> PASS
A58: RES-EQP-001 | B58: CORE-112; MON-072 | C58: Одежда | D58: Экипировка | E58: Экипировка | F58: B_EXPLICIT | G58: PARTIAL | H58: =TRUE() -> TRUE | I58: =FALSE() -> FALSE | J58: =TRUE() -> TRUE | K58: экземпляр | L58: =TRUE() -> TRUE | M58: =FALSE() -> FALSE | N58: MASTER_DEFINED_OR_PARTIAL | O58: TEMPLATE_OR_DESCRIPTION_ONLY | P58: =FALSE() -> FALSE | R58: =FALSE() -> FALSE | S58: PDF с. 97, 110, 116, 128; CORE-112; MON-072 | T58: Общий тип; зоны, герметичность и горючесть задаются экземпляром/мастером. | U58: =IF(COUNTIF($A$5:$A$68,A58)=1,"PASS","DUPLICATE") -> PASS
A59: RES-CON-001 | B59: AQ2-005 | C59: Рюкзак | D59: Контейнер | E59: Контейнер | F59: B_EXPLICIT | G59: PARTIAL | H59: =TRUE() -> TRUE | I59: =FALSE() -> FALSE | J59: =TRUE() -> TRUE | K59: экземпляр | L59: =FALSE() -> FALSE | M59: =FALSE() -> FALSE | N59: MASTER_DEFINED_OR_PARTIAL | O59: TEMPLATE_OR_DESCRIPTION_ONLY | P59: =FALSE() -> FALSE | R59: =FALSE() -> FALSE | S59: PDF с. 94, 97, 128; AQ2-005 | T59: Вместимость и масса не заданы; вложенные бонусные customItem действуют только внутри рюкзака. | U59: =IF(COUNTIF($A$5:$A$68,A59)=1,"PASS","DUPLICATE") -> PASS
A60: RES-RES-001 | C60: Железные кандалы | D60: Ограничивающий предмет | E60: Ограничивающий предмет | F60: B_EXPLICIT | G60: PARTIAL | H60: =TRUE() -> TRUE | I60: =FALSE() -> FALSE | J60: =TRUE() -> TRUE | K60: экземпляр | L60: =FALSE() -> FALSE | M60: =FALSE() -> FALSE | N60: MASTER_DEFINED_OR_PARTIAL | O60: TEMPLATE_OR_DESCRIPTION_ONLY | P60: =FALSE() -> FALSE | R60: =FALSE() -> FALSE | S60: PDF с. 92 | T60: Связь с конкретным замком/ключом должна храниться у экземпляра; отдельная карточка v1.2 не найдена. | U60: =IF(COUNTIF($A$5:$A$68,A60)=1,"PASS","DUPLICATE") -> PASS
A61: RES-KEY-001 | C61: Ключ от замка кандалов | D61: Ключ | E61: Ключ | F61: B_EXPLICIT | G61: PARTIAL | H61: =TRUE() -> TRUE | I61: =FALSE() -> FALSE | J61: =TRUE() -> TRUE | K61: экземпляр | L61: =FALSE() -> FALSE | M61: =FALSE() -> FALSE | N61: MASTER_DEFINED_OR_PARTIAL | O61: TEMPLATE_OR_DESCRIPTION_ONLY | P61: =FALSE() -> FALSE | R61: =FALSE() -> FALSE | S61: PDF с. 92 | T61: С ключом освобождение: R20+D против 35; схема идентификатора замка не определена. | U61: =IF(COUNTIF($A$5:$A$68,A61)=1,"PASS","DUPLICATE") -> PASS
A62: RES-CON-002 | C62: Крепкий алкоголь, 100 мл | D62: Расходник | E62: Расходник | F62: B_EXPLICIT | G62: PARTIAL | H62: =TRUE() -> TRUE | I62: =TRUE() -> TRUE | J62: =TRUE() -> TRUE | K62: порция | L62: =FALSE() -> FALSE | M62: =FALSE() -> FALSE | N62: MASTER_DEFINED_OR_PARTIAL | O62: TEMPLATE_OR_DESCRIPTION_ONLY | P62: =FALSE() -> FALSE | R62: =FALSE() -> FALSE | S62: PDF с. 91 | T62: Участвует в механике опьянения; отдельная карточка v1.2 не найдена. | U62: =IF(COUNTIF($A$5:$A$68,A62)=1,"PASS","DUPLICATE") -> PASS
A63: RES-CON-003 | C63: Слабоалкогольный напиток, 1 л | D63: Расходник | E63: Расходник | F63: B_EXPLICIT | G63: PARTIAL | H63: =TRUE() -> TRUE | I63: =TRUE() -> TRUE | J63: =TRUE() -> TRUE | K63: порция | L63: =FALSE() -> FALSE | M63: =FALSE() -> FALSE | N63: MASTER_DEFINED_OR_PARTIAL | O63: TEMPLATE_OR_DESCRIPTION_ONLY | P63: =FALSE() -> FALSE | R63: =FALSE() -> FALSE | S63: PDF с. 91 | T63: Участвует в той же механике опьянения; отдельная карточка v1.2 не найдена. | U63: =IF(COUNTIF($A$5:$A$68,A63)=1,"PASS","DUPLICATE") -> PASS
A64: RES-TOL-001 | C64: Медицинское оборудование | D64: Инструмент | E64: Инструмент | F64: B_EXPLICIT | G64: PARTIAL | H64: =TRUE() -> TRUE | I64: =FALSE() -> FALSE | J64: =TRUE() -> TRUE | K64: комплект | L64: =FALSE() -> FALSE | M64: =FALSE() -> FALSE | N64: MASTER_DEFINED_OR_PARTIAL | O64: TEMPLATE_OR_DESCRIPTION_ONLY | P64: =FALSE() -> FALSE | R64: =FALSE() -> FALSE | S64: PDF с. 91 | T64: Требуется для устранения травмы; состав и бонусы не заданы; отдельная карточка v1.2 не найдена. | U64: =IF(COUNTIF($A$5:$A$68,A64)=1,"PASS","DUPLICATE") -> PASS
A65: RES-CUR-000 | B65: AQA-011; AQ2-004 | C65: Деньги | D65: Валюта/ресурс | E65: Валюта/ресурс | F65: B_EXPLICIT | G65: PARTIAL | H65: =TRUE() -> TRUE | I65: =TRUE() -> TRUE | J65: =TRUE() -> TRUE | K65: единица | L65: =FALSE() -> FALSE | M65: =FALSE() -> FALSE | N65: MASTER_DEFINED_OR_PARTIAL | O65: TEMPLATE_OR_DESCRIPTION_ONLY | P65: =FALSE() -> FALSE | R65: =FALSE() -> FALSE | S65: PDF с. 39, 110; AQA-011; AQ2-004 | T65: Рекомендуется хранить ресурсом, а не экипируемым предметом. | U65: =IF(COUNTIF($A$5:$A$68,A65)=1,"PASS","DUPLICATE") -> PASS
A66: RES-CUR-001 | C66: Медная монета | D66: Валюта/ресурс | E66: Валюта/ресурс | F66: B_EXPLICIT | G66: PARTIAL | H66: =TRUE() -> TRUE | I66: =TRUE() -> TRUE | J66: =TRUE() -> TRUE | K66: монета | L66: =FALSE() -> FALSE | M66: =FALSE() -> FALSE | N66: MASTER_DEFINED_OR_PARTIAL | O66: TEMPLATE_OR_DESCRIPTION_ONLY | P66: =FALSE() -> FALSE | R66: =FALSE() -> FALSE | S66: PDF с. 39 | T66: Курс обмена не задан. | U66: =IF(COUNTIF($A$5:$A$68,A66)=1,"PASS","DUPLICATE") -> PASS
A67: RES-CUR-002 | C67: Серебряная монета | D67: Валюта/ресурс | E67: Валюта/ресурс | F67: B_EXPLICIT | G67: PARTIAL | H67: =TRUE() -> TRUE | I67: =TRUE() -> TRUE | J67: =TRUE() -> TRUE | K67: монета | L67: =FALSE() -> FALSE | M67: =FALSE() -> FALSE | N67: MASTER_DEFINED_OR_PARTIAL | O67: TEMPLATE_OR_DESCRIPTION_ONLY | P67: =FALSE() -> FALSE | R67: =FALSE() -> FALSE | S67: PDF с. 39 | T67: Курс обмена не задан. | U67: =IF(COUNTIF($A$5:$A$68,A67)=1,"PASS","DUPLICATE") -> PASS
A68: RES-CUR-003 | C68: Золотая монета | D68: Валюта/ресурс | E68: Валюта/ресурс | F68: B_EXPLICIT | G68: PARTIAL | H68: =TRUE() -> TRUE | I68: =TRUE() -> TRUE | J68: =TRUE() -> TRUE | K68: монета | L68: =FALSE() -> FALSE | M68: =FALSE() -> FALSE | N68: MASTER_DEFINED_OR_PARTIAL | O68: TEMPLATE_OR_DESCRIPTION_ONLY | P68: =FALSE() -> FALSE | R68: =FALSE() -> FALSE | S68: PDF с. 39 | T68: Курс обмена не задан. | U68: =IF(COUNTIF($A$5:$A$68,A68)=1,"PASS","DUPLICATE") -> PASS

Sheet 02_Профили_оружия
A1: Профили оружия и щитов — исходные выражения
A2: Столбцы I–J сохраняют канонический шаблон. Исполняемая база и модификатор характеристики разделены на 02A. При MASTER_OVERRIDE damage/penetration, statRequirements, rangeMeters и accuracyBonus берутся из активной WeaponProfileVersion; навыки, ёмкость, перезарядка, HP и особые правила остаются шаблонными.
A4: ItemTypeID | B4: Rule ID | C4: Название | D4: Руки | E4: Требования | F4: Стат точности | G4: Навык/класс | H4: Штраф без навыка/класса | I4: Урон: исходное выражение | J4: Пробитие: исходное выражение | K4: Дальность, м | L4: Боеприпас | M4: Ёмкость | N4: Перезарядка, действий | O4: Перезарядка атомарна | P4: Блок | Q4: Парирование | R4: Shield max HP | S4: Можно метать | T4: Штраф метания | U4: Особое правило | V4: PDF, с.
A5: ITM-WPN-001 | B5: CORE-021 | C5: Лёгкий арбалет | D5: 2 | E5: PROFILE: statRequirements{S:Rs,D:Rd}; instanceDamage=Dm; rangeMeters=Rn | F5: D | G5: Стрельба или Сталкер/Солдат ПР | H5: −5 | I5: Dm | J5: R12 | K5: Rn | L5: Арбалетный болт | N5: 1 | O5: =FALSE() -> FALSE | S5: =FALSE() -> FALSE | U5: Формульная допустимость по F-WPN-001; ёмкость не задана; боеприпас при объявлении расходуется. | V5: 68
A6: ITM-WPN-002 | B6: CORE-022 | C6: Тяжёлый арбалет | D6: 2 | E6: PROFILE: statRequirements{S:Rs,D:Rd}; instanceDamage=Dm; rangeMeters=Rn | F6: D | G6: Стрельба или Сталкер/Солдат ПР | H6: −5 | I6: Dm | J6: R20 | K6: Rn | L6: Арбалетный болт | N6: 1 | O6: =FALSE() -> FALSE | S6: =FALSE() -> FALSE | U6: Формульная допустимость по F-WPN-002; ёмкость не задана. | V6: 69
A7: ITM-WPN-003 | B7: CORE-023 | C7: Кенси | D7: 1 | E7: S8; D19 | F7: D | G7: Стрельба; класс Сталкер/Солдат ПР | H7: −15 без класса | I7: 10 | J7: R12 | K7: 20 | L7: Арбалетный болт | M7: 8 | N7: 1 | O7: =FALSE() -> FALSE | S7: =FALSE() -> FALSE | U7: Высокая Стрельба: один раз за личный ход за 1 действие особая атака двумя Кенси; каждый выстрел разрешается отдельно. Совершенная: можно назначить отдельные цели. | V7: 69
A8: ITM-WPN-004 | B8: CORE-024 | C8: Эривел | D8: 2 | E8: S16; D12 | F8: D | G8: Стрельба; класс Сталкер/Солдат ПР | H8: −15 без класса | I8: 2×R20 (один бросок) | J8: R20 (независимый) | K8: 30 | L8: Арбалетный болт | M8: 4 | N8: 1 | O8: =FALSE() -> FALSE | S8: =FALSE() -> FALSE | V8: 69
A9: ITM-WPN-005 | B9: CORE-025 | C9: Эстрефорд | D9: 2 | E9: S19; D14 | F9: D | G9: Стрельба; класс Сталкер/Солдат ПР | H9: −15 без класса | I9: 30 | J9: 16 | K9: 30 | L9: Арбалетный болт | N9: 1 | O9: =FALSE() -> FALSE | S9: =FALSE() -> FALSE | U9: Ёмкость не задана. | V9: 70
A10: ITM-WPN-006 | B10: CORE-026 | C10: Айнцберн | D10: 2 | E10: S22; D22; I12; Стрельба ≥ средняя | F10: D | G10: Стрельба; класс Сталкер/Солдат ПР | H10: −15 без класса | I10: R20+30 | J10: R20+20 (независимый) | K10: 100 | L10: Арбалетный болт | N10: 2 | O10: =TRUE() -> TRUE | S10: =FALSE() -> FALSE | U10: Ёмкость не задана. Абсолютная Стрельба: R6>2 — точная заявленная зона. | V10: 70
A11: ITM-WPN-007 | B11: CORE-027 | C11: Лёгкий лук | D11: 2 | E11: PROFILE: statRequirements{S:Rs,D:Rd}; instanceDamage=Dm; rangeMeters=Rn | F11: D | G11: Стрельба из лука | H11: −5 | I11: Dm | J11: R12 | K11: Rn | L11: Стрела | M11: 1 | N11: 1 | O11: =FALSE() -> FALSE | S11: =FALSE() -> FALSE | U11: Высокий навык: перезарядка 0; абсолютный: R6>2 — точная зона. | V11: 71
A12: ITM-WPN-008 | B12: CORE-028 | C12: Тяжёлый лук | D12: 2 | E12: PROFILE: statRequirements{S:Rs,D:Rd}; instanceDamage=Dm; rangeMeters=Rn | F12: D | G12: Стрельба из лука | H12: −5 | I12: Dm | J12: R20 | K12: Rn | L12: Стрела | M12: 1 | N12: 1 | O12: =FALSE() -> FALSE | S12: =FALSE() -> FALSE | U12: Высокий навык: перезарядка 0; абсолютный: R6>2 — точная зона. | V12: 71
A13: ITM-WPN-009 | B13: CORE-029 | C13: Длинный лук | D13: 2 | E13: PROFILE: statRequirements{S:Rs,D:Rd}; instanceDamage=Dm; rangeMeters=Rn | F13: D | G13: Стрельба из лука | H13: −5 | I13: Dm | J13: R12 | K13: Rn | L13: Стрела | M13: 1 | N13: 1 | O13: =FALSE() -> FALSE | S13: =FALSE() -> FALSE | U13: Дальность может иметь шаг 0,5. Высокий навык: перезарядка 0; абсолютный: R6>2 — точная зона. | V13: 72
A14: ITM-WPN-010 | B14: CORE-031 | C14: Грубое оружие | D14: 1 | E14: PROFILE: statRequirements{S:Rs,D:Rd} | F14: D | G14: Владение грубым оружием | H14: −3 | I14: +S к R12 | J14: R12 | O14: =FALSE() -> FALSE | S14: =TRUE() -> TRUE | U14: При непробитии проходит половина финального урона; урон ≥3×Z: D20<10 — пропуск 3 раундов. | V14: 73
A15: ITM-WPN-011 | B15: CORE-032 | C15: Одноручный меч | D15: 1 | E15: PROFILE: statRequirements{S:Rs,D:Rd} | F15: D | G15: Фехтование | H15: −5 | I15: R20+S | J15: R12 | O15: =FALSE() -> FALSE | S15: =TRUE() -> TRUE | V15: 73
A16: ITM-WPN-012 | B16: CORE-033 | C16: Полуторный меч | D16: 1 или 2, фиксировано | E16: PROFILE: statRequirements{S:Rs(хват),D:Rd}; gripMode фиксирован | F16: D | G16: Фехтование | H16: −5 | I16: R20+S | J16: R20 | O16: =FALSE() -> FALSE | S16: =TRUE() -> TRUE | U16: Хват задаётся в заявке/выдаче и не меняется. | V16: 73
A17: ITM-WPN-013 | B17: CORE-034 | C17: Двуручный меч | D17: 2 | E17: PROFILE: statRequirements{S:Rs,D:Rd} | F17: D | G17: Фехтование | H17: −5 | I17: R20+5+S | J17: R20+5 | O17: =FALSE() -> FALSE | S17: =TRUE() -> TRUE | T17: −10 | V17: 74
A18: ITM-WPN-014 | B18: CORE-035 | C18: Шпага | D18: 1 | E18: PROFILE: statRequirements{S:Rs,D:Rd} | F18: D | G18: Фехтование | H18: −5 | I18: R12+D | J18: R12 | O18: =FALSE() -> FALSE | Q18: 5 | S18: =TRUE() -> TRUE | T18: −10 | V18: 74
A19: ITM-WPN-015 | B19: CORE-036 | C19: Копьё | D19: 2 | E19: PROFILE: statRequirements{S:Rs,D:Rd} | F19: D | G19: Владение копьём | H19: −2 | I19: R12+S | J19: R12 | O19: =FALSE() -> FALSE | S19: =TRUE() -> TRUE | U19: +3 к упреждающему удару. | V19: 74
A20: ITM-WPN-016 | B20: CORE-037 | C20: Кинжал | D20: 1 | E20: PROFILE: statRequirements{S:Rs,D:Rd} | F20: D | G20: Владение коротким оружием | H20: −5 | I20: R12+D; proc: 20+D | J20: R6 | O20: =FALSE() -> FALSE | S20: =TRUE() -> TRUE | U20: Итог меткости ≥40 и пробитие: база урона 20; высокий навык с двумя кинжалами — 2 атаки 1/ход. | V20: 74
A21: ITM-WPN-017 | B21: CORE-038 | C21: Мизерикордия | D21: 1 | E21: PROFILE: statRequirements{S:Rs,D:Rd} | F21: D | G21: Владение коротким оружием | H21: −5 | I21: R6+D; proc: 20+D | J21: R20 | O21: =FALSE() -> FALSE | S21: =TRUE() -> TRUE | U21: Итог меткости ≥40: игнорировать броню, база урона 20. | V21: 75
A22: ITM-WPN-018 | B22: CORE-039 | C22: Одноручный топор | D22: 1 | E22: PROFILE: statRequirements{S:Rs,D:Rd} | F22: D | G22: Владение топорами | H22: −5 | I22: R12+S; proc: 20+S | J22: R20 | O22: =FALSE() -> FALSE | S22: =TRUE() -> TRUE | U22: Итог меткости ≥41: игнорировать броню, база урона 20. | V22: 75
A23: ITM-WPN-019 | B23: CORE-040 | C23: Клевец | D23: 1 | E23: PROFILE: statRequirements{S:Rs,D:Rd} | F23: D | G23: Владение топорами | H23: −5 | I23: R6+S; proc: 20+S | J23: R20+5 | O23: =FALSE() -> FALSE | S23: =TRUE() -> TRUE | U23: Итог меткости ≥35: игнорировать броню, база урона 20. | V23: 75
A24: ITM-WPN-020 | B24: CORE-041 | C24: Двуручный топор | D24: 2 | E24: PROFILE: statRequirements{S:Rs,D:Rd} | F24: D | G24: Владение топорами | H24: −5 | I24: R20+S; proc: 20+S | J24: R20+10 | O24: =FALSE() -> FALSE | S24: =TRUE() -> TRUE | T24: −10 | U24: Итог меткости ≥37: игнорировать броню, база урона 20. | V24: 75
A25: ITM-WPN-021 | B25: CORE-042 | C25: Кастет | D25: 1 | E25: PROFILE: statRequirements{S:Rs,D:Rd} | F25: D | G25: Рукопашный бой; Солдат | H25: −5 без обоих; Солдат +3 к точности | I25: R6+S | J25: R6 | O25: =FALSE() -> FALSE | S25: =TRUE() -> TRUE | T25: −10 | U25: Высокий+: два отдельно разрешаемых удара за действие не чаще 1 раза за личный ход; абсолютный: также удар ногой без пробития. | V25: 76
A26: ITM-WPN-022 | B26: CORE-043 | C26: Деревянный круглый щит | D26: 1 | E26: PROFILE: statRequirements{S:Rs,D:Rd} | F26: D | G26: Владение щитом | H26: −5 | I26: R6+S | J26: R6 | O26: =FALSE() -> FALSE | P26: 3 | R26: 60 | S26: =TRUE() -> TRUE | U26: Меткость ≥30: −1 к следующей серии цели. | V26: 77
A27: ITM-WPN-023 | B27: CORE-044 | C27: Железный круглый щит | D27: 1 | E27: PROFILE: statRequirements{S:Rs,D:Rd} | F27: D | G27: Владение щитом | H27: −5 | I27: R6+S | J27: R6 | O27: =FALSE() -> FALSE | P27: 3 | R27: 100 | S27: =TRUE() -> TRUE | U27: Меткость ≥30: −1 к следующей серии цели. | V27: 77
A28: ITM-WPN-024 | B28: CORE-045 | C28: Деревянный треугольный щит | D28: 1 | E28: PROFILE: statRequirements{S:Rs,D:Rd} | F28: D | G28: Владение щитом | H28: −5 | I28: R6+3+S | J28: R6 | O28: =FALSE() -> FALSE | P28: 3 | R28: 80 | S28: =TRUE() -> TRUE | U28: Меткость ≥30: −1 к следующей серии цели. | V28: 78
A29: ITM-WPN-025 | B29: CORE-046 | C29: Железный треугольный щит | D29: 1 | E29: PROFILE: statRequirements{S:Rs,D:Rd} | F29: D | G29: Владение щитом | H29: −5 | I29: R6+3+S | J29: R6 | O29: =FALSE() -> FALSE | P29: 3 | R29: 130 | S29: =TRUE() -> TRUE | U29: Меткость ≥30: −1 к следующей серии цели. | V29: 78
A30: ITM-WPN-026 | B30: CORE-047 | C30: Корнадора | D30: 2 | E30: S22; D16 | F30: D | G30: Солдат ПР; Фехтование; Владение щитом | H30: −15 ко всем ролам без класса | I30: меч R20+S | J30: меч R20 | O30: =FALSE() -> FALSE | P30: 3 | R30: 400 | S30: =TRUE() -> TRUE | U30: Защита ≥40: немедленная контратака; меч/щит можно метать отдельно. | V30: 79
A31: ITM-WPN-027 | B31: CORE-048 | C31: Бларадэ | D31: 2 | E31: S15; D22 | F31: D | G31: Солдат ПР; Фехтование; Владение щитом | H31: −15 ко всем ролам без класса | I31: щит R12+S; шпага R12+D | J31: щит R12; шпага R20 | O31: =FALSE() -> FALSE | P31: 3 | Q31: 5 | R31: 200 | S31: =TRUE() -> TRUE | U31: Щит при меткости ≥30: −1 к следующей серии цели. После разрешения атаки щитом независимо от попадания следующая атака шпагой той же Бларадэ в этом личном ходу получает +5 к меткости/урону/пробитию; бонус расходуется атакой или сгорает в конце хода. | V31: 80

Sheet 03_Профили_брони
A1: Профили брони — исходные выражения
A2: Столбец G сохраняет каноническую запись правил. Машинооднозначная семантика находится на листе 02A_Семантика_Runtime: каждый дайс брони вычисляется заново для каждой отдельно разрешаемой атаки; результат не сохраняется в экземпляре брони.
A4: ItemTypeID | B4: Rule ID | C4: Название | D4: Модель покрытия | E4: Зоны | F4: Требование S | G4: Броня: исходное выражение | H4: Физическая броня | I4: Допускает слои | J4: Герметичен | K4: Твёрдая шея | L4: Бег | M4: Акробатика | N4: Уклонение | O4: M | P4: Защиты/иммунитеты | Q4: Условие/ограничение | R4: PDF, с.
A5: ITM-ARM-001 | B5: CORE-049 | C5: Кожаный доспех | D5: ZONE_ELEMENT | E5: Одна из 6 | F5: 2 за элемент | G5: R6 | H5: =TRUE() -> TRUE | I5: =TRUE() -> TRUE | J5: =FALSE() -> FALSE | K5: =FALSE() -> FALSE | P5: Шлем не закрывает лицо. | R5: 81
A6: ITM-ARM-002 | B6: CORE-050 | C6: Бригантина | D6: ZONE_ELEMENT | E6: Одна из 6 | F6: 3 за элемент | G6: R12 | H6: =TRUE() -> TRUE | I6: =TRUE() -> TRUE | J6: =FALSE() -> FALSE | K6: =TRUE() -> TRUE | L6: −1 за элемент | M6: −1 за элемент | O6: −3 при >2 | P6: Голова+корпус: твёрдая защита шеи; иммунитет удушению. | R6: 81
A7: ITM-ARM-003 | B7: CORE-051 | C7: Кольчуга | D7: ZONE_ELEMENT | E7: Одна из 6 | F7: 3 за элемент | G7: R12 | H7: =TRUE() -> TRUE | I7: =TRUE() -> TRUE | J7: =FALSE() -> FALSE | K7: =FALSE() -> FALSE | L7: −1 за элемент | M7: −1 за элемент | O7: −3 при >2 | P7: Каждый релевантный слой отдельно уменьшает электрический урон на R12; результаты слоёв складываются. | R7: 81
A8: ITM-ARM-004 | B8: CORE-052 | C8: Латы | D8: ZONE_ELEMENT | E8: Одна из 6 | F8: 4 за элемент | G8: R20 | H8: =TRUE() -> TRUE | I8: =TRUE() -> TRUE | J8: =FALSE() -> FALSE | K8: =TRUE() -> TRUE | L8: −2 за элемент | M8: −2 за элемент | O8: −5 при >2 | P8: Голова+корпус: твёрдая защита шеи. | R8: 82
A9: ITM-ARM-005 | B9: CORE-053 | C9: Нэйт | D9: FULL_SUIT | E9: Все 6 | F9: 6 | G9: — | H9: =FALSE() -> FALSE | I9: =FALSE() -> FALSE | J9: =TRUE() -> TRUE | K9: =FALSE() -> FALSE | P9: Пока герметичен: +20 к проверкам против заражения симбионтом, болезни, внешней химии и ядовитых испарений; −20 от каждой порции электрического, ментального, химического урона или урона от ядовитых испарений; +20 во встречных проверках против недамажащего электрического/пси-контроля; полностью блокирует вдыхаемые феромоны и заражённые испарения. | Q9: При потере ≥1 HP носителем или отдельном режущем/колющем/огненном/разъедающем повреждении костюма теряет все свойства; не защищает от проглоченного/введённого/внутреннего яда и не снимает прежний эффект; ремонт не формализован. | R9: 82
A10: ITM-ARM-006 | B10: CORE-054 | C10: Кастелькросс | D10: FULL_SUIT | E10: Все 6 | F10: 20 | G10: R20 | H10: =TRUE() -> TRUE | I10: =TRUE() -> TRUE | J10: =FALSE() -> FALSE | K10: =TRUE() -> TRUE | L10: −6 | M10: −6 | O10: −3 | P10: Ментальный урон −5/порция; +5 против пси-контроля; твёрдая защита шеи. | Q10: Слои разрешены CORE-151, физическая совместимость подтверждается мастером. Без Солдата ПР −15 к перемещениям; не защищает от химических феромонов. | R10: 82
A11: ITM-ARM-007 | B11: CORE-055 | C11: Цесмор | D11: FULL_SUIT | E11: Все 6 | F11: 14 | G11: R20 | H11: =TRUE() -> TRUE | I11: =TRUE() -> TRUE | J11: =FALSE() -> FALSE | K11: =FALSE() -> FALSE | Q11: Слои разрешены CORE-151, физическая совместимость подтверждается мастером. Без Сталкера/Солдата ПР −15 к перемещениям. | R11: 82
A12: ITM-ARM-008 | B12: CORE-056 | C12: Гленхейм | D12: FULL_SUIT | E12: Все 6 | F12: 24 | G12: 2×R20+5 (тот же бросок) | H12: =TRUE() -> TRUE | I12: =TRUE() -> TRUE | J12: =FALSE() -> FALSE | K12: =TRUE() -> TRUE | L12: −12 | M12: −12 | N12: −6 | O12: −5 | P12: Иммунитет травмирующим и удушающим приёмам. | Q12: Слои разрешены CORE-151, физическая совместимость подтверждается мастером. Без Солдата ПР −15 к перемещениям. | R12: 83

Sheet 04_Фармацевтика
A1: Профили фармацевтики
A2: Хранение и передача Pure-only препаратов разрешены любой расе; блокируется только применение к недопустимой расе. Лимиты считаются по скользящим 24 часам. Одноимённые продолжающиеся эффекты не складываются: повтор обновляет срок/условие, но не усиливает значение.
A4: ItemTypeID | B4: Rule ID | C4: Название | D4: Ограничение расы | E4: Макс. доз/24ч | F4: Эффект | G4: Длительность | H4: Стоимость в бою | I4: Политика отказа | J4: Примечание
A5: ITM-PHA-001 | B5: CORE-059 | C5: Антисептик | D5: Любая | E5: не задан | F5: Следующая попытка болезни через обработанную рану: −10; затем эффект заканчивается. | G5: До срабатывания | H5: 1 действие | I5: NOT_DEFINED | J5: Одна доза на одну рану по поздней нормализации.
A6: ITM-PHA-002 | B6: CORE-060 | C6: Отвар, приводящий в сознание | D6: Любая | E6: 3 | F6: Снять тяжёлое ранение; HP=1; отменить сон/паралич; остановить таймер смерти. | G6: Мгновенно | H6: 1 действие | I6: BLOCK_AT_LIMIT | J6: Не отменяет окончательную смерть.
A7: ITM-PHA-003 | B7: CORE-061 | C7: Снотворное | D7: Любая | E7: 3 | F7: (R20_effect+5)×K должно строго превысить R20_target+Z+модификаторы цели; дайсы независимы, равенство = провал; при успехе сон. | G7: 1 час; любой урон или отвар завершает | H7: 1 действие | I7: BLOCK_AT_LIMIT | J7: K доз одновременно; каждая считается в лимит.
A8: ITM-PHA-004 | B8: CORE-062 | C8: Отвар-паралитик | D8: Любая | E8: 3 | F8: (R20_effect+5)×K должно строго превысить R20_target+Z+модификаторы цели; дайсы независимы, равенство = провал; при успехе паралич. | G8: 1 час или до отвара; урон не завершает | H8: 1 действие | I8: BLOCK_AT_LIMIT | J8: K доз одновременно; жизненные процессы не прекращаются.
A9: ITM-PHA-005 | B9: CORE-063 | C9: Кровоостанавливающий отвар | D9: Любая | E9: 5 | F9: Остановить все текущие кровотечения. | G9: Мгновенно | H9: 1 действие | I9: BLOCK_AT_LIMIT
A10: ITM-PHA-006 | B10: CORE-064 | C10: Восстанавливающий отвар | D10: Любая | E10: 2 | F10: Восстановить 25 HP, не выше максимума. | G10: Мгновенно | H10: 1 действие | I10: BLOCK_AT_LIMIT | J10: Не выводит из тяжёлого ранения/окончательной смерти.
A11: ITM-PHA-007 | B11: CORE-065 | C11: Симбиотический отвар | D11: Любая | E11: 4 | F11: Восстановить 50 ОЭ одному выбранному симбионту, не выше максимума. | G11: Мгновенно | H11: 1 действие | I11: BLOCK_AT_LIMIT
A12: ITM-PHA-008 | B12: CORE-066 | C12: Таблетка ночного зрения | D12: Только Чистые | E12: 2 | F12: Видеть в темноте как днём. | G12: 2 часа | H12: 1 действие | I12: BLOCK_WRONG_RACE_OR_LIMIT | J12: Хранить/передавать может любая раса.
A13: ITM-PHA-009 | B13: CORE-067 | C13: Таблетка бритвенных рефлексов | D13: Только Чистые | E13: 3 | F13: +3 к уклонению и парированию. | G13: max(1, round(R20/3)) личных ходов | H13: 1 действие | I13: BLOCK_WRONG_RACE_OR_LIMIT | J13: Повтор не складывается; обновляет срок.
A14: ITM-PHA-010 | B14: CORE-068 | C14: Таблетка ледяного спокойствия | D14: Только Чистые | E14: 3 | F14: +3 к меткости; безэмоциональность — нарративно. | G14: max(1, round(R20/3)) личных ходов | H14: 1 действие | I14: BLOCK_WRONG_RACE_OR_LIMIT | J14: Повтор не складывается; обновляет срок.
A15: ITM-PHA-011 | B15: CORE-069 | C15: Таблетка взрывной мощи | D15: Только Чистые | E15: 2 | F15: Следующая проверка S: +6; сохраняет дееспособность при тяжёлом ранении до конца боя. | G15: До следующей проверки S / до конца боя | H15: 1 действие | I15: BLOCK_WRONG_RACE_OR_LIMIT | J15: Обычное добивание сохраняется.
A16: ITM-PHA-012 | B16: CORE-070 | C16: Таблетка куража | D16: Только Чистые | E16: 4 | F16: +1 к серии/числу действий до конца боя. | G16: До конца боя | H16: 1 действие | I16: BLOCK_WRONG_RACE_OR_LIMIT | J16: Первая доза в текущем ходу сразу добавляет 1 оставшееся действие.
A17: ITM-PHA-013 | B17: CORE-071 | C17: Восстанавливающая таблетка | D17: Только Чистые | E17: 5 | F17: В конце каждого личного хода цели +5 HP, не выше максимума. | G17: До конца боя | H17: 1 действие | I17: BLOCK_WRONG_RACE_OR_LIMIT | J17: Не действует в тяжёлом ранении.
A18: ITM-PHA-014 | B18: CORE-072 | C18: Таблетка неудержимости | D18: Только Чистые | E18: 3 | F18: +5 к сопротивлению/освобождению от эффектов с тегом контроля. | G18: До конца боя | H18: 1 действие | I18: BLOCK_WRONG_RACE_OR_LIMIT

Sheet 05_Формулы_валидации
A1: Формулы допустимости заявки игрока
A2: executionMode=VALIDATION_ONLY. Производственные дайсы относятся только к validationWitness. По CORE-185 переменные L/Lw/Ls — целые неотрицательные; Lw>0 там, где является делителем. Игрок вводит только выходы формулы; runtime-выражения и специальные свойства не меняются.
A4: FormulaID | B4: ItemTypeID | C4: Вариант | D4: Dm | E4: Rn | F4: Rs | G4: Rd | H4: Независимые дайсы | I4: Общие переменные | J4: Порядок/заметка | K4: Домен | L4: Execution mode | M4: Generation enabled | N4: GM override | O4: Контракт проверки | P4: ID уникален
A5: F-WPN-001 | B5: ITM-WPN-001 | C5: DEFAULT | D5: Dm = R12_DMG+L | E5: Rn = R12_RANGE+Dm+L | F5: Rs = MAX(1,CEIL(Dm×Rn/(R20_RS+3×Lw))) | G5: Rd = MAX(1,CEIL(2×Rn/Lw)) | H5: R12_DMG,R12_RANGE,R20_RS | I5: L,Lw | J5: Dm→Rn→Rs→Rd | K5: L,Lw,Ls∈Z≥0; Lw>0 там, где является делителем; каждое вхождение R4/R6/R12/R20 независимо; вычисленные поля переиспользуются по порядку формулы | L5: VALIDATION_ONLY | M5: =FALSE() -> FALSE | N5: BYPASS_FORMULA_BOUNDS; CORE-187/188 | O5: EXISTS one joint witness; сохранить formulaId, formulaVersion=ITEM_FORMULAS_V1.2 и весь witness | P5: =IF(COUNTIF($A$5:$A$26,A5)=1,"PASS","DUPLICATE") -> PASS
A6: F-WPN-002 | B6: ITM-WPN-002 | C6: DEFAULT | D6: Dm = R20_DMG+L | E6: Rn = R12_RANGE+Dm+L | F6: Rs = MAX(1,CEIL(Dm×Rn/(R20_RS+2×Lw))) | G6: Rd = MAX(1,CEIL(2×Rn/Lw)) | H6: R20_DMG,R12_RANGE,R20_RS | I6: L,Lw | J6: Dm→Rn→Rs→Rd | K6: L,Lw,Ls∈Z≥0; Lw>0 там, где является делителем; каждое вхождение R4/R6/R12/R20 независимо; вычисленные поля переиспользуются по порядку формулы | L6: VALIDATION_ONLY | M6: =FALSE() -> FALSE | N6: BYPASS_FORMULA_BOUNDS; CORE-187/188 | O6: EXISTS one joint witness; сохранить formulaId, formulaVersion=ITEM_FORMULAS_V1.2 и весь witness | P6: =IF(COUNTIF($A$5:$A$26,A6)=1,"PASS","DUPLICATE") -> PASS
A7: F-WPN-003 | B7: ITM-WPN-007 | C7: DEFAULT | D7: Dm = R6_DMG+L | E7: Rn = R12_RANGE+Dm+L | F7: Rs = MAX(5,CEIL(Dm×Rn/(R20_RS+2.5×Lw))) | G7: Rd = MAX(5,CEIL(3×Rn/(Lw+R6_RD))) | H7: R6_DMG,R12_RANGE,R20_RS,R6_RD | I7: L,Lw | J7: Dm→Rn→Rs→Rd | K7: L,Lw,Ls∈Z≥0; Lw>0 там, где является делителем; каждое вхождение R4/R6/R12/R20 независимо; вычисленные поля переиспользуются по порядку формулы | L7: VALIDATION_ONLY | M7: =FALSE() -> FALSE | N7: BYPASS_FORMULA_BOUNDS; CORE-187/188 | O7: EXISTS one joint witness; сохранить formulaId, formulaVersion=ITEM_FORMULAS_V1.2 и весь witness | P7: =IF(COUNTIF($A$5:$A$26,A7)=1,"PASS","DUPLICATE") -> PASS
A8: F-WPN-004 | B8: ITM-WPN-008 | C8: DEFAULT | D8: Dm = R12_DMG+L | E8: Rn = R12_RANGE+Dm+L | F8: Rs = MAX(6,CEIL(Dm×Rn/(R20_RS+2×Lw))) | G8: Rd = MAX(7,CEIL(4×Rn/(Lw+R6_RD))) | H8: R12_DMG,R12_RANGE,R20_RS,R6_RD | I8: L,Lw | J8: Dm→Rn→Rs→Rd | K8: L,Lw,Ls∈Z≥0; Lw>0 там, где является делителем; каждое вхождение R4/R6/R12/R20 независимо; вычисленные поля переиспользуются по порядку формулы | L8: VALIDATION_ONLY | M8: =FALSE() -> FALSE | N8: BYPASS_FORMULA_BOUNDS; CORE-187/188 | O8: EXISTS one joint witness; сохранить formulaId, formulaVersion=ITEM_FORMULAS_V1.2 и весь witness | P8: =IF(COUNTIF($A$5:$A$26,A8)=1,"PASS","DUPLICATE") -> PASS
A9: F-WPN-005 | B9: ITM-WPN-009 | C9: DEFAULT | D9: Dm = R20_DMG+L | E9: Rn = R20_RANGE+Dm+1.5×L | F9: Rs = MAX(8,CEIL(Dm×Rn/(R20_RS+1.5×Lw))) | G9: Rd = MAX(9,CEIL(5×Rn/(Lw+R6_RD))) | H9: R20_DMG,R20_RANGE,R20_RS,R6_RD | I9: L,Lw | J9: Dm→Rn→Rs→Rd | K9: L,Lw,Ls∈Z≥0; Lw>0 там, где является делителем; каждое вхождение R4/R6/R12/R20 независимо; вычисленные поля переиспользуются по порядку формулы | L9: VALIDATION_ONLY | M9: =FALSE() -> FALSE | N9: BYPASS_FORMULA_BOUNDS; CORE-187/188 | O9: EXISTS one joint witness; сохранить formulaId, formulaVersion=ITEM_FORMULAS_V1.2 и весь witness | P9: =IF(COUNTIF($A$5:$A$26,A9)=1,"PASS","DUPLICATE") -> PASS
A10: F-WPN-006 | B10: ITM-WPN-010 | C10: DEFAULT | F10: Rs = MAX(11,CEIL((80−Lw)/(R4_RS+L))) | G10: Rd = MAX(6,CEIL((40−Lw)/(R4_RD+L))) | H10: R4_RS,R4_RD | I10: L,Lw | J10: Rs,Rd независимо по дайсам | K10: L,Lw,Ls∈Z≥0; Lw>0 там, где является делителем; каждое вхождение R4/R6/R12/R20 независимо; вычисленные поля переиспользуются по порядку формулы | L10: VALIDATION_ONLY | M10: =FALSE() -> FALSE | N10: BYPASS_FORMULA_BOUNDS; CORE-187/188 | O10: EXISTS one joint witness; сохранить formulaId, formulaVersion=ITEM_FORMULAS_V1.2 и весь witness | P10: =IF(COUNTIF($A$5:$A$26,A10)=1,"PASS","DUPLICATE") -> PASS
A11: F-WPN-007 | B11: ITM-WPN-011 | C11: DEFAULT | F11: Rs = MAX(9,CEIL((80−(Lw+Ls)/2)/(R6_RS+L))) | G11: Rd = MAX(9,CEIL((80−(Lw+Ls)/2)/(R6_RD+L))) | H11: R6_RS,R6_RD | I11: L,Lw,Ls | J11: Rs,Rd независимо по дайсам | K11: L,Lw,Ls∈Z≥0; Lw>0 там, где является делителем; каждое вхождение R4/R6/R12/R20 независимо; вычисленные поля переиспользуются по порядку формулы | L11: VALIDATION_ONLY | M11: =FALSE() -> FALSE | N11: BYPASS_FORMULA_BOUNDS; CORE-187/188 | O11: EXISTS one joint witness; сохранить formulaId, formulaVersion=ITEM_FORMULAS_V1.2 и весь witness | P11: =IF(COUNTIF($A$5:$A$26,A11)=1,"PASS","DUPLICATE") -> PASS
A12: F-WPN-008A | B12: ITM-WPN-012 | C12: ONE_HAND | F12: Rs = MAX(13,CEIL((100−(Lw+Ls)/2)/(R4_RS+L))) | G12: Rd = MAX(9,CEIL((50−(Lw+Ls)/2)/(R4_RD+L))) | H12: R4_RS,R4_RD | I12: L,Lw,Ls | J12: Хват фиксируется | K12: L,Lw,Ls∈Z≥0; Lw>0 там, где является делителем; каждое вхождение R4/R6/R12/R20 независимо; вычисленные поля переиспользуются по порядку формулы | L12: VALIDATION_ONLY | M12: =FALSE() -> FALSE | N12: BYPASS_FORMULA_BOUNDS; CORE-187/188 | O12: EXISTS one joint witness; сохранить formulaId, formulaVersion=ITEM_FORMULAS_V1.2 и весь witness | P12: =IF(COUNTIF($A$5:$A$26,A12)=1,"PASS","DUPLICATE") -> PASS
A13: F-WPN-008B | B13: ITM-WPN-012 | C13: TWO_HAND | F13: Rs = MAX(9,CEIL((60−(Lw+Ls)/2)/(R4_RS+L))) | G13: Rd = MAX(9,CEIL((50−(Lw+Ls)/2)/(R4_RD+L))) | H13: R4_RS,R4_RD | I13: L,Lw,Ls | J13: Хват фиксируется | K13: L,Lw,Ls∈Z≥0; Lw>0 там, где является делителем; каждое вхождение R4/R6/R12/R20 независимо; вычисленные поля переиспользуются по порядку формулы | L13: VALIDATION_ONLY | M13: =FALSE() -> FALSE | N13: BYPASS_FORMULA_BOUNDS; CORE-187/188 | O13: EXISTS one joint witness; сохранить formulaId, formulaVersion=ITEM_FORMULAS_V1.2 и весь witness | P13: =IF(COUNTIF($A$5:$A$26,A13)=1,"PASS","DUPLICATE") -> PASS
A14: F-WPN-009 | B14: ITM-WPN-013 | C14: DEFAULT | F14: Rs = MAX(12,CEIL((100−(Lw+Ls)/2)/(R4_RS+L))) | G14: Rd = MAX(9,CEIL((80−(Lw+Ls)/2)/(R6_RD+L))) | H14: R4_RS,R6_RD | I14: L,Lw,Ls | K14: L,Lw,Ls∈Z≥0; Lw>0 там, где является делителем; каждое вхождение R4/R6/R12/R20 независимо; вычисленные поля переиспользуются по порядку формулы | L14: VALIDATION_ONLY | M14: =FALSE() -> FALSE | N14: BYPASS_FORMULA_BOUNDS; CORE-187/188 | O14: EXISTS one joint witness; сохранить formulaId, formulaVersion=ITEM_FORMULAS_V1.2 и весь witness | P14: =IF(COUNTIF($A$5:$A$26,A14)=1,"PASS","DUPLICATE") -> PASS
A15: F-WPN-010 | B15: ITM-WPN-014 | C15: DEFAULT | F15: Rs = MAX(5,CEIL((50−(Lw+Ls)/2)/(R6_RS+L))) | G15: Rd = MAX(12,CEIL((100−(Lw+Ls)/2)/(R4_RD+L))) | H15: R6_RS,R4_RD | I15: L,Lw,Ls | K15: L,Lw,Ls∈Z≥0; Lw>0 там, где является делителем; каждое вхождение R4/R6/R12/R20 независимо; вычисленные поля переиспользуются по порядку формулы | L15: VALIDATION_ONLY | M15: =FALSE() -> FALSE | N15: BYPASS_FORMULA_BOUNDS; CORE-187/188 | O15: EXISTS one joint witness; сохранить formulaId, formulaVersion=ITEM_FORMULAS_V1.2 и весь witness | P15: =IF(COUNTIF($A$5:$A$26,A15)=1,"PASS","DUPLICATE") -> PASS
A16: F-WPN-011 | B16: ITM-WPN-015 | C16: DEFAULT | F16: Rs = MAX(7,CEIL((70−(Lw+Ls)/2)/(R6_RS+L))) | G16: Rd = MAX(6,CEIL((70−(Lw+Ls)/2)/(R6_RD+L))) | H16: R6_RS,R6_RD | I16: L,Lw,Ls | K16: L,Lw,Ls∈Z≥0; Lw>0 там, где является делителем; каждое вхождение R4/R6/R12/R20 независимо; вычисленные поля переиспользуются по порядку формулы | L16: VALIDATION_ONLY | M16: =FALSE() -> FALSE | N16: BYPASS_FORMULA_BOUNDS; CORE-187/188 | O16: EXISTS one joint witness; сохранить formulaId, formulaVersion=ITEM_FORMULAS_V1.2 и весь witness | P16: =IF(COUNTIF($A$5:$A$26,A16)=1,"PASS","DUPLICATE") -> PASS
A17: F-WPN-012 | B17: ITM-WPN-016 | C17: DEFAULT | F17: Rs = MAX(6,CEIL((50−(Lw+Ls)/2)/(R6_RS+L))) | G17: Rd = MAX(11,CEIL((80−(Lw+Ls)/2)/(R4_RD+L))) | H17: R6_RS,R4_RD | I17: L,Lw,Ls | K17: L,Lw,Ls∈Z≥0; Lw>0 там, где является делителем; каждое вхождение R4/R6/R12/R20 независимо; вычисленные поля переиспользуются по порядку формулы | L17: VALIDATION_ONLY | M17: =FALSE() -> FALSE | N17: BYPASS_FORMULA_BOUNDS; CORE-187/188 | O17: EXISTS one joint witness; сохранить formulaId, formulaVersion=ITEM_FORMULAS_V1.2 и весь witness | P17: =IF(COUNTIF($A$5:$A$26,A17)=1,"PASS","DUPLICATE") -> PASS
A18: F-WPN-013 | B18: ITM-WPN-017 | C18: DEFAULT | F18: Rs = MAX(7,CEIL((60−(Lw+Ls)/2)/(R6_RS+L))) | G18: Rd = MAX(11,CEIL((80−(Lw+Ls)/2)/(R4_RD+L))) | H18: R6_RS,R4_RD | I18: L,Lw,Ls | K18: L,Lw,Ls∈Z≥0; Lw>0 там, где является делителем; каждое вхождение R4/R6/R12/R20 независимо; вычисленные поля переиспользуются по порядку формулы | L18: VALIDATION_ONLY | M18: =FALSE() -> FALSE | N18: BYPASS_FORMULA_BOUNDS; CORE-187/188 | O18: EXISTS one joint witness; сохранить formulaId, formulaVersion=ITEM_FORMULAS_V1.2 и весь witness | P18: =IF(COUNTIF($A$5:$A$26,A18)=1,"PASS","DUPLICATE") -> PASS
A19: F-WPN-014 | B19: ITM-WPN-018 | C19: DEFAULT | F19: Rs = MAX(10,CEIL((90−(Lw+Ls)/2)/(R6_RS+L))) | G19: Rd = MAX(9,CEIL((80−(Lw+Ls)/2)/(R6_RD+L))) | H19: R6_RS,R6_RD | I19: L,Lw,Ls | K19: L,Lw,Ls∈Z≥0; Lw>0 там, где является делителем; каждое вхождение R4/R6/R12/R20 независимо; вычисленные поля переиспользуются по порядку формулы | L19: VALIDATION_ONLY | M19: =FALSE() -> FALSE | N19: BYPASS_FORMULA_BOUNDS; CORE-187/188 | O19: EXISTS one joint witness; сохранить formulaId, formulaVersion=ITEM_FORMULAS_V1.2 и весь witness | P19: =IF(COUNTIF($A$5:$A$26,A19)=1,"PASS","DUPLICATE") -> PASS
A20: F-WPN-015 | B20: ITM-WPN-019 | C20: DEFAULT | F20: Rs = MAX(12,CEIL((100−(Lw+Ls)/2)/(R6_RS+L))) | G20: Rd = MAX(9,CEIL((90−(Lw+Ls)/2)/(R6_RD+L))) | H20: R6_RS,R6_RD | I20: L,Lw,Ls | K20: L,Lw,Ls∈Z≥0; Lw>0 там, где является делителем; каждое вхождение R4/R6/R12/R20 независимо; вычисленные поля переиспользуются по порядку формулы | L20: VALIDATION_ONLY | M20: =FALSE() -> FALSE | N20: BYPASS_FORMULA_BOUNDS; CORE-187/188 | O20: EXISTS one joint witness; сохранить formulaId, formulaVersion=ITEM_FORMULAS_V1.2 и весь witness | P20: =IF(COUNTIF($A$5:$A$26,A20)=1,"PASS","DUPLICATE") -> PASS
A21: F-WPN-016 | B21: ITM-WPN-020 | C21: DEFAULT | F21: Rs = MAX(14,CEIL((100−(Lw+Ls)/2)/(R4_RS+L))) | G21: Rd = MAX(9,CEIL((80−(Lw+Ls)/2)/(R4_RD+L))) | H21: R4_RS,R4_RD | I21: L,Lw,Ls | K21: L,Lw,Ls∈Z≥0; Lw>0 там, где является делителем; каждое вхождение R4/R6/R12/R20 независимо; вычисленные поля переиспользуются по порядку формулы | L21: VALIDATION_ONLY | M21: =FALSE() -> FALSE | N21: BYPASS_FORMULA_BOUNDS; CORE-187/188 | O21: EXISTS one joint witness; сохранить formulaId, formulaVersion=ITEM_FORMULAS_V1.2 и весь witness | P21: =IF(COUNTIF($A$5:$A$26,A21)=1,"PASS","DUPLICATE") -> PASS
A22: F-WPN-017 | B22: ITM-WPN-021 | C22: DEFAULT | F22: Rs = MAX(9,CEIL((60−(Lw+Ls)/2)/(R4_RS+L))) | G22: Rd = MAX(12,CEIL((80−(Lw+Ls)/2)/(R4_RD+L))) | H22: R4_RS,R4_RD | I22: L,Lw,Ls | K22: L,Lw,Ls∈Z≥0; Lw>0 там, где является делителем; каждое вхождение R4/R6/R12/R20 независимо; вычисленные поля переиспользуются по порядку формулы | L22: VALIDATION_ONLY | M22: =FALSE() -> FALSE | N22: BYPASS_FORMULA_BOUNDS; CORE-187/188 | O22: EXISTS one joint witness; сохранить formulaId, formulaVersion=ITEM_FORMULAS_V1.2 и весь witness | P22: =IF(COUNTIF($A$5:$A$26,A22)=1,"PASS","DUPLICATE") -> PASS
A23: F-WPN-018 | B23: ITM-WPN-022 | C23: DEFAULT | F23: Rs = MAX(10,CEIL((90−Lw)/(R6_RS+L))) | G23: Rd = MAX(9,CEIL((80−Lw)/(R6_RD+L))) | H23: R6_RS,R6_RD | I23: L,Lw | K23: L,Lw,Ls∈Z≥0; Lw>0 там, где является делителем; каждое вхождение R4/R6/R12/R20 независимо; вычисленные поля переиспользуются по порядку формулы | L23: VALIDATION_ONLY | M23: =FALSE() -> FALSE | N23: BYPASS_FORMULA_BOUNDS; CORE-187/188 | O23: EXISTS one joint witness; сохранить formulaId, formulaVersion=ITEM_FORMULAS_V1.2 и весь witness | P23: =IF(COUNTIF($A$5:$A$26,A23)=1,"PASS","DUPLICATE") -> PASS
A24: F-WPN-019 | B24: ITM-WPN-023 | C24: DEFAULT | F24: Rs = MAX(12,CEIL((100−(Lw+Ls)/2)/(R4_RS+L))) | G24: Rd = MAX(9,CEIL((80−(Lw+Ls)/2)/(R6_RD+L))) | H24: R4_RS,R6_RD | I24: L,Lw,Ls | K24: L,Lw,Ls∈Z≥0; Lw>0 там, где является делителем; каждое вхождение R4/R6/R12/R20 независимо; вычисленные поля переиспользуются по порядку формулы | L24: VALIDATION_ONLY | M24: =FALSE() -> FALSE | N24: BYPASS_FORMULA_BOUNDS; CORE-187/188 | O24: EXISTS one joint witness; сохранить formulaId, formulaVersion=ITEM_FORMULAS_V1.2 и весь witness | P24: =IF(COUNTIF($A$5:$A$26,A24)=1,"PASS","DUPLICATE") -> PASS
A25: F-WPN-020 | B25: ITM-WPN-024 | C25: DEFAULT | F25: Rs = MAX(11,CEIL((100−Lw)/(R4_RS+L))) | G25: Rd = MAX(9,CEIL((80−Lw)/(R6_RD+L))) | H25: R4_RS,R6_RD | I25: L,Lw | K25: L,Lw,Ls∈Z≥0; Lw>0 там, где является делителем; каждое вхождение R4/R6/R12/R20 независимо; вычисленные поля переиспользуются по порядку формулы | L25: VALIDATION_ONLY | M25: =FALSE() -> FALSE | N25: BYPASS_FORMULA_BOUNDS; CORE-187/188 | O25: EXISTS one joint witness; сохранить formulaId, formulaVersion=ITEM_FORMULAS_V1.2 и весь witness | P25: =IF(COUNTIF($A$5:$A$26,A25)=1,"PASS","DUPLICATE") -> PASS
A26: F-WPN-021 | B26: ITM-WPN-025 | C26: DEFAULT | F26: Rs = MAX(14,CEIL((120−Lw)/(R4_RS+L))) | G26: Rd = MAX(9,CEIL((80−Lw)/(R6_RD+L))) | H26: R4_RS,R6_RD | I26: L,Lw | K26: L,Lw,Ls∈Z≥0; Lw>0 там, где является делителем; каждое вхождение R4/R6/R12/R20 независимо; вычисленные поля переиспользуются по порядку формулы | L26: VALIDATION_ONLY | M26: =FALSE() -> FALSE | N26: BYPASS_FORMULA_BOUNDS; CORE-187/188 | O26: EXISTS one joint witness; сохранить formulaId, formulaVersion=ITEM_FORMULAS_V1.2 и весь witness | P26: =IF(COUNTIF($A$5:$A$26,A26)=1,"PASS","DUPLICATE") -> PASS

Sheet 06_Диапазоны
A1: Необходимые диапазоны для быстрого pre-check
A2: Только быстрый отсев для PLAYER_FORMULA_VALIDATED. PASS по min/max не заменяет joint witness. Границы рассчитаны для L/Lw/Ls∈Z≥0 и Lw>0 при делении; MASTER_OVERRIDE полностью их обходит.
A4: FormulaID | B4: ItemTypeID | C4: Вариант | D4: Dm min | E4: Dm max | F4: Rn min | G4: Rn max | H4: Rs min | I4: Rs max | J4: Rd min | K4: Rd max | L4: Шаг Rn | M4: Интерпретация
A5: F-WPN-001 | B5: ITM-WPN-001 | C5: DEFAULT | D5: 1 | E5: ∞ | F5: 2 | G5: ∞ | H5: 1 | I5: ∞ | J5: 1 | K5: ∞ | L5: 1 | M5: Необходимые границы при CORE-185; joint witness обязателен
A6: F-WPN-002 | B6: ITM-WPN-002 | C6: DEFAULT | D6: 1 | E6: ∞ | F6: 2 | G6: ∞ | H6: 1 | I6: ∞ | J6: 1 | K6: ∞ | L6: 1 | M6: Необходимые границы при CORE-185; joint witness обязателен
A7: F-WPN-003 | B7: ITM-WPN-007 | C7: DEFAULT | D7: 1 | E7: ∞ | F7: 2 | G7: ∞ | H7: 5 | I7: ∞ | J7: 5 | K7: ∞ | L7: 1 | M7: Необходимые границы при CORE-185; joint witness обязателен
A8: F-WPN-004 | B8: ITM-WPN-008 | C8: DEFAULT | D8: 1 | E8: ∞ | F8: 2 | G8: ∞ | H8: 6 | I8: ∞ | J8: 7 | K8: ∞ | L8: 1 | M8: Необходимые границы при CORE-185; joint witness обязателен
A9: F-WPN-005 | B9: ITM-WPN-009 | C9: DEFAULT | D9: 1 | E9: ∞ | F9: 2 | G9: ∞ | H9: 8 | I9: ∞ | J9: 9 | K9: ∞ | L9: 0.5 | M9: Необходимые границы при CORE-185; Rn имеет шаг 0,5; joint witness обязателен
A10: F-WPN-006 | B10: ITM-WPN-010 | C10: DEFAULT | H10: 11 | I10: 80 | J10: 6 | K10: 40 | L10: 1 | M10: Необходимый прямоугольник при CORE-185; пара Rs/Rd проверяется одной формулой
A11: F-WPN-007 | B11: ITM-WPN-011 | C11: DEFAULT | H11: 9 | I11: 80 | J11: 9 | K11: 80 | L11: 1 | M11: Необходимый прямоугольник при CORE-185; пара Rs/Rd проверяется одной формулой
A12: F-WPN-008A | B12: ITM-WPN-012 | C12: ONE_HAND | H12: 13 | I12: 100 | J12: 9 | K12: 50 | L12: 1 | M12: Необходимый прямоугольник при CORE-185; пара Rs/Rd проверяется одной формулой
A13: F-WPN-008B | B13: ITM-WPN-012 | C13: TWO_HAND | H13: 9 | I13: 60 | J13: 9 | K13: 50 | L13: 1 | M13: Необходимый прямоугольник при CORE-185; пара Rs/Rd проверяется одной формулой
A14: F-WPN-009 | B14: ITM-WPN-013 | C14: DEFAULT | H14: 12 | I14: 100 | J14: 9 | K14: 80 | L14: 1 | M14: Необходимый прямоугольник при CORE-185; пара Rs/Rd проверяется одной формулой
A15: F-WPN-010 | B15: ITM-WPN-014 | C15: DEFAULT | H15: 5 | I15: 50 | J15: 12 | K15: 100 | L15: 1 | M15: Необходимый прямоугольник при CORE-185; пара Rs/Rd проверяется одной формулой
A16: F-WPN-011 | B16: ITM-WPN-015 | C16: DEFAULT | H16: 7 | I16: 70 | J16: 6 | K16: 70 | L16: 1 | M16: Необходимый прямоугольник при CORE-185; пара Rs/Rd проверяется одной формулой
A17: F-WPN-012 | B17: ITM-WPN-016 | C17: DEFAULT | H17: 6 | I17: 50 | J17: 11 | K17: 80 | L17: 1 | M17: Необходимый прямоугольник при CORE-185; пара Rs/Rd проверяется одной формулой
A18: F-WPN-013 | B18: ITM-WPN-017 | C18: DEFAULT | H18: 7 | I18: 60 | J18: 11 | K18: 80 | L18: 1 | M18: Необходимый прямоугольник при CORE-185; пара Rs/Rd проверяется одной формулой
A19: F-WPN-014 | B19: ITM-WPN-018 | C19: DEFAULT | H19: 10 | I19: 90 | J19: 9 | K19: 80 | L19: 1 | M19: Необходимый прямоугольник при CORE-185; пара Rs/Rd проверяется одной формулой
A20: F-WPN-015 | B20: ITM-WPN-019 | C20: DEFAULT | H20: 12 | I20: 100 | J20: 9 | K20: 90 | L20: 1 | M20: Необходимый прямоугольник при CORE-185; пара Rs/Rd проверяется одной формулой
A21: F-WPN-016 | B21: ITM-WPN-020 | C21: DEFAULT | H21: 14 | I21: 100 | J21: 9 | K21: 80 | L21: 1 | M21: Необходимый прямоугольник при CORE-185; пара Rs/Rd проверяется одной формулой
... A26: F-WPN-021 | B26: ITM-WPN-025 | C26: DEFAULT | H26: 14 | I26: 120 | J26: 9 | K26: 80 | L26: 1 | M26: Необходимый прямоугольник при CORE-185; пара Rs/Rd проверяется одной формулой

Sheet 07_Модель_экземпляра
A1: Контракт физического экземпляра предмета
A2: ItemInstance хранит владение и физическое состояние. Числовой профиль оружия вынесен в неизменяемые WeaponProfileVersion на 07B; instanceDamage не является результатом боевого броска, instancePenetration не существует.
A4: Field | B4: Scope | C4: Data type | D4: Required | E4: Default | F4: Validation / constraint | G4: Purpose
A5: itemInstanceId | B5: ITEM_INSTANCE | C5: UUID | D5: =TRUE() -> TRUE | E5: — | F5: Уникален; неизменяем | G5: Идентичность физического экземпляра
A6: itemTypeId | B6: ITEM_INSTANCE | C6: ID | D6: =TRUE() -> TRUE | E6: — | F6: FK → 01_Каталог.ItemTypeID; после создания экземпляра не изменяется | G6: Канонический механический тип
A7: activeWeaponProfileVersionIdByVariant | B7: ITEM_INSTANCE | C7: MAP<ATTACK_VARIANT,UUID> | D7: CONDITIONAL | E7: {} | F7: Обязательно для оружия; DEFAULT для обычного, ONE_HAND/TWO_HAND для полуторного, SWORD/SHIELD/RAPIER для составного; FK → 07B | G7: Активные версии эффективного профиля
A8: massKg | B8: TEMPLATE_OR_INSTANCE | C8: DECIMAL | D8: =FALSE() -> FALSE | F8: Конечное число ≥0; если не задано в PDF — ввод мастера | G8: Метание, переносимый груз и будущая нагрузка
A9: heldSizeClass | B9: TEMPLATE_OR_INSTANCE | C9: ENUM | D9: =FALSE() -> FALSE | E9: UNKNOWN | F9: FITS_IN_FIST | LARGE | UNKNOWN | G9: Взаимодействия удержания
A10: armorWeightClass | B10: TEMPLATE | C10: ENUM | D10: =FALSE() -> FALSE | E10: UNKNOWN | F10: LIGHT | OTHER | UNKNOWN | G10: Эффекты лёгкой брони
A11: flammability | B11: TEMPLATE_OR_INSTANCE | C11: ENUM | D11: =FALSE() -> FALSE | E11: UNKNOWN | F11: COMBUSTIBLE | NONCOMBUSTIBLE | UNKNOWN | G11: Явные эффекты; предметное горение не автоматизируется
A12: isIgnitionSource | B12: TEMPLATE | C12: BOOLEAN | D12: =FALSE() -> FALSE | E12: =FALSE() -> FALSE | F12: Огниво=true; custom item — по решению мастера | G12: Воспламенение покрытия
A13: isFood | B13: TEMPLATE | C13: BOOLEAN | D13: =FALSE() -> FALSE | E13: =FALSE() -> FALSE | F13: true для конкретного пищевого custom item | G13: Допустимая цель пищевого яда
A14: canReceivePoison | B14: TEMPLATE | C14: BOOLEAN | D14: =FALSE() -> FALSE | E14: =FALSE() -> FALSE | F14: true для подходящего оружия, снаряда или пищи; каждый профиль покрытия обязан иметь effectFamily=POISON и poisonSourceKind. | G14: Допустимость типизированного ядовитого покрытия; ALL_POISON проверяется до payload.
A15: canReceiveFlammableCoating | B15: TEMPLATE | C15: BOOLEAN | D15: =FALSE() -> FALSE | E15: =FALSE() -> FALSE | F15: true для подходящего оружия или снаряда | G15: Допустимость горючего покрытия
A16: gripMode | B16: ITEM_INSTANCE | C16: ENUM | D16: CONDITIONAL | F16: ONE_HAND | TWO_HAND; обязателен для полуторного меча; после выдачи не меняется CORE-188 | G16: Фиксированный хват и формульный вариант
A17: ownerType | B17: OWNERSHIP | C17: ENUM | D17: =TRUE() -> TRUE | E17: CHARACTER | F17: CHARACTER | CORPSE | BATTLE_SCENE; доступ к CORPSE разрешается только при внешнем lootPolicy=LOOTABLE. | G17: Ровно один владелец или сцена
A18: ownerId | B18: OWNERSHIP | C18: ID | D18: =TRUE() -> TRUE | E18: — | F18: Согласован с ownerType; CHARACTER включает игрока и НПС | G18: Текущий владелец
A19: battleSceneId | B19: OWNERSHIP | C19: ID | D19: CONDITIONAL | F19: Обязателен при ownerType=BATTLE_SCENE | G19: Боевая сцена
A20: scenePointId | B20: OWNERSHIP | C20: ID | D20: CONDITIONAL | F20: Обязателен при ownerType=BATTLE_SCENE | G20: Положение брошенного предмета
A21: originalThrowerId | B21: OWNERSHIP | C21: ID | D21: =FALSE() -> FALSE | F21: Сохраняется для условного возврата после боя | G21: Исходный метатель
A22: containerId | B22: OWNERSHIP | C22: ID | D22: =FALSE() -> FALSE | F22: FK на контейнер. Для CANONICAL_MONSTER/CUSTOM_MONSTER контейнер не создаётся; LOOT guard выполняется раньше. | G22: Контейнер
A23: quantity | B23: STACK | C23: INTEGER | D23: =TRUE() -> TRUE | E23: 1 | F23: ≥1; изменение атомарно | G23: Количество
A24: stackKey | B24: STACK | C24: STRING | D24: =TRUE() -> TRUE | E24: — | F24: Учитывает itemType, активный effective profile, качество, покрытия, HP и sealed state | G24: Группировка идентичных экземпляров
A25: qualityRoll | B25: ITEM_INSTANCE | C25: INTEGER | D25: =FALSE() -> FALSE | F25: 1..20; рекомендация, не меняет механику автоматически | G25: Стартовая оценка
A26: qualityTier | B26: ITEM_INSTANCE | C26: ENUM | D26: =FALSE() -> FALSE | F26: По шкале PDF; финализирует мастер | G26: Качество
A27: equipped | B27: EQUIPMENT | C27: BOOLEAN | D27: =TRUE() -> TRUE | E27: =FALSE() -> FALSE | F27: Выданный предмет не экипируется автоматически | G27: Состояние экипировки
A28: equippedSlots | B28: EQUIPMENT | C28: ARRAY<ENUM> | D28: =FALSE() -> FALSE | E28: [] | F28: Руки или зоны тела | G28: Занятые слоты
A29: bodyZone | B29: EQUIPMENT | C29: ENUM | D29: =FALSE() -> FALSE | F29: HEAD|TORSO|ARM_L|ARM_R|LEG_L|LEG_R | G29: Зона брони
A30: currentAmmo | B30: WEAPON_STATE | C30: INTEGER | D30: =FALSE() -> FALSE | F30: 0..magazineCapacity; ёмкость не меняется CORE-188 | G30: Заряженный боезапас
A31: shieldCurrentHP | B31: WEAPON_STATE | C31: INTEGER | D31: =FALSE() -> FALSE | F31: 0..shieldMaxHP; max HP не меняется CORE-188 | G31: Текущее HP щита
A32: broken | B32: ITEM_STATE | C32: BOOLEAN | D32: =TRUE() -> TRUE | E32: =FALSE() -> FALSE | F32: При 0 HP щит не даёт бонусов; ремонт MANUAL_ONLY | G32: Неисправность
A33: sealed | B33: ITEM_STATE | C33: BOOLEAN | D33: =FALSE() -> FALSE | F33: Только Нэйт; true при выдаче | G33: Герметичность
A34: linkedSetInstanceId | B34: COMPOSITE | C34: ID | D34: =FALSE() -> FALSE | F34: Обязателен для компонентов Корнадоры/Бларадэ | G34: Связанный комплект
A35: componentRole | B35: COMPOSITE | C35: ENUM | D35: =FALSE() -> FALSE | F35: SWORD | RAPIER | SHIELD | G35: Роль компонента
A36: activeCoatings | B36: ITEM_STATE | C36: ARRAY<OBJECT> | D36: =FALSE() -> FALSE | E36: [] | F36: Каждый объект: effectFamily, poisonSourceKind, sourceAbilityId/sourceItemId, payload, appliedAt, expiry/consumeCondition. Для яда effectFamily=POISON обязателен. | G36: Яд/горючая слюна; любой ALL_POISON иммунитет блокирует обычный и симбиотический poison payload.
A37: customBonusStat | B37: CUSTOM_ITEM | C37: ENUM | D37: =FALSE() -> FALSE | F37: S|D|I|W|M|Z|C | G37: Одна характеристика custom item
A38: customBonusValue | B38: CUSTOM_ITEM | C38: INTEGER | D38: =FALSE() -> FALSE | F38: >0; только структурированный custom item | G38: Бонус
A39: activeOnlyInBackpack | B39: CUSTOM_ITEM | C39: BOOLEAN | D39: =FALSE() -> FALSE | E39: =TRUE() -> TRUE | F39: Для бонусного custom item всегда true | G39: Условие бонуса
A40: provenance | B40: AUDIT | C40: JSON | D40: =TRUE() -> TRUE | E40: — | F40: source, previousOwner, operationId; при клонировании: templateOrigin, templateId, templateVersionId|catalogVersion, sourceItemKey, cloneGraphId. | G40: Происхождение, deep-clone и доказательство отсутствия write-back.
A41: issuedBy | B41: AUDIT | C41: ID | D41: =TRUE() -> TRUE | E41: — | F41: Мастер либо процесс согласования | G41: Кто выдал
A42: issueReason | B42: AUDIT | C42: STRING | D42: =TRUE() -> TRUE | E42: — | F42: Не пусто для мастерской операции | G42: Причина выдачи
A43: createdAt | B43: AUDIT | C43: DATETIME | D43: =TRUE() -> TRUE | E43: — | F43: Неизменяемо после создания | G43: Время создания экземпляра
A44: updatedAt | B44: AUDIT | C44: DATETIME | D44: =TRUE() -> TRUE | E44: — | F44: Меняется при операции с состоянием; не подменяет аудит профиля | G44: Последнее изменение состояния
A45: cloneGraphId | B45: AUDIT | C45: UUID | D45: CONDITIONAL | F45: Обязателен для имущества инстанцированного SentientEnemy; новый на каждое добавление. | G45: Граница независимого item graph
A46: sourceItemKey | B46: AUDIT | C46: STRING | D46: CONDITIONAL | F46: Стабильный ключ предмета внутри template version; не является runtime UUID. | G46: Сопоставление clone provenance
A47: cloneSourceItemInstanceId | B47: AUDIT | C47: UUID | D47: =FALSE() -> FALSE | F47: Только аудит миграции/клона; новый itemInstanceId всегда отличен. | G47: Трассировка источника без shared mutable state
A48: templateOrigin | B48: AUDIT | C48: ENUM | D48: CONDITIONAL | F48: CAMPAIGN_CUSTOM | SYSTEM_DEFAULT_SENTIENT; для обычной выдачи может отсутствовать. | G48: Источник врага-мыслящего
A49: templateVersionRef | B49: AUDIT | C49: ID | D49: CONDITIONAL | F49: campaign versionId либо system catalogVersion; неизменяемая ссылка. | G49: Воспроизводимость клона
A50: cloneWriteBack | B50: AUDIT | C50: ENUM | D50: =TRUE() -> TRUE | E50: NONE | F50: Единственное допустимое значение NONE. | G50: Запрет изменения шаблона из экземпляра

Sheet 08_Операции
A1: Команды и пользовательские пути предметов
A2: Команды предметов и междоменный combat dispatch. ItemInstance создаётся только для предметных source; труп/лут и deep-clone SentientEnemy имеют явные guard/UUID-контракты.
A4: OperationID | B4: Command | C4: Actor | D4: Context | E4: Input / action | F4: Preconditions / validation | G4: State transition / result | H4: Rule IDs / source
A5: OP-REQ-PLAYER | B5: PLAYER_REQUEST_ITEM | C5: Игрок | D5: Только незавершённое создание собственного персонажа | E5: Выбрать тип/вариант и формульно выводимые поля не-Чистого оружия; оружие Чистых — только неизменный шаблон | F5: Не-Чистое: CORE-185 exact joint witness. Чистое: PURE_WEAPON_PROFILE_LOCKED при любом расхождении. После создания редактирование запрещено | G5: Локальная заявка; после успеха WeaponProfileVersion со statSource PLAYER_FORMULA_VALIDATED либо TEMPLATE_FIXED | H5: CORE-184; CORE-185; CORE-186; CORE-190
A6: OP-REQ-VALIDATE | B6: VALIDATE_PLAYER_WEAPON_PROFILE | C6: Система | D6: Отправка заявки при создании | E6: Проверить один общий witness L/Lw/Ls и независимые производственные дайсы | F6: FORMULA_MODE=VALIDATION_ONLY; все заявленные выходы совпадают одновременно; min/max только быстрый отказ | G6: VALID или INVALID; сохранить formulaId/formulaVersion/witness; без бросков и без создания предмета | H6: CORE-183; CORE-184; CORE-185; CORE-190
A7: OP-REQ-GM | B7: GM_FINALIZE_REQUEST | C7: Мастер | D7: До завершения создания персонажа | E7: Утвердить валидированный профиль либо применить разрешённый instanceProfilePatch | F7: Роль и причина; структурная валидация; itemTypeId существующего экземпляра неизменяем | G7: Создать полную WeaponProfileVersion; итоговый предмет не экипирован; MASTER_OVERRIDE при изменении профиля | H7: CORE-183; CORE-187; CORE-188; CORE-190
A8: OP-GM-GIVE | B8: GM_GIVE_READY_ITEM | C8: Мастер | D8: Любое допустимое состояние | E8: Выдать готовый экземпляр известного типа владельцу PLAYER/NPC | F8: Полный effective profile; неизменный шаблон может остаться TEMPLATE_FIXED, иной профиль — MASTER_OVERRIDE; reason обязателен | G8: Создать ItemInstance и начальную WeaponProfileVersion; provenance/audit | H8: CORE-183; CORE-187; CORE-188; CORE-190; AQA-032
A9: OP-GM-REMOVE | B9: GM_REMOVE_ITEM | C9: Мастер | D9: Любое допустимое состояние | E9: Изъять экземпляр/часть стека | F9: Причина обязательна | G9: Удалить у владельца; сохранить аудит | H9: AQA-032
A10: OP-GM-DESTROY | B10: GM_DESTROY_ITEM | C10: Мастер | D10: Любое допустимое состояние | E10: Уничтожить экземпляр | F10: Причина обязательна | G10: Экземпляр более недоступен; сохранить аудит | H10: AQA-032
A11: OP-GM-STORY | B11: GM_TRANSFORM_TO_STORY_ITEM | C11: Мастер | D11: Вне/в бою по мастерскому решению | E11: Преобразовать в сюжетный предмет | F11: Свободный текст не даёт механику без структуры | G11: Обновить тип/эффект и аудит | H11: AQA-032; AQ2-005
A12: OP-EQUIP | B12: EQUIP | C12: Игрок/мастер НПС | D12: Вне боя или бой | E12: Экипировать из инвентаря | F12: В бою 1 действие; требования S/D/навыка не блокируют | G12: Занять руки/зоны; посчитать штрафы | H12: AQA-014; AQA-032; CORE-016; CORE-177
A13: OP-UNEQUIP | B13: UNEQUIP | C13: Игрок/мастер НПС | D13: Вне боя или бой | E13: Снять предмет | F13: В бою 1 действие | G13: Освободить слот; вернуть в инвентарь | H13: AQA-032
A14: OP-TRANSFER | B14: TRANSFER | C14: Игрок | D14: Вне боя | E14: Передать согласному персонажу той же локации | F14: Атомарно; не допускает двойного владельца | G14: Сменить ownerId; покрытия/бонусы следуют за экземпляром | H14: AQA-032; CORE-180
A15: OP-SPLIT | B15: SPLIT_STACK | C15: Игрок/мастер | D15: Передача/лут/применение | E15: Выделить q единиц | F15: 1≤q≤quantity; сохранить stack signature | G15: Два стека; суммарное количество неизменно | H15: CQA-061; SYM-183
... A33: OP-ROUTE-SYMBIONT-XP | B33: ROUTE_SYMBIONT_XP_EVENT | C33: Система | D33: После фиксации каждого исходного D20 | E33: Передать нормализованный RollOccurrence | F33: originRollId не обработан; actorType=PLAYER_CHARACTER; rawFace=1|20; original; не confirmation/substitution | G33: Для DAMAGE/PENETRATION/ARMOR: +1 CHARACTER_PROGRESS_COUNTER; иначе маршрутизацию определяет CORE-230; повтор — NO_OP | H33: SYM-021; CORE-230; CORE-233

Sheet 09_Открытый_каталог
A1: Открытые классы, модификаторы и нарративные кандидаты
A2: Эти строки подтверждают наличие понятия/объекта в мире, но не являются готовыми полными механическими карточками. Мастер может оформить конкретный story/custom item.
A4: RefID | B4: Название/упоминание | C4: Класс | D4: Рекомендуемое представление | E4: Граница автоматизации | F4: Источник
A5: GEN-001 | B5: Материалы для изготовления | C5: C_GENERIC | D5: Не каталогизировать автоматически | E5: Крафт не автоматизируется; мастер может создать обычные предметы вручную. | F5: PDF §4.1, с. 67
A6: GEN-002 | B6: Инструменты для изготовления | C6: C_GENERIC | D6: Мастерский/сюжетный предмет | E6: Закрытого списка и бонусов нет. | F6: PDF §4.1, с. 67
A7: GEN-003 | B7: Острый предмет | C7: C_GENERIC | D7: Тег/способность экземпляра | E7: Позволяет освобождаться обычной проверкой; не отдельный шаблон. | F7: PDF с. 92
A8: GEN-004 | B8: Бритва, стамеска и сходные | C8: C_EXAMPLES | D8: Custom item | E8: Примеры коротких подручных предметов без собственного профиля. | F8: PDF с. 106
A9: GEN-005 | B9: Тяжёлое подручное средство | C9: C_GENERIC | D9: Маппинг на «Грубое оружие» по решению мастера | E9: Конкретный предмет определяет мастер. | F9: PDF с. 106
A10: GEN-006 | B10: Бросаемый предмет | C10: C_GENERIC | D10: Поведение любого экземпляра | E10: Масса и возможность броска задаются мастером. | F10: PDF с. 100
A11: GEN-007 | B11: Пища | C11: C_GENERIC | D11: Custom/stackable item | E11: Нет закрытого списка и питательной механики. | F11: PDF с. 96, 107–108
A12: GEN-008 | B12: Ингредиент | C12: C_GENERIC | D12: Custom/stackable item | E12: Нет перечня и свойств. | F12: PDF с. 108
A13: GEN-009 | B13: Некачественный алкоголь | C13: C_GENERIC | D13: Custom consumable | E13: Порог качества не определён. | F13: PDF с. 96
A14: GEN-010 | B14: Любой заявленный стартовый предмет | C14: C_OPEN_CATALOG | D14: Свободное описание → согласование мастером | E14: До структурирования не имеет механики. | F14: PDF с. 110; AQA-012
A15: GEN-011 | B15: Уникальный артефакт | C15: C_OPEN_CATALOG | D15: Только с согласия мастера | E15: Именованных артефактов с механикой нет. | F15: PDF с. 110
... A110: X-006 | B110: Яма/петля как подготовленная ловушка | C110: X_EXCLUDED | D110: Объект сцены | E110: Не помещать в инвентарь как готовый предмет. | F110: PDF с. 215

Sheet 10_Решения_и_пробелы
A1: Нормализация, конфликты и отсутствующие данные
A2: Строки OPEN_* не блокируют сам реестр: они явно определяют, где приложение должно оставить поле nullable, запросить мастера или не автоматизировать операцию.
A4: IssueID | B4: Severity | C4: Область | D4: Наблюдение | E4: Решение для разработки | F4: Status
A5: ISS-001 | B5: BLOCKER | C5: Формульное оружие | D5: У 21 типа нет канонических готовых чисел. | E5: Экземпляр получает готовые значения из заявки/решения мастера; приложение не бросает производственные дайсы. | F5: RESOLVED_BY_MODEL
A6: ISS-002 | B6: HIGH | C6: Проверка заявки игрока | D6: Независимые min/max не доказывают совместную достижимость; ранняя версия использовала L/W/S. | E6: Требовать exact joint witness по приоритетному CORE-185: L/Lw/Ls∈Z≥0, Lw>0 при делении; каждое вхождение дайса независимо. | F6: RESOLVED_BY_CORE_185
A7: ISS-003 | B7: HIGH | C7: Мастерский override | D7: Старая модель разрешала произвольные числа без полного контракта. | E7: Разрешить только поля CORE-188: закрытая грамматика DAMAGE/PENETRATION, MAP требований, rangeMeters, accuracyBonus и условный instanceDamage; formula bounds обходятся, структура — нет. | F7: RESOLVED_BY_RULES_V1.2
A8: ISS-004 | B8: HIGH | C8: Крафт | D8: CORE-014/015 исключены из runtime. | E8: Формулы сохраняются только как VALIDATION_ONLY; generationEnabled=false. | F8: RESOLVED_BY_USER
A9: ISS-005 | B9: MEDIUM | C9: Масса | D9: Нет массы всех 49 предметов; она нужна для метания/груза. | E9: massKg nullable/задаётся мастером у экземпляра; не выдумывать. | F9: OPEN_DATA
A10: ISS-006 | B10: MEDIUM | C10: Нагрузка/ёмкость | D10: Нет формулы нагрузки и ёмкости рюкзака. | E10: Не автоматизировать ограничения вместимости/веса. | F10: OPEN_RULE
A11: ISS-007 | B11: MEDIUM | C11: Экономика | D11: Нет цен и курсов монет. | E11: price/currency nullable; операции торговли не проектировать по этому реестру. | F11: OPEN_DATA
A12: ISS-008 | B12: MEDIUM | C12: Боеприпасы | D12: Не определены совместимость, масса, запас и извлечение. | E12: Хранить стрелы/болты отдельными ресурсами; совместимость — nullable/мастерская. | F12: OPEN_RULE
A13: ISS-009 | B13: MEDIUM | C13: Магазины | D13: Неясен статус отдельного предмета и частичная дозарядка. | E13: Магазины помечены PARTIAL; автоматизировать только capacity/reload профиля оружия. | F13: OPEN_RULE
A14: ISS-010 | B14: MEDIUM | C14: Комплекты | D14: Корнадора/Бларадэ одновременно комплект и раздельно метаемые компоненты. | E14: Bundle + два связанных component instances. | F14: RESOLVED_BY_MODEL
A15: ISS-011 | B15: MEDIUM | C15: Стекование | D15: Точное определение «идентичного» предмета не дано. | E15: stackKey включает профиль, качество, состояние, покрытия и состав. | F15: RESOLVED_BY_MODEL
... A45: ISS-041 | B45: HIGH | C45: Системный SentientEnemy | D45: Будущий default template origin не поддерживался item provenance. | E45: SYSTEM_DEFAULT_SENTIENT использует тот же clone, стабильные ItemType/IconAssetKey и независимый runtime graph. | F45: RESOLVED_BY_CORE_227

Sheet 11_Трассировка_правил
A1: Трассировка на Executable Rules Registry v1.7
A2: Предметные строки и 64 иконки сохранены; AQA-044/CORE-215 синхронизированы с восстановленным генератором 80–150%. Q-* остаются sourceQuestionIds.
A4: Rule ID | B4: Статус | C4: Название | D4: Итоговый алгоритм | E4: Исключения / приоритет | F4: Источник карточки
A5: CORE-014 | B5: Не автоматизируется | C5: Расчёт предмета при создании | D5: Нормативная база (действует во всей непротиворечащей части): рассчитать параметры строго в пронумерованной очередности; каждый символ дайса бросить отдельно; L=итоговый бонус Крафта; требования округлить вверх; для Rs/Rd без собственного минимума применить min=1. Приоритетные авторские дельты (заменяют только прямо пересекающиеся ветви): [Q-CORE-059] В Windows-приложении мы не рассматриваем механику крафта, она не автоматизируется с помощью windows приложения [Прямое уточнение 2026-07-28] Карточка остаётся tombstone для изготовления. Формулы являются только нормативным источником области допустимости по CORE-185: система ищет доказательство достижимости профиля, но не выполняет производственные броски, не рассчитывает материалы/время и не создаёт предмет. | E5: фиксированные заводские предметы используют собственные параметры и условия производства; создание без навыка «Крафт» требует Q-CORE-059. Поздние дельты применяются по приоритету AQ3 > AQ2 > AQA/CQA > базовая карточка; локальное исключение сильнее общего. FORMULA_MODE=VALIDATION_ONLY; generationEnabled=false. Это исключение не восстанавливает крафт. | F5: §4.1, стр. 67–68. Прямое уточнение пользователя 2026-07-28
A6: CORE-015 | B6: Не автоматизируется | C6: Время, ресурсы и успех крафта | D6: Нормативная база (действует во всей непротиворечащей части): по умолчанию craftHours=max(1,50−W); материалы списать атомарно в начале; отдельной проверки успешности нет; по окончании создать предмет с параметрами CORE-014. Приоритетные авторские дельты (заменяют только прямо пересекающиеся ветви): [Исключение из реализации] Карточка сохранена как tombstone и не исполняется приложением. крафт как игровое действие исключён Q-CORE-059 | E6: иной явно заданный срок имеет приоритет. Поздние дельты применяются по приоритету AQ3 > AQ2 > AQA/CQA > базовая карточка; локальное исключение сильнее общего. Прямое уточнение 2026-07-28 не восстанавливает изготовление, время, материалы или проверку Крафта. | F6: §4.1, стр. 67. Прямое уточнение пользователя 2026-07-28
A7: CORE-016 | B7: Активно | C7: Штраф за невыполненное требование снаряжения | D7: Нормативная база (действует во всей непротиворечащей части): для брони: суммировать S-требования всех отдельных элементов; цельный костюм учитывать один раз, дополнительные слои прибавлять; при дефиците penalty=2×(requiredS−S) ко всем физическим действиям, перемещению и активным защитам. Способ объединения нескольких дефицитов оружия не определён. Приоритетные авторские дельты (заменяют только прямо пересекающиеся ветви): [Q-CORE-004] Суммировать (если например оружие требует 14 силы и 13 ловкости, а у персонажа 12 силы и 12 ловкости, дефицит = 3, штраф = 6) Для оружия использовать полный MAP требований активной версии профиля. Суммировать положительные дефициты по всем указанным характеристикам S/D/I/W/M/Z/C и применить действующий множитель штрафа; пустая карта означает отсутствие требований. | E7: собственные штрафы предмета и классовые исключения применяются дополнительно/вместо согласно конкретному описанию. Поздние дельты применяются по приоритету AQ3 > AQ2 > AQA/CQA > базовая карточка; локальное исключение сильнее общего. | F7: §5.1, стр. 85; §5.4.7, стр. 103. Прямое уточнение пользователя 2026-07-28
A8: CORE-018 | B8: Активно | C8: Общая работа щита | D8: атака не достигает носителя; определить обычный урон атаки без отдельного спасброска брони щита; shieldHP=max(0,shieldHP−damage); избыточный урон при разрушении не переносить на носителя; при 0 HP щит уничтожен и не даёт бонусов до ремонта. | E8: пассивная броня носителя не проверяется, поскольку атака его не достигает. | F8: §4.4, стр. 77–80.
A9: CORE-019 | B9: Активно | C9: Владение щитом | D9: при навыке прибавить его бонус к атаке/блоку; без навыка применить −5 к атаке и один общий −5 к проверке блока; постоянный +3 самого щита сохраняется, отдельный −3 не добавлять. | E9: «Солдат Последнего Рассвета» добавляется там, где прямо указан. | F9: §4.4, стр. 77–80; §6.2, стр. 106.
A10: CORE-020 | B10: Активно | C10: Модификаторы оружейного навыка | D10: Нормативная база (действует во всей непротиворечащей части): подходящий навык прибавляется к тем проверкам, которые каталог называет модифицируемыми; для большинства ближнего оружия — точность и урон, для стрелкового — точность. При отсутствии применять только явно указанный штраф; если штраф не задан — 0. Приоритетные авторские дельты (заменяют только прямо пересекающиеся ветви): [Q-CORE-005] Только к броскам на меткость Если в активном профиле задан accuracyBonus, он отдельным аддитивным слагаемым прибавляется к проверке меткости; это не заменяет и не отменяет обычные характеристики, навыки, штрафы и специальные модификаторы. | E10: метание накладывает собственные совокупные штрафы CORE-128/CORE-129; смысл «к ролу» у ряда предметов требует Q-CORE-005. Поздние дельты применяются по приоритету AQ3 > AQ2 > AQA/CQA > базовая карточка; локальное исключение сильнее общего. | F10: §4.2–4.4, стр. 68–80; §6.2, стр. 106–108. Прямое уточнение пользователя 2026-07-28
A11: CORE-021 | B11: Активно | C11: Лёгкий арбалет | D11: при создании: Dm=R12+L; затем Rn=R12+Dm+L; затем Rs=ceil(Dm×Rn/(R20+3×Lw)), минимум 1; затем Rd=ceil(2×Rn/Lw), минимум 1. На каждом выстреле Pr=R12, урон = созданный Dm, предел дальности = Rn; перезарядка = 1 боевое действие. Без указанного владения −5 к точности. | E11: общие требования/стрельба/броня CORE-016, CORE-126, CORE-150. Формула создания используется только для точной проверки достижимости готового профиля игрока по CORE-185; крафт не автоматизируется. Боевые выражения активного профиля разрешаются по CORE-189. | F11: §4.2, таблица 1, стр. 68. Прямое уточнение пользователя 2026-07-28
A12: CORE-022 | B12: Активно | C12: Тяжёлый арбалет | D12: Dm=R20+L; Rn=R12+Dm+L; Rs=ceil(Dm×Rn/(R20+2×Lw)), минимум 1; Rd=ceil(2×Rn/Lw), минимум 1; на выстреле Pr=R20, урон = Dm; перезарядка 1 действие; без владения −5 к точности. | E12: общие правила стрельбы. Формула создания используется только для точной проверки достижимости готового профиля игрока по CORE-185; крафт не автоматизируется. Боевые выражения активного профиля разрешаются по CORE-189. | F12: §4.2, таблица 1, стр. 69. Прямое уточнение пользователя 2026-07-28
A13: CORE-023 | B13: Активно | C13: Кенси | D13: имеет канонический шаблон, фиксированный для заявки игрока; мастер может изменить конкретный экземпляр по CORE-187/CORE-188. Вне такого override оружие создаётся только на конвейерной линии оружейного завода Кенси: магазин 8 болтов, дальность 20 м, урон 10, Pr=R12 на выстрел; замена магазина = 1 действие; без классового навыка −15 к точности. При «Стрельбе» высокого уровня можно один раз за личный ход за 1 действие выстрелить из двух Кенси (каждый выстрел отдельно); с совершенного уровня каждому назначается собственная цель. | E13: особая серия CORE-017. PLAYER_REQUEST=TEMPLATE_FIXED: игрок не меняет характеристики оружия Чистых. MASTER_OVERRIDE конкретного экземпляра разрешён по CORE-187/CORE-188 и не изменяет глобальный шаблон. | F13: §4.2, таблица 1, стр. 69. Прямое уточнение пользователя 2026-07-28
A14: CORE-024 | B14: Активно | C14: Эривел | D14: имеет канонический шаблон, фиксированный для заявки игрока; мастер может изменить конкретный экземпляр по CORE-187/CORE-188. Вне такого override оружие создаётся только на конвейерной линии оружейного завода Эривела: магазин 4 болта; замена = 1 действие; дальность 30 м; на каждом выстреле Pr=R20, damage=2×R20; без классового навыка −15 к точности. | E14: каждый символ дайса независим. PLAYER_REQUEST=TEMPLATE_FIXED: игрок не меняет характеристики оружия Чистых. MASTER_OVERRIDE конкретного экземпляра разрешён по CORE-187/CORE-188 и не изменяет глобальный шаблон. | F14: §4.2, таблица 1, стр. 69. Прямое уточнение пользователя 2026-07-28
A15: CORE-025 | B15: Активно | C15: Эстрефорд | D15: имеет канонический шаблон, фиксированный для заявки игрока; мастер может изменить конкретный экземпляр по CORE-187/CORE-188. Вне такого override оружие создаётся только на конвейерной линии оружейного завода Эстрефорда: дальность 30 м, Pr=16, damage=30, перезарядка 1 действие; без классового навыка −15 к точности. | E15: общие правила. PLAYER_REQUEST=TEMPLATE_FIXED: игрок не меняет характеристики оружия Чистых. MASTER_OVERRIDE конкретного экземпляра разрешён по CORE-187/CORE-188 и не изменяет глобальный шаблон. | F15: §4.2, таблица 1, стр. 70. Прямое уточнение пользователя 2026-07-28
... A161: CORE-233 | B161: Активно | C161: Дедупликация события опыта по originRollId | D161: Первое валидное событие получает PENDING и затем один terminal status. Повтор того же ключа получает IGNORED_DUPLICATE и не меняет состояние. REJECTED_INVALID применяется к некорректным данным. | E161: Не дедуплицировать отдельный CHARACTERISTIC_PROGRESS CORE-085 тем же eventType; два независимых D20 имеют разные originRollId. | F161: Прямое авторское решение Q-SYMBIONT-XP-001 — опыт симбионтов за natural 20/1, 2026-07-30

Sheet 12_Справочники
A1: Справочники кодов
A2: Рекомендуемые enum-значения и смысловые договорённости для модели приложения.
A4: Dictionary | B4: Code | C4: Meaning
A5: CATALOG_CLASS | B5: A_CANONICAL | C5: Именованный предмет из таблиц 1–5 PDF
A6: CATALOG_CLASS | B6: B_EXPLICIT | C6: Явная предметная сущность вне таблиц
A7: CATALOG_CLASS | B7: C_GENERIC | C7: Открытый класс/пример для решения мастера
A8: CATALOG_CLASS | B8: D_NARRATIVE | C8: Упоминание мира без собственной механики
A9: MECHANICS | B9: FULL | C9: Достаточно данных для основной runtime-механики
A10: MECHANICS | B10: PARTIAL | C10: Сущность участвует в правилах, но часть полей не определена
A11: PARAMETER_SOURCE | B11: TEMPLATE_FIXED | C11: Готовые параметры неизменны в каноническом шаблоне; боевые Runtime-броски описываются отдельно.
A12: PARAMETER_SOURCE | B12: INSTANCE_RESOLVED | C12: Готовые параметры сохраняются у экземпляра; результаты боевых Runtime-бросков сюда не входят.
A13: PARAMETER_SOURCE | B13: INSTANCE_ZONE | C13: Экземпляр требует выбора зоны
A14: STAT_SOURCE | B14: PLAYER_FORMULA_VALIDATED | C14: Игрок указал только формульные выходы; найден joint witness и сохранена версия формулы.
A15: STAT_SOURCE | B15: MASTER_OVERRIDE | C15: Мастер указал профиль вне формул с аудитом
... A124: ProcessingStatus | B124: REJECTED_INVALID | C124: Невалидная структура RollOccurrence отклонена до изменения состояния.

Sheet 13_Контроль
A1: Автоматический контроль целостности v1.6_with_icons
A2: Все строки должны иметь PASS. Каталог, формулы, баланс и 64 PNG неизменны; trace AQA-044/CORE-215 согласован с Rules v1.7.
A4: Проверка | B4: Фактическое значение | C4: Ожидается | D4: Статус | E4: Комментарий
A5: Основной каталог: строки | B5: =COUNTA('01_Каталог'!$A$5:$A$68) -> 64 | C5: 64 | D5: =IF(B5=C5,"PASS","FAIL") -> PASS | E5: 49 A + 15 B
A6: Канонические предметы | B6: =COUNTIF('01_Каталог'!$F$5:$F$68,"A_CANONICAL") -> 49 | C6: 49 | D6: =IF(B6=C6,"PASS","FAIL") -> PASS | E6: Таблицы 1–5
A7: Явные сущности B | B7: =COUNTIF('01_Каталог'!$F$5:$F$68,"B_EXPLICIT") -> 15 | C7: 15 | D7: =IF(B7=C7,"PASS","FAIL") -> PASS | E7: Вне таблиц
A8: Оружие | B8: =COUNTIF('01_Каталог'!$D$5:$D$68,"Оружие") -> 27 | C8: 27 | D8: =IF(B8=C8,"PASS","FAIL") -> PASS | E8: Включая щиты и комплекты
A9: Броня | B9: =COUNTIF('01_Каталог'!$D$5:$D$68,"Броня") -> 8 | C9: 8 | D9: =IF(B9=C9,"PASS","FAIL") -> PASS
A10: Фармацевтика | B10: =COUNTIF('01_Каталог'!$D$5:$D$68,"Фармацевтика") -> 14 | C10: 14 | D10: =IF(B10=C10,"PASS","FAIL") -> PASS
A11: Формульные типы | B11: =COUNTIF('01_Каталог'!$O$5:$O$68,"EXACT_JOINT_FORMULA") -> 21 | C11: 21 | D11: =IF(B11=C11,"PASS","FAIL") -> PASS | E11: Полуторный меч — один тип, два хвата
A12: Профили формул | B12: =COUNTA('05_Формулы_валидации'!$A$5:$A$26) -> 22 | C12: 22 | D12: =IF(B12=C12,"PASS","FAIL") -> PASS
A13: Уникальные ItemTypeID | B13: =COUNTIF('01_Каталог'!$U$5:$U$68,"PASS") -> 64 | C13: 64 | D13: =IF(B13=C13,"PASS","FAIL") -> PASS
A14: Уникальные FormulaID | B14: =COUNTIF('05_Формулы_валидации'!$P$5:$P$26,"PASS") -> 22 | C14: 22 | D14: =IF(B14=C14,"PASS","FAIL") -> PASS
A15: Catalog generation enabled = FALSE | B15: =COUNTA('01_Каталог'!$R$5:$R$68)-COUNTIF('01_Каталог'!$R$5:$R$68,TRUE()) -> 64 | C15: 64 | D15: =IF(B15=C15,"PASS","FAIL") -> PASS | E15: Ни один предмет каталога не создаётся формулами
A16: Formula mode VALIDATION_ONLY | B16: =COUNTIF('05_Формулы_валидации'!$L$5:$L$26,"VALIDATION_ONLY") -> 22 | C16: 22 | D16: =IF(B16=C16,"PASS","FAIL") -> PASS
A17: Formula generation enabled = FALSE | B17: =COUNTA('05_Формулы_валидации'!$M$5:$M$26)-COUNTIF('05_Формулы_валидации'!$M$5:$M$26,TRUE()) -> 22 | C17: 22 | D17: =IF(B17=C17,"PASS","FAIL") -> PASS | E17: Формулы работают только как validator
A18: GM instance override allowed | B18: =IF(AND('01_Каталог'!$P$5=TRUE(),'01_Каталог'!$P$6=TRUE(),'01_Каталог'!$P$7=TRUE(),'01_Каталог'!$P$8=TRUE(),'01_Каталог'!$P$9=TRUE(),'01_Каталог'!$P$10=TRUE(),'01_Каталог'!$P$11=TRUE(),'01_Каталог'!$P$12=TRUE(),'01_Каталог'!$P$13=TRUE(),'01_Каталог'!$P$14=TRUE(),'01_Каталог'!$P$15=TRUE(),'01_Каталог'!$P$16=TRUE(),'01_Каталог'!$P$17=TRUE(),'01_Каталог'!$P$18=TRUE(),'01_Каталог'!$P$19=TRUE(),'01_Каталог'!$P$20=TRUE(),'01_Каталог'!$P$21=TRUE(),'01_Каталог'!$P$22=TRUE(),'01_Каталог'!$P$23=TRUE(),'01_Каталог'!$P$24=TRUE(),'01_Каталог'!$P$25=TRUE(),'01_Каталог'!$P$26=TRUE(),'01_Каталог'!$P$27=TRUE(),'01_Каталог'!$P$28=TRUE(),'01_Каталог'!$P$29=TRUE(),'01_Каталог'!$P$30=TRUE(),'01_Каталог'!$P$31=TRUE()),27,0) -> 27 | C18: 27 | D18: =IF(B18=C18,"PASS","FAIL") -> PASS | E18: Все оружие, включая 6 типов Чистых
A19: Профили оружия | B19: =COUNTA('02_Профили_оружия'!$A$5:$A$31) -> 27 | C19: 27 | D19: =IF(B19=C19,"PASS","FAIL") -> PASS
A20: Профили брони | B20: =COUNTA('03_Профили_брони'!$A$5:$A$12) -> 8 | C20: 8 | D20: =IF(B20=C20,"PASS","FAIL") -> PASS
A21: Профили фармацевтики | B21: =COUNTA('04_Фармацевтика'!$A$5:$A$18) -> 14 | C21: 14 | D21: =IF(B21=C21,"PASS","FAIL") -> PASS
A22: Отсутствующие Rule ID в трассировке | B22: =COUNTIF('11_Трассировка_правил'!$B$5:$B$156,"MISSING") -> 0 | C22: 0 | D22: =IF(B22=C22,"PASS","FAIL") -> PASS | E22: Все выбранные источники найдены в v1.4
A23: Нормализованные боевые значения | B23: =COUNTA('02A_Семантика_Runtime'!$A$5:$A$69) -> 65 | C23: 65 | D23: =IF(B23=C23,"PASS","FAIL") -> PASS | E23: 58 оружейных + 7 броневых
A24: Уникальные CombatValueDefID | B24: =COUNTIF('02A_Семантика_Runtime'!$V$5:$V$69,"PASS") -> 65 | C24: 65 | D24: =IF(B24=C24,"PASS","FAIL") -> PASS | E24: Все определения имеют уникальный ID
A25: Семантический контракт Runtime | B25: =COUNTIF('02A_Семантика_Runtime'!$W$5:$W$69,"PASS") -> 65 | C25: 65 | D25: =IF(B25=C25,"PASS","FAIL") -> PASS | E25: valueMode/scope/group/persistence согласованы
A26: Определения DAMAGE | B26: =COUNTIF('02A_Семантика_Runtime'!$E$5:$E$69,"DAMAGE") -> 29 | C26: 29 | D26: =IF(B26=C26,"PASS","FAIL") -> PASS | E26: 27 одинарных вариантов + 2 варианта Бларадэ
A27: Определения PENETRATION | B27: =COUNTIF('02A_Семантика_Runtime'!$E$5:$E$69,"PENETRATION") -> 29 | C27: 29 | D27: =IF(B27=C27,"PASS","FAIL") -> PASS | E27: 27 одинарных вариантов + 2 варианта Бларадэ
A28: Определения ARMOR | B28: =COUNTIF('02A_Семантика_Runtime'!$E$5:$E$69,"ARMOR") -> 7 | C28: 7 | D28: =IF(B28=C28,"PASS","FAIL") -> PASS | E28: Нэйт не имеет runtime-брони
A29: VALUE_MODE = INSTANCE_VALUE | B29: =COUNTIF('02A_Семантика_Runtime'!$G$5:$G$69,"INSTANCE_VALUE") -> 5 | C29: 5 | D29: =IF(B29=C29,"PASS","FAIL") -> PASS | E29: Лёгкий/тяжёлый арбалет и три лука
A30: VALUE_MODE = CONSTANT | B30: =COUNTIF('02A_Семантика_Runtime'!$G$5:$G$69,"CONSTANT") -> 3 | C30: 3 | D30: =IF(B30=C30,"PASS","FAIL") -> PASS | E30: Кенси damage, Эстрефорд damage+penetration
A31: VALUE_MODE = PER_ATTACK_ROLL | B31: =COUNTIF('02A_Семантика_Runtime'!$G$5:$G$69,"PER_ATTACK_ROLL") -> 57 | C31: 57 | D31: =IF(B31=C31,"PASS","FAIL") -> PASS | E31: Новый бросок на каждую отдельно разрешаемую атаку
A32: PER_ATTACK_ROLL имеет корректный scope | B32: =COUNTIFS('02A_Семантика_Runtime'!$G$5:$G$69,"PER_ATTACK_ROLL",'02A_Семантика_Runtime'!$M$5:$M$69,"EACH_RESOLVED_ATTACK") -> 57 | C32: 57 | D32: =IF(B32=C32,"PASS","FAIL") -> PASS | E32: Ни один боевой дайс не имеет scope экземпляра
A33: PER_ATTACK_ROLL имеет rollGroupId | B33: =COUNTIFS('02A_Семантика_Runtime'!$G$5:$G$69,"PER_ATTACK_ROLL",'02A_Семантика_Runtime'!$N$5:$N$69,"<>") -> 57 | C33: 57 | D33: =IF(B33=C33,"PASS","FAIL") -> PASS | E33: Сырые броски адресуются по группе
A34: Dice-free определения без rollGroupId | B34: =COUNTBLANK('02A_Семантика_Runtime'!$N$5:$N$69) -> 8 | C34: 8 | D34: =IF(B34=C34,"PASS","FAIL") -> PASS | E34: INSTANCE_VALUE + CONSTANT
A35: Dm ссылается на instanceDamage | B35: =COUNTIFS('02A_Семантика_Runtime'!$G$5:$G$69,"INSTANCE_VALUE",'02A_Семантика_Runtime'!$O$5:$O$69,"instanceDamage") -> 5 | C35: 5 | D35: =IF(B35=C35,"PASS","FAIL") -> PASS | E35: Готовое производственное значение
A36: Итоги сохраняются только в AttackResolution/log | B36: =COUNTIF('02A_Семантика_Runtime'!$Q$5:$Q$69,"ATTACK_RESOLUTION_AND_COMBAT_LOG") -> 65 | C36: 65 | D36: =IF(B36=C36,"PASS","FAIL") -> PASS | E36: ItemInstance не мутирует
A37: Сырые броски PER_ATTACK сохраняются в AttackResolution/log | B37: =COUNTIFS('02A_Семантика_Runtime'!$G$5:$G$69,"PER_ATTACK_ROLL",'02A_Семантика_Runtime'!$R$5:$R$69,"ATTACK_RESOLUTION_AND_COMBAT_LOG") -> 57 | C37: 57 | D37: =IF(B37=C37,"PASS","FAIL") -> PASS | E37: Один результат на rollGroupId
A38: instancePenetration отсутствует | B38: =COUNTIF('07_Модель_экземпляра'!$A$5:$A$44,"instancePenetration")+COUNTIF('07B_Профиль_оружия'!$A$5:$A$33,"instancePenetration") -> 0 | C38: 0 | D38: =IF(B38=C38,"PASS","FAIL") -> PASS | E38: Пробитие не является свойством экземпляра
A39: instanceDamage присутствует ровно один раз | B39: =COUNTIF('07B_Профиль_оружия'!$A$5:$A$33,"instanceDamage") -> 1 | C39: 1 | D39: =IF(B39=C39,"PASS","FAIL") -> PASS | E39: Только поле WeaponProfileVersion для INSTANCE_VALUE
A40: Заголовок атомарности перезарядки уточнён | B40: =COUNTIF('02_Профили_оружия'!$O$4,"Перезарядка атомарна") -> 1 | C40: 1 | D40: =IF(B40=C40,"PASS","FAIL") -> PASS | E40: Поле относится только к reload cost
A41: Поля контракта AttackResolution | B41: =COUNTA('07A_Разрешение_атаки'!$A$5:$A$18) -> 14 | C41: 14 | D41: =IF(B41=C41,"PASS","FAIL") -> PASS | E41: Включая version IDs, variant и snapshot
A42: Эривел: damage и penetration независимы | B42: =IF('02A_Семантика_Runtime'!$N$11<>'02A_Семантика_Runtime'!$N$12,1,0) -> 1 | C42: 1 | D42: =IF(B42=C42,"PASS","FAIL") -> PASS | E42: Разные rollGroupId
A43: Айнцберн: damage и penetration независимы | B43: =IF('02A_Семантика_Runtime'!$N$15<>'02A_Семантика_Runtime'!$N$16,1,0) -> 1 | C43: 1 | D43: =IF(B43=C43,"PASS","FAIL") -> PASS | E43: Разные rollGroupId
A44: Эривел: 2*R20 означает один бросок | B44: =COUNTIFS('02A_Семантика_Runtime'!$B$5:$B$69,"ITM-WPN-004",'02A_Семантика_Runtime'!$E$5:$E$69,"DAMAGE",'02A_Семантика_Runtime'!$I$5:$I$69,"2*ROLL(R20)",'02A_Семантика_Runtime'!$N$5:$N$69,"<>") -> 1 | C44: 1 | D44: =IF(B44=C44,"PASS","FAIL") -> PASS | E44: Один токен R20 и один rollGroupId
A45: Гленхейм: 2*R20+5 означает тот же бросок | B45: =COUNTIFS('02A_Семантика_Runtime'!$B$5:$B$69,"ITM-ARM-008",'02A_Семантика_Runtime'!$I$5:$I$69,"2*ROLL(R20)+5",'02A_Семантика_Runtime'!$N$5:$N$69,"<>") -> 1 | C45: 1 | D45: =IF(B45=C45,"PASS","FAIL") -> PASS | E45: Множитель не создаёт второй R20
A46: Оружие Чистых locked игроку и override мастеру | B46: =IF(AND('01_Каталог'!$O$7="TEMPLATE_FIXED",'01_Каталог'!$P$7=TRUE(),'01_Каталог'!$O$8="TEMPLATE_FIXED",'01_Каталог'!$P$8=TRUE(),'01_Каталог'!$O$9="TEMPLATE_FIXED",'01_Каталог'!$P$9=TRUE(),'01_Каталог'!$O$10="TEMPLATE_FIXED",'01_Каталог'!$P$10=TRUE(),'01_Каталог'!$O$30="TEMPLATE_FIXED",'01_Каталог'!$P$30=TRUE(),'01_Каталог'!$O$31="TEMPLATE_FIXED",'01_Каталог'!$P$31=TRUE()),6,0) -> 6 | C46: 6 | D46: =IF(B46=C46,"PASS","FAIL") -> PASS | E46: Шесть канонических типов CORE-186
A47: STAT_SOURCE PLAYER_FORMULA_VALIDATED | B47: =COUNTIFS('12_Справочники'!$A$5:$A$82,"STAT_SOURCE",'12_Справочники'!$B$5:$B$82,"PLAYER_FORMULA_VALIDATED") -> 1 | C47: 1 | D47: =IF(B47=C47,"PASS","FAIL") -> PASS | E47: Единственное каноническое имя enum
A48: Устаревший PLAYER_REQUEST_VALIDATED отсутствует | B48: =COUNTIF('12_Справочники'!$B$5:$B$82,"PLAYER_REQUEST_VALIDATED") -> 0 | C48: 0 | D48: =IF(B48=C48,"PASS","FAIL") -> PASS | E48: Нет legacy enum
A49: Формулы используют домен CORE-185 | B49: =COUNTA('05_Формулы_валидации'!$K$5:$K$26) -> 22 | C49: 22 | D49: =IF(B49=C49,"PASS","FAIL") -> PASS | E49: L/Lw/Ls; неотрицательные; содержимое дополнительно проверяется при сборке
A50: Мастерская грамматика дайсов | B50: =COUNTA('07B_Профиль_оружия'!$A$38:$A$45) -> 8 | C50: 8 | D50: =IF(B50=C50,"PASS","FAIL") -> PASS | E50: Закрытый список CORE-188
A51: Bare R20 не выбирается мастером | B51: =COUNTIF('07B_Профиль_оружия'!$A$38:$A$45,"R20") -> 0 | C51: 0 | D51: =IF(B51=C51,"PASS","FAIL") -> PASS | E51: Канонический R20 может лишь наследоваться
A52: Разрешённые поля master patch | B52: =COUNTA('07B_Профиль_оружия'!$A$50:$A$55) -> 6 | C52: 6 | D52: =IF(B52=C52,"PASS","FAIL") -> PASS | E52: Никакие шаблонные спецсвойства не меняются
A53: Поля WeaponProfileVersion | B53: =COUNTA('07B_Профиль_оружия'!$A$5:$A$33) -> 29 | C53: 29 | D53: =IF(B53=C53,"PASS","FAIL") -> PASS | E53: Версия, owner scope, effective profile и аудит
A54: Строк трассировки v1.4 | B54: =COUNTA('11_Трассировка_правил'!$A$5:$A$156) -> 152 | C54: 152 | D54: =IF(B54=C54,"PASS","FAIL") -> PASS | E54: 109 исторических + v1.3/v1.4 зависимости
A55: CORE-216…229 в трассировке | B55: =COUNTIF('11_Трассировка_правил'!$A$5:$A$156,"CORE-216")+COUNTIF('11_Трассировка_правил'!$A$5:$A$156,"CORE-217")+COUNTIF('11_Трассировка_правил'!$A$5:$A$156,"CORE-218")+COUNTIF('11_Трассировка_правил'!$A$5:$A$156,"CORE-219")+COUNTIF('11_Трассировка_правил'!$A$5:$A$156,"CORE-220")+COUNTIF('11_Трассировка_правил'!$A$5:$A$156,"CORE-221")+COUNTIF('11_Трассировка_правил'!$A$5:$A$156,"CORE-222")+COUNTIF('11_Трассировка_правил'!$A$5:$A$156,"CORE-223")+COUNTIF('11_Трассировка_правил'!$A$5:$A$156,"CORE-224")+COUNTIF('11_Трассировка_правил'!$A$5:$A$156,"CORE-225")+COUNTIF('11_Трассировка_правил'!$A$5:$A$156,"CORE-226")+COUNTIF('11_Трассировка_правил'!$A$5:$A$156,"CORE-227")+COUNTIF('11_Трассировка_правил'!$A$5:$A$156,"CORE-228")+COUNTIF('11_Трассировка_правил'!$A$5:$A$156,"CORE-229") -> 14 | C55: 14 | D55: =IF(B55=C55,"PASS","FAIL") -> PASS | E55: Все новые правила присутствуют
A56: Трассировка указывает v1.7 | B56: =IF('11_Трассировка_правил'!$A$1="Трассировка на Executable Rules Registry v1.7",1,0) -> 1 | C56: 1 | D56: =IF(B56=C56,"PASS","FAIL") -> PASS | E56: Источник обновлён до Rules v1.7
A57: baseExpression отделён от attacker stat | B57: =COUNTIFS('02A_Семантика_Runtime'!$E$5:$E$69,"DAMAGE",'02A_Семантика_Runtime'!$J$5:$J$69,"<>",'02A_Семантика_Runtime'!$J$5:$J$69,"<>NONE") -> 20 | C57: 20 | D57: =IF(B57=C57,"PASS","FAIL") -> PASS | E57: S/D добавляется один раз
A58: sourceScope заполнен | B58: =COUNTIF('02A_Семантика_Runtime'!$K$5:$K$69,"<>") -> 65 | C58: 65 | D58: =IF(B58=C58,"PASS","FAIL") -> PASS | E58: Не смешан с evaluationScope
A59: NPC scope в операции master patch | B59: =IF(AND('08_Операции'!$B$28="MASTER_PATCH_WEAPON_PROFILE",'08_Операции'!$D$28="Инвентарь любого игрока или НПС"),1,0) -> 1 | C59: 1 | D59: =IF(B59=C59,"PASS","FAIL") -> PASS | E59: Отдельная операция изменения оружия
A60: Master override header синхронизирован | B60: =COUNTIF('01_Каталог'!$P$4,"Master profile override allowed") -> 1 | C60: 1 | D60: =IF(B60=C60,"PASS","FAIL") -> PASS | E60: Видимый и внутренний заголовок будут одинаковы
A61: Коды ошибок профиля = Rules v1.5 | B61: =COUNTIF('12_Справочники'!$A$5:$A$108,"VALIDATION_ERROR") -> 15 | C61: 15 | D61: =IF(B61=C61,"PASS","FAIL") -> PASS | E61: 15 weapon-profile ошибок; combat/catalog errors типизированы отдельно
A62: FORMULA_PROFILE_REQUIRED присутствует | B62: =COUNTIFS('12_Справочники'!$A$5:$A$82,"VALIDATION_ERROR",'12_Справочники'!$B$5:$B$82,"FORMULA_PROFILE_REQUIRED") -> 1 | C62: 1 | D62: =IF(B62=C62,"PASS","FAIL") -> PASS | E62: Обязательный код CORE-184
A63: Ненормативный EFFECTIVE_WEAPON_PROFILE_INCOMPLETE отсутствует | B63: =COUNTIF('12_Справочники'!$B$5:$B$82,"EFFECTIVE_WEAPON_PROFILE_INCOMPLETE") -> 0 | C63: 0 | D63: =IF(B63=C63,"PASS","FAIL") -> PASS | E63: Item Registry не расширяет weapon enum Rules v1.5
A64: Исторические ссылки v1.2 сохранены | B64: 6 | C64: 6 | D64: PASS | E64: Исторические строки не переписываются; текущая версия задаётся паспортом и трассировкой
A65: Основной каталог v1.3 | B65: =COUNTA('01_Каталог'!$A$5:$A$68) -> 64 | C65: 64 | D65: =IF(B65=C65,"PASS","FAIL") -> PASS | E65: ItemTypeID неизменны
A66: Строк иконок v1.3 | B66: =COUNTIF('15_Иконки_предметов'!$L$5:$L$68,"PASS") -> 64 | C66: 64 | D66: =IF(B66=C66,"PASS","FAIL") -> PASS | E66: PNG 96×96
A67: Новых monster/web ItemTypeID | B67: 0 | C67: 0 | D67: =IF(B67=C67,"PASS","FAIL") -> PASS | E67: Должно быть 0
A68: Forbidden web refs | B68: =COUNTIF('09_Открытый_каталог'!$D$5:$D$110,"CREATION_FORBIDDEN") -> 2 | C68: 2 | D68: =IF(B68=C68,"PASS","FAIL") -> PASS | E68: MOD-005/006 CREATION_FORBIDDEN
A69: Непредметных source kind | B69: =COUNTA('07C_Непредметные_атаки'!$A$5:$A$9) -> 5 | C69: 5 | D69: =IF(B69=C69,"PASS","FAIL") -> PASS | E69: 07C
A70: Полей source-neutral AttackResolution | B70: =COUNTA('07A_Разрешение_атаки'!$A$5:$A$32) -> 28 | C70: 28 | D70: =IF(B70=C70,"PASS","FAIL") -> PASS | E70: 14 старых + 14 новых
A71: DefenseChoice NONE | B71: =COUNTIFS('07A_Разрешение_атаки'!$A$5:$A$32,"defenseChoice",'07A_Разрешение_атаки'!$E$5:$E$32,"NONE") -> 1 | C71: 1 | D71: =IF(B71=C71,"PASS","FAIL") -> PASS | E71: 07A
A72: ArmorLayerState NO_LAYERS | B72: =COUNTIFS('12_Справочники'!$A$5:$A$108,"ARMOR_LAYER_STATE",'12_Справочники'!$B$5:$B$108,"NO_LAYERS") -> 1 | C72: 1 | D72: =IF(B72=C72,"PASS","FAIL") -> PASS | E72: 12_Справочники
A73: Операций corpse guard | B73: =COUNTIF('08_Операции'!$B$5:$B$32,"CHECK_CORPSE_LOOT_POLICY") -> 1 | C73: 1 | D73: =IF(B73=C73,"PASS","FAIL") -> PASS | E73: До container dereference
A74: Операций deep clone | B74: =COUNTIF('08_Операции'!$B$5:$B$32,"DEEP_CLONE_SENTIENT_INVENTORY") -> 1 | C74: 1 | D74: =IF(B74=C74,"PASS","FAIL") -> PASS | E74: SentientEnemy item graph
A75: Типизированных ядов Тайпана | B75: 3 | C75: 3 | D75: =IF(B75=C75,"PASS","FAIL") -> PASS | E75: POISON/SYMBIOTIC
A76: SYSTEM_DEFAULT_SENTIENT origin | B76: =COUNTIFS('12_Справочники'!$A$5:$A$108,"TEMPLATE_ORIGIN",'12_Справочники'!$B$5:$B$108,"SYSTEM_DEFAULT_SENTIENT") -> 1 | C76: 1 | D76: =IF(B76=C76,"PASS","FAIL") -> PASS | E76: Будущий pack
A77: Сценариев QA v1.3 | B77: =COUNTIF('17_QA_совместимость'!$G$5:$G$20,"PASS") -> 16 | C77: 16 | D77: =IF(B77=C77,"PASS","FAIL") -> PASS | E77: 17_QA_совместимость
A78: Runtime-вариантов хвата ITM-WPN-012 | B78: =COUNTIFS('02A_Семантика_Runtime'!$B$5:$B$69,"ITM-WPN-012",'02A_Семантика_Runtime'!$D$5:$D$69,"ONE_HAND")+COUNTIFS('02A_Семантика_Runtime'!$B$5:$B$69,"ITM-WPN-012",'02A_Семантика_Runtime'!$D$5:$D$69,"TWO_HAND") -> 4 | C78: 4 | D78: =IF(B78=C78,"PASS","FAIL") -> PASS | E78: ONE_HAND/TWO_HAND × DAMAGE/PENETRATION
A79: CORE-229 и criticalResolution | B79: =COUNTIF('11_Трассировка_правил'!$A$5:$A$156,"CORE-229")+COUNTIF('07A_Разрешение_атаки'!$A$5:$A$32,"criticalResolutionByStage") -> 2 | C79: 2 | D79: =IF(B79=C79,"PASS","FAIL") -> PASS | E79: Trace + поле боевого порядка критов
A80: MON-115 в трассировке | B80: =COUNTIF('11_Трассировка_правил'!$A$5:$A$156,"MON-115") -> 1 | C80: 1 | D80: =IF(B80=C80,"PASS","FAIL") -> PASS | E80: Локальный armor override
A81: Политика IGNORE_ARMOR в 07C | B81: =IF('07C_Непредметные_атаки'!$G$7="Typed profile; armorPolicy from contract. IGNORE_ARMOR_BY_MON-115 => penetrationResolution=SKIP; no armor roll/comparison.",1,0) -> 1 | C81: 1 | D81: =IF(B81=C81,"PASS","FAIL") -> PASS | E81: Canonical special attack
A82: Сценариев QA v1.4 | B82: =COUNTIF('17_QA_совместимость'!$G$5:$G$20,"PASS") -> 16 | C82: 16 | D82: =IF(B82=C82,"PASS","FAIL") -> PASS | E82: 17_QA_совместимость
A83: Runtime rows имеют rollKind | B83: =COUNTA('02A_Семантика_Runtime'!$X$5:$X$69) -> 65 | C83: 65 | D83: =IF(B83=C83,"PASS","FAIL") -> PASS | E83: 02A X5:X69
A84: Runtime rows имеют dieType | B84: =COUNTA('02A_Семантика_Runtime'!$Y$5:$Y$69) -> 65 | C84: 65 | D84: =IF(B84=C84,"PASS","FAIL") -> PASS | E84: 02A Y5:Y69
A85: D20 rows классифицированы NO_DIRECT_BUT_POOL | B85: =COUNTIFS('02A_Семантика_Runtime'!$Y$5:$Y$69,"D20",'02A_Семантика_Runtime'!$Z$5:$Z$69,"NO_DIRECT_BUT_POOL") -> 25 | C85: 25 | D85: =IF(B85=C85,"PASS","FAIL") -> PASS | E85: 02A Y/Z
A86: RollOccurrence contract fields | B86: =COUNTA('19_XP_RollOccurrences'!$A$5:$A$27) -> 23 | C86: 23 | D86: =IF(B86=C86,"PASS","FAIL") -> PASS | E86: 19_XP_RollOccurrences
A87: Новые XP Rule IDs в трассировке | B87: =COUNTIF('11_Трассировка_правил'!$A$5:$A$161,"CORE-229")+COUNTIF('11_Трассировка_правил'!$A$5:$A$161,"SYM-021")+COUNTIF('11_Трассировка_правил'!$A$5:$A$161,"CORE-230")+COUNTIF('11_Трассировка_правил'!$A$5:$A$161,"CORE-231")+COUNTIF('11_Трассировка_правил'!$A$5:$A$161,"CORE-232")+COUNTIF('11_Трассировка_правил'!$A$5:$A$161,"CORE-233") -> 6 | C87: 6 | D87: =IF(B87=C87,"PASS","FAIL") -> PASS | E87: CORE-229; SYM-021; CORE-230…233
A88: Dependency tuple | B88: Rules v1.7 | Character-Skills-Symbionts v1.2 | Items v1.6_with_icons | Bestiary v1.4 | Sentient v1.2 | C88: Rules v1.7 | Character-Skills-Symbionts v1.2 | Items v1.6_with_icons | Bestiary v1.4 | Sentient v1.2 | D88: PASS | E88: Current extension tuple; frozen consumers use builtAgainst + forward compatibility

Sheet 02A_Семантика_Runtime
A1: Машинооднозначная семантика Runtime — статические определения шаблонов
A2: baseExpression не содержит attacker.S/D: характеристика добавляется один раз через damageModifierStat. Каждый исходный D20 получает RollOccurrence. DAMAGE/PENETRATION/ARMOR остаются некритическими и имеют NO_DIRECT_BUT_POOL только для PLAYER_CHARACTER rawFace=1/20.
A4: CombatValueDefID | B4: ItemTypeID | C4: Название | D4: attackVariantId | E4: valueKind | F4: sourceNotation | G4: valueMode | H4: effectiveTemplateExpression | I4: baseExpression | J4: damageModifierStat | K4: sourceScope | L4: conditionalOverride | M4: evaluationScope | N4: rollGroupId | O4: instanceSourceField | P4: resolvedResultField | Q4: resolvedResultPersistence | R4: rawRollPersistence | S4: Примечание | T4: Rule ID | U4: PDF, с. | V4: ID check | W4: Semantic check | X4: rollKind | Y4: dieType | Z4: progressionEligibility
A5: CVD-WPN-001-DEFAULT-DAMAGE | B5: ITM-WPN-001 | C5: Лёгкий арбалет | D5: DEFAULT | E5: DAMAGE | F5: Dm | G5: INSTANCE_VALUE | H5: item.instanceDamage | I5: item.instanceDamage | J5: NONE | K5: WEAPON_PROFILE_VERSION | M5: PROFILE_SNAPSHOT | O5: instanceDamage | P5: resolvedDamage | Q5: ATTACK_RESOLUTION_AND_COMBAT_LOG | R5: NOT_APPLICABLE | S5: Готовое производственное Dm читается из экземпляра; это не результат боевого броска. | T5: CORE-021 | U5: 68 | V5: =IF(COUNTIF($A$5:$A$69,A5)=1,"PASS","DUPLICATE") -> PASS | W5: =IF(OR(AND(G5="PER_ATTACK_ROLL",M5="EACH_RESOLVED_ATTACK",N5<>"",O5="",R5="ATTACK_RESOLUTION_AND_COMBAT_LOG",K5<>""),AND(G5="INSTANCE_VALUE",M5="PROFILE_SNAPSHOT",N5="",O5="instanceDamage",R5="NOT_APPLICABLE",K5="WEAPON_PROFILE_VERSION"),AND(G5="CONSTANT",M5="PROFILE_SNAPSHOT",N5="",O5="",R5="NOT_APPLICABLE",K5="ITEM_TEMPLATE")),IF(Q5="ATTACK_RESOLUTION_AND_COMBAT_LOG","PASS","FAIL"),"FAIL") -> PASS | X5: DAMAGE | Y5: NONE | Z5: NEVER_PROGRESSION
A6: CVD-WPN-001-DEFAULT-PENETRATION | B6: ITM-WPN-001 | C6: Лёгкий арбалет | D6: DEFAULT | E6: PENETRATION | F6: R12 | G6: PER_ATTACK_ROLL | H6: ROLL(R12) | I6: ROLL(R12) | J6: NONE | K6: ITEM_TEMPLATE | M6: EACH_RESOLVED_ATTACK | N6: RG-WPN-001-DEFAULT-PENETRATION | P6: resolvedPenetration | Q6: ATTACK_RESOLUTION_AND_COMBAT_LOG | R6: ATTACK_RESOLUTION_AND_COMBAT_LOG | S6: Новый бросок для каждой отдельно разрешаемой атаки. | T6: CORE-021 | U6: 68 | V6: =IF(COUNTIF($A$5:$A$69,A6)=1,"PASS","DUPLICATE") -> PASS | W6: =IF(OR(AND(G6="PER_ATTACK_ROLL",M6="EACH_RESOLVED_ATTACK",N6<>"",O6="",R6="ATTACK_RESOLUTION_AND_COMBAT_LOG",K6<>""),AND(G6="INSTANCE_VALUE",M6="PROFILE_SNAPSHOT",N6="",O6="instanceDamage",R6="NOT_APPLICABLE",K6="WEAPON_PROFILE_VERSION"),AND(G6="CONSTANT",M6="PROFILE_SNAPSHOT",N6="",O6="",R6="NOT_APPLICABLE",K6="ITEM_TEMPLATE")),IF(Q6="ATTACK_RESOLUTION_AND_COMBAT_LOG","PASS","FAIL"),"FAIL") -> PASS | X6: PENETRATION | Y6: OTHER_DIE | Z6: NEVER_PROGRESSION
A7: CVD-WPN-002-DEFAULT-DAMAGE | B7: ITM-WPN-002 | C7: Тяжёлый арбалет | D7: DEFAULT | E7: DAMAGE | F7: Dm | G7: INSTANCE_VALUE | H7: item.instanceDamage | I7: item.instanceDamage | J7: NONE | K7: WEAPON_PROFILE_VERSION | M7: PROFILE_SNAPSHOT | O7: instanceDamage | P7: resolvedDamage | Q7: ATTACK_RESOLUTION_AND_COMBAT_LOG | R7: NOT_APPLICABLE | S7: Готовое производственное Dm читается из экземпляра; это не результат боевого броска. | T7: CORE-022 | U7: 69 | V7: =IF(COUNTIF($A$5:$A$69,A7)=1,"PASS","DUPLICATE") -> PASS | W7: =IF(OR(AND(G7="PER_ATTACK_ROLL",M7="EACH_RESOLVED_ATTACK",N7<>"",O7="",R7="ATTACK_RESOLUTION_AND_COMBAT_LOG",K7<>""),AND(G7="INSTANCE_VALUE",M7="PROFILE_SNAPSHOT",N7="",O7="instanceDamage",R7="NOT_APPLICABLE",K7="WEAPON_PROFILE_VERSION"),AND(G7="CONSTANT",M7="PROFILE_SNAPSHOT",N7="",O7="",R7="NOT_APPLICABLE",K7="ITEM_TEMPLATE")),IF(Q7="ATTACK_RESOLUTION_AND_COMBAT_LOG","PASS","FAIL"),"FAIL") -> PASS | X7: DAMAGE | Y7: NONE | Z7: NEVER_PROGRESSION
A8: CVD-WPN-002-DEFAULT-PENETRATION | B8: ITM-WPN-002 | C8: Тяжёлый арбалет | D8: DEFAULT | E8: PENETRATION | F8: R20 | G8: PER_ATTACK_ROLL | H8: ROLL(R20) | I8: ROLL(R20) | J8: NONE | K8: ITEM_TEMPLATE | M8: EACH_RESOLVED_ATTACK | N8: RG-WPN-002-DEFAULT-PENETRATION | P8: resolvedPenetration | Q8: ATTACK_RESOLUTION_AND_COMBAT_LOG | R8: ATTACK_RESOLUTION_AND_COMBAT_LOG | S8: Новый бросок для каждой отдельно разрешаемой атаки. | T8: CORE-022 | U8: 69 | V8: =IF(COUNTIF($A$5:$A$69,A8)=1,"PASS","DUPLICATE") -> PASS | W8: =IF(OR(AND(G8="PER_ATTACK_ROLL",M8="EACH_RESOLVED_ATTACK",N8<>"",O8="",R8="ATTACK_RESOLUTION_AND_COMBAT_LOG",K8<>""),AND(G8="INSTANCE_VALUE",M8="PROFILE_SNAPSHOT",N8="",O8="instanceDamage",R8="NOT_APPLICABLE",K8="WEAPON_PROFILE_VERSION"),AND(G8="CONSTANT",M8="PROFILE_SNAPSHOT",N8="",O8="",R8="NOT_APPLICABLE",K8="ITEM_TEMPLATE")),IF(Q8="ATTACK_RESOLUTION_AND_COMBAT_LOG","PASS","FAIL"),"FAIL") -> PASS | X8: PENETRATION | Y8: D20 | Z8: NO_DIRECT_BUT_POOL
A9: CVD-WPN-003-DEFAULT-DAMAGE | B9: ITM-WPN-003 | C9: Кенси | D9: DEFAULT | E9: DAMAGE | F9: 10 | G9: CONSTANT | H9: 10 | I9: 10 | J9: NONE | K9: ITEM_TEMPLATE | M9: PROFILE_SNAPSHOT | P9: resolvedDamage | Q9: ATTACK_RESOLUTION_AND_COMBAT_LOG | R9: NOT_APPLICABLE | S9: Фиксированное значение шаблона; бросок не выполняется. | T9: CORE-023 | U9: 69 | V9: =IF(COUNTIF($A$5:$A$69,A9)=1,"PASS","DUPLICATE") -> PASS | W9: =IF(OR(AND(G9="PER_ATTACK_ROLL",M9="EACH_RESOLVED_ATTACK",N9<>"",O9="",R9="ATTACK_RESOLUTION_AND_COMBAT_LOG",K9<>""),AND(G9="INSTANCE_VALUE",M9="PROFILE_SNAPSHOT",N9="",O9="instanceDamage",R9="NOT_APPLICABLE",K9="WEAPON_PROFILE_VERSION"),AND(G9="CONSTANT",M9="PROFILE_SNAPSHOT",N9="",O9="",R9="NOT_APPLICABLE",K9="ITEM_TEMPLATE")),IF(Q9="ATTACK_RESOLUTION_AND_COMBAT_LOG","PASS","FAIL"),"FAIL") -> PASS | X9: DAMAGE | Y9: NONE | Z9: NEVER_PROGRESSION
A10: CVD-WPN-003-DEFAULT-PENETRATION | B10: ITM-WPN-003 | C10: Кенси | D10: DEFAULT | E10: PENETRATION | F10: R12 | G10: PER_ATTACK_ROLL | H10: ROLL(R12) | I10: ROLL(R12) | J10: NONE | K10: ITEM_TEMPLATE | M10: EACH_RESOLVED_ATTACK | N10: RG-WPN-003-DEFAULT-PENETRATION | P10: resolvedPenetration | Q10: ATTACK_RESOLUTION_AND_COMBAT_LOG | R10: ATTACK_RESOLUTION_AND_COMBAT_LOG | S10: Новый бросок для каждой отдельно разрешаемой атаки. | T10: CORE-023 | U10: 69 | V10: =IF(COUNTIF($A$5:$A$69,A10)=1,"PASS","DUPLICATE") -> PASS | W10: =IF(OR(AND(G10="PER_ATTACK_ROLL",M10="EACH_RESOLVED_ATTACK",N10<>"",O10="",R10="ATTACK_RESOLUTION_AND_COMBAT_LOG",K10<>""),AND(G10="INSTANCE_VALUE",M10="PROFILE_SNAPSHOT",N10="",O10="instanceDamage",R10="NOT_APPLICABLE",K10="WEAPON_PROFILE_VERSION"),AND(G10="CONSTANT",M10="PROFILE_SNAPSHOT",N10="",O10="",R10="NOT_APPLICABLE",K10="ITEM_TEMPLATE")),IF(Q10="ATTACK_RESOLUTION_AND_COMBAT_LOG","PASS","FAIL"),"FAIL") -> PASS | X10: PENETRATION | Y10: OTHER_DIE | Z10: NEVER_PROGRESSION
A11: CVD-WPN-004-DEFAULT-DAMAGE | B11: ITM-WPN-004 | C11: Эривел | D11: DEFAULT | E11: DAMAGE | F11: 2×R20 (один бросок) | G11: PER_ATTACK_ROLL | H11: 2*ROLL(R20) | I11: 2*ROLL(R20) | J11: NONE | K11: ITEM_TEMPLATE | M11: EACH_RESOLVED_ATTACK | N11: RG-WPN-004-DEFAULT-DAMAGE | P11: resolvedDamage | Q11: ATTACK_RESOLUTION_AND_COMBAT_LOG | R11: ATTACK_RESOLUTION_AND_COMBAT_LOG | S11: Новый бросок для каждой отдельно разрешаемой атаки. В выражении используется один базовый бросок; множитель не создаёт второй. | T11: CORE-024 | U11: 69 | V11: =IF(COUNTIF($A$5:$A$69,A11)=1,"PASS","DUPLICATE") -> PASS | W11: =IF(OR(AND(G11="PER_ATTACK_ROLL",M11="EACH_RESOLVED_ATTACK",N11<>"",O11="",R11="ATTACK_RESOLUTION_AND_COMBAT_LOG",K11<>""),AND(G11="INSTANCE_VALUE",M11="PROFILE_SNAPSHOT",N11="",O11="instanceDamage",R11="NOT_APPLICABLE",K11="WEAPON_PROFILE_VERSION"),AND(G11="CONSTANT",M11="PROFILE_SNAPSHOT",N11="",O11="",R11="NOT_APPLICABLE",K11="ITEM_TEMPLATE")),IF(Q11="ATTACK_RESOLUTION_AND_COMBAT_LOG","PASS","FAIL"),"FAIL") -> PASS | X11: DAMAGE | Y11: D20 | Z11: NO_DIRECT_BUT_POOL
A12: CVD-WPN-004-DEFAULT-PENETRATION | B12: ITM-WPN-004 | C12: Эривел | D12: DEFAULT | E12: PENETRATION | F12: R20 (независимый) | G12: PER_ATTACK_ROLL | H12: ROLL(R20) | I12: ROLL(R20) | J12: NONE | K12: ITEM_TEMPLATE | M12: EACH_RESOLVED_ATTACK | N12: RG-WPN-004-DEFAULT-PENETRATION | P12: resolvedPenetration | Q12: ATTACK_RESOLUTION_AND_COMBAT_LOG | R12: ATTACK_RESOLUTION_AND_COMBAT_LOG | S12: Новый бросок для каждой отдельно разрешаемой атаки. rollGroupId отличается от другого броска этой атаки; результаты независимы. | T12: CORE-024 | U12: 69 | V12: =IF(COUNTIF($A$5:$A$69,A12)=1,"PASS","DUPLICATE") -> PASS | W12: =IF(OR(AND(G12="PER_ATTACK_ROLL",M12="EACH_RESOLVED_ATTACK",N12<>"",O12="",R12="ATTACK_RESOLUTION_AND_COMBAT_LOG",K12<>""),AND(G12="INSTANCE_VALUE",M12="PROFILE_SNAPSHOT",N12="",O12="instanceDamage",R12="NOT_APPLICABLE",K12="WEAPON_PROFILE_VERSION"),AND(G12="CONSTANT",M12="PROFILE_SNAPSHOT",N12="",O12="",R12="NOT_APPLICABLE",K12="ITEM_TEMPLATE")),IF(Q12="ATTACK_RESOLUTION_AND_COMBAT_LOG","PASS","FAIL"),"FAIL") -> PASS | X12: PENETRATION | Y12: D20 | Z12: NO_DIRECT_BUT_POOL
A13: CVD-WPN-005-DEFAULT-DAMAGE | B13: ITM-WPN-005 | C13: Эстрефорд | D13: DEFAULT | E13: DAMAGE | F13: 30 | G13: CONSTANT | H13: 30 | I13: 30 | J13: NONE | K13: ITEM_TEMPLATE | M13: PROFILE_SNAPSHOT | P13: resolvedDamage | Q13: ATTACK_RESOLUTION_AND_COMBAT_LOG | R13: NOT_APPLICABLE | S13: Фиксированное значение шаблона; бросок не выполняется. | T13: CORE-025 | U13: 70 | V13: =IF(COUNTIF($A$5:$A$69,A13)=1,"PASS","DUPLICATE") -> PASS | W13: =IF(OR(AND(G13="PER_ATTACK_ROLL",M13="EACH_RESOLVED_ATTACK",N13<>"",O13="",R13="ATTACK_RESOLUTION_AND_COMBAT_LOG",K13<>""),AND(G13="INSTANCE_VALUE",M13="PROFILE_SNAPSHOT",N13="",O13="instanceDamage",R13="NOT_APPLICABLE",K13="WEAPON_PROFILE_VERSION"),AND(G13="CONSTANT",M13="PROFILE_SNAPSHOT",N13="",O13="",R13="NOT_APPLICABLE",K13="ITEM_TEMPLATE")),IF(Q13="ATTACK_RESOLUTION_AND_COMBAT_LOG","PASS","FAIL"),"FAIL") -> PASS | X13: DAMAGE | Y13: NONE | Z13: NEVER_PROGRESSION
A14: CVD-WPN-005-DEFAULT-PENETRATION | B14: ITM-WPN-005 | C14: Эстрефорд | D14: DEFAULT | E14: PENETRATION | F14: 16 | G14: CONSTANT | H14: 16 | I14: 16 | J14: NONE | K14: ITEM_TEMPLATE | M14: PROFILE_SNAPSHOT | P14: resolvedPenetration | Q14: ATTACK_RESOLUTION_AND_COMBAT_LOG | R14: NOT_APPLICABLE | S14: Фиксированное значение шаблона; бросок не выполняется. | T14: CORE-025 | U14: 70 | V14: =IF(COUNTIF($A$5:$A$69,A14)=1,"PASS","DUPLICATE") -> PASS | W14: =IF(OR(AND(G14="PER_ATTACK_ROLL",M14="EACH_RESOLVED_ATTACK",N14<>"",O14="",R14="ATTACK_RESOLUTION_AND_COMBAT_LOG",K14<>""),AND(G14="INSTANCE_VALUE",M14="PROFILE_SNAPSHOT",N14="",O14="instanceDamage",R14="NOT_APPLICABLE",K14="WEAPON_PROFILE_VERSION"),AND(G14="CONSTANT",M14="PROFILE_SNAPSHOT",N14="",O14="",R14="NOT_APPLICABLE",K14="ITEM_TEMPLATE")),IF(Q14="ATTACK_RESOLUTION_AND_COMBAT_LOG","PASS","FAIL"),"FAIL") -> PASS | X14: PENETRATION | Y14: NONE | Z14: NEVER_PROGRESSION
A15: CVD-WPN-006-DEFAULT-DAMAGE | B15: ITM-WPN-006 | C15: Айнцберн | D15: DEFAULT | E15: DAMAGE | F15: R20+30 | G15: PER_ATTACK_ROLL | H15: ROLL(R20)+30 | I15: ROLL(R20)+30 | J15: NONE | K15: ITEM_TEMPLATE | M15: EACH_RESOLVED_ATTACK | N15: RG-WPN-006-DEFAULT-DAMAGE | P15: resolvedDamage | Q15: ATTACK_RESOLUTION_AND_COMBAT_LOG | R15: ATTACK_RESOLUTION_AND_COMBAT_LOG | S15: Новый бросок для каждой отдельно разрешаемой атаки. | T15: CORE-026 | U15: 70 | V15: =IF(COUNTIF($A$5:$A$69,A15)=1,"PASS","DUPLICATE") -> PASS | W15: =IF(OR(AND(G15="PER_ATTACK_ROLL",M15="EACH_RESOLVED_ATTACK",N15<>"",O15="",R15="ATTACK_RESOLUTION_AND_COMBAT_LOG",K15<>""),AND(G15="INSTANCE_VALUE",M15="PROFILE_SNAPSHOT",N15="",O15="instanceDamage",R15="NOT_APPLICABLE",K15="WEAPON_PROFILE_VERSION"),AND(G15="CONSTANT",M15="PROFILE_SNAPSHOT",N15="",O15="",R15="NOT_APPLICABLE",K15="ITEM_TEMPLATE")),IF(Q15="ATTACK_RESOLUTION_AND_COMBAT_LOG","PASS","FAIL"),"FAIL") -> PASS | X15: DAMAGE | Y15: D20 | Z15: NO_DIRECT_BUT_POOL
A16: CVD-WPN-006-DEFAULT-PENETRATION | B16: ITM-WPN-006 | C16: Айнцберн | D16: DEFAULT | E16: PENETRATION | F16: R20+20 (независимый) | G16: PER_ATTACK_ROLL | H16: ROLL(R20)+20 | I16: ROLL(R20)+20 | J16: NONE | K16: ITEM_TEMPLATE | M16: EACH_RESOLVED_ATTACK | N16: RG-WPN-006-DEFAULT-PENETRATION | P16: resolvedPenetration | Q16: ATTACK_RESOLUTION_AND_COMBAT_LOG | R16: ATTACK_RESOLUTION_AND_COMBAT_LOG | S16: Новый бросок для каждой отдельно разрешаемой атаки. rollGroupId отличается от другого броска этой атаки; результаты независимы. | T16: CORE-026 | U16: 70 | V16: =IF(COUNTIF($A$5:$A$69,A16)=1,"PASS","DUPLICATE") -> PASS | W16: =IF(OR(AND(G16="PER_ATTACK_ROLL",M16="EACH_RESOLVED_ATTACK",N16<>"",O16="",R16="ATTACK_RESOLUTION_AND_COMBAT_LOG",K16<>""),AND(G16="INSTANCE_VALUE",M16="PROFILE_SNAPSHOT",N16="",O16="instanceDamage",R16="NOT_APPLICABLE",K16="WEAPON_PROFILE_VERSION"),AND(G16="CONSTANT",M16="PROFILE_SNAPSHOT",N16="",O16="",R16="NOT_APPLICABLE",K16="ITEM_TEMPLATE")),IF(Q16="ATTACK_RESOLUTION_AND_COMBAT_LOG","PASS","FAIL"),"FAIL") -> PASS | X16: PENETRATION | Y16: D20 | Z16: NO_DIRECT_BUT_POOL
A17: CVD-WPN-007-DEFAULT-DAMAGE | B17: ITM-WPN-007 | C17: Лёгкий лук | D17: DEFAULT | E17: DAMAGE | F17: Dm | G17: INSTANCE_VALUE | H17: item.instanceDamage | I17: item.instanceDamage | J17: NONE | K17: WEAPON_PROFILE_VERSION | M17: PROFILE_SNAPSHOT | O17: instanceDamage | P17: resolvedDamage | Q17: ATTACK_RESOLUTION_AND_COMBAT_LOG | R17: NOT_APPLICABLE | S17: Готовое производственное Dm читается из экземпляра; это не результат боевого броска. | T17: CORE-027 | U17: 71 | V17: =IF(COUNTIF($A$5:$A$69,A17)=1,"PASS","DUPLICATE") -> PASS | W17: =IF(OR(AND(G17="PER_ATTACK_ROLL",M17="EACH_RESOLVED_ATTACK",N17<>"",O17="",R17="ATTACK_RESOLUTION_AND_COMBAT_LOG",K17<>""),AND(G17="INSTANCE_VALUE",M17="PROFILE_SNAPSHOT",N17="",O17="instanceDamage",R17="NOT_APPLICABLE",K17="WEAPON_PROFILE_VERSION"),AND(G17="CONSTANT",M17="PROFILE_SNAPSHOT",N17="",O17="",R17="NOT_APPLICABLE",K17="ITEM_TEMPLATE")),IF(Q17="ATTACK_RESOLUTION_AND_COMBAT_LOG","PASS","FAIL"),"FAIL") -> PASS | X17: DAMAGE | Y17: NONE | Z17: NEVER_PROGRESSION
A18: CVD-WPN-007-DEFAULT-PENETRATION | B18: ITM-WPN-007 | C18: Лёгкий лук | D18: DEFAULT | E18: PENETRATION | F18: R12 | G18: PER_ATTACK_ROLL | H18: ROLL(R12) | I18: ROLL(R12) | J18: NONE | K18: ITEM_TEMPLATE | M18: EACH_RESOLVED_ATTACK | N18: RG-WPN-007-DEFAULT-PENETRATION | P18: resolvedPenetration | Q18: ATTACK_RESOLUTION_AND_COMBAT_LOG | R18: ATTACK_RESOLUTION_AND_COMBAT_LOG | S18: Новый бросок для каждой отдельно разрешаемой атаки. | T18: CORE-027 | U18: 71 | V18: =IF(COUNTIF($A$5:$A$69,A18)=1,"PASS","DUPLICATE") -> PASS | W18: =IF(OR(AND(G18="PER_ATTACK_ROLL",M18="EACH_RESOLVED_ATTACK",N18<>"",O18="",R18="ATTACK_RESOLUTION_AND_COMBAT_LOG",K18<>""),AND(G18="INSTANCE_VALUE",M18="PROFILE_SNAPSHOT",N18="",O18="instanceDamage",R18="NOT_APPLICABLE",K18="WEAPON_PROFILE_VERSION"),AND(G18="CONSTANT",M18="PROFILE_SNAPSHOT",N18="",O18="",R18="NOT_APPLICABLE",K18="ITEM_TEMPLATE")),IF(Q18="ATTACK_RESOLUTION_AND_COMBAT_LOG","PASS","FAIL"),"FAIL") -> PASS | X18: PENETRATION | Y18: OTHER_DIE | Z18: NEVER_PROGRESSION
A19: CVD-WPN-008-DEFAULT-DAMAGE | B19: ITM-WPN-008 | C19: Тяжёлый лук | D19: DEFAULT | E19: DAMAGE | F19: Dm | G19: INSTANCE_VALUE | H19: item.instanceDamage | I19: item.instanceDamage | J19: NONE | K19: WEAPON_PROFILE_VERSION | M19: PROFILE_SNAPSHOT | O19: instanceDamage | P19: resolvedDamage | Q19: ATTACK_RESOLUTION_AND_COMBAT_LOG | R19: NOT_APPLICABLE | S19: Готовое производственное Dm читается из экземпляра; это не результат боевого броска. | T19: CORE-028 | U19: 71 | V19: =IF(COUNTIF($A$5:$A$69,A19)=1,"PASS","DUPLICATE") -> PASS | W19: =IF(OR(AND(G19="PER_ATTACK_ROLL",M19="EACH_RESOLVED_ATTACK",N19<>"",O19="",R19="ATTACK_RESOLUTION_AND_COMBAT_LOG",K19<>""),AND(G19="INSTANCE_VALUE",M19="PROFILE_SNAPSHOT",N19="",O19="instanceDamage",R19="NOT_APPLICABLE",K19="WEAPON_PROFILE_VERSION"),AND(G19="CONSTANT",M19="PROFILE_SNAPSHOT",N19="",O19="",R19="NOT_APPLICABLE",K19="ITEM_TEMPLATE")),IF(Q19="ATTACK_RESOLUTION_AND_COMBAT_LOG","PASS","FAIL"),"FAIL") -> PASS | X19: DAMAGE | Y19: NONE | Z19: NEVER_PROGRESSION
A20: CVD-WPN-008-DEFAULT-PENETRATION | B20: ITM-WPN-008 | C20: Тяжёлый лук | D20: DEFAULT | E20: PENETRATION | F20: R20 | G20: PER_ATTACK_ROLL | H20: ROLL(R20) | I20: ROLL(R20) | J20: NONE | K20: ITEM_TEMPLATE | M20: EACH_RESOLVED_ATTACK | N20: RG-WPN-008-DEFAULT-PENETRATION | P20: resolvedPenetration | Q20: ATTACK_RESOLUTION_AND_COMBAT_LOG | R20: ATTACK_RESOLUTION_AND_COMBAT_LOG | S20: Новый бросок для каждой отдельно разрешаемой атаки. | T20: CORE-028 | U20: 71 | V20: =IF(COUNTIF($A$5:$A$69,A20)=1,"PASS","DUPLICATE") -> PASS | W20: =IF(OR(AND(G20="PER_ATTACK_ROLL",M20="EACH_RESOLVED_ATTACK",N20<>"",O20="",R20="ATTACK_RESOLUTION_AND_COMBAT_LOG",K20<>""),AND(G20="INSTANCE_VALUE",M20="PROFILE_SNAPSHOT",N20="",O20="instanceDamage",R20="NOT_APPLICABLE",K20="WEAPON_PROFILE_VERSION"),AND(G20="CONSTANT",M20="PROFILE_SNAPSHOT",N20="",O20="",R20="NOT_APPLICABLE",K20="ITEM_TEMPLATE")),IF(Q20="ATTACK_RESOLUTION_AND_COMBAT_LOG","PASS","FAIL"),"FAIL") -> PASS | X20: PENETRATION | Y20: D20 | Z20: NO_DIRECT_BUT_POOL
A21: CVD-WPN-009-DEFAULT-DAMAGE | B21: ITM-WPN-009 | C21: Длинный лук | D21: DEFAULT | E21: DAMAGE | F21: Dm | G21: INSTANCE_VALUE | H21: item.instanceDamage | I21: item.instanceDamage | J21: NONE | K21: WEAPON_PROFILE_VERSION | M21: PROFILE_SNAPSHOT | O21: instanceDamage | P21: resolvedDamage | Q21: ATTACK_RESOLUTION_AND_COMBAT_LOG | R21: NOT_APPLICABLE | S21: Готовое производственное Dm читается из экземпляра; это не результат боевого броска. | T21: CORE-029 | U21: 72 | V21: =IF(COUNTIF($A$5:$A$69,A21)=1,"PASS","DUPLICATE") -> PASS | W21: =IF(OR(AND(G21="PER_ATTACK_ROLL",M21="EACH_RESOLVED_ATTACK",N21<>"",O21="",R21="ATTACK_RESOLUTION_AND_COMBAT_LOG",K21<>""),AND(G21="INSTANCE_VALUE",M21="PROFILE_SNAPSHOT",N21="",O21="instanceDamage",R21="NOT_APPLICABLE",K21="WEAPON_PROFILE_VERSION"),AND(G21="CONSTANT",M21="PROFILE_SNAPSHOT",N21="",O21="",R21="NOT_APPLICABLE",K21="ITEM_TEMPLATE")),IF(Q21="ATTACK_RESOLUTION_AND_COMBAT_LOG","PASS","FAIL"),"FAIL") -> PASS | X21: DAMAGE | Y21: NONE | Z21: NEVER_PROGRESSION
A22: CVD-WPN-009-DEFAULT-PENETRATION | B22: ITM-WPN-009 | C22: Длинный лук | D22: DEFAULT | E22: PENETRATION | F22: R12 | G22: PER_ATTACK_ROLL | H22: ROLL(R12) | I22: ROLL(R12) | J22: NONE | K22: ITEM_TEMPLATE | M22: EACH_RESOLVED_ATTACK | N22: RG-WPN-009-DEFAULT-PENETRATION | P22: resolvedPenetration | Q22: ATTACK_RESOLUTION_AND_COMBAT_LOG | R22: ATTACK_RESOLUTION_AND_COMBAT_LOG | S22: Новый бросок для каждой отдельно разрешаемой атаки. | T22: CORE-029 | U22: 72 | V22: =IF(COUNTIF($A$5:$A$69,A22)=1,"PASS","DUPLICATE") -> PASS | W22: =IF(OR(AND(G22="PER_ATTACK_ROLL",M22="EACH_RESOLVED_ATTACK",N22<>"",O22="",R22="ATTACK_RESOLUTION_AND_COMBAT_LOG",K22<>""),AND(G22="INSTANCE_VALUE",M22="PROFILE_SNAPSHOT",N22="",O22="instanceDamage",R22="NOT_APPLICABLE",K22="WEAPON_PROFILE_VERSION"),AND(G22="CONSTANT",M22="PROFILE_SNAPSHOT",N22="",O22="",R22="NOT_APPLICABLE",K22="ITEM_TEMPLATE")),IF(Q22="ATTACK_RESOLUTION_AND_COMBAT_LOG","PASS","FAIL"),"FAIL") -> PASS | X22: PENETRATION | Y22: OTHER_DIE | Z22: NEVER_PROGRESSION
A23: CVD-WPN-010-DEFAULT-DAMAGE | B23: ITM-WPN-010 | C23: Грубое оружие | D23: DEFAULT | E23: DAMAGE | F23: +S к R12 | G23: PER_ATTACK_ROLL | H23: ROLL(R12)+attacker.S | I23: ROLL(R12) | J23: S | K23: ITEM_TEMPLATE | M23: EACH_RESOLVED_ATTACK | N23: RG-WPN-010-DEFAULT-DAMAGE | P23: resolvedDamage | Q23: ATTACK_RESOLUTION_AND_COMBAT_LOG | R23: ATTACK_RESOLUTION_AND_COMBAT_LOG | S23: Новый бросок для каждой отдельно разрешаемой атаки. | T23: CORE-031 | U23: 73 | V23: =IF(COUNTIF($A$5:$A$69,A23)=1,"PASS","DUPLICATE") -> PASS | W23: =IF(OR(AND(G23="PER_ATTACK_ROLL",M23="EACH_RESOLVED_ATTACK",N23<>"",O23="",R23="ATTACK_RESOLUTION_AND_COMBAT_LOG",K23<>""),AND(G23="INSTANCE_VALUE",M23="PROFILE_SNAPSHOT",N23="",O23="instanceDamage",R23="NOT_APPLICABLE",K23="WEAPON_PROFILE_VERSION"),AND(G23="CONSTANT",M23="PROFILE_SNAPSHOT",N23="",O23="",R23="NOT_APPLICABLE",K23="ITEM_TEMPLATE")),IF(Q23="ATTACK_RESOLUTION_AND_COMBAT_LOG","PASS","FAIL"),"FAIL") -> PASS | X23: DAMAGE | Y23: OTHER_DIE | Z23: NEVER_PROGRESSION
A24: CVD-WPN-010-DEFAULT-PENETRATION | B24: ITM-WPN-010 | C24: Грубое оружие | D24: DEFAULT | E24: PENETRATION | F24: R12 | G24: PER_ATTACK_ROLL | H24: ROLL(R12) | I24: ROLL(R12) | J24: NONE | K24: ITEM_TEMPLATE | M24: EACH_RESOLVED_ATTACK | N24: RG-WPN-010-DEFAULT-PENETRATION | P24: resolvedPenetration | Q24: ATTACK_RESOLUTION_AND_COMBAT_LOG | R24: ATTACK_RESOLUTION_AND_COMBAT_LOG | S24: Новый бросок для каждой отдельно разрешаемой атаки. | T24: CORE-031 | U24: 73 | V24: =IF(COUNTIF($A$5:$A$69,A24)=1,"PASS","DUPLICATE") -> PASS | W24: =IF(OR(AND(G24="PER_ATTACK_ROLL",M24="EACH_RESOLVED_ATTACK",N24<>"",O24="",R24="ATTACK_RESOLUTION_AND_COMBAT_LOG",K24<>""),AND(G24="INSTANCE_VALUE",M24="PROFILE_SNAPSHOT",N24="",O24="instanceDamage",R24="NOT_APPLICABLE",K24="WEAPON_PROFILE_VERSION"),AND(G24="CONSTANT",M24="PROFILE_SNAPSHOT",N24="",O24="",R24="NOT_APPLICABLE",K24="ITEM_TEMPLATE")),IF(Q24="ATTACK_RESOLUTION_AND_COMBAT_LOG","PASS","FAIL"),"FAIL") -> PASS | X24: PENETRATION | Y24: OTHER_DIE | Z24: NEVER_PROGRESSION
A25: CVD-WPN-011-DEFAULT-DAMAGE | B25: ITM-WPN-011 | C25: Одноручный меч | D25: DEFAULT | E25: DAMAGE | F25: R20+S | G25: PER_ATTACK_ROLL | H25: ROLL(R20)+attacker.S | I25: ROLL(R20) | J25: S | K25: ITEM_TEMPLATE | M25: EACH_RESOLVED_ATTACK | N25: RG-WPN-011-DEFAULT-DAMAGE | P25: resolvedDamage | Q25: ATTACK_RESOLUTION_AND_COMBAT_LOG | R25: ATTACK_RESOLUTION_AND_COMBAT_LOG | S25: Новый бросок для каждой отдельно разрешаемой атаки. | T25: CORE-032 | U25: 73 | V25: =IF(COUNTIF($A$5:$A$69,A25)=1,"PASS","DUPLICATE") -> PASS | W25: =IF(OR(AND(G25="PER_ATTACK_ROLL",M25="EACH_RESOLVED_ATTACK",N25<>"",O25="",R25="ATTACK_RESOLUTION_AND_COMBAT_LOG",K25<>""),AND(G25="INSTANCE_VALUE",M25="PROFILE_SNAPSHOT",N25="",O25="instanceDamage",R25="NOT_APPLICABLE",K25="WEAPON_PROFILE_VERSION"),AND(G25="CONSTANT",M25="PROFILE_SNAPSHOT",N25="",O25="",R25="NOT_APPLICABLE",K25="ITEM_TEMPLATE")),IF(Q25="ATTACK_RESOLUTION_AND_COMBAT_LOG","PASS","FAIL"),"FAIL") -> PASS | X25: DAMAGE | Y25: D20 | Z25: NO_DIRECT_BUT_POOL
A26: CVD-WPN-011-DEFAULT-PENETRATION | B26: ITM-WPN-011 | C26: Одноручный меч | D26: DEFAULT | E26: PENETRATION | F26: R12 | G26: PER_ATTACK_ROLL | H26: ROLL(R12) | I26: ROLL(R12) | J26: NONE | K26: ITEM_TEMPLATE | M26: EACH_RESOLVED_ATTACK | N26: RG-WPN-011-DEFAULT-PENETRATION | P26: resolvedPenetration | Q26: ATTACK_RESOLUTION_AND_COMBAT_LOG | R26: ATTACK_RESOLUTION_AND_COMBAT_LOG | S26: Новый бросок для каждой отдельно разрешаемой атаки. | T26: CORE-032 | U26: 73 | V26: =IF(COUNTIF($A$5:$A$69,A26)=1,"PASS","DUPLICATE") -> PASS | W26: =IF(OR(AND(G26="PER_ATTACK_ROLL",M26="EACH_RESOLVED_ATTACK",N26<>"",O26="",R26="ATTACK_RESOLUTION_AND_COMBAT_LOG",K26<>""),AND(G26="INSTANCE_VALUE",M26="PROFILE_SNAPSHOT",N26="",O26="instanceDamage",R26="NOT_APPLICABLE",K26="WEAPON_PROFILE_VERSION"),AND(G26="CONSTANT",M26="PROFILE_SNAPSHOT",N26="",O26="",R26="NOT_APPLICABLE",K26="ITEM_TEMPLATE")),IF(Q26="ATTACK_RESOLUTION_AND_COMBAT_LOG","PASS","FAIL"),"FAIL") -> PASS | X26: PENETRATION | Y26: OTHER_DIE | Z26: NEVER_PROGRESSION
A27: CVD-WPN-012-ONE_HAND-DAMAGE | B27: ITM-WPN-012 | C27: Полуторный меч | D27: ONE_HAND | E27: DAMAGE | F27: R20+S | G27: PER_ATTACK_ROLL | H27: ROLL(R20)+attacker.S | I27: ROLL(R20) | J27: S | K27: ITEM_TEMPLATE | M27: EACH_RESOLVED_ATTACK | N27: RG-WPN-012-ONE_HAND-DAMAGE | P27: resolvedDamage | Q27: ATTACK_RESOLUTION_AND_COMBAT_LOG | R27: ATTACK_RESOLUTION_AND_COMBAT_LOG | S27: Полуторный меч: фиксированный хват одной рукой; новый бросок для каждой отдельно разрешаемой атаки. | T27: CORE-033 | U27: 73 | V27: =IF(COUNTIF($A$5:$A$69,A27)=1,"PASS","DUPLICATE") -> PASS | W27: =IF(OR(AND(G27="PER_ATTACK_ROLL",M27="EACH_RESOLVED_ATTACK",N27<>"",O27="",R27="ATTACK_RESOLUTION_AND_COMBAT_LOG",K27<>""),AND(G27="INSTANCE_VALUE",M27="PROFILE_SNAPSHOT",N27="",O27="instanceDamage",R27="NOT_APPLICABLE",K27="WEAPON_PROFILE_VERSION"),AND(G27="CONSTANT",M27="PROFILE_SNAPSHOT",N27="",O27="",R27="NOT_APPLICABLE",K27="ITEM_TEMPLATE")),IF(Q27="ATTACK_RESOLUTION_AND_COMBAT_LOG","PASS","FAIL"),"FAIL") -> PASS | X27: DAMAGE | Y27: D20 | Z27: NO_DIRECT_BUT_POOL
A28: CVD-WPN-012-ONE_HAND-PENETRATION | B28: ITM-WPN-012 | C28: Полуторный меч | D28: ONE_HAND | E28: PENETRATION | F28: R20 | G28: PER_ATTACK_ROLL | H28: ROLL(R20) | I28: ROLL(R20) | J28: NONE | K28: ITEM_TEMPLATE | M28: EACH_RESOLVED_ATTACK | N28: RG-WPN-012-ONE_HAND-PENETRATION | P28: resolvedPenetration | Q28: ATTACK_RESOLUTION_AND_COMBAT_LOG | R28: ATTACK_RESOLUTION_AND_COMBAT_LOG | S28: Полуторный меч: фиксированный хват одной рукой; новый бросок для каждой отдельно разрешаемой атаки. | T28: CORE-033 | U28: 73 | V28: =IF(COUNTIF($A$5:$A$69,A28)=1,"PASS","DUPLICATE") -> PASS | W28: =IF(OR(AND(G28="PER_ATTACK_ROLL",M28="EACH_RESOLVED_ATTACK",N28<>"",O28="",R28="ATTACK_RESOLUTION_AND_COMBAT_LOG",K28<>""),AND(G28="INSTANCE_VALUE",M28="PROFILE_SNAPSHOT",N28="",O28="instanceDamage",R28="NOT_APPLICABLE",K28="WEAPON_PROFILE_VERSION"),AND(G28="CONSTANT",M28="PROFILE_SNAPSHOT",N28="",O28="",R28="NOT_APPLICABLE",K28="ITEM_TEMPLATE")),IF(Q28="ATTACK_RESOLUTION_AND_COMBAT_LOG","PASS","FAIL"),"FAIL") -> PASS | X28: PENETRATION | Y28: D20 | Z28: NO_DIRECT_BUT_POOL
A29: CVD-WPN-013-DEFAULT-DAMAGE | B29: ITM-WPN-013 | C29: Двуручный меч | D29: DEFAULT | E29: DAMAGE | F29: R20+5+S | G29: PER_ATTACK_ROLL | H29: ROLL(R20)+5+attacker.S | I29: ROLL(R20)+5 | J29: S | K29: ITEM_TEMPLATE | M29: EACH_RESOLVED_ATTACK | N29: RG-WPN-013-DEFAULT-DAMAGE | P29: resolvedDamage | Q29: ATTACK_RESOLUTION_AND_COMBAT_LOG | R29: ATTACK_RESOLUTION_AND_COMBAT_LOG | S29: Новый бросок для каждой отдельно разрешаемой атаки. | T29: CORE-034 | U29: 74 | V29: =IF(COUNTIF($A$5:$A$69,A29)=1,"PASS","DUPLICATE") -> PASS | W29: =IF(OR(AND(G29="PER_ATTACK_ROLL",M29="EACH_RESOLVED_ATTACK",N29<>"",O29="",R29="ATTACK_RESOLUTION_AND_COMBAT_LOG",K29<>""),AND(G29="INSTANCE_VALUE",M29="PROFILE_SNAPSHOT",N29="",O29="instanceDamage",R29="NOT_APPLICABLE",K29="WEAPON_PROFILE_VERSION"),AND(G29="CONSTANT",M29="PROFILE_SNAPSHOT",N29="",O29="",R29="NOT_APPLICABLE",K29="ITEM_TEMPLATE")),IF(Q29="ATTACK_RESOLUTION_AND_COMBAT_LOG","PASS","FAIL"),"FAIL") -> PASS | X29: DAMAGE | Y29: D20 | Z29: NO_DIRECT_BUT_POOL
A30: CVD-WPN-013-DEFAULT-PENETRATION | B30: ITM-WPN-013 | C30: Двуручный меч | D30: DEFAULT | E30: PENETRATION | F30: R20+5 | G30: PER_ATTACK_ROLL | H30: ROLL(R20)+5 | I30: ROLL(R20)+5 | J30: NONE | K30: ITEM_TEMPLATE | M30: EACH_RESOLVED_ATTACK | N30: RG-WPN-013-DEFAULT-PENETRATION | P30: resolvedPenetration | Q30: ATTACK_RESOLUTION_AND_COMBAT_LOG | R30: ATTACK_RESOLUTION_AND_COMBAT_LOG | S30: Новый бросок для каждой отдельно разрешаемой атаки. | T30: CORE-034 | U30: 74 | V30: =IF(COUNTIF($A$5:$A$69,A30)=1,"PASS","DUPLICATE") -> PASS | W30: =IF(OR(AND(G30="PER_ATTACK_ROLL",M30="EACH_RESOLVED_ATTACK",N30<>"",O30="",R30="ATTACK_RESOLUTION_AND_COMBAT_LOG",K30<>""),AND(G30="INSTANCE_VALUE",M30="PROFILE_SNAPSHOT",N30="",O30="instanceDamage",R30="NOT_APPLICABLE",K30="WEAPON_PROFILE_VERSION"),AND(G30="CONSTANT",M30="PROFILE_SNAPSHOT",N30="",O30="",R30="NOT_APPLICABLE",K30="ITEM_TEMPLATE")),IF(Q30="ATTACK_RESOLUTION_AND_COMBAT_LOG","PASS","FAIL"),"FAIL") -> PASS | X30: PENETRATION | Y30: D20 | Z30: NO_DIRECT_BUT_POOL
A31: CVD-WPN-014-DEFAULT-DAMAGE | B31: ITM-WPN-014 | C31: Шпага | D31: DEFAULT | E31: DAMAGE | F31: R12+D | G31: PER_ATTACK_ROLL | H31: ROLL(R12)+attacker.D | I31: ROLL(R12) | J31: D | K31: ITEM_TEMPLATE | M31: EACH_RESOLVED_ATTACK | N31: RG-WPN-014-DEFAULT-DAMAGE | P31: resolvedDamage | Q31: ATTACK_RESOLUTION_AND_COMBAT_LOG | R31: ATTACK_RESOLUTION_AND_COMBAT_LOG | S31: Новый бросок для каждой отдельно разрешаемой атаки. | T31: CORE-035 | U31: 74 | V31: =IF(COUNTIF($A$5:$A$69,A31)=1,"PASS","DUPLICATE") -> PASS | W31: =IF(OR(AND(G31="PER_ATTACK_ROLL",M31="EACH_RESOLVED_ATTACK",N31<>"",O31="",R31="ATTACK_RESOLUTION_AND_COMBAT_LOG",K31<>""),AND(G31="INSTANCE_VALUE",M31="PROFILE_SNAPSHOT",N31="",O31="instanceDamage",R31="NOT_APPLICABLE",K31="WEAPON_PROFILE_VERSION"),AND(G31="CONSTANT",M31="PROFILE_SNAPSHOT",N31="",O31="",R31="NOT_APPLICABLE",K31="ITEM_TEMPLATE")),IF(Q31="ATTACK_RESOLUTION_AND_COMBAT_LOG","PASS","FAIL"),"FAIL") -> PASS | X31: DAMAGE | Y31: OTHER_DIE | Z31: NEVER_PROGRESSION
A32: CVD-WPN-014-DEFAULT-PENETRATION | B32: ITM-WPN-014 | C32: Шпага | D32: DEFAULT | E32: PENETRATION | F32: R12 | G32: PER_ATTACK_ROLL | H32: ROLL(R12) | I32: ROLL(R12) | J32: NONE | K32: ITEM_TEMPLATE | M32: EACH_RESOLVED_ATTACK | N32: RG-WPN-014-DEFAULT-PENETRATION | P32: resolvedPenetration | Q32: ATTACK_RESOLUTION_AND_COMBAT_LOG | R32: ATTACK_RESOLUTION_AND_COMBAT_LOG | S32: Новый бросок для каждой отдельно разрешаемой атаки. | T32: CORE-035 | U32: 74 | V32: =IF(COUNTIF($A$5:$A$69,A32)=1,"PASS","DUPLICATE") -> PASS | W32: =IF(OR(AND(G32="PER_ATTACK_ROLL",M32="EACH_RESOLVED_ATTACK",N32<>"",O32="",R32="ATTACK_RESOLUTION_AND_COMBAT_LOG",K32<>""),AND(G32="INSTANCE_VALUE",M32="PROFILE_SNAPSHOT",N32="",O32="instanceDamage",R32="NOT_APPLICABLE",K32="WEAPON_PROFILE_VERSION"),AND(G32="CONSTANT",M32="PROFILE_SNAPSHOT",N32="",O32="",R32="NOT_APPLICABLE",K32="ITEM_TEMPLATE")),IF(Q32="ATTACK_RESOLUTION_AND_COMBAT_LOG","PASS","FAIL"),"FAIL") -> PASS | X32: PENETRATION | Y32: OTHER_DIE | Z32: NEVER_PROGRESSION
A33: CVD-WPN-015-DEFAULT-DAMAGE | B33: ITM-WPN-015 | C33: Копьё | D33: DEFAULT | E33: DAMAGE | F33: R12+S | G33: PER_ATTACK_ROLL | H33: ROLL(R12)+attacker.S | I33: ROLL(R12) | J33: S | K33: ITEM_TEMPLATE | M33: EACH_RESOLVED_ATTACK | N33: RG-WPN-015-DEFAULT-DAMAGE | P33: resolvedDamage | Q33: ATTACK_RESOLUTION_AND_COMBAT_LOG | R33: ATTACK_RESOLUTION_AND_COMBAT_LOG | S33: Новый бросок для каждой отдельно разрешаемой атаки. | T33: CORE-036 | U33: 74 | V33: =IF(COUNTIF($A$5:$A$69,A33)=1,"PASS","DUPLICATE") -> PASS | W33: =IF(OR(AND(G33="PER_ATTACK_ROLL",M33="EACH_RESOLVED_ATTACK",N33<>"",O33="",R33="ATTACK_RESOLUTION_AND_COMBAT_LOG",K33<>""),AND(G33="INSTANCE_VALUE",M33="PROFILE_SNAPSHOT",N33="",O33="instanceDamage",R33="NOT_APPLICABLE",K33="WEAPON_PROFILE_VERSION"),AND(G33="CONSTANT",M33="PROFILE_SNAPSHOT",N33="",O33="",R33="NOT_APPLICABLE",K33="ITEM_TEMPLATE")),IF(Q33="ATTACK_RESOLUTION_AND_COMBAT_LOG","PASS","FAIL"),"FAIL") -> PASS | X33: DAMAGE | Y33: OTHER_DIE | Z33: NEVER_PROGRESSION
A34: CVD-WPN-015-DEFAULT-PENETRATION | B34: ITM-WPN-015 | C34: Копьё | D34: DEFAULT | E34: PENETRATION | F34: R12 | G34: PER_ATTACK_ROLL | H34: ROLL(R12) | I34: ROLL(R12) | J34: NONE | K34: ITEM_TEMPLATE | M34: EACH_RESOLVED_ATTACK | N34: RG-WPN-015-DEFAULT-PENETRATION | P34: resolvedPenetration | Q34: ATTACK_RESOLUTION_AND_COMBAT_LOG | R34: ATTACK_RESOLUTION_AND_COMBAT_LOG | S34: Новый бросок для каждой отдельно разрешаемой атаки. | T34: CORE-036 | U34: 74 | V34: =IF(COUNTIF($A$5:$A$69,A34)=1,"PASS","DUPLICATE") -> PASS | W34: =IF(OR(AND(G34="PER_ATTACK_ROLL",M34="EACH_RESOLVED_ATTACK",N34<>"",O34="",R34="ATTACK_RESOLUTION_AND_COMBAT_LOG",K34<>""),AND(G34="INSTANCE_VALUE",M34="PROFILE_SNAPSHOT",N34="",O34="instanceDamage",R34="NOT_APPLICABLE",K34="WEAPON_PROFILE_VERSION"),AND(G34="CONSTANT",M34="PROFILE_SNAPSHOT",N34="",O34="",R34="NOT_APPLICABLE",K34="ITEM_TEMPLATE")),IF(Q34="ATTACK_RESOLUTION_AND_COMBAT_LOG","PASS","FAIL"),"FAIL") -> PASS | X34: PENETRATION | Y34: OTHER_DIE | Z34: NEVER_PROGRESSION
A35: CVD-WPN-016-DEFAULT-DAMAGE | B35: ITM-WPN-016 | C35: Кинжал | D35: DEFAULT | E35: DAMAGE | F35: R12+D; proc: 20+D | G35: PER_ATTACK_ROLL | H35: ROLL(R12)+attacker.D | I35: ROLL(R12) | J35: D | K35: ITEM_TEMPLATE | L35: IF(accuracyTotal>=40 AND penetrationPassed,20+attacker.D,baseDamage+attacker.D) | M35: EACH_RESOLVED_ATTACK | N35: RG-WPN-016-DEFAULT-DAMAGE | P35: resolvedDamage | Q35: ATTACK_RESOLUTION_AND_COMBAT_LOG | R35: ATTACK_RESOLUTION_AND_COMBAT_LOG | S35: Новый бросок для каждой отдельно разрешаемой атаки. Условная ветвь заменяет базовое выражение; базовый дайс бросается только в выбранной ветви. | T35: CORE-037 | U35: 74 | V35: =IF(COUNTIF($A$5:$A$69,A35)=1,"PASS","DUPLICATE") -> PASS | W35: =IF(OR(AND(G35="PER_ATTACK_ROLL",M35="EACH_RESOLVED_ATTACK",N35<>"",O35="",R35="ATTACK_RESOLUTION_AND_COMBAT_LOG",K35<>""),AND(G35="INSTANCE_VALUE",M35="PROFILE_SNAPSHOT",N35="",O35="instanceDamage",R35="NOT_APPLICABLE",K35="WEAPON_PROFILE_VERSION"),AND(G35="CONSTANT",M35="PROFILE_SNAPSHOT",N35="",O35="",R35="NOT_APPLICABLE",K35="ITEM_TEMPLATE")),IF(Q35="ATTACK_RESOLUTION_AND_COMBAT_LOG","PASS","FAIL"),"FAIL") -> PASS | X35: DAMAGE | Y35: OTHER_DIE | Z35: NEVER_PROGRESSION
A36: CVD-WPN-016-DEFAULT-PENETRATION | B36: ITM-WPN-016 | C36: Кинжал | D36: DEFAULT | E36: PENETRATION | F36: R6 | G36: PER_ATTACK_ROLL | H36: ROLL(R6) | I36: ROLL(R6) | J36: NONE | K36: ITEM_TEMPLATE | M36: EACH_RESOLVED_ATTACK | N36: RG-WPN-016-DEFAULT-PENETRATION | P36: resolvedPenetration | Q36: ATTACK_RESOLUTION_AND_COMBAT_LOG | R36: ATTACK_RESOLUTION_AND_COMBAT_LOG | S36: Новый бросок для каждой отдельно разрешаемой атаки. | T36: CORE-037 | U36: 74 | V36: =IF(COUNTIF($A$5:$A$69,A36)=1,"PASS","DUPLICATE") -> PASS | W36: =IF(OR(AND(G36="PER_ATTACK_ROLL",M36="EACH_RESOLVED_ATTACK",N36<>"",O36="",R36="ATTACK_RESOLUTION_AND_COMBAT_LOG",K36<>""),AND(G36="INSTANCE_VALUE",M36="PROFILE_SNAPSHOT",N36="",O36="instanceDamage",R36="NOT_APPLICABLE",K36="WEAPON_PROFILE_VERSION"),AND(G36="CONSTANT",M36="PROFILE_SNAPSHOT",N36="",O36="",R36="NOT_APPLICABLE",K36="ITEM_TEMPLATE")),IF(Q36="ATTACK_RESOLUTION_AND_COMBAT_LOG","PASS","FAIL"),"FAIL") -> PASS | X36: PENETRATION | Y36: OTHER_DIE | Z36: NEVER_PROGRESSION
A37: CVD-WPN-017-DEFAULT-DAMAGE | B37: ITM-WPN-017 | C37: Мизерикордия | D37: DEFAULT | E37: DAMAGE | F37: R6+D; proc: 20+D | G37: PER_ATTACK_ROLL | H37: ROLL(R6)+attacker.D | I37: ROLL(R6) | J37: D | K37: ITEM_TEMPLATE | L37: IF(accuracyTotal>=40,20+attacker.D,baseDamage+attacker.D); armorIgnoredOnTrue=true | M37: EACH_RESOLVED_ATTACK | N37: RG-WPN-017-DEFAULT-DAMAGE | P37: resolvedDamage | Q37: ATTACK_RESOLUTION_AND_COMBAT_LOG | R37: ATTACK_RESOLUTION_AND_COMBAT_LOG | S37: Новый бросок для каждой отдельно разрешаемой атаки. Условная ветвь заменяет базовое выражение; базовый дайс бросается только в выбранной ветви. | T37: CORE-038 | U37: 75 | V37: =IF(COUNTIF($A$5:$A$69,A37)=1,"PASS","DUPLICATE") -> PASS | W37: =IF(OR(AND(G37="PER_ATTACK_ROLL",M37="EACH_RESOLVED_ATTACK",N37<>"",O37="",R37="ATTACK_RESOLUTION_AND_COMBAT_LOG",K37<>""),AND(G37="INSTANCE_VALUE",M37="PROFILE_SNAPSHOT",N37="",O37="instanceDamage",R37="NOT_APPLICABLE",K37="WEAPON_PROFILE_VERSION"),AND(G37="CONSTANT",M37="PROFILE_SNAPSHOT",N37="",O37="",R37="NOT_APPLICABLE",K37="ITEM_TEMPLATE")),IF(Q37="ATTACK_RESOLUTION_AND_COMBAT_LOG","PASS","FAIL"),"FAIL") -> PASS | X37: DAMAGE | Y37: OTHER_DIE | Z37: NEVER_PROGRESSION
A38: CVD-WPN-017-DEFAULT-PENETRATION | B38: ITM-WPN-017 | C38: Мизерикордия | D38: DEFAULT | E38: PENETRATION | F38: R20 | G38: PER_ATTACK_ROLL | H38: ROLL(R20) | I38: ROLL(R20) | J38: NONE | K38: ITEM_TEMPLATE | M38: EACH_RESOLVED_ATTACK | N38: RG-WPN-017-DEFAULT-PENETRATION | P38: resolvedPenetration | Q38: ATTACK_RESOLUTION_AND_COMBAT_LOG | R38: ATTACK_RESOLUTION_AND_COMBAT_LOG | S38: Новый бросок для каждой отдельно разрешаемой атаки. | T38: CORE-038 | U38: 75 | V38: =IF(COUNTIF($A$5:$A$69,A38)=1,"PASS","DUPLICATE") -> PASS | W38: =IF(OR(AND(G38="PER_ATTACK_ROLL",M38="EACH_RESOLVED_ATTACK",N38<>"",O38="",R38="ATTACK_RESOLUTION_AND_COMBAT_LOG",K38<>""),AND(G38="INSTANCE_VALUE",M38="PROFILE_SNAPSHOT",N38="",O38="instanceDamage",R38="NOT_APPLICABLE",K38="WEAPON_PROFILE_VERSION"),AND(G38="CONSTANT",M38="PROFILE_SNAPSHOT",N38="",O38="",R38="NOT_APPLICABLE",K38="ITEM_TEMPLATE")),IF(Q38="ATTACK_RESOLUTION_AND_COMBAT_LOG","PASS","FAIL"),"FAIL") -> PASS | X38: PENETRATION | Y38: D20 | Z38: NO_DIRECT_BUT_POOL
A39: CVD-WPN-018-DEFAULT-DAMAGE | B39: ITM-WPN-018 | C39: Одноручный топор | D39: DEFAULT | E39: DAMAGE | F39: R12+S; proc: 20+S | G39: PER_ATTACK_ROLL | H39: ROLL(R12)+attacker.S | I39: ROLL(R12) | J39: S | K39: ITEM_TEMPLATE | L39: IF(accuracyTotal>=41,20+attacker.S,baseDamage+attacker.S); armorIgnoredOnTrue=true | M39: EACH_RESOLVED_ATTACK | N39: RG-WPN-018-DEFAULT-DAMAGE | P39: resolvedDamage | Q39: ATTACK_RESOLUTION_AND_COMBAT_LOG | R39: ATTACK_RESOLUTION_AND_COMBAT_LOG | S39: Новый бросок для каждой отдельно разрешаемой атаки. Условная ветвь заменяет базовое выражение; базовый дайс бросается только в выбранной ветви. | T39: CORE-039 | U39: 75 | V39: =IF(COUNTIF($A$5:$A$69,A39)=1,"PASS","DUPLICATE") -> PASS | W39: =IF(OR(AND(G39="PER_ATTACK_ROLL",M39="EACH_RESOLVED_ATTACK",N39<>"",O39="",R39="ATTACK_RESOLUTION_AND_COMBAT_LOG",K39<>""),AND(G39="INSTANCE_VALUE",M39="PROFILE_SNAPSHOT",N39="",O39="instanceDamage",R39="NOT_APPLICABLE",K39="WEAPON_PROFILE_VERSION"),AND(G39="CONSTANT",M39="PROFILE_SNAPSHOT",N39="",O39="",R39="NOT_APPLICABLE",K39="ITEM_TEMPLATE")),IF(Q39="ATTACK_RESOLUTION_AND_COMBAT_LOG","PASS","FAIL"),"FAIL") -> PASS | X39: DAMAGE | Y39: OTHER_DIE | Z39: NEVER_PROGRESSION
A40: CVD-WPN-018-DEFAULT-PENETRATION | B40: ITM-WPN-018 | C40: Одноручный топор | D40: DEFAULT | E40: PENETRATION | F40: R20 | G40: PER_ATTACK_ROLL | H40: ROLL(R20) | I40: ROLL(R20) | J40: NONE | K40: ITEM_TEMPLATE | M40: EACH_RESOLVED_ATTACK | N40: RG-WPN-018-DEFAULT-PENETRATION | P40: resolvedPenetration | Q40: ATTACK_RESOLUTION_AND_COMBAT_LOG | R40: ATTACK_RESOLUTION_AND_COMBAT_LOG | S40: Новый бросок для каждой отдельно разрешаемой атаки. | T40: CORE-039 | U40: 75 | V40: =IF(COUNTIF($A$5:$A$69,A40)=1,"PASS","DUPLICATE") -> PASS | W40: =IF(OR(AND(G40="PER_ATTACK_ROLL",M40="EACH_RESOLVED_ATTACK",N40<>"",O40="",R40="ATTACK_RESOLUTION_AND_COMBAT_LOG",K40<>""),AND(G40="INSTANCE_VALUE",M40="PROFILE_SNAPSHOT",N40="",O40="instanceDamage",R40="NOT_APPLICABLE",K40="WEAPON_PROFILE_VERSION"),AND(G40="CONSTANT",M40="PROFILE_SNAPSHOT",N40="",O40="",R40="NOT_APPLICABLE",K40="ITEM_TEMPLATE")),IF(Q40="ATTACK_RESOLUTION_AND_COMBAT_LOG","PASS","FAIL"),"FAIL") -> PASS | X40: PENETRATION | Y40: D20 | Z40: NO_DIRECT_BUT_POOL
A41: CVD-WPN-019-DEFAULT-DAMAGE | B41: ITM-WPN-019 | C41: Клевец | D41: DEFAULT | E41: DAMAGE | F41: R6+S; proc: 20+S | G41: PER_ATTACK_ROLL | H41: ROLL(R6)+attacker.S | I41: ROLL(R6) | J41: S | K41: ITEM_TEMPLATE | L41: IF(accuracyTotal>=35,20+attacker.S,baseDamage+attacker.S); armorIgnoredOnTrue=true | M41: EACH_RESOLVED_ATTACK | N41: RG-WPN-019-DEFAULT-DAMAGE | P41: resolvedDamage | Q41: ATTACK_RESOLUTION_AND_COMBAT_LOG | R41: ATTACK_RESOLUTION_AND_COMBAT_LOG | S41: Новый бросок для каждой отдельно разрешаемой атаки. Условная ветвь заменяет базовое выражение; базовый дайс бросается только в выбранной ветви. | T41: CORE-040 | U41: 75 | V41: =IF(COUNTIF($A$5:$A$69,A41)=1,"PASS","DUPLICATE") -> PASS | W41: =IF(OR(AND(G41="PER_ATTACK_ROLL",M41="EACH_RESOLVED_ATTACK",N41<>"",O41="",R41="ATTACK_RESOLUTION_AND_COMBAT_LOG",K41<>""),AND(G41="INSTANCE_VALUE",M41="PROFILE_SNAPSHOT",N41="",O41="instanceDamage",R41="NOT_APPLICABLE",K41="WEAPON_PROFILE_VERSION"),AND(G41="CONSTANT",M41="PROFILE_SNAPSHOT",N41="",O41="",R41="NOT_APPLICABLE",K41="ITEM_TEMPLATE")),IF(Q41="ATTACK_RESOLUTION_AND_COMBAT_LOG","PASS","FAIL"),"FAIL") -> PASS | X41: DAMAGE | Y41: OTHER_DIE | Z41: NEVER_PROGRESSION
A42: CVD-WPN-019-DEFAULT-PENETRATION | B42: ITM-WPN-019 | C42: Клевец | D42: DEFAULT | E42: PENETRATION | F42: R20+5 | G42: PER_ATTACK_ROLL | H42: ROLL(R20)+5 | I42: ROLL(R20)+5 | J42: NONE | K42: ITEM_TEMPLATE | M42: EACH_RESOLVED_ATTACK | N42: RG-WPN-019-DEFAULT-PENETRATION | P42: resolvedPenetration | Q42: ATTACK_RESOLUTION_AND_COMBAT_LOG | R42: ATTACK_RESOLUTION_AND_COMBAT_LOG | S42: Новый бросок для каждой отдельно разрешаемой атаки. | T42: CORE-040 | U42: 75 | V42: =IF(COUNTIF($A$5:$A$69,A42)=1,"PASS","DUPLICATE") -> PASS | W42: =IF(OR(AND(G42="PER_ATTACK_ROLL",M42="EACH_RESOLVED_ATTACK",N42<>"",O42="",R42="ATTACK_RESOLUTION_AND_COMBAT_LOG",K42<>""),AND(G42="INSTANCE_VALUE",M42="PROFILE_SNAPSHOT",N42="",O42="instanceDamage",R42="NOT_APPLICABLE",K42="WEAPON_PROFILE_VERSION"),AND(G42="CONSTANT",M42="PROFILE_SNAPSHOT",N42="",O42="",R42="NOT_APPLICABLE",K42="ITEM_TEMPLATE")),IF(Q42="ATTACK_RESOLUTION_AND_COMBAT_LOG","PASS","FAIL"),"FAIL") -> PASS | X42: PENETRATION | Y42: D20 | Z42: NO_DIRECT_BUT_POOL
A43: CVD-WPN-020-DEFAULT-DAMAGE | B43: ITM-WPN-020 | C43: Двуручный топор | D43: DEFAULT | E43: DAMAGE | F43: R20+S; proc: 20+S | G43: PER_ATTACK_ROLL | H43: ROLL(R20)+attacker.S | I43: ROLL(R20) | J43: S | K43: ITEM_TEMPLATE | L43: IF(accuracyTotal>=37,20+attacker.S,baseDamage+attacker.S); armorIgnoredOnTrue=true | M43: EACH_RESOLVED_ATTACK | N43: RG-WPN-020-DEFAULT-DAMAGE | P43: resolvedDamage | Q43: ATTACK_RESOLUTION_AND_COMBAT_LOG | R43: ATTACK_RESOLUTION_AND_COMBAT_LOG | S43: Новый бросок для каждой отдельно разрешаемой атаки. Условная ветвь заменяет базовое выражение; базовый дайс бросается только в выбранной ветви. | T43: CORE-041 | U43: 75 | V43: =IF(COUNTIF($A$5:$A$69,A43)=1,"PASS","DUPLICATE") -> PASS | W43: =IF(OR(AND(G43="PER_ATTACK_ROLL",M43="EACH_RESOLVED_ATTACK",N43<>"",O43="",R43="ATTACK_RESOLUTION_AND_COMBAT_LOG",K43<>""),AND(G43="INSTANCE_VALUE",M43="PROFILE_SNAPSHOT",N43="",O43="instanceDamage",R43="NOT_APPLICABLE",K43="WEAPON_PROFILE_VERSION"),AND(G43="CONSTANT",M43="PROFILE_SNAPSHOT",N43="",O43="",R43="NOT_APPLICABLE",K43="ITEM_TEMPLATE")),IF(Q43="ATTACK_RESOLUTION_AND_COMBAT_LOG","PASS","FAIL"),"FAIL") -> PASS | X43: DAMAGE | Y43: D20 | Z43: NO_DIRECT_BUT_POOL
A44: CVD-WPN-020-DEFAULT-PENETRATION | B44: ITM-WPN-020 | C44: Двуручный топор | D44: DEFAULT | E44: PENETRATION | F44: R20+10 | G44: PER_ATTACK_ROLL | H44: ROLL(R20)+10 | I44: ROLL(R20)+10 | J44: NONE | K44: ITEM_TEMPLATE | M44: EACH_RESOLVED_ATTACK | N44: RG-WPN-020-DEFAULT-PENETRATION | P44: resolvedPenetration | Q44: ATTACK_RESOLUTION_AND_COMBAT_LOG | R44: ATTACK_RESOLUTION_AND_COMBAT_LOG | S44: Новый бросок для каждой отдельно разрешаемой атаки. | T44: CORE-041 | U44: 75 | V44: =IF(COUNTIF($A$5:$A$69,A44)=1,"PASS","DUPLICATE") -> PASS | W44: =IF(OR(AND(G44="PER_ATTACK_ROLL",M44="EACH_RESOLVED_ATTACK",N44<>"",O44="",R44="ATTACK_RESOLUTION_AND_COMBAT_LOG",K44<>""),AND(G44="INSTANCE_VALUE",M44="PROFILE_SNAPSHOT",N44="",O44="instanceDamage",R44="NOT_APPLICABLE",K44="WEAPON_PROFILE_VERSION"),AND(G44="CONSTANT",M44="PROFILE_SNAPSHOT",N44="",O44="",R44="NOT_APPLICABLE",K44="ITEM_TEMPLATE")),IF(Q44="ATTACK_RESOLUTION_AND_COMBAT_LOG","PASS","FAIL"),"FAIL") -> PASS | X44: PENETRATION | Y44: D20 | Z44: NO_DIRECT_BUT_POOL
A45: CVD-WPN-021-DEFAULT-DAMAGE | B45: ITM-WPN-021 | C45: Кастет | D45: DEFAULT | E45: DAMAGE | F45: R6+S | G45: PER_ATTACK_ROLL | H45: ROLL(R6)+attacker.S | I45: ROLL(R6) | J45: S | K45: ITEM_TEMPLATE | M45: EACH_RESOLVED_ATTACK | N45: RG-WPN-021-DEFAULT-DAMAGE | P45: resolvedDamage | Q45: ATTACK_RESOLUTION_AND_COMBAT_LOG | R45: ATTACK_RESOLUTION_AND_COMBAT_LOG | S45: Новый бросок для каждой отдельно разрешаемой атаки. | T45: CORE-042 | U45: 76 | V45: =IF(COUNTIF($A$5:$A$69,A45)=1,"PASS","DUPLICATE") -> PASS | W45: =IF(OR(AND(G45="PER_ATTACK_ROLL",M45="EACH_RESOLVED_ATTACK",N45<>"",O45="",R45="ATTACK_RESOLUTION_AND_COMBAT_LOG",K45<>""),AND(G45="INSTANCE_VALUE",M45="PROFILE_SNAPSHOT",N45="",O45="instanceDamage",R45="NOT_APPLICABLE",K45="WEAPON_PROFILE_VERSION"),AND(G45="CONSTANT",M45="PROFILE_SNAPSHOT",N45="",O45="",R45="NOT_APPLICABLE",K45="ITEM_TEMPLATE")),IF(Q45="ATTACK_RESOLUTION_AND_COMBAT_LOG","PASS","FAIL"),"FAIL") -> PASS | X45: DAMAGE | Y45: OTHER_DIE | Z45: NEVER_PROGRESSION
A46: CVD-WPN-021-DEFAULT-PENETRATION | B46: ITM-WPN-021 | C46: Кастет | D46: DEFAULT | E46: PENETRATION | F46: R6 | G46: PER_ATTACK_ROLL | H46: ROLL(R6) | I46: ROLL(R6) | J46: NONE | K46: ITEM_TEMPLATE | M46: EACH_RESOLVED_ATTACK | N46: RG-WPN-021-DEFAULT-PENETRATION | P46: resolvedPenetration | Q46: ATTACK_RESOLUTION_AND_COMBAT_LOG | R46: ATTACK_RESOLUTION_AND_COMBAT_LOG | S46: Новый бросок для каждой отдельно разрешаемой атаки. | T46: CORE-042 | U46: 76 | V46: =IF(COUNTIF($A$5:$A$69,A46)=1,"PASS","DUPLICATE") -> PASS | W46: =IF(OR(AND(G46="PER_ATTACK_ROLL",M46="EACH_RESOLVED_ATTACK",N46<>"",O46="",R46="ATTACK_RESOLUTION_AND_COMBAT_LOG",K46<>""),AND(G46="INSTANCE_VALUE",M46="PROFILE_SNAPSHOT",N46="",O46="instanceDamage",R46="NOT_APPLICABLE",K46="WEAPON_PROFILE_VERSION"),AND(G46="CONSTANT",M46="PROFILE_SNAPSHOT",N46="",O46="",R46="NOT_APPLICABLE",K46="ITEM_TEMPLATE")),IF(Q46="ATTACK_RESOLUTION_AND_COMBAT_LOG","PASS","FAIL"),"FAIL") -> PASS | X46: PENETRATION | Y46: OTHER_DIE | Z46: NEVER_PROGRESSION
A47: CVD-WPN-022-DEFAULT-DAMAGE | B47: ITM-WPN-022 | C47: Деревянный круглый щит | D47: DEFAULT | E47: DAMAGE | F47: R6+S | G47: PER_ATTACK_ROLL | H47: ROLL(R6)+attacker.S | I47: ROLL(R6) | J47: S | K47: ITEM_TEMPLATE | M47: EACH_RESOLVED_ATTACK | N47: RG-WPN-022-DEFAULT-DAMAGE | P47: resolvedDamage | Q47: ATTACK_RESOLUTION_AND_COMBAT_LOG | R47: ATTACK_RESOLUTION_AND_COMBAT_LOG | S47: Новый бросок для каждой отдельно разрешаемой атаки. | T47: CORE-043 | U47: 77 | V47: =IF(COUNTIF($A$5:$A$69,A47)=1,"PASS","DUPLICATE") -> PASS | W47: =IF(OR(AND(G47="PER_ATTACK_ROLL",M47="EACH_RESOLVED_ATTACK",N47<>"",O47="",R47="ATTACK_RESOLUTION_AND_COMBAT_LOG",K47<>""),AND(G47="INSTANCE_VALUE",M47="PROFILE_SNAPSHOT",N47="",O47="instanceDamage",R47="NOT_APPLICABLE",K47="WEAPON_PROFILE_VERSION"),AND(G47="CONSTANT",M47="PROFILE_SNAPSHOT",N47="",O47="",R47="NOT_APPLICABLE",K47="ITEM_TEMPLATE")),IF(Q47="ATTACK_RESOLUTION_AND_COMBAT_LOG","PASS","FAIL"),"FAIL") -> PASS | X47: DAMAGE | Y47: OTHER_DIE | Z47: NEVER_PROGRESSION
A48: CVD-WPN-022-DEFAULT-PENETRATION | B48: ITM-WPN-022 | C48: Деревянный круглый щит | D48: DEFAULT | E48: PENETRATION | F48: R6 | G48: PER_ATTACK_ROLL | H48: ROLL(R6) | I48: ROLL(R6) | J48: NONE | K48: ITEM_TEMPLATE | M48: EACH_RESOLVED_ATTACK | N48: RG-WPN-022-DEFAULT-PENETRATION | P48: resolvedPenetration | Q48: ATTACK_RESOLUTION_AND_COMBAT_LOG | R48: ATTACK_RESOLUTION_AND_COMBAT_LOG | S48: Новый бросок для каждой отдельно разрешаемой атаки. | T48: CORE-043 | U48: 77 | V48: =IF(COUNTIF($A$5:$A$69,A48)=1,"PASS","DUPLICATE") -> PASS | W48: =IF(OR(AND(G48="PER_ATTACK_ROLL",M48="EACH_RESOLVED_ATTACK",N48<>"",O48="",R48="ATTACK_RESOLUTION_AND_COMBAT_LOG",K48<>""),AND(G48="INSTANCE_VALUE",M48="PROFILE_SNAPSHOT",N48="",O48="instanceDamage",R48="NOT_APPLICABLE",K48="WEAPON_PROFILE_VERSION"),AND(G48="CONSTANT",M48="PROFILE_SNAPSHOT",N48="",O48="",R48="NOT_APPLICABLE",K48="ITEM_TEMPLATE")),IF(Q48="ATTACK_RESOLUTION_AND_COMBAT_LOG","PASS","FAIL"),"FAIL") -> PASS | X48: PENETRATION | Y48: OTHER_DIE | Z48: NEVER_PROGRESSION
A49: CVD-WPN-023-DEFAULT-DAMAGE | B49: ITM-WPN-023 | C49: Железный круглый щит | D49: DEFAULT | E49: DAMAGE | F49: R6+S | G49: PER_ATTACK_ROLL | H49: ROLL(R6)+attacker.S | I49: ROLL(R6) | J49: S | K49: ITEM_TEMPLATE | M49: EACH_RESOLVED_ATTACK | N49: RG-WPN-023-DEFAULT-DAMAGE | P49: resolvedDamage | Q49: ATTACK_RESOLUTION_AND_COMBAT_LOG | R49: ATTACK_RESOLUTION_AND_COMBAT_LOG | S49: Новый бросок для каждой отдельно разрешаемой атаки. | T49: CORE-044 | U49: 77 | V49: =IF(COUNTIF($A$5:$A$69,A49)=1,"PASS","DUPLICATE") -> PASS | W49: =IF(OR(AND(G49="PER_ATTACK_ROLL",M49="EACH_RESOLVED_ATTACK",N49<>"",O49="",R49="ATTACK_RESOLUTION_AND_COMBAT_LOG",K49<>""),AND(G49="INSTANCE_VALUE",M49="PROFILE_SNAPSHOT",N49="",O49="instanceDamage",R49="NOT_APPLICABLE",K49="WEAPON_PROFILE_VERSION"),AND(G49="CONSTANT",M49="PROFILE_SNAPSHOT",N49="",O49="",R49="NOT_APPLICABLE",K49="ITEM_TEMPLATE")),IF(Q49="ATTACK_RESOLUTION_AND_COMBAT_LOG","PASS","FAIL"),"FAIL") -> PASS | X49: DAMAGE | Y49: OTHER_DIE | Z49: NEVER_PROGRESSION
A50: CVD-WPN-023-DEFAULT-PENETRATION | B50: ITM-WPN-023 | C50: Железный круглый щит | D50: DEFAULT | E50: PENETRATION | F50: R6 | G50: PER_ATTACK_ROLL | H50: ROLL(R6) | I50: ROLL(R6) | J50: NONE | K50: ITEM_TEMPLATE | M50: EACH_RESOLVED_ATTACK | N50: RG-WPN-023-DEFAULT-PENETRATION | P50: resolvedPenetration | Q50: ATTACK_RESOLUTION_AND_COMBAT_LOG | R50: ATTACK_RESOLUTION_AND_COMBAT_LOG | S50: Новый бросок для каждой отдельно разрешаемой атаки. | T50: CORE-044 | U50: 77 | V50: =IF(COUNTIF($A$5:$A$69,A50)=1,"PASS","DUPLICATE") -> PASS | W50: =IF(OR(AND(G50="PER_ATTACK_ROLL",M50="EACH_RESOLVED_ATTACK",N50<>"",O50="",R50="ATTACK_RESOLUTION_AND_COMBAT_LOG",K50<>""),AND(G50="INSTANCE_VALUE",M50="PROFILE_SNAPSHOT",N50="",O50="instanceDamage",R50="NOT_APPLICABLE",K50="WEAPON_PROFILE_VERSION"),AND(G50="CONSTANT",M50="PROFILE_SNAPSHOT",N50="",O50="",R50="NOT_APPLICABLE",K50="ITEM_TEMPLATE")),IF(Q50="ATTACK_RESOLUTION_AND_COMBAT_LOG","PASS","FAIL"),"FAIL") -> PASS | X50: PENETRATION | Y50: OTHER_DIE | Z50: NEVER_PROGRESSION
A51: CVD-WPN-024-DEFAULT-DAMAGE | B51: ITM-WPN-024 | C51: Деревянный треугольный щит | D51: DEFAULT | E51: DAMAGE | F51: R6+3+S | G51: PER_ATTACK_ROLL | H51: ROLL(R6)+3+attacker.S | I51: ROLL(R6)+3 | J51: S | K51: ITEM_TEMPLATE | M51: EACH_RESOLVED_ATTACK | N51: RG-WPN-024-DEFAULT-DAMAGE | P51: resolvedDamage | Q51: ATTACK_RESOLUTION_AND_COMBAT_LOG | R51: ATTACK_RESOLUTION_AND_COMBAT_LOG | S51: Новый бросок для каждой отдельно разрешаемой атаки. | T51: CORE-045 | U51: 78 | V51: =IF(COUNTIF($A$5:$A$69,A51)=1,"PASS","DUPLICATE") -> PASS | W51: =IF(OR(AND(G51="PER_ATTACK_ROLL",M51="EACH_RESOLVED_ATTACK",N51<>"",O51="",R51="ATTACK_RESOLUTION_AND_COMBAT_LOG",K51<>""),AND(G51="INSTANCE_VALUE",M51="PROFILE_SNAPSHOT",N51="",O51="instanceDamage",R51="NOT_APPLICABLE",K51="WEAPON_PROFILE_VERSION"),AND(G51="CONSTANT",M51="PROFILE_SNAPSHOT",N51="",O51="",R51="NOT_APPLICABLE",K51="ITEM_TEMPLATE")),IF(Q51="ATTACK_RESOLUTION_AND_COMBAT_LOG","PASS","FAIL"),"FAIL") -> PASS | X51: DAMAGE | Y51: OTHER_DIE | Z51: NEVER_PROGRESSION
A52: CVD-WPN-024-DEFAULT-PENETRATION | B52: ITM-WPN-024 | C52: Деревянный треугольный щит | D52: DEFAULT | E52: PENETRATION | F52: R6 | G52: PER_ATTACK_ROLL | H52: ROLL(R6) | I52: ROLL(R6) | J52: NONE | K52: ITEM_TEMPLATE | M52: EACH_RESOLVED_ATTACK | N52: RG-WPN-024-DEFAULT-PENETRATION | P52: resolvedPenetration | Q52: ATTACK_RESOLUTION_AND_COMBAT_LOG | R52: ATTACK_RESOLUTION_AND_COMBAT_LOG | S52: Новый бросок для каждой отдельно разрешаемой атаки. | T52: CORE-045 | U52: 78 | V52: =IF(COUNTIF($A$5:$A$69,A52)=1,"PASS","DUPLICATE") -> PASS | W52: =IF(OR(AND(G52="PER_ATTACK_ROLL",M52="EACH_RESOLVED_ATTACK",N52<>"",O52="",R52="ATTACK_RESOLUTION_AND_COMBAT_LOG",K52<>""),AND(G52="INSTANCE_VALUE",M52="PROFILE_SNAPSHOT",N52="",O52="instanceDamage",R52="NOT_APPLICABLE",K52="WEAPON_PROFILE_VERSION"),AND(G52="CONSTANT",M52="PROFILE_SNAPSHOT",N52="",O52="",R52="NOT_APPLICABLE",K52="ITEM_TEMPLATE")),IF(Q52="ATTACK_RESOLUTION_AND_COMBAT_LOG","PASS","FAIL"),"FAIL") -> PASS | X52: PENETRATION | Y52: OTHER_DIE | Z52: NEVER_PROGRESSION
A53: CVD-WPN-025-DEFAULT-DAMAGE | B53: ITM-WPN-025 | C53: Железный треугольный щит | D53: DEFAULT | E53: DAMAGE | F53: R6+3+S | G53: PER_ATTACK_ROLL | H53: ROLL(R6)+3+attacker.S | I53: ROLL(R6)+3 | J53: S | K53: ITEM_TEMPLATE | M53: EACH_RESOLVED_ATTACK | N53: RG-WPN-025-DEFAULT-DAMAGE | P53: resolvedDamage | Q53: ATTACK_RESOLUTION_AND_COMBAT_LOG | R53: ATTACK_RESOLUTION_AND_COMBAT_LOG | S53: Новый бросок для каждой отдельно разрешаемой атаки. | T53: CORE-046 | U53: 78 | V53: =IF(COUNTIF($A$5:$A$69,A53)=1,"PASS","DUPLICATE") -> PASS | W53: =IF(OR(AND(G53="PER_ATTACK_ROLL",M53="EACH_RESOLVED_ATTACK",N53<>"",O53="",R53="ATTACK_RESOLUTION_AND_COMBAT_LOG",K53<>""),AND(G53="INSTANCE_VALUE",M53="PROFILE_SNAPSHOT",N53="",O53="instanceDamage",R53="NOT_APPLICABLE",K53="WEAPON_PROFILE_VERSION"),AND(G53="CONSTANT",M53="PROFILE_SNAPSHOT",N53="",O53="",R53="NOT_APPLICABLE",K53="ITEM_TEMPLATE")),IF(Q53="ATTACK_RESOLUTION_AND_COMBAT_LOG","PASS","FAIL"),"FAIL") -> PASS | X53: DAMAGE | Y53: OTHER_DIE | Z53: NEVER_PROGRESSION
A54: CVD-WPN-025-DEFAULT-PENETRATION | B54: ITM-WPN-025 | C54: Железный треугольный щит | D54: DEFAULT | E54: PENETRATION | F54: R6 | G54: PER_ATTACK_ROLL | H54: ROLL(R6) | I54: ROLL(R6) | J54: NONE | K54: ITEM_TEMPLATE | M54: EACH_RESOLVED_ATTACK | N54: RG-WPN-025-DEFAULT-PENETRATION | P54: resolvedPenetration | Q54: ATTACK_RESOLUTION_AND_COMBAT_LOG | R54: ATTACK_RESOLUTION_AND_COMBAT_LOG | S54: Новый бросок для каждой отдельно разрешаемой атаки. | T54: CORE-046 | U54: 78 | V54: =IF(COUNTIF($A$5:$A$69,A54)=1,"PASS","DUPLICATE") -> PASS | W54: =IF(OR(AND(G54="PER_ATTACK_ROLL",M54="EACH_RESOLVED_ATTACK",N54<>"",O54="",R54="ATTACK_RESOLUTION_AND_COMBAT_LOG",K54<>""),AND(G54="INSTANCE_VALUE",M54="PROFILE_SNAPSHOT",N54="",O54="instanceDamage",R54="NOT_APPLICABLE",K54="WEAPON_PROFILE_VERSION"),AND(G54="CONSTANT",M54="PROFILE_SNAPSHOT",N54="",O54="",R54="NOT_APPLICABLE",K54="ITEM_TEMPLATE")),IF(Q54="ATTACK_RESOLUTION_AND_COMBAT_LOG","PASS","FAIL"),"FAIL") -> PASS | X54: PENETRATION | Y54: OTHER_DIE | Z54: NEVER_PROGRESSION
A55: CVD-WPN-026-SWORD-DAMAGE | B55: ITM-WPN-026 | C55: Корнадора | D55: SWORD | E55: DAMAGE | F55: меч R20+S | G55: PER_ATTACK_ROLL | H55: ROLL(R20)+attacker.S | I55: ROLL(R20) | J55: S | K55: ITEM_TEMPLATE | M55: EACH_RESOLVED_ATTACK | N55: RG-WPN-026-SWORD-DAMAGE | P55: resolvedDamage | Q55: ATTACK_RESOLUTION_AND_COMBAT_LOG | R55: ATTACK_RESOLUTION_AND_COMBAT_LOG | S55: Новый бросок для каждой отдельно разрешаемой атаки. Значение относится к варианту/компоненту SWORD. | T55: CORE-047 | U55: 79 | V55: =IF(COUNTIF($A$5:$A$69,A55)=1,"PASS","DUPLICATE") -> PASS | W55: =IF(OR(AND(G55="PER_ATTACK_ROLL",M55="EACH_RESOLVED_ATTACK",N55<>"",O55="",R55="ATTACK_RESOLUTION_AND_COMBAT_LOG",K55<>""),AND(G55="INSTANCE_VALUE",M55="PROFILE_SNAPSHOT",N55="",O55="instanceDamage",R55="NOT_APPLICABLE",K55="WEAPON_PROFILE_VERSION"),AND(G55="CONSTANT",M55="PROFILE_SNAPSHOT",N55="",O55="",R55="NOT_APPLICABLE",K55="ITEM_TEMPLATE")),IF(Q55="ATTACK_RESOLUTION_AND_COMBAT_LOG","PASS","FAIL"),"FAIL") -> PASS | X55: DAMAGE | Y55: D20 | Z55: NO_DIRECT_BUT_POOL
... A69: CVD-WPN-012-TWO_HAND-PENETRATION | B69: ITM-WPN-012 | C69: Полуторный меч | D69: TWO_HAND | E69: PENETRATION | F69: R20 | G69: PER_ATTACK_ROLL | H69: ROLL(R20) | I69: ROLL(R20) | J69: NONE | K69: ITEM_TEMPLATE | M69: EACH_RESOLVED_ATTACK | N69: RG-WPN-012-TWO_HAND-PENETRATION | P69: resolvedPenetration | Q69: ATTACK_RESOLUTION_AND_COMBAT_LOG | R69: ATTACK_RESOLUTION_AND_COMBAT_LOG | S69: Полуторный меч: фиксированный хват двумя руками; новый бросок для каждой отдельно разрешаемой атаки. | T69: CORE-033 | U69: 73 | V69: =IF(COUNTIF($A$5:$A$69,A69)=1,"PASS","DUPLICATE") -> PASS | W69: =IF(OR(AND(G69="PER_ATTACK_ROLL",M69="EACH_RESOLVED_ATTACK",N69<>"",O69="",R69="ATTACK_RESOLUTION_AND_COMBAT_LOG",K69<>""),AND(G69="INSTANCE_VALUE",M69="PROFILE_SNAPSHOT",N69="",O69="instanceDamage",R69="NOT_APPLICABLE",K69="WEAPON_PROFILE_VERSION"),AND(G69="CONSTANT",M69="PROFILE_SNAPSHOT",N69="",O69="",R69="NOT_APPLICABLE",K69="ITEM_TEMPLATE")),IF(Q69="ATTACK_RESOLUTION_AND_COMBAT_LOG","PASS","FAIL"),"FAIL") -> PASS | X69: PENETRATION | Y69: D20 | Z69: NO_DIRECT_BUT_POOL

Sheet 07A_Разрешение_атаки
A1: Контракт разрешения боевых значений
A2: Каждая атака фиксирует sourceSnapshot и нормализованные RollOccurrence. DAMAGE/PENETRATION/ARMOR не становятся критическими; player rawFace=1/20 на исходном D20 направляет 1 балл только в CHARACTER_PROGRESS_COUNTER.
A4: Field | B4: Scope | C4: Data type | D4: Required | E4: Default | F4: Validation / constraint | G4: Purpose
A5: attackResolutionId | B5: ATTACK_RESOLUTION | C5: UUID | D5: =TRUE() -> TRUE | E5: — | F5: Уникален; неизменяем | G5: Идентичность разрешения конкретной атаки
A6: combatValueDefinitionIds | B6: ATTACK_RESOLUTION | C6: ARRAY<ID> | D6: =TRUE() -> TRUE | E6: [] | F6: Статический CVD, dynamic WeaponProfileVersion, MonsterAttackProfile, canonical special или symbiont rule; ровно реально использованные определения. | G6: Какие выражения разрешались
A7: itemInstanceIdByDefinition | B7: ATTACK_RESOLUTION | C7: MAP<ID,UUID> | D7: CONDITIONAL | E7: {} | F7: Обязательно только при sourceKind=ITEM; отсутствует для monster/symbiont/natural-armor source. | G7: Связь выражения с оружием/щитом/бронёй
A8: weaponProfileVersionIdsByDefinition | B8: ATTACK_RESOLUTION | C8: MAP<ID,UUID> | D8: CONDITIONAL | E8: {} | F8: Обязательно только для ITEM DAMAGE/PENETRATION; не подставлять фиктивную версию для монстра. | G8: Связь результата с версией профиля
A9: attackVariantIdByDefinition | B9: ATTACK_RESOLUTION | C9: MAP<ID,ENUM> | D9: CONDITIONAL | E9: {} | F9: Обязательно только для ITEM; для иных sourceKind используется профиль/ability ID. | G9: Использованный вариант
A10: effectiveWeaponProfileSnapshotsByVersion | B10: ATTACK_RESOLUTION | C10: MAP<UUID,JSON> | D10: CONDITIONAL | E10: {} | F10: Только sourceKind=ITEM; общий sourceSnapshotByDefinition обязателен для всех sourceKind. | G10: Повторяемость и отсутствие ретроспективного пересчёта
A11: rollResultsByGroupId | B11: ATTACK_RESOLUTION | C11: MAP<STRING,INTEGER> | D11: CONDITIONAL | E11: {} | F11: Ровно один сырой результат на каждый использованный rollGroupId; для dice-free определений записи нет | G11: Исходы бросков до множителей и бонусов
A12: resolvedDamage | B12: ATTACK_RESOLUTION | C12: NUMBER | D12: CONDITIONAL | E12: null | F12: Вычислен по активному DAMAGE-определению | G12: Итог урона до последующих правил снижения
A13: resolvedPenetration | B13: ATTACK_RESOLUTION | C13: NUMBER | D13: CONDITIONAL | E13: null | F13: Вычислен по активному PENETRATION-определению При armorPolicy=IGNORE_ARMOR_BY_MON-115 значение остаётся null: penetration не разрешается. | G13: Итог пробития этой атаки
A14: resolvedArmorByDefinition | B14: ATTACK_RESOLUTION | C14: MAP<ID,INTEGER> | D14: CONDITIONAL | E14: {} | F14: Значения только присутствующих слоёв. При armorLayerState=NO_LAYERS карта пуста, сравнение Pr>armor не выполняется. При armorPolicy=IGNORE_ARMOR_BY_MON-115 карта остаётся пустой: armor dice и сравнение не выполняются. | G14: Результаты брони этой атаки
A15: evaluationInputsSnapshot | B15: ATTACK_RESOLUTION | C15: JSON | D15: =TRUE() -> TRUE | E15: — | F15: Снимок sourceKind-specific профиля/правила, характеристик, модификаторов, DefenseChoice и armor layer set. При IGNORE_ARMOR исходный armor layer set сохраняется в снимке только для аудита и не влияет на урон. | G15: Повторяемость и аудит вычисления
A16: evaluatedAt | B16: ATTACK_RESOLUTION | C16: DATETIME | D16: =TRUE() -> TRUE | E16: — | F16: Время завершения разрешения | G16: Хронология
A17: combatLogEntryId | B17: ATTACK_RESOLUTION | C17: ID | D17: =TRUE() -> TRUE | E17: — | F17: Ссылка на неизменяемую запись боевого журнала | G17: Долговременное хранение результата
A18: itemInstanceWriteBack | B18: ATTACK_RESOLUTION | C18: ENUM | D18: =TRUE() -> TRUE | E18: NONE | F18: NONE; применимо при ITEM, для иных sourceKind поле остаётся NONE без фиктивного item. | G18: Явный запрет сохранять runtime-результаты в экземпляр предмета
A19: sourceKindByDefinition | B19: ATTACK_RESOLUTION | C19: MAP<ID,ENUM> | D19: =TRUE() -> TRUE | E19: {} | F19: ITEM | MONSTER_BASE_ATTACK | CANONICAL_SPECIAL_ATTACK | SYMBIONT_ABILITY | NATURAL_ARMOR. | G19: Выбор доменного resolver
A20: sourceSnapshotByDefinition | B20: ATTACK_RESOLUTION | C20: MAP<ID,JSON> | D20: =TRUE() -> TRUE | E20: {} | F20: Полный неизменяемый снимок каждого реально использованного source; поздняя правка не влияет. | G20: Общая повторяемость
A21: monsterAttackProfileIdByDefinition | B21: ATTACK_RESOLUTION | C21: MAP<ID,ID> | D21: CONDITIONAL | E21: {} | F21: Для MONSTER_BASE_ATTACK; ItemInstance отсутствует. | G21: Базовая атака монстра
A22: monsterEntityIdByDefinition | B22: ATTACK_RESOLUTION | C22: MAP<ID,UUID> | D22: CONDITIONAL | E22: {} | F22: Для monster-domain source; экземпляр атаки/брони. | G22: Связь с актором
A23: canonicalAttackProfileIdByDefinition | B23: ATTACK_RESOLUTION | C23: MAP<ID,ID> | D23: CONDITIONAL | E23: {} | F23: Для CANONICAL_SPECIAL_ATTACK. | G23: Каноническая особая атака
A24: symbiontAbilityRuleIdByDefinition | B24: ATTACK_RESOLUTION | C24: MAP<ID,RULE_ID> | D24: CONDITIONAL | E24: {} | F24: Для SYMBIONT_ABILITY. | G24: Источник способности
A25: armorLayerState | B25: ATTACK_RESOLUTION | C25: ENUM | D25: =TRUE() -> TRUE | E25: NO_LAYERS | F25: NO_LAYERS | PRESENT. NO_LAYERS пропускает любой Pr, включая 0. | G25: Безошибочное разрешение брони
A26: defenseChoice | B26: ATTACK_RESOLUTION | C26: ENUM | D26: =TRUE() -> TRUE | E26: NONE | F26: Одна доступная защита либо NONE. | G26: Выбор effectiveController цели
A27: defenseTotal | B27: ATTACK_RESOLUTION | C27: NUMBER | D27: =TRUE() -> TRUE | E27: 0 | F27: При NONE всегда 0 и бросок защиты отсутствует. | G27: Этап точности
A28: monsterTemplateWriteBack | B28: ATTACK_RESOLUTION | C28: ENUM | D28: =TRUE() -> TRUE | E28: NONE | F28: Единственное допустимое значение NONE. | G28: Запрет записи runtime-результатов в шаблон
A29: criticalResolutionByStage | B29: ATTACK_RESOLUTION | C29: MAP<ENUM,JSON> | D29: CONDITIONAL | E29: {} | F29: Только для этапов проверки с allowCritical=true. Хранит rawFace, criticalPolarity, confirmedGrade и resolutionMode; CORE-229 применяется до числового сравнения. DAMAGE/PENETRATION/ARMOR не включаются без отдельного прямого правила. | G29: Воспроизводимый боевой приоритет критичности по каждому этапу
A30: armorPolicy | B30: ATTACK_RESOLUTION | C30: ENUM | D30: =TRUE() -> TRUE | E30: STANDARD | F30: STANDARD | IGNORE_ARMOR_BY_MON-115. Локальная политика берётся из неизменяемого sourceSnapshot. | G30: Выбор обычного либо локально переопределённого конвейера брони
A31: penetrationResolution | B31: ATTACK_RESOLUTION | C31: ENUM | D31: =TRUE() -> TRUE | E31: NOT_RESOLVED | F31: NOT_RESOLVED | RESOLVED | SKIP. При IGNORE_ARMOR_BY_MON-115 обязательно SKIP и resolvedPenetration=null. | G31: Явное состояние этапа пробития
A32: armorResolution | B32: ATTACK_RESOLUTION | C32: ENUM | D32: =TRUE() -> TRUE | E32: NOT_RESOLVED | F32: NOT_RESOLVED | RESOLVED | SKIP. При IGNORE_ARMOR_BY_MON-115 обязательно SKIP и resolvedArmorByDefinition={}. | G32: Явное состояние этапа брони
A33: rollOccurrences | B33: ATTACK_RESOLUTION | C33: ARRAY<RollOccurrence> | D33: =TRUE() -> TRUE | E33: [] | F33: Одна запись на каждый фактически брошенный die occurrence; исходный D20 имеет уникальный originRollId. Множитель результата не создаёт вторую запись. | G33: Нормализованный аудит исходных, подтверждающих и служебных бросков
A34: rollMetadataByOriginRollId | B34: ATTACK_RESOLUTION | C34: MAP<UUID,RollOccurrence> | D34: =TRUE() -> TRUE | E34: {} | F34: Ключи уникальны; повторное разрешение originRollId не изменяет состояние. | G34: Дедупликация CORE-233
A35: progressionEvents | B35: ATTACK_RESOLUTION | C35: ARRAY<SymbiontXpEvent> | D35: =TRUE() -> TRUE | E35: [] | F35: Только для PLAYER_CHARACTER, original D20, rawFace=1|20; максимум одно событие на originRollId. | G35: Маршрут DIRECT_SYMBIONT | CHARACTER_PROGRESS_COUNTER | NEVER_PROGRESSION
A36: processedProgressionOriginRollIds | B36: ATTACK_RESOLUTION | C36: SET<UUID> | D36: =TRUE() -> TRUE | E36: {} | F36: После атомарной обработки содержит originRollId; повтор — IGNORED_DUPLICATE. | G36: Серверная защита от повторного XP/баллов
A37: progressionDependencyTuple | B37: ATTACK_RESOLUTION | C37: STRING | D37: =TRUE() -> TRUE | E37: Rules v1.6 | Character-Skills-Symbionts v1.1 | Items v1.5_with_icons | Bestiary v1.3 | Sentient v1.2 | F37: Должно дословно равняться: Rules v1.6 | Character-Skills-Symbionts v1.1 | Items v1.5_with_icons | Bestiary v1.3 | Sentient v1.2 | G37: Импорт и воспроизведение по совместимой линии

Sheet 07B_Профиль_оружия
A1: Версионный эффективный профиль оружия
A2: Одна WeaponProfileVersion относится к одному itemInstanceId и attackVariantId. Эффективный профиль = templateProfile + instanceProfilePatch; формулы крафта не исполняются. CORE-183…190.
A4: Field | B4: Scope | C4: Data type | D4: Required | E4: Default | F4: Validation / constraint | G4: Purpose
A5: weaponProfileVersionId | B5: WEAPON_PROFILE_VERSION | C5: UUID | D5: =TRUE() -> TRUE | E5: — | F5: Уникален; неизменяем | G5: Идентичность версии
A6: previousVersionId | B6: WEAPON_PROFILE_VERSION | C6: UUID | D6: =FALSE() -> FALSE | F6: FK на предыдущую версию того же itemInstanceId+attackVariantId | G6: Цепочка версий
A7: itemInstanceId | B7: WEAPON_PROFILE_VERSION | C7: UUID | D7: =TRUE() -> TRUE | E7: — | F7: FK → 07_Модель_экземпляра.itemInstanceId | G7: Конкретный экземпляр
A8: ownerId | B8: WEAPON_PROFILE_VERSION | C8: ID | D8: =TRUE() -> TRUE | E8: — | F8: Снимок владельца на момент создания версии; CHARACTER включает игрока и НПС | G8: Аудит области действия
A9: ownerType | B9: WEAPON_PROFILE_VERSION | C9: ENUM | D9: =TRUE() -> TRUE | E9: CHARACTER | F9: CHARACTER | CORPSE | BATTLE_SCENE; для master patch существующего оружия обычно CHARACTER | G9: Тип владельца
A10: attackVariantId | B10: WEAPON_PROFILE_VERSION | C10: ENUM | D10: =TRUE() -> TRUE | E10: DEFAULT | F10: DEFAULT|ONE_HAND|TWO_HAND|SWORD|SHIELD|RAPIER; для многовариантного оружия обязателен | G10: Вариант профиля/атаки
A11: statSource | B11: WEAPON_PROFILE_VERSION | C11: ENUM | D11: =TRUE() -> TRUE | E11: TEMPLATE_FIXED | F11: TEMPLATE_FIXED | PLAYER_FORMULA_VALIDATED | MASTER_OVERRIDE | G11: Происхождение профиля
A12: templateProfileVersion | B12: WEAPON_PROFILE_VERSION | C12: STRING | D12: =TRUE() -> TRUE | E12: ITEM_REGISTRY_V1.2 | F12: Версия канонического шаблона, от которого строится effective profile | G12: Трассировка шаблона
A13: formulaId | B13: PLAYER_VALIDATION | C13: ID | D13: CONDITIONAL | F13: Обязателен для PLAYER_FORMULA_VALIDATED; FK → 05_Формулы_валидации | G13: Использованная формула
A14: formulaVersion | B14: PLAYER_VALIDATION | C14: STRING | D14: CONDITIONAL | F14: Для PLAYER_FORMULA_VALIDATED = ITEM_FORMULAS_V1.2 | G14: Воспроизводимость валидатора
A15: validationStatus | B15: PLAYER_VALIDATION | C15: ENUM | D15: =TRUE() -> TRUE | E15: NOT_APPLICABLE | F15: PLAYER_FORMULA_VALIDATED→VALID; MASTER_OVERRIDE→OVERRIDDEN; TEMPLATE_FIXED→NOT_APPLICABLE | G15: Итог проверки
A16: validationWitness | B16: PLAYER_VALIDATION | C16: JSON | D16: CONDITIONAL | F16: Обязателен для PLAYER_FORMULA_VALIDATED; L/Lw/Ls и каждый независимый производственный дайс | G16: Доказательство joint feasibility
A17: instanceProfilePatch | B17: WEAPON_PROFILE_VERSION | C17: JSON | D17: CONDITIONAL | E17: {} | F17: Для PLAYER_FORMULA_VALIDATED содержит только формульные выходы; для MASTER_OVERRIDE — только поля MasterPatchFieldsTable | G17: Дельта к шаблону/предыдущей версии
A18: effectiveProfile | B18: WEAPON_PROFILE_VERSION | C18: JSON | D18: =TRUE() -> TRUE | E18: — | F18: Полный результат templateProfile + instanceProfilePatch; совпадает с afterProfile и структурированными полями версии | G18: Единый runtime-снимок профиля
A19: damageDefinition | B19: EFFECTIVE_PROFILE | C19: OBJECT | D19: =TRUE() -> TRUE | E19: — | F19: definitionId,valueMode,sourceNotation,baseExpression,sourceScope,evaluationScope,rollGroupId; master dice — только по закрытой грамматике | G19: Базовое определение урона
A20: penetrationDefinition | B20: EFFECTIVE_PROFILE | C20: OBJECT | D20: =TRUE() -> TRUE | E20: — | F20: Та же структура; rollGroupId независим от DAMAGE, если обе величины бросаются | G20: Базовое определение пробития
A21: instanceDamage | B21: EFFECTIVE_PROFILE | C21: NUMBER | D21: CONDITIONAL | F21: Обязателен и >0 только когда effective damageDefinition.valueMode=INSTANCE_VALUE; никогда не хранит исход боя | G21: Готовое Dm
A22: statRequirements | B22: EFFECTIVE_PROFILE | C22: MAP<STAT,NUMBER> | D22: =TRUE() -> TRUE | E22: {} | F22: Ключи S/D/I/W/M/Z/C; значения конечные >0; пустая карта = нет требований | G22: Требования для использования без штрафа
A23: rangeMeters | B23: EFFECTIVE_PROFILE | C23: DECIMAL | D23: CONDITIONAL | F23: Для дальнобойного attackVariantId конечное >0; для ближнего отсутствует | G23: Предельная дальность
A24: accuracyBonus | B24: EFFECTIVE_PROFILE | C24: DECIMAL | D24: =FALSE() -> FALSE | F24: Отсутствует либо конечное >0; аддитивно к обычной проверке точности | G24: Мастерский бонус точности
A25: actorId | B25: VERSION_AUDIT | C25: ID | D25: =TRUE() -> TRUE | E25: — | F25: Игрок, мастер или системный актор | G25: Кто инициировал версию
A26: actorRole | B26: VERSION_AUDIT | C26: ENUM | D26: =TRUE() -> TRUE | E26: — | F26: PLAYER | MASTER | SYSTEM | G26: Роль инициатора
A27: reason | B27: VERSION_AUDIT | C27: STRING | D27: CONDITIONAL | F27: Обязателен для MASTER_OVERRIDE | G27: Основание изменения
A28: createdAt | B28: VERSION_AUDIT | C28: DATETIME | D28: =TRUE() -> TRUE | E28: — | F28: Неизменяемо | G28: Время версии
A29: beforeProfile | B29: VERSION_AUDIT | C29: JSON | D29: CONDITIONAL | F29: Обязателен для изменения существующего MASTER_OVERRIDE; null при первичном создании | G29: Снимок до операции
A30: afterProfile | B30: VERSION_AUDIT | C30: JSON | D30: =TRUE() -> TRUE | E30: — | F30: Полный effective profile после patch | G30: Снимок после операции
A31: effectiveFrom | B31: VERSION_AUDIT | C31: ENUM | D31: =TRUE() -> TRUE | E31: NEXT_RESOLVED_ATTACK | F31: Новая версия не меняет уже начатую атаку | G31: Граница активации
A32: active | B32: VERSION_AUDIT | C32: BOOLEAN | D32: =TRUE() -> TRUE | E32: =FALSE() -> FALSE | F32: В каждый момент одна активная версия на itemInstanceId+attackVariantId | G32: Текущая версия
A33: immutableAudit | B33: VERSION_AUDIT | C33: BOOLEAN | D33: =TRUE() -> TRUE | E33: =TRUE() -> TRUE | F33: Всегда true; версия, before/after и ссылки боевого лога не переписываются | G33: Запрет ретроспективной мутации
A35: Закрытая грамматика мастерских дайсов
A36: X — конечное положительное число. Bare R20 не выбирается как новый шаблон, но уже существующий канонический R20 сохраняется, пока поле не заменено. definitionId и rollGroupId генерируются из weaponProfileVersionId+attackVariantId+valueKind.
A37: sourceNotation | B37: X required | C37: X domain | D37: valueMode | E37: baseExpression | F37: evaluationScope | G37: Rule ID
A38: R4 | B38: =FALSE() -> FALSE | C38: — | D38: PER_ATTACK_ROLL | E38: ROLL(R4) | F38: EACH_RESOLVED_ATTACK | G38: CORE-188/189
A39: R4+X | B39: =TRUE() -> TRUE | C39: finite NUMBER >0 | D39: PER_ATTACK_ROLL | E39: ROLL(R4)+X | F39: EACH_RESOLVED_ATTACK | G39: CORE-188/189
A40: R6 | B40: =FALSE() -> FALSE | C40: — | D40: PER_ATTACK_ROLL | E40: ROLL(R6) | F40: EACH_RESOLVED_ATTACK | G40: CORE-188/189
A41: R6+X | B41: =TRUE() -> TRUE | C41: finite NUMBER >0 | D41: PER_ATTACK_ROLL | E41: ROLL(R6)+X | F41: EACH_RESOLVED_ATTACK | G41: CORE-188/189
A42: R12 | B42: =FALSE() -> FALSE | C42: — | D42: PER_ATTACK_ROLL | E42: ROLL(R12) | F42: EACH_RESOLVED_ATTACK | G42: CORE-188/189
A43: R12+X | B43: =TRUE() -> TRUE | C43: finite NUMBER >0 | D43: PER_ATTACK_ROLL | E43: ROLL(R12)+X | F43: EACH_RESOLVED_ATTACK | G43: CORE-188/189
A44: R20+X | B44: =TRUE() -> TRUE | C44: finite NUMBER >0 | D44: PER_ATTACK_ROLL | E44: ROLL(R20)+X | F44: EACH_RESOLVED_ATTACK | G44: CORE-188/189
A45: R20*2+X | B45: =TRUE() -> TRUE | C45: finite NUMBER >0 | D45: PER_ATTACK_ROLL | E45: 2*ROLL(R20)+X | F45: EACH_RESOLVED_ATTACK | G45: CORE-188/189
A47: Разрешённые поля instanceProfilePatch мастера
A48: Неуказанное поле наследуется. Явный null разрешён только для удаления optional accuracyBonus либо instanceDamage, если итоговый damageDefinition больше не INSTANCE_VALUE. Шаблон, itemTypeId, навыки, ёмкость, перезарядка, HP и особые эффекты не меняются.
A49: Patch field | B49: Actor | C49: Applicable to | D49: Validation | E49: If omitted | F49: Explicit null | G49: Rule ID
A50: damageDefinition | B50: MASTER | C50: Любой известный тип/вариант оружия | D50: Только MasterDiceGrammarTable; полный объект definition | E50: Наследовать | F50: Запрещён | G50: CORE-187/188/189
A51: penetrationDefinition | B51: MASTER | C51: Любой известный тип/вариант оружия | D51: Только MasterDiceGrammarTable; отдельный rollGroupId | E51: Наследовать | F51: Запрещён | G51: CORE-187/188/189
A52: instanceDamage | B52: MASTER | C52: Только effective DAMAGE=INSTANCE_VALUE | D52: Конечное NUMBER >0; formula bounds не применяются | E52: Наследовать | F52: Только если итоговый DAMAGE≠INSTANCE_VALUE | G52: CORE-187/188
A53: statRequirements | B53: MASTER | C53: Любое оружие игрока/НПС, включая Чистых | D53: Полный MAP S/D/I/W/M/Z/C; каждое значение >0; {} снимает требования | E53: Наследовать | F53: Использовать {}, не null | G53: CORE-187/188
A54: rangeMeters | B54: MASTER | C54: Только дальнобойный attackVariantId | D54: Конечное DECIMAL >0 | E54: Наследовать | F54: Запрещён для дальнобойного | G54: CORE-187/188
A55: accuracyBonus | B55: MASTER | C55: Любое оружие игрока/НПС, включая Чистых | D55: Отсутствует либо конечное DECIMAL >0 | E55: Наследовать | F55: Удалить бонус | G55: CORE-187/188

Sheet 14_Изменения_v1.2
A1: Изменения Item Registry v1.2
A2: Синхронизация с Symbiosis_V7_Executable_Rules_Registry_v1.2. Правила не дублируют крафт: реестр описывает готовые экземпляры, валидацию игрока и мастерские версии профиля.
A4: № | B4: Область | C4: Rule IDs | D4: Изменение | E4: Результат для приложения | F4: Статус
A5: 1 | B5: Версия источника | C5: Rules v1.2 | D5: Трассировка всех 97 карточек обновлена; добавлены 4 затронутые карточки и CORE-183…190. | E5: 109 связанных правил без MISSING. | F5: SYNCED
A6: 2 | B6: Права игрока | C6: CORE-184/185/186 | D6: Редактирование только при создании; не-Чистое — формульные выходы, Чистое — read-only. | E6: Нет редактирования оружия игроком после создания. | F6: SYNCED
A7: 3 | B7: Права мастера | C7: CORE-187/188 | D7: Все 27 видов оружия допускают instance-level override, включая шесть Чистых. | E7: Одинаковый путь для игроков и НПС. | F7: SYNCED
A8: 4 | B8: Профиль оружия | C8: CORE-183/190 | D8: Добавлена неизменяемая WeaponProfileVersion и active pointer в ItemInstance. | E8: История, before/after и безопасная активация. | F8: SYNCED
A9: 5 | B9: Мастерский patch | C9: CORE-188 | D9: Добавлены 6 разрешённых полей и 8 шаблонов дайсов. | E9: Формульные границы обходятся, структурные — нет. | F9: SYNCED
A10: 6 | B10: Runtime | C10: CORE-189 | D10: Разделены baseExpression, damageModifierStat, sourceScope и evaluationScope. | E10: Характеристика не прибавляется дважды после override. | F10: SYNCED
A11: 7 | B11: Формулы игрока | C11: CORE-185 | D11: L/W/S заменены на L/Lw/Ls и пересчитаны быстрые диапазоны. | E11: Одна приоритетная область достижимости. | F11: SYNCED
A12: 8 | B12: Оружие Чистых | C12: CORE-186/187/188 | D12: TEMPLATE_FIXED сохранён для игрока; master override включён. | E12: Шаблон не мутирует, меняется экземпляр. | F12: SYNCED
A13: 9 | B13: Разрешение атаки | C13: CORE-189/190 | D13: Добавлены version IDs, attackVariant и snapshot. | E13: Поздняя правка не меняет начатую/завершённую атаку. | F13: SYNCED
A14: 10 | B14: Справочники | C14: CORE-184…190 | D14: Унифицированы enum и перенесены 15 кодов ошибок. | E14: Единый контракт API/UI. | F14: SYNCED
A15: 11 | B15: Операции | C15: CORE-187/190 | D15: Добавлены MASTER_PATCH_WEAPON_PROFILE и ACTIVATE_WEAPON_PROFILE_VERSION. | E15: Атомарный жизненный цикл версии. | F15: SYNCED
A16: 12 | B16: Контроль | C16: CORE-183…190 | D16: Добавлены межреестровые проверки и проверка заголовков/enum. | E16: Каждое расхождение превращается в FAIL. | F16: SYNCED

Sheet 15_Иконки_предметов
A1: Иконки предметов — встроенные ассеты | N1: Контроль полноты
A2: 64 пиктограммы 96×96 px в формате PNG. TYPE_ALIGNED — образ соответствует типу предмета; PROVISIONAL_VISUAL — у именного изделия нет утверждённого визуального канона; PROVISIONAL_ENTITY — самостоятельность сущности в инвентаре не решена. | N2: Ожидается предметов | O2: =COUNTA('01_Каталог'!$A$5:$A$68) -> 64
N3: Строк с иконками | O3: =COUNTA($A$5:$A$68) -> 64
A4: ItemTypeID | B4: Иконка | C4: Название | D4: Категория | E4: Подкатегория | F4: IconAssetKey | G4: FileName | H4: Формат | I4: Размер, px | J4: VisualStatus | K4: Альтернативное описание | L4: Контроль | N4: Строк PASS | O4: =COUNTIF($L$5:$L$68,"PASS") -> 64
A5: ITM-WPN-001 | C5: Лёгкий арбалет | D5: Оружие | E5: Арбалет | F5: ITM-WPN-001 | G5: itm-wpn-001.png | H5: PNG | I5: 96×96 | J5: TYPE_ALIGNED | K5: лёгкий арбалет с тонкими плечами | L5: =IF(AND(COUNTIF('01_Каталог'!$A$5:$A$68,A5)=1,COUNTIF($F$5:$F$68,F5)=1,H5="PNG",I5="96×96"),"PASS","FAIL") -> PASS | N5: Итог | O5: =IF(AND(O2=O3,O2=O4),"PASS","FAIL") -> PASS
A6: ITM-WPN-002 | C6: Тяжёлый арбалет | D6: Оружие | E6: Арбалет | F6: ITM-WPN-002 | G6: itm-wpn-002.png | H6: PNG | I6: 96×96 | J6: TYPE_ALIGNED | K6: массивный тяжёлый арбалет | L6: =IF(AND(COUNTIF('01_Каталог'!$A$5:$A$68,A6)=1,COUNTIF($F$5:$F$68,F6)=1,H6="PNG",I6="96×96"),"PASS","FAIL") -> PASS
A7: ITM-WPN-003 | C7: Кенси | D7: Оружие | E7: Арбалет | F7: ITM-WPN-003 | G7: itm-wpn-003.png | H7: PNG | I7: 96×96 | J7: PROVISIONAL_VISUAL | K7: компактный магазинный арбалет Кенси | L7: =IF(AND(COUNTIF('01_Каталог'!$A$5:$A$68,A7)=1,COUNTIF($F$5:$F$68,F7)=1,H7="PNG",I7="96×96"),"PASS","FAIL") -> PASS | N7: Источник | O7: https://lucide.dev
A8: ITM-WPN-004 | C8: Эривел | D8: Оружие | E8: Арбалет | F8: ITM-WPN-004 | G8: itm-wpn-004.png | H8: PNG | I8: 96×96 | J8: PROVISIONAL_VISUAL | K8: тяжёлый магазинный арбалет Эривел | L8: =IF(AND(COUNTIF('01_Каталог'!$A$5:$A$68,A8)=1,COUNTIF($F$5:$F$68,F8)=1,H8="PNG",I8="96×96"),"PASS","FAIL") -> PASS | N8: Лицензия | O8: https://github.com/lucide-icons/lucide/blob/main/LICENSE
A9: ITM-WPN-005 | C9: Эстрефорд | D9: Оружие | E9: Арбалет | F9: ITM-WPN-005 | G9: itm-wpn-005.png | H9: PNG | I9: 96×96 | J9: PROVISIONAL_VISUAL | K9: усиленный арбалет Эстрефорд | L9: =IF(AND(COUNTIF('01_Каталог'!$A$5:$A$68,A9)=1,COUNTIF($F$5:$F$68,F9)=1,H9="PNG",I9="96×96"),"PASS","FAIL") -> PASS | N9: Версия | O9: Lucide 1.8.0 / ISC
A10: ITM-WPN-006 | C10: Айнцберн | D10: Оружие | E10: Арбалет | F10: ITM-WPN-006 | G10: itm-wpn-006.png | H10: PNG | I10: 96×96 | J10: PROVISIONAL_VISUAL | K10: дальнобойный арбалет Айнцберн | L10: =IF(AND(COUNTIF('01_Каталог'!$A$5:$A$68,A10)=1,COUNTIF($F$5:$F$68,F10)=1,H10="PNG",I10="96×96"),"PASS","FAIL") -> PASS
A11: ITM-WPN-007 | C11: Лёгкий лук | D11: Оружие | E11: Лук | F11: ITM-WPN-007 | G11: itm-wpn-007.png | H11: PNG | I11: 96×96 | J11: TYPE_ALIGNED | K11: лёгкий лук со стрелой | L11: =IF(AND(COUNTIF('01_Каталог'!$A$5:$A$68,A11)=1,COUNTIF($F$5:$F$68,F11)=1,H11="PNG",I11="96×96"),"PASS","FAIL") -> PASS
A12: ITM-WPN-008 | C12: Тяжёлый лук | D12: Оружие | E12: Лук | F12: ITM-WPN-008 | G12: itm-wpn-008.png | H12: PNG | I12: 96×96 | J12: TYPE_ALIGNED | K12: мощный тяжёлый лук | L12: =IF(AND(COUNTIF('01_Каталог'!$A$5:$A$68,A12)=1,COUNTIF($F$5:$F$68,F12)=1,H12="PNG",I12="96×96"),"PASS","FAIL") -> PASS
A13: ITM-WPN-009 | C13: Длинный лук | D13: Оружие | E13: Лук | F13: ITM-WPN-009 | G13: itm-wpn-009.png | H13: PNG | I13: 96×96 | J13: TYPE_ALIGNED | K13: длинный лук | L13: =IF(AND(COUNTIF('01_Каталог'!$A$5:$A$68,A13)=1,COUNTIF($F$5:$F$68,F13)=1,H13="PNG",I13="96×96"),"PASS","FAIL") -> PASS
A14: ITM-WPN-010 | C14: Грубое оружие | D14: Оружие | E14: Ближнее оружие | F14: ITM-WPN-010 | G14: itm-wpn-010.png | H14: PNG | I14: 96×96 | J14: TYPE_ALIGNED | K14: грубое дробящее оружие | L14: =IF(AND(COUNTIF('01_Каталог'!$A$5:$A$68,A14)=1,COUNTIF($F$5:$F$68,F14)=1,H14="PNG",I14="96×96"),"PASS","FAIL") -> PASS
A15: ITM-WPN-011 | C15: Одноручный меч | D15: Оружие | E15: Ближнее оружие | F15: ITM-WPN-011 | G15: itm-wpn-011.png | H15: PNG | I15: 96×96 | J15: TYPE_ALIGNED | K15: одноручный меч | L15: =IF(AND(COUNTIF('01_Каталог'!$A$5:$A$68,A15)=1,COUNTIF($F$5:$F$68,F15)=1,H15="PNG",I15="96×96"),"PASS","FAIL") -> PASS
A16: ITM-WPN-012 | C16: Полуторный меч | D16: Оружие | E16: Ближнее оружие | F16: ITM-WPN-012 | G16: itm-wpn-012.png | H16: PNG | I16: 96×96 | J16: TYPE_ALIGNED | K16: полуторный меч с переменным хватом | L16: =IF(AND(COUNTIF('01_Каталог'!$A$5:$A$68,A16)=1,COUNTIF($F$5:$F$68,F16)=1,H16="PNG",I16="96×96"),"PASS","FAIL") -> PASS
A17: ITM-WPN-013 | C17: Двуручный меч | D17: Оружие | E17: Ближнее оружие | F17: ITM-WPN-013 | G17: itm-wpn-013.png | H17: PNG | I17: 96×96 | J17: TYPE_ALIGNED | K17: крупный двуручный меч | L17: =IF(AND(COUNTIF('01_Каталог'!$A$5:$A$68,A17)=1,COUNTIF($F$5:$F$68,F17)=1,H17="PNG",I17="96×96"),"PASS","FAIL") -> PASS
A18: ITM-WPN-014 | C18: Шпага | D18: Оружие | E18: Ближнее оружие | F18: ITM-WPN-014 | G18: itm-wpn-014.png | H18: PNG | I18: 96×96 | J18: TYPE_ALIGNED | K18: тонкая шпага с чашевидной гардой | L18: =IF(AND(COUNTIF('01_Каталог'!$A$5:$A$68,A18)=1,COUNTIF($F$5:$F$68,F18)=1,H18="PNG",I18="96×96"),"PASS","FAIL") -> PASS
A19: ITM-WPN-015 | C19: Копьё | D19: Оружие | E19: Ближнее оружие | F19: ITM-WPN-015 | G19: itm-wpn-015.png | H19: PNG | I19: 96×96 | J19: TYPE_ALIGNED | K19: длинное копьё | L19: =IF(AND(COUNTIF('01_Каталог'!$A$5:$A$68,A19)=1,COUNTIF($F$5:$F$68,F19)=1,H19="PNG",I19="96×96"),"PASS","FAIL") -> PASS
